Workbook

Sheet Basic Infrastructure
A1: # | B1: Item of Work | C1: Unit | D1: Qty. | E1: Rate | F1: Amount
A3: A. Site Development
A4: A1 | B4: Fencing : Chain Linked fencing 2.6 in total, 0.6 m below ground with metal stakes of 2. mt, 2 feet underground and 2 m above ground | C4: RMT | D4: 14000 | E4: 13.22 | F4: =E4*D4 -> 185080
A5: A2 | B5: All weather boundary road for full property 8 m wide mcadamised with soil and stones wet and compressed with road roller | C5: LS | D5: LS | E5: LS | F5: 500000
A6: A3 | B6: Arterial road full length with one crossing at 1000 m from South east corner of property. Macadammised all weather road with one divider 1 m wide and coaltar topping with kerbs and infrastructure corridor for telecommunication electricity and water lines. | K6: =165*165 -> 27225 | L6: =195*210 -> 40950 | M6: =K6/L6 -> 0.66483516
A7: A4 | B7: All weather internal roads for full property 8 m wide mcadamised with soil and stones wet and compressed with road roller running from South to north at a distance of 200 m with storm water drainage, irrigation lines and two cross roads at 500 m distance each
A8: A5 | B8: Guard posts all along the bounday at 1000 m distance | C8: No. | D8: 15 | E8: =500000/88 -> 5681.8182 | F8: =E8*D8 -> 85227.273
A9: A6 | B9: Entry gate and guard room | C9: No. | D9: 1 | E9: =2000000/88 -> 22727.273 | F9: =E9*D9 -> 22727.273
A10: Sub-Total | F10: =SUM(F4:F9) -> 793034.55
I11: GM | J11: 1 | K11: 2000 | L11: =K11*J11 -> 2000
A12: B. Land Preparation | I12: Sales | J12: 1 | K12: 1500 | L12: =K12*J12 -> 1500
A13: # | B13: Item of Work | C13: Unit | D13: Qty. | E13: Rate | F13: Amount | I13: Crop Mgr | J13: 3 | K13: 1000 | L13: =K13*J13 -> 3000
A14: B1 | B14: Land clearing - clearing of bushes, removal of root mass and making suitable for operation by a tractor | C14: Ha | D14: 300 | E14: =6250/88 -> 71.022727 | F14: =D14*E14 -> 21306.818 | I14: Field supervisors | J14: 3 | K14: 1000 | L14: =K14*J14 -> 3000
A15: B2 | B15: MB Ploughing of arable land to a depth of 30 cm | C15: Ha | D15: 300 | E15: =6250/88 -> 71.022727 | F15: =D15*E15 -> 21306.818 | N15: =100*10000 -> 1000000
A16: B3 | B16: Disc/ Cultivator ploughing - cross - to breal soil lumps (if any) | C16: Ha | D16: =D15 -> 300 | E16: =5000/88 -> 56.818182 | F16: =D16*E16 -> 17045.455 | I16: other permanent labour inc drivers | L16: =K16*J16 -> 0
A17: B4 | B17: Manure application: manure cost, transportation, spreading in the field | C17: Ha | D17: =D16 -> 300 | E17: =75000/88 -> 852.27273 | F17: =D17*E17 -> 255681.82 | I17: FnA | J17: 3 | K17: 600 | L17: =K17*J17 -> 1800
A18: B5 | B18: Planing and rotavator application for mixing of manure in the top soil | C18: Ha | D18: =D17 -> 300 | E18: =E15 -> 71.022727 | F18: =D18*E18 -> 21306.818 | I18: Workshop | J18: 2 | K18: 600 | L18: =K18*J18 -> 1200
A19: B6 | B19: Water tank for Drip Irrigation | C19: CUM | D19: =15*15*3 -> 675 | E19: =12000/88 -> 136.36364 | F19: =E19*D19 -> 92045.455 | I19: Warehouse | J19: 2 | K19: 600 | L19: =K19*J19 -> 1200
I20: Deshelling | J20: 4 | K20: 600 | L20: =K20*J20 -> 2400
A21: Total Carried Over to Summary | F21: =SUM(F14:F19) -> 428693.18 | I21: Canteen | J21: 1 | K21: 3000 | L21: =K21*J21 -> 3000
L22: =SUM(L11:L21) -> 19100
A23: C. Buildings
A24: # | B24: Item of Work | C24: Unit | D24: Qty. | E24: Rate | F24: Amount
A25: C1 | B25: Administration building, including Medical room, creche, offices, conference room, officers canteen | C25: SQM | D25: 350 | E25: 250 | F25: =D25*E25 -> 87500
A26: C2 | B26: Tube well cabins with generator pump room and residence for operator approximately 30 SQMT each | C26: No.s | D26: 35 | E26: =(12000/88)*30 -> 4090.9091 | F26: =D26*E26 -> 143181.82
A27: C3 | B27: Warehouse inclusive of area for deshelling | C27: SQM | D27: 2400 | E27: =10000/88 -> 113.63636 | F27: =D27*E27 -> 272727.27
A28: C4 | B28: Residential buldings as per details | C28: SQM | D28: 1000 | E28: 250 | F28: =D28*E28 -> 250000
A29: C5 | B29: Collection centers in field | C29: SQM | D29: 1500 | E29: =900/88 -> 10.227273 | F29: =D29*E29 -> 15340.909
A30: C6 | B30: Utilities - Electrical Room, water tank diesel storage etc | C30: LS | D30: 1 | E30: =1000000/88 -> 11363.636 | F30: =D30*E30 -> 11363.636
A31: Total Carried Over to Summary | F31: =SUM(F25:F30) -> 780113.64
B35: Total Basic Infrastructure | F35: =F31+F10+F21 -> 2001841.4 | G35: =F35/300 -> 6672.8045

Sheet Core Equipment 
A1: S.No. | B1: Equipments | C1: Capacity | D1: Quantity | E1: Unit | F1: Unit Price in Euros | G1: Total Price in Euros
A2: 1 | B2: Tractors Large | C2: 75-90 HP | D2: 10 | E2: No. | F2: =1500000/88 -> 17045.455 | G2: =F2*D2 -> 170454.55
A3: 2 | B3: Tractors small | C3: 40-45 HP | D3: 5 | E3: lot | F3: =800000/88 -> 9090.9091 | G3: =F3*D3 -> 45454.545
A4: 3 | B4: Tube wells inclusiveof Boring and Pumps | C4: 30 cubic m / hour depth 60 m | D4: 60 | E4: =E2 -> No. | F4: =1200000/88 -> 13636.364 | G4: =F4*D4 -> 818181.82
A5: 4 | B5: Generators (diesel) | C5: 25 KVA | D5: 30 | E5: No. | F5: =300000/88 -> 3409.0909 | G5: =F5*D5 -> 102272.73
A6: 5 | B6: Solar Panels with invertor and battery | C6: 25 KVA | D6: 30 | E6: No. | F6: =800000/88 -> 9090.9091 | G6: =F6*D6 -> 272727.27
A7: 4 | B7: Ripper/ MB plough | C7: suitable for large tractor | D7: =D2 -> 10 | E7: No. | F7: =30000/88 -> 340.90909 | G7: =F7*D7 -> 3409.0909
A8: 5 | B8: Cultivator | C8: suitable for large tractor | D8: 10 | E8: =E4 -> No. | F8: =F7 -> 340.90909 | G8: =F8*D8 -> 3409.0909
A9: 6 | B9: Disc Plough | C9: suitable for large tractor | D9: 10 | E9: =E8 -> No. | F9: =F8 -> 340.90909 | G9: =F9*D9 -> 3409.0909
A10: 7 | B10: Rotavator | C10: suitable for large tractor | D10: 5 | E10: =E9 -> No. | F10: =130000/88 -> 1477.2727 | G10: =F10*D10 -> 7386.3636
A11: 8 | B11: Seed Coating machine (for seed treatment) | C11: 500 Kg | D11: 3 | E11: No | F11: =300000/88 -> 3409.0909 | G11: =F11*D11 -> 10227.273
A12: 9 | B12: Seed Drill with fertiliser applicator and/ or bund maker | C12: suitable for large tractor | D12: 10 | E12: =E10 -> No. | F12: =120000/88 -> 1363.6364 | G12: =F12*D12 -> 13636.364
A13: 10 | B13: Harvesters | C13: suitable for large tractor | D13: 10 | E13: =E12 -> No. | F13: =200000/88 -> 2272.7273 | G13: =D13*F13 -> 22727.273
A14: 11 | B14: Multipurpose trolley | C14: 100 cum | D14: 5 | E14: =E12 -> No. | F14: =250000/88 -> 2840.9091 | G14: =F14*D14 -> 14204.545
A15: 12 | B15: Diesel Tank - to be attached to tractor | C15: 5 KL | D15: 2 | E15: =E14 -> No. | F15: =300000/88 -> 3409.0909 | G15: =D15*F15 -> 6818.1818
A16: 13 | B16: Diesel Storage | C16: 10 KL | D16: 1 | E16: =E15 -> No. | F16: =500000/88 -> 5681.8182 | G16: =D16*F16 -> 5681.8182
A17: 14 | B17: Weigh Bridge | C17: 60 MT | D17: 1 | E17: =E16 -> No. | F17: =1200000/88 -> 13636.364 | G17: =D17*F17 -> 13636.364
A18: 15 | B18: Electric Generator/ transformer/ internal lines | C18: 60 KVA | D18: 2 | E18: =E17 -> No. | F18: =3200000/88 -> 36363.636 | G18: =D18*F18 -> 72727.273
A19: 16 | B19: underground Irrigation pipes including valves | C19: 300 mm main, 150 mm lateral | D19: 300 | E19: Ha | F19: =37500/88 -> 426.13636 | G19: =D19*F19 -> 127840.91
A20: 17 | B20: Sprinklers - Manual movement with one irrigation | C20: suitable | D20: 4000 | E20: No. | F20: =500/88 -> 5.6818182 | G20: =D20*F20 -> 22727.273
A21: 18 | B21: Pickup vehicles | D21: 4 | E21: No. | F21: =1000000/88 -> 11363.636 | G21: =D21*F21 -> 45454.545
A22: 19 | B22: MUV | C22: suitable | D22: 8 | E22: no. | F22: =1600000/88 -> 18181.818 | G22: =D22*F22 -> 145454.55
A23: 20 | B23: Sprayers (Kubota) | C23: suitable | D23: 3 | E23: no. | F23: =2400000/88 -> 27272.727 | G23: =D23*F23 -> 81818.182
A24: 21 | B24: Drip for Vegetables | C24: Distance 1.0 m | D24: 190 | E24: Ha | F24: =80000*2.5/88 -> 2272.7273 | G24: =D24*F24 -> 431818.18
A25: 22 | B25: Potato Planter | C25: Planter with fertiliser application | D25: 5 | E25: No. | F25: =180000/88 -> 2045.4545 | G25: =D25*F25 -> 10227.273
A26: 23 | B26: Groundnut desheller | C26: Deshelling machine | D26: 2 | E26: No. | F26: =2000000/88 -> 22727.273 | G26: =D26*F26 -> 45454.545
A27: 24 | B27: Potato Harvester | C27: Harvester with mud shaker | D27: 5 | E27: No | F27: =200000/88 -> 2272.7273 | G27: =D27*F27 -> 11363.636
A28: 25 | B28: Vegetable Pack house | C28: Vegetable pack house for round/ long vegetables 10 MT/ Hr | D28: 1 | E28: LS | F28: =12000000/88 -> 136363.64 | G28: =D28*F28 -> 136363.64
A29: 26 | B29: Combine Harvesters | D29: 2 | E29: LS | F29: =4000000/88 -> 45454.545 | G29: =F29*D29 -> 90909.091
A30: 27 | B30: Brick making machine | C30: 2000-3000 bricks per hour | D30: 1 | E30: LS | F30: =2400000/88 -> 27272.727 | G30: =F30*D30 -> 27272.727
A31: 28 | B31: Crates | D31: 5000 | E31: LS | F31: =400/88 -> 4.5454545 | G31: =F31*D31 -> 22727.273
A32: 29 | B32: Packing lines | D32: 4 | E32: LS | F32: =2500000/88 -> 28409.091 | G32: =F32*D32 -> 113636.36
A33: 30 | B33: Potato Chips Line | D33: 1 | E33: LS | F33: =350000 -> 350000 | G33: =F33*D33 -> 350000
A34: 31 | B34: Cold Storage | C34: 3000 MT | D34: 1 | E34: LS | F34: =(14000*3000)/88 -> 477272.73 | G34: =F34*D34 -> 477272.73
A35: 32 | B35: Workshop equipment and spares | C35: 5% of equipment cost | D35: 1 | E35: LS | F35: =(SUM(G2:G34))*0.05 -> 186335.23 | G35: =D35*F35 -> 186335.23
B36: Total Price (Rs. In Euros) | G36: =SUM(G2:G35) -> 3913039.8

Sheet Other Equipment
A1: S No | B1: Function Area | C1: Equipment Description | D1: Nos | E1: Unit Rate Rs | F1: Est Price Rs
F2: Base Price | G2: Excise | H2: VAT | I2: Total
A3: 1 | C3: Computer, printer and table | D3: 15 | E3: =50000/88 -> 568.18182 | F3: =D3*E3 -> 8522.7273 | I3: =H3+++G3+F3 -> 8522.7273
A4: 2 | C4: Almirah | D4: =D3 -> 15 | E4: =7000/88 -> 79.545455 | F4: =IF(D4=0,E4,E4*D4) -> 1193.1818 | I4: =H4+++G4+F4 -> 1193.1818
C5: Office Chairs | D5: =D4*3 -> 45 | E5: =4500/88 -> 51.136364 | F5: =IF(D5=0,E5,E5*D5) -> 2301.1364 | I5: =H5+++G5+F5 -> 2301.1364
C6: Office tables | D6: =D4 -> 15 | E6: =6000/88 -> 68.181818 | F6: =IF(D6=0,E6,E6*D6) -> 1022.7273 | I6: =H6+++G6+F6 -> 1022.7273
C7: Computer tables | D7: =D6 -> 15 | E7: =6000/88 -> 68.181818 | F7: =IF(D7=0,E7,E7*D7) -> 1022.7273 | I7: =H7+++G7+F7 -> 1022.7273
C8: Computer chairs | D8: =D7 -> 15 | E8: =4000/88 -> 45.454545 | F8: =IF(D8=0,E8,E8*D8) -> 681.81818 | I8: =H8+++G8+F8 -> 681.81818
A9: 3 | C9: Fire Extinguishers | D9: =D8 -> 15 | E9: =3000/88 -> 34.090909 | F9: =IF(D9=0,E9,E9*D9) -> 511.36364 | I9: =H9+++G9+F9 -> 511.36364
A10: Sub Total | F10: =SUBTOTAL(9,F3:F9) -> 15255.682 | G10: =SUBTOTAL(9,G3:G9) -> 0 | H10: =SUBTOTAL(9,H3:H9) -> 0 | I10: =H10+++G10+F10 -> 15255.682

Sheet Growing cost  assum
C1: Year 1 | D1: Year 2 | E1: Year 3 | F1: Year 4 | G1: Year 5 | H1: Year 6 | I1: Year 7 | J1: Year 8 | K1: Year 9 | L1: Year 10
A4: Groundnut
A5: Description | B5: Cost/ Ha | C5: 80 | D5: =C5 -> 80 | E5: =D5 -> 80 | F5: =E5 -> 80 | G5: =F5 -> 80 | H5: =G5 -> 80 | I5: =H5 -> 80 | J5: =I5 -> 80 | K5: =J5 -> 80 | L5: =K5 -> 80
A6: Land preparation | B6: 19.56 | C6: =$B6*C$5 -> 1564.8 | D6: =$B6*D$5 -> 1564.8 | E6: =$B6*E$5 -> 1564.8 | F6: =$B6*F$5 -> 1564.8 | G6: =$B6*G$5 -> 1564.8 | H6: =$B6*H$5 -> 1564.8 | I6: =$B6*I$5 -> 1564.8 | J6: =$B6*J$5 -> 1564.8 | ... L6: =$B6*L$5 -> 1564.8 | N6: =64000/2.5 -> 25600 | P6: Litre
A7: Seed Cost | B7: =100*120/88 -> 136.36364 | C7: =$B7*C$5 -> 10909.091 | D7: =$B7*D$5 -> 10909.091 | E7: =$B7*E$5 -> 10909.091 | F7: =$B7*F$5 -> 10909.091 | G7: =$B7*G$5 -> 10909.091 | H7: =$B7*H$5 -> 10909.091 | I7: =$B7*I$5 -> 10909.091 | J7: =$B7*J$5 -> 10909.091 | ... L7: =$B7*L$5 -> 10909.091 | O7: Diesel consumption per hour | P7: 10
A8: Seed treatment cost | B8: =1350*1.5*2.5/88 -> 57.528409 | C8: =$B8*C$5 -> 4602.2727 | D8: =$B8*D$5 -> 4602.2727 | E8: =$B8*E$5 -> 4602.2727 | F8: =$B8*F$5 -> 4602.2727 | G8: =$B8*G$5 -> 4602.2727 | H8: =$B8*H$5 -> 4602.2727 | I8: =$B8*I$5 -> 4602.2727 | J8: =$B8*J$5 -> 4602.2727 | ... L8: =$B8*L$5 -> 4602.2727 | O8: Diesel price | P8: =75/88 -> 0.85227273
A9: Sowing cost | B9: =B6 -> 19.56 | C9: =$B9*C$5 -> 1564.8 | D9: =$B9*D$5 -> 1564.8 | E9: =$B9*E$5 -> 1564.8 | F9: =$B9*F$5 -> 1564.8 | G9: =$B9*G$5 -> 1564.8 | H9: =$B9*H$5 -> 1564.8 | I9: =$B9*I$5 -> 1564.8 | J9: =$B9*J$5 -> 1564.8 | ... L9: =$B9*L$5 -> 1564.8 | O9: Diese; cost /hour | P9: =P8*P7 -> 8.5227273
A10: Fertiliser (basal application)* urea in two doses | B10: =Q17 -> 36.409091 | C10: =$B10*C$5 -> 2912.7273 | D10: =$B10*D$5 -> 2912.7273 | E10: =$B10*E$5 -> 2912.7273 | F10: =$B10*F$5 -> 2912.7273 | G10: =$B10*G$5 -> 2912.7273 | H10: =$B10*H$5 -> 2912.7273 | I10: =$B10*I$5 -> 2912.7273 | J10: =$B10*J$5 -> 2912.7273 | ... L10: =$B10*L$5 -> 2912.7273 | O10: Diesel cost / Ha/ hour | P10: =P9*25/33 -> 6.4566116
A11: Pre emergent Herbicide spray | B11: =500*1.5*2.5/88 -> 21.306818 | C11: =$B11*C$5 -> 1704.5455 | D11: =$B11*D$5 -> 1704.5455 | E11: =$B11*E$5 -> 1704.5455 | F11: =$B11*F$5 -> 1704.5455 | G11: =$B11*G$5 -> 1704.5455 | H11: =$B11*H$5 -> 1704.5455 | I11: =$B11*I$5 -> 1704.5455 | J11: =$B11*J$5 -> 1704.5455 | ... L11: =$B11*L$5 -> 1704.5455 | O11: No. of irrigations / season | P11: 5
A12: Fungicide and Insecticide spray | B12: =(2500*1.5*2.5)/88 -> 106.53409 | C12: =$B12*C$5 -> 8522.7273 | D12: =$B12*D$5 -> 8522.7273 | E12: =$B12*E$5 -> 8522.7273 | F12: =$B12*F$5 -> 8522.7273 | G12: =$B12*G$5 -> 8522.7273 | H12: =$B12*H$5 -> 8522.7273 | I12: =$B12*I$5 -> 8522.7273 | J12: =$B12*J$5 -> 8522.7273 | ... L12: =$B12*L$5 -> 8522.7273 | O12: Total diesel cost per season per Ha | P12: =P11*P10*2 -> 64.566116
A13: Diesel for irrigation | B13: =P12 -> 64.566116 | C13: =B13*C5 -> 5165.2893 | D13: =C13 -> 5165.2893 | E13: =D13 -> 5165.2893 | F13: =E13 -> 5165.2893 | G13: =F13 -> 5165.2893 | H13: =G13 -> 5165.2893 | I13: =H13 -> 5165.2893 | J13: =I13 -> 5165.2893 | K13: =J13 -> 5165.2893 | L13: =K13 -> 5165.2893
A14: Harvesting (incl labour) | B14: =1500*2.5/88 -> 42.613636 | C14: =$B14*C$5 -> 3409.0909 | D14: =$B14*D$5 -> 3409.0909 | E14: =$B14*E$5 -> 3409.0909 | F14: =$B14*F$5 -> 3409.0909 | G14: =$B14*G$5 -> 3409.0909 | H14: =$B14*H$5 -> 3409.0909 | I14: =$B14*I$5 -> 3409.0909 | J14: =$B14*J$5 -> 3409.0909 | ... L14: =$B14*L$5 -> 3409.0909 | N14: Fertiliser basal/ Ha | O14: QTY | P14: Price | Q14: Val/ Ha
A15: Total Cost | B15: =SUM(B6:B14) -> 504.4418 | C15: =SUM(C5:C14) -> 40435.344 | D15: =SUM(D5:D14) -> 40435.344 | E15: =SUM(E5:E14) -> 40435.344 | F15: =SUM(F5:F14) -> 40435.344 | G15: =SUM(G5:G14) -> 40435.344 | H15: =SUM(H5:H14) -> 40435.344 | I15: =SUM(I5:I14) -> 40435.344 | J15: =SUM(J5:J14) -> 40435.344 | ... L15: =SUM(L5:L14) -> 40435.344 | N15: DAP | O15: 100 | P15: =1200/50/88 -> 0.27272727 | Q15: =P15*O15 -> 27.272727
A16: Yield | C16: =700*1.5*2.5 -> 2625 | D16: =750*1.5*2.5 -> 2812.5 | E16: =775*1.5*2.5 -> 2906.25 | F16: =850*1.5*2.5 -> 3187.5 | G16: =1000*1.5*2.5 -> 3750 | H16: =G16 -> 3750 | I16: =H16 -> 3750 | J16: =I16 -> 3750 | K16: =J16 -> 3750 | L16: =K16 -> 3750 | N16: Urea in two doses | O16: =40*1.5*2.5 -> 150 | P16: =268/50/88 -> 0.060909091 | Q16: =P16*O16 -> 9.1363636
A17: Price / Kg | C17: 0.24 | D17: =C17 -> 0.24 | E17: =D17 -> 0.24 | F17: =E17 -> 0.24 | G17: =F17 -> 0.24 | H17: =G17 -> 0.24 | I17: =H17 -> 0.24 | J17: =I17 -> 0.24 | K17: =J17 -> 0.24 | L17: =K17 -> 0.24 | Q17: =SUM(Q15:Q16) -> 36.409091
A18: Realisation | C18: =C17*C16*C5 -> 50400 | D18: =D17*D16*D5 -> 54000 | E18: =E17*E16*E5 -> 55800 | F18: =F17*F16*F5 -> 61200 | G18: =G17*G16*G5 -> 72000 | H18: =H17*H16*H5 -> 72000 | I18: =I17*I16*I5 -> 72000 | J18: =J17*J16*J5 -> 72000 | ... L18: =L17*L16*L5 -> 72000
A20: Operating margin | C20: =C18-C15 -> 9964.6562 | D20: =D18-D15 -> 13564.656 | E20: =E18-E15 -> 15364.656 | F20: =F18-F15 -> 20764.656 | G20: =G18-G15 -> 31564.656 | H20: =H18-H15 -> 31564.656 | I20: =I18-I15 -> 31564.656 | J20: =J18-J15 -> 31564.656 | ... L20: =L18-L15 -> 31564.656
A22: Cowpea
A23: Description | C23: 40 | D23: =C23 -> 40 | E23: =D23 -> 40 | F23: =E23 -> 40 | G23: =F23 -> 40 | H23: =G23 -> 40 | I23: =H23 -> 40 | J23: =I23 -> 40 | K23: =J23 -> 40 | L23: =K23 -> 40
A24: Land preparation | B24: =B42 -> 19.56 | C24: =C$23*$B24 -> 782.4 | D24: =D$23*$B24 -> 782.4 | E24: =E$23*$B24 -> 782.4 | F24: =F$23*$B24 -> 782.4 | G24: =G$23*$B24 -> 782.4 | H24: =H$23*$B24 -> 782.4 | I24: =I$23*$B24 -> 782.4 | J24: =J$23*$B24 -> 782.4 | ... L24: =L$23*$B24 -> 782.4
A25: Seed Cost | B25: =30*100/88 -> 34.090909 | C25: =C$23*$B25 -> 1363.6364 | D25: =D$23*$B25 -> 1363.6364 | E25: =E$23*$B25 -> 1363.6364 | F25: =F$23*$B25 -> 1363.6364 | G25: =G$23*$B25 -> 1363.6364 | H25: =H$23*$B25 -> 1363.6364 | I25: =I$23*$B25 -> 1363.6364 | J25: =J$23*$B25 -> 1363.6364 | ... L25: =L$23*$B25 -> 1363.6364
A26: Seed treatment cost | B26: =35 -> 35 | C26: =C$23*$B26 -> 1400 | D26: =D$23*$B26 -> 1400 | E26: =E$23*$B26 -> 1400 | F26: =F$23*$B26 -> 1400 | G26: =G$23*$B26 -> 1400 | H26: =H$23*$B26 -> 1400 | I26: =I$23*$B26 -> 1400 | J26: =J$23*$B26 -> 1400 | ... L26: =L$23*$B26 -> 1400
A27: Sowing cost | B27: =B45 -> 56.818182 | C27: =C$23*$B27 -> 2272.7273 | D27: =D$23*$B27 -> 2272.7273 | E27: =E$23*$B27 -> 2272.7273 | F27: =F$23*$B27 -> 2272.7273 | G27: =G$23*$B27 -> 2272.7273 | H27: =H$23*$B27 -> 2272.7273 | I27: =I$23*$B27 -> 2272.7273 | J27: =J$23*$B27 -> 2272.7273 | ... L27: =L$23*$B27 -> 2272.7273
A28: Fertiliser (basal application)* urea in two doses | B28: =B10 -> 36.409091 | C28: =C$23*$B28 -> 1456.3636 | D28: =D$23*$B28 -> 1456.3636 | E28: =E$23*$B28 -> 1456.3636 | F28: =F$23*$B28 -> 1456.3636 | G28: =G$23*$B28 -> 1456.3636 | H28: =H$23*$B28 -> 1456.3636 | I28: =I$23*$B28 -> 1456.3636 | J28: =J$23*$B28 -> 1456.3636 | ... L28: =L$23*$B28 -> 1456.3636
A29: Post emergent Herbicide spray | B29: =10000/88 -> 113.63636 | C29: =C$23*$B29 -> 4545.4545 | D29: =D$23*$B29 -> 4545.4545 | E29: =E$23*$B29 -> 4545.4545 | F29: =F$23*$B29 -> 4545.4545 | G29: =G$23*$B29 -> 4545.4545 | H29: =H$23*$B29 -> 4545.4545 | I29: =I$23*$B29 -> 4545.4545 | J29: =J$23*$B29 -> 4545.4545 | ... L29: =L$23*$B29 -> 4545.4545
A30: Fungicide and Insecticide spray | B30: =34 -> 34 | C30: =C$23*$B30 -> 1360 | D30: =D$23*$B30 -> 1360 | E30: =E$23*$B30 -> 1360 | F30: =F$23*$B30 -> 1360 | G30: =G$23*$B30 -> 1360 | H30: =H$23*$B30 -> 1360 | I30: =I$23*$B30 -> 1360 | J30: =J$23*$B30 -> 1360 | ... L30: =L$23*$B30 -> 1360
A31: =A13 -> Diesel for irrigation | B31: =B13/2 -> 32.283058 | C31: =C$23*$B31 -> 1291.3223 | D31: =D$23*$B31 -> 1291.3223 | E31: =E$23*$B31 -> 1291.3223 | F31: =F$23*$B31 -> 1291.3223 | G31: =G$23*$B31 -> 1291.3223 | H31: =H$23*$B31 -> 1291.3223 | I31: =I$23*$B31 -> 1291.3223 | J31: =J$23*$B31 -> 1291.3223 | ... L31: =L$23*$B31 -> 1291.3223
A32: Harvesting (incl labour) | B32: =137 -> 137 | C32: =C$23*$B32 -> 5480 | D32: =D$23*$B32 -> 5480 | E32: =E$23*$B32 -> 5480 | F32: =F$23*$B32 -> 5480 | G32: =G$23*$B32 -> 5480 | H32: =H$23*$B32 -> 5480 | I32: =I$23*$B32 -> 5480 | J32: =J$23*$B32 -> 5480 | ... L32: =L$23*$B32 -> 5480
A33: Total Cost | B33: =SUM(B24:B32) -> 498.7976 | C33: =SUM(C24:C32) -> 19951.904 | D33: =SUM(D24:D32) -> 19951.904 | E33: =SUM(E24:E32) -> 19951.904 | F33: =SUM(F24:F32) -> 19951.904 | G33: =SUM(G24:G32) -> 19951.904 | H33: =SUM(H24:H32) -> 19951.904 | I33: =SUM(I24:I32) -> 19951.904 | ... L33: =SUM(L24:L32) -> 19951.904
A34: Yield | C34: 900 | D34: 1000 | E34: =1100 -> 1100 | F34: =E34 -> 1100 | G34: =F34 -> 1100 | H34: =G34 -> 1100 | I34: =H34 -> 1100 | J34: =I34 -> 1100 | K34: =J34 -> 1100 | L34: =K34 -> 1100
A35: Price / Kg | C35: 1.3 | D35: =C35 -> 1.3 | E35: =D35 -> 1.3 | F35: =E35 -> 1.3 | G35: =F35 -> 1.3 | H35: =G35 -> 1.3 | I35: =H35 -> 1.3 | J35: =I35 -> 1.3 | K35: =J35 -> 1.3 | L35: =K35 -> 1.3
A36: Realisation | C36: =C35*C34*C23 -> 46800 | D36: =D35*D34*D23 -> 52000 | E36: =E35*E34*E23 -> 57200 | F36: =F35*F34*F23 -> 57200 | G36: =G35*G34*G23 -> 57200 | H36: =H35*H34*H23 -> 57200 | I36: =I35*I34*I23 -> 57200 | J36: =J35*J34*J23 -> 57200 | ... L36: =L35*L34*L23 -> 57200
A38: Operating margin | C38: =C36-C33 -> 26848.096 | D38: =D36-D33 -> 32048.096 | E38: =E36-E33 -> 37248.096 | F38: =F36-F33 -> 37248.096 | G38: =G36-G33 -> 37248.096 | H38: =H36-H33 -> 37248.096 | I38: =I36-I33 -> 37248.096 | J38: =J36-J33 -> 37248.096 | ... L38: =L36-L33 -> 37248.096
A40: Wheat
A41: Description | B41: Cost / Ha | C41: 80 | D41: =C41 -> 80 | E41: =D41 -> 80 | F41: =E41 -> 80 | G41: =F41 -> 80 | H41: =G41 -> 80 | I41: =H41 -> 80 | J41: =I41 -> 80 | K41: =J41 -> 80 | L41: =K41 -> 80
A42: Land preparation | B42: =B60 -> 19.56 | C42: =$B42*C$41 -> 1564.8 | D42: =$B42*D$41 -> 1564.8 | E42: =$B42*E$41 -> 1564.8 | F42: =$B42*F$41 -> 1564.8 | G42: =$B42*G$41 -> 1564.8 | H42: =$B42*H$41 -> 1564.8 | I42: =$B42*I$41 -> 1564.8 | J42: =$B42*J$41 -> 1564.8 | ... L42: =$B42*L$41 -> 1564.8
A43: Seed Cost | B43: =100*75/88 -> 85.227273 | C43: =$B43*C$41 -> 6818.1818 | D43: =$B43*D$41 -> 6818.1818 | E43: =$B43*E$41 -> 6818.1818 | F43: =$B43*F$41 -> 6818.1818 | G43: =$B43*G$41 -> 6818.1818 | H43: =$B43*H$41 -> 6818.1818 | I43: =$B43*I$41 -> 6818.1818 | J43: =$B43*J$41 -> 6818.1818 | ... L43: =$B43*L$41 -> 6818.1818
A44: Seed treatment cost | C44: =$B44*C$41 -> 0 | D44: =$B44*D$41 -> 0 | E44: =$B44*E$41 -> 0 | F44: =$B44*F$41 -> 0 | G44: =$B44*G$41 -> 0 | H44: =$B44*H$41 -> 0 | I44: =$B44*I$41 -> 0 | J44: =$B44*J$41 -> 0 | ... L44: =$B44*L$41 -> 0
A45: Sowing cost | B45: =5000/88 -> 56.818182 | C45: =$B45*C$41 -> 4545.4545 | D45: =$B45*D$41 -> 4545.4545 | E45: =$B45*E$41 -> 4545.4545 | F45: =$B45*F$41 -> 4545.4545 | G45: =$B45*G$41 -> 4545.4545 | H45: =$B45*H$41 -> 4545.4545 | I45: =$B45*I$41 -> 4545.4545 | J45: =$B45*J$41 -> 4545.4545 | ... L45: =$B45*L$41 -> 4545.4545
A46: Fertiliser (basal application)* urea in two doses | B46: =10000/88 -> 113.63636 | C46: =$B46*C$41 -> 9090.9091 | D46: =$B46*D$41 -> 9090.9091 | E46: =$B46*E$41 -> 9090.9091 | F46: =$B46*F$41 -> 9090.9091 | G46: =$B46*G$41 -> 9090.9091 | H46: =$B46*H$41 -> 9090.9091 | I46: =$B46*I$41 -> 9090.9091 | J46: =$B46*J$41 -> 9090.9091 | ... L46: =$B46*L$41 -> 9090.9091
A47: Post emergent Herbicide spray | B47: =B45+2500/88 -> 85.227273 | C47: =$B47*C$41 -> 6818.1818 | D47: =$B47*D$41 -> 6818.1818 | E47: =$B47*E$41 -> 6818.1818 | F47: =$B47*F$41 -> 6818.1818 | G47: =$B47*G$41 -> 6818.1818 | H47: =$B47*H$41 -> 6818.1818 | I47: =$B47*I$41 -> 6818.1818 | J47: =$B47*J$41 -> 6818.1818 | ... L47: =$B47*L$41 -> 6818.1818
A48: Fungicide and Insecticide spray | B48: =B47 -> 85.227273 | C48: =$B48*C$41 -> 6818.1818 | D48: =$B48*D$41 -> 6818.1818 | E48: =$B48*E$41 -> 6818.1818 | F48: =$B48*F$41 -> 6818.1818 | G48: =$B48*G$41 -> 6818.1818 | H48: =$B48*H$41 -> 6818.1818 | I48: =$B48*I$41 -> 6818.1818 | J48: =$B48*J$41 -> 6818.1818 | ... L48: =$B48*L$41 -> 6818.1818
A49: =A13 -> Diesel for irrigation | B49: =B13*2 -> 129.13223 | C49: =$B49*C$41 -> 10330.579 | D49: =$B49*D$41 -> 10330.579 | E49: =$B49*E$41 -> 10330.579 | F49: =$B49*F$41 -> 10330.579 | G49: =$B49*G$41 -> 10330.579 | H49: =$B49*H$41 -> 10330.579 | I49: =$B49*I$41 -> 10330.579 | J49: =$B49*J$41 -> 10330.579 | ... L49: =$B49*L$41 -> 10330.579
A50: Harvesting (incl labour) | B50: =10000/88 -> 113.63636 | C50: =$B50*C$41 -> 9090.9091 | D50: =$B50*D$41 -> 9090.9091 | E50: =$B50*E$41 -> 9090.9091 | F50: =$B50*F$41 -> 9090.9091 | G50: =$B50*G$41 -> 9090.9091 | H50: =$B50*H$41 -> 9090.9091 | I50: =$B50*I$41 -> 9090.9091 | J50: =$B50*J$41 -> 9090.9091 | ... L50: =$B50*L$41 -> 9090.9091
A51: Total Cost | B51: =SUM(B42:B50) -> 688.46496 | C51: =$B51*C$41 -> 55077.197 | D51: =$B51*D$41 -> 55077.197 | E51: =$B51*E$41 -> 55077.197 | F51: =$B51*F$41 -> 55077.197 | G51: =$B51*G$41 -> 55077.197 | H51: =$B51*H$41 -> 55077.197 | I51: =$B51*I$41 -> 55077.197 | J51: =$B51*J$41 -> 55077.197 | ... L51: =$B51*L$41 -> 55077.197
A52: Yield | C52: 3750 | D52: 4000 | E52: 4250 | F52: 4500 | G52: 5000 | H52: =G52 -> 5000 | I52: =H52 -> 5000 | J52: =I52 -> 5000 | K52: =J52 -> 5000 | L52: =K52 -> 5000
A53: Price / Kg | C53: =16/88 -> 0.18181818 | D53: =C53 -> 0.18181818 | E53: =D53 -> 0.18181818 | F53: =E53 -> 0.18181818 | G53: =F53 -> 0.18181818 | H53: =G53 -> 0.18181818 | I53: =H53 -> 0.18181818 | J53: =I53 -> 0.18181818 | K53: =J53 -> 0.18181818 | L53: =K53 -> 0.18181818
A54: Realisation | C54: =C53*C52*C41 -> 54545.455 | D54: =D53*D52*D41 -> 58181.818 | E54: =E53*E52*E41 -> 61818.182 | F54: =F53*F52*F41 -> 65454.545 | G54: =G53*G52*G41 -> 72727.273 | H54: =H53*H52*H41 -> 72727.273 | I54: =I53*I52*I41 -> 72727.273 | J54: =J53*J52*J41 -> 72727.273 | ... L54: =L53*L52*L41 -> 72727.273
A56: Operating margin | C56: =C54-C51 -> -531.74215 | D56: =D54-D51 -> 3104.6215 | E56: =E54-E51 -> 6740.9851 | F56: =F54-F51 -> 10377.349 | G56: =G54-G51 -> 17650.076 | H56: =H54-H51 -> 17650.076 | I56: =I54-I51 -> 17650.076 | J56: =J54-J51 -> 17650.076 | ... L56: =L54-L51 -> 17650.076
A58: Sesame
A59: Description | B59: Cost/ Ha | C59: 80 | D59: =C59 -> 80 | E59: =D59 -> 80 | F59: =E59 -> 80 | G59: =F59 -> 80 | H59: =G59 -> 80 | I59: =H59 -> 80 | J59: =I59 -> 80 | K59: =J59 -> 80 | L59: =K59 -> 80
A60: Land preparation | B60: 19.56 | C60: =$B60*C$5 -> 1564.8 | D60: =$B60*D$5 -> 1564.8 | E60: =$B60*E$5 -> 1564.8 | F60: =$B60*F$5 -> 1564.8 | G60: =$B60*G$5 -> 1564.8 | H60: =$B60*H$5 -> 1564.8 | I60: =$B60*I$5 -> 1564.8 | J60: =$B60*J$5 -> 1564.8 | ... L60: =$B60*L$5 -> 1564.8 | P60: Litre
A61: Seed Cost | B61: =300*6/88 -> 20.454545 | C61: =$B61*C$5 -> 1636.3636 | D61: =$B61*D$5 -> 1636.3636 | E61: =$B61*E$5 -> 1636.3636 | F61: =$B61*F$5 -> 1636.3636 | G61: =$B61*G$5 -> 1636.3636 | H61: =$B61*H$5 -> 1636.3636 | I61: =$B61*I$5 -> 1636.3636 | J61: =$B61*J$5 -> 1636.3636 | ... L61: =$B61*L$5 -> 1636.3636 | O61: Diesel consumption per hour | P61: 10
A62: Seed treatment cost | B62: =150*1.5*2.5/88 -> 6.3920455 | C62: =$B62*C$5 -> 511.36364 | D62: =$B62*D$5 -> 511.36364 | E62: =$B62*E$5 -> 511.36364 | F62: =$B62*F$5 -> 511.36364 | G62: =$B62*G$5 -> 511.36364 | H62: =$B62*H$5 -> 511.36364 | I62: =$B62*I$5 -> 511.36364 | J62: =$B62*J$5 -> 511.36364 | ... L62: =$B62*L$5 -> 511.36364 | O62: Diesel price | P62: =75/88 -> 0.85227273
A63: Sowing cost | B63: =B60 -> 19.56 | C63: =$B63*C$5 -> 1564.8 | D63: =$B63*D$5 -> 1564.8 | E63: =$B63*E$5 -> 1564.8 | F63: =$B63*F$5 -> 1564.8 | G63: =$B63*G$5 -> 1564.8 | H63: =$B63*H$5 -> 1564.8 | I63: =$B63*I$5 -> 1564.8 | J63: =$B63*J$5 -> 1564.8 | ... L63: =$B63*L$5 -> 1564.8 | O63: Diese; cost /hour | P63: =P62*P61 -> 8.5227273
A64: Fertiliser (basal application)* urea in two doses | B64: =Q17 -> 36.409091 | C64: =$B64*C$5 -> 2912.7273 | D64: =$B64*D$5 -> 2912.7273 | E64: =$B64*E$5 -> 2912.7273 | F64: =$B64*F$5 -> 2912.7273 | G64: =$B64*G$5 -> 2912.7273 | H64: =$B64*H$5 -> 2912.7273 | I64: =$B64*I$5 -> 2912.7273 | J64: =$B64*J$5 -> 2912.7273 | ... L64: =$B64*L$5 -> 2912.7273 | O64: Diesel cost / Ha/ hour | P64: =P63*25/33 -> 6.4566116
A65: Pre emergent Herbicide spray | B65: =500*1.5*2.5/88 -> 21.306818 | C65: =$B65*C$5 -> 1704.5455 | D65: =$B65*D$5 -> 1704.5455 | E65: =$B65*E$5 -> 1704.5455 | F65: =$B65*F$5 -> 1704.5455 | G65: =$B65*G$5 -> 1704.5455 | H65: =$B65*H$5 -> 1704.5455 | I65: =$B65*I$5 -> 1704.5455 | J65: =$B65*J$5 -> 1704.5455 | ... L65: =$B65*L$5 -> 1704.5455 | O65: No. of irrigations / season | P65: 3
A66: Fungicide and Insecticide spray | B66: =(1000*1.5*2.5)/88 -> 42.613636 | C66: =$B66*C$5 -> 3409.0909 | D66: =$B66*D$5 -> 3409.0909 | E66: =$B66*E$5 -> 3409.0909 | F66: =$B66*F$5 -> 3409.0909 | G66: =$B66*G$5 -> 3409.0909 | H66: =$B66*H$5 -> 3409.0909 | I66: =$B66*I$5 -> 3409.0909 | J66: =$B66*J$5 -> 3409.0909 | ... L66: =$B66*L$5 -> 3409.0909 | O66: Total diesel cost per season per Ha | P66: =P65*P64*2 -> 38.739669
A67: =A13 -> Diesel for irrigation | B67: =P66 -> 38.739669 | C67: =B67*C5 -> 3099.1736 | D67: =C67 -> 3099.1736 | E67: =D67 -> 3099.1736 | F67: =E67 -> 3099.1736 | G67: =F67 -> 3099.1736 | H67: =G67 -> 3099.1736 | I67: =H67 -> 3099.1736 | J67: =I67 -> 3099.1736 | K67: =J67 -> 3099.1736 | L67: =K67 -> 3099.1736
A68: Harvesting (incl labour) | B68: =1000*2.5/88 -> 28.409091 | C68: =$B68*C$5 -> 2272.7273 | D68: =$B68*D$5 -> 2272.7273 | E68: =$B68*E$5 -> 2272.7273 | F68: =$B68*F$5 -> 2272.7273 | G68: =$B68*G$5 -> 2272.7273 | H68: =$B68*H$5 -> 2272.7273 | I68: =$B68*I$5 -> 2272.7273 | J68: =$B68*J$5 -> 2272.7273 | ... L68: =$B68*L$5 -> 2272.7273
A69: Total Cost | B69: =SUM(B60:B68) -> 233.4449 | C69: =$B69*C$5 -> 18675.592 | D69: =$B69*D$5 -> 18675.592 | E69: =$B69*E$5 -> 18675.592 | F69: =$B69*F$5 -> 18675.592 | G69: =$B69*G$5 -> 18675.592 | H69: =$B69*H$5 -> 18675.592 | I69: =$B69*I$5 -> 18675.592 | J69: =$B69*J$5 -> 18675.592 | ... L69: =$B69*L$5 -> 18675.592
A70: Yield | C70: 800 | D70: 900 | E70: 1000 | F70: =E70 -> 1000 | G70: =F70 -> 1000 | H70: =G70 -> 1000 | I70: =H70 -> 1000 | J70: =I70 -> 1000 | K70: =J70 -> 1000 | L70: =K70 -> 1000
A71: Price / Kg | C71: 0.55 | D71: =C71 -> 0.55 | E71: =D71 -> 0.55 | F71: =E71 -> 0.55 | G71: =F71 -> 0.55 | H71: =G71 -> 0.55 | I71: =H71 -> 0.55 | J71: =I71 -> 0.55 | K71: =J71 -> 0.55 | L71: =K71 -> 0.55
A72: Realisation | C72: =C71*C70*C5 -> 35200 | D72: =D71*D70*D5 -> 39600 | E72: =E71*E70*E5 -> 44000 | F72: =F71*F70*F5 -> 44000 | G72: =G71*G70*G5 -> 44000 | H72: =H71*H70*H5 -> 44000 | I72: =I71*I70*I5 -> 44000 | J72: =J71*J70*J5 -> 44000 | ... L72: =L71*L70*L5 -> 44000
A74: Operating margin | C74: =C72-C69 -> 16524.408 | D74: =D72-D69 -> 20924.408 | E74: =E72-E69 -> 25324.408 | F74: =F72-F69 -> 25324.408 | G74: =G72-G69 -> 25324.408 | H74: =H72-H69 -> 25324.408 | I74: =I72-I69 -> 25324.408 | J74: =J72-J69 -> 25324.408 | ... L74: =L72-L69 -> 25324.408
A77: Okra - with drip and mulching
A78: Description | B78: Cost/ Ha | C78: 20 | D78: =C78 -> 20 | E78: =D78 -> 20 | F78: =E78 -> 20 | G78: =F78 -> 20 | H78: =G78 -> 20 | I78: =H78 -> 20 | J78: =I78 -> 20 | K78: =J78 -> 20 | L78: =K78 -> 20
N79: Diesel consumption per hour | O79: 10
A80: Land preparation | B80: =1500*2.5/88 -> 42.613636 | C80: =$B80*C$78 -> 852.27273 | D80: =$B80*D$78 -> 852.27273 | E80: =$B80*E$78 -> 852.27273 | F80: =$B80*F$78 -> 852.27273 | G80: =$B80*G$78 -> 852.27273 | H80: =$B80*H$78 -> 852.27273 | I80: =$B80*I$78 -> 852.27273 | J80: =$B80*J$78 -> 852.27273 | ... L80: =$B80*L$78 -> 852.27273 | N80: Diesel price | O80: =75/88 -> 0.85227273
A81: Seed Cost | B81: =4000*2.5/88 -> 113.63636 | C81: =$B81*C$78 -> 2272.7273 | D81: =$B81*D$78 -> 2272.7273 | E81: =$B81*E$78 -> 2272.7273 | F81: =$B81*F$78 -> 2272.7273 | G81: =$B81*G$78 -> 2272.7273 | H81: =$B81*H$78 -> 2272.7273 | I81: =$B81*I$78 -> 2272.7273 | J81: =$B81*J$78 -> 2272.7273 | ... L81: =$B81*L$78 -> 2272.7273 | N81: Diese; cost /hour | O81: =O80*O79 -> 8.5227273
A82: Seed treatment cost | C82: =$B82*C$78 -> 0 | D82: =$B82*D$78 -> 0 | E82: =$B82*E$78 -> 0 | F82: =$B82*F$78 -> 0 | G82: =$B82*G$78 -> 0 | H82: =$B82*H$78 -> 0 | I82: =$B82*I$78 -> 0 | J82: =$B82*J$78 -> 0 | ... L82: =$B82*L$78 -> 0 | N82: Diesel cost / Ha/ hour | O82: =O81*25/66 -> 3.2283058
A83: Sowing cost | B83: =18000*2.5/88 -> 511.36364 | C83: =$B83*C$78 -> 10227.273 | D83: =$B83*D$78 -> 10227.273 | E83: =$B83*E$78 -> 10227.273 | F83: =$B83*F$78 -> 10227.273 | G83: =$B83*G$78 -> 10227.273 | H83: =$B83*H$78 -> 10227.273 | I83: =$B83*I$78 -> 10227.273 | J83: =$B83*J$78 -> 10227.273 | ... L83: =$B83*L$78 -> 10227.273 | N83: No. of irrigations / season | O83: 9
A84: Fertiliser | B84: =20000*2.5/88 -> 568.18182 | C84: =$B84*C$78 -> 11363.636 | D84: =$B84*D$78 -> 11363.636 | E84: =$B84*E$78 -> 11363.636 | F84: =$B84*F$78 -> 11363.636 | G84: =$B84*G$78 -> 11363.636 | H84: =$B84*H$78 -> 11363.636 | I84: =$B84*I$78 -> 11363.636 | J84: =$B84*J$78 -> 11363.636 | ... L84: =$B84*L$78 -> 11363.636 | N84: Total diesel cost per season per Ha | O84: =O83*O82*2 -> 58.109504
A85: Pre emergent Herbicide spray | C85: =$B85*C$78 -> 0 | D85: =$B85*D$78 -> 0 | E85: =$B85*E$78 -> 0 | F85: =$B85*F$78 -> 0 | G85: =$B85*G$78 -> 0 | H85: =$B85*H$78 -> 0 | I85: =$B85*I$78 -> 0 | J85: =$B85*J$78 -> 0 | ... L85: =$B85*L$78 -> 0
A86: Fungicide and Insecticide spray | B86: =15000*2.5/88 -> 426.13636 | C86: =$B86*C$78 -> 8522.7273 | D86: =$B86*D$78 -> 8522.7273 | E86: =$B86*E$78 -> 8522.7273 | F86: =$B86*F$78 -> 8522.7273 | G86: =$B86*G$78 -> 8522.7273 | H86: =$B86*H$78 -> 8522.7273 | I86: =$B86*I$78 -> 8522.7273 | J86: =$B86*J$78 -> 8522.7273 | ... L86: =$B86*L$78 -> 8522.7273
A87: Diesel for Irrigation | B87: =O84 -> 58.109504 | C87: =$B87*C$78 -> 1162.1901 | D87: =$B87*D$78 -> 1162.1901 | E87: =$B87*E$78 -> 1162.1901 | F87: =$B87*F$78 -> 1162.1901 | G87: =$B87*G$78 -> 1162.1901 | H87: =$B87*H$78 -> 1162.1901 | I87: =$B87*I$78 -> 1162.1901 | J87: =$B87*J$78 -> 1162.1901 | ... L87: =$B87*L$78 -> 1162.1901
A88: Harvesting (incl labour) | B88: =38500*2.5/88 -> 1093.75 | C88: =$B88*C$78 -> 21875 | D88: =$B88*D$78 -> 21875 | E88: =$B88*E$78 -> 21875 | F88: =$B88*F$78 -> 21875 | G88: =$B88*G$78 -> 21875 | H88: =$B88*H$78 -> 21875 | I88: =$B88*I$78 -> 21875 | J88: =$B88*J$78 -> 21875 | ... L88: =$B88*L$78 -> 21875
A89: Total Cost | B89: =SUM(B80:B88) -> 2813.7913 | C89: =SUM(C80:C88) -> 56275.826 | D89: =SUM(D80:D88) -> 56275.826 | E89: =SUM(E80:E88) -> 56275.826 | F89: =SUM(F80:F88) -> 56275.826 | G89: =SUM(G80:G88) -> 56275.826 | H89: =SUM(H80:H88) -> 56275.826 | I89: =SUM(I80:I88) -> 56275.826 | ... L89: =SUM(L80:L88) -> 56275.826
A90: Yield | C90: 8000 | D90: =C90+1000 -> 9000 | E90: =D90+1000 -> 10000 | F90: =E90+1000 -> 11000 | G90: =F90+1000 -> 12000 | H90: =G90 -> 12000 | I90: =H90 -> 12000 | J90: =I90 -> 12000 | K90: =J90 -> 12000 | L90: =K90 -> 12000
A91: Price / Kg | C91: 0.35 | D91: =C91 -> 0.35 | E91: =D91 -> 0.35 | F91: =E91 -> 0.35 | G91: =F91 -> 0.35 | H91: =G91 -> 0.35 | I91: =H91 -> 0.35 | J91: =I91 -> 0.35 | K91: =J91 -> 0.35 | L91: =K91 -> 0.35
A92: Realisation | C92: =C91*C90*C78 -> 56000 | D92: =D91*D90*D78 -> 63000 | E92: =E91*E90*E78 -> 70000 | F92: =F91*F90*F78 -> 77000 | G92: =G91*G90*G78 -> 84000 | H92: =H91*H90*H78 -> 84000 | I92: =I91*I90*I78 -> 84000 | J92: =J91*J90*J78 -> 84000 | ... L92: =L91*L90*L78 -> 84000
A94: Operating margin | C94: =C92-C89 -> -275.82645 | D94: =D92-D89 -> 6724.1736 | E94: =E92-E89 -> 13724.174 | F94: =F92-F89 -> 20724.174 | G94: =G92-G89 -> 27724.174 | H94: =H92-H89 -> 27724.174 | I94: =I92-I89 -> 27724.174 | J94: =J92-J89 -> 27724.174 | ... L94: =L92-L89 -> 27724.174
A96: Sorghum for Seed
A97: Description | B97: Cost/Ha | C97: 40 | D97: =C97 -> 40 | E97: =D97 -> 40 | F97: =E97 -> 40 | G97: =F97 -> 40 | H97: =G97 -> 40 | I97: =H97 -> 40 | J97: =I97 -> 40 | K97: =J97 -> 40 | L97: =K97 -> 40
A98: Land preparation | B98: =B80 -> 42.613636 | C98: =$B98*C$97 -> 1704.5455 | D98: =$B98*D$97 -> 1704.5455 | E98: =$B98*E$97 -> 1704.5455 | F98: =$B98*F$97 -> 1704.5455 | G98: =$B98*G$97 -> 1704.5455 | H98: =$B98*H$97 -> 1704.5455 | I98: =$B98*I$97 -> 1704.5455 | J98: =$B98*J$97 -> 1704.5455 | ... L98: =$B98*L$97 -> 1704.5455
A99: Seed Cost | B99: =2000/88 -> 22.727273 | C99: =$B99*C$97 -> 909.09091 | D99: =$B99*D$97 -> 909.09091 | E99: =$B99*E$97 -> 909.09091 | F99: =$B99*F$97 -> 909.09091 | G99: =$B99*G$97 -> 909.09091 | H99: =$B99*H$97 -> 909.09091 | I99: =$B99*I$97 -> 909.09091 | J99: =$B99*J$97 -> 909.09091 | ... L99: =$B99*L$97 -> 909.09091
A100: Seed treatment cost | B100: =B62 -> 6.3920455 | C100: =$B100*C$97 -> 255.68182 | D100: =$B100*D$97 -> 255.68182 | E100: =$B100*E$97 -> 255.68182 | F100: =$B100*F$97 -> 255.68182 | G100: =$B100*G$97 -> 255.68182 | H100: =$B100*H$97 -> 255.68182 | I100: =$B100*I$97 -> 255.68182 | J100: =$B100*J$97 -> 255.68182 | ... L100: =$B100*L$97 -> 255.68182
A101: Sowing cost | B101: =B63*2 -> 39.12 | C101: =$B101*C$97 -> 1564.8 | D101: =$B101*D$97 -> 1564.8 | E101: =$B101*E$97 -> 1564.8 | F101: =$B101*F$97 -> 1564.8 | G101: =$B101*G$97 -> 1564.8 | H101: =$B101*H$97 -> 1564.8 | I101: =$B101*I$97 -> 1564.8 | J101: =$B101*J$97 -> 1564.8 | ... L101: =$B101*L$97 -> 1564.8
A102: Fertiliser (basal application)* urea in two doses | B102: =B64 -> 36.409091 | C102: =$B102*C$97 -> 1456.3636 | D102: =$B102*D$97 -> 1456.3636 | E102: =$B102*E$97 -> 1456.3636 | F102: =$B102*F$97 -> 1456.3636 | G102: =$B102*G$97 -> 1456.3636 | H102: =$B102*H$97 -> 1456.3636 | I102: =$B102*I$97 -> 1456.3636 | J102: =$B102*J$97 -> 1456.3636 | ... L102: =$B102*L$97 -> 1456.3636
A103: Pre emergent Herbicide spray | B103: =B65*0.7 -> 14.914773 | C103: =$B103*C$97 -> 596.59091 | D103: =$B103*D$97 -> 596.59091 | E103: =$B103*E$97 -> 596.59091 | F103: =$B103*F$97 -> 596.59091 | G103: =$B103*G$97 -> 596.59091 | H103: =$B103*H$97 -> 596.59091 | I103: =$B103*I$97 -> 596.59091 | J103: =$B103*J$97 -> 596.59091 | ... L103: =$B103*L$97 -> 596.59091
A104: Fungicide and Insecticide spray | B104: =B66*1.5 -> 63.920455 | C104: =$B104*C$97 -> 2556.8182 | D104: =$B104*D$97 -> 2556.8182 | E104: =$B104*E$97 -> 2556.8182 | F104: =$B104*F$97 -> 2556.8182 | G104: =$B104*G$97 -> 2556.8182 | H104: =$B104*H$97 -> 2556.8182 | I104: =$B104*I$97 -> 2556.8182 | J104: =$B104*J$97 -> 2556.8182 | ... L104: =$B104*L$97 -> 2556.8182
A105: =A87 -> Diesel for Irrigation | B105: =B67 -> 38.739669 | C105: =$B105*C$97 -> 1549.5868 | D105: =$B105*D$97 -> 1549.5868 | E105: =$B105*E$97 -> 1549.5868 | F105: =$B105*F$97 -> 1549.5868 | G105: =$B105*G$97 -> 1549.5868 | H105: =$B105*H$97 -> 1549.5868 | I105: =$B105*I$97 -> 1549.5868 | J105: =$B105*J$97 -> 1549.5868 | ... L105: =$B105*L$97 -> 1549.5868
A106: Harvesting (incl labour) | B106: 45 | C106: =$B106*C$97 -> 1800 | D106: =$B106*D$97 -> 1800 | E106: =$B106*E$97 -> 1800 | F106: =$B106*F$97 -> 1800 | G106: =$B106*G$97 -> 1800 | H106: =$B106*H$97 -> 1800 | I106: =$B106*I$97 -> 1800 | J106: =$B106*J$97 -> 1800 | ... L106: =$B106*L$97 -> 1800
A107: Total Cost | B107: =SUM(B97:B106) -> 309.83694 | C107: =SUM(C97:C106) -> 12433.478 | D107: =SUM(D97:D106) -> 12433.478 | E107: =SUM(E97:E106) -> 12433.478 | F107: =SUM(F97:F106) -> 12433.478 | G107: =SUM(G97:G106) -> 12433.478 | H107: =SUM(H97:H106) -> 12433.478 | I107: =SUM(I97:I106) -> 12433.478 | ... L107: =SUM(L97:L106) -> 12433.478
A108: Yield | C108: 2000 | D108: =C108*1.1 -> 2200 | E108: =D108*1.1 -> 2420 | F108: =E108*1.1 -> 2662 | G108: =F108*1.1 -> 2928.2 | H108: =G108 -> 2928.2 | I108: =H108 -> 2928.2 | J108: =I108 -> 2928.2 | K108: =J108 -> 2928.2 | L108: =K108 -> 2928.2
A109: Price / Kg | C109: =(0.4/75)*88 -> 0.46933333 | D109: =C109 -> 0.46933333 | E109: =D109 -> 0.46933333 | F109: =E109 -> 0.46933333 | G109: =F109 -> 0.46933333 | H109: =G109 -> 0.46933333 | I109: =H109 -> 0.46933333 | J109: =I109 -> 0.46933333 | K109: =J109 -> 0.46933333 | L109: =K109 -> 0.46933333
A110: Realisation | C110: =C109*C108*C97 -> 37546.667 | D110: =D109*D108*D97 -> 41301.333 | E110: =E109*E108*E97 -> 45431.467 | F110: =F109*F108*F97 -> 49974.613 | G110: =G109*G108*G97 -> 54972.075 | H110: =H109*H108*H97 -> 54972.075 | I110: =I109*I108*I97 -> 54972.075 | J110: =J109*J108*J97 -> 54972.075 | ... L110: =L109*L108*L97 -> 54972.075
A112: Operating margin | C112: =C110-C107 -> 25113.189 | D112: =D110-D107 -> 28867.856 | E112: =E110-E107 -> 32997.989 | F112: =F110-F107 -> 37541.136 | G112: =G110-G107 -> 42538.597 | H112: =H110-H107 -> 42538.597 | I112: =I110-I107 -> 42538.597 | J112: =J110-J107 -> 42538.597 | ... L112: =L110-L107 -> 42538.597
A114: Onion - with drip
B115: Cost/ Ha | C115: 80 | D115: =C115 -> 80 | E115: =D115 -> 80 | F115: =E115 -> 80 | G115: =F115 -> 80 | H115: =G115 -> 80 | I115: =H115 -> 80 | J115: =I115 -> 80 | K115: =J115 -> 80 | L115: =K115 -> 80
...

Sheet Fin Assumptions
A2: Debt Assumptions
A3: Long term Debt
A4: Moratorium Period | B4: 8 | C4: quarters
A5: Repayment period (years) | B5: 8
A6: Repayment period (Quarters) | B6: =B5*4 -> 32
A8: Rate of interest | B8: 0.06 | C8: p.a.
A10: Quarterly principal payment | B10: =B36/B6 -> 174106.27
A12: Working Capital Loan
A13: Eligibility | B13: 0
A14: margin Money | B14: 1
A15: Rate of interest | B15: 0.04
A16: Requirement
A17: Raw material | B17: 0 | C17: days
A18: Finished Products | B18: 0 | C18: days
A19: Debtors | B19: 30 | C19: days
A22: Income tax rate | B22: 0.05 | C22: p.a.
A24: Depreciation Rates | B24: Book Depr | C24: Tax Depr
A25: Plant & Machinery | B25: 0.1034 | C25: 0.15
A26: Office Furniture | B26: 0.0633 | C26: 0.1
A27: Miscellaneous Fixed Assets | B27: 0.1034 | C27: 0.15
A28: Buildings-Plant (technical) | B28: 0.0334 | C28: 0.05
A29: Buildings-Non technical | B29: 0.0163 | C29: 0.05
A32: Means of finance
A33: Components | B33: Euro | C33: Proportion (%)
A34: Equity | B34: ='Project Cost'!D21*0.3 -> 2387743.1 | C34: =1-C36-C35 -> 0.3 | D34: =B34*0.25 -> 596935.77
A35: Grant | C35: =B35/$B$37 -> 0 | D35: =B35*0.25 -> 0
A36: Debt | B36: =B37-B34 -> 5571400.6 | C36: =B36/$B$37 -> 0.7 | D36: =B36*0.25 -> 1392850.1
A37: Total | B37: ='Project Cost'!D21 -> 7959143.7 | C37: =B37/$B$37 -> 1
A41: Salaries
A42: GM | B42: 1 | C42: 90000 | D42: =C42*B42 -> 90000 | G42: Project Head | H42: 1 | I42: 150000 | J42: =I42*H42 -> 150000
A43: Sales Manager | B43: 1 | C43: 70000 | D43: =C43*B43 -> 70000 | G43: General Manager | H43: 1 | I43: 113636 | J43: =I43*H43 -> 113636
A44: Crop Manager | B44: 3 | C44: 25000 | D44: =C44*B44 -> 75000 | G44: Marketing Head | H44: 1 | I44: =I43 -> 113636 | J44: =I44*H44 -> 113636
A45: Field supervisors | B45: 3 | C45: 20455 | D45: =C45*B45 -> 61365 | G45: Sales Head | H45: 1 | I45: =I44 -> 113636 | J45: =I45*H45 -> 113636
G46: Accounts and Finance Head | H46: 1 | I46: =I45 -> 113636 | J46: =I46*H46 -> 113636
A47: Finance and Accounts | B47: 2 | C47: =1200000/88 -> 13636.364 | D47: =C47*B47 -> 27272.727 | G47: Marketing & Sales Support | H47: 2 | I47: 25000 | J47: =I47*H47 -> 50000
A48: Workshop Supervisor | B48: 1 | C48: =1200000/88 -> 13636.364 | D48: =C48*B48 -> 13636.364 | G48: Finance & Accounts Support | H48: 1 | I48: 25000 | J48: =I48*H48 -> 25000
A49: Warehouse Supervisor | B49: 1 | C49: =1200000/88 -> 13636.364 | D49: =C49*B49 -> 13636.364 | G49: Workshop Staff | H49: 2 | I49: 20000 | J49: =I49*H49 -> 40000
A50: Deshelling Supervisor | B50: 2 | C50: =1200000/88 -> 13636.364 | D50: =C50*B50 -> 27272.727 | G50: Warehouse Staff | H50: 2 | I50: 20000 | J50: =I50*H50 -> 40000
A51: Canteen Supervisor | B51: 1 | C51: =500000/88 -> 5681.8182 | D51: =C51*B51 -> 5681.8182 | G51: De-shelling Staff | H51: 2 | I51: 20000 | J51: =I51*H51 -> 40000
A52: Permant Labour (incl drivers) | B52: 65 | C52: 3000 | D52: =C52*B52 -> 195000 | G52: Canteen Staff | H52: 2 | I52: 12000 | J52: =I52*H52 -> 24000
A53: Total | D53: =SUM(D42:D52) -> 578865 | G53: Labour | H53: 80 | I53: 3000 | J53: =I53*H53 -> 240000 | K53: =J56-J53 -> 1723544
G54: HO Supervision | H54: LS | I54: 500000 | J54: 500000
C55: =300*80 -> 24000 | G55: Staff Travel | H55: LS | I55: 400000 | J55: 400000
C56: =C55/88*12 -> 3272.7273 | J56: =SUM(J42:J55) -> 1963544

Sheet Project Cost
B2: Cost of Project
B3: Particulars | C3: Unit | D3: Total
B4: Project Management Services | C4: Acre | D4: 1200000
B5: Central Facility | C5: Acre
B7: Civil Works
B8: Technical | D8: ='Basic Infrastructure'!F35 -> 2001841.4 | F8: =D8+D9+D13+D16+D18 -> 6380136.8
B9: Project Engineering Services | D9: 200000 | F9: =5%*F8 -> 319006.84
B10: Total | D10: =D8+D9 -> 2201841.4 | F10: =F8+F9 -> 6699143.7
B12: Plant Machinery & Equipments
B13: Plant & Machinery | D13: ='Core Equipment '!G36 -> 3913039.8
B15: Utilities & Other assets
B16: Total Utilities & other Assets | D16: ='Other Equipment'!I10 -> 15255.682
B18: R&D | C18: 0 | D18: 250000
B19: Contingencies | C19: 0.05 | D19: =5%*D20 -> 379006.84
B20: Sub-total | D20: =D10+D13+D16+D18+D4 -> 7580136.8
B21: Total Project Cost | D21: =D20+D19 -> 7959143.7
B26: Means of Finance
B27: Equity
B28: Grant
B29: Long Term Debt
B30: Total

Sheet P&L
B2: Profitability Statement
B3: Year | D3: Year 1 | E3: Year 2 | F3: Year 3 | G3: Year 4 | H3: Year 5 | I3: Year 6 | J3: Year 7 | K3: Year 8 | L3: Year 9 | M3: Year 10
B4: Groundnut | D4: ='Growing cost assum'!C18 -> 50400 | E4: ='Growing cost assum'!D18 -> 54000 | F4: ='Growing cost assum'!E18 -> 55800 | G4: ='Growing cost assum'!F18 -> 61200 | H4: ='Growing cost assum'!G18 -> 72000 | I4: ='Growing cost assum'!H18 -> 72000 | J4: ='Growing cost assum'!I18 -> 72000 | K4: ='Growing cost assum'!J18 -> 72000 | ... M4: ='Growing cost assum'!L18 -> 72000
B5: Cowpea | D5: ='Growing cost assum'!C36 -> 46800 | E5: ='Growing cost assum'!D36 -> 52000 | F5: ='Growing cost assum'!E36 -> 57200 | G5: ='Growing cost assum'!F36 -> 57200 | H5: ='Growing cost assum'!G36 -> 57200 | I5: ='Growing cost assum'!H36 -> 57200 | J5: ='Growing cost assum'!I36 -> 57200 | K5: ='Growing cost assum'!J36 -> 57200 | ... M5: ='Growing cost assum'!L36 -> 57200
B6: Wheat | D6: ='Growing cost assum'!C54 -> 54545.455 | E6: ='Growing cost assum'!D54 -> 58181.818 | F6: ='Growing cost assum'!E54 -> 61818.182 | G6: ='Growing cost assum'!F54 -> 65454.545 | H6: ='Growing cost assum'!G54 -> 72727.273 | I6: ='Growing cost assum'!H54 -> 72727.273 | J6: ='Growing cost assum'!I54 -> 72727.273 | K6: ='Growing cost assum'!J54 -> 72727.273 | ... M6: ='Growing cost assum'!L54 -> 72727.273
B7: Sesame | D7: ='Growing cost assum'!C72 -> 35200 | E7: ='Growing cost assum'!D72 -> 39600 | F7: ='Growing cost assum'!E72 -> 44000 | G7: ='Growing cost assum'!F72 -> 44000 | H7: ='Growing cost assum'!G72 -> 44000 | I7: ='Growing cost assum'!H72 -> 44000 | J7: ='Growing cost assum'!I72 -> 44000 | K7: ='Growing cost assum'!J72 -> 44000 | ... M7: ='Growing cost assum'!L72 -> 44000
B8: Okra | D8: ='Growing cost assum'!C92 -> 56000 | E8: ='Growing cost assum'!D92 -> 63000 | F8: ='Growing cost assum'!E92 -> 70000 | G8: ='Growing cost assum'!F92 -> 77000 | H8: ='Growing cost assum'!G92 -> 84000 | I8: ='Growing cost assum'!H92 -> 84000 | J8: ='Growing cost assum'!I92 -> 84000 | K8: ='Growing cost assum'!J92 -> 84000 | ... M8: ='Growing cost assum'!L92 -> 84000
B9: Sorghum for seed | D9: ='Growing cost assum'!C110 -> 37546.667 | E9: ='Growing cost assum'!D110 -> 41301.333 | F9: ='Growing cost assum'!E110 -> 45431.467 | G9: ='Growing cost assum'!F110 -> 49974.613 | H9: ='Growing cost assum'!G110 -> 54972.075 | I9: ='Growing cost assum'!H110 -> 54972.075 | J9: ='Growing cost assum'!I110 -> 54972.075 | K9: ='Growing cost assum'!J110 -> 54972.075 | ... M9: ='Growing cost assum'!L110 -> 54972.075
B10: Onion | D10: ='Growing cost assum'!C128 -> 2400000 | E10: ='Growing cost assum'!D128 -> 2640000 | F10: ='Growing cost assum'!E128 -> 2880000 | G10: ='Growing cost assum'!F128 -> 3120000 | H10: ='Growing cost assum'!G128 -> 3360000 | I10: ='Growing cost assum'!H128 -> 3600000 | J10: ='Growing cost assum'!I128 -> 3600000 | K10: ='Growing cost assum'!J128 -> 3600000 | ... M10: ='Growing cost assum'!L128 -> 3600000
B11: Aubergine | D11: ='Growing cost assum'!C147 -> 250000 | E11: ='Growing cost assum'!D147 -> 275000 | F11: ='Growing cost assum'!E147 -> 302500 | G11: ='Growing cost assum'!F147 -> 332750 | H11: ='Growing cost assum'!G147 -> 366025 | I11: ='Growing cost assum'!H147 -> 400000 | J11: ='Growing cost assum'!I147 -> 400000 | K11: ='Growing cost assum'!J147 -> 400000 | ... M11: ='Growing cost assum'!L147 -> 400000
B12: Tomato | D12: ='Growing cost assum'!C165 -> 500000 | E12: ='Growing cost assum'!D165 -> 580000 | F12: ='Growing cost assum'!E165 -> 660000 | G12: ='Growing cost assum'!F165 -> 740000 | H12: ='Growing cost assum'!G165 -> 820000 | I12: ='Growing cost assum'!H165 -> 900000 | J12: ='Growing cost assum'!I165 -> 900000 | K12: ='Growing cost assum'!J165 -> 900000 | ... M12: ='Growing cost assum'!L165 -> 900000
B13: Potato | D13: ='Growing cost assum'!C183 -> 320000 | E13: ='Growing cost assum'!D183 -> 400000 | F13: ='Growing cost assum'!E183 -> 480000 | G13: ='Growing cost assum'!F183 -> 560000 | H13: ='Growing cost assum'!G183 -> 600000 | I13: ='Growing cost assum'!H183 -> 600000 | J13: ='Growing cost assum'!I183 -> 600000 | K13: ='Growing cost assum'!J183 -> 600000 | ... M13: ='Growing cost assum'!L183 -> 600000
B14: Alfa Alfa
B16: Revenue | D16: =SUM(D4:D13) -> 3750492.1 | E16: =SUM(E4:E13) -> 4203083.2 | F16: =SUM(F4:F13) -> 4656749.6 | G16: =SUM(G4:G13) -> 5107579.2 | H16: =SUM(H4:H13) -> 5530924.3 | I16: =SUM(I4:I13) -> 5884899.3 | J16: =SUM(J4:J13) -> 5884899.3 | K16: =SUM(K4:K13) -> 5884899.3 | ... M16: =SUM(M4:M13) -> 5884899.3 | IT16: =SUM(A16:IS16) -> 52673325
B18: Variable Expenses
B19: Land preparation | D19: ='Growing cost assum'!C6+'Growing cost assum'!C24+'Growing cost assum'!C42+'Growing cost assum'!C60+'Growing cost assum'!C80+'Growing cost assum'!C98+'Growing cost assum'!C116+'Growing cost assum'!C135+'Growing cost assum'!C153+'Growing cost assum'!C171+'Growing cost assum'!C189 -> 19113.164 | E19: ='Growing cost assum'!D6+'Growing cost assum'!D24+'Growing cost assum'!D42+'Growing cost assum'!D60+'Growing cost assum'!D80+'Growing cost assum'!D98+'Growing cost assum'!D116+'Growing cost assum'!D135+'Growing cost assum'!D153+'Growing cost assum'!D171+'Growing cost assum'!D189 -> 19113.164 | F19: ='Growing cost assum'!E6+'Growing cost assum'!E24+'Growing cost assum'!E42+'Growing cost assum'!E60+'Growing cost assum'!E80+'Growing cost assum'!E98+'Growing cost assum'!E116+'Growing cost assum'!E135+'Growing cost assum'!E153+'Growing cost assum'!E171+'Growing cost assum'!E189 -> 19113.164 | G19: ='Growing cost assum'!F6+'Growing cost assum'!F24+'Growing cost assum'!F42+'Growing cost assum'!F60+'Growing cost assum'!F80+'Growing cost assum'!F98+'Growing cost assum'!F116+'Growing cost assum'!F135+'Growing cost assum'!F153+'Growing cost assum'!F171+'Growing cost assum'!F189 -> 19113.164 | H19: ='Growing cost assum'!G6+'Growing cost assum'!G24+'Growing cost assum'!G42+'Growing cost assum'!G60+'Growing cost assum'!G80+'Growing cost assum'!G98+'Growing cost assum'!G116+'Growing cost assum'!G135+'Growing cost assum'!G153+'Growing cost assum'!G171+'Growing cost assum'!G189 -> 19113.164 | I19: ='Growing cost assum'!H6+'Growing cost assum'!H24+'Growing cost assum'!H42+'Growing cost assum'!H60+'Growing cost assum'!H80+'Growing cost assum'!H98+'Growing cost assum'!H116+'Growing cost assum'!H135+'Growing cost assum'!H153+'Growing cost assum'!H171+'Growing cost assum'!H189 -> 19113.164 | J19: ='Growing cost assum'!I6+'Growing cost assum'!I24+'Growing cost assum'!I42+'Growing cost assum'!I60+'Growing cost assum'!I80+'Growing cost assum'!I98+'Growing cost assum'!I116+'Growing cost assum'!I135+'Growing cost assum'!I153+'Growing cost assum'!I171+'Growing cost assum'!I189 -> 19113.164 | K19: ='Growing cost assum'!J6+'Growing cost assum'!J24+'Growing cost assum'!J42+'Growing cost assum'!J60+'Growing cost assum'!J80+'Growing cost assum'!J98+'Growing cost assum'!J116+'Growing cost assum'!J135+'Growing cost assum'!J153+'Growing cost assum'!J171+'Growing cost assum'!J189 -> 19113.164 | ... M19: ='Growing cost assum'!L6+'Growing cost assum'!L24+'Growing cost assum'!L42+'Growing cost assum'!L60+'Growing cost assum'!L80+'Growing cost assum'!L98+'Growing cost assum'!L116+'Growing cost assum'!L135+'Growing cost assum'!L153+'Growing cost assum'!L171+'Growing cost assum'!L189 -> 19113.164
B20: Seed Cost | D20: ='Growing cost assum'!C7+'Growing cost assum'!C25+'Growing cost assum'!C43+'Growing cost assum'!C61+'Growing cost assum'!C81+'Growing cost assum'!C99+'Growing cost assum'!C117+'Growing cost assum'!C136+'Growing cost assum'!C154+'Growing cost assum'!C172+'Growing cost assum'!C190 -> 126216.91 | E20: ='Growing cost assum'!D7+'Growing cost assum'!D25+'Growing cost assum'!D43+'Growing cost assum'!D61+'Growing cost assum'!D81+'Growing cost assum'!D99+'Growing cost assum'!D117+'Growing cost assum'!D136+'Growing cost assum'!D154+'Growing cost assum'!D172+'Growing cost assum'!D190 -> 126216.91 | F20: ='Growing cost assum'!E7+'Growing cost assum'!E25+'Growing cost assum'!E43+'Growing cost assum'!E61+'Growing cost assum'!E81+'Growing cost assum'!E99+'Growing cost assum'!E117+'Growing cost assum'!E136+'Growing cost assum'!E154+'Growing cost assum'!E172+'Growing cost assum'!E190 -> 126216.91 | G20: ='Growing cost assum'!F7+'Growing cost assum'!F25+'Growing cost assum'!F43+'Growing cost assum'!F61+'Growing cost assum'!F81+'Growing cost assum'!F99+'Growing cost assum'!F117+'Growing cost assum'!F136+'Growing cost assum'!F154+'Growing cost assum'!F172+'Growing cost assum'!F190 -> 126216.91 | H20: ='Growing cost assum'!G7+'Growing cost assum'!G25+'Growing cost assum'!G43+'Growing cost assum'!G61+'Growing cost assum'!G81+'Growing cost assum'!G99+'Growing cost assum'!G117+'Growing cost assum'!G136+'Growing cost assum'!G154+'Growing cost assum'!G172+'Growing cost assum'!G190 -> 126216.91 | I20: ='Growing cost assum'!H7+'Growing cost assum'!H25+'Growing cost assum'!H43+'Growing cost assum'!H61+'Growing cost assum'!H81+'Growing cost assum'!H99+'Growing cost assum'!H117+'Growing cost assum'!H136+'Growing cost assum'!H154+'Growing cost assum'!H172+'Growing cost assum'!H190 -> 126216.91 | J20: ='Growing cost assum'!I7+'Growing cost assum'!I25+'Growing cost assum'!I43+'Growing cost assum'!I61+'Growing cost assum'!I81+'Growing cost assum'!I99+'Growing cost assum'!I117+'Growing cost assum'!I136+'Growing cost assum'!I154+'Growing cost assum'!I172+'Growing cost assum'!I190 -> 126216.91 | K20: ='Growing cost assum'!J7+'Growing cost assum'!J25+'Growing cost assum'!J43+'Growing cost assum'!J61+'Growing cost assum'!J81+'Growing cost assum'!J99+'Growing cost assum'!J117+'Growing cost assum'!J136+'Growing cost assum'!J154+'Growing cost assum'!J172+'Growing cost assum'!J190 -> 126216.91 | ... M20: ='Growing cost assum'!L7+'Growing cost assum'!L25+'Growing cost assum'!L43+'Growing cost assum'!L61+'Growing cost assum'!L81+'Growing cost assum'!L99+'Growing cost assum'!L117+'Growing cost assum'!L136+'Growing cost assum'!L154+'Growing cost assum'!L172+'Growing cost assum'!L190 -> 126216.91
B21: Seed treatment / Nursery cost | D21: ='Growing cost assum'!C8+'Growing cost assum'!C26+'Growing cost assum'!C44+'Growing cost assum'!C62+'Growing cost assum'!C82+'Growing cost assum'!C100+'Growing cost assum'!C118+'Growing cost assum'!C137+'Growing cost assum'!C155+'Growing cost assum'!C173+'Growing cost assum'!C191 -> 27223.864 | E21: ='Growing cost assum'!D8+'Growing cost assum'!D26+'Growing cost assum'!D44+'Growing cost assum'!D62+'Growing cost assum'!D82+'Growing cost assum'!D100+'Growing cost assum'!D118+'Growing cost assum'!D137+'Growing cost assum'!D155+'Growing cost assum'!D173+'Growing cost assum'!D191 -> 27223.864 | F21: ='Growing cost assum'!E8+'Growing cost assum'!E26+'Growing cost assum'!E44+'Growing cost assum'!E62+'Growing cost assum'!E82+'Growing cost assum'!E100+'Growing cost assum'!E118+'Growing cost assum'!E137+'Growing cost assum'!E155+'Growing cost assum'!E173+'Growing cost assum'!E191 -> 27223.864 | G21: ='Growing cost assum'!F8+'Growing cost assum'!F26+'Growing cost assum'!F44+'Growing cost assum'!F62+'Growing cost assum'!F82+'Growing cost assum'!F100+'Growing cost assum'!F118+'Growing cost assum'!F137+'Growing cost assum'!F155+'Growing cost assum'!F173+'Growing cost assum'!F191 -> 27223.864 | H21: ='Growing cost assum'!G8+'Growing cost assum'!G26+'Growing cost assum'!G44+'Growing cost assum'!G62+'Growing cost assum'!G82+'Growing cost assum'!G100+'Growing cost assum'!G118+'Growing cost assum'!G137+'Growing cost assum'!G155+'Growing cost assum'!G173+'Growing cost assum'!G191 -> 27223.864 | I21: ='Growing cost assum'!H8+'Growing cost assum'!H26+'Growing cost assum'!H44+'Growing cost assum'!H62+'Growing cost assum'!H82+'Growing cost assum'!H100+'Growing cost assum'!H118+'Growing cost assum'!H137+'Growing cost assum'!H155+'Growing cost assum'!H173+'Growing cost assum'!H191 -> 27223.864 | J21: ='Growing cost assum'!I8+'Growing cost assum'!I26+'Growing cost assum'!I44+'Growing cost assum'!I62+'Growing cost assum'!I82+'Growing cost assum'!I100+'Growing cost assum'!I118+'Growing cost assum'!I137+'Growing cost assum'!I155+'Growing cost assum'!I173+'Growing cost assum'!I191 -> 27223.864 | K21: ='Growing cost assum'!J8+'Growing cost assum'!J26+'Growing cost assum'!J44+'Growing cost assum'!J62+'Growing cost assum'!J82+'Growing cost assum'!J100+'Growing cost assum'!J118+'Growing cost assum'!J137+'Growing cost assum'!J155+'Growing cost assum'!J173+'Growing cost assum'!J191 -> 27223.864 | ... M21: ='Growing cost assum'!L8+'Growing cost assum'!L26+'Growing cost assum'!L44+'Growing cost assum'!L62+'Growing cost assum'!L82+'Growing cost assum'!L100+'Growing cost assum'!L118+'Growing cost assum'!L137+'Growing cost assum'!L155+'Growing cost assum'!L173+'Growing cost assum'!L191 -> 27223.864
B22: Sowing cost | D22: ='Growing cost assum'!C9+'Growing cost assum'!C27+'Growing cost assum'!C45+'Growing cost assum'!C63+'Growing cost assum'!C83+'Growing cost assum'!C101+'Growing cost assum'!C119+'Growing cost assum'!C138+'Growing cost assum'!C156+'Growing cost assum'!C174+'Growing cost assum'!C192 -> 60932.127 | E22: ='Growing cost assum'!D9+'Growing cost assum'!D27+'Growing cost assum'!D45+'Growing cost assum'!D63+'Growing cost assum'!D83+'Growing cost assum'!D101+'Growing cost assum'!D119+'Growing cost assum'!D138+'Growing cost assum'!D156+'Growing cost assum'!D174+'Growing cost assum'!D192 -> 60932.127 | F22: ='Growing cost assum'!E9+'Growing cost assum'!E27+'Growing cost assum'!E45+'Growing cost assum'!E63+'Growing cost assum'!E83+'Growing cost assum'!E101+'Growing cost assum'!E119+'Growing cost assum'!E138+'Growing cost assum'!E156+'Growing cost assum'!E174+'Growing cost assum'!E192 -> 60932.127 | G22: ='Growing cost assum'!F9+'Growing cost assum'!F27+'Growing cost assum'!F45+'Growing cost assum'!F63+'Growing cost assum'!F83+'Growing cost assum'!F101+'Growing cost assum'!F119+'Growing cost assum'!F138+'Growing cost assum'!F156+'Growing cost assum'!F174+'Growing cost assum'!F192 -> 60932.127 | H22: ='Growing cost assum'!G9+'Growing cost assum'!G27+'Growing cost assum'!G45+'Growing cost assum'!G63+'Growing cost assum'!G83+'Growing cost assum'!G101+'Growing cost assum'!G119+'Growing cost assum'!G138+'Growing cost assum'!G156+'Growing cost assum'!G174+'Growing cost assum'!G192 -> 60932.127 | I22: ='Growing cost assum'!H9+'Growing cost assum'!H27+'Growing cost assum'!H45+'Growing cost assum'!H63+'Growing cost assum'!H83+'Growing cost assum'!H101+'Growing cost assum'!H119+'Growing cost assum'!H138+'Growing cost assum'!H156+'Growing cost assum'!H174+'Growing cost assum'!H192 -> 60932.127 | J22: ='Growing cost assum'!I9+'Growing cost assum'!I27+'Growing cost assum'!I45+'Growing cost assum'!I63+'Growing cost assum'!I83+'Growing cost assum'!I101+'Growing cost assum'!I119+'Growing cost assum'!I138+'Growing cost assum'!I156+'Growing cost assum'!I174+'Growing cost assum'!I192 -> 60932.127 | K22: ='Growing cost assum'!J9+'Growing cost assum'!J27+'Growing cost assum'!J45+'Growing cost assum'!J63+'Growing cost assum'!J83+'Growing cost assum'!J101+'Growing cost assum'!J119+'Growing cost assum'!J138+'Growing cost assum'!J156+'Growing cost assum'!J174+'Growing cost assum'!J192 -> 60932.127 | ... M22: ='Growing cost assum'!L9+'Growing cost assum'!L27+'Growing cost assum'!L45+'Growing cost assum'!L63+'Growing cost assum'!L83+'Growing cost assum'!L101+'Growing cost assum'!L119+'Growing cost assum'!L138+'Growing cost assum'!L156+'Growing cost assum'!L174+'Growing cost assum'!L192 -> 60932.127
B23: Fertiliser (basal application)* urea in two doses | D23: ='Growing cost assum'!C10+'Growing cost assum'!C28+'Growing cost assum'!C46+'Growing cost assum'!C64+'Growing cost assum'!C84+'Growing cost assum'!C102+'Growing cost assum'!C120+'Growing cost assum'!C139+'Growing cost assum'!C157+'Growing cost assum'!C175+'Growing cost assum'!C193 -> 144760.91 | E23: ='Growing cost assum'!D10+'Growing cost assum'!D28+'Growing cost assum'!D46+'Growing cost assum'!D64+'Growing cost assum'!D84+'Growing cost assum'!D102+'Growing cost assum'!D120+'Growing cost assum'!D139+'Growing cost assum'!D157+'Growing cost assum'!D175+'Growing cost assum'!D193 -> 144760.91 | F23: ='Growing cost assum'!E10+'Growing cost assum'!E28+'Growing cost assum'!E46+'Growing cost assum'!E64+'Growing cost assum'!E84+'Growing cost assum'!E102+'Growing cost assum'!E120+'Growing cost assum'!E139+'Growing cost assum'!E157+'Growing cost assum'!E175+'Growing cost assum'!E193 -> 144760.91 | G23: ='Growing cost assum'!F10+'Growing cost assum'!F28+'Growing cost assum'!F46+'Growing cost assum'!F64+'Growing cost assum'!F84+'Growing cost assum'!F102+'Growing cost assum'!F120+'Growing cost assum'!F139+'Growing cost assum'!F157+'Growing cost assum'!F175+'Growing cost assum'!F193 -> 144760.91 | H23: ='Growing cost assum'!G10+'Growing cost assum'!G28+'Growing cost assum'!G46+'Growing cost assum'!G64+'Growing cost assum'!G84+'Growing cost assum'!G102+'Growing cost assum'!G120+'Growing cost assum'!G139+'Growing cost assum'!G157+'Growing cost assum'!G175+'Growing cost assum'!G193 -> 144760.91 | I23: ='Growing cost assum'!H10+'Growing cost assum'!H28+'Growing cost assum'!H46+'Growing cost assum'!H64+'Growing cost assum'!H84+'Growing cost assum'!H102+'Growing cost assum'!H120+'Growing cost assum'!H139+'Growing cost assum'!H157+'Growing cost assum'!H175+'Growing cost assum'!H193 -> 144760.91 | J23: ='Growing cost assum'!I10+'Growing cost assum'!I28+'Growing cost assum'!I46+'Growing cost assum'!I64+'Growing cost assum'!I84+'Growing cost assum'!I102+'Growing cost assum'!I120+'Growing cost assum'!I139+'Growing cost assum'!I157+'Growing cost assum'!I175+'Growing cost assum'!I193 -> 144760.91 | K23: ='Growing cost assum'!J10+'Growing cost assum'!J28+'Growing cost assum'!J46+'Growing cost assum'!J64+'Growing cost assum'!J84+'Growing cost assum'!J102+'Growing cost assum'!J120+'Growing cost assum'!J139+'Growing cost assum'!J157+'Growing cost assum'!J175+'Growing cost assum'!J193 -> 144760.91 | ... M23: ='Growing cost assum'!L10+'Growing cost assum'!L28+'Growing cost assum'!L46+'Growing cost assum'!L64+'Growing cost assum'!L84+'Growing cost assum'!L102+'Growing cost assum'!L120+'Growing cost assum'!L139+'Growing cost assum'!L157+'Growing cost assum'!L175+'Growing cost assum'!L193 -> 144760.91
B24: Pre emergent Herbicide spray | D24: ='Growing cost assum'!C11+'Growing cost assum'!C29+'Growing cost assum'!C47+'Growing cost assum'!C65+'Growing cost assum'!C85+'Growing cost assum'!C103+'Growing cost assum'!C121+'Growing cost assum'!C140+'Growing cost assum'!C158+'Growing cost assum'!C176+'Growing cost assum'!C194 -> 55142.045 | E24: ='Growing cost assum'!D11+'Growing cost assum'!D29+'Growing cost assum'!D47+'Growing cost assum'!D65+'Growing cost assum'!D85+'Growing cost assum'!D103+'Growing cost assum'!D121+'Growing cost assum'!D140+'Growing cost assum'!D158+'Growing cost assum'!D176+'Growing cost assum'!D194 -> 55142.045 | F24: ='Growing cost assum'!E11+'Growing cost assum'!E29+'Growing cost assum'!E47+'Growing cost assum'!E65+'Growing cost assum'!E85+'Growing cost assum'!E103+'Growing cost assum'!E121+'Growing cost assum'!E140+'Growing cost assum'!E158+'Growing cost assum'!E176+'Growing cost assum'!E194 -> 55142.045 | G24: ='Growing cost assum'!F11+'Growing cost assum'!F29+'Growing cost assum'!F47+'Growing cost assum'!F65+'Growing cost assum'!F85+'Growing cost assum'!F103+'Growing cost assum'!F121+'Growing cost assum'!F140+'Growing cost assum'!F158+'Growing cost assum'!F176+'Growing cost assum'!F194 -> 55142.045 | H24: ='Growing cost assum'!G11+'Growing cost assum'!G29+'Growing cost assum'!G47+'Growing cost assum'!G65+'Growing cost assum'!G85+'Growing cost assum'!G103+'Growing cost assum'!G121+'Growing cost assum'!G140+'Growing cost assum'!G158+'Growing cost assum'!G176+'Growing cost assum'!G194 -> 55142.045 | I24: ='Growing cost assum'!H11+'Growing cost assum'!H29+'Growing cost assum'!H47+'Growing cost assum'!H65+'Growing cost assum'!H85+'Growing cost assum'!H103+'Growing cost assum'!H121+'Growing cost assum'!H140+'Growing cost assum'!H158+'Growing cost assum'!H176+'Growing cost assum'!H194 -> 55142.045 | J24: ='Growing cost assum'!I11+'Growing cost assum'!I29+'Growing cost assum'!I47+'Growing cost assum'!I65+'Growing cost assum'!I85+'Growing cost assum'!I103+'Growing cost assum'!I121+'Growing cost assum'!I140+'Growing cost assum'!I158+'Growing cost assum'!I176+'Growing cost assum'!I194 -> 55142.045 | K24: ='Growing cost assum'!J11+'Growing cost assum'!J29+'Growing cost assum'!J47+'Growing cost assum'!J65+'Growing cost assum'!J85+'Growing cost assum'!J103+'Growing cost assum'!J121+'Growing cost assum'!J140+'Growing cost assum'!J158+'Growing cost assum'!J176+'Growing cost assum'!J194 -> 55142.045 | ... M24: ='Growing cost assum'!L11+'Growing cost assum'!L29+'Growing cost assum'!L47+'Growing cost assum'!L65+'Growing cost assum'!L85+'Growing cost assum'!L103+'Growing cost assum'!L121+'Growing cost assum'!L140+'Growing cost assum'!L158+'Growing cost assum'!L176+'Growing cost assum'!L194 -> 55142.045
B25: Fungicide and Insecticide spray | D25: ='Growing cost assum'!C12+'Growing cost assum'!C30+'Growing cost assum'!C48+'Growing cost assum'!C66+'Growing cost assum'!C86+'Growing cost assum'!C104+'Growing cost assum'!C122+'Growing cost assum'!C141+'Growing cost assum'!C159+'Growing cost assum'!C177+'Growing cost assum'!C195 -> 80678.182 | E25: ='Growing cost assum'!D12+'Growing cost assum'!D30+'Growing cost assum'!D48+'Growing cost assum'!D66+'Growing cost assum'!D86+'Growing cost assum'!D104+'Growing cost assum'!D122+'Growing cost assum'!D141+'Growing cost assum'!D159+'Growing cost assum'!D177+'Growing cost assum'!D195 -> 80678.182 | F25: ='Growing cost assum'!E12+'Growing cost assum'!E30+'Growing cost assum'!E48+'Growing cost assum'!E66+'Growing cost assum'!E86+'Growing cost assum'!E104+'Growing cost assum'!E122+'Growing cost assum'!E141+'Growing cost assum'!E159+'Growing cost assum'!E177+'Growing cost assum'!E195 -> 80678.182 | G25: ='Growing cost assum'!F12+'Growing cost assum'!F30+'Growing cost assum'!F48+'Growing cost assum'!F66+'Growing cost assum'!F86+'Growing cost assum'!F104+'Growing cost assum'!F122+'Growing cost assum'!F141+'Growing cost assum'!F159+'Growing cost assum'!F177+'Growing cost assum'!F195 -> 80678.182 | H25: ='Growing cost assum'!G12+'Growing cost assum'!G30+'Growing cost assum'!G48+'Growing cost assum'!G66+'Growing cost assum'!G86+'Growing cost assum'!G104+'Growing cost assum'!G122+'Growing cost assum'!G141+'Growing cost assum'!G159+'Growing cost assum'!G177+'Growing cost assum'!G195 -> 80678.182 | I25: ='Growing cost assum'!H12+'Growing cost assum'!H30+'Growing cost assum'!H48+'Growing cost assum'!H66+'Growing cost assum'!H86+'Growing cost assum'!H104+'Growing cost assum'!H122+'Growing cost assum'!H141+'Growing cost assum'!H159+'Growing cost assum'!H177+'Growing cost assum'!H195 -> 80678.182 | J25: ='Growing cost assum'!I12+'Growing cost assum'!I30+'Growing cost assum'!I48+'Growing cost assum'!I66+'Growing cost assum'!I86+'Growing cost assum'!I104+'Growing cost assum'!I122+'Growing cost assum'!I141+'Growing cost assum'!I159+'Growing cost assum'!I177+'Growing cost assum'!I195 -> 80678.182 | K25: ='Growing cost assum'!J12+'Growing cost assum'!J30+'Growing cost assum'!J48+'Growing cost assum'!J66+'Growing cost assum'!J86+'Growing cost assum'!J104+'Growing cost assum'!J122+'Growing cost assum'!J141+'Growing cost assum'!J159+'Growing cost assum'!J177+'Growing cost assum'!J195 -> 80678.182 | ... M25: ='Growing cost assum'!L12+'Growing cost assum'!L30+'Growing cost assum'!L48+'Growing cost assum'!L66+'Growing cost assum'!L86+'Growing cost assum'!L104+'Growing cost assum'!L122+'Growing cost assum'!L141+'Growing cost assum'!L159+'Growing cost assum'!L177+'Growing cost assum'!L195 -> 80678.182
B26: Diesel for irrigation | D26: ='Growing cost assum'!C13+'Growing cost assum'!C31+'Growing cost assum'!C49+'Growing cost assum'!C67+'Growing cost assum'!C87+'Growing cost assum'!C105+'Growing cost assum'!C123+'Growing cost assum'!C142+'Growing cost assum'!C160+'Growing cost assum'!C178+'Growing cost assum'!C196 -> 47553.182 | E26: ='Growing cost assum'!D13+'Growing cost assum'!D31+'Growing cost assum'!D49+'Growing cost assum'!D67+'Growing cost assum'!D87+'Growing cost assum'!D105+'Growing cost assum'!D123+'Growing cost assum'!D142+'Growing cost assum'!D160+'Growing cost assum'!D178+'Growing cost assum'!D196 -> 47553.182 | F26: ='Growing cost assum'!E13+'Growing cost assum'!E31+'Growing cost assum'!E49+'Growing cost assum'!E67+'Growing cost assum'!E87+'Growing cost assum'!E105+'Growing cost assum'!E123+'Growing cost assum'!E142+'Growing cost assum'!E160+'Growing cost assum'!E178+'Growing cost assum'!E196 -> 47553.182 | G26: ='Growing cost assum'!F13+'Growing cost assum'!F31+'Growing cost assum'!F49+'Growing cost assum'!F67+'Growing cost assum'!F87+'Growing cost assum'!F105+'Growing cost assum'!F123+'Growing cost assum'!F142+'Growing cost assum'!F160+'Growing cost assum'!F178+'Growing cost assum'!F196 -> 47553.182 | H26: ='Growing cost assum'!G13+'Growing cost assum'!G31+'Growing cost assum'!G49+'Growing cost assum'!G67+'Growing cost assum'!G87+'Growing cost assum'!G105+'Growing cost assum'!G123+'Growing cost assum'!G142+'Growing cost assum'!G160+'Growing cost assum'!G178+'Growing cost assum'!G196 -> 47553.182 | I26: ='Growing cost assum'!H13+'Growing cost assum'!H31+'Growing cost assum'!H49+'Growing cost assum'!H67+'Growing cost assum'!H87+'Growing cost assum'!H105+'Growing cost assum'!H123+'Growing cost assum'!H142+'Growing cost assum'!H160+'Growing cost assum'!H178+'Growing cost assum'!H196 -> 47553.182 | J26: ='Growing cost assum'!I13+'Growing cost assum'!I31+'Growing cost assum'!I49+'Growing cost assum'!I67+'Growing cost assum'!I87+'Growing cost assum'!I105+'Growing cost assum'!I123+'Growing cost assum'!I142+'Growing cost assum'!I160+'Growing cost assum'!I178+'Growing cost assum'!I196 -> 47553.182 | K26: ='Growing cost assum'!J13+'Growing cost assum'!J31+'Growing cost assum'!J49+'Growing cost assum'!J67+'Growing cost assum'!J87+'Growing cost assum'!J105+'Growing cost assum'!J123+'Growing cost assum'!J142+'Growing cost assum'!J160+'Growing cost assum'!J178+'Growing cost assum'!J196 -> 47553.182 | ... M26: ='Growing cost assum'!L13+'Growing cost assum'!L31+'Growing cost assum'!L49+'Growing cost assum'!L67+'Growing cost assum'!L87+'Growing cost assum'!L105+'Growing cost assum'!L123+'Growing cost assum'!L142+'Growing cost assum'!L160+'Growing cost assum'!L178+'Growing cost assum'!L196 -> 47553.182
B27: Harvesting (incl labour) | D27: ='Growing cost assum'!C14+'Growing cost assum'!C32+'Growing cost assum'!C50+'Growing cost assum'!C68+'Growing cost assum'!C88+'Growing cost assum'!C106+'Growing cost assum'!C124+'Growing cost assum'!C143+'Growing cost assum'!C161+'Growing cost assum'!C179+'Growing cost assum'!C197 -> 145291.36 | E27: ='Growing cost assum'!D14+'Growing cost assum'!D32+'Growing cost assum'!D50+'Growing cost assum'!D68+'Growing cost assum'!D88+'Growing cost assum'!D106+'Growing cost assum'!D124+'Growing cost assum'!D143+'Growing cost assum'!D161+'Growing cost assum'!D179+'Growing cost assum'!D197 -> 145291.36 | F27: ='Growing cost assum'!E14+'Growing cost assum'!E32+'Growing cost assum'!E50+'Growing cost assum'!E68+'Growing cost assum'!E88+'Growing cost assum'!E106+'Growing cost assum'!E124+'Growing cost assum'!E143+'Growing cost assum'!E161+'Growing cost assum'!E179+'Growing cost assum'!E197 -> 145291.36 | G27: ='Growing cost assum'!F14+'Growing cost assum'!F32+'Growing cost assum'!F50+'Growing cost assum'!F68+'Growing cost assum'!F88+'Growing cost assum'!F106+'Growing cost assum'!F124+'Growing cost assum'!F143+'Growing cost assum'!F161+'Growing cost assum'!F179+'Growing cost assum'!F197 -> 145291.36 | H27: ='Growing cost assum'!G14+'Growing cost assum'!G32+'Growing cost assum'!G50+'Growing cost assum'!G68+'Growing cost assum'!G88+'Growing cost assum'!G106+'Growing cost assum'!G124+'Growing cost assum'!G143+'Growing cost assum'!G161+'Growing cost assum'!G179+'Growing cost assum'!G197 -> 145291.36 | I27: ='Growing cost assum'!H14+'Growing cost assum'!H32+'Growing cost assum'!H50+'Growing cost assum'!H68+'Growing cost assum'!H88+'Growing cost assum'!H106+'Growing cost assum'!H124+'Growing cost assum'!H143+'Growing cost assum'!H161+'Growing cost assum'!H179+'Growing cost assum'!H197 -> 145291.36 | J27: ='Growing cost assum'!I14+'Growing cost assum'!I32+'Growing cost assum'!I50+'Growing cost assum'!I68+'Growing cost assum'!I88+'Growing cost assum'!I106+'Growing cost assum'!I124+'Growing cost assum'!I143+'Growing cost assum'!I161+'Growing cost assum'!I179+'Growing cost assum'!I197 -> 145291.36 | K27: ='Growing cost assum'!J14+'Growing cost assum'!J32+'Growing cost assum'!J50+'Growing cost assum'!J68+'Growing cost assum'!J88+'Growing cost assum'!J106+'Growing cost assum'!J124+'Growing cost assum'!J143+'Growing cost assum'!J161+'Growing cost assum'!J179+'Growing cost assum'!J197 -> 145291.36 | ... M27: ='Growing cost assum'!L14+'Growing cost assum'!L32+'Growing cost assum'!L50+'Growing cost assum'!L68+'Growing cost assum'!L88+'Growing cost assum'!L106+'Growing cost assum'!L124+'Growing cost assum'!L143+'Growing cost assum'!L161+'Growing cost assum'!L179+'Growing cost assum'!L197 -> 145291.36
B29: Total Variable Costs | D29: =SUM(D19:D27) -> 706911.75 | E29: =SUM(E19:E27) -> 706911.75 | F29: =SUM(F19:F27) -> 706911.75 | G29: =SUM(G19:G27) -> 706911.75 | H29: =SUM(H19:H27) -> 706911.75 | I29: =SUM(I19:I27) -> 706911.75 | J29: =SUM(J19:J27) -> 706911.75 | K29: =SUM(K19:K27) -> 706911.75 | ... M29: =SUM(M19:M27) -> 706911.75
B31: Fixed Expenses
B32: Salaries (Permanent) | D32: ='Fin Assumptions'!D53 -> 578865 | E32: =D32*1.05 -> 607808.25 | F32: =E32*1.05 -> 638198.66 | G32: =F32*1.05 -> 670108.6 | H32: =G32*1.05 -> 703614.03 | I32: =H32*1.05 -> 738794.73 | J32: =I32*1.05 -> 775734.46 | K32: =J32*1.05 -> 814521.19 | L32: =K32*1.05 -> 855247.25 | M32: =L32*1.05 -> 898009.61
B33: Maintenance | D33: =2%*'Project Cost'!$D$21 -> 159182.87 | E33: =2%*'Project Cost'!$D$21 -> 159182.87 | F33: =2%*'Project Cost'!$D$21 -> 159182.87 | G33: =3%*'Project Cost'!$D$21 -> 238774.31 | H33: =3%*'Project Cost'!$D$21 -> 238774.31 | I33: =3%*'Project Cost'!$D$21 -> 238774.31 | J33: =4%*'Project Cost'!$D$21 -> 318365.75 | K33: =4%*'Project Cost'!$D$21 -> 318365.75 | L33: =4%*'Project Cost'!$D$21 -> 318365.75 | M33: =4%*'Project Cost'!$D$21 -> 318365.75
B34: PMC | D34: 0 | E34: =300000 -> 300000 | F34: =E34+25000 -> 325000 | G34: =F34+25000 -> 350000 | H34: =G34+25000 -> 375000 | I34: =H34+25000 -> 400000 | J34: =I34+25000 -> 425000 | K34: =J34+25000 -> 450000 | L34: =K34+25000 -> 475000 | M34: =L34+25000 -> 500000
B35: R&D | D35: 25000 | E35: =D35*1.05 -> 26250 | F35: =E35*1.05 -> 27562.5 | G35: =F35*1.05 -> 28940.625 | H35: =G35*1.05 -> 30387.656 | I35: =H35*1.05 -> 31907.039 | J35: =I35*1.05 -> 33502.391 | K35: =J35*1.05 -> 35177.511 | L35: =K35*1.05 -> 36936.386 | M35: =L35*1.05 -> 38783.205
B36: Insurance | D36: =Dep.!C42*1% -> 52176.491 | E36: =Dep.!D42*1% -> 44540.018 | F36: =Dep.!E42*1% -> 38039.515 | G36: =Dep.!F42*1% -> 32505.063 | H36: =Dep.!G42*1% -> 27792.205 | I36: =Dep.!H42*1% -> 23778.13 | J36: =Dep.!I42*1% -> 20358.429 | K36: =Dep.!J42*1% -> 17444.332 | ... M36: =Dep.!L42*1% -> 12842.361
B38: Total Fixed Costs | D38: =SUM(D32:D36) -> 815224.36 | E38: =SUM(E32:E36) -> 1137781.1 | F38: =SUM(F32:F36) -> 1187983.6 | G38: =SUM(G32:G36) -> 1320328.6 | H38: =SUM(H32:H36) -> 1375568.2 | I38: =SUM(I32:I36) -> 1433254.2 | J38: =SUM(J32:J36) -> 1572961 | K38: =SUM(K32:K36) -> 1635508.8 | ... M38: =SUM(M32:M36) -> 1768000.9
B40: Total Expenses | D40: =D38+D29 -> 1522136.1 | E40: =E38+E29 -> 1844692.9 | F40: =F38+F29 -> 1894895.3 | G40: =G38+G29 -> 2027240.3 | H40: =H38+H29 -> 2082479.9 | I40: =I38+I29 -> 2140166 | J40: =J38+J29 -> 2279872.8 | K40: =K38+K29 -> 2342420.5 | ... M40: =M38+M29 -> 2474912.7
B42: EBITDA | D42: =D16-D40 -> 2228356 | E42: =E16-E40 -> 2358390.3 | F42: =F16-F40 -> 2761854.4 | G42: =G16-G40 -> 3080338.8 | H42: =H16-H40 -> 3448444.4 | I42: =I16-I40 -> 3744733.4 | J42: =J16-J40 -> 3605026.6 | K42: =K16-K40 -> 3542478.8 | ... M42: =M16-M40 -> 3409986.7
B43: Interest Long Term Debt (LTD) | D43: =Debt!D49 -> 334284.03 | E43: =Debt!E49 -> 334284.03 | F43: =Debt!F49 -> 318614.47 | G43: =Debt!G49 -> 276828.97 | H43: =Debt!H49 -> 235043.46 | I43: =Debt!I49 -> 193257.96 | J43: =Debt!J49 -> 151472.45 | K43: =Debt!K49 -> 109686.95 | ... M43: =Debt!M49 -> 26115.94
B44: Interest Working Capital borrowing | D44: =Debt!D71 -> 10001.312 | E44: =Debt!E71 -> 22416.443 | F44: =Debt!F71 -> 24835.998 | G44: =Debt!G71 -> 27240.422 | H44: =Debt!H71 -> 29498.263 | I44: =Debt!I71 -> 31386.13 | J44: =Debt!J71 -> 31386.13 | K44: =Debt!K71 -> 31386.13 | ... M44: =Debt!M71 -> 31386.13
B45: Depreciation | D45: =Dep.!C20 -> 471469.83 | E45: =Dep.!D20 -> 471469.83 | F45: =Dep.!E20 -> 471469.83 | G45: =Dep.!F20 -> 471469.83 | H45: =Dep.!G20 -> 471469.83 | I45: =Dep.!H20 -> 471469.83 | J45: =Dep.!I20 -> 471469.83 | K45: =Dep.!J20 -> 471469.83 | ... M45: =Dep.!L20 -> 471469.83
B46: PBT | D46: =D42-SUM(D43:D45) -> 1412600.8 | E46: =E42-SUM(E43:E45) -> 1530220 | F46: =F42-SUM(F43:F45) -> 1946934.1 | G46: =G42-SUM(G43:G45) -> 2304799.6 | H46: =H42-SUM(H43:H45) -> 2712432.9 | I46: =I42-SUM(I43:I45) -> 3048619.5 | J46: =J42-SUM(J43:J45) -> 2950698.2 | K46: =K42-SUM(K43:K45) -> 2929935.9 | ... M46: =M42-SUM(M43:M45) -> 2881014.8
B47: Tax | D47: =D58 -> 49341.925 | E47: =E58 -> 61902.121 | F47: =F58 -> 88417.681 | G47: =G58 -> 111141.21 | H47: =H58 -> 135630.84 | I47: =I58 -> 155934.09 | J47: =J58 -> 154009.89 | K47: =K58 -> 155499.8 | ... M47: =M58 -> 157034.21
B48: Net Profit (PAT) | D48: =D46-D47 -> 1363258.9 | E48: =E46-E47 -> 1468317.8 | F48: =F46-F47 -> 1858516.4 | G48: =G46-G47 -> 2193658.4 | H48: =H46-H47 -> 2576802 | I48: =I46-I47 -> 2892685.4 | J48: =J46-J47 -> 2796688.3 | K48: =K46-K47 -> 2774436.1 | ... M48: =M46-M47 -> 2723980.6
B50: Net Cash from Operations | D50: =D48+D45 -> 1834728.7 | E50: =E48+E45 -> 1939787.7 | F50: =F48+F45 -> 2329986.2 | G50: =G48+G45 -> 2665128.2 | H50: =H48+H45 -> 3048271.8 | I50: =I48+I45 -> 3364155.2 | J50: =J48+J45 -> 3268158.1 | K50: =K48+K45 -> 3245905.9 | ... M50: =M48+M45 -> 3195450.4
B53: Tax Calculation
B54: PBT | D54: =D46 -> 1412600.8 | E54: =E46 -> 1530220 | F54: =F46 -> 1946934.1 | G54: =G46 -> 2304799.6 | H54: =H46 -> 2712432.9 | I54: =I46 -> 3048619.5 | J54: =J46 -> 2950698.2 | K54: =K46 -> 2929935.9 | ... M54: =M46 -> 2881014.8
B55: Book Depreciation | D55: =D45 -> 471469.83 | E55: =E45 -> 471469.83 | F55: =F45 -> 471469.83 | G55: =G45 -> 471469.83 | H55: =H45 -> 471469.83 | I55: =I45 -> 471469.83 | J55: =J45 -> 471469.83 | K55: =K45 -> 471469.83 | ... M55: =M45 -> 471469.83
B56: Tax depreciation | D56: =Dep.!C34 -> 897232.17 | E56: =Dep.!D34 -> 763647.37 | F56: =Dep.!E34 -> 650050.26 | G56: =Dep.!F34 -> 553445.22 | H56: =Dep.!G34 -> 471285.81 | I56: =Dep.!H34 -> 401407.45 | J56: =Dep.!I34 -> 341970.11 | K56: =Dep.!J34 -> 291409.69 | ... M56: =Dep.!L34 -> 211800.51
B57: Taxable Income | D57: =D54+D55-D56 -> 986838.49 | E57: =E54+E55-E56 -> 1238042.4 | F57: =F54+F55-F56 -> 1768353.6 | G57: =G54+G55-G56 -> 2222824.2 | H57: =H54+H55-H56 -> 2712616.9 | I57: =I54+I55-I56 -> 3118681.9 | J57: =J54+J55-J56 -> 3080197.9 | K57: =K54+K55-K56 -> 3109996.1 | ... M57: =M54+M55-M56 -> 3140684.1
B58: Income Tax | D58: =IF(D60>=0,D57*'Fin Assumptions'!$B$22,0) -> 49341.925 | E58: =IF(E60>=0,E57*'Fin Assumptions'!$B$22,0) -> 61902.121 | F58: =IF(F60>=0,F57*'Fin Assumptions'!$B$22,0) -> 88417.681 | G58: =IF(G60>=0,G57*'Fin Assumptions'!$B$22,0) -> 111141.21 | H58: =IF(H60>=0,H57*'Fin Assumptions'!$B$22,0) -> 135630.84 | I58: =IF(I60>=0,I57*'Fin Assumptions'!$B$22,0) -> 155934.09 | J58: =IF(J60>=0,J57*'Fin Assumptions'!$B$22,0) -> 154009.89 | K58: =IF(K60>=0,K57*'Fin Assumptions'!$B$22,0) -> 155499.8 | ... M58: =IF(M60>=0,M57*'Fin Assumptions'!$B$22,0) -> 157034.21
B60: Cumulative taxable income | D60: =SUM($D$57:D57) -> 986838.49 | E60: =SUM($D$57:E57) -> 2224880.9 | F60: =SUM($D$57:F57) -> 3993234.5 | G60: =SUM($D$57:G57) -> 6216058.7 | H60: =SUM($D$57:H57) -> 8928675.6 | I60: =SUM($D$57:I57) -> 12047357 | J60: =SUM($D$57:J57) -> 15127555 | K60: =SUM($D$57:K57) -> 18237551 | L60: =SUM($D$57:L57) -> 21367345
B62: Cash flow statement
B63: Year | C63: 0 | D63: 1 | E63: 2 | F63: 3 | G63: 4 | H63: 5 | I63: 6 | J63: 7 | K63: 8 | L63: 9
B64: Sources
B65: Cash from Operations
B66: PAT | D66: =D48 -> 1363258.9 | E66: =E48 -> 1468317.8 | F66: =F48 -> 1858516.4 | G66: =G48 -> 2193658.4 | H66: =H48 -> 2576802 | I66: =I48 -> 2892685.4 | J66: =J48 -> 2796688.3 | K66: =K48 -> 2774436.1 | L66: =L48 -> 2750230.8
B67: Add Depreciation | D67: =D45 -> 471469.83 | E67: =E45 -> 471469.83 | F67: =F45 -> 471469.83 | G67: =G45 -> 471469.83 | H67: =H45 -> 471469.83 | I67: =I45 -> 471469.83 | J67: =J45 -> 471469.83 | K67: =K45 -> 471469.83 | L67: =L45 -> 471469.83
B68: Net Cash from Operations | D68: =SUM(D66:D67) -> 1834728.7 | E68: =SUM(E66:E67) -> 1939787.7 | F68: =SUM(F66:F67) -> 2329986.2 | G68: =SUM(G66:G67) -> 2665128.2 | H68: =SUM(H66:H67) -> 3048271.8 | I68: =SUM(I66:I67) -> 3364155.2 | J68: =SUM(J66:J67) -> 3268158.1 | K68: =SUM(K66:K67) -> 3245905.9 | L68: =SUM(L66:L67) -> 3221700.6
B70: Cash From Financing
B71: Promoters Contribution | C71: =+'Fin Assumptions'!B34 -> 2387743.1
B72: Grant | C72: =+'Fin Assumptions'!B35 -> 0
B73: Term Loan | C73: =+'Fin Assumptions'!B36 -> 5571400.6
B74: Increase in Working Capital Borrowing
B75: Total Cash inflow | C75: =SUM(C71:C74) -> 7959143.7 | D75: =D68+SUM(D71:D74) -> 1834728.7 | E75: =E68+SUM(E71:E74) -> 1939787.7 | F75: =F68+SUM(F71:F74) -> 2329986.2 | G75: =G68+SUM(G71:G74) -> 2665128.2 | H75: =H68+SUM(H71:H74) -> 3048271.8 | I75: =I68+SUM(I71:I74) -> 3364155.2 | J75: =J68+SUM(J71:J74) -> 3268158.1 | K75: =K68+SUM(K71:K74) -> 3245905.9 | L75: =L68+SUM(L71:L74) -> 3221700.6
B77: Uses
B78: Capital expenditure | C78: =C75 -> 7959143.7 | D78: 0 | E78: =D78*3 -> 0 | F78: =Dep.!E16 -> 0 | G78: =Dep.!F16 -> 0 | H78: =Dep.!G16 -> 0 | I78: =Dep.!H16 -> 0 | J78: =H78 -> 0
B79: Increase in Working capital | D79: =Debt!D68-Debt!C68 -> 104180.34 | E79: =Debt!E68-Debt!D68 -> 129324.28 | F79: =Debt!F68-Debt!E68 -> 25203.694 | G79: =Debt!G68-Debt!F68 -> 25046.084 | H79: =Debt!H68-Debt!G68 -> 23519.177 | I79: =Debt!I68-Debt!H68 -> 19665.278 | J79: =Debt!J68-Debt!I68 -> 0 | K79: =Debt!K68-Debt!J68 -> 0 | L79: =Debt!L68-Debt!K68 -> 0
B80: Repayment of principal | E80: =Debt!E50 -> 0 | F80: =Debt!F50 -> 696425.07 | G80: =Debt!G50 -> 696425.07 | H80: =Debt!H50 -> 696425.07 | I80: =Debt!I50 -> 696425.07 | J80: =Debt!J50 -> 696425.07 | K80: =Debt!K50 -> 696425.07 | L80: =Debt!L50 -> 696425.07
B81: Total Uses | C81: =SUM(C78:C80) -> 7959143.7 | D81: =SUM(D78:D80) -> 104180.34 | E81: =SUM(E78:E80) -> 129324.28 | F81: =SUM(F78:F80) -> 721628.76 | G81: =SUM(G78:G80) -> 721471.15 | H81: =SUM(H78:H80) -> 719944.25 | I81: =SUM(I78:I80) -> 716090.35 | J81: =SUM(J78:J80) -> 696425.07 | ... L81: =SUM(L78:L80) -> 696425.07
B83: Opening Cash Balance | D83: =C85 -> 0 | E83: =D85 -> 1730548.4 | F83: =E85 -> 3541011.8 | G83: =F85 -> 5149369.2 | H83: =G85 -> 7093026.3 | I83: =H85 -> 9421353.9 | J83: =I85 -> 12069419 | K83: =J85 -> 14641152 | L83: =K85 -> 17190633
B84: Surplus/ Deficit | C84: =C75-C81 -> 0 | D84: =D75-D81 -> 1730548.4 | E84: =E75-E81 -> 1810463.4 | F84: =F75-F81 -> 1608357.4 | G84: =G75-G81 -> 1943657.1 | H84: =H75-H81 -> 2328327.6 | I84: =I75-I81 -> 2648064.9 | J84: =J75-J81 -> 2571733 | ... L84: =L75-L81 -> 2525275.5
B85: Closing Cash Balance | C85: 0 | D85: =D83+D84 -> 1730548.4 | E85: =E83+E84 -> 3541011.8 | F85: =F83+F84 -> 5149369.2 | G85: =G83+G84 -> 7093026.3 | H85: =H83+H84 -> 9421353.9 | I85: =I83+I84 -> 12069419 | J85: =J83+J84 -> 14641152 | K85: =K83+K84 -> 17190633 | L85: =L83+L84 -> 19715908
B89: Balance Sheet | D89: =D3 -> Year 1 | E89: =E3 -> Year 2 | F89: =F3 -> Year 3 | G89: =G3 -> Year 4 | H89: =H3 -> Year 5 | I89: =I3 -> Year 6 | J89: =J3 -> Year 7 | K89: =K3 -> Year 8 | L89: =L3 -> Year 9 | M89: 2025-26
B90: Liabitilies
B91: Equity Capital | D91: =C71 -> 2387743.1 | E91: =D91 -> 2387743.1 | F91: =E91 -> 2387743.1 | G91: =F91 -> 2387743.1 | H91: =G91 -> 2387743.1 | I91: =H91 -> 2387743.1 | J91: =I91 -> 2387743.1 | K91: =J91 -> 2387743.1 | L91: =K91 -> 2387743.1 | M91: =L91 -> 2387743.1
B92: Reserve & Surplus | D92: =D48 -> 1363258.9 | E92: =D92+E48 -> 2831576.7 | F92: =E92+F48 -> 4690093.1 | G92: =F92+G48 -> 6883751.5 | H92: =G92+H48 -> 9460553.5 | I92: =H92+I48 -> 12353239 | J92: =I92+J48 -> 15149927 | K92: =J92+K48 -> 17924363 | L92: =K92+L48 -> 20674594 | M92: =SUM($C$48:M48)+$C$92 -> 23398575
B93: Grant/ Subsidy | D93: =C72 -> 0 | E93: =D93+E72 -> 0 | F93: =E93 -> 0 | G93: =F93 -> 0 | H93: =G93 -> 0 | I93: =H93 -> 0 | J93: =I93 -> 0 | K93: =J93 -> 0 | L93: =K93 -> 0 | M93: =L93 -> 0
B94: Term Loan | D94: =C73 -> 5571400.6 | E94: =C73+E73-E80 -> 5571400.6 | F94: =E94-F80 -> 4874975.5 | G94: =F94-G80 -> 4178550.4 | H94: =G94-H80 -> 3482125.4 | I94: =H94-I80 -> 2785700.3 | J94: =I94-J80 -> 2089275.2 | K94: =J94-K80 -> 1392850.1 | L94: =K94-L80 -> 696425.07 | M94: =L94-M80 -> 696425.07
B95: Total Liabilities | D95: =SUM(D91:D94) -> 9322402.6 | E95: =SUM(E91:E94) -> 10790720 | F95: =SUM(F91:F94) -> 11952812 | G95: =SUM(G91:G94) -> 13450045 | H95: =SUM(H91:H94) -> 15330422 | I95: =SUM(I91:I94) -> 17526682 | J95: =SUM(J91:J94) -> 19626945 | K95: =SUM(K91:K94) -> 21704957 | ... M95: =SUM(M91:M94) -> 26482743
B97: Assets
B98: Gross Fixed Assets | D98: =C75 -> 7959143.7 | E98: =D98+SUM(E78) -> 7959143.7 | F98: =E98 -> 7959143.7 | G98: =F98+F78 -> 7959143.7 | H98: =G98+G78 -> 7959143.7 | I98: =H98+H78 -> 7959143.7 | J98: =I98+I78 -> 7959143.7 | K98: =J98+J78 -> 7959143.7 | L98: =K98+K78 -> 7959143.7 | M98: =L98+L78 -> 7959143.7 | O98: =M98+M99+M100+M101 -> 16245226
B99: Less Accumulated Dep. | D99: =D45 -> 471469.83 | E99: =D99+E45 -> 942939.66 | F99: =E99+F45 -> 1414409.5 | G99: =F99+G45 -> 1885879.3 | H99: =G99+H45 -> 2357349.1 | I99: =H99+I45 -> 2828819 | J99: =I99+J45 -> 3300288.8 | K99: =J99+K45 -> 3771758.6 | L99: =K99+L45 -> 4243228.5 | M99: =L99+M45 -> 4714698.3
B100: Net Fixed Assets | D100: =D98-D99 -> 7487673.8 | E100: =E98-E99 -> 7016204 | F100: =F98-F99 -> 6544734.2 | G100: =G98-G99 -> 6073264.3 | H100: =H98-H99 -> 5601794.5 | I100: =I98-I99 -> 5130324.7 | J100: =J98-J99 -> 4658854.9 | K100: =K98-K99 -> 4187385 | ... M100: =M98-M99 -> 3244445.4
B101: Working Capital | D101: =C101+D79 -> 104180.34 | E101: =D101+E79 -> 233504.62 | F101: =E101+F79 -> 258708.31 | G101: =F101+G79 -> 283754.4 | H101: =G101+H79 -> 307273.57 | I101: =H101+I79 -> 326938.85 | J101: =I101+J79 -> 326938.85 | K101: =J101+K79 -> 326938.85 | ... M101: =L101+M79 -> 326938.85
B102: Cash Bal | D102: =D85 -> 1730548.4 | E102: =E85 -> 3541011.8 | F102: =F85 -> 5149369.2 | G102: =G85 -> 7093026.3 | H102: =H85 -> 9421353.9 | I102: =I85 -> 12069419 | J102: =J85 -> 14641152 | K102: =K85 -> 17190633 | ... M102: =M85 -> 0
B103: Total Assets | D103: =D100+D101+D102 -> 9322402.6 | E103: =E100+E101+E102 -> 10790720 | F103: =F100+F101+F102 -> 11952812 | G103: =G100+G101+G102 -> 13450045 | H103: =H100+H101+H102 -> 15330422 | I103: =I100+I101+I102 -> 17526682 | J103: =J100+J101+J102 -> 19626945 | K103: =K100+K101+K102 -> 21704957 | ... M103: =M100+M101+M102 -> 3571384.2
D104: =D95-D103 -> 0 | E104: =E95-E103 -> 0 | F104: =F95-F103 -> 0 | G104: =G95-G103 -> 0 | H104: =H95-H103 -> 0 | I104: =I95-I103 -> 0 | J104: =J95-J103 -> 0 | K104: =K95-K103 -> 0 | ... M104: =M95-M103 -> 22911359
B107: Financial Performance Indicators
B108: Year | D108: 1 | E108: 2 | F108: 3 | G108: 4 | H108: 5 | I108: 6 | J108: 7 | K108: 8 | L108: 9
B109: EBITDA Margin | D109: =D42/D16 -> 0.5941503 | E109: =E42/E16 -> 0.56110959 | F109: =F42/F16 -> 0.59308629 | G109: =G42/G16 -> 0.60309174 | H109: =H42/H16 -> 0.62348428 | I109: =I42/I16 -> 0.63632922 | J109: =J42/J16 -> 0.61258933 | K109: =K42/K16 -> 0.60196082 | L109: =L42/L16 -> 0.59091543
B110: PAT margin | D110: =D48/D16 -> 0.36348801 | E110: =E48/E16 -> 0.34934304 | F110: =F48/F16 -> 0.39910163 | G110: =G48/G16 -> 0.42949083 | H110: =H48/H16 -> 0.46588994 | I110: =I48/I16 -> 0.49154373 | J110: =J48/J16 -> 0.47523128 | K110: =K48/K16 -> 0.47145005 | L110: =L48/L16 -> 0.46733693
B111: Debt-Equity Ratio | D111: =D94/D91 -> 2.3333333 | E111: =E94/E91 -> 2.3333333 | F111: =F94/F91 -> 2.0416667 | G111: =G94/G91 -> 1.75 | H111: =H94/H91 -> 1.4583333 | I111: =I94/I91 -> 1.1666667 | J111: =K94/J91 -> 0.58333333 | K111: =L94/K91 -> 0.29166667 | L111: =M94/L91 -> 0.29166667
B112: Debt to EBITDA ratio | D112: =D94/D42 -> 2.5002291 | E112: =E94/E42 -> 2.3623743 | F112: =F94/F42 -> 1.7651095 | G112: =G94/G42 -> 1.356523 | H112: =H94/H42 -> 1.009767 | I112: =I94/I42 -> 0.74389816 | J112: =J94/J42 -> 0.57954502 | K112: =K94/K42 -> 0.39318517 | L112: =L94/L42 -> 0.20026729
B113: Interest Coverage Ratio | D113: =D42/(D43+D44) -> 6.4724103 | E113: =E42/(E43+E44) -> 6.6116824 | F113: =F42/(F43+F44) -> 8.0414925 | G113: =G42/(G43+G44) -> 10.130381 | H113: =H42/(H43+H44) -> 13.035541 | I113: =I42/(I43+I44) -> 16.669628 | J113: =J42/(J43+J44) -> 19.714834 | K113: =K42/(K43+K44) -> 25.110949 | L113: =L42/(L43+L44) -> 35.024301
B114: DSCR | D114: =+D136 -> 6.4724103 | E114: =E136 -> 6.6116824 | F114: =F136 -> 2.655947 | G114: =G136 -> 3.0788165 | H114: =H136 -> 3.5885157 | I114: =I136 -> 4.0656376 | J114: =J136 -> 4.0999586 | K114: =K136 -> 0 | L114: =L136 -> 0
B115: Average DSCR | D115: =D137 -> 3.8115129
B117: Calculation -Interest Coverage Ratio
B118: EBITDA | D118: =D42 -> 2228356 | E118: =E42 -> 2358390.3 | F118: =F42 -> 2761854.4 | G118: =G42 -> 3080338.8 | H118: =H42 -> 3448444.4 | I118: =I42 -> 3744733.4 | J118: =J42 -> 3605026.6 | K118: =K42 -> 3542478.8 | L118: =L42 -> 3477477.9
B119: Interest
B120: Long term Debt (LTD) | D120: =D43 -> 334284.03 | E120: =E43 -> 334284.03 | F120: =F43 -> 318614.47 | G120: =G43 -> 276828.97 | H120: =H43 -> 235043.46 | I120: =I43 -> 193257.96 | J120: =J43 -> 151472.45 | K120: =K43 -> 109686.95 | L120: =L43 -> 67901.444
B121: Working Capital Borrowing | D121: =D44 -> 10001.312 | E121: =E44 -> 22416.443 | F121: =F44 -> 24835.998 | G121: =G44 -> 27240.422 | H121: =H44 -> 29498.263 | I121: =I44 -> 31386.13 | J121: =J44 -> 31386.13 | K121: =K44 -> 31386.13 | L121: =L44 -> 31386.13
B122: Total interest paid | D122: =SUM(D120:D121) -> 344285.35 | E122: =SUM(E120:E121) -> 356700.48 | F122: =SUM(F120:F121) -> 343450.47 | G122: =SUM(G120:G121) -> 304069.39 | H122: =SUM(H120:H121) -> 264541.72 | I122: =SUM(I120:I121) -> 224644.09 | J122: =SUM(J120:J121) -> 182858.58 | K122: =SUM(K120:K121) -> 141073.08 | L122: =SUM(L120:L121) -> 99287.574
B124: Interest Coverage Ratio | D124: =D118/D122 -> 6.4724103 | E124: =E118/E122 -> 6.6116824 | F124: =F118/F122 -> 8.0414925 | G124: =G118/G122 -> 10.130381 | H124: =H118/H122 -> 13.035541 | I124: =I118/I122 -> 16.669628 | J124: =J118/J122 -> 19.714834 | K124: =K118/K122 -> 25.110949 | L124: =L118/L122 -> 35.024301
...

Sheet Debt
J1: EMI (Quarterly) | K1: =-PMT('Fin Assumptions'!B8/4,'Fin Assumptions'!B6,'Fin Assumptions'!B36,0,0) -> 220499.86
C2: Reducing Bal method | J2: EQI Method
C3: Quarter | D3: Opening Bal | E3: Interest | F3: principal | G3: Closing bal | J3: Opening Bal | K3: Interest | L3: principal | M3: Closing bal
C4: 1 | D4: ='Fin Assumptions'!B36 -> 5571400.6 | E4: =D4*'Fin Assumptions'!$B$8/4 -> 83571.008 | F4: =IF(AND(C4>'Fin Assumptions'!$B$4,C4<=('Fin Assumptions'!$B$4+'Fin Assumptions'!$B$6)),'Fin Assumptions'!$B$10,0) -> 0 | G4: =D4-F4 -> 5571400.6 | J4: =$D$4 -> 5571400.6 | K4: =J4*'Fin Assumptions'!$B$8/4 -> 83571.008 | L4: =IF(AND(C4>'Fin Assumptions'!$B$4,C4<=('Fin Assumptions'!$B$4+'Fin Assumptions'!$B$6)),(Debt!$K$1-Debt!K4),0) -> 0 | M4: =J4-L4 -> 5571400.6
C5: 2 | D5: =G4 -> 5571400.6 | E5: =D5*'Fin Assumptions'!$B$8/4 -> 83571.008 | F5: =IF(AND(C5>'Fin Assumptions'!$B$4,C5<=('Fin Assumptions'!$B$4+'Fin Assumptions'!$B$6)),'Fin Assumptions'!$B$10,0) -> 0 | G5: =D5-F5 -> 5571400.6 | J5: =M4 -> 5571400.6 | K5: =J5*'Fin Assumptions'!$B$8/4 -> 83571.008 | L5: =IF(AND(C5>'Fin Assumptions'!$B$4,C5<=('Fin Assumptions'!$B$4+'Fin Assumptions'!$B$6)),(Debt!$K$1-Debt!K5),0) -> 0 | M5: =J5-L5 -> 5571400.6
C6: 3 | D6: =G5 -> 5571400.6 | E6: =D6*'Fin Assumptions'!$B$8/4 -> 83571.008 | F6: =IF(AND(C6>'Fin Assumptions'!$B$4,C6<=('Fin Assumptions'!$B$4+'Fin Assumptions'!$B$6)),'Fin Assumptions'!$B$10,0) -> 0 | G6: =D6-F6 -> 5571400.6 | J6: =M5 -> 5571400.6 | K6: =J6*'Fin Assumptions'!$B$8/4 -> 83571.008 | L6: =IF(AND(C6>'Fin Assumptions'!$B$4,C6<=('Fin Assumptions'!$B$4+'Fin Assumptions'!$B$6)),(Debt!$K$1-Debt!K6),0) -> 0 | M6: =J6-L6 -> 5571400.6
C7: 4 | D7: =G6 -> 5571400.6 | E7: =D7*'Fin Assumptions'!$B$8/4 -> 83571.008 | F7: =IF(AND(C7>'Fin Assumptions'!$B$4,C7<=('Fin Assumptions'!$B$4+'Fin Assumptions'!$B$6)),'Fin Assumptions'!$B$10,0) -> 0 | G7: =D7-F7 -> 5571400.6 | J7: =M6 -> 5571400.6 | K7: =J7*'Fin Assumptions'!$B$8/4 -> 83571.008 | L7: =IF(AND(C7>'Fin Assumptions'!$B$4,C7<=('Fin Assumptions'!$B$4+'Fin Assumptions'!$B$6)),(Debt!$K$1-Debt!K7),0) -> 0 | M7: =J7-L7 -> 5571400.6 | O7: EMI (Quarterly) | P7: Int | Q7: Principal
C8: 5 | D8: =G7 -> 5571400.6 | E8: =D8*'Fin Assumptions'!$B$8/4 -> 83571.008 | F8: =IF(AND(C8>'Fin Assumptions'!$B$4,C8<=('Fin Assumptions'!$B$4+'Fin Assumptions'!$B$6)),'Fin Assumptions'!$B$10,0) -> 0 | G8: =D8-F8 -> 5571400.6 | J8: =M7 -> 5571400.6 | K8: =J8*'Fin Assumptions'!$B$8/4 -> 83571.008 | L8: =IF(AND(C8>'Fin Assumptions'!$B$4,C8<=('Fin Assumptions'!$B$4+'Fin Assumptions'!$B$6)),(Debt!$K$1-Debt!K8),0) -> 0 | M8: =J8-L8 -> 5571400.6
C9: 6 | D9: =G8 -> 5571400.6 | E9: =D9*'Fin Assumptions'!$B$8/4 -> 83571.008 | F9: =IF(AND(C9>'Fin Assumptions'!$B$4,C9<=('Fin Assumptions'!$B$4+'Fin Assumptions'!$B$6)),'Fin Assumptions'!$B$10,0) -> 0 | G9: =D9-F9 -> 5571400.6 | J9: =M8 -> 5571400.6 | K9: =J9*'Fin Assumptions'!$B$8/4 -> 83571.008 | L9: =IF(AND(C9>'Fin Assumptions'!$B$4,C9<=('Fin Assumptions'!$B$4+'Fin Assumptions'!$B$6)),(Debt!$K$1-Debt!K9),0) -> 0 | M9: =J9-L9 -> 5571400.6
C10: 7 | D10: =G9 -> 5571400.6 | E10: =D10*'Fin Assumptions'!$B$8/4 -> 83571.008 | F10: =IF(AND(C10>'Fin Assumptions'!$B$4,C10<=('Fin Assumptions'!$B$4+'Fin Assumptions'!$B$6)),'Fin Assumptions'!$B$10,0) -> 0 | G10: =D10-F10 -> 5571400.6 | J10: =M9 -> 5571400.6 | K10: =J10*'Fin Assumptions'!$B$8/4 -> 83571.008 | L10: =IF(AND(C10>'Fin Assumptions'!$B$4,C10<=('Fin Assumptions'!$B$4+'Fin Assumptions'!$B$6)),(Debt!$K$1-Debt!K10),0) -> 0 | M10: =J10-L10 -> 5571400.6
C11: 8 | D11: =G10 -> 5571400.6 | E11: =D11*'Fin Assumptions'!$B$8/4 -> 83571.008 | F11: =IF(AND(C11>'Fin Assumptions'!$B$4,C11<=('Fin Assumptions'!$B$4+'Fin Assumptions'!$B$6)),'Fin Assumptions'!$B$10,0) -> 0 | G11: =D11-F11 -> 5571400.6 | J11: =M10 -> 5571400.6 | K11: =J11*'Fin Assumptions'!$B$8/4 -> 83571.008 | L11: =IF(AND(C11>'Fin Assumptions'!$B$4,C11<=('Fin Assumptions'!$B$4+'Fin Assumptions'!$B$6)),(Debt!$K$1-Debt!K11),0) -> 0 | M11: =J11-L11 -> 5571400.6
C12: 9 | D12: =G11 -> 5571400.6 | E12: =D12*'Fin Assumptions'!$B$8/4 -> 83571.008 | F12: =IF(AND(C12>'Fin Assumptions'!$B$4,C12<=('Fin Assumptions'!$B$4+'Fin Assumptions'!$B$6)),'Fin Assumptions'!$B$10,0) -> 174106.27 | G12: =D12-F12 -> 5397294.3 | J12: =M11 -> 5571400.6 | K12: =J12*'Fin Assumptions'!$B$8/4 -> 83571.008 | L12: =IF(AND(C12>'Fin Assumptions'!$B$4,C12<=('Fin Assumptions'!$B$4+'Fin Assumptions'!$B$6)),(Debt!$K$1-Debt!K12),0) -> 136928.85 | M12: =J12-L12 -> 5434471.7 | N12: 1 | O12: =-PMT(12%/4,20,$D$4,0,0) -> 374485.63 | P12: =-IPMT(12%/4,N12,20,$D$4,0) -> 167142.02 | Q12: =-PPMT(12%/4,N12,20,$D$4,0) -> 207343.61
C13: 10 | D13: =G12 -> 5397294.3 | E13: =D13*'Fin Assumptions'!$B$8/4 -> 80959.414 | F13: =IF(AND(C13>'Fin Assumptions'!$B$4,C13<=('Fin Assumptions'!$B$4+'Fin Assumptions'!$B$6)),'Fin Assumptions'!$B$10,0) -> 174106.27 | G13: =D13-F13 -> 5223188 | J13: =M12 -> 5434471.7 | K13: =J13*'Fin Assumptions'!$B$8/4 -> 81517.076 | L13: =IF(AND(C13>'Fin Assumptions'!$B$4,C13<=('Fin Assumptions'!$B$4+'Fin Assumptions'!$B$6)),(Debt!$K$1-Debt!K13),0) -> 138982.78 | M13: =J13-L13 -> 5295488.9 | N13: 2 | O13: =-PMT(12%/4,20,$D$4,0,0) -> 374485.63 | P13: =-IPMT(12%/4,N13,20,$D$4,0) -> 160921.71 | Q13: =-PPMT(12%/4,N13,20,$D$4,0) -> 213563.92
C14: 11 | D14: =G13 -> 5223188 | E14: =D14*'Fin Assumptions'!$B$8/4 -> 78347.82 | F14: =IF(AND(C14>'Fin Assumptions'!$B$4,C14<=('Fin Assumptions'!$B$4+'Fin Assumptions'!$B$6)),'Fin Assumptions'!$B$10,0) -> 174106.27 | G14: =D14-F14 -> 5049081.8 | J14: =M13 -> 5295488.9 | K14: =J14*'Fin Assumptions'!$B$8/4 -> 79432.334 | L14: =IF(AND(C14>'Fin Assumptions'!$B$4,C14<=('Fin Assumptions'!$B$4+'Fin Assumptions'!$B$6)),(Debt!$K$1-Debt!K14),0) -> 141067.53 | M14: =J14-L14 -> 5154421.4 | N14: 3 | O14: =-PMT(12%/4,20,$D$4,0,0) -> 374485.63 | P14: =-IPMT(12%/4,N14,20,$D$4,0) -> 154514.79 | Q14: =-PPMT(12%/4,N14,20,$D$4,0) -> 219970.84
C15: 12 | D15: =G14 -> 5049081.8 | E15: =D15*'Fin Assumptions'!$B$8/4 -> 75736.226 | F15: =IF(AND(C15>'Fin Assumptions'!$B$4,C15<=('Fin Assumptions'!$B$4+'Fin Assumptions'!$B$6)),'Fin Assumptions'!$B$10,0) -> 174106.27 | G15: =D15-F15 -> 4874975.5 | J15: =M14 -> 5154421.4 | K15: =J15*'Fin Assumptions'!$B$8/4 -> 77316.321 | L15: =IF(AND(C15>'Fin Assumptions'!$B$4,C15<=('Fin Assumptions'!$B$4+'Fin Assumptions'!$B$6)),(Debt!$K$1-Debt!K15),0) -> 143183.54 | M15: =J15-L15 -> 5011237.9 | N15: 4 | O15: =-PMT(12%/4,20,$D$4,0,0) -> 374485.63 | P15: =-IPMT(12%/4,N15,20,$D$4,0) -> 147915.67 | Q15: =-PPMT(12%/4,N15,20,$D$4,0) -> 226569.97
C16: 13 | D16: =G15 -> 4874975.5 | E16: =D16*'Fin Assumptions'!$B$8/4 -> 73124.632 | F16: =IF(AND(C16>'Fin Assumptions'!$B$4,C16<=('Fin Assumptions'!$B$4+'Fin Assumptions'!$B$6)),'Fin Assumptions'!$B$10,0) -> 174106.27 | G16: =D16-F16 -> 4700869.2 | J16: =M15 -> 5011237.9 | K16: =J16*'Fin Assumptions'!$B$8/4 -> 75168.568 | L16: =IF(AND(C16>'Fin Assumptions'!$B$4,C16<=('Fin Assumptions'!$B$4+'Fin Assumptions'!$B$6)),(Debt!$K$1-Debt!K16),0) -> 145331.29 | M16: =J16-L16 -> 4865906.6 | N16: 5 | O16: =-PMT(12%/4,20,$D$4,0,0) -> 374485.63 | P16: =-IPMT(12%/4,N16,20,$D$4,0) -> 141118.57 | Q16: =-PPMT(12%/4,N16,20,$D$4,0) -> 233367.06
C17: 14 | D17: =G16 -> 4700869.2 | E17: =D17*'Fin Assumptions'!$B$8/4 -> 70513.038 | F17: =IF(AND(C17>'Fin Assumptions'!$B$4,C17<=('Fin Assumptions'!$B$4+'Fin Assumptions'!$B$6)),'Fin Assumptions'!$B$10,0) -> 174106.27 | G17: =D17-F17 -> 4526763 | J17: =M16 -> 4865906.6 | K17: =J17*'Fin Assumptions'!$B$8/4 -> 72988.599 | L17: =IF(AND(C17>'Fin Assumptions'!$B$4,C17<=('Fin Assumptions'!$B$4+'Fin Assumptions'!$B$6)),(Debt!$K$1-Debt!K17),0) -> 147511.26 | M17: =J17-L17 -> 4718395.3 | N17: 6 | O17: =-PMT(12%/4,20,$D$4,0,0) -> 374485.63 | P17: =-IPMT(12%/4,N17,20,$D$4,0) -> 134117.55 | Q17: =-PPMT(12%/4,N17,20,$D$4,0) -> 240368.08
C18: 15 | D18: =G17 -> 4526763 | E18: =D18*'Fin Assumptions'!$B$8/4 -> 67901.444 | F18: =IF(AND(C18>'Fin Assumptions'!$B$4,C18<=('Fin Assumptions'!$B$4+'Fin Assumptions'!$B$6)),'Fin Assumptions'!$B$10,0) -> 174106.27 | G18: =D18-F18 -> 4352656.7 | J18: =M17 -> 4718395.3 | K18: =J18*'Fin Assumptions'!$B$8/4 -> 70775.93 | L18: =IF(AND(C18>'Fin Assumptions'!$B$4,C18<=('Fin Assumptions'!$B$4+'Fin Assumptions'!$B$6)),(Debt!$K$1-Debt!K18),0) -> 149723.93 | M18: =J18-L18 -> 4568671.4 | N18: 7 | O18: =-PMT(12%/4,20,$D$4,0,0) -> 374485.63 | P18: =-IPMT(12%/4,N18,20,$D$4,0) -> 126906.51 | Q18: =-PPMT(12%/4,N18,20,$D$4,0) -> 247579.12
C19: 16 | D19: =G18 -> 4352656.7 | E19: =D19*'Fin Assumptions'!$B$8/4 -> 65289.85 | F19: =IF(AND(C19>'Fin Assumptions'!$B$4,C19<=('Fin Assumptions'!$B$4+'Fin Assumptions'!$B$6)),'Fin Assumptions'!$B$10,0) -> 174106.27 | G19: =D19-F19 -> 4178550.4 | J19: =M18 -> 4568671.4 | K19: =J19*'Fin Assumptions'!$B$8/4 -> 68530.071 | L19: =IF(AND(C19>'Fin Assumptions'!$B$4,C19<=('Fin Assumptions'!$B$4+'Fin Assumptions'!$B$6)),(Debt!$K$1-Debt!K19),0) -> 151969.79 | M19: =J19-L19 -> 4416701.6 | N19: 8 | O19: =-PMT(12%/4,20,$D$4,0,0) -> 374485.63 | P19: =-IPMT(12%/4,N19,20,$D$4,0) -> 119479.14 | Q19: =-PPMT(12%/4,N19,20,$D$4,0) -> 255006.49
C20: 17 | D20: =G19 -> 4178550.4 | E20: =D20*'Fin Assumptions'!$B$8/4 -> 62678.256 | F20: =IF(AND(C20>'Fin Assumptions'!$B$4,C20<=('Fin Assumptions'!$B$4+'Fin Assumptions'!$B$6)),'Fin Assumptions'!$B$10,0) -> 174106.27 | G20: =D20-F20 -> 4004444.2 | J20: =M19 -> 4416701.6 | K20: =J20*'Fin Assumptions'!$B$8/4 -> 66250.524 | L20: =IF(AND(C20>'Fin Assumptions'!$B$4,C20<=('Fin Assumptions'!$B$4+'Fin Assumptions'!$B$6)),(Debt!$K$1-Debt!K20),0) -> 154249.34 | M20: =J20-L20 -> 4262452.2 | N20: 9 | O20: =-PMT(12%/4,20,$D$4,0,0) -> 374485.63 | P20: =-IPMT(12%/4,N20,20,$D$4,0) -> 111828.94 | Q20: =-PPMT(12%/4,N20,20,$D$4,0) -> 262656.69
C21: 18 | D21: =G20 -> 4004444.2 | E21: =D21*'Fin Assumptions'!$B$8/4 -> 60066.662 | F21: =IF(AND(C21>'Fin Assumptions'!$B$4,C21<=('Fin Assumptions'!$B$4+'Fin Assumptions'!$B$6)),'Fin Assumptions'!$B$10,0) -> 174106.27 | G21: =D21-F21 -> 3830337.9 | J21: =M20 -> 4262452.2 | K21: =J21*'Fin Assumptions'!$B$8/4 -> 63936.784 | L21: =IF(AND(C21>'Fin Assumptions'!$B$4,C21<=('Fin Assumptions'!$B$4+'Fin Assumptions'!$B$6)),(Debt!$K$1-Debt!K21),0) -> 156563.08 | M21: =J21-L21 -> 4105889.2 | N21: 10 | O21: =-PMT(12%/4,20,$D$4,0,0) -> 374485.63 | P21: =-IPMT(12%/4,N21,20,$D$4,0) -> 103949.24 | Q21: =-PPMT(12%/4,N21,20,$D$4,0) -> 270536.39
C22: 19 | D22: =G21 -> 3830337.9 | E22: =D22*'Fin Assumptions'!$B$8/4 -> 57455.068 | F22: =IF(AND(C22>'Fin Assumptions'!$B$4,C22<=('Fin Assumptions'!$B$4+'Fin Assumptions'!$B$6)),'Fin Assumptions'!$B$10,0) -> 174106.27 | G22: =D22-F22 -> 3656231.6 | J22: =M21 -> 4105889.2 | K22: =J22*'Fin Assumptions'!$B$8/4 -> 61588.338 | L22: =IF(AND(C22>'Fin Assumptions'!$B$4,C22<=('Fin Assumptions'!$B$4+'Fin Assumptions'!$B$6)),(Debt!$K$1-Debt!K22),0) -> 158911.52 | M22: =J22-L22 -> 3946977.6 | N22: 11 | O22: =-PMT(12%/4,20,$D$4,0,0) -> 374485.63 | P22: =-IPMT(12%/4,N22,20,$D$4,0) -> 95833.152 | Q22: =-PPMT(12%/4,N22,20,$D$4,0) -> 278652.48
C23: 20 | D23: =G22 -> 3656231.6 | E23: =D23*'Fin Assumptions'!$B$8/4 -> 54843.474 | F23: =IF(AND(C23>'Fin Assumptions'!$B$4,C23<=('Fin Assumptions'!$B$4+'Fin Assumptions'!$B$6)),'Fin Assumptions'!$B$10,0) -> 174106.27 | G23: =D23-F23 -> 3482125.4 | J23: =M22 -> 3946977.6 | K23: =J23*'Fin Assumptions'!$B$8/4 -> 59204.665 | L23: =IF(AND(C23>'Fin Assumptions'!$B$4,C23<=('Fin Assumptions'!$B$4+'Fin Assumptions'!$B$6)),(Debt!$K$1-Debt!K23),0) -> 161295.2 | M23: =J23-L23 -> 3785682.5 | N23: 12 | O23: =-PMT(12%/4,20,$D$4,0,0) -> 374485.63 | P23: =-IPMT(12%/4,N23,20,$D$4,0) -> 87473.577 | Q23: =-PPMT(12%/4,N23,20,$D$4,0) -> 287012.05
... C31: 28 | D31: =G30 -> 2263381.5 | E31: =D31*'Fin Assumptions'!$B$8/4 -> 33950.722 | F31: =IF(AND(C31>'Fin Assumptions'!$B$4,C31<=('Fin Assumptions'!$B$4+'Fin Assumptions'!$B$6)),'Fin Assumptions'!$B$10,0) -> 174106.27 | G31: =D31-F31 -> 2089275.2 | J31: =M30 -> 2586801.2 | K31: =J31*'Fin Assumptions'!$B$8/4 -> 38802.018 | L31: =IF(AND(C31>'Fin Assumptions'!$B$4,C31<=('Fin Assumptions'!$B$4+'Fin Assumptions'!$B$6)),(Debt!$K$1-Debt!K31),0) -> 181697.84 | M31: =J31-L31 -> 2405103.4 | N31: 20 | O31: =-PMT(12%/4,20,$D$4,0,0) -> 374485.63 | P31: =-IPMT(12%/4,N31,20,$D$4,0) -> 10907.348 | Q31: =-PPMT(12%/4,N31,20,$D$4,0) -> 363578.28
C32: 29 | D32: =G31 -> 2089275.2 | E32: =D32*'Fin Assumptions'!$B$8/4 -> 31339.128 | F32: =IF(AND(C32>'Fin Assumptions'!$B$4,C32<=('Fin Assumptions'!$B$4+'Fin Assumptions'!$B$6)),'Fin Assumptions'!$B$10,0) -> 174106.27 | G32: =D32-F32 -> 1915168.9 | J32: =M31 -> 2405103.4 | K32: =J32*'Fin Assumptions'!$B$8/4 -> 36076.551 | L32: =IF(AND(C32>'Fin Assumptions'!$B$4,C32<=('Fin Assumptions'!$B$4+'Fin Assumptions'!$B$6)),(Debt!$K$1-Debt!K32),0) -> 184423.31 | M32: =J32-L32 -> 2220680.1 | N32: 21
C33: 30 | D33: =G32 -> 1915168.9 | E33: =D33*'Fin Assumptions'!$B$8/4 -> 28727.534 | F33: =IF(AND(C33>'Fin Assumptions'!$B$4,C33<=('Fin Assumptions'!$B$4+'Fin Assumptions'!$B$6)),'Fin Assumptions'!$B$10,0) -> 174106.27 | G33: =D33-F33 -> 1741062.7 | J33: =M32 -> 2220680.1 | K33: =J33*'Fin Assumptions'!$B$8/4 -> 33310.201 | L33: =IF(AND(C33>'Fin Assumptions'!$B$4,C33<=('Fin Assumptions'!$B$4+'Fin Assumptions'!$B$6)),(Debt!$K$1-Debt!K33),0) -> 187189.66 | M33: =J33-L33 -> 2033490.4 | N33: 22
C34: 31 | D34: =G33 -> 1741062.7 | E34: =D34*'Fin Assumptions'!$B$8/4 -> 26115.94 | F34: =IF(AND(C34>'Fin Assumptions'!$B$4,C34<=('Fin Assumptions'!$B$4+'Fin Assumptions'!$B$6)),'Fin Assumptions'!$B$10,0) -> 174106.27 | G34: =D34-F34 -> 1566956.4 | J34: =M33 -> 2033490.4 | K34: =J34*'Fin Assumptions'!$B$8/4 -> 30502.356 | L34: =IF(AND(C34>'Fin Assumptions'!$B$4,C34<=('Fin Assumptions'!$B$4+'Fin Assumptions'!$B$6)),(Debt!$K$1-Debt!K34),0) -> 189997.5 | M34: =J34-L34 -> 1843492.9 | N34: 23
C35: 32 | D35: =G34 -> 1566956.4 | E35: =D35*'Fin Assumptions'!$B$8/4 -> 23504.346 | F35: =IF(AND(C35>'Fin Assumptions'!$B$4,C35<=('Fin Assumptions'!$B$4+'Fin Assumptions'!$B$6)),'Fin Assumptions'!$B$10,0) -> 174106.27 | G35: =D35-F35 -> 1392850.1 | J35: =M34 -> 1843492.9 | K35: =J35*'Fin Assumptions'!$B$8/4 -> 27652.394 | L35: =IF(AND(C35>'Fin Assumptions'!$B$4,C35<=('Fin Assumptions'!$B$4+'Fin Assumptions'!$B$6)),(Debt!$K$1-Debt!K35),0) -> 192847.47 | M35: =J35-L35 -> 1650645.4 | N35: 24
C36: 33 | D36: =G35 -> 1392850.1 | E36: =D36*'Fin Assumptions'!$B$8/4 -> 20892.752 | F36: =IF(AND(C36>'Fin Assumptions'!$B$4,C36<=('Fin Assumptions'!$B$4+'Fin Assumptions'!$B$6)),'Fin Assumptions'!$B$10,0) -> 174106.27 | G36: =D36-F36 -> 1218743.9 | J36: =M35 -> 1650645.4 | K36: =J36*'Fin Assumptions'!$B$8/4 -> 24759.682 | L36: =IF(AND(C36>'Fin Assumptions'!$B$4,C36<=('Fin Assumptions'!$B$4+'Fin Assumptions'!$B$6)),(Debt!$K$1-Debt!K36),0) -> 195740.18 | M36: =J36-L36 -> 1454905.3
C37: 34 | D37: =G36 -> 1218743.9 | E37: =D37*'Fin Assumptions'!$B$8/4 -> 18281.158 | F37: =IF(AND(C37>'Fin Assumptions'!$B$4,C37<=('Fin Assumptions'!$B$4+'Fin Assumptions'!$B$6)),'Fin Assumptions'!$B$10,0) -> 174106.27 | G37: =D37-F37 -> 1044637.6 | J37: =M36 -> 1454905.3 | K37: =J37*'Fin Assumptions'!$B$8/4 -> 21823.579 | L37: =IF(AND(C37>'Fin Assumptions'!$B$4,C37<=('Fin Assumptions'!$B$4+'Fin Assumptions'!$B$6)),(Debt!$K$1-Debt!K37),0) -> 198676.28 | M37: =J37-L37 -> 1256229
C38: 35 | D38: =G37 -> 1044637.6 | E38: =D38*'Fin Assumptions'!$B$8/4 -> 15669.564 | F38: =IF(AND(C38>'Fin Assumptions'!$B$4,C38<=('Fin Assumptions'!$B$4+'Fin Assumptions'!$B$6)),'Fin Assumptions'!$B$10,0) -> 174106.27 | G38: =D38-F38 -> 870531.34 | J38: =M37 -> 1256229 | K38: =J38*'Fin Assumptions'!$B$8/4 -> 18843.435 | L38: =IF(AND(C38>'Fin Assumptions'!$B$4,C38<=('Fin Assumptions'!$B$4+'Fin Assumptions'!$B$6)),(Debt!$K$1-Debt!K38),0) -> 201656.43 | M38: =J38-L38 -> 1054572.5
C39: 36 | D39: =G38 -> 870531.34 | E39: =D39*'Fin Assumptions'!$B$8/4 -> 13057.97 | F39: =IF(AND(C39>'Fin Assumptions'!$B$4,C39<=('Fin Assumptions'!$B$4+'Fin Assumptions'!$B$6)),'Fin Assumptions'!$B$10,0) -> 174106.27 | G39: =D39-F39 -> 696425.07 | J39: =M38 -> 1054572.5 | K39: =J39*'Fin Assumptions'!$B$8/4 -> 15818.588 | L39: =IF(AND(C39>'Fin Assumptions'!$B$4,C39<=('Fin Assumptions'!$B$4+'Fin Assumptions'!$B$6)),(Debt!$K$1-Debt!K39),0) -> 204681.27 | M39: =J39-L39 -> 849891.28
C40: 37 | D40: =G39 -> 696425.07 | E40: =D40*'Fin Assumptions'!$B$8/4 -> 10446.376 | F40: =IF(AND(C40>'Fin Assumptions'!$B$4,C40<=('Fin Assumptions'!$B$4+'Fin Assumptions'!$B$6)),'Fin Assumptions'!$B$10,0) -> 174106.27 | G40: =D40-F40 -> 522318.8 | J40: =M39 -> 849891.28 | K40: =J40*'Fin Assumptions'!$B$8/4 -> 12748.369 | L40: =IF(AND(C40>'Fin Assumptions'!$B$4,C40<=('Fin Assumptions'!$B$4+'Fin Assumptions'!$B$6)),(Debt!$K$1-Debt!K40),0) -> 207751.49 | M40: =J40-L40 -> 642139.79
C41: 38 | D41: =G40 -> 522318.8 | E41: =D41*'Fin Assumptions'!$B$8/4 -> 7834.782 | F41: =IF(AND(C41>'Fin Assumptions'!$B$4,C41<=('Fin Assumptions'!$B$4+'Fin Assumptions'!$B$6)),'Fin Assumptions'!$B$10,0) -> 174106.27 | G41: =D41-F41 -> 348212.54 | J41: =M40 -> 642139.79 | K41: =J41*'Fin Assumptions'!$B$8/4 -> 9632.0968 | L41: =IF(AND(C41>'Fin Assumptions'!$B$4,C41<=('Fin Assumptions'!$B$4+'Fin Assumptions'!$B$6)),(Debt!$K$1-Debt!K41),0) -> 210867.76 | M41: =J41-L41 -> 431272.02
C42: 39 | D42: =G41 -> 348212.54 | E42: =D42*'Fin Assumptions'!$B$8/4 -> 5223.188 | F42: =IF(AND(C42>'Fin Assumptions'!$B$4,C42<=('Fin Assumptions'!$B$4+'Fin Assumptions'!$B$6)),'Fin Assumptions'!$B$10,0) -> 174106.27 | G42: =D42-F42 -> 174106.27 | J42: =M41 -> 431272.02 | K42: =J42*'Fin Assumptions'!$B$8/4 -> 6469.0803 | L42: =IF(AND(C42>'Fin Assumptions'!$B$4,C42<=('Fin Assumptions'!$B$4+'Fin Assumptions'!$B$6)),(Debt!$K$1-Debt!K42),0) -> 214030.78 | M42: =J42-L42 -> 217241.24
C43: 40 | D43: =G42 -> 174106.27 | E43: =D43*'Fin Assumptions'!$B$8/4 -> 2611.594 | F43: =IF(AND(C43>'Fin Assumptions'!$B$4,C43<=('Fin Assumptions'!$B$4+'Fin Assumptions'!$B$6)),'Fin Assumptions'!$B$10,0) -> 174106.27 | G43: =D43-F43 -> -1.6298145e-09 | J43: =M42 -> 217241.24 | K43: =J43*'Fin Assumptions'!$B$8/4 -> 3258.6186 | L43: =IF(AND(C43>'Fin Assumptions'!$B$4,C43<=('Fin Assumptions'!$B$4+'Fin Assumptions'!$B$6)),(Debt!$K$1-Debt!K43),0) -> 217241.24 | M43: =J43-L43 -> 5.8207661e-10
B47: Reducing Bal. Method
B48: Year | D48: 1 | E48: 2 | F48: 3 | G48: 4 | H48: 5 | I48: 6 | J48: 7 | K48: 8 | L48: 9 | M48: 10
B49: Annual interest paid | D49: =SUM(E4:E7) -> 334284.03 | E49: =SUM(E8:E11) -> 334284.03 | F49: =SUM(E12:E15) -> 318614.47 | G49: =SUM(E16:E19) -> 276828.97 | H49: =SUM(E20:E23) -> 235043.46 | I49: =SUM(E24:E27) -> 193257.96 | J49: =SUM(E28:E31) -> 151472.45 | K49: =SUM(E32:E35) -> 109686.95 | L49: =SUM(E36:E39) -> 67901.444 | M49: =SUM(E40:E43) -> 26115.94
B50: principal Payment | D50: =SUM(F4:F7) -> 0 | E50: =SUM(F8:F11) -> 0 | F50: =SUM(F12:F15) -> 696425.07 | G50: =SUM(F16:F19) -> 696425.07 | H50: =SUM(F20:F23) -> 696425.07 | I50: =SUM(F24:F27) -> 696425.07 | J50: =SUM(F28:F31) -> 696425.07 | K50: =SUM(F32:F35) -> 696425.07 | L50: =SUM(F36:F39) -> 696425.07 | M50: =SUM(F40:F43) -> 696425.07
B51: Total LTD payment | D51: =SUM(D49:D50) -> 334284.03 | E51: =SUM(E49:E50) -> 334284.03 | F51: =SUM(F49:F50) -> 1015039.5 | G51: =SUM(G49:G50) -> 973254.04 | H51: =SUM(H49:H50) -> 931468.53 | I51: =SUM(I49:I50) -> 889683.03 | J51: =SUM(J49:J50) -> 847897.52 | K51: =SUM(K49:K50) -> 806112.02 | ... M51: =SUM(M49:M50) -> 722541.01
B53: Balance LTD | C53: =D4 -> 5571400.6 | D53: =C53-D50 -> 5571400.6 | E53: =D53-E50 -> 5571400.6 | F53: =E53-F50 -> 4874975.5 | G53: =F53-G50 -> 4178550.4 | H53: =G53-H50 -> 3482125.4 | I53: =H53-I50 -> 2785700.3 | J53: =I53-J50 -> 2089275.2 | K53: =J53-K50 -> 1392850.1 | ... M53: =L53-M50 -> -9.3132257e-10
B57: Working Capital Loans
B58: Eligibility | C58: 0.75
B59: Interest Rate | C59: 0.12
B60: Working capital requirement :
B61: Raw Materials | D61: days
B62: Finished Products | C62: 0 | D62: days
B63: Debtors and inventory | C63: days | D63: 10 | E63: 20 | F63: =E63 -> 20 | G63: =F63 -> 20 | H63: =G63 -> 20 | I63: =H63 -> 20 | J63: =I63 -> 20 | K63: =J63 -> 20 | L63: =K63 -> 20 | M63: =L63 -> 20
B64: Year | D64: 1 | E64: 2 | F64: 3 | G64: 4 | H64: 5 | I64: 6 | J64: 7 | K64: 8 | L64: 9 | M64: 10
B65: Working Capital
B66: Raw Material | D66: 0 | E66: 0 | F66: 0 | G66: 0 | H66: 0 | I66: 0 | J66: 0 | K66: 0 | L66: 0 | M66: 0
B67: Debtors and inventory | D67: =+D63*'P&L'!D16/360 -> 104180.34 | E67: =+E63*'P&L'!E16/360 -> 233504.62 | F67: =+F63*'P&L'!F16/360 -> 258708.31 | G67: =+G63*'P&L'!G16/360 -> 283754.4 | H67: =+H63*'P&L'!H16/360 -> 307273.57 | I67: =+I63*'P&L'!I16/360 -> 326938.85 | J67: =+J63*'P&L'!J16/360 -> 326938.85 | K67: =+K63*'P&L'!K16/360 -> 326938.85 | ... M67: =+M63*'P&L'!M16/360 -> 326938.85
B68: Total Working Capital | D68: =SUM(D66:D67) -> 104180.34 | E68: =SUM(E66:E67) -> 233504.62 | F68: =SUM(F66:F67) -> 258708.31 | G68: =SUM(G66:G67) -> 283754.4 | H68: =SUM(H66:H67) -> 307273.57 | I68: =SUM(I66:I67) -> 326938.85 | J68: =SUM(J66:J67) -> 326938.85 | K68: =SUM(K66:K67) -> 326938.85 | ... M68: =SUM(M66:M67) -> 326938.85
B69: Margin Money
B70: WC Borrowing | D70: =D67*0.8 -> 83344.269 | E70: =E68*0.8 -> 186803.7 | F70: =F68*0.8 -> 206966.65 | G70: =G68*0.8 -> 227003.52 | H70: =H68*0.8 -> 245818.86 | I70: =I68*0.8 -> 261551.08 | J70: =J68*0.8 -> 261551.08 | K70: =K68*0.8 -> 261551.08 | L70: =L68*0.8 -> 261551.08 | M70: =M68*0.8 -> 261551.08
B71: Interest on WC | D71: =D70*$C$59 -> 10001.312 | E71: =E70*$C$59 -> 22416.443 | F71: =F70*$C$59 -> 24835.998 | G71: =G70*$C$59 -> 27240.422 | H71: =H70*$C$59 -> 29498.263 | I71: =I70*$C$59 -> 31386.13 | J71: =J70*$C$59 -> 31386.13 | K71: =K70*$C$59 -> 31386.13 | ... M71: =M70*$C$59 -> 31386.13

Sheet Dep.
A2: Depreciation Rates | B2: Book Depr | C2: Tax Depr
A3: ='Fin Assumptions'!A25 -> Plant & Machinery | B3: ='Fin Assumptions'!B25 -> 0.1034 | C3: ='Fin Assumptions'!C25 -> 0.15
A4: ='Fin Assumptions'!A27 -> Miscellaneous Fixed Assets | B4: ='Fin Assumptions'!B27 -> 0.1034 | C4: ='Fin Assumptions'!C27 -> 0.15
A5: ='Fin Assumptions'!A28 -> Buildings-Plant (technical) | B5: ='Fin Assumptions'!B28 -> 0.0334 | C5: ='Fin Assumptions'!C28 -> 0.05
A6: ='Fin Assumptions'!A29 -> Buildings-Non technical | B6: ='Fin Assumptions'!B29 -> 0.0163 | C6: ='Fin Assumptions'!C29 -> 0.05
A9: Book Depreciation-SLM
C10: Years
A11: Assets | B11: Value | C11: 1 | D11: 2 | E11: 3 | F11: 4 | G11: 5 | H11: 6 | I11: 7 | J11: 8 | K11: 9 | L11: 10
A12: P &M
A13: Building
A14: MFA
A15: =A3 -> Plant & Machinery | B15: ='Project Cost'!D13 -> 3913039.8 | C15: =$B15*$B3 -> 404608.31 | D15: =($B15+$D12)*$B3 -> 404608.31 | E15: =($B15+$D12)*$B3 -> 404608.31 | F15: =($B15+$D12)*$B3 -> 404608.31 | G15: =($B15+$D12)*$B3 -> 404608.31 | H15: =($B15+$D12)*$B3 -> 404608.31 | I15: =($B15+$D12)*$B3 -> 404608.31 | J15: =($B15+$D12)*$B3 -> 404608.31 | K15: =($B15+$D12)*$B3 -> 404608.31 | L15: =($B15+$D12)*$B3 -> 404608.31
A16: Additional assets
A17: =A4 -> Miscellaneous Fixed Assets | B17: ='Other Equipment'!I10/100000 -> 0.15255682 | C17: =$B17*$B4 -> 0.015774375 | D17: =($B17+$D14)*$B4 -> 0.015774375 | E17: =($B17+$D14)*$B4 -> 0.015774375 | F17: =($B17+$D14)*$B4 -> 0.015774375 | G17: =($B17+$D14)*$B4 -> 0.015774375 | H17: =($B17+$D14)*$B4 -> 0.015774375 | I17: =($B17+$D14)*$B4 -> 0.015774375 | J17: =($B17+$D14)*$B4 -> 0.015774375 | K17: =($B17+$D14)*$B4 -> 0.015774375 | L17: =($B17+$D14)*$B4 -> 0.015774375
A18: =A5 -> Buildings-Plant (technical) | B18: ='Project Cost'!D8 -> 2001841.4 | C18: =$B18*$B5 -> 66861.502 | D18: =($B18+$D13)*$B5 -> 66861.502 | E18: =($B18+$D13)*$B5 -> 66861.502 | F18: =($B18+$D13)*$B5 -> 66861.502 | G18: =($B18+$D13)*$B5 -> 66861.502 | H18: =($B18+$D13)*$B5 -> 66861.502 | I18: =($B18+$D13)*$B5 -> 66861.502 | J18: =($B18+$D13)*$B5 -> 66861.502 | K18: =($B18+$D13)*$B5 -> 66861.502 | L18: =($B18+$D13)*$B5 -> 66861.502
A19: =A6 -> Buildings-Non technical | B19: 0 | C19: =$B19*$B6 -> 0 | D19: =$B19*$B6 -> 0 | E19: =$B19*$B6 -> 0 | F19: =$B19*$B6 -> 0 | G19: =$B19*$B6 -> 0 | H19: =$B19*$B6 -> 0 | I19: =$B19*$B6 -> 0 | J19: =$B19*$B6 -> 0 | ... L19: =$B19*$B6 -> 0
A20: Depreciation | C20: =SUM(C15:C19) -> 471469.83 | D20: =SUM(D15:D19) -> 471469.83 | E20: =SUM(E15:E19) -> 471469.83 | F20: =SUM(F15:F19) -> 471469.83 | G20: =SUM(G15:G19) -> 471469.83 | H20: =SUM(H15:H19) -> 471469.83 | I20: =SUM(I15:I19) -> 471469.83 | J20: =SUM(J15:J19) -> 471469.83 | ... L20: =SUM(L15:L19) -> 471469.83
A21: Closing Bal
A22: =A15 -> Plant & Machinery | B22: =B15 -> 3913039.8 | C22: =B22-C15 -> 3508431.5 | D22: =C22-D15 -> 3103823.1 | E22: =D22-E15 -> 2699214.8 | F22: =E22-F15+F16 -> 2294606.5 | G22: =F22-G15+G16 -> 1889998.2 | H22: =G22-H15+H16 -> 1485389.9 | I22: =H22-I15+I16 -> 1080781.6 | J22: =I22-J15+J16 -> 676173.27 | K22: =J22-K15+K16 -> 271564.96 | L22: =K22-L15 -> -133043.35
A23: =A17 -> Miscellaneous Fixed Assets | B23: =B17 -> 0.15255682 | C23: =B23-C17 -> 0.13678244 | D23: =C23-D17 -> 0.12100807 | E23: =D23-E17 -> 0.10523369 | F23: =E23-F17 -> 0.089459318 | G23: =F23-G17 -> 0.073684943 | H23: =G23-H17 -> 0.057910568 | I23: =H23-I17 -> 0.042136193 | J23: =I23-J17 -> 0.026361818 | ... L23: =K23-L17 -> -0.0051869318
A24: =A18 -> Buildings-Plant (technical) | B24: =B18 -> 2001841.4 | C24: =B24-C18 -> 1934979.9 | D24: =C24-D18 -> 1868118.4 | E24: =D24-E18 -> 1801256.9 | F24: =E24-F18 -> 1734395.4 | G24: =F24-G18 -> 1667533.9 | H24: =G24-H18 -> 1600672.4 | I24: =H24-I18 -> 1533810.9 | J24: =I24-J18 -> 1466949.4 | ... L24: =K24-L18 -> 1333226.3
A25: =A19 -> Buildings-Non technical | B25: =B19 -> 0 | C25: =B25-C19 -> 0 | D25: =C25-D19 -> 0 | E25: =D25-E19 -> 0 | F25: =E25-F19 -> 0 | G25: =F25-G19 -> 0 | H25: =G25-H19 -> 0 | I25: =H25-I19 -> 0 | J25: =I25-J19 -> 0 | ... L25: =K25-L19 -> 0
A28: Tax Depreciation-WDV | C28: Years
A29: Assets | B29: Value | C29: 1 | D29: 2 | E29: 3 | F29: 4 | G29: 5 | H29: 6 | I29: 7 | J29: 8 | K29: 9 | L29: 10
A30: =A22 -> Plant & Machinery | B30: =B15 -> 3913039.8 | C30: =$B30*$C3 -> 586955.97 | D30: =C37*$C3 -> 498912.57 | E30: =D37*$C3 -> 424075.69 | F30: =E37*$C3 -> 360464.33 | G30: =F37*$C3 -> 306394.68 | H30: =G37*$C3 -> 260435.48 | I30: =H37*$C3 -> 221370.16 | J30: =I37*$C3 -> 188164.63 | K30: =J37*$C3 -> 159939.94 | L30: =K37*$C3 -> 135948.95
A31: =A23 -> Miscellaneous Fixed Assets | B31: 0 | C31: =$B31*$C4 -> 0 | D31: =C38*$C4 -> 0.022883523 | E31: =D38*$C4 -> 0.019450994 | F31: =E38*$C4 -> 0.016533345 | G31: =F38*$C4 -> 0.014053343 | H31: =G38*$C4 -> 0.011945342 | I31: =H38*$C4 -> 0.010153541 | J31: =I38*$C4 -> 0.0086305095 | K31: =J38*$C4 -> 0.0073359331 | L31: =K38*$C4 -> 0.0062355431
A32: =A24 -> Buildings-Plant (technical) | B32: ='Project Cost'!D8 -> 2001841.4 | C32: =$B32*$C4 -> 300276.2 | D32: =C39*$C4 -> 255234.77 | E32: =D39*$C4 -> 216949.56 | F32: =E39*$C4 -> 184407.12 | G32: =F39*$C4 -> 156746.06 | H32: =G39*$C4 -> 133234.15 | I32: =H39*$C4 -> 113249.03 | J32: =I39*$C4 -> 96261.671 | K32: =J39*$C4 -> 81822.421 | L32: =K39*$C4 -> 69549.058
A33: =A25 -> Buildings-Non technical | B33: ='Project Cost'!D9 -> 200000 | C33: =$B33*$C6 -> 10000 | D33: =C40*$C6 -> 9500 | E33: =D40*$C6 -> 9025 | F33: =E40*$C6 -> 8573.75 | G33: =F40*$C6 -> 8145.0625 | H33: =G40*$C6 -> 7737.8094 | I33: =H40*$C6 -> 7350.9189 | J33: =I40*$C6 -> 6983.373 | K33: =J40*$C6 -> 6634.2043 | L33: =K40*$C6 -> 6302.4941
A34: Depreciation | C34: =SUM(C30:C33) -> 897232.17 | D34: =SUM(D30:D33) -> 763647.37 | E34: =SUM(E30:E33) -> 650050.26 | F34: =SUM(F30:F33) -> 553445.22 | G34: =SUM(G30:G33) -> 471285.81 | H34: =SUM(H30:H33) -> 401407.45 | I34: =SUM(I30:I33) -> 341970.11 | J34: =SUM(J30:J33) -> 291409.69 | ... L34: =SUM(L30:L33) -> 211800.51
A36: Closing Bal
A37: =A30 -> Plant & Machinery | B37: =B30 -> 3913039.8 | C37: =B37-C30 -> 3326083.8 | D37: =C37-D30 -> 2827171.2 | E37: =D37-E30 -> 2403095.6 | F37: =E37-F30 -> 2042631.2 | G37: =F37-G30 -> 1736236.5 | H37: =G37-H30 -> 1475801.1 | I37: =H37-I30 -> 1254430.9 | J37: =I37-J30 -> 1066266.3 | ... L37: =K37-L30 -> 770377.37
A38: =A31 -> Miscellaneous Fixed Assets | B38: ='Other Equipment'!I10/100000 -> 0.15255682 | C38: =B38-C31 -> 0.15255682 | D38: =C38-D31 -> 0.1296733 | E38: =D38-E31 -> 0.1102223 | F38: =E38-F31 -> 0.093688956 | G38: =F38-G31 -> 0.079635613 | H38: =G38-H31 -> 0.067690271 | I38: =H38-I31 -> 0.05753673 | J38: =I38-J31 -> 0.048906221 | ... L38: =K38-L31 -> 0.035334744
A39: =A32 -> Buildings-Plant (technical) | B39: =B32 -> 2001841.4 | C39: =B39-C32 -> 1701565.2 | D39: =C39-D32 -> 1446330.4 | E39: =D39-E32 -> 1229380.8 | F39: =E39-F32 -> 1044973.7 | G39: =F39-G32 -> 888227.65 | H39: =G39-H32 -> 754993.5 | I39: =H39-I32 -> 641744.48 | J39: =I39-J32 -> 545482.8 | ... L39: =K39-L32 -> 394111.33
A40: =A33 -> Buildings-Non technical | B40: =B33 -> 200000 | C40: =B40-C33 -> 190000 | D40: =C40-D33 -> 180500 | E40: =D40-E33 -> 171475 | F40: =E40-F33 -> 162901.25 | G40: =F40-G33 -> 154756.19 | H40: =G40-H33 -> 147018.38 | I40: =H40-I33 -> 139667.46 | J40: =I40-J33 -> 132684.09 | ... L40: =K40-L33 -> 119747.39
A42: Total WDV | C42: =SUM(C37:C40) -> 5217649.1 | D42: =SUM(D37:D40) -> 4454001.8 | E42: =SUM(E37:E40) -> 3803951.5 | F42: =SUM(F37:F40) -> 3250506.3 | G42: =SUM(G37:G40) -> 2779220.5 | H42: =SUM(H37:H40) -> 2377813 | I42: =SUM(I37:I40) -> 2035842.9 | J42: =SUM(J37:J40) -> 1744433.2 | ... L42: =SUM(L37:L40) -> 1284236.1

Sheet Sheet1
A4: Electrical Equipments
A5: Sr No. | B5: Items | C5: Description | D5: Quantity | E5: Unit | F5: Rate (INR) | G5: Amount (Rs)
A6: 1 | B6: Substation
C7: 500 KVA Transformer with OLTC 22 KV/433 V, Outdoor | D7: 1 | E7: nos | F7: =815000+15000 -> 830000 | G7: 830000
C8: Supply Erection and Fixing of 22 KV 2P structure | D8: 1 | E8: set | F8: =275000+18000 -> 293000 | G8: 293000
C9: Supply, Fabrication & Erection of Substation Yard Fencing | D9: 1 | E9: set | F9: =75000+6000 -> 81000 | G9: 81000
C10: Supply & Erection of 100/% A NI CT with MS Enclosure | D10: 1 | E10: nos | F10: =3000+500 -> 3500 | G10: 3500
C11: OLTC Panel | D11: 1 | E11: nos | F11: 2000 | G11: 2000
C12: Metering Box with wiring set | D12: 1 | E12: nos | F12: =14000+1250 -> 15250 | G12: 15250
C13: Load Break Switch | D13: 1 | E13: nos | F13: =215000+4000 -> 219000 | G13: 219000
A14: 2 | B14: Power House
C15: Supply, Erection & Commissioning | D15: 1 | E15: nos | F15: =595000+12500 -> 607500 | G15: 607500
A16: 3 | B16: Panel Boards
C17: Supply, Erection & Commissioning of LSB made comprising of 125A TPN SFU-1 NO as Incomer and 63A TPN SFU - 6 Nos as outgoing | D17: 2 | E17: nos | F17: =20500+1200 -> 21700 | G17: 43400
C18: Supply, Erection& Commissioning of LDB made comprising of 32 A DB MCB - 1 No as Incomer and 6A SP MCB - 8 Nos as outgoing | D18: 6 | E18: nos | F18: =2750+450 -> 3200 | G18: 19200
C19: Supply Erection & Commissioning of MCB DB made up of 16SWG CRCA | D19: 3 | E19: nos | F19: =9750+600 -> 10350 | G19: 31050
C20: Supply, Erection & Commissioning of 100 KVAR APFC Panel | D20: 1 | E20: nos | F20: =250000+1000 -> 251000 | G20: 251000
C21: Genset Panel | D21: 1 | E21: nos | F21: 2500 | G21: 2500
A22: 4 | B22: UG Cables | G22: 0
C23: 3.5 C X 185 sqmm 22 KV HT A1 Arm Cable | D23: 160 | E23: meter | F23: 1260 | G23: 201600
C24: 3.5 C X 400 sqmm A1 Arm Cable (between Transformer & MV Panel) | D24: 250 | E24: meter | F24: =1120+48 -> 1168 | G24: 292000
C25: 3.5 C X 240 sqmm A1 Arm Cable (between Genset & MV Panel) | D25: 180 | E25: meter | F25: =648+46 -> 694 | G25: 124920
C26: 3.5 C X 185 sqmm A1 Arm Cable (between MV Panel & APFC Panel) | D26: 380 | E26: meter | F26: =585+42 -> 627 | G26: 238260
C27: 3.5 C X 35 sqmm A1 Arm Cable (between MV Panel & MLSB & MCB Power DB) | D27: 225 | E27: meter | F27: =175+28 -> 203 | G27: 45675
C28: 4 C X 10 sqmm CU Arm Cable (from SSB1 &2 to Ripening Chambers & From SSB2 to cold rooms, pre cooler) | D28: 1200 | E28: meter | F28: =352+18 -> 370 | G28: 444000
C29: 2 C X 4 sqmm Cu Arm Cable (between LSB & LDB) | D29: 350 | E29: meter | F29: =140+11 -> 151 | G29: 52850
C30: 19 C X 1.5 sqmm Cu Arm Cable (between OLTC CP to RTCC) | D30: 25 | E30: meter | F30: =230+21 -> 251 | G30: 6275
C31: 3 C X 2.5sqmm Cu Arm Cable | D31: 850 | E31: meter | F31: =92+9 -> 101 | G31: 85850
C32: 3 C X 1.5 sqmm Cu Arm Cable (between LDB & Street Lights) | D32: 750 | E32: meter | F32: =66+9 -> 75 | G32: 56250
A33: 5 | B33: Supply & Erection of End Termination | G33: 0
C34: 22 KV X 185 sqmm Outdoor Cable Joints kit | D34: 3 | E34: nos | F34: =16900+3000 -> 19900 | G34: 59700
C35: 22 KV X 185 sqmm Indoor Cable Joints kit | D35: 3 | E35: nos | F35: =11500+2500 -> 14000 | G35: 42000
C36: 3.5 C X 400 sqmm | D36: 6 | E36: nos | F36: =1015+550 -> 1565 | G36: 9390
C37: 3.5 C X 240 sqmm | D37: 8 | E37: nos | F37: =690+450 -> 1140 | G37: 9120
C38: 3.5 C X 185 sqmm | D38: 10 | E38: nos | F38: =450+375 -> 825 | G38: 8250
C39: 3.5 C X 35 sqmm | D39: 8 | E39: nos | F39: =150+150 -> 300 | G39: 2400
C40: 4 C X 10 sqmm | D40: 60 | E40: nos | F40: =145+125 -> 270 | G40: 16200
C41: 2C X 4 sqmm | D41: 16 | E41: nos | F41: =65+55 -> 120 | G41: 1920
C42: 19 C X 1.5sqmm | D42: 2 | E42: nos | F42: =90+100 -> 190 | G42: 380
C43: 3 C X 2.5sqmm , 3 C X 1.5 sqmm | D43: 60 | E43: nos | F43: =55+50 -> 105 | G43: 6300
A44: 6 | B44: Earthing
C45: Earth Electrode for Transformer & MV Panel, SSB, Genset & Plant Earthing | D45: 18 | E45: nos | F45: =3850+500 -> 4350 | G45: 78300
C46: 25 X 6 mm Cu Flat for Transformer Neutral Earthing | D46: 75 | E46: nos | F46: =650+40 -> 690 | G46: 51750
C47: 25 X 3 mm Cu Flat for Transformer, MV Panel, SSB & Plant Body Earthing | D47: 650 | E47: nos | F47: =360+32 -> 392 | G47: 254800
C48: No 8 SWG Copper | D48: 300 | E48: nos | F48: =55+9 -> 64 | G48: 19200
C49: No 10 SWG Copper | D49: 200 | E49: nos | F49: =45+7 -> 52 | G49: 10400
C50: No 18 SWG Copper | D50: 25 | E50: nos | F50: =25+5 -> 30 | G50: 750
C51: Supply & Erection of Earth Bus with 25X3 CU Flat and Bolt, Nut etc. | D51: 5 | E51: nos | F51: =350+75 -> 425 | G51: 2125
A52: 7 | B52: Miscellaneous
C53: Metal Halide Lamp with fitting include post (Outdoor) - 250 W | D53: 6 | E53: nos | F53: =10750+1000 -> 11750 | G53: 70500
C54: Metal Halide Lamp with fitting with GI Bend Pipe 3'X11/2" - 250 W | D54: 9 | E54: nos | F54: =4800+400 -> 5200 | G54: 46800
C55: CFL Street light fitting with lamp & pipe support - (1X36 W) | D55: 3 | E55: nos | F55: =1600+250 -> 1850 | G55: 5550
C56: 36 W CFL Street light fitting, lamp with 15' height . 21/2' below the ground level GI Pipe Post, Bend | D56: 17 | E56: nos | F56: =3800+750 -> 4550 | G56: 77350
C57: 250 W Flood Light with supporting brackets | D57: 5 | E57: nos | F57: =10300+300 -> 10600 | G57: 53000
C58: Metal Halide Lamp with fitting (Indoor) -250 W | D58: 7 | E58: nos | F58: =4900+450 -> 5350 | G58: 37450
C59: Metal Halide Lamp with fitting | D59: 25 | E59: nos | F59: =3600+450 -> 4050 | G59: 101250
A61: 8 | B61: Electrical Inspectorate | C61: Design, Preparation & Forwarding of Substation, MV Panel Room, Physical and Schematic layout drawings to Inspectorate for obtaing approval | D61: LS | F61: 35000 | G61: 35000
C62: Forwarding completion report to the inspectorate, and approval for obating Safety Certificate | D62: LS | F62: 25000 | G62: 25000
C63: Preparation of site plan drawing and submission to KSEB along with HT application load sanction, signing test report etc. | D63: LS | F63: 25000 | G63: 25000
A64: 9 | B64: D G Set | C64: 160 KVA | D64: 2 | E64: nos | F64: 840000 | G64: 1680000
F65: Total | G65: =SUM(G7:G64) -> 6675965

Sheet Sheet2
B2: ESTIMATED COST OF TECHNICAL CIVIL WORKS
B3: Central Facility Building
B4: Fruits & Vegetables Cold Storage and CA stores
B5: Sr No | C5: Item Description | E5: Quantity | F5: Unit | G5: Amount (Rs)
B6: 1 | C6: Earth work excavation for foundation in all soils and sub soils to full depth | E6: 12976 | F6: cft | G6: 129760
B7: 2 | C7: Cement Concrete 1:4:8 | E7: 10441.5 | F7: cft | G7: 626490
B8: 3 | C8: Reinforced Cement Concrete 1:2:4 | E8: 17422.225 | F8: cft | G8: 6097778.7
B9: 4 | C9: Filling in basement with excavated earth | E9: 26098.875 | F9: cft | G9: 208791
B10: 5 | C10: Brick work in cement mortar | E10: 2212.5 | F10: cft | G10: 188062.5
B11: 6 | C11: Plastering with CM 1:6 in all floors including curing etc. complete complying with standard specifications | E11: 13494 | F11: sft | G11: 215904
B12: 7 | C12: Grano Flooring with 1:2:3 mix | E12: 18450 | F12: sft | G12: 738000
B13: 8 | C13: Contingencies and others | G13: 5213.75
B14: 9 | C14: Pre-Engineered Building
D15: Roof Structure ( in MT) | E15: 93 | F15: MT | G15: 6975000
D16: Supply, fixing of Puffed Panel (30mm) | E16: 2060 | F16: sq m | G16: 3708000
D17: Supply, fixing of Puffed Panel (50mm) | E17: 2670 | F17: sq m | G17: 4806000
D18: Painting of roof structures | E18: 93 | F18: MT | G18: 558000
D19: Supply of joineries | E19: 400 | F19: sq m | G19: 1920000
D20: Transportation, Loading and Unloading | E20: 93 | F20: MT | G20: 558000
B21: Ripening Chamber
B22: Sr No | C22: Item Description | E22: Quantity | F22: Unit | G22: Amount (Rs)
B23: 1 | C23: Earth work excavation for foundation in all soils and sub soils to full depth | E23: 4800 | F23: cft | G23: 48000
B24: 2 | C24: Cement Concrete 1:4:8 | E24: 1746.38 | F24: cft | G24: 104782.8
B25: 3 | C25: Reinforced Cement Concrete 1:2:4 | E25: 3806.8475 | F25: cft | G25: 1332396.6
B26: 4 | C26: Filling in basement with excavated earth | E26: 13017.375 | F26: cft | G26: 104139
B27: 5 | C27: Brick work in cement mortar | E27: 1016.25 | F27: cft | G27: 86381.25
B28: 6 | C28: Plastering with CM 1:6 in all floors including curing etc. complete complying with standard specifications | E28: 4204 | F28: sft | G28: 67264
B29: 7 | C29: Grano Flooring with 1:2:3 mix | E29: 2892.75 | F29: sft | G29: 115710
B30: 8 | C30: Contingencies and others | G30: 326.62
D31: Roof Structure ( in MT) | E31: 11 | F31: MT | G31: 825000
D32: Supply, fixing of Puffed Panel (30mm) | E32: 225 | F32: sq m | G32: 405000
D33: Supply, fixing of Puffed Panel (50mm) | E33: 270 | F33: sq m | G33: 486000
D34: Painting of roof structures | E34: 11 | F34: MT | G34: 66000
D35: Supply of joineries | E35: 20 | F35: sq m | G35: 96000
D36: Transportation, Loading and Unloading | E36: 11 | F36: MT | G36: 66000
B37: Multi Purpose Cold Storage
B38: Sr No | C38: Item Description | E38: Quantity | F38: Unit | G38: Amount (Rs)
B39: 1 | C39: Earth work excavation for foundation in all soils and sub soils to full depth | E39: 8032 | F39: cft | G39: 80320
B40: 2 | C40: Cement Concrete 1:4:8 | E40: 4765.5 | F40: cft | G40: 285930
B41: 3 | C41: Reinforced Cement Concrete 1:2:4 | E41: 8281.895 | F41: cft | G41: 2898663.2
B42: 4 | C42: Filling in basement with excavated earth | E42: 34894.125 | F42: cft | G42: 279153
B43: 5 | C43: Brick work in cement mortar | E43: 1365 | F43: cft | G43: 116025
B44: 6 | C44: Plastering with CM 1:6 in all floors including curing etc. complete complying with standard specifications | E44: 8159 | F44: sft | G44: 130544
B45: 7 | C45: Grano Flooring with 1:2:3 mix | E45: 8025 | F45: sft | G45: 321000
B46: 8 | C46: Contingencies and others | G46: 8364.75
D47: Roof Structure (in MT) | E47: 40 | F47: MT | G47: 3000000
D48: Supply, fixing of Puffed Panel (30mm) | E48: 895 | F48: sq m | G48: 1611000
D49: Supply, fixing of Puffed Panel (50mm) | E49: 1670 | F49: sq m | G49: 3006000
D50: Painting of roof structures | E50: 40 | F50: MT | G50: 240000
D51: Supply of joineries | E51: 300 | F51: sq m | G51: 1440000
D52: Transportation, Loading and Unloading | E52: 40 | F52: MT | G52: 240000
B53: Collection Centre 1 at Mettupalayam
B54: Pack House with Pre-cooling Facility
B55: Sr No | C55: Item Description | E55: Quantity | F55: Unit | G55: Amount (Rs)
B56: 1 | C56: Earth work excavation for foundation in all soils and sub soils to full depth | E56: 8288 | F56: cft | G56: 82880
B57: 2 | C57: Cement Concrete 1:4:8 | E57: 5665 | F57: cft | G57: 339900
B58: 3 | C58: Reinforced Cement Concrete 1:2:4 | E58: 9292 | F58: cft | G58: 3252200
B59: 4 | C59: Filling in basement with excavated earth | E59: 45000 | F59: cft | G59: 360000
B60: 5 | C60: Brick work in cement mortar | E60: 1500 | F60: cft | G60: 127500
B61: 6 | C61: Plastering with CM 1:6 in all floors including curing etc. complete complying with standard specifications | E61: 6758 | F61: sft | G61: 108128
B62: 7 | C62: Grano Flooring with 1:2:3 mix | E62: 2304 | F62: sft | G62: 92160
B63: 8 | C63: Contingencies and others | G63: 2232
B64: Collection Centre 2 at Bodinayakanur
B65: Pack House with Pre-cooling Facility
B66: Sr No | C66: Item Description | E66: Quantity | F66: Unit | G66: Amount (Rs)
B67: 1 | C67: Earth work excavation for foundation in all soils and sub soils to full depth | E67: 7776 | F67: cft | G67: 77760
B68: 2 | C68: Cement Concrete 1:4:8 | E68: 2681 | F68: cft | G68: 160860
B69: 3 | C69: Reinforced Cement Concrete 1:2:4 | E69: 5020.525 | F69: cft | G69: 1757183.7
B70: 4 | C70: Filling in basement with excavated earth | E70: 1915.865 | F70: cft | G70: 15326.92
B71: 5 | C71: Brick work in cement mortar | E71: 982.5 | F71: cft | G71: 83512.5
B72: 6 | C72: Plastering with CM 1:6 in all floors including curing etc. complete complying with standard specifications | E72: 4757 | F72: sft | G72: 76112
B73: 7 | C73: Grano Flooring with 1:2:3 mix | E73: 4290.25 | F73: sft | G73: 171610
B74: 8 | C74: Contingencies and others | G74: 11634.75
E75: Total | G75: =SUM(G6:G74) -> 50914000

Sheet Sheet3
B3: Central Facility at Pudussery : Office Building
B4: Ground Floor | D4: Quantity | E4: Unit | F4: Amount (Rs)
B5: Sr No | C5: Item Description
B6: 1 | C6: Earth work excavation for foundation in all soils and sub soils to full depth | D6: 4480 | E6: cft | F6: 44800
B7: 2 | C7: Cement Concrete 1:4:8 for flooring including consolidating as per standard specification, curing tec. | D7: 1313.96 | E7: cft | F7: 78837.6
B8: 3 | C8: Reinforced Cement Concrete 1:2:4 using 20mm gauge machine broken hard granite stone jelly with necessary steel reinforcement | D8: 3985.225 | E8: cft | F8: 1394828.8
B9: 4 | C9: Brick work in cement mortar 1:7 using country bricks | D9: 4373.025 | E9: cft | F9: 34984.2
B10: 5 | C10: Filling in basement with excavated earth | D10: 9036 | E10: cft | F10: 768060
B11: 6 | C11: Plastering with CM 1:5 mix 10mm thick including cost of al labor charges | D11: 3252 | E11: cft | F11: 58536
B12: 7 | C12: Plastering with CM 1:7 in all floors including curing etc. complete complying with standard specifications | D12: 8679 | E12: sft | F12: 138864
B13: 8 | C13: Supplying and fixing country wood for Doors, Windows and Ventilators | D13: 426.5 | E13: sft | F13: 234575
B14: 9 | C14: White Washing two coats in all the floors complete complying with standard specifications | D14: 11931 | E14: cft | F14: 119310
B15: 10 | C15: Painting two coats of new wood works | D15: 426.5 | E15: cft | F15: 3412
B16: 11 | C16: Paving the floor with ceramic tiles with c.m. 1:6 | D16: 3252 | E16: cft | F16: 292680
B17: 12 | C17: Providing ceramic Wall Tiles on toilet floors | D17: Lump Sum | F17: 40000
B18: 13 | C18: Provision for stair case | D18: Lump Sum | F18: 25000
B19: 14 | C19: Provision for Water Supply and Sanitation | D19: Lump Sum | F19: 100000
B20: 15 | C20: Provision for providing internal electrification arrangement to the light pipes | D20: Lump Sum | F20: 100000
B21: 16 | C21: Contingencies | D21: Lump Sum | F21: 1112.45
B22: First Floor | D22: Quantity | E22: Unit | F22: Amount (Rs)
B23: Sr No | C23: Item Description
B24: 1 | C24: Brick work in cement mortar 1:7 using country bricks | D24: 4330.65 | E24: cft | F24: 368105.25
B25: 2 | C25: Reinforced Cement Concrete 1:2:4 using 20mm gauge machine broken hard granite stone jelly with necessary steel reinforcement | D25: 2811.75 | E25: cft | F25: 984112.5
B26: 3 | C26: Plastering with CM 1:5 mix 10mm thick including cost of al labor charges | D26: 2572.5 | E26: cft | F26: 46305
B27: 4 | C27: Plastering with CM 1:7 in all floors including curing etc. complete complying with standard specifications | D27: 9823 | E27: sft | F27: 157168
B28: 5 | C28: Supplying and fixing country wood for Doors, Windows and Ventilators | D28: 545 | E28: sft | F28: 299750
B29: 6 | C29: White Washing two coats in all the floors complete complying with standard specifications | D29: 12395.5 | E29: cft | F29: 123955
B30: 7 | C30: Painting two coats of new wood works | D30: 545 | E30: cft | F30: 4360
B31: 8 | C31: Paving the floor with ceramic tiles with c.m. 1:6 | D31: 2572.5 | E31: cft | F31: 231525
B32: 9 | C32: Weathering Course - Terracotta tiles with Lime surki and cement mortar | D32: 3773.25 | E32: sft | F32: 158476.5
B33: 10 | C33: Provision for Water Supply and Sanitation | D33: Lump Sum | F33: 100000
B34: 11 | C34: Provision for providing internal electrification arrangement to the light pipes | D34: Lump Sum | F34: 100000
B35: 12 | C35: Provision for overhead Tank | D35: Lump Sum | F35: 600000
B36: 13 | C36: Contingencies | D36: Lump Sum | F36: 1242.75
B37: Collection Center (Bodinayakanur
B38: Security cum Office Room | D38: Quantity | E38: Unit | F38: Amount (Rs)
B39: Sr No | C39: Item Description
B40: 1 | C40: Earth work excavation for foundation in all soils and sub soils to full depth | D40: 217.5 | E40: cft | F40: 870
B41: 2 | C41: Cement Concrete 1:5:10 for flooring including consolidating as per standard specification, curing tec. | D41: 264.5175 | E41: cft | F41: 7935.525
B42: 3 | C42: Supplying and Filling in foundation with fillings and in layers not more than 15 cm thick , well rammed, watered etc | D42: 43.5 | E42: sft | F42: 261
B43: 4 | C43: Random Rubble Masonry in cement mortar 1:5 for foundation and basement | D43: 233.25 | E43: cft | F43: 5831.25
B44: 5 | C44: Brick work in cement mortar 1:5 using country bricks | D44: 220.875 | E44: cft | F44: 8835
B45: 6 | C45: Reinforced Cement Concrete 1:2:4 using 20mm gauge machine broken hard granite stone jelly with necessary steel reinforcement | D45: 48.8975 | E45: cft | F45: 7334.625
B46: 7 | C46: Plastering with CM 1:3 mix 10mm thick including cost of al labor charges | D46: 42.25 | E46: cft | F46: 422.5
B47: 8 | C47: Plastering with CM 1:5 in all floors including curing etc. complete complying with standard specifications | D47: 641.5 | E47: sft | F47: 3207.5
B48: 9 | C48: Supplying and fixing steel Doors, Windows and Ventilators | D48: 39 | E48: sft | F48: 5850
B49: 10 | C49: White Washing two coats in all the floors complete complying with standard specifications | D49: 683.75 | E49: sft | F49: 4102.5
B50: 11 | C50: Painting two coats of new steel works | D50: 39 | E50: cft | F50: 156
B51: 12 | C51: Cement Mortar Flooring | D51: 42.25 | E51: sft | F51: 422.5
B52: 13 | C52: Weathering course with lime surki etc | D52: 42.38 | E52: sft | F52: 423.8
B53: 14 | C53: Contingencies | D53: Lump Sum | F53: 347.8
B54: Collection Center (Mettupalayam)
B55: Security cum Office Room | D55: Quantity | E55: Unit | F55: Amount (Rs)
B56: Sr No | C56: Item Description
B57: 1 | C57: Earth work excavation for foundation in all soils and sub soils to full depth | D57: 217.5 | E57: cft | F57: 870
B58: 2 | C58: Cement Concrete 1:5:10 for flooring including consolidating as per standard specification, curing tec. | D58: 264.5175 | E58: cft | F58: 7935.525
B59: 3 | C59: Supplying and Filling in foundation with fillings and in layers not more than 15 cm thick , well rammed, watered etc | D59: 43.5 | E59: sft | F59: 261
B60: 4 | C60: Random Rubble Masonry in cement mortar 1:5 for foundation and basement | D60: 233.25 | E60: cft | F60: 5831.25
B61: 5 | C61: Brick work in cement mortar 1:5 using country bricks | D61: 220.875 | E61: cft | F61: 8835
B62: 6 | C62: Reinforced Cement Concrete 1:2:4 using 20mm gauge machine broken hard granite stone jelly with necessary steel reinforcement | D62: 48.8975 | E62: cft | F62: 7334.625
B63: 7 | C63: Plastering with CM 1:3 mix 10mm thick including cost of al labor charges | D63: 42.25 | E63: cft | F63: 422.5
B64: 8 | C64: Plastering with CM 1:5 in all floors including curing etc. complete complying with standard specifications | D64: 641.5 | E64: sft | F64: 3207.5
B65: 9 | C65: Supplying and fixing steel Doors, Windows and Ventilators | D65: 39 | E65: sft | F65: 5850
B66: 10 | C66: White Washing two coats in all the floors complete complying with standard specifications | D66: 683.75 | E66: sft | F66: 4102.5
B67: 11 | C67: Painting two coats of new steel works | D67: 39 | E67: cft | F67: 156
B68: 12 | C68: Cement Mortar Flooring | D68: 42.25 | E68: sft | F68: 422.5
B69: 13 | C69: Weathering course with lime surki etc | D69: 42.38 | E69: sft | F69: 423.8
B70: 14 | C70: Contingencies | D70: Lump Sum | F70: 347.8
E71: Total | F71: =SUM(F6:F70) -> 6702000

Sheet Sheet4
B3: Central Facility at Pudussery
B4: COST ESTIMATES FOR MACHINERY AND EQUIPMENTS
B5: Fruits & Vegetables Cold Storage and CA stores
B6: Sr No. | C6: Items | D6: Description | E6: Quantity | F6: Unit | G6: Total Amount (INR)
B7: 1 | C7: Insulation Panels (PUF) | D7: Panels Ceiling 150 mm | E7: 864 | F7: sq m | G7: 2180445.7
D8: Panesl wall 120mm | E8: 1655 | F8: sq m | G8: 3607118.8
D9: Panesl Partition 100 mm | E9: 504 | F9: sq m | G9: 982852.42
D10: Panels Corridor 80mm | E10: 229 | F10: sq m | G10: 367766.67
D11: Floor Insulation with PUF 100mm | E11: 864 | F11: sq m | G11: 1699756.5
D12: Accessories including erection for above | E12: 3300 | F12: sq m | G12: 1173503.8
D13: Freight | E13: 4116 | G13: 1029000
B14: 2 | C14: Controlled Atmosphere Equipments & System | D14: Supply and Installation of Controlled Atmosphere Storages | E14: LS as per offer at Annexure of FFT Fresh Food Technology (I) Pvt Ltd | G14: 21636517
D15: Spare Parts | E15: LS as per offer at Annexure of FFT Fresh Food Technology (I) Pvt Ltd | G15: 439200
D16: Supply of Gas Tight Doors | E16: LS for 8 number of doors | G16: 2573285
D17: Supply of Elastomeric Coating | E17: LS as per offer at Annexure of FFT Fresh Food Technology (I) Pvt Ltd | G17: 1189500
D18: Supply & Installation of Humidification System | E18: LS as per offer at Annexure of FFT Fresh Food Technology (I) Pvt Ltd | G18: 3965000
B19: 3 | C19: Refrigeration System | D19: Supply & Installation of Refrigeartion System | E19: LS as per offer at Annexure of FFT Fresh Food Technology (I) Pvt Ltd | G19: 9000000
B20: Multi Purpose Cold Storage
B21: Sr No. | C21: Items | D21: Description | E21: Quantity | F21: Unit | G21: Total Amount (INR)
B22: 1 | C22: Insulation Panels (PUF) | D22: Wall Panels 80 mm | E22: 1323 | F22: sq m | G22: 2124695.7
D23: Ceiling Panels 80mm | E23: 736 | F23: sq m | G23: 1181992.4
D24: Partition Panels 80mm | E24: 324 | F24: sq m | G24: 520333.63
D25: Floor Insulation with PUF 80mm | E25: 736 | F25: sq m | G25: 1160885.4
D26: Accessories including erection for above | E26: 3119 | F26: sq m | G26: 983913.5
B27: 2 | C27: Freight | E27: 2382.61 | G27: 476522
B28: 3 | C28: Doors | D28: Single leaf manual sliding door | E28: 2 | F28: nos | G28: 540362.35
B29: 4 | C29: Refrigeration System | D29: Supply & Installation of Refrigeartion System | E29: LS as per offer at Annexure of FFT Fresh Food Technology (I) Pvt Ltd | G29: 8000000
B30: Ripening Rooms
B31: Sr No. | C31: Items | D31: Description | E31: Quantity | F31: Unit | G31: Total Amount (INR)
B32: 1 | C32: Panels and Equipments (Supply & Erection) | D32: Panel - Walls, Ceiling and Partitions | E32: 732 | F32: sq m | G32: 1207800
D33: PUF Floor Slabs | E33: 240 | F33: sq m | G33: 343203
D34: RibbStyle | E34: 4 | F34: Set | G34: 291600
D35: Bio-Conservation | E35: 4 | F35: Nos | G35: 333040
D36: Humidification | E36: 4 | F36: Nos | G36: 520720
D37: Ripening Manager | E37: 4 | F37: Nos | G37: 1457600
D38: Thermo log | E38: 4 | F38: Nos | G38: 125320
D39: Instrumentation Cable | E39: 6 | F39: Set | G39: 312600
D40: Ethylene Cylinder | E40: 6 | F40: Set | G40: 156600
D41: Import Duty on items 3,4,5,6,7,8,9 above | E41: LS | G41: 951700
D42: Service Tax on Erection Cost @10.30% | G42: 75087
B43: 2 | C43: Transportation & Freight | E43: LS | G43: 500000
B44: 3 | C44: Doors | D44: Gas tight Mounted on Rails | E44: 4 | G44: 817600
B45: 4 | C45: Refrigeration System | D45: Supply & Installation of Refrigeartion System | E45: LS as per offer at Annexure of FFT Fresh Food Technology (I) Pvt Ltd | G45: 3500000
B46: Pre-Cooling Rooms ( 2x10 MT)
B47: Sr No. | C47: Items | D47: Description | E47: Quantity | F47: Unit | G47: Total Amount (INR)
B49: 1 | C49: Panels and Equipments (Supply) | D49: Panel - Walls, Ceiling and Partitions | E49: 396 | F49: sq m | G49: 635963.33
D50: PUF Floor Slabs | E50: 120 | F50: sq m | G50: 189274.8
D51: Accessories | E51: 516 | F51: sq m | G51: 61920
B52: 2 | C52: Panels and Equipments (Erection) | D52: Panel - Walls, Ceiling and Partitions | E52: 396 | F52: sq m | G52: 120116.7
D53: PUF Floor Slabs | E53: 120 | F53: sq m | G53: 9927
D54: Accessories | E54: 516 | F54: sq m | G54: 28457.4
B55: 3 | C55: Transportation & Freight | E55: 516 | F55: sq m | G55: 129000
B56: 4 | C56: Doors | E56: 2 | G56: 442788.32
B57: 5 | C57: Refrigeration System | D57: Supply & Installation of Refrigeartion System | E57: LS as per offer at Annexure of FFT Fresh Food Technology (I) Pvt Ltd | G57: 2100000
B58: Dock Shelter | E58: 2 | G58: 424434.4
B59: Automised Clear Sectional Door | E59: 1 | G59: 269573.2
B60: Storage Racks
B61: Sr No. | C61: Items | D61: Description | E61: Quantity | F61: Unit | G61: Total Amount (INR)
B62: 1 | C62: Storage racks | D62: Layout 100'X70'X19.50' No of racks in layout - 8 No of Pallets per rack - 96 No of pallets in layout - 768 | E62: As per Quotation | F62: 1 set | G62: 3809379.5
B63: 2 | C63: Storage racks | D63: Layout 200'X88'X19.50' No of racks in layout - 16 No of Pallets per rack - 128 No of pallets in layout - 2048 | E63: As per Quotation | F63: 1 set | G63: 10035146
B64: 3 | C64: Storage racks | D64: Size 1200X1000X150 mm Load Capacity - 1500 kgs | E64: 1 | F64: nos | G64: 5708.025
B65: 4 | C65: Plastic Bins | D65: 1200x1000x775 mm | E65: 3200 | F65: Lump Sum as per FFT offer | G65: 28800000
B66: 5 | C66: Super Jumbo Crates | D66: 810x568x425 mm | E66: 4500 | F66: nos | G66: 9450000
B67: 6 | C67: Plastic Crates | D67: 595x395x256 mm | E67: 20000 | F67: nos | G67: 6000000
B68: Electrical Equipments
B69: Sr No. | C69: Items | D69: Description | E69: Quantity | F69: Unit | G69: Total Amount (INR)
D70: 500 KVA Transformer with OLTC 22 KV/433 V, Outdoor | E70: 1 | F70: nos | G70: 830000
D71: Supply Erection and Fixing of 22 KV 2P structure | E71: 1 | F71: set | G71: 293000
D72: Supply, Fabrication & Erection of Substation Yard Fencing | E72: 1 | F72: set | G72: 81000
D73: Supply & Erection of 100/% A NI CT with MS Enclosure | E73: 1 | F73: nos | G73: 3500
D74: OLTC Panel | E74: 1 | F74: nos | G74: 2000
D75: Metering Box with wiring set | E75: 1 | F75: nos | G75: 15250
D76: Load Break Switch | E76: 1 | F76: nos | G76: 219000
D77: Supply, Erection & Commissioning | E77: 1 | F77: nos | G77: 607500
D78: Supply, Erection & Commissioning of LSB made comprising of 125A TPN SFU-1 NO as Incomer and 63A TPN SFU - 6 Nos as outgoing | E78: 2 | F78: nos | G78: 43400
D79: Supply, Erection& Commissioning of LDB made comprising of 32 A DB MCB - 1 No as Incomer and 6A SP MCB - 8 Nos as outgoing | E79: 6 | F79: nos | G79: 19200
D80: Supply Erection & Commissioning of MCB DB made up of 16SWG CRCA | E80: 3 | F80: nos | G80: 31050
D81: Supply, Erection & Commissioning of 100 KVAR APFC Panel | E81: 1 | F81: nos | G81: 251000
... D92: 3 C X 1.5 sqmm Cu Arm Cable (between LDB & Street Lights) | E92: 750 | F92: meter | G92: 56250
B93: 5 | C93: Supply & Erection of End Termination | D93: 22 KV X 185 sqmm Outdoor Cable Joints kit | E93: 3 | F93: nos | G93: 59700
D94: 22 KV X 185 sqmm Indoor Cable Joints kit | E94: 3 | F94: nos | G94: 42000
D95: 3.5 C X 400 sqmm | E95: 6 | F95: nos | G95: 9390
D96: 3.5 C X 240 sqmm | E96: 8 | F96: nos | G96: 9120
D97: 3.5 C X 185 sqmm | E97: 10 | F97: nos | G97: 8250
D98: 3.5 C X 35 sqmm | E98: 8 | F98: nos | G98: 2400
D99: 4 C X 10 sqmm | E99: 60 | F99: nos | G99: 16200
D100: 2C X 4 sqmm | E100: 16 | F100: nos | G100: 1920
D101: 19 C X 1.5sqmm | E101: 2 | F101: nos | G101: 380
D102: 3 C X 2.5sqmm , 3 C X 1.5 sqmm | E102: 60 | F102: nos | G102: 6300
B103: 6 | C103: Earthing | D103: Earth Electrode for Transformer & MV Panel, SSB, Genset & Plant Earthing | E103: 18 | F103: nos | G103: 78300
D104: 25 X 6 mm Cu Flat for Transformer Neutral Earthing | E104: 75 | F104: nos | G104: 51750
D105: 25 X 3 mm Cu Flat for Transformer, MV Panel, SSB & Plant Body Earthing | E105: 650 | F105: nos | G105: 254800
D106: No 8 SWG Copper | E106: 300 | F106: nos | G106: 19200
D107: No 10 SWG Copper | E107: 200 | F107: nos | G107: 10400
D108: No 18 SWG Copper | E108: 25 | F108: nos | G108: 750
D109: Supply & Erection of Earth Bus with 25X3 CU Flat and Bolt, Nut etc. | E109: 5 | F109: nos | G109: 2125
B110: 7 | C110: Miscellaneous | D110: Metal Halide Lamp with fitting include post (Outdoor) - 250 W | E110: 6 | F110: nos | G110: 70500
D111: Metal Halide Lamp with fitting with GI Bend Pipe 3'X11/2" - 250 W | E111: 9 | F111: nos | G111: 46800
D112: CFL Street light fitting with lamp & pipe support - (1X36 W) | E112: 3 | F112: nos | G112: 5550
D113: 36 W CFL Street light fitting, lamp with 15' height . 21/2' below the ground level GI Pipe Post, Bend | E113: 17 | F113: nos | G113: 77350
...

Sheet Sheet5
C3: Year | D3: 1 | E3: 2 | F3: 3 | G3: 4 | H3: 5 | I3: 6 | J3: 7 | K3: 8 | L3: 9 | M3: 10
C4: Capacity Utilization | D4: 0.7 | E4: 0.8 | F4: 0.9 | G4: 0.95 | H4: 0.95 | I4: 0.95 | J4: 0.95 | K4: 0.95 | L4: 0.95 | M4: 0.95
C5: Revenue
C6: Sale of Product | D6: 3085.11 | E6: 3525.84 | F6: 3966.57 | G6: 4186.935 | H6: 4186.935 | I6: 4186.935 | J6: 4186.935 | K6: 4186.935 | L6: 4186.935 | M6: 4186.935
C7: Rental - spare capacity | D7: 31.85 | E7: 36.4 | F7: 40.95 | G7: 43.225 | H7: 43.225 | I7: 43.225 | J7: 43.225 | K7: 43.225 | L7: 43.225 | M7: 43.225
C8: Rental- Ripening Chambers | D8: 0 | E8: 0 | F8: 0 | G8: 0 | H8: 0 | I8: 0 | J8: 0 | K8: 0 | L8: 0 | M8: 0
C9: Rental-Sorting/ grading/ packing | D9: 0 | E9: 0 | F9: 0 | G9: 0 | H9: 0 | I9: 0 | J9: 0 | K9: 0 | L9: 0 | M9: 0
C10: Revenue | D10: 3116.96 | E10: 3562.24 | F10: 4007.52 | G10: 4230.16 | H10: 4230.16 | I10: 4230.16 | J10: 4230.16 | K10: 4230.16 | L10: 4230.16 | M10: 4230.16
C12: Expenses
C13: Raw material Cost | D13: 1733.3289 | E13: 1980.9474 | F13: 2228.5658 | G13: 2352.375 | H13: 2352.375 | I13: 2352.375 | J13: 2352.375 | K13: 2352.375 | L13: 2352.375 | M13: 2352.375
C14: Other expenses like ripening costs etc. | D14: 10.08 | E14: 11.52 | F14: 12.96 | G14: 13.68 | H14: 13.68 | I14: 13.68 | J14: 13.68 | K14: 13.68 | L14: 13.68 | M14: 13.68
C15: Power & Fuel | D15: 23.2428 | E15: 26.5632 | F15: 29.8836 | G15: 31.5438 | H15: 31.5438 | I15: 31.5438 | J15: 31.5438 | K15: 31.5438 | L15: 31.5438 | M15: 31.5438
C16: Employee Cost | D16: 66.36 | E16: 69.678 | F16: 73.1619 | G16: 76.819995 | H16: 80.660995 | I16: 84.694044 | J16: 84.694044 | K16: 84.694044 | L16: 84.694044 | M16: 84.694044
C17: Direct Labour | D17: 18.69 | E17: 21.36 | F17: 24.03 | G17: 25.365 | H17: 25.365 | I17: 25.365 | J17: 25.365 | K17: 25.365 | L17: 25.365 | M17: 25.365
C18: Packaging cost | D18: 0 | E18: 0 | F18: 0 | G18: 0 | H18: 0 | I18: 0 | J18: 0 | K18: 0 | L18: 0 | M18: 0
C19: Transport Cost | D19: 281.93661 | E19: 322.21326 | F19: 362.48992 | G19: 382.62825 | H19: 382.62825 | I19: 382.62825 | J19: 382.62825 | K19: 382.62825 | L19: 382.62825 | M19: 382.62825
C20: Insurance | D20: 20.097853 | E20: 17.151321 | F20: 14.643361 | G20: 12.508359 | H20: 10.690532 | I20: 9.1424571 | J20: 7.8238185 | K20: 6.7003393 | L20: 5.7428772 | M20: 4.926655
C21: Rent Collection centres | D21: 0.3 | E21: 0.3 | F21: 0.3 | G21: 0.3 | H21: 0.3 | I21: 0.36 | J21: 0.36 | K21: 0.36 | L21: 0.36 | M21: 0.36
C22: Contingency | D22: 15.5848 | E22: 17.8112 | F22: 20.0376 | G22: 21.1508 | H22: 21.1508 | I22: 21.1508 | J22: 21.1508 | K22: 21.1508 | L22: 21.1508 | M22: 21.1508
C23: Total Expenses | D23: 2169.621 | E23: 2467.5444 | F23: 2766.0722 | G23: 2916.3712 | H23: 2918.3944 | I23: 2920.9394 | J23: 2919.6207 | K23: 2918.4972 | L23: 2917.5398 | M23: 2916.7235
C25: EBITDA | D25: 947.33899 | E25: 1094.6956 | F25: 1241.4478 | G25: 1313.7888 | H25: 1311.7656 | I25: 1309.2206 | J25: 1310.5393 | K25: 1311.6628 | L25: 1312.6202 | M25: 1313.4365
... C33: Net Cash from Operations | D33: 661.3885 | E33: 741.93736 | F33: 831.03665 | G33: 874.7405 | H33: 872.74575 | I33: 872.01845 | J33: 875.21189 | K33: 875.64599 | L33: 870.63509 | M33: 866.37314

Sheet Sheet6
C2: Year | D2: 1 | E2: 2 | F2: 3 | G2: 4 | H2: 5 | I2: 6 | J2: 7 | K2: 8 | L2: 9 | M2: 10
C3: EBITDA Margin | D3: 0.30393043 | E3: 0.30730542 | F3: 0.30977957 | G3: 0.31057662 | H3: 0.31009835 | I3: 0.30949672 | J3: 0.30980844 | K3: 0.31007403 | L3: 0.31030037 | M3: 0.31049333
C4: PAT margin | D4: 0.148276 | E4: 0.15235336 | F4: 0.15765823 | G4: 0.15969192 | H4: 0.15922036 | I4: 0.15904843 | J4: 0.15980335 | K4: 0.15990598 | L4: 0.15872141 | M4: 0.17169388
C5: Debt-Equity Ratio | D5: 0.36434252 | E5: 0.24344625 | F5: 0.15824629 | G5: 0.098868056 | H5: 0.056505271 | I5: 0.024727423 | J5: 0 | K5: 0 | L5: 0 | M5: 0
C6: Debt to EBITDA ratio | D6: 1.1351509 | E6: 0.89648514 | F6: 0.71479766 | G6: 0.58892278 | H6: 0.48818692 | I6: 0.38729414 | J6: 0.28516517 | K6: 0.28492092 | L6: 0.28471309 | M6: 0.28453615
C7: Interest Coverage Ratio | D7: 7.6603489 | E7: 8.9405353 | F7: 11.120846 | G7: 13.329682 | H7: 15.761144 | I7: 19.283166 | J7: 24.933611 | K7: 30.519529 | L7: 30.541807 | M7: 30.560799
C8: DSCR | D8: 7.6603489 | E8: 4.2799135 | F8: 5.0678409 | G8: 5.6654594 | H8: 6.0572527 | I8: 6.5061613 | J8: 7.0499095 | K8: 30.519529 | L8: 30.541807 | M8: 30.560799
C9: Average DSCR | D9: 5.8416944

Sheet Sheet7
C3: Cash flow statement
C4: Year | D4: 0 | E4: 1 | F4: 2 | G4: 3 | H4: 4 | I4: 5 | J4: 6 | K4: 7 | L4: 8 | M4: 9 | N4: 10
C5: Sources
C6: Cash from Operations
C7: PAT | E7: 462.17037 | F7: 542.71922 | G7: 631.81851 | H7: 675.52237 | I7: 673.52762 | J7: 672.80032 | K7: 675.99376 | L7: 676.42786 | M7: 671.41695 | N7: 726.2926
C8: Add Depreciation | E8: 199.21814 | F8: 199.21814 | G8: 199.21814 | H8: 199.21814 | I8: 199.21814 | J8: 199.21814 | K8: 199.21814 | L8: 199.21814 | M8: 199.21814 | N8: 140.08053
C9: Net Cash from Operations | E9: 661.3885 | F9: 741.93736 | G9: 831.03665 | H9: 874.7405 | I9: 872.74575 | J9: 872.01845 | K9: 875.21189 | L9: 875.64599 | M9: 870.63509 | N9: 866.37314
C11: Cash From Financing
C12: Equity | D12: 733.56569
C13: Grant | D13: 1000
C14: Term Loan | D14: 800
C15: Increase in Working Capital Borrowing | D15: 0 | E15: 275.37275 | F15: 39.338964 | G15: 39.338964 | H15: 19.669482 | I15: 0 | J15: 0 | K15: 0 | L15: 0 | M15: 0 | N15: 0
C16: Total Cash inflow | D16: 2533.5657 | E16: 936.76125 | F16: 781.27632 | G16: 870.37561 | H16: 894.40999 | I16: 872.74575 | J16: 872.01845 | K16: 875.21189 | L16: 875.64599 | M16: 870.63509 | N16: 866.37314
C18: Uses
C19: Capital expenditure | D19: 2441.7748
C20: Increase in Working capital | E20: 367.16366 | F20: 52.451952 | G20: 52.451952 | H20: 26.225976 | I20: 0 | J20: 0 | K20: 0 | L20: 0 | M20: 0 | N20: 0
C21: Repayment of principal | E21: 0 | F21: 133.33333 | G21: 133.33333 | H21: 133.33333 | I21: 133.33333 | J21: 133.33333 | K21: 133.33333 | L21: 0 | M21: 0 | N21: 0
C22: Total Uses | D22: 2441.7748 | E22: 367.16366 | F22: 185.78529 | G22: 185.78529 | H22: 159.55931 | I22: 133.33333 | J22: 133.33333 | K22: 133.33333 | L22: 0 | M22: 0 | N22: 0
C24: Opening Cash Balance | D24: 0 | E24: 91.790916 | F24: 661.3885 | G24: 1256.8795 | H24: 1941.4699 | I24: 2676.3205 | J24: 3415.733 | K24: 4154.4181 | L24: 4896.2966 | M24: 5771.9426 | N24: 6642.5777
C25: Surplus/ Deficit | D25: 91.790916 | E25: 569.59759 | F25: 595.49104 | G25: 684.59032 | H25: 734.85068 | I25: 739.41242 | J25: 738.68512 | K25: 741.87856 | L25: 875.64599 | M25: 870.63509 | N25: 866.37314
C26: Closing Cash Balance | D26: 91.790916 | E26: 661.3885 | F26: 1256.8795 | G26: 1941.4699 | H26: 2676.3205 | I26: 3415.733 | J26: 4154.4181 | K26: 4896.2966 | L26: 5771.9426 | M26: 6642.5777 | N26: 7508.9509

Sheet Sheet8
C3: Year | D3: 0 | E3: 1 | F3: 2 | G3: 3 | H3: 4 | I3: 5 | J3: 6 | K3: 7 | L3: 8 | M3: 9 | N3: 10
C4: Liabitilies
C5: Equity Capital | D5: 733.56569 | E5: 733.56569 | F5: 733.56569 | G5: 733.56569 | H5: 733.56569 | I5: 733.56569 | J5: 733.56569 | K5: 733.56569 | L5: 733.56569 | M5: 733.56569 | N5: 733.56569
C6: Reserve & Surplus | D6: 0 | E6: 462.17037 | F6: 1004.8896 | G6: 1636.7081 | H6: 2312.2305 | I6: 2985.7581 | J6: 3658.5584 | K6: 4334.5522 | L6: 5010.98 | M6: 5682.397 | N6: 6408.6896
C7: Grant/ Subsidy | D7: 1000 | E7: 1000 | F7: 1000 | G7: 1000 | H7: 1000 | I7: 1000 | J7: 1000 | K7: 1000 | L7: 1000 | M7: 1000 | N7: 1000
C8: Net Worth | D8: 1733.5657 | E8: 2195.7361 | F8: 2738.4553 | G8: 3370.2738 | H8: 4045.7962 | I8: 4719.3238 | J8: 5392.1241 | K8: 6068.1178 | L8: 6744.5457 | M8: 7415.9627 | N8: 8142.2553
C9: Term Loan | D9: 800 | E9: 800 | F9: 666.66667 | G9: 533.33333 | H9: 400 | I9: 266.66667 | J9: 133.33333 | K9: 0 | L9: 0 | M9: 0 | N9: 0
C10: Working Capital Loan | D10: 0 | E10: 275.37275 | F10: 314.71171 | G10: 354.05067 | H10: 373.72016 | I10: 373.72016 | J10: 373.72016 | K10: 373.72016 | L10: 373.72016 | M10: 373.72016 | N10: 373.72016
C11: Total Liabilities | D11: 2533.5657 | E11: 3271.1088 | F11: 3719.8337 | G11: 4257.6578 | H11: 4819.5163 | I11: 5359.7106 | J11: 5899.1776 | K11: 6441.838 | L11: 7118.2659 | M11: 7789.6828 | N11: 8515.9754
C13: Assets
C14: Gross Fixed Assets | D14: 2441.7748 | E14: 2441.7748 | F14: 2441.7748 | G14: 2441.7748 | H14: 2441.7748 | I14: 2441.7748 | J14: 2441.7748 | K14: 2441.7748 | L14: 2441.7748 | M14: 2441.7748 | N14: 2441.7748
C15: Less Accumulated Dep. | D15: 0 | E15: 199.21814 | F15: 398.43627 | G15: 597.65441 | H15: 796.87254 | I15: 996.09068 | J15: 1195.3088 | K15: 1394.5269 | L15: 1593.7451 | M15: 1792.9632 | N15: 1933.0438
C16: Net Fixed Assets | D16: 2441.7748 | E16: 2242.5566 | F16: 2043.3385 | G16: 1844.1204 | H16: 1644.9022 | I16: 1445.6841 | J16: 1246.466 | K16: 1047.2478 | L16: 848.02969 | M16: 648.81155 | N16: 508.73102
C17: Working Capital | D17: 0 | E17: 367.16366 | F17: 419.61561 | G17: 472.06757 | H17: 498.29354 | I17: 498.29354 | J17: 498.29354 | K17: 498.29354 | L17: 498.29354 | M17: 498.29354 | N17: 498.29354
C18: Cash Bal | D18: 91.790916 | E18: 661.3885 | F18: 1256.8795 | G18: 1941.4699 | H18: 2676.3205 | I18: 3415.733 | J18: 4154.4181 | K18: 4896.2966 | L18: 5771.9426 | M18: 6642.5777 | N18: 7508.9509
C19: Total Assets | D19: 2533.5657 | E19: 3271.1088 | F19: 3719.8337 | G19: 4257.6578 | H19: 4819.5163 | I19: 5359.7106 | J19: 5899.1776 | K19: 6441.838 | L19: 7118.2659 | M19: 7789.6828 | N19: 8515.9754
