Workbook

Sheet 00_Cover
B1: 3 Fermes Incubatrices · Financial Model L1 v11
B3: Built via xlsx_build/ framework (declarative TabSpec + procedural helpers)
B5: MODEL STATUS | C5: =IF('18_Validation'!M29=0,"ALL CHECKS PASS","CHECKS FAILING") -> ALL CHECKS PASS | D5: ='18_Validation'!M29&" total fails" -> 0 total fails
B7: Check | C7: Description | D7: Fails
B8: L1 | C8: S&U balance | D8: ='18_Validation'!M6 -> 0
B9: L2 | C9: CWIP zero at COD | D9: ='18_Validation'!M7 -> 0
B10: L3 | C10: Book NBV ≥ 0 | D10: ='18_Validation'!M8 -> 0
B11: L4 | C11: DTL ≥ 0 | D11: ='18_Validation'!M9 -> 0
B12: L5 | C12: Debt ≥ 0 | D12: ='18_Validation'!M10 -> 0
B13: L6 | C13: BS balance | D13: ='18_Validation'!M13 -> 0
B14: L7 | C14: Cash floor ≥ 0 | D14: ='18_Validation'!M14 -> 0
B15: L8 | C15: NOL ≥ 0 | D15: ='18_Validation'!M17 -> 0
B16: L9 | C16: DTL closing ≥ 0 | D16: ='18_Validation'!M18 -> 0
B17: L11 | C17: CFS reconciliation | D17: ='18_Validation'!M21 -> 0
B18: L12 | C18: IS EBITDA arithmetic | D18: ='18_Validation'!M24 -> 0
B19: L13 | C19: IS pre-tax consistency | D19: ='18_Validation'!M25 -> 0
B20: L14 | C20: Named range smoke test | D20: ='18_Validation'!M26 -> 0
B22: KPI SNAPSHOT — steady-state (Y6)
B23: Revenue SS | D23: =REV_TOTAL_Y6 -> 1567503
B24: OpEx SS (farming) | D24: =-IS_OPEX_Y6 -> 578623.98
B25: EBITDA SS | D25: =IS_EBITDA_Y6 -> 988879.02
B26: CFADS SS | D26: =CFADS_Y6 -> 988879.02
B27: Debt outstanding Y6 | D27: =DEBT_CLOSE_Y6 -> 1877540.9
B28: Total CAPEX | D28: =CAPEX_TOTAL_YM1+CAPEX_TOTAL_Y0+CAPEX_TOTAL_Y1+CAPEX_TOTAL_Y2+CAPEX_TOTAL_Y3+CAPEX_TOTAL_Y4+CAPEX_TOTAL_Y5+CAPEX_TOTAL_Y6 -> 5566792.4
B30: Note: Senior debt not yet sized — DSCR and returns are indicative only

Sheet 01_Assumptions
B1: 01 — Assumptions
B3: Parameter | C3: Unit | D3: Value
B4: Engine inputs (computed parameters)
B5: Farmers per cooperative farm (filière A) | C5: persons | D5: 40
B6: Water technicians per farm (filière B) | C6: persons | D6: 4
B7: Energy technicians per farm (filière C) | C7: persons | D7: 2
B8: Mechanisation operators per farm (filière D) | C8: persons | D8: 6
B9: Number of cooperative farms — Phase A wave | C9: UOFs | D9: 10
B10: Number of cooperative farms — full programme | C10: UOFs | D10: 50
B11: Bootstrap cohort — number of trainees | C11: persons | D11: 120
B12: Calendar days per month | C12: days | D12: 25
B13: International specialist trainers | C13: persons | D13: 3
B14: International specialist — annual cost | C14: €/yr | D14: 40000
B15: Total beds — Phase A | C15: beds | D15: 135
B16: Resident trainees — Phase A | C16: persons | D16: 135
... B27: USD source — diesel price | C27: USD/L | D27: 1
B29: Programme structure
B30: Number of incubator farms | C30: count | D30: 3
B31: Surface area per farm | C31: ha | D31: 100
B32: Project life (Y-1 → Y6) | C32: years | D32: 8
B33: Commissioning year (COD) | C33: year | D33: 1
B34: Gate evaluation year | C34: year | D34: 2
B35: Training start year | C35: year | D35: 1
B36: Training stop year | C36: year | D36: 2
B37: EUR / USD exchange rate | C37: EUR/USD | D37: 1.1
B39: Training throughput
B40: Simultaneous training slots per farm | C40: persons | D40: 90
B41: Staggered cohorts per farm | C41: cohorts | D41: 2
B42: Trainees per cohort | C42: persons | D42: 45
B43: Annual throughput at steady state | C43: persons/yr | D43: 270
B44: Filière A share — farmers | C44: % | D44: 0.76923077
B45: Filière B share — water technicians | C45: % | D45: 0.076923077
B46: Filière C share — energy technicians | C46: % | D46: 0.038461538
B47: Filière D share — mechanisation operators | C47: % | D47: 0.11538462
B48: Programme target — filière A graduates | C48: persons | D48: 520
B49: Programme target — filière B graduates | C49: persons | D49: 40
B50: Programme target — filière C graduates | C50: persons | D50: 20
B51: Programme target — filière D graduates | C51: persons | D51: 60
B52: Programme target — total graduates | C52: persons | D52: 640
B54: Cost per trainee by filière
B55: Duration — filière A | C55: months | D55: 12
B56: Duration — filière B | C56: months | D56: 9
B57: Duration — filière C | C57: months | D57: 9
B58: Duration — filière D | C58: months | D58: 12
B59: Gross daily stipend | C59: €/day | D59: 7
B60: Productive work offset (from month 4) | C60: €/day | D60: 5
B61: Work offset starts at month | C61: month | D61: 3
B62: Net cost per trainee — filière A | C62: €/person | D62: 850
B63: Net cost per trainee — filière B | C63: €/person | D63: 700
B64: Net cost per trainee — filière C | C64: €/person | D64: 700
B65: Net cost per trainee — filière D | C65: €/person | D65: 850
B67: Trainer team
B68: Filière trainers (12 per farm × 3 farms) | C68: persons | D68: 12
B69: Specialist trainers (shared pool) | C69: persons | D69: 4
B70: Total trainers | C70: persons | D70: 16
B71: Filière trainer — annual cost | C71: €/yr | D71: 20000
B72: Specialist trainer — annual cost | C72: €/yr | D72: 40000
B73: Filière trainers active years | C73: years | D73: 2
B74: Specialist trainers active years | C74: years | D74: 2
B75: Train-the-Trainer duration | C75: years | D75: 1
B76: Train-the-Trainer cost per trainer per year | C76: €/trainer-yr | D76: 18000
B77: International specialist experts (one-time) | C77: € | D77: 120000
B79: Agriculture & livestock
B80: Monitoring plots (% of farm area) | C80: % | D80: 0.3
B81: Pedagogical plots (% of farm area) | C81: % | D81: 0.55
B82: Infrastructure & housing (% of farm area) | C82: % | D82: 0.15
B83: Market garden surface per farm | C83: ha | D83: 25
B84: Cereal surface per farm | C84: ha | D84: 50
B85: Agroforestry surface per farm | C85: ha | D85: 5
B86: Market garden harvest cycles per year | C86: cycles/yr | D86: 3
B87: Dairy herd per farm | C87: heads | D87: 30
B88: Dairy yield per cow | C88: L/yr | D88: 5600
B89: Beef stock per farm (average) | C89: heads | D89: 75
B90: Beef offtake rate | C90: % | D90: 0.8
B91: Average liveweight at sale | C91: kg | D91: 280
... B105: Alfalfa transfer price | C105: €/t DM | D105: 200
B107: Housing
B108: Standard farm staff per farm | C108: persons | D108: 40
B109: Additional trainee beds per farm | C109: beds | D109: 45
B110: Dormitory cost per bed | C110: €/bed | D110: 2200
B111: Refectory & common areas per farm | C111: € | D111: 16000
B112: Residents requiring family housing | C112: % | D112: 0.15
B113: Family housing units (programme) | C113: units | D113: 20
B114: Family housing cost per unit | C114: €/unit | D114: 2000
B116: Pre-programme set-up (Y-1)
B117: Curriculum design + certification partner | C117: € | D117: 220000
B118: Classroom equipment per farm | C118: € | D118: 45000
B119: Plateau eau (filière B) | C119: € | D119: 60000
B120: Plateau PV (filière C) | C120: € | D120: 50000
B121: Atelier méca (filière D) | C121: € | D121: 60000
B122: Classroom / IT / communications | C122: € | D122: 40000
B123: Number of filière curricula | C123: count | D123: 2
B124: Curriculum materials per filière | C124: € | D124: 25000
B126: Monitoring, certification, communication
B127: Certification partner (set-up + 5 years) | C127: € | D127: 0
B128: Monitoring equipment (plots) | C128: € | D128: 60000
B129: Data coordinator — annual | C129: €/yr | D129: 40000
B130: Monitoring years (Y1 → Y6) | C130: years | D130: 2
B131: Communication materials | C131: € | D131: 20000
B132: Communication officer — annual | C132: €/yr | D132: 15000
...

Sheet 02_Timeline
B1: 02 — Timeline / Programme state
D3: Total | E3: Y-1 | F3: Y0 | G3: Y1 | H3: Y2 | I3: Y3 | J3: Y4 | K3: Y5 | L3: Y6
E4: -1 | F4: 0 | G4: 1 | H4: 2 | I4: 3 | J4: 4 | K4: 5 | L4: 6
B7: Programme phase
B8: Pre-programme (Y-1) | C8: flag | D8: =SUM(E8:L8) -> 1 | E8: =IF(E$4=-1,1,0) -> 1 | F8: =IF(F$4=-1,1,0) -> 0 | G8: =IF(G$4=-1,1,0) -> 0 | H8: =IF(H$4=-1,1,0) -> 0 | I8: =IF(I$4=-1,1,0) -> 0 | J8: =IF(J$4=-1,1,0) -> 0 | K8: =IF(K$4=-1,1,0) -> 0 | L8: =IF(L$4=-1,1,0) -> 0
B9: Construction (Y0) | C9: flag | D9: =SUM(E9:L9) -> 1 | E9: =IF(E$4=0,1,0) -> 0 | F9: =IF(F$4=0,1,0) -> 1 | G9: =IF(G$4=0,1,0) -> 0 | H9: =IF(H$4=0,1,0) -> 0 | I9: =IF(I$4=0,1,0) -> 0 | J9: =IF(J$4=0,1,0) -> 0 | K9: =IF(K$4=0,1,0) -> 0 | L9: =IF(L$4=0,1,0) -> 0
B10: Phase A — training (Y1-Y2) | C10: flag | D10: =SUM(E10:L10) -> 2 | E10: =IF(AND(E$4>=ASM_A06_TRAINING_START_YEAR,E$4<=ASM_A07_TRAINING_STOP_YEAR),1,0) -> 0 | F10: =IF(AND(F$4>=ASM_A06_TRAINING_START_YEAR,F$4<=ASM_A07_TRAINING_STOP_YEAR),1,0) -> 0 | G10: =IF(AND(G$4>=ASM_A06_TRAINING_START_YEAR,G$4<=ASM_A07_TRAINING_STOP_YEAR),1,0) -> 1 | H10: =IF(AND(H$4>=ASM_A06_TRAINING_START_YEAR,H$4<=ASM_A07_TRAINING_STOP_YEAR),1,0) -> 1 | I10: =IF(AND(I$4>=ASM_A06_TRAINING_START_YEAR,I$4<=ASM_A07_TRAINING_STOP_YEAR),1,0) -> 0 | J10: =IF(AND(J$4>=ASM_A06_TRAINING_START_YEAR,J$4<=ASM_A07_TRAINING_STOP_YEAR),1,0) -> 0 | K10: =IF(AND(K$4>=ASM_A06_TRAINING_START_YEAR,K$4<=ASM_A07_TRAINING_STOP_YEAR),1,0) -> 0 | L10: =IF(AND(L$4>=ASM_A06_TRAINING_START_YEAR,L$4<=ASM_A07_TRAINING_STOP_YEAR),1,0) -> 0
B11: Deployment support (Y3+) | C11: flag | D11: =SUM(E11:L11) -> 4 | E11: =IF(E$4>ASM_A07_TRAINING_STOP_YEAR,1,0) -> 0 | F11: =IF(F$4>ASM_A07_TRAINING_STOP_YEAR,1,0) -> 0 | G11: =IF(G$4>ASM_A07_TRAINING_STOP_YEAR,1,0) -> 0 | H11: =IF(H$4>ASM_A07_TRAINING_STOP_YEAR,1,0) -> 0 | I11: =IF(I$4>ASM_A07_TRAINING_STOP_YEAR,1,0) -> 1 | J11: =IF(J$4>ASM_A07_TRAINING_STOP_YEAR,1,0) -> 1 | K11: =IF(K$4>ASM_A07_TRAINING_STOP_YEAR,1,0) -> 1 | L11: =IF(L$4>ASM_A07_TRAINING_STOP_YEAR,1,0) -> 1
B12: Post-commissioning operations (Y1+) | C12: flag | D12: =SUM(E12:L12) -> 6 | E12: =IF(E$4>=ASM_A04_COD_YEAR,1,0) -> 0 | F12: =IF(F$4>=ASM_A04_COD_YEAR,1,0) -> 0 | G12: =IF(G$4>=ASM_A04_COD_YEAR,1,0) -> 1 | H12: =IF(H$4>=ASM_A04_COD_YEAR,1,0) -> 1 | I12: =IF(I$4>=ASM_A04_COD_YEAR,1,0) -> 1 | J12: =IF(J$4>=ASM_A04_COD_YEAR,1,0) -> 1 | K12: =IF(K$4>=ASM_A04_COD_YEAR,1,0) -> 1 | L12: =IF(L$4>=ASM_A04_COD_YEAR,1,0) -> 1
B14: O2 — Production & operations
B15: Farms operational | C15: count | D15: =SUM(E15:L15) -> 18 | E15: =IF(E$4>=ASM_A04_COD_YEAR,ASM_A01_N_FARMS,0) -> 0 | F15: =IF(F$4>=ASM_A04_COD_YEAR,ASM_A01_N_FARMS,0) -> 0 | G15: =IF(G$4>=ASM_A04_COD_YEAR,ASM_A01_N_FARMS,0) -> 3 | H15: =IF(H$4>=ASM_A04_COD_YEAR,ASM_A01_N_FARMS,0) -> 3 | I15: =IF(I$4>=ASM_A04_COD_YEAR,ASM_A01_N_FARMS,0) -> 3 | J15: =IF(J$4>=ASM_A04_COD_YEAR,ASM_A01_N_FARMS,0) -> 3 | K15: =IF(K$4>=ASM_A04_COD_YEAR,ASM_A01_N_FARMS,0) -> 3 | L15: =IF(L$4>=ASM_A04_COD_YEAR,ASM_A01_N_FARMS,0) -> 3
B16: Farms in construction | C16: count | D16: =SUM(E16:L16) -> 3 | E16: =IF(E$4=0,ASM_A01_N_FARMS,0) -> 0 | F16: =IF(F$4=0,ASM_A01_N_FARMS,0) -> 3 | G16: =IF(G$4=0,ASM_A01_N_FARMS,0) -> 0 | H16: =IF(H$4=0,ASM_A01_N_FARMS,0) -> 0 | I16: =IF(I$4=0,ASM_A01_N_FARMS,0) -> 0 | J16: =IF(J$4=0,ASM_A01_N_FARMS,0) -> 0 | K16: =IF(K$4=0,ASM_A01_N_FARMS,0) -> 0 | L16: =IF(L$4=0,ASM_A01_N_FARMS,0) -> 0
B17: Production flag | C17: % SS | D17: =SUM(E17:L17) -> 5.15 | E17: =IF(E$4<ASM_A04_COD_YEAR,0,IF(E$4=ASM_A04_COD_YEAR,ASM_E20_RAMP_Y1_PCT,IF(E$4=ASM_A04_COD_YEAR+1,ASM_E21_RAMP_Y2_PCT,1))) -> 0 | F17: =IF(F$4<ASM_A04_COD_YEAR,0,IF(F$4=ASM_A04_COD_YEAR,ASM_E20_RAMP_Y1_PCT,IF(F$4=ASM_A04_COD_YEAR+1,ASM_E21_RAMP_Y2_PCT,1))) -> 0 | G17: =IF(G$4<ASM_A04_COD_YEAR,0,IF(G$4=ASM_A04_COD_YEAR,ASM_E20_RAMP_Y1_PCT,IF(G$4=ASM_A04_COD_YEAR+1,ASM_E21_RAMP_Y2_PCT,1))) -> 0.4 | H17: =IF(H$4<ASM_A04_COD_YEAR,0,IF(H$4=ASM_A04_COD_YEAR,ASM_E20_RAMP_Y1_PCT,IF(H$4=ASM_A04_COD_YEAR+1,ASM_E21_RAMP_Y2_PCT,1))) -> 0.75 | I17: =IF(I$4<ASM_A04_COD_YEAR,0,IF(I$4=ASM_A04_COD_YEAR,ASM_E20_RAMP_Y1_PCT,IF(I$4=ASM_A04_COD_YEAR+1,ASM_E21_RAMP_Y2_PCT,1))) -> 1 | J17: =IF(J$4<ASM_A04_COD_YEAR,0,IF(J$4=ASM_A04_COD_YEAR,ASM_E20_RAMP_Y1_PCT,IF(J$4=ASM_A04_COD_YEAR+1,ASM_E21_RAMP_Y2_PCT,1))) -> 1 | K17: =IF(K$4<ASM_A04_COD_YEAR,0,IF(K$4=ASM_A04_COD_YEAR,ASM_E20_RAMP_Y1_PCT,IF(K$4=ASM_A04_COD_YEAR+1,ASM_E21_RAMP_Y2_PCT,1))) -> 1 | L17: =IF(L$4<ASM_A04_COD_YEAR,0,IF(L$4=ASM_A04_COD_YEAR,ASM_E20_RAMP_Y1_PCT,IF(L$4=ASM_A04_COD_YEAR+1,ASM_E21_RAMP_Y2_PCT,1))) -> 1
B19: O1 — Training throughput (residents in year)
B20: Filière A — farmers | C20: persons | D20: =SUM(E20:L20) -> 416 | E20: =IF(AND(E$4>=ASM_A06_TRAINING_START_YEAR,E$4<=ASM_A07_TRAINING_STOP_YEAR),ROUND(ASM_B04_THROUGHPUT_ANNUAL*ASM_B05_PCT_FILIERE_A,0),0) -> 0 | F20: =IF(AND(F$4>=ASM_A06_TRAINING_START_YEAR,F$4<=ASM_A07_TRAINING_STOP_YEAR),ROUND(ASM_B04_THROUGHPUT_ANNUAL*ASM_B05_PCT_FILIERE_A,0),0) -> 0 | G20: =IF(AND(G$4>=ASM_A06_TRAINING_START_YEAR,G$4<=ASM_A07_TRAINING_STOP_YEAR),ROUND(ASM_B04_THROUGHPUT_ANNUAL*ASM_B05_PCT_FILIERE_A,0),0) -> 208 | H20: =IF(AND(H$4>=ASM_A06_TRAINING_START_YEAR,H$4<=ASM_A07_TRAINING_STOP_YEAR),ROUND(ASM_B04_THROUGHPUT_ANNUAL*ASM_B05_PCT_FILIERE_A,0),0) -> 208 | I20: =IF(AND(I$4>=ASM_A06_TRAINING_START_YEAR,I$4<=ASM_A07_TRAINING_STOP_YEAR),ROUND(ASM_B04_THROUGHPUT_ANNUAL*ASM_B05_PCT_FILIERE_A,0),0) -> 0 | J20: =IF(AND(J$4>=ASM_A06_TRAINING_START_YEAR,J$4<=ASM_A07_TRAINING_STOP_YEAR),ROUND(ASM_B04_THROUGHPUT_ANNUAL*ASM_B05_PCT_FILIERE_A,0),0) -> 0 | K20: =IF(AND(K$4>=ASM_A06_TRAINING_START_YEAR,K$4<=ASM_A07_TRAINING_STOP_YEAR),ROUND(ASM_B04_THROUGHPUT_ANNUAL*ASM_B05_PCT_FILIERE_A,0),0) -> 0 | L20: =IF(AND(L$4>=ASM_A06_TRAINING_START_YEAR,L$4<=ASM_A07_TRAINING_STOP_YEAR),ROUND(ASM_B04_THROUGHPUT_ANNUAL*ASM_B05_PCT_FILIERE_A,0),0) -> 0
B21: Filière B — water technicians | C21: persons | D21: =SUM(E21:L21) -> 42 | E21: =IF(AND(E$4>=ASM_A06_TRAINING_START_YEAR,E$4<=ASM_A07_TRAINING_STOP_YEAR),ROUND(ASM_B04_THROUGHPUT_ANNUAL*ASM_B06_PCT_FILIERE_B,0),0) -> 0 | F21: =IF(AND(F$4>=ASM_A06_TRAINING_START_YEAR,F$4<=ASM_A07_TRAINING_STOP_YEAR),ROUND(ASM_B04_THROUGHPUT_ANNUAL*ASM_B06_PCT_FILIERE_B,0),0) -> 0 | G21: =IF(AND(G$4>=ASM_A06_TRAINING_START_YEAR,G$4<=ASM_A07_TRAINING_STOP_YEAR),ROUND(ASM_B04_THROUGHPUT_ANNUAL*ASM_B06_PCT_FILIERE_B,0),0) -> 21 | H21: =IF(AND(H$4>=ASM_A06_TRAINING_START_YEAR,H$4<=ASM_A07_TRAINING_STOP_YEAR),ROUND(ASM_B04_THROUGHPUT_ANNUAL*ASM_B06_PCT_FILIERE_B,0),0) -> 21 | I21: =IF(AND(I$4>=ASM_A06_TRAINING_START_YEAR,I$4<=ASM_A07_TRAINING_STOP_YEAR),ROUND(ASM_B04_THROUGHPUT_ANNUAL*ASM_B06_PCT_FILIERE_B,0),0) -> 0 | J21: =IF(AND(J$4>=ASM_A06_TRAINING_START_YEAR,J$4<=ASM_A07_TRAINING_STOP_YEAR),ROUND(ASM_B04_THROUGHPUT_ANNUAL*ASM_B06_PCT_FILIERE_B,0),0) -> 0 | K21: =IF(AND(K$4>=ASM_A06_TRAINING_START_YEAR,K$4<=ASM_A07_TRAINING_STOP_YEAR),ROUND(ASM_B04_THROUGHPUT_ANNUAL*ASM_B06_PCT_FILIERE_B,0),0) -> 0 | L21: =IF(AND(L$4>=ASM_A06_TRAINING_START_YEAR,L$4<=ASM_A07_TRAINING_STOP_YEAR),ROUND(ASM_B04_THROUGHPUT_ANNUAL*ASM_B06_PCT_FILIERE_B,0),0) -> 0
B22: Filière C — energy technicians | C22: persons | D22: =SUM(E22:L22) -> 20 | E22: =IF(AND(E$4>=ASM_A06_TRAINING_START_YEAR,E$4<=ASM_A07_TRAINING_STOP_YEAR),ROUND(ASM_B04_THROUGHPUT_ANNUAL*ASM_B07_PCT_FILIERE_C,0),0) -> 0 | F22: =IF(AND(F$4>=ASM_A06_TRAINING_START_YEAR,F$4<=ASM_A07_TRAINING_STOP_YEAR),ROUND(ASM_B04_THROUGHPUT_ANNUAL*ASM_B07_PCT_FILIERE_C,0),0) -> 0 | G22: =IF(AND(G$4>=ASM_A06_TRAINING_START_YEAR,G$4<=ASM_A07_TRAINING_STOP_YEAR),ROUND(ASM_B04_THROUGHPUT_ANNUAL*ASM_B07_PCT_FILIERE_C,0),0) -> 10 | H22: =IF(AND(H$4>=ASM_A06_TRAINING_START_YEAR,H$4<=ASM_A07_TRAINING_STOP_YEAR),ROUND(ASM_B04_THROUGHPUT_ANNUAL*ASM_B07_PCT_FILIERE_C,0),0) -> 10 | I22: =IF(AND(I$4>=ASM_A06_TRAINING_START_YEAR,I$4<=ASM_A07_TRAINING_STOP_YEAR),ROUND(ASM_B04_THROUGHPUT_ANNUAL*ASM_B07_PCT_FILIERE_C,0),0) -> 0 | J22: =IF(AND(J$4>=ASM_A06_TRAINING_START_YEAR,J$4<=ASM_A07_TRAINING_STOP_YEAR),ROUND(ASM_B04_THROUGHPUT_ANNUAL*ASM_B07_PCT_FILIERE_C,0),0) -> 0 | K22: =IF(AND(K$4>=ASM_A06_TRAINING_START_YEAR,K$4<=ASM_A07_TRAINING_STOP_YEAR),ROUND(ASM_B04_THROUGHPUT_ANNUAL*ASM_B07_PCT_FILIERE_C,0),0) -> 0 | L22: =IF(AND(L$4>=ASM_A06_TRAINING_START_YEAR,L$4<=ASM_A07_TRAINING_STOP_YEAR),ROUND(ASM_B04_THROUGHPUT_ANNUAL*ASM_B07_PCT_FILIERE_C,0),0) -> 0
B23: Filière D — mechanisation operators | C23: persons | D23: =SUM(E23:L23) -> 62 | E23: =IF(AND(E$4>=ASM_A06_TRAINING_START_YEAR,E$4<=ASM_A07_TRAINING_STOP_YEAR),ASM_B04_THROUGHPUT_ANNUAL-ROUND(ASM_B04_THROUGHPUT_ANNUAL*ASM_B05_PCT_FILIERE_A,0)-ROUND(ASM_B04_THROUGHPUT_ANNUAL*ASM_B06_PCT_FILIERE_B,0)-ROUND(ASM_B04_THROUGHPUT_ANNUAL*ASM_B07_PCT_FILIERE_C,0),0) -> 0 | F23: =IF(AND(F$4>=ASM_A06_TRAINING_START_YEAR,F$4<=ASM_A07_TRAINING_STOP_YEAR),ASM_B04_THROUGHPUT_ANNUAL-ROUND(ASM_B04_THROUGHPUT_ANNUAL*ASM_B05_PCT_FILIERE_A,0)-ROUND(ASM_B04_THROUGHPUT_ANNUAL*ASM_B06_PCT_FILIERE_B,0)-ROUND(ASM_B04_THROUGHPUT_ANNUAL*ASM_B07_PCT_FILIERE_C,0),0) -> 0 | G23: =IF(AND(G$4>=ASM_A06_TRAINING_START_YEAR,G$4<=ASM_A07_TRAINING_STOP_YEAR),ASM_B04_THROUGHPUT_ANNUAL-ROUND(ASM_B04_THROUGHPUT_ANNUAL*ASM_B05_PCT_FILIERE_A,0)-ROUND(ASM_B04_THROUGHPUT_ANNUAL*ASM_B06_PCT_FILIERE_B,0)-ROUND(ASM_B04_THROUGHPUT_ANNUAL*ASM_B07_PCT_FILIERE_C,0),0) -> 31 | H23: =IF(AND(H$4>=ASM_A06_TRAINING_START_YEAR,H$4<=ASM_A07_TRAINING_STOP_YEAR),ASM_B04_THROUGHPUT_ANNUAL-ROUND(ASM_B04_THROUGHPUT_ANNUAL*ASM_B05_PCT_FILIERE_A,0)-ROUND(ASM_B04_THROUGHPUT_ANNUAL*ASM_B06_PCT_FILIERE_B,0)-ROUND(ASM_B04_THROUGHPUT_ANNUAL*ASM_B07_PCT_FILIERE_C,0),0) -> 31 | I23: =IF(AND(I$4>=ASM_A06_TRAINING_START_YEAR,I$4<=ASM_A07_TRAINING_STOP_YEAR),ASM_B04_THROUGHPUT_ANNUAL-ROUND(ASM_B04_THROUGHPUT_ANNUAL*ASM_B05_PCT_FILIERE_A,0)-ROUND(ASM_B04_THROUGHPUT_ANNUAL*ASM_B06_PCT_FILIERE_B,0)-ROUND(ASM_B04_THROUGHPUT_ANNUAL*ASM_B07_PCT_FILIERE_C,0),0) -> 0 | J23: =IF(AND(J$4>=ASM_A06_TRAINING_START_YEAR,J$4<=ASM_A07_TRAINING_STOP_YEAR),ASM_B04_THROUGHPUT_ANNUAL-ROUND(ASM_B04_THROUGHPUT_ANNUAL*ASM_B05_PCT_FILIERE_A,0)-ROUND(ASM_B04_THROUGHPUT_ANNUAL*ASM_B06_PCT_FILIERE_B,0)-ROUND(ASM_B04_THROUGHPUT_ANNUAL*ASM_B07_PCT_FILIERE_C,0),0) -> 0 | K23: =IF(AND(K$4>=ASM_A06_TRAINING_START_YEAR,K$4<=ASM_A07_TRAINING_STOP_YEAR),ASM_B04_THROUGHPUT_ANNUAL-ROUND(ASM_B04_THROUGHPUT_ANNUAL*ASM_B05_PCT_FILIERE_A,0)-ROUND(ASM_B04_THROUGHPUT_ANNUAL*ASM_B06_PCT_FILIERE_B,0)-ROUND(ASM_B04_THROUGHPUT_ANNUAL*ASM_B07_PCT_FILIERE_C,0),0) -> 0 | L23: =IF(AND(L$4>=ASM_A06_TRAINING_START_YEAR,L$4<=ASM_A07_TRAINING_STOP_YEAR),ASM_B04_THROUGHPUT_ANNUAL-ROUND(ASM_B04_THROUGHPUT_ANNUAL*ASM_B05_PCT_FILIERE_A,0)-ROUND(ASM_B04_THROUGHPUT_ANNUAL*ASM_B06_PCT_FILIERE_B,0)-ROUND(ASM_B04_THROUGHPUT_ANNUAL*ASM_B07_PCT_FILIERE_C,0),0) -> 0
B25: O1 — Cumulative certified (programme running total)
B26: Cumulative certified A — farmers | C26: persons | D26: =SUM(E26:L26) -> 2704 | E26: =IF(E$4>=ASM_A06_TRAINING_START_YEAR,MIN(ROUND(ASM_B04_THROUGHPUT_ANNUAL*ASM_B05_PCT_FILIERE_A,0)*(E$4-ASM_A06_TRAINING_START_YEAR+1),ASM_B09_TARGET_CERTIFIED_A),0) -> 0 | F26: =IF(F$4>=ASM_A06_TRAINING_START_YEAR,MIN(ROUND(ASM_B04_THROUGHPUT_ANNUAL*ASM_B05_PCT_FILIERE_A,0)*(F$4-ASM_A06_TRAINING_START_YEAR+1),ASM_B09_TARGET_CERTIFIED_A),0) -> 0 | G26: =IF(G$4>=ASM_A06_TRAINING_START_YEAR,MIN(ROUND(ASM_B04_THROUGHPUT_ANNUAL*ASM_B05_PCT_FILIERE_A,0)*(G$4-ASM_A06_TRAINING_START_YEAR+1),ASM_B09_TARGET_CERTIFIED_A),0) -> 208 | H26: =IF(H$4>=ASM_A06_TRAINING_START_YEAR,MIN(ROUND(ASM_B04_THROUGHPUT_ANNUAL*ASM_B05_PCT_FILIERE_A,0)*(H$4-ASM_A06_TRAINING_START_YEAR+1),ASM_B09_TARGET_CERTIFIED_A),0) -> 416 | I26: =IF(I$4>=ASM_A06_TRAINING_START_YEAR,MIN(ROUND(ASM_B04_THROUGHPUT_ANNUAL*ASM_B05_PCT_FILIERE_A,0)*(I$4-ASM_A06_TRAINING_START_YEAR+1),ASM_B09_TARGET_CERTIFIED_A),0) -> 520 | J26: =IF(J$4>=ASM_A06_TRAINING_START_YEAR,MIN(ROUND(ASM_B04_THROUGHPUT_ANNUAL*ASM_B05_PCT_FILIERE_A,0)*(J$4-ASM_A06_TRAINING_START_YEAR+1),ASM_B09_TARGET_CERTIFIED_A),0) -> 520 | K26: =IF(K$4>=ASM_A06_TRAINING_START_YEAR,MIN(ROUND(ASM_B04_THROUGHPUT_ANNUAL*ASM_B05_PCT_FILIERE_A,0)*(K$4-ASM_A06_TRAINING_START_YEAR+1),ASM_B09_TARGET_CERTIFIED_A),0) -> 520 | L26: =IF(L$4>=ASM_A06_TRAINING_START_YEAR,MIN(ROUND(ASM_B04_THROUGHPUT_ANNUAL*ASM_B05_PCT_FILIERE_A,0)*(L$4-ASM_A06_TRAINING_START_YEAR+1),ASM_B09_TARGET_CERTIFIED_A),0) -> 520
B27: Cumulative certified B — water technicians | C27: persons | D27: =SUM(E27:L27) -> 221 | E27: =IF(E$4>=ASM_A06_TRAINING_START_YEAR,MIN(ROUND(ASM_B04_THROUGHPUT_ANNUAL*ASM_B06_PCT_FILIERE_B,0)*(E$4-ASM_A06_TRAINING_START_YEAR+1),ASM_B10_TARGET_CERTIFIED_B),0) -> 0 | F27: =IF(F$4>=ASM_A06_TRAINING_START_YEAR,MIN(ROUND(ASM_B04_THROUGHPUT_ANNUAL*ASM_B06_PCT_FILIERE_B,0)*(F$4-ASM_A06_TRAINING_START_YEAR+1),ASM_B10_TARGET_CERTIFIED_B),0) -> 0 | G27: =IF(G$4>=ASM_A06_TRAINING_START_YEAR,MIN(ROUND(ASM_B04_THROUGHPUT_ANNUAL*ASM_B06_PCT_FILIERE_B,0)*(G$4-ASM_A06_TRAINING_START_YEAR+1),ASM_B10_TARGET_CERTIFIED_B),0) -> 21 | H27: =IF(H$4>=ASM_A06_TRAINING_START_YEAR,MIN(ROUND(ASM_B04_THROUGHPUT_ANNUAL*ASM_B06_PCT_FILIERE_B,0)*(H$4-ASM_A06_TRAINING_START_YEAR+1),ASM_B10_TARGET_CERTIFIED_B),0) -> 40 | I27: =IF(I$4>=ASM_A06_TRAINING_START_YEAR,MIN(ROUND(ASM_B04_THROUGHPUT_ANNUAL*ASM_B06_PCT_FILIERE_B,0)*(I$4-ASM_A06_TRAINING_START_YEAR+1),ASM_B10_TARGET_CERTIFIED_B),0) -> 40 | J27: =IF(J$4>=ASM_A06_TRAINING_START_YEAR,MIN(ROUND(ASM_B04_THROUGHPUT_ANNUAL*ASM_B06_PCT_FILIERE_B,0)*(J$4-ASM_A06_TRAINING_START_YEAR+1),ASM_B10_TARGET_CERTIFIED_B),0) -> 40 | K27: =IF(K$4>=ASM_A06_TRAINING_START_YEAR,MIN(ROUND(ASM_B04_THROUGHPUT_ANNUAL*ASM_B06_PCT_FILIERE_B,0)*(K$4-ASM_A06_TRAINING_START_YEAR+1),ASM_B10_TARGET_CERTIFIED_B),0) -> 40 | L27: =IF(L$4>=ASM_A06_TRAINING_START_YEAR,MIN(ROUND(ASM_B04_THROUGHPUT_ANNUAL*ASM_B06_PCT_FILIERE_B,0)*(L$4-ASM_A06_TRAINING_START_YEAR+1),ASM_B10_TARGET_CERTIFIED_B),0) -> 40
B28: Cumulative certified C — energy technicians | C28: persons | D28: =SUM(E28:L28) -> 110 | E28: =IF(E$4>=ASM_A06_TRAINING_START_YEAR,MIN(ROUND(ASM_B04_THROUGHPUT_ANNUAL*ASM_B07_PCT_FILIERE_C,0)*(E$4-ASM_A06_TRAINING_START_YEAR+1),ASM_B11_TARGET_CERTIFIED_C),0) -> 0 | F28: =IF(F$4>=ASM_A06_TRAINING_START_YEAR,MIN(ROUND(ASM_B04_THROUGHPUT_ANNUAL*ASM_B07_PCT_FILIERE_C,0)*(F$4-ASM_A06_TRAINING_START_YEAR+1),ASM_B11_TARGET_CERTIFIED_C),0) -> 0 | G28: =IF(G$4>=ASM_A06_TRAINING_START_YEAR,MIN(ROUND(ASM_B04_THROUGHPUT_ANNUAL*ASM_B07_PCT_FILIERE_C,0)*(G$4-ASM_A06_TRAINING_START_YEAR+1),ASM_B11_TARGET_CERTIFIED_C),0) -> 10 | H28: =IF(H$4>=ASM_A06_TRAINING_START_YEAR,MIN(ROUND(ASM_B04_THROUGHPUT_ANNUAL*ASM_B07_PCT_FILIERE_C,0)*(H$4-ASM_A06_TRAINING_START_YEAR+1),ASM_B11_TARGET_CERTIFIED_C),0) -> 20 | I28: =IF(I$4>=ASM_A06_TRAINING_START_YEAR,MIN(ROUND(ASM_B04_THROUGHPUT_ANNUAL*ASM_B07_PCT_FILIERE_C,0)*(I$4-ASM_A06_TRAINING_START_YEAR+1),ASM_B11_TARGET_CERTIFIED_C),0) -> 20 | J28: =IF(J$4>=ASM_A06_TRAINING_START_YEAR,MIN(ROUND(ASM_B04_THROUGHPUT_ANNUAL*ASM_B07_PCT_FILIERE_C,0)*(J$4-ASM_A06_TRAINING_START_YEAR+1),ASM_B11_TARGET_CERTIFIED_C),0) -> 20 | K28: =IF(K$4>=ASM_A06_TRAINING_START_YEAR,MIN(ROUND(ASM_B04_THROUGHPUT_ANNUAL*ASM_B07_PCT_FILIERE_C,0)*(K$4-ASM_A06_TRAINING_START_YEAR+1),ASM_B11_TARGET_CERTIFIED_C),0) -> 20 | L28: =IF(L$4>=ASM_A06_TRAINING_START_YEAR,MIN(ROUND(ASM_B04_THROUGHPUT_ANNUAL*ASM_B07_PCT_FILIERE_C,0)*(L$4-ASM_A06_TRAINING_START_YEAR+1),ASM_B11_TARGET_CERTIFIED_C),0) -> 20
B29: Cumulative certified D — mechanisation operators | C29: persons | D29: =SUM(E29:L29) -> 331 | E29: =IF(E$4>=ASM_A06_TRAINING_START_YEAR,MIN((ASM_B04_THROUGHPUT_ANNUAL-ROUND(ASM_B04_THROUGHPUT_ANNUAL*ASM_B05_PCT_FILIERE_A,0)-ROUND(ASM_B04_THROUGHPUT_ANNUAL*ASM_B06_PCT_FILIERE_B,0)-ROUND(ASM_B04_THROUGHPUT_ANNUAL*ASM_B07_PCT_FILIERE_C,0))*(E$4-ASM_A06_TRAINING_START_YEAR+1),ASM_B12_TARGET_CERTIFIED_D),0) -> 0 | F29: =IF(F$4>=ASM_A06_TRAINING_START_YEAR,MIN((ASM_B04_THROUGHPUT_ANNUAL-ROUND(ASM_B04_THROUGHPUT_ANNUAL*ASM_B05_PCT_FILIERE_A,0)-ROUND(ASM_B04_THROUGHPUT_ANNUAL*ASM_B06_PCT_FILIERE_B,0)-ROUND(ASM_B04_THROUGHPUT_ANNUAL*ASM_B07_PCT_FILIERE_C,0))*(F$4-ASM_A06_TRAINING_START_YEAR+1),ASM_B12_TARGET_CERTIFIED_D),0) -> 0 | G29: =IF(G$4>=ASM_A06_TRAINING_START_YEAR,MIN((ASM_B04_THROUGHPUT_ANNUAL-ROUND(ASM_B04_THROUGHPUT_ANNUAL*ASM_B05_PCT_FILIERE_A,0)-ROUND(ASM_B04_THROUGHPUT_ANNUAL*ASM_B06_PCT_FILIERE_B,0)-ROUND(ASM_B04_THROUGHPUT_ANNUAL*ASM_B07_PCT_FILIERE_C,0))*(G$4-ASM_A06_TRAINING_START_YEAR+1),ASM_B12_TARGET_CERTIFIED_D),0) -> 31 | H29: =IF(H$4>=ASM_A06_TRAINING_START_YEAR,MIN((ASM_B04_THROUGHPUT_ANNUAL-ROUND(ASM_B04_THROUGHPUT_ANNUAL*ASM_B05_PCT_FILIERE_A,0)-ROUND(ASM_B04_THROUGHPUT_ANNUAL*ASM_B06_PCT_FILIERE_B,0)-ROUND(ASM_B04_THROUGHPUT_ANNUAL*ASM_B07_PCT_FILIERE_C,0))*(H$4-ASM_A06_TRAINING_START_YEAR+1),ASM_B12_TARGET_CERTIFIED_D),0) -> 60 | I29: =IF(I$4>=ASM_A06_TRAINING_START_YEAR,MIN((ASM_B04_THROUGHPUT_ANNUAL-ROUND(ASM_B04_THROUGHPUT_ANNUAL*ASM_B05_PCT_FILIERE_A,0)-ROUND(ASM_B04_THROUGHPUT_ANNUAL*ASM_B06_PCT_FILIERE_B,0)-ROUND(ASM_B04_THROUGHPUT_ANNUAL*ASM_B07_PCT_FILIERE_C,0))*(I$4-ASM_A06_TRAINING_START_YEAR+1),ASM_B12_TARGET_CERTIFIED_D),0) -> 60 | J29: =IF(J$4>=ASM_A06_TRAINING_START_YEAR,MIN((ASM_B04_THROUGHPUT_ANNUAL-ROUND(ASM_B04_THROUGHPUT_ANNUAL*ASM_B05_PCT_FILIERE_A,0)-ROUND(ASM_B04_THROUGHPUT_ANNUAL*ASM_B06_PCT_FILIERE_B,0)-ROUND(ASM_B04_THROUGHPUT_ANNUAL*ASM_B07_PCT_FILIERE_C,0))*(J$4-ASM_A06_TRAINING_START_YEAR+1),ASM_B12_TARGET_CERTIFIED_D),0) -> 60 | K29: =IF(K$4>=ASM_A06_TRAINING_START_YEAR,MIN((ASM_B04_THROUGHPUT_ANNUAL-ROUND(ASM_B04_THROUGHPUT_ANNUAL*ASM_B05_PCT_FILIERE_A,0)-ROUND(ASM_B04_THROUGHPUT_ANNUAL*ASM_B06_PCT_FILIERE_B,0)-ROUND(ASM_B04_THROUGHPUT_ANNUAL*ASM_B07_PCT_FILIERE_C,0))*(K$4-ASM_A06_TRAINING_START_YEAR+1),ASM_B12_TARGET_CERTIFIED_D),0) -> 60 | L29: =IF(L$4>=ASM_A06_TRAINING_START_YEAR,MIN((ASM_B04_THROUGHPUT_ANNUAL-ROUND(ASM_B04_THROUGHPUT_ANNUAL*ASM_B05_PCT_FILIERE_A,0)-ROUND(ASM_B04_THROUGHPUT_ANNUAL*ASM_B06_PCT_FILIERE_B,0)-ROUND(ASM_B04_THROUGHPUT_ANNUAL*ASM_B07_PCT_FILIERE_C,0))*(L$4-ASM_A06_TRAINING_START_YEAR+1),ASM_B12_TARGET_CERTIFIED_D),0) -> 60

Sheet 03_Training
B1: 03 — Training / Human capital [€] ← feeds CAPEX · OpEx · Revenue
D3: Total | E3: Y-1 | F3: Y0 | G3: Y1 | H3: Y2 | I3: Y3 | J3: Y4 | K3: Y5 | L3: Y6
E4: -1 | F4: 0 | G4: 1 | H4: 2 | I4: 3 | J4: 4 | K4: 5 | L4: 6
B6: Summary
B7: 1. Training infrastructure (one-time CAP) | C7: € | D7: =SUM(E7:L7) -> 1488000 | E7: =E38 -> 628000 | F7: =F38 -> 860000 | G7: =G38 -> 0 | H7: =H38 -> 0 | I7: =I38 -> 0 | J7: =J38 -> 0 | K7: =K38 -> 0 | L7: =L38 -> 0
B8: 2. Recurring training (annual OPEX, net of work offset) | C8: € | D8: =SUM(E8:L8) -> 1359700 | E8: =E61 -> 0 | F8: =F61 -> 0 | G8: =G61 -> 679850 | H8: =H61 -> 679850 | I8: =I61 -> 0 | J8: =J61 -> 0 | K8: =K61 -> 0 | L8: =L61 -> 0
B9: 3. Training revenue (= 0; grant-funded) | C9: € | D9: =SUM(E9:L9) -> 0 | E9: =0 -> 0 | F9: =0 -> 0 | G9: =0 -> 0 | H9: =0 -> 0 | I9: =0 -> 0 | J9: =0 -> 0 | K9: =0 -> 0 | L9: =0 -> 0
B10: TOTAL TRAINING PROGRAMME COST | C10: € | D10: =SUM(E10:L10) -> 2847700 | E10: =E7+E8-E9 -> 628000 | F10: =F7+F8-F9 -> 860000 | G10: =G7+G8-G9 -> 679850 | H10: =H7+H8-H9 -> 679850 | I10: =I7+I8-I9 -> 0 | J10: =J7+J8-J9 -> 0 | K10: =K7+K8-K9 -> 0 | L10: =L7+L8-L9 -> 0
B12: Training infrastructure — one-time CAP build
B13: Curriculum, certification & expert support
B14: Curriculum design + certification partner | C14: € | D14: =SUM(E14:L14) -> 220000 | E14: =E$98*FLAG_PREPROG_YM1 -> 220000 | F14: =F$98*FLAG_PREPROG_Y0 -> 0 | G14: =G$98*FLAG_PREPROG_Y1 -> 0 | H14: =H$98*FLAG_PREPROG_Y2 -> 0 | I14: =I$98*FLAG_PREPROG_Y3 -> 0 | J14: =J$98*FLAG_PREPROG_Y4 -> 0 | K14: =K$98*FLAG_PREPROG_Y5 -> 0 | L14: =L$98*FLAG_PREPROG_Y6 -> 0
B15: Train-the-Trainer (programme team) | C15: € | D15: =SUM(E15:L15) -> 288000 | E15: =E$124*E$88*E$89*FLAG_PREPROG_YM1 -> 288000 | F15: =F$124*F$88*F$89*FLAG_PREPROG_Y0 -> 0 | G15: =G$124*G$88*G$89*FLAG_PREPROG_Y1 -> 0 | H15: =H$124*H$88*H$89*FLAG_PREPROG_Y2 -> 0 | I15: =I$124*I$88*I$89*FLAG_PREPROG_Y3 -> 0 | J15: =J$124*J$88*J$89*FLAG_PREPROG_Y4 -> 0 | K15: =K$124*K$88*K$89*FLAG_PREPROG_Y5 -> 0 | L15: =L$124*L$88*L$89*FLAG_PREPROG_Y6 -> 0
B16: International specialist experts (one-time) | C16: € | D16: =SUM(E16:L16) -> 120000 | E16: =E$125*FLAG_PREPROG_YM1 -> 120000 | F16: =F$125*FLAG_PREPROG_Y0 -> 0 | G16: =G$125*FLAG_PREPROG_Y1 -> 0 | H16: =H$125*FLAG_PREPROG_Y2 -> 0 | I16: =I$125*FLAG_PREPROG_Y3 -> 0 | J16: =J$125*FLAG_PREPROG_Y4 -> 0 | K16: =K$125*FLAG_PREPROG_Y5 -> 0 | L16: =L$125*FLAG_PREPROG_Y6 -> 0
B17: Curriculum materials (per filière) | C17: € | D17: =SUM(E17:L17) -> 50000 | E17: =E$100*E$101*FLAG_CONSTRUCT_YM1 -> 0 | F17: =F$100*F$101*FLAG_CONSTRUCT_Y0 -> 50000 | G17: =G$100*G$101*FLAG_CONSTRUCT_Y1 -> 0 | H17: =H$100*H$101*FLAG_CONSTRUCT_Y2 -> 0 | I17: =I$100*I$101*FLAG_CONSTRUCT_Y3 -> 0 | J17: =J$100*J$101*FLAG_CONSTRUCT_Y4 -> 0 | K17: =K$100*K$101*FLAG_CONSTRUCT_Y5 -> 0 | L17: =L$100*L$101*FLAG_CONSTRUCT_Y6 -> 0
B18: Subtotal — Curriculum & certification | C18: € | D18: =SUM(D14:D17) -> 678000 | E18: =SUM(E14:E17) -> 628000 | F18: =SUM(F14:F17) -> 50000 | G18: =SUM(G14:G17) -> 0 | H18: =SUM(H14:H17) -> 0 | I18: =SUM(I14:I17) -> 0 | J18: =SUM(J14:J17) -> 0 | K18: =SUM(K14:K17) -> 0 | L18: =SUM(L14:L17) -> 0
B20: Pedagogical plateaux & classroom
B21: Classroom equipment (3 farms) | C21: € | D21: =SUM(E21:L21) -> 135000 | E21: =E$65*E$99*FLAG_CONSTRUCT_YM1 -> 0 | F21: =F$65*F$99*FLAG_CONSTRUCT_Y0 -> 135000 | G21: =G$65*G$99*FLAG_CONSTRUCT_Y1 -> 0 | H21: =H$65*H$99*FLAG_CONSTRUCT_Y2 -> 0 | I21: =I$65*I$99*FLAG_CONSTRUCT_Y3 -> 0 | J21: =J$65*J$99*FLAG_CONSTRUCT_Y4 -> 0 | K21: =K$65*K$99*FLAG_CONSTRUCT_Y5 -> 0 | L21: =L$65*L$99*FLAG_CONSTRUCT_Y6 -> 0
B22: Plateau eau — pumping bench + irrigation lab + drilling station (filière B) | C22: € | D22: =ASM_G02A_PLATEAU_EAU_EUR -> 60000 | E22: =ASM_G02A_PLATEAU_EAU_EUR*FLAG_CONSTRUCT_YM1 -> 0 | F22: =ASM_G02A_PLATEAU_EAU_EUR*FLAG_CONSTRUCT_Y0 -> 60000 | G22: =ASM_G02A_PLATEAU_EAU_EUR*FLAG_CONSTRUCT_Y1 -> 0 | H22: =ASM_G02A_PLATEAU_EAU_EUR*FLAG_CONSTRUCT_Y2 -> 0 | I22: =ASM_G02A_PLATEAU_EAU_EUR*FLAG_CONSTRUCT_Y3 -> 0 | J22: =ASM_G02A_PLATEAU_EAU_EUR*FLAG_CONSTRUCT_Y4 -> 0 | K22: =ASM_G02A_PLATEAU_EAU_EUR*FLAG_CONSTRUCT_Y5 -> 0 | L22: =ASM_G02A_PLATEAU_EAU_EUR*FLAG_CONSTRUCT_Y6 -> 0
B23: Plateau PV — array + hybrid inverters + BESS + SCADA (filière C) | C23: € | D23: =ASM_G02B_PLATEAU_PV_EUR -> 50000 | E23: =ASM_G02B_PLATEAU_PV_EUR*FLAG_CONSTRUCT_YM1 -> 0 | F23: =ASM_G02B_PLATEAU_PV_EUR*FLAG_CONSTRUCT_Y0 -> 50000 | G23: =ASM_G02B_PLATEAU_PV_EUR*FLAG_CONSTRUCT_Y1 -> 0 | H23: =ASM_G02B_PLATEAU_PV_EUR*FLAG_CONSTRUCT_Y2 -> 0 | I23: =ASM_G02B_PLATEAU_PV_EUR*FLAG_CONSTRUCT_Y3 -> 0 | J23: =ASM_G02B_PLATEAU_PV_EUR*FLAG_CONSTRUCT_Y4 -> 0 | K23: =ASM_G02B_PLATEAU_PV_EUR*FLAG_CONSTRUCT_Y5 -> 0 | L23: =ASM_G02B_PLATEAU_PV_EUR*FLAG_CONSTRUCT_Y6 -> 0
B24: Atelier méca — workshop + lifting + tractor + diagnostic (filière D) | C24: € | D24: =ASM_G02C_ATELIER_MECA_EUR -> 60000 | E24: =ASM_G02C_ATELIER_MECA_EUR*FLAG_CONSTRUCT_YM1 -> 0 | F24: =ASM_G02C_ATELIER_MECA_EUR*FLAG_CONSTRUCT_Y0 -> 60000 | G24: =ASM_G02C_ATELIER_MECA_EUR*FLAG_CONSTRUCT_Y1 -> 0 | H24: =ASM_G02C_ATELIER_MECA_EUR*FLAG_CONSTRUCT_Y2 -> 0 | I24: =ASM_G02C_ATELIER_MECA_EUR*FLAG_CONSTRUCT_Y3 -> 0 | J24: =ASM_G02C_ATELIER_MECA_EUR*FLAG_CONSTRUCT_Y4 -> 0 | K24: =ASM_G02C_ATELIER_MECA_EUR*FLAG_CONSTRUCT_Y5 -> 0 | L24: =ASM_G02C_ATELIER_MECA_EUR*FLAG_CONSTRUCT_Y6 -> 0
B25: Classroom / IT / comms — multipurpose rooms + workstations + technical library | C25: € | D25: =ASM_G02D_CLASSROOM_IT_EUR -> 40000 | E25: =ASM_G02D_CLASSROOM_IT_EUR*FLAG_CONSTRUCT_YM1 -> 0 | F25: =ASM_G02D_CLASSROOM_IT_EUR*FLAG_CONSTRUCT_Y0 -> 40000 | G25: =ASM_G02D_CLASSROOM_IT_EUR*FLAG_CONSTRUCT_Y1 -> 0 | H25: =ASM_G02D_CLASSROOM_IT_EUR*FLAG_CONSTRUCT_Y2 -> 0 | I25: =ASM_G02D_CLASSROOM_IT_EUR*FLAG_CONSTRUCT_Y3 -> 0 | J25: =ASM_G02D_CLASSROOM_IT_EUR*FLAG_CONSTRUCT_Y4 -> 0 | K25: =ASM_G02D_CLASSROOM_IT_EUR*FLAG_CONSTRUCT_Y5 -> 0 | L25: =ASM_G02D_CLASSROOM_IT_EUR*FLAG_CONSTRUCT_Y6 -> 0
B26: Subtotal — Pedagogical plateaux & classroom | C26: € | D26: =SUM(D21:D25) -> 345000 | E26: =SUM(E21:E25) -> 0 | F26: =SUM(F21:F25) -> 345000 | G26: =SUM(G21:G25) -> 0 | H26: =SUM(H21:H25) -> 0 | I26: =SUM(I21:I25) -> 0 | J26: =SUM(J21:J25) -> 0 | K26: =SUM(K21:K25) -> 0 | L26: =SUM(L21:L25) -> 0
B28: Accommodation
B29: Trainee dormitories | C29: € | D29: =SUM(E29:L29) -> 297000 | E29: =E$126*E$65*E$94*FLAG_CONSTRUCT_YM1 -> 0 | F29: =F$126*F$65*F$94*FLAG_CONSTRUCT_Y0 -> 297000 | G29: =G$126*G$65*G$94*FLAG_CONSTRUCT_Y1 -> 0 | H29: =H$126*H$65*H$94*FLAG_CONSTRUCT_Y2 -> 0 | I29: =I$126*I$65*I$94*FLAG_CONSTRUCT_Y3 -> 0 | J29: =J$126*J$65*J$94*FLAG_CONSTRUCT_Y4 -> 0 | K29: =K$126*K$65*K$94*FLAG_CONSTRUCT_Y5 -> 0 | L29: =L$126*L$65*L$94*FLAG_CONSTRUCT_Y6 -> 0
B30: Refectory & common areas | C30: € | D30: =SUM(E30:L30) -> 48000 | E30: =E$65*E$95*FLAG_CONSTRUCT_YM1 -> 0 | F30: =F$65*F$95*FLAG_CONSTRUCT_Y0 -> 48000 | G30: =G$65*G$95*FLAG_CONSTRUCT_Y1 -> 0 | H30: =H$65*H$95*FLAG_CONSTRUCT_Y2 -> 0 | I30: =I$65*I$95*FLAG_CONSTRUCT_Y3 -> 0 | J30: =J$65*J$95*FLAG_CONSTRUCT_Y4 -> 0 | K30: =K$65*K$95*FLAG_CONSTRUCT_Y5 -> 0 | L30: =L$65*L$95*FLAG_CONSTRUCT_Y6 -> 0
B31: Family housing | C31: € | D31: =SUM(E31:L31) -> 40000 | E31: =E$127*E$97*FLAG_CONSTRUCT_YM1 -> 0 | F31: =F$127*F$97*FLAG_CONSTRUCT_Y0 -> 40000 | G31: =G$127*G$97*FLAG_CONSTRUCT_Y1 -> 0 | H31: =H$127*H$97*FLAG_CONSTRUCT_Y2 -> 0 | I31: =I$127*I$97*FLAG_CONSTRUCT_Y3 -> 0 | J31: =J$127*J$97*FLAG_CONSTRUCT_Y4 -> 0 | K31: =K$127*K$97*FLAG_CONSTRUCT_Y5 -> 0 | L31: =L$127*L$97*FLAG_CONSTRUCT_Y6 -> 0
B32: Subtotal — Accommodation | C32: € | D32: =SUM(D29:D31) -> 385000 | E32: =SUM(E29:E31) -> 0 | F32: =SUM(F29:F31) -> 385000 | G32: =SUM(G29:G31) -> 0 | H32: =SUM(H29:H31) -> 0 | I32: =SUM(I29:I31) -> 0 | J32: =SUM(J29:J31) -> 0 | K32: =SUM(K29:K31) -> 0 | L32: =SUM(L29:L31) -> 0
B34: Monitoring & communications
B35: Monitoring equipment | C35: € | D35: =SUM(E35:L35) -> 60000 | E35: =E$103*FLAG_CONSTRUCT_YM1 -> 0 | F35: =F$103*FLAG_CONSTRUCT_Y0 -> 60000 | G35: =G$103*FLAG_CONSTRUCT_Y1 -> 0 | H35: =H$103*FLAG_CONSTRUCT_Y2 -> 0 | I35: =I$103*FLAG_CONSTRUCT_Y3 -> 0 | J35: =J$103*FLAG_CONSTRUCT_Y4 -> 0 | K35: =K$103*FLAG_CONSTRUCT_Y5 -> 0 | L35: =L$103*FLAG_CONSTRUCT_Y6 -> 0
B36: Communication materials | C36: € | D36: =SUM(E36:L36) -> 20000 | E36: =E$106*FLAG_CONSTRUCT_YM1 -> 0 | F36: =F$106*FLAG_CONSTRUCT_Y0 -> 20000 | G36: =G$106*FLAG_CONSTRUCT_Y1 -> 0 | H36: =H$106*FLAG_CONSTRUCT_Y2 -> 0 | I36: =I$106*FLAG_CONSTRUCT_Y3 -> 0 | J36: =J$106*FLAG_CONSTRUCT_Y4 -> 0 | K36: =K$106*FLAG_CONSTRUCT_Y5 -> 0 | L36: =L$106*FLAG_CONSTRUCT_Y6 -> 0
B37: Subtotal — Monitoring & communications | C37: € | D37: =SUM(D35:D36) -> 80000 | E37: =SUM(E35:E36) -> 0 | F37: =SUM(F35:F36) -> 80000 | G37: =SUM(G35:G36) -> 0 | H37: =SUM(H35:H36) -> 0 | I37: =SUM(I35:I36) -> 0 | J37: =SUM(J35:J36) -> 0 | K37: =SUM(K35:K36) -> 0 | L37: =SUM(L35:L36) -> 0
B38: TOTAL TRAINING INFRASTRUCTURE | C38: € | D38: =D18+D26+D32+D37 -> 1488000 | E38: =E18+E26+E32+E37 -> 628000 | F38: =F18+F26+F32+F37 -> 860000 | G38: =G18+G26+G32+G37 -> 0 | H38: =H18+H26+H32+H37 -> 0 | I38: =I18+I26+I32+I37 -> 0 | J38: =J18+J26+J32+J37 -> 0 | K38: =K18+K26+K32+K37 -> 0 | L38: =L18+L26+L32+L37 -> 0
B40: Recurring training — annual OPEX
B41: Trainers — filière + specialist
B42: Filière trainers | C42: €/yr | D42: =SUM(E42:L42) -> 480000 | E42: =E$82*E$84*IF(AND(E$4>=ASM_A04_COD_YEAR,E$4<ASM_A04_COD_YEAR+ASM_D06_YEARS_TRAINERS_ACTIVE),1,0) -> 0 | F42: =F$82*F$84*IF(AND(F$4>=ASM_A04_COD_YEAR,F$4<ASM_A04_COD_YEAR+ASM_D06_YEARS_TRAINERS_ACTIVE),1,0) -> 0 | G42: =G$82*G$84*IF(AND(G$4>=ASM_A04_COD_YEAR,G$4<ASM_A04_COD_YEAR+ASM_D06_YEARS_TRAINERS_ACTIVE),1,0) -> 240000 | H42: =H$82*H$84*IF(AND(H$4>=ASM_A04_COD_YEAR,H$4<ASM_A04_COD_YEAR+ASM_D06_YEARS_TRAINERS_ACTIVE),1,0) -> 240000 | I42: =I$82*I$84*IF(AND(I$4>=ASM_A04_COD_YEAR,I$4<ASM_A04_COD_YEAR+ASM_D06_YEARS_TRAINERS_ACTIVE),1,0) -> 0 | J42: =J$82*J$84*IF(AND(J$4>=ASM_A04_COD_YEAR,J$4<ASM_A04_COD_YEAR+ASM_D06_YEARS_TRAINERS_ACTIVE),1,0) -> 0 | K42: =K$82*K$84*IF(AND(K$4>=ASM_A04_COD_YEAR,K$4<ASM_A04_COD_YEAR+ASM_D06_YEARS_TRAINERS_ACTIVE),1,0) -> 0 | L42: =L$82*L$84*IF(AND(L$4>=ASM_A04_COD_YEAR,L$4<ASM_A04_COD_YEAR+ASM_D06_YEARS_TRAINERS_ACTIVE),1,0) -> 0
B43: Specialist trainers | C43: €/yr | D43: =SUM(E43:L43) -> 320000 | E43: =E$83*E$85*IF(AND(E$4>=ASM_A04_COD_YEAR,E$4<ASM_A04_COD_YEAR+ASM_D07_YEARS_SPECIALIST_ACTIVE),1,0) -> 0 | F43: =F$83*F$85*IF(AND(F$4>=ASM_A04_COD_YEAR,F$4<ASM_A04_COD_YEAR+ASM_D07_YEARS_SPECIALIST_ACTIVE),1,0) -> 0 | G43: =G$83*G$85*IF(AND(G$4>=ASM_A04_COD_YEAR,G$4<ASM_A04_COD_YEAR+ASM_D07_YEARS_SPECIALIST_ACTIVE),1,0) -> 160000 | H43: =H$83*H$85*IF(AND(H$4>=ASM_A04_COD_YEAR,H$4<ASM_A04_COD_YEAR+ASM_D07_YEARS_SPECIALIST_ACTIVE),1,0) -> 160000 | I43: =I$83*I$85*IF(AND(I$4>=ASM_A04_COD_YEAR,I$4<ASM_A04_COD_YEAR+ASM_D07_YEARS_SPECIALIST_ACTIVE),1,0) -> 0 | J43: =J$83*J$85*IF(AND(J$4>=ASM_A04_COD_YEAR,J$4<ASM_A04_COD_YEAR+ASM_D07_YEARS_SPECIALIST_ACTIVE),1,0) -> 0 | K43: =K$83*K$85*IF(AND(K$4>=ASM_A04_COD_YEAR,K$4<ASM_A04_COD_YEAR+ASM_D07_YEARS_SPECIALIST_ACTIVE),1,0) -> 0 | L43: =L$83*L$85*IF(AND(L$4>=ASM_A04_COD_YEAR,L$4<ASM_A04_COD_YEAR+ASM_D07_YEARS_SPECIALIST_ACTIVE),1,0) -> 0
B44: Subtotal — Trainers | C44: € | D44: =SUM(D42:D43) -> 800000 | E44: =SUM(E42:E43) -> 0 | F44: =SUM(F42:F43) -> 0 | G44: =SUM(G42:G43) -> 400000 | H44: =SUM(H42:H43) -> 400000 | I44: =SUM(I42:I43) -> 0 | J44: =SUM(J42:J43) -> 0 | K44: =SUM(K42:K43) -> 0 | L44: =SUM(L42:L43) -> 0
B46: Trainee stipends — net of productive-work credit
B47: Filière A — stipends paid | C47: €/yr | D47: =SUM(E47:L47) -> 873600 | E47: =E$148*E$136*FLAG_VALIDATION_YM1 -> 0 | F47: =F$148*F$136*FLAG_VALIDATION_Y0 -> 0 | G47: =G$148*G$136*FLAG_VALIDATION_Y1 -> 436800 | H47: =H$148*H$136*FLAG_VALIDATION_Y2 -> 436800 | I47: =I$148*I$136*FLAG_VALIDATION_Y3 -> 0 | J47: =J$148*J$136*FLAG_VALIDATION_Y4 -> 0 | K47: =K$148*K$136*FLAG_VALIDATION_Y5 -> 0 | L47: =L$148*L$136*FLAG_VALIDATION_Y6 -> 0
B48: Filière A — productive-work credit (notional) | C48: €/yr | D48: =SUM(E48:L48) -> -520000 | E48: =-E$148*E$140*FLAG_VALIDATION_YM1 -> 0 | F48: =-F$148*F$140*FLAG_VALIDATION_Y0 -> 0 | G48: =-G$148*G$140*FLAG_VALIDATION_Y1 -> -260000 | H48: =-H$148*H$140*FLAG_VALIDATION_Y2 -> -260000 | I48: =-I$148*I$140*FLAG_VALIDATION_Y3 -> 0 | J48: =-J$148*J$140*FLAG_VALIDATION_Y4 -> 0 | K48: =-K$148*K$140*FLAG_VALIDATION_Y5 -> 0 | L48: =-L$148*L$140*FLAG_VALIDATION_Y6 -> 0
B49: Filière B — stipends paid | C49: €/yr | D49: =SUM(E49:L49) -> 66150 | E49: =E$149*E$137*FLAG_VALIDATION_YM1 -> 0 | F49: =F$149*F$137*FLAG_VALIDATION_Y0 -> 0 | G49: =G$149*G$137*FLAG_VALIDATION_Y1 -> 33075 | H49: =H$149*H$137*FLAG_VALIDATION_Y2 -> 33075 | I49: =I$149*I$137*FLAG_VALIDATION_Y3 -> 0 | J49: =J$149*J$137*FLAG_VALIDATION_Y4 -> 0 | K49: =K$149*K$137*FLAG_VALIDATION_Y5 -> 0 | L49: =L$149*L$137*FLAG_VALIDATION_Y6 -> 0
B50: Filière B — productive-work credit (notional) | C50: €/yr | D50: =SUM(E50:L50) -> -36750 | E50: =-E$149*E$141*FLAG_VALIDATION_YM1 -> 0 | F50: =-F$149*F$141*FLAG_VALIDATION_Y0 -> 0 | G50: =-G$149*G$141*FLAG_VALIDATION_Y1 -> -18375 | H50: =-H$149*H$141*FLAG_VALIDATION_Y2 -> -18375 | I50: =-I$149*I$141*FLAG_VALIDATION_Y3 -> 0 | J50: =-J$149*J$141*FLAG_VALIDATION_Y4 -> 0 | K50: =-K$149*K$141*FLAG_VALIDATION_Y5 -> 0 | L50: =-L$149*L$141*FLAG_VALIDATION_Y6 -> 0
B51: Filière C — stipends paid | C51: €/yr | D51: =SUM(E51:L51) -> 31500 | E51: =E$150*E$138*FLAG_VALIDATION_YM1 -> 0 | F51: =F$150*F$138*FLAG_VALIDATION_Y0 -> 0 | G51: =G$150*G$138*FLAG_VALIDATION_Y1 -> 15750 | H51: =H$150*H$138*FLAG_VALIDATION_Y2 -> 15750 | I51: =I$150*I$138*FLAG_VALIDATION_Y3 -> 0 | J51: =J$150*J$138*FLAG_VALIDATION_Y4 -> 0 | K51: =K$150*K$138*FLAG_VALIDATION_Y5 -> 0 | L51: =L$150*L$138*FLAG_VALIDATION_Y6 -> 0
B52: Filière C — productive-work credit (notional) | C52: €/yr | D52: =SUM(E52:L52) -> -17500 | E52: =-E$150*E$142*FLAG_VALIDATION_YM1 -> 0 | F52: =-F$150*F$142*FLAG_VALIDATION_Y0 -> 0 | G52: =-G$150*G$142*FLAG_VALIDATION_Y1 -> -8750 | H52: =-H$150*H$142*FLAG_VALIDATION_Y2 -> -8750 | I52: =-I$150*I$142*FLAG_VALIDATION_Y3 -> 0 | J52: =-J$150*J$142*FLAG_VALIDATION_Y4 -> 0 | K52: =-K$150*K$142*FLAG_VALIDATION_Y5 -> 0 | L52: =-L$150*L$142*FLAG_VALIDATION_Y6 -> 0
B53: Filière D — stipends paid | C53: €/yr | D53: =SUM(E53:L53) -> 130200 | E53: =E$151*E$139*FLAG_VALIDATION_YM1 -> 0 | F53: =F$151*F$139*FLAG_VALIDATION_Y0 -> 0 | G53: =G$151*G$139*FLAG_VALIDATION_Y1 -> 65100 | H53: =H$151*H$139*FLAG_VALIDATION_Y2 -> 65100 | I53: =I$151*I$139*FLAG_VALIDATION_Y3 -> 0 | J53: =J$151*J$139*FLAG_VALIDATION_Y4 -> 0 | K53: =K$151*K$139*FLAG_VALIDATION_Y5 -> 0 | L53: =L$151*L$139*FLAG_VALIDATION_Y6 -> 0
B54: Filière D — productive-work credit (notional) | C54: €/yr | D54: =SUM(E54:L54) -> -77500 | E54: =-E$151*E$143*FLAG_VALIDATION_YM1 -> 0 | F54: =-F$151*F$143*FLAG_VALIDATION_Y0 -> 0 | G54: =-G$151*G$143*FLAG_VALIDATION_Y1 -> -38750 | H54: =-H$151*H$143*FLAG_VALIDATION_Y2 -> -38750 | I54: =-I$151*I$143*FLAG_VALIDATION_Y3 -> 0 | J54: =-J$151*J$143*FLAG_VALIDATION_Y4 -> 0 | K54: =-K$151*K$143*FLAG_VALIDATION_Y5 -> 0 | L54: =-L$151*L$143*FLAG_VALIDATION_Y6 -> 0
B55: Subtotal — Trainee stipends (net) | C55: € | D55: =SUM(D47:D54) -> 449700 | E55: =SUM(E47:E54) -> 0 | F55: =SUM(F47:F54) -> 0 | G55: =SUM(G47:G54) -> 224850 | H55: =SUM(H47:H54) -> 224850 | I55: =SUM(I47:I54) -> 0 | J55: =SUM(J47:J54) -> 0 | K55: =SUM(K47:K54) -> 0 | L55: =SUM(L47:L54) -> 0
B57: Monitoring & communications
B58: Data coordinator — O2 governance | C58: €/yr | D58: =SUM(E58:L58) -> 80000 | E58: =E$104*IF(AND(E$4>=ASM_A04_COD_YEAR,E$4<ASM_A04_COD_YEAR+ASM_H04_N_YEARS_MONITORING),1,0) -> 0 | F58: =F$104*IF(AND(F$4>=ASM_A04_COD_YEAR,F$4<ASM_A04_COD_YEAR+ASM_H04_N_YEARS_MONITORING),1,0) -> 0 | G58: =G$104*IF(AND(G$4>=ASM_A04_COD_YEAR,G$4<ASM_A04_COD_YEAR+ASM_H04_N_YEARS_MONITORING),1,0) -> 40000 | H58: =H$104*IF(AND(H$4>=ASM_A04_COD_YEAR,H$4<ASM_A04_COD_YEAR+ASM_H04_N_YEARS_MONITORING),1,0) -> 40000 | I58: =I$104*IF(AND(I$4>=ASM_A04_COD_YEAR,I$4<ASM_A04_COD_YEAR+ASM_H04_N_YEARS_MONITORING),1,0) -> 0 | J58: =J$104*IF(AND(J$4>=ASM_A04_COD_YEAR,J$4<ASM_A04_COD_YEAR+ASM_H04_N_YEARS_MONITORING),1,0) -> 0 | K58: =K$104*IF(AND(K$4>=ASM_A04_COD_YEAR,K$4<ASM_A04_COD_YEAR+ASM_H04_N_YEARS_MONITORING),1,0) -> 0 | L58: =L$104*IF(AND(L$4>=ASM_A04_COD_YEAR,L$4<ASM_A04_COD_YEAR+ASM_H04_N_YEARS_MONITORING),1,0) -> 0
B59: Communication officer — O3 | C59: €/yr | D59: =SUM(E59:L59) -> 30000 | E59: =E$107*IF(AND(E$4>=ASM_A04_COD_YEAR,E$4<ASM_A04_COD_YEAR+ASM_H07_N_YEARS_O3),1,0) -> 0 | F59: =F$107*IF(AND(F$4>=ASM_A04_COD_YEAR,F$4<ASM_A04_COD_YEAR+ASM_H07_N_YEARS_O3),1,0) -> 0 | G59: =G$107*IF(AND(G$4>=ASM_A04_COD_YEAR,G$4<ASM_A04_COD_YEAR+ASM_H07_N_YEARS_O3),1,0) -> 15000 | H59: =H$107*IF(AND(H$4>=ASM_A04_COD_YEAR,H$4<ASM_A04_COD_YEAR+ASM_H07_N_YEARS_O3),1,0) -> 15000 | I59: =I$107*IF(AND(I$4>=ASM_A04_COD_YEAR,I$4<ASM_A04_COD_YEAR+ASM_H07_N_YEARS_O3),1,0) -> 0 | J59: =J$107*IF(AND(J$4>=ASM_A04_COD_YEAR,J$4<ASM_A04_COD_YEAR+ASM_H07_N_YEARS_O3),1,0) -> 0 | K59: =K$107*IF(AND(K$4>=ASM_A04_COD_YEAR,K$4<ASM_A04_COD_YEAR+ASM_H07_N_YEARS_O3),1,0) -> 0 | L59: =L$107*IF(AND(L$4>=ASM_A04_COD_YEAR,L$4<ASM_A04_COD_YEAR+ASM_H07_N_YEARS_O3),1,0) -> 0
B60: Subtotal — Monitoring & communications | C60: € | D60: =SUM(D58:D59) -> 110000 | E60: =SUM(E58:E59) -> 0 | F60: =SUM(F58:F59) -> 0 | G60: =SUM(G58:G59) -> 55000 | H60: =SUM(H58:H59) -> 55000 | I60: =SUM(I58:I59) -> 0 | J60: =SUM(J58:J59) -> 0 | K60: =SUM(K58:K59) -> 0 | L60: =SUM(L58:L59) -> 0
B61: TOTAL RECURRING TRAINING | C61: € | D61: =D44+D55+D60 -> 1359700 | E61: =E44+E55+E60 -> 0 | F61: =F44+F55+F60 -> 0 | G61: =G44+G55+G60 -> 679850 | H61: =H44+H55+H60 -> 679850 | I61: =I44+I55+I60 -> 0 | J61: =J44+J55+J60 -> 0 | K61: =K44+K55+K60 -> 0 | L61: =L44+L55+L60 -> 0
B64: Inputs from Assumptions
B65: A01 — Number of incubator farms | C65: farms | D65: =SUM(E65:L65) -> 24 | E65: =ASM_A01_N_FARMS -> 3 | F65: =ASM_A01_N_FARMS -> 3 | G65: =ASM_A01_N_FARMS -> 3 | H65: =ASM_A01_N_FARMS -> 3 | I65: =ASM_A01_N_FARMS -> 3 | J65: =ASM_A01_N_FARMS -> 3 | K65: =ASM_A01_N_FARMS -> 3 | L65: =ASM_A01_N_FARMS -> 3
B66: B01 — Simultaneous training slots per farm | C66: slots | D66: =SUM(E66:L66) -> 720 | E66: =ASM_B01_TRAINING_SLOTS_PER_FARM -> 90 | F66: =ASM_B01_TRAINING_SLOTS_PER_FARM -> 90 | G66: =ASM_B01_TRAINING_SLOTS_PER_FARM -> 90 | H66: =ASM_B01_TRAINING_SLOTS_PER_FARM -> 90 | I66: =ASM_B01_TRAINING_SLOTS_PER_FARM -> 90 | J66: =ASM_B01_TRAINING_SLOTS_PER_FARM -> 90 | K66: =ASM_B01_TRAINING_SLOTS_PER_FARM -> 90 | L66: =ASM_B01_TRAINING_SLOTS_PER_FARM -> 90
B67: B02 — Staggered cohorts per farm | C67: cohorts | D67: =SUM(E67:L67) -> 16 | E67: =ASM_B02_COHORTS_PER_FARM -> 2 | F67: =ASM_B02_COHORTS_PER_FARM -> 2 | G67: =ASM_B02_COHORTS_PER_FARM -> 2 | H67: =ASM_B02_COHORTS_PER_FARM -> 2 | I67: =ASM_B02_COHORTS_PER_FARM -> 2 | J67: =ASM_B02_COHORTS_PER_FARM -> 2 | K67: =ASM_B02_COHORTS_PER_FARM -> 2 | L67: =ASM_B02_COHORTS_PER_FARM -> 2
B68: X01 — Farmers per cooperative farm (filière A) | C68: persons | D68: =SUM(E68:L68) -> 320 | E68: =ASM_X01_PER_UOF_FERMIERS -> 40 | F68: =ASM_X01_PER_UOF_FERMIERS -> 40 | G68: =ASM_X01_PER_UOF_FERMIERS -> 40 | H68: =ASM_X01_PER_UOF_FERMIERS -> 40 | I68: =ASM_X01_PER_UOF_FERMIERS -> 40 | J68: =ASM_X01_PER_UOF_FERMIERS -> 40 | K68: =ASM_X01_PER_UOF_FERMIERS -> 40 | L68: =ASM_X01_PER_UOF_FERMIERS -> 40
B69: X02 — Water technicians per farm (filière B) | C69: persons | D69: =SUM(E69:L69) -> 32 | E69: =ASM_X02_PER_UOF_TECH_EAU -> 4 | F69: =ASM_X02_PER_UOF_TECH_EAU -> 4 | G69: =ASM_X02_PER_UOF_TECH_EAU -> 4 | H69: =ASM_X02_PER_UOF_TECH_EAU -> 4 | I69: =ASM_X02_PER_UOF_TECH_EAU -> 4 | J69: =ASM_X02_PER_UOF_TECH_EAU -> 4 | K69: =ASM_X02_PER_UOF_TECH_EAU -> 4 | L69: =ASM_X02_PER_UOF_TECH_EAU -> 4
B70: X03 — Energy technicians per farm (filière C) | C70: persons | D70: =SUM(E70:L70) -> 16 | E70: =ASM_X03_PER_UOF_TECH_ENERGIE -> 2 | F70: =ASM_X03_PER_UOF_TECH_ENERGIE -> 2 | G70: =ASM_X03_PER_UOF_TECH_ENERGIE -> 2 | H70: =ASM_X03_PER_UOF_TECH_ENERGIE -> 2 | I70: =ASM_X03_PER_UOF_TECH_ENERGIE -> 2 | J70: =ASM_X03_PER_UOF_TECH_ENERGIE -> 2 | K70: =ASM_X03_PER_UOF_TECH_ENERGIE -> 2 | L70: =ASM_X03_PER_UOF_TECH_ENERGIE -> 2
B71: X04 — Mechanisation operators per farm (filière D) | C71: persons | D71: =SUM(E71:L71) -> 48 | E71: =ASM_X04_PER_UOF_MECA -> 6 | F71: =ASM_X04_PER_UOF_MECA -> 6 | G71: =ASM_X04_PER_UOF_MECA -> 6 | H71: =ASM_X04_PER_UOF_MECA -> 6 | I71: =ASM_X04_PER_UOF_MECA -> 6 | J71: =ASM_X04_PER_UOF_MECA -> 6 | K71: =ASM_X04_PER_UOF_MECA -> 6 | L71: =ASM_X04_PER_UOF_MECA -> 6
B72: X05 — Number of cooperative farms — Phase A wave | C72: UOFs | D72: =SUM(E72:L72) -> 80 | E72: =ASM_X05_N_UOF_PHASE_A -> 10 | F72: =ASM_X05_N_UOF_PHASE_A -> 10 | G72: =ASM_X05_N_UOF_PHASE_A -> 10 | H72: =ASM_X05_N_UOF_PHASE_A -> 10 | I72: =ASM_X05_N_UOF_PHASE_A -> 10 | J72: =ASM_X05_N_UOF_PHASE_A -> 10 | K72: =ASM_X05_N_UOF_PHASE_A -> 10 | L72: =ASM_X05_N_UOF_PHASE_A -> 10
B73: X07 — Bootstrap cohort — number of trainees | C73: persons | D73: =SUM(E73:L73) -> 960 | E73: =ASM_X07_COHORTE_0_TRAINEES -> 120 | F73: =ASM_X07_COHORTE_0_TRAINEES -> 120 | G73: =ASM_X07_COHORTE_0_TRAINEES -> 120 | H73: =ASM_X07_COHORTE_0_TRAINEES -> 120 | I73: =ASM_X07_COHORTE_0_TRAINEES -> 120 | J73: =ASM_X07_COHORTE_0_TRAINEES -> 120 | K73: =ASM_X07_COHORTE_0_TRAINEES -> 120 | L73: =ASM_X07_COHORTE_0_TRAINEES -> 120
B74: C01 — Duration — filière A | C74: months | D74: =SUM(E74:L74) -> 96 | E74: =ASM_C01_DURATION_A_MONTHS -> 12 | F74: =ASM_C01_DURATION_A_MONTHS -> 12 | G74: =ASM_C01_DURATION_A_MONTHS -> 12 | H74: =ASM_C01_DURATION_A_MONTHS -> 12 | I74: =ASM_C01_DURATION_A_MONTHS -> 12 | J74: =ASM_C01_DURATION_A_MONTHS -> 12 | K74: =ASM_C01_DURATION_A_MONTHS -> 12 | L74: =ASM_C01_DURATION_A_MONTHS -> 12
B75: C02 — Duration — filière B | C75: months | D75: =SUM(E75:L75) -> 72 | E75: =ASM_C02_DURATION_B_MONTHS -> 9 | F75: =ASM_C02_DURATION_B_MONTHS -> 9 | G75: =ASM_C02_DURATION_B_MONTHS -> 9 | H75: =ASM_C02_DURATION_B_MONTHS -> 9 | I75: =ASM_C02_DURATION_B_MONTHS -> 9 | J75: =ASM_C02_DURATION_B_MONTHS -> 9 | K75: =ASM_C02_DURATION_B_MONTHS -> 9 | L75: =ASM_C02_DURATION_B_MONTHS -> 9
B76: C03 — Duration — filière C | C76: months | D76: =SUM(E76:L76) -> 72 | E76: =ASM_C03_DURATION_C_MONTHS -> 9 | F76: =ASM_C03_DURATION_C_MONTHS -> 9 | G76: =ASM_C03_DURATION_C_MONTHS -> 9 | H76: =ASM_C03_DURATION_C_MONTHS -> 9 | I76: =ASM_C03_DURATION_C_MONTHS -> 9 | J76: =ASM_C03_DURATION_C_MONTHS -> 9 | K76: =ASM_C03_DURATION_C_MONTHS -> 9 | L76: =ASM_C03_DURATION_C_MONTHS -> 9
B77: C04 — Duration — filière D | C77: months | D77: =SUM(E77:L77) -> 96 | E77: =ASM_C04_DURATION_D_MONTHS -> 12 | F77: =ASM_C04_DURATION_D_MONTHS -> 12 | G77: =ASM_C04_DURATION_D_MONTHS -> 12 | H77: =ASM_C04_DURATION_D_MONTHS -> 12 | I77: =ASM_C04_DURATION_D_MONTHS -> 12 | J77: =ASM_C04_DURATION_D_MONTHS -> 12 | K77: =ASM_C04_DURATION_D_MONTHS -> 12 | L77: =ASM_C04_DURATION_D_MONTHS -> 12
B78: C05 — Gross daily stipend | C78: €/d | D78: =SUM(E78:L78) -> 56 | E78: =ASM_C05_STIPEND_PER_DAY_EUR -> 7 | F78: =ASM_C05_STIPEND_PER_DAY_EUR -> 7 | G78: =ASM_C05_STIPEND_PER_DAY_EUR -> 7 | H78: =ASM_C05_STIPEND_PER_DAY_EUR -> 7 | I78: =ASM_C05_STIPEND_PER_DAY_EUR -> 7 | J78: =ASM_C05_STIPEND_PER_DAY_EUR -> 7 | K78: =ASM_C05_STIPEND_PER_DAY_EUR -> 7 | L78: =ASM_C05_STIPEND_PER_DAY_EUR -> 7
B79: C06 — Productive work offset (from month 4) | C79: €/d | D79: =SUM(E79:L79) -> 40 | E79: =ASM_C06_WORK_OFFSET_PER_DAY_EUR -> 5 | F79: =ASM_C06_WORK_OFFSET_PER_DAY_EUR -> 5 | G79: =ASM_C06_WORK_OFFSET_PER_DAY_EUR -> 5 | H79: =ASM_C06_WORK_OFFSET_PER_DAY_EUR -> 5 | I79: =ASM_C06_WORK_OFFSET_PER_DAY_EUR -> 5 | J79: =ASM_C06_WORK_OFFSET_PER_DAY_EUR -> 5 | K79: =ASM_C06_WORK_OFFSET_PER_DAY_EUR -> 5 | L79: =ASM_C06_WORK_OFFSET_PER_DAY_EUR -> 5
B80: C07 — Work offset starts at month | C80: month | D80: =SUM(E80:L80) -> 24 | E80: =ASM_C07_OFFSET_START_MONTH -> 3 | F80: =ASM_C07_OFFSET_START_MONTH -> 3 | G80: =ASM_C07_OFFSET_START_MONTH -> 3 | H80: =ASM_C07_OFFSET_START_MONTH -> 3 | I80: =ASM_C07_OFFSET_START_MONTH -> 3 | J80: =ASM_C07_OFFSET_START_MONTH -> 3 | K80: =ASM_C07_OFFSET_START_MONTH -> 3 | L80: =ASM_C07_OFFSET_START_MONTH -> 3
B81: X08 — Calendar days per month | C81: days | D81: =SUM(E81:L81) -> 200 | E81: =ASM_X08_DAYS_PER_MONTH -> 25 | F81: =ASM_X08_DAYS_PER_MONTH -> 25 | G81: =ASM_X08_DAYS_PER_MONTH -> 25 | H81: =ASM_X08_DAYS_PER_MONTH -> 25 | I81: =ASM_X08_DAYS_PER_MONTH -> 25 | J81: =ASM_X08_DAYS_PER_MONTH -> 25 | K81: =ASM_X08_DAYS_PER_MONTH -> 25 | L81: =ASM_X08_DAYS_PER_MONTH -> 25
B82: D01 — Filière trainers (12 per farm × 3 farms) | C82: persons | D82: =SUM(E82:L82) -> 96 | E82: =ASM_D01_N_TRAINERS_FILIERE -> 12 | F82: =ASM_D01_N_TRAINERS_FILIERE -> 12 | G82: =ASM_D01_N_TRAINERS_FILIERE -> 12 | H82: =ASM_D01_N_TRAINERS_FILIERE -> 12 | I82: =ASM_D01_N_TRAINERS_FILIERE -> 12 | J82: =ASM_D01_N_TRAINERS_FILIERE -> 12 | K82: =ASM_D01_N_TRAINERS_FILIERE -> 12 | L82: =ASM_D01_N_TRAINERS_FILIERE -> 12
B83: D02 — Specialist trainers (shared pool) | C83: persons | D83: =SUM(E83:L83) -> 32 | E83: =ASM_D02_N_TRAINERS_SPECIALIST -> 4 | F83: =ASM_D02_N_TRAINERS_SPECIALIST -> 4 | G83: =ASM_D02_N_TRAINERS_SPECIALIST -> 4 | H83: =ASM_D02_N_TRAINERS_SPECIALIST -> 4 | I83: =ASM_D02_N_TRAINERS_SPECIALIST -> 4 | J83: =ASM_D02_N_TRAINERS_SPECIALIST -> 4 | K83: =ASM_D02_N_TRAINERS_SPECIALIST -> 4 | L83: =ASM_D02_N_TRAINERS_SPECIALIST -> 4
B84: D04 — Filière trainer — annual cost | C84: €/yr | D84: =SUM(E84:L84) -> 160000 | E84: =ASM_D04_COST_TRAINER_FILIERE_YEAR -> 20000 | F84: =ASM_D04_COST_TRAINER_FILIERE_YEAR -> 20000 | G84: =ASM_D04_COST_TRAINER_FILIERE_YEAR -> 20000 | H84: =ASM_D04_COST_TRAINER_FILIERE_YEAR -> 20000 | I84: =ASM_D04_COST_TRAINER_FILIERE_YEAR -> 20000 | J84: =ASM_D04_COST_TRAINER_FILIERE_YEAR -> 20000 | K84: =ASM_D04_COST_TRAINER_FILIERE_YEAR -> 20000 | L84: =ASM_D04_COST_TRAINER_FILIERE_YEAR -> 20000
B85: D05 — Specialist trainer — annual cost | C85: €/yr | D85: =SUM(E85:L85) -> 320000 | E85: =ASM_D05_COST_TRAINER_SPECIALIST_YEAR -> 40000 | F85: =ASM_D05_COST_TRAINER_SPECIALIST_YEAR -> 40000 | G85: =ASM_D05_COST_TRAINER_SPECIALIST_YEAR -> 40000 | H85: =ASM_D05_COST_TRAINER_SPECIALIST_YEAR -> 40000 | I85: =ASM_D05_COST_TRAINER_SPECIALIST_YEAR -> 40000 | J85: =ASM_D05_COST_TRAINER_SPECIALIST_YEAR -> 40000 | K85: =ASM_D05_COST_TRAINER_SPECIALIST_YEAR -> 40000 | L85: =ASM_D05_COST_TRAINER_SPECIALIST_YEAR -> 40000
B86: D06 — Filière trainers active years | C86: years | D86: =SUM(E86:L86) -> 16 | E86: =ASM_D06_YEARS_TRAINERS_ACTIVE -> 2 | F86: =ASM_D06_YEARS_TRAINERS_ACTIVE -> 2 | G86: =ASM_D06_YEARS_TRAINERS_ACTIVE -> 2 | H86: =ASM_D06_YEARS_TRAINERS_ACTIVE -> 2 | I86: =ASM_D06_YEARS_TRAINERS_ACTIVE -> 2 | J86: =ASM_D06_YEARS_TRAINERS_ACTIVE -> 2 | K86: =ASM_D06_YEARS_TRAINERS_ACTIVE -> 2 | L86: =ASM_D06_YEARS_TRAINERS_ACTIVE -> 2
B87: D07 — Specialist trainers active years | C87: years | D87: =SUM(E87:L87) -> 16 | E87: =ASM_D07_YEARS_SPECIALIST_ACTIVE -> 2 | F87: =ASM_D07_YEARS_SPECIALIST_ACTIVE -> 2 | G87: =ASM_D07_YEARS_SPECIALIST_ACTIVE -> 2 | H87: =ASM_D07_YEARS_SPECIALIST_ACTIVE -> 2 | I87: =ASM_D07_YEARS_SPECIALIST_ACTIVE -> 2 | J87: =ASM_D07_YEARS_SPECIALIST_ACTIVE -> 2 | K87: =ASM_D07_YEARS_SPECIALIST_ACTIVE -> 2 | L87: =ASM_D07_YEARS_SPECIALIST_ACTIVE -> 2
B88: D08 — Train-the-Trainer duration | C88: years | D88: =SUM(E88:L88) -> 8 | E88: =ASM_D08_DURATION_TOT_YEARS -> 1 | F88: =ASM_D08_DURATION_TOT_YEARS -> 1 | G88: =ASM_D08_DURATION_TOT_YEARS -> 1 | H88: =ASM_D08_DURATION_TOT_YEARS -> 1 | I88: =ASM_D08_DURATION_TOT_YEARS -> 1 | J88: =ASM_D08_DURATION_TOT_YEARS -> 1 | K88: =ASM_D08_DURATION_TOT_YEARS -> 1 | L88: =ASM_D08_DURATION_TOT_YEARS -> 1
B89: D09 — Train-the-Trainer cost per trainer per year | C89: €/yr | D89: =SUM(E89:L89) -> 144000 | E89: =ASM_D09_COST_TOT_PER_TRAINER_YEAR -> 18000 | F89: =ASM_D09_COST_TOT_PER_TRAINER_YEAR -> 18000 | G89: =ASM_D09_COST_TOT_PER_TRAINER_YEAR -> 18000 | H89: =ASM_D09_COST_TOT_PER_TRAINER_YEAR -> 18000 | I89: =ASM_D09_COST_TOT_PER_TRAINER_YEAR -> 18000 | J89: =ASM_D09_COST_TOT_PER_TRAINER_YEAR -> 18000 | K89: =ASM_D09_COST_TOT_PER_TRAINER_YEAR -> 18000 | L89: =ASM_D09_COST_TOT_PER_TRAINER_YEAR -> 18000
B90: X10 — International specialist trainers | C90: persons | D90: =SUM(E90:L90) -> 24 | E90: =ASM_X10_N_SPECIALISTS_INTL -> 3 | F90: =ASM_X10_N_SPECIALISTS_INTL -> 3 | G90: =ASM_X10_N_SPECIALISTS_INTL -> 3 | H90: =ASM_X10_N_SPECIALISTS_INTL -> 3 | I90: =ASM_X10_N_SPECIALISTS_INTL -> 3 | J90: =ASM_X10_N_SPECIALISTS_INTL -> 3 | K90: =ASM_X10_N_SPECIALISTS_INTL -> 3 | L90: =ASM_X10_N_SPECIALISTS_INTL -> 3
B91: X11 — International specialist — annual cost | C91: €/yr | D91: =SUM(E91:L91) -> 320000 | E91: =ASM_X11_COST_SPECIALIST_INTL_EUR_YR -> 40000 | F91: =ASM_X11_COST_SPECIALIST_INTL_EUR_YR -> 40000 | G91: =ASM_X11_COST_SPECIALIST_INTL_EUR_YR -> 40000 | H91: =ASM_X11_COST_SPECIALIST_INTL_EUR_YR -> 40000 | I91: =ASM_X11_COST_SPECIALIST_INTL_EUR_YR -> 40000 | J91: =ASM_X11_COST_SPECIALIST_INTL_EUR_YR -> 40000 | K91: =ASM_X11_COST_SPECIALIST_INTL_EUR_YR -> 40000 | L91: =ASM_X11_COST_SPECIALIST_INTL_EUR_YR -> 40000
B92: X12 — Total beds — Phase A | C92: beds | D92: =SUM(E92:L92) -> 1080 | E92: =ASM_X12_PHASE_A_TOTAL_BEDS -> 135 | F92: =ASM_X12_PHASE_A_TOTAL_BEDS -> 135 | G92: =ASM_X12_PHASE_A_TOTAL_BEDS -> 135 | H92: =ASM_X12_PHASE_A_TOTAL_BEDS -> 135 | I92: =ASM_X12_PHASE_A_TOTAL_BEDS -> 135 | J92: =ASM_X12_PHASE_A_TOTAL_BEDS -> 135 | K92: =ASM_X12_PHASE_A_TOTAL_BEDS -> 135 | L92: =ASM_X12_PHASE_A_TOTAL_BEDS -> 135
B93: X13 — Resident trainees — Phase A | C93: persons | D93: =SUM(E93:L93) -> 1080 | E93: =ASM_X13_PHASE_A_RESIDENTS -> 135 | F93: =ASM_X13_PHASE_A_RESIDENTS -> 135 | G93: =ASM_X13_PHASE_A_RESIDENTS -> 135 | H93: =ASM_X13_PHASE_A_RESIDENTS -> 135 | I93: =ASM_X13_PHASE_A_RESIDENTS -> 135 | J93: =ASM_X13_PHASE_A_RESIDENTS -> 135 | K93: =ASM_X13_PHASE_A_RESIDENTS -> 135 | L93: =ASM_X13_PHASE_A_RESIDENTS -> 135
B94: F03 — Dormitory cost per bed | C94: €/bed | D94: =SUM(E94:L94) -> 17600 | E94: =ASM_F03_COST_PER_TRAINEE_BED_EUR -> 2200 | F94: =ASM_F03_COST_PER_TRAINEE_BED_EUR -> 2200 | G94: =ASM_F03_COST_PER_TRAINEE_BED_EUR -> 2200 | H94: =ASM_F03_COST_PER_TRAINEE_BED_EUR -> 2200 | I94: =ASM_F03_COST_PER_TRAINEE_BED_EUR -> 2200 | J94: =ASM_F03_COST_PER_TRAINEE_BED_EUR -> 2200 | K94: =ASM_F03_COST_PER_TRAINEE_BED_EUR -> 2200 | L94: =ASM_F03_COST_PER_TRAINEE_BED_EUR -> 2200
B95: F04 — Refectory & common areas per farm | C95: €/farm | D95: =SUM(E95:L95) -> 128000 | E95: =ASM_F04_COST_REFECTOIRE_PER_FARM_EUR -> 16000 | F95: =ASM_F04_COST_REFECTOIRE_PER_FARM_EUR -> 16000 | G95: =ASM_F04_COST_REFECTOIRE_PER_FARM_EUR -> 16000 | H95: =ASM_F04_COST_REFECTOIRE_PER_FARM_EUR -> 16000 | I95: =ASM_F04_COST_REFECTOIRE_PER_FARM_EUR -> 16000 | J95: =ASM_F04_COST_REFECTOIRE_PER_FARM_EUR -> 16000 | K95: =ASM_F04_COST_REFECTOIRE_PER_FARM_EUR -> 16000 | L95: =ASM_F04_COST_REFECTOIRE_PER_FARM_EUR -> 16000
B96: F05 — Residents requiring family housing | C96: % | D96: =SUM(E96:L96) -> 1.2 | E96: =ASM_F05_PCT_RESIDENTS_FAMILY_HOUSING -> 0.15 | F96: =ASM_F05_PCT_RESIDENTS_FAMILY_HOUSING -> 0.15 | G96: =ASM_F05_PCT_RESIDENTS_FAMILY_HOUSING -> 0.15 | H96: =ASM_F05_PCT_RESIDENTS_FAMILY_HOUSING -> 0.15 | I96: =ASM_F05_PCT_RESIDENTS_FAMILY_HOUSING -> 0.15 | J96: =ASM_F05_PCT_RESIDENTS_FAMILY_HOUSING -> 0.15 | K96: =ASM_F05_PCT_RESIDENTS_FAMILY_HOUSING -> 0.15 | L96: =ASM_F05_PCT_RESIDENTS_FAMILY_HOUSING -> 0.15
B97: F07 — Family housing cost per unit | C97: €/unit | D97: =SUM(E97:L97) -> 16000 | E97: =ASM_F07_COST_PER_FAMILY_UNIT_EUR -> 2000 | F97: =ASM_F07_COST_PER_FAMILY_UNIT_EUR -> 2000 | G97: =ASM_F07_COST_PER_FAMILY_UNIT_EUR -> 2000 | H97: =ASM_F07_COST_PER_FAMILY_UNIT_EUR -> 2000 | I97: =ASM_F07_COST_PER_FAMILY_UNIT_EUR -> 2000 | J97: =ASM_F07_COST_PER_FAMILY_UNIT_EUR -> 2000 | K97: =ASM_F07_COST_PER_FAMILY_UNIT_EUR -> 2000 | L97: =ASM_F07_COST_PER_FAMILY_UNIT_EUR -> 2000
B98: G01 — Curriculum design + certification partner | C98: € | D98: =SUM(E98:L98) -> 1760000 | E98: =ASM_G01_COST_CURRICULUM_SETUP_EUR -> 220000 | F98: =ASM_G01_COST_CURRICULUM_SETUP_EUR -> 220000 | G98: =ASM_G01_COST_CURRICULUM_SETUP_EUR -> 220000 | H98: =ASM_G01_COST_CURRICULUM_SETUP_EUR -> 220000 | I98: =ASM_G01_COST_CURRICULUM_SETUP_EUR -> 220000 | J98: =ASM_G01_COST_CURRICULUM_SETUP_EUR -> 220000 | K98: =ASM_G01_COST_CURRICULUM_SETUP_EUR -> 220000 | L98: =ASM_G01_COST_CURRICULUM_SETUP_EUR -> 220000
B99: G02 — Classroom equipment per farm | C99: €/farm | D99: =SUM(E99:L99) -> 360000 | E99: =ASM_G02_COST_PEDAGOGICAL_EQUIP_PER_FARM_EUR -> 45000 | F99: =ASM_G02_COST_PEDAGOGICAL_EQUIP_PER_FARM_EUR -> 45000 | G99: =ASM_G02_COST_PEDAGOGICAL_EQUIP_PER_FARM_EUR -> 45000 | H99: =ASM_G02_COST_PEDAGOGICAL_EQUIP_PER_FARM_EUR -> 45000 | I99: =ASM_G02_COST_PEDAGOGICAL_EQUIP_PER_FARM_EUR -> 45000 | J99: =ASM_G02_COST_PEDAGOGICAL_EQUIP_PER_FARM_EUR -> 45000 | K99: =ASM_G02_COST_PEDAGOGICAL_EQUIP_PER_FARM_EUR -> 45000 | L99: =ASM_G02_COST_PEDAGOGICAL_EQUIP_PER_FARM_EUR -> 45000
B100: G03 — Number of filière curricula | C100: count | D100: =SUM(E100:L100) -> 16 | E100: =ASM_G03_N_FILIERE_CURRICULA -> 2 | F100: =ASM_G03_N_FILIERE_CURRICULA -> 2 | G100: =ASM_G03_N_FILIERE_CURRICULA -> 2 | H100: =ASM_G03_N_FILIERE_CURRICULA -> 2 | I100: =ASM_G03_N_FILIERE_CURRICULA -> 2 | J100: =ASM_G03_N_FILIERE_CURRICULA -> 2 | K100: =ASM_G03_N_FILIERE_CURRICULA -> 2 | L100: =ASM_G03_N_FILIERE_CURRICULA -> 2
B101: G04 — Curriculum materials per filière | C101: €/filière | D101: =SUM(E101:L101) -> 200000 | E101: =ASM_G04_COST_CURRICULUM_PER_FILIERE_EUR -> 25000 | F101: =ASM_G04_COST_CURRICULUM_PER_FILIERE_EUR -> 25000 | G101: =ASM_G04_COST_CURRICULUM_PER_FILIERE_EUR -> 25000 | H101: =ASM_G04_COST_CURRICULUM_PER_FILIERE_EUR -> 25000 | I101: =ASM_G04_COST_CURRICULUM_PER_FILIERE_EUR -> 25000 | J101: =ASM_G04_COST_CURRICULUM_PER_FILIERE_EUR -> 25000 | K101: =ASM_G04_COST_CURRICULUM_PER_FILIERE_EUR -> 25000 | L101: =ASM_G04_COST_CURRICULUM_PER_FILIERE_EUR -> 25000
B102: H01 — Certification partner (set-up + 5 years) | C102: € | D102: =SUM(E102:L102) -> 0 | E102: =ASM_H01_COST_CERTIFICATION_SETUP_EUR -> 0 | F102: =ASM_H01_COST_CERTIFICATION_SETUP_EUR -> 0 | G102: =ASM_H01_COST_CERTIFICATION_SETUP_EUR -> 0 | H102: =ASM_H01_COST_CERTIFICATION_SETUP_EUR -> 0 | I102: =ASM_H01_COST_CERTIFICATION_SETUP_EUR -> 0 | J102: =ASM_H01_COST_CERTIFICATION_SETUP_EUR -> 0 | K102: =ASM_H01_COST_CERTIFICATION_SETUP_EUR -> 0 | L102: =ASM_H01_COST_CERTIFICATION_SETUP_EUR -> 0
B103: H02 — Monitoring equipment (plots) | C103: € | D103: =SUM(E103:L103) -> 480000 | E103: =ASM_H02_COST_MONITORING_EQUIP_EUR -> 60000 | F103: =ASM_H02_COST_MONITORING_EQUIP_EUR -> 60000 | G103: =ASM_H02_COST_MONITORING_EQUIP_EUR -> 60000 | H103: =ASM_H02_COST_MONITORING_EQUIP_EUR -> 60000 | I103: =ASM_H02_COST_MONITORING_EQUIP_EUR -> 60000 | J103: =ASM_H02_COST_MONITORING_EQUIP_EUR -> 60000 | K103: =ASM_H02_COST_MONITORING_EQUIP_EUR -> 60000 | L103: =ASM_H02_COST_MONITORING_EQUIP_EUR -> 60000
B104: H03 — Data coordinator — annual | C104: €/yr | D104: =SUM(E104:L104) -> 320000 | E104: =ASM_H03_COST_COORDINATOR_YEAR_EUR -> 40000 | F104: =ASM_H03_COST_COORDINATOR_YEAR_EUR -> 40000 | G104: =ASM_H03_COST_COORDINATOR_YEAR_EUR -> 40000 | H104: =ASM_H03_COST_COORDINATOR_YEAR_EUR -> 40000 | I104: =ASM_H03_COST_COORDINATOR_YEAR_EUR -> 40000 | J104: =ASM_H03_COST_COORDINATOR_YEAR_EUR -> 40000 | K104: =ASM_H03_COST_COORDINATOR_YEAR_EUR -> 40000 | L104: =ASM_H03_COST_COORDINATOR_YEAR_EUR -> 40000
B105: H04 — Monitoring years (Y1 → Y6) | C105: years | D105: =SUM(E105:L105) -> 16 | E105: =ASM_H04_N_YEARS_MONITORING -> 2 | F105: =ASM_H04_N_YEARS_MONITORING -> 2 | G105: =ASM_H04_N_YEARS_MONITORING -> 2 | H105: =ASM_H04_N_YEARS_MONITORING -> 2 | I105: =ASM_H04_N_YEARS_MONITORING -> 2 | J105: =ASM_H04_N_YEARS_MONITORING -> 2 | K105: =ASM_H04_N_YEARS_MONITORING -> 2 | L105: =ASM_H04_N_YEARS_MONITORING -> 2
B106: H05 — Communication materials | C106: € | D106: =SUM(E106:L106) -> 160000 | E106: =ASM_H05_COST_COMMS_MATERIALS_EUR -> 20000 | F106: =ASM_H05_COST_COMMS_MATERIALS_EUR -> 20000 | G106: =ASM_H05_COST_COMMS_MATERIALS_EUR -> 20000 | H106: =ASM_H05_COST_COMMS_MATERIALS_EUR -> 20000 | I106: =ASM_H05_COST_COMMS_MATERIALS_EUR -> 20000 | J106: =ASM_H05_COST_COMMS_MATERIALS_EUR -> 20000 | K106: =ASM_H05_COST_COMMS_MATERIALS_EUR -> 20000 | L106: =ASM_H05_COST_COMMS_MATERIALS_EUR -> 20000
B107: H06 — Communication officer — annual | C107: €/yr | D107: =SUM(E107:L107) -> 120000 | E107: =ASM_H06_COST_COMMS_OFFICER_YEAR_EUR -> 15000 | F107: =ASM_H06_COST_COMMS_OFFICER_YEAR_EUR -> 15000 | G107: =ASM_H06_COST_COMMS_OFFICER_YEAR_EUR -> 15000 | H107: =ASM_H06_COST_COMMS_OFFICER_YEAR_EUR -> 15000 | I107: =ASM_H06_COST_COMMS_OFFICER_YEAR_EUR -> 15000 | J107: =ASM_H06_COST_COMMS_OFFICER_YEAR_EUR -> 15000 | K107: =ASM_H06_COST_COMMS_OFFICER_YEAR_EUR -> 15000 | L107: =ASM_H06_COST_COMMS_OFFICER_YEAR_EUR -> 15000
B108: H07 — External visits — number of years | C108: years | D108: =SUM(E108:L108) -> 16 | E108: =ASM_H07_N_YEARS_O3 -> 2 | F108: =ASM_H07_N_YEARS_O3 -> 2 | G108: =ASM_H07_N_YEARS_O3 -> 2 | H108: =ASM_H07_N_YEARS_O3 -> 2 | I108: =ASM_H07_N_YEARS_O3 -> 2 | J108: =ASM_H07_N_YEARS_O3 -> 2 | K108: =ASM_H07_N_YEARS_O3 -> 2 | L108: =ASM_H07_N_YEARS_O3 -> 2
B110: Calculated values
B111: B04 — Annual throughput | C111: persons/yr | D111: =SUM(E111:L111) -> 2160 | E111: =E$65*E$66 -> 270 | F111: =F$65*F$66 -> 270 | G111: =G$65*G$66 -> 270 | H111: =H$65*H$66 -> 270 | I111: =I$65*I$66 -> 270 | J111: =J$65*J$66 -> 270 | K111: =K$65*K$66 -> 270 | L111: =L$65*L$66 -> 270
B112: ΣX01:X04 — Sum per-UOF staffing | C112: persons | D112: =SUM(E112:L112) -> 416 | E112: =E$68+E$69+E$70+E$71 -> 52 | F112: =F$68+F$69+F$70+F$71 -> 52 | G112: =G$68+G$69+G$70+G$71 -> 52 | H112: =H$68+H$69+H$70+H$71 -> 52 | I112: =I$68+I$69+I$70+I$71 -> 52 | J112: =J$68+J$69+J$70+J$71 -> 52 | K112: =K$68+K$69+K$70+K$71 -> 52 | L112: =L$68+L$69+L$70+L$71 -> 52
...

Sheet 04_Genetics
B1: 04 — Block 3 Genetics (animal + plant) [€] ← feeds 05_CAPEX · 07_Revenue · 08_OpEx · 06_S&U
D3: Total | E3: Y-1 | F3: Y0 | G3: Y1 | H3: Y2 | I3: Y3 | J3: Y4 | K3: Y5 | L3: Y6
E4: -1 | F4: 0 | G4: 1 | H4: 2 | I4: 3 | J4: 4 | K4: 5 | L4: 6
B6: Summary
B7: 1. Animal genetics — hardware | C7: € | D7: =SUM(E7:L7) -> 298401 | E7: =E20 -> 0 | F7: =F20 -> 298401 | G7: =G20 -> 0 | H7: =H20 -> 0 | I7: =I20 -> 0 | J7: =J20 -> 0 | K7: =K20 -> 0 | L7: =L20 -> 0
B8: 2. Animal genetics — operations (pre-op + recurring) | C8: € | D8: =SUM(E8:L8) -> 388360 | E8: =E26+E34 -> 0 | F8: =F26+F34 -> 104800 | G8: =G26+G34 -> 141780 | H8: =H26+H34 -> 141780 | I8: =I26+I34 -> 0 | J8: =J26+J34 -> 0 | K8: =K26+K34 -> 0 | L8: =L26+L34 -> 0
B9: 3. Plant genetics — hardware | C9: € | D9: =SUM(E9:L9) -> 200000 | E9: =E40 -> 0 | F9: =F40 -> 200000 | G9: =G40 -> 0 | H9: =H40 -> 0 | I9: =I40 -> 0 | J9: =J40 -> 0 | K9: =K40 -> 0 | L9: =L40 -> 0
B10: 4. Plant genetics — operations (pre-op + recurring) | C10: € | D10: =SUM(E10:L10) -> 291000 | E10: =E48+E55 -> 0 | F10: =F48+F55 -> 73000 | G10: =G48+G55 -> 109000 | H10: =H48+H55 -> 109000 | I10: =I48+I55 -> 0 | J10: =J48+J55 -> 0 | K10: =K48+K55 -> 0 | L10: =L48+L55 -> 0
B11: 5. Genetics programme revenue (= 0; grant-funded) | C11: € | D11: =SUM(E11:L11) -> 0 | E11: =0 -> 0 | F11: =0 -> 0 | G11: =0 -> 0 | H11: =0 -> 0 | I11: =0 -> 0 | J11: =0 -> 0 | K11: =0 -> 0 | L11: =0 -> 0
B12: TOTAL GENETICS PROGRAMME COST | C12: € | D12: =SUM(E12:L12) -> 1177761 | E12: =E7+E8+E9+E10-E11 -> 0 | F12: =F7+F8+F9+F10-F11 -> 676201 | G12: =G7+G8+G9+G10-G11 -> 250780 | H12: =H7+H8+H9+H10-H11 -> 250780 | I12: =I7+I8+I9+I10-I11 -> 0 | J12: =J7+J8+J9+J10-J11 -> 0 | K12: =K7+K8+K9+K10-K11 -> 0 | L12: =L7+L8+L9+L10-L11 -> 0
B14: Animal genetics
B15: Hardware (one-time, Y0)
B16: Veterinary centre (standalone building) | C16: € | D16: =SUM(E16:L16) -> 125000 | E16: =$F$59*FLAG_CONSTRUCT_YM1 -> 0 | F16: =$F$59*FLAG_CONSTRUCT_Y0 -> 125000 | G16: =$F$59*FLAG_CONSTRUCT_Y1 -> 0 | H16: =$F$59*FLAG_CONSTRUCT_Y2 -> 0 | I16: =$F$59*FLAG_CONSTRUCT_Y3 -> 0 | J16: =$F$59*FLAG_CONSTRUCT_Y4 -> 0 | K16: =$F$59*FLAG_CONSTRUCT_Y5 -> 0 | L16: =$F$59*FLAG_CONSTRUCT_Y6 -> 0
B17: Animal equipment (pharma + lab + restraint) | C17: € | D17: =SUM(E17:L17) -> 150000 | E17: =$F$60*FLAG_CONSTRUCT_YM1 -> 0 | F17: =$F$60*FLAG_CONSTRUCT_Y0 -> 150000 | G17: =$F$60*FLAG_CONSTRUCT_Y1 -> 0 | H17: =$F$60*FLAG_CONSTRUCT_Y2 -> 0 | I17: =$F$60*FLAG_CONSTRUCT_Y3 -> 0 | J17: =$F$60*FLAG_CONSTRUCT_Y4 -> 0 | K17: =$F$60*FLAG_CONSTRUCT_Y5 -> 0 | L17: =$F$60*FLAG_CONSTRUCT_Y6 -> 0
B18: Identification system per farm (PREMIUM tier) | C18: € | D18: =SUM(E18:L18) -> 15000 | E18: =ASM_A01_N_FARMS*$F$61*FLAG_CONSTRUCT_YM1 -> 0 | F18: =ASM_A01_N_FARMS*$F$61*FLAG_CONSTRUCT_Y0 -> 15000 | G18: =ASM_A01_N_FARMS*$F$61*FLAG_CONSTRUCT_Y1 -> 0 | H18: =ASM_A01_N_FARMS*$F$61*FLAG_CONSTRUCT_Y2 -> 0 | I18: =ASM_A01_N_FARMS*$F$61*FLAG_CONSTRUCT_Y3 -> 0 | J18: =ASM_A01_N_FARMS*$F$61*FLAG_CONSTRUCT_Y4 -> 0 | K18: =ASM_A01_N_FARMS*$F$61*FLAG_CONSTRUCT_Y5 -> 0 | L18: =ASM_A01_N_FARMS*$F$61*FLAG_CONSTRUCT_Y6 -> 0
B19: AI hardware (shared — tank + ultrasound) | C19: € | D19: =SUM(E19:L19) -> 8401 | E19: =$F$62*FLAG_CONSTRUCT_YM1 -> 0 | F19: =$F$62*FLAG_CONSTRUCT_Y0 -> 8401 | G19: =$F$62*FLAG_CONSTRUCT_Y1 -> 0 | H19: =$F$62*FLAG_CONSTRUCT_Y2 -> 0 | I19: =$F$62*FLAG_CONSTRUCT_Y3 -> 0 | J19: =$F$62*FLAG_CONSTRUCT_Y4 -> 0 | K19: =$F$62*FLAG_CONSTRUCT_Y5 -> 0 | L19: =$F$62*FLAG_CONSTRUCT_Y6 -> 0
B20: Subtotal — Animal genetics hardware | C20: € | D20: =SUM(D16:D19) -> 298401 | E20: =SUM(E16:E19) -> 0 | F20: =SUM(F16:F19) -> 298401 | G20: =SUM(G16:G19) -> 0 | H20: =SUM(H16:H19) -> 0 | I20: =SUM(I16:I19) -> 0 | J20: =SUM(J16:J19) -> 0 | K20: =SUM(K16:K19) -> 0 | L20: =SUM(L16:L19) -> 0
B22: Pre-op (one-time Y0 expense)
B23: Partner support per farm (PREMIUM, pre-op) | C23: € | D23: =SUM(E23:L23) -> 72000 | E23: =ASM_A01_N_FARMS*$F$63*FLAG_CONSTRUCT_YM1 -> 0 | F23: =ASM_A01_N_FARMS*$F$63*FLAG_CONSTRUCT_Y0 -> 72000 | G23: =ASM_A01_N_FARMS*$F$63*FLAG_CONSTRUCT_Y1 -> 0 | H23: =ASM_A01_N_FARMS*$F$63*FLAG_CONSTRUCT_Y2 -> 0 | I23: =ASM_A01_N_FARMS*$F$63*FLAG_CONSTRUCT_Y3 -> 0 | J23: =ASM_A01_N_FARMS*$F$63*FLAG_CONSTRUCT_Y4 -> 0 | K23: =ASM_A01_N_FARMS*$F$63*FLAG_CONSTRUCT_Y5 -> 0 | L23: =ASM_A01_N_FARMS*$F$63*FLAG_CONSTRUCT_Y6 -> 0
B24: Inseminator training (3 months, pre-op) | C24: € | D24: =SUM(E24:L24) -> 25300 | E24: =$F$64*FLAG_CONSTRUCT_YM1 -> 0 | F24: =$F$64*FLAG_CONSTRUCT_Y0 -> 25300 | G24: =$F$64*FLAG_CONSTRUCT_Y1 -> 0 | H24: =$F$64*FLAG_CONSTRUCT_Y2 -> 0 | I24: =$F$64*FLAG_CONSTRUCT_Y3 -> 0 | J24: =$F$64*FLAG_CONSTRUCT_Y4 -> 0 | K24: =$F$64*FLAG_CONSTRUCT_Y5 -> 0 | L24: =$F$64*FLAG_CONSTRUCT_Y6 -> 0
B25: Initial AI doses (working capital) | C25: € | D25: =SUM(E25:L25) -> 7500 | E25: =$F$65*$F$66*FLAG_CONSTRUCT_YM1 -> 0 | F25: =$F$65*$F$66*FLAG_CONSTRUCT_Y0 -> 7500 | G25: =$F$65*$F$66*FLAG_CONSTRUCT_Y1 -> 0 | H25: =$F$65*$F$66*FLAG_CONSTRUCT_Y2 -> 0 | I25: =$F$65*$F$66*FLAG_CONSTRUCT_Y3 -> 0 | J25: =$F$65*$F$66*FLAG_CONSTRUCT_Y4 -> 0 | K25: =$F$65*$F$66*FLAG_CONSTRUCT_Y5 -> 0 | L25: =$F$65*$F$66*FLAG_CONSTRUCT_Y6 -> 0
B26: Subtotal — Animal genetics pre-op | C26: € | D26: =SUM(D23:D25) -> 104800 | E26: =SUM(E23:E25) -> 0 | F26: =SUM(F23:F25) -> 104800 | G26: =SUM(G23:G25) -> 0 | H26: =SUM(H23:H25) -> 0 | I26: =SUM(I23:I25) -> 0 | J26: =SUM(J23:J25) -> 0 | K26: =SUM(K23:K25) -> 0 | L26: =SUM(L23:L25) -> 0
B28: Recurring (annual, post-commissioning)
B29: Herd-management software per farm | C29: €/yr | D29: =SUM(E29:L29) -> 4560 | E29: =ASM_A01_N_FARMS*$F$67*FLAG_VALIDATION_YM1 -> 0 | F29: =ASM_A01_N_FARMS*$F$67*FLAG_VALIDATION_Y0 -> 0 | G29: =ASM_A01_N_FARMS*$F$67*FLAG_VALIDATION_Y1 -> 2280 | H29: =ASM_A01_N_FARMS*$F$67*FLAG_VALIDATION_Y2 -> 2280 | I29: =ASM_A01_N_FARMS*$F$67*FLAG_VALIDATION_Y3 -> 0 | J29: =ASM_A01_N_FARMS*$F$67*FLAG_VALIDATION_Y4 -> 0 | K29: =ASM_A01_N_FARMS*$F$67*FLAG_VALIDATION_Y5 -> 0 | L29: =ASM_A01_N_FARMS*$F$67*FLAG_VALIDATION_Y6 -> 0
B30: Local inseminator salary | C30: €/yr | D30: =SUM(E30:L30) -> 13000 | E30: =$F$68*FLAG_VALIDATION_YM1 -> 0 | F30: =$F$68*FLAG_VALIDATION_Y0 -> 0 | G30: =$F$68*FLAG_VALIDATION_Y1 -> 6500 | H30: =$F$68*FLAG_VALIDATION_Y2 -> 6500 | I30: =$F$68*FLAG_VALIDATION_Y3 -> 0 | J30: =$F$68*FLAG_VALIDATION_Y4 -> 0 | K30: =$F$68*FLAG_VALIDATION_Y5 -> 0 | L30: =$F$68*FLAG_VALIDATION_Y6 -> 0
B31: Veterinary inputs across herd (vaccines, prophylaxis) | C31: €/yr | D31: =SUM(E31:L31) -> 36000 | E31: =$F$69*$F$70*FLAG_VALIDATION_YM1 -> 0 | F31: =$F$69*$F$70*FLAG_VALIDATION_Y0 -> 0 | G31: =$F$69*$F$70*FLAG_VALIDATION_Y1 -> 18000 | H31: =$F$69*$F$70*FLAG_VALIDATION_Y2 -> 18000 | I31: =$F$69*$F$70*FLAG_VALIDATION_Y3 -> 0 | J31: =$F$69*$F$70*FLAG_VALIDATION_Y4 -> 0 | K31: =$F$69*$F$70*FLAG_VALIDATION_Y5 -> 0 | L31: =$F$69*$F$70*FLAG_VALIDATION_Y6 -> 0
B32: Programme management (Y1+Y2) | C32: €/yr | D32: =SUM(E32:L32) -> 158700 | E32: =$F$71*FLAG_VALIDATION_YM1 -> 0 | F32: =$F$71*FLAG_VALIDATION_Y0 -> 0 | G32: =$F$71*FLAG_VALIDATION_Y1 -> 79350 | H32: =$F$71*FLAG_VALIDATION_Y2 -> 79350 | I32: =$F$71*FLAG_VALIDATION_Y3 -> 0 | J32: =$F$71*FLAG_VALIDATION_Y4 -> 0 | K32: =$F$71*FLAG_VALIDATION_Y5 -> 0 | L32: =$F$71*FLAG_VALIDATION_Y6 -> 0
B33: Consumables (Y1+Y2) | C33: €/yr | D33: =SUM(E33:L33) -> 71300 | E33: =$F$72*FLAG_VALIDATION_YM1 -> 0 | F33: =$F$72*FLAG_VALIDATION_Y0 -> 0 | G33: =$F$72*FLAG_VALIDATION_Y1 -> 35650 | H33: =$F$72*FLAG_VALIDATION_Y2 -> 35650 | I33: =$F$72*FLAG_VALIDATION_Y3 -> 0 | J33: =$F$72*FLAG_VALIDATION_Y4 -> 0 | K33: =$F$72*FLAG_VALIDATION_Y5 -> 0 | L33: =$F$72*FLAG_VALIDATION_Y6 -> 0
B34: Subtotal — Animal genetics recurring | C34: € | D34: =SUM(D29:D33) -> 283560 | E34: =SUM(E29:E33) -> 0 | F34: =SUM(F29:F33) -> 0 | G34: =SUM(G29:G33) -> 141780 | H34: =SUM(H29:H33) -> 141780 | I34: =SUM(I29:I33) -> 0 | J34: =SUM(J29:J33) -> 0 | K34: =SUM(K29:K33) -> 0 | L34: =SUM(L29:L33) -> 0
B36: Plant genetics
B37: Hardware (one-time, Y0)
B38: Plant centre building (500 m² covered) | C38: € | D38: =SUM(E38:L38) -> 125000 | E38: =$F$75*FLAG_CONSTRUCT_YM1 -> 0 | F38: =$F$75*FLAG_CONSTRUCT_Y0 -> 125000 | G38: =$F$75*FLAG_CONSTRUCT_Y1 -> 0 | H38: =$F$75*FLAG_CONSTRUCT_Y2 -> 0 | I38: =$F$75*FLAG_CONSTRUCT_Y3 -> 0 | J38: =$F$75*FLAG_CONSTRUCT_Y4 -> 0 | K38: =$F$75*FLAG_CONSTRUCT_Y5 -> 0 | L38: =$F$75*FLAG_CONSTRUCT_Y6 -> 0
B39: Plant equipment (germinators + drip + greenhouse + tools) | C39: € | D39: =SUM(E39:L39) -> 75000 | E39: =$F$76*FLAG_CONSTRUCT_YM1 -> 0 | F39: =$F$76*FLAG_CONSTRUCT_Y0 -> 75000 | G39: =$F$76*FLAG_CONSTRUCT_Y1 -> 0 | H39: =$F$76*FLAG_CONSTRUCT_Y2 -> 0 | I39: =$F$76*FLAG_CONSTRUCT_Y3 -> 0 | J39: =$F$76*FLAG_CONSTRUCT_Y4 -> 0 | K39: =$F$76*FLAG_CONSTRUCT_Y5 -> 0 | L39: =$F$76*FLAG_CONSTRUCT_Y6 -> 0
B40: Subtotal — Plant genetics hardware | C40: € | D40: =SUM(D38:D39) -> 200000 | E40: =SUM(E38:E39) -> 0 | F40: =SUM(F38:F39) -> 200000 | G40: =SUM(G38:G39) -> 0 | H40: =SUM(H38:H39) -> 0 | I40: =SUM(I38:I39) -> 0 | J40: =SUM(J38:J39) -> 0 | K40: =SUM(K38:K39) -> 0 | L40: =SUM(L38:L39) -> 0
B42: Pre-op (one-time Y0 expense)
B43: Nursery operator training (3 months, pre-op) | C43: € | D43: =SUM(E43:L43) -> 17000 | E43: =$F$77*FLAG_CONSTRUCT_YM1 -> 0 | F43: =$F$77*FLAG_CONSTRUCT_Y0 -> 17000 | G43: =$F$77*FLAG_CONSTRUCT_Y1 -> 0 | H43: =$F$77*FLAG_CONSTRUCT_Y2 -> 0 | I43: =$F$77*FLAG_CONSTRUCT_Y3 -> 0 | J43: =$F$77*FLAG_CONSTRUCT_Y4 -> 0 | K43: =$F$77*FLAG_CONSTRUCT_Y5 -> 0 | L43: =$F$77*FLAG_CONSTRUCT_Y6 -> 0
B44: Plant partner support (pre-op) | C44: € | D44: =SUM(E44:L44) -> 24000 | E44: =$F$78*FLAG_CONSTRUCT_YM1 -> 0 | F44: =$F$78*FLAG_CONSTRUCT_Y0 -> 24000 | G44: =$F$78*FLAG_CONSTRUCT_Y1 -> 0 | H44: =$F$78*FLAG_CONSTRUCT_Y2 -> 0 | I44: =$F$78*FLAG_CONSTRUCT_Y3 -> 0 | J44: =$F$78*FLAG_CONSTRUCT_Y4 -> 0 | K44: =$F$78*FLAG_CONSTRUCT_Y5 -> 0 | L44: =$F$78*FLAG_CONSTRUCT_Y6 -> 0
B45: Imported G0 seeds (working capital) | C45: € | D45: =SUM(E45:L45) -> 8000 | E45: =$F$79*FLAG_CONSTRUCT_YM1 -> 0 | F45: =$F$79*FLAG_CONSTRUCT_Y0 -> 8000 | G45: =$F$79*FLAG_CONSTRUCT_Y1 -> 0 | H45: =$F$79*FLAG_CONSTRUCT_Y2 -> 0 | I45: =$F$79*FLAG_CONSTRUCT_Y3 -> 0 | J45: =$F$79*FLAG_CONSTRUCT_Y4 -> 0 | K45: =$F$79*FLAG_CONSTRUCT_Y5 -> 0 | L45: =$F$79*FLAG_CONSTRUCT_Y6 -> 0
B46: Mother trees (acacia / faidherbia / fruit) | C46: € | D46: =SUM(E46:L46) -> 18000 | E46: =$F$80*FLAG_CONSTRUCT_YM1 -> 0 | F46: =$F$80*FLAG_CONSTRUCT_Y0 -> 18000 | G46: =$F$80*FLAG_CONSTRUCT_Y1 -> 0 | H46: =$F$80*FLAG_CONSTRUCT_Y2 -> 0 | I46: =$F$80*FLAG_CONSTRUCT_Y3 -> 0 | J46: =$F$80*FLAG_CONSTRUCT_Y4 -> 0 | K46: =$F$80*FLAG_CONSTRUCT_Y5 -> 0 | L46: =$F$80*FLAG_CONSTRUCT_Y6 -> 0
B47: Acacia senegal mother nursery (gum arabic) | C47: € | D47: =SUM(E47:L47) -> 6000 | E47: =$F$81*FLAG_CONSTRUCT_YM1 -> 0 | F47: =$F$81*FLAG_CONSTRUCT_Y0 -> 6000 | G47: =$F$81*FLAG_CONSTRUCT_Y1 -> 0 | H47: =$F$81*FLAG_CONSTRUCT_Y2 -> 0 | I47: =$F$81*FLAG_CONSTRUCT_Y3 -> 0 | J47: =$F$81*FLAG_CONSTRUCT_Y4 -> 0 | K47: =$F$81*FLAG_CONSTRUCT_Y5 -> 0 | L47: =$F$81*FLAG_CONSTRUCT_Y6 -> 0
B48: Subtotal — Plant genetics pre-op | C48: € | D48: =SUM(D43:D47) -> 73000 | E48: =SUM(E43:E47) -> 0 | F48: =SUM(F43:F47) -> 73000 | G48: =SUM(G43:G47) -> 0 | H48: =SUM(H43:H47) -> 0 | I48: =SUM(I43:I47) -> 0 | J48: =SUM(J43:J47) -> 0 | K48: =SUM(K43:K47) -> 0 | L48: =SUM(L43:L47) -> 0
B50: Recurring (annual, post-commissioning)
B51: Plant inputs (substrate, pots, water, energy) | C51: €/yr | D51: =SUM(E51:L51) -> 36000 | E51: =$F$82*FLAG_VALIDATION_YM1 -> 0 | F51: =$F$82*FLAG_VALIDATION_Y0 -> 0 | G51: =$F$82*FLAG_VALIDATION_Y1 -> 18000 | H51: =$F$82*FLAG_VALIDATION_Y2 -> 18000 | I51: =$F$82*FLAG_VALIDATION_Y3 -> 0 | J51: =$F$82*FLAG_VALIDATION_Y4 -> 0 | K51: =$F$82*FLAG_VALIDATION_Y5 -> 0 | L51: =$F$82*FLAG_VALIDATION_Y6 -> 0
B52: Plant centre staff (1 agronomist + 2 workers + 1 technician) | C52: €/yr | D52: =SUM(E52:L52) -> 32000 | E52: =$F$83*FLAG_VALIDATION_YM1 -> 0 | F52: =$F$83*FLAG_VALIDATION_Y0 -> 0 | G52: =$F$83*FLAG_VALIDATION_Y1 -> 16000 | H52: =$F$83*FLAG_VALIDATION_Y2 -> 16000 | I52: =$F$83*FLAG_VALIDATION_Y3 -> 0 | J52: =$F$83*FLAG_VALIDATION_Y4 -> 0 | K52: =$F$83*FLAG_VALIDATION_Y5 -> 0 | L52: =$F$83*FLAG_VALIDATION_Y6 -> 0
B53: Programme management (Y1+Y2) | C53: €/yr | D53: =SUM(E53:L53) -> 103500 | E53: =$F$84*FLAG_VALIDATION_YM1 -> 0 | F53: =$F$84*FLAG_VALIDATION_Y0 -> 0 | G53: =$F$84*FLAG_VALIDATION_Y1 -> 51750 | H53: =$F$84*FLAG_VALIDATION_Y2 -> 51750 | I53: =$F$84*FLAG_VALIDATION_Y3 -> 0 | J53: =$F$84*FLAG_VALIDATION_Y4 -> 0 | K53: =$F$84*FLAG_VALIDATION_Y5 -> 0 | L53: =$F$84*FLAG_VALIDATION_Y6 -> 0
B54: Consumables (Y1+Y2) | C54: €/yr | D54: =SUM(E54:L54) -> 46500 | E54: =$F$85*FLAG_VALIDATION_YM1 -> 0 | F54: =$F$85*FLAG_VALIDATION_Y0 -> 0 | G54: =$F$85*FLAG_VALIDATION_Y1 -> 23250 | H54: =$F$85*FLAG_VALIDATION_Y2 -> 23250 | I54: =$F$85*FLAG_VALIDATION_Y3 -> 0 | J54: =$F$85*FLAG_VALIDATION_Y4 -> 0 | K54: =$F$85*FLAG_VALIDATION_Y5 -> 0 | L54: =$F$85*FLAG_VALIDATION_Y6 -> 0
B55: Subtotal — Plant genetics recurring | C55: € | D55: =SUM(D51:D54) -> 218000 | E55: =SUM(E51:E54) -> 0 | F55: =SUM(F51:F54) -> 0 | G55: =SUM(G51:G54) -> 109000 | H55: =SUM(H51:H54) -> 109000 | I55: =SUM(I51:I54) -> 0 | J55: =SUM(J51:J54) -> 0 | K55: =SUM(K51:K54) -> 0 | L55: =SUM(L51:L54) -> 0
B58: Inputs from Assumptions (Animal genetics)
B59: S01 — Veterinary centre (standalone building) | C59: € | D59: =SUM(E59:L59) -> 1000000 | E59: =ASM_S01_CENTRE_VETERINAIRE_EUR -> 125000 | F59: =ASM_S01_CENTRE_VETERINAIRE_EUR -> 125000 | G59: =ASM_S01_CENTRE_VETERINAIRE_EUR -> 125000 | H59: =ASM_S01_CENTRE_VETERINAIRE_EUR -> 125000 | I59: =ASM_S01_CENTRE_VETERINAIRE_EUR -> 125000 | J59: =ASM_S01_CENTRE_VETERINAIRE_EUR -> 125000 | K59: =ASM_S01_CENTRE_VETERINAIRE_EUR -> 125000 | L59: =ASM_S01_CENTRE_VETERINAIRE_EUR -> 125000
B60: S02 — Animal additional equipment (pharma + lab) | C60: € | D60: =SUM(E60:L60) -> 1200000 | E60: =ASM_S02_ANIMAL_EQUIPMENT_EUR -> 150000 | F60: =ASM_S02_ANIMAL_EQUIPMENT_EUR -> 150000 | G60: =ASM_S02_ANIMAL_EQUIPMENT_EUR -> 150000 | H60: =ASM_S02_ANIMAL_EQUIPMENT_EUR -> 150000 | I60: =ASM_S02_ANIMAL_EQUIPMENT_EUR -> 150000 | J60: =ASM_S02_ANIMAL_EQUIPMENT_EUR -> 150000 | K60: =ASM_S02_ANIMAL_EQUIPMENT_EUR -> 150000 | L60: =ASM_S02_ANIMAL_EQUIPMENT_EUR -> 150000
B61: S03 — Identification system per farm (PREMIUM tier) | C61: €/farm | D61: =SUM(E61:L61) -> 40000 | E61: =ASM_S03_IDENTIFICATION_EUR_PER_FARM -> 5000 | F61: =ASM_S03_IDENTIFICATION_EUR_PER_FARM -> 5000 | G61: =ASM_S03_IDENTIFICATION_EUR_PER_FARM -> 5000 | H61: =ASM_S03_IDENTIFICATION_EUR_PER_FARM -> 5000 | I61: =ASM_S03_IDENTIFICATION_EUR_PER_FARM -> 5000 | J61: =ASM_S03_IDENTIFICATION_EUR_PER_FARM -> 5000 | K61: =ASM_S03_IDENTIFICATION_EUR_PER_FARM -> 5000 | L61: =ASM_S03_IDENTIFICATION_EUR_PER_FARM -> 5000
B62: S04 — AI hardware (shared — tank + ultrasound) | C62: € | D62: =SUM(E62:L62) -> 67208 | E62: =ASM_S04_IA_HARDWARE_SHARED_EUR -> 8401 | F62: =ASM_S04_IA_HARDWARE_SHARED_EUR -> 8401 | G62: =ASM_S04_IA_HARDWARE_SHARED_EUR -> 8401 | H62: =ASM_S04_IA_HARDWARE_SHARED_EUR -> 8401 | I62: =ASM_S04_IA_HARDWARE_SHARED_EUR -> 8401 | J62: =ASM_S04_IA_HARDWARE_SHARED_EUR -> 8401 | K62: =ASM_S04_IA_HARDWARE_SHARED_EUR -> 8401 | L62: =ASM_S04_IA_HARDWARE_SHARED_EUR -> 8401
B63: S05 — Partner support — PREMIUM per farm (28 days + travel) | C63: €/farm | D63: =SUM(E63:L63) -> 192000 | E63: =ASM_S05_CA71_ACCOMPAGNEMENT_EUR_PER_FARM -> 24000 | F63: =ASM_S05_CA71_ACCOMPAGNEMENT_EUR_PER_FARM -> 24000 | G63: =ASM_S05_CA71_ACCOMPAGNEMENT_EUR_PER_FARM -> 24000 | H63: =ASM_S05_CA71_ACCOMPAGNEMENT_EUR_PER_FARM -> 24000 | I63: =ASM_S05_CA71_ACCOMPAGNEMENT_EUR_PER_FARM -> 24000 | J63: =ASM_S05_CA71_ACCOMPAGNEMENT_EUR_PER_FARM -> 24000 | K63: =ASM_S05_CA71_ACCOMPAGNEMENT_EUR_PER_FARM -> 24000 | L63: =ASM_S05_CA71_ACCOMPAGNEMENT_EUR_PER_FARM -> 24000
B64: S06 — Inseminator training (3 months) | C64: € | D64: =SUM(E64:L64) -> 202400 | E64: =ASM_S06_ELVANOVIA_FORMATION_EUR -> 25300 | F64: =ASM_S06_ELVANOVIA_FORMATION_EUR -> 25300 | G64: =ASM_S06_ELVANOVIA_FORMATION_EUR -> 25300 | H64: =ASM_S06_ELVANOVIA_FORMATION_EUR -> 25300 | I64: =ASM_S06_ELVANOVIA_FORMATION_EUR -> 25300 | J64: =ASM_S06_ELVANOVIA_FORMATION_EUR -> 25300 | K64: =ASM_S06_ELVANOVIA_FORMATION_EUR -> 25300 | L64: =ASM_S06_ELVANOVIA_FORMATION_EUR -> 25300
B65: S07 — Initial AI doses | C65: doses | D65: =SUM(E65:L65) -> 12000 | E65: =ASM_S07_DOSES_INITIAL_N -> 1500 | F65: =ASM_S07_DOSES_INITIAL_N -> 1500 | G65: =ASM_S07_DOSES_INITIAL_N -> 1500 | H65: =ASM_S07_DOSES_INITIAL_N -> 1500 | I65: =ASM_S07_DOSES_INITIAL_N -> 1500 | J65: =ASM_S07_DOSES_INITIAL_N -> 1500 | K65: =ASM_S07_DOSES_INITIAL_N -> 1500 | L65: =ASM_S07_DOSES_INITIAL_N -> 1500
B66: S08 — Cost per AI dose | C66: €/u | D66: =SUM(E66:L66) -> 40 | E66: =ASM_S08_DOSE_EUR_PER_PAILLETTE -> 5 | F66: =ASM_S08_DOSE_EUR_PER_PAILLETTE -> 5 | G66: =ASM_S08_DOSE_EUR_PER_PAILLETTE -> 5 | H66: =ASM_S08_DOSE_EUR_PER_PAILLETTE -> 5 | I66: =ASM_S08_DOSE_EUR_PER_PAILLETTE -> 5 | J66: =ASM_S08_DOSE_EUR_PER_PAILLETTE -> 5 | K66: =ASM_S08_DOSE_EUR_PER_PAILLETTE -> 5 | L66: =ASM_S08_DOSE_EUR_PER_PAILLETTE -> 5
B67: S09 — Herd-management software per farm per year | C67: €/yr/farm | D67: =SUM(E67:L67) -> 6080 | E67: =ASM_S09_FARMBRITE_LICENCE_EUR_YR_PER_FARM -> 760 | F67: =ASM_S09_FARMBRITE_LICENCE_EUR_YR_PER_FARM -> 760 | G67: =ASM_S09_FARMBRITE_LICENCE_EUR_YR_PER_FARM -> 760 | H67: =ASM_S09_FARMBRITE_LICENCE_EUR_YR_PER_FARM -> 760 | I67: =ASM_S09_FARMBRITE_LICENCE_EUR_YR_PER_FARM -> 760 | J67: =ASM_S09_FARMBRITE_LICENCE_EUR_YR_PER_FARM -> 760 | K67: =ASM_S09_FARMBRITE_LICENCE_EUR_YR_PER_FARM -> 760 | L67: =ASM_S09_FARMBRITE_LICENCE_EUR_YR_PER_FARM -> 760
B68: S10 — Local inseminator salary (recurring from Y2) | C68: €/yr | D68: =SUM(E68:L68) -> 52000 | E68: =ASM_S10_INSEMINATOR_SALARY_EUR_YR -> 6500 | F68: =ASM_S10_INSEMINATOR_SALARY_EUR_YR -> 6500 | G68: =ASM_S10_INSEMINATOR_SALARY_EUR_YR -> 6500 | H68: =ASM_S10_INSEMINATOR_SALARY_EUR_YR -> 6500 | I68: =ASM_S10_INSEMINATOR_SALARY_EUR_YR -> 6500 | J68: =ASM_S10_INSEMINATOR_SALARY_EUR_YR -> 6500 | K68: =ASM_S10_INSEMINATOR_SALARY_EUR_YR -> 6500 | L68: =ASM_S10_INSEMINATOR_SALARY_EUR_YR -> 6500
B69: S11 — Veterinary inputs per head per year (vaccines, prophylaxis) | C69: €/head/yr | D69: =SUM(E69:L69) -> 144 | E69: =ASM_S11_ANIMAL_VET_INPUTS_EUR_PER_HEAD_YR -> 18 | F69: =ASM_S11_ANIMAL_VET_INPUTS_EUR_PER_HEAD_YR -> 18 | G69: =ASM_S11_ANIMAL_VET_INPUTS_EUR_PER_HEAD_YR -> 18 | H69: =ASM_S11_ANIMAL_VET_INPUTS_EUR_PER_HEAD_YR -> 18 | I69: =ASM_S11_ANIMAL_VET_INPUTS_EUR_PER_HEAD_YR -> 18 | J69: =ASM_S11_ANIMAL_VET_INPUTS_EUR_PER_HEAD_YR -> 18 | K69: =ASM_S11_ANIMAL_VET_INPUTS_EUR_PER_HEAD_YR -> 18 | L69: =ASM_S11_ANIMAL_VET_INPUTS_EUR_PER_HEAD_YR -> 18
B70: S12 — AI programme herd (820 Artine + 180 incubators) | C70: head | D70: =SUM(E70:L70) -> 8000 | E70: =ASM_S12_ANIMAL_CHEPTEL_SIZE -> 1000 | F70: =ASM_S12_ANIMAL_CHEPTEL_SIZE -> 1000 | G70: =ASM_S12_ANIMAL_CHEPTEL_SIZE -> 1000 | H70: =ASM_S12_ANIMAL_CHEPTEL_SIZE -> 1000 | I70: =ASM_S12_ANIMAL_CHEPTEL_SIZE -> 1000 | J70: =ASM_S12_ANIMAL_CHEPTEL_SIZE -> 1000 | K70: =ASM_S12_ANIMAL_CHEPTEL_SIZE -> 1000 | L70: =ASM_S12_ANIMAL_CHEPTEL_SIZE -> 1000
B71: S13 — Programme management — animal (Y1+Y2) | C71: €/yr | D71: =SUM(E71:L71) -> 634800 | E71: =ASM_S13_PROGRAMME_MGMT_ANIMAL_EUR_YR -> 79350 | F71: =ASM_S13_PROGRAMME_MGMT_ANIMAL_EUR_YR -> 79350 | G71: =ASM_S13_PROGRAMME_MGMT_ANIMAL_EUR_YR -> 79350 | H71: =ASM_S13_PROGRAMME_MGMT_ANIMAL_EUR_YR -> 79350 | I71: =ASM_S13_PROGRAMME_MGMT_ANIMAL_EUR_YR -> 79350 | J71: =ASM_S13_PROGRAMME_MGMT_ANIMAL_EUR_YR -> 79350 | K71: =ASM_S13_PROGRAMME_MGMT_ANIMAL_EUR_YR -> 79350 | L71: =ASM_S13_PROGRAMME_MGMT_ANIMAL_EUR_YR -> 79350
B72: S14 — Consumables — animal (Y1+Y2) | C72: €/yr | D72: =SUM(E72:L72) -> 285200 | E72: =ASM_S14_CONSUMABLES_ANIMAL_EUR_YR -> 35650 | F72: =ASM_S14_CONSUMABLES_ANIMAL_EUR_YR -> 35650 | G72: =ASM_S14_CONSUMABLES_ANIMAL_EUR_YR -> 35650 | H72: =ASM_S14_CONSUMABLES_ANIMAL_EUR_YR -> 35650 | I72: =ASM_S14_CONSUMABLES_ANIMAL_EUR_YR -> 35650 | J72: =ASM_S14_CONSUMABLES_ANIMAL_EUR_YR -> 35650 | K72: =ASM_S14_CONSUMABLES_ANIMAL_EUR_YR -> 35650 | L72: =ASM_S14_CONSUMABLES_ANIMAL_EUR_YR -> 35650
B74: Inputs from Assumptions (Plant genetics)
B75: T01 — Plant centre building (500 m² covered) | C75: € | D75: =SUM(E75:L75) -> 1000000 | E75: =ASM_T01_CENTRE_VEGETAL_BUILDING_EUR -> 125000 | F75: =ASM_T01_CENTRE_VEGETAL_BUILDING_EUR -> 125000 | G75: =ASM_T01_CENTRE_VEGETAL_BUILDING_EUR -> 125000 | H75: =ASM_T01_CENTRE_VEGETAL_BUILDING_EUR -> 125000 | I75: =ASM_T01_CENTRE_VEGETAL_BUILDING_EUR -> 125000 | J75: =ASM_T01_CENTRE_VEGETAL_BUILDING_EUR -> 125000 | K75: =ASM_T01_CENTRE_VEGETAL_BUILDING_EUR -> 125000 | L75: =ASM_T01_CENTRE_VEGETAL_BUILDING_EUR -> 125000
B76: T02 — Plant equipment (germinators, drip irrigation) | C76: € | D76: =SUM(E76:L76) -> 600000 | E76: =ASM_T02_VEGETAL_EQUIPMENT_EUR -> 75000 | F76: =ASM_T02_VEGETAL_EQUIPMENT_EUR -> 75000 | G76: =ASM_T02_VEGETAL_EQUIPMENT_EUR -> 75000 | H76: =ASM_T02_VEGETAL_EQUIPMENT_EUR -> 75000 | I76: =ASM_T02_VEGETAL_EQUIPMENT_EUR -> 75000 | J76: =ASM_T02_VEGETAL_EQUIPMENT_EUR -> 75000 | K76: =ASM_T02_VEGETAL_EQUIPMENT_EUR -> 75000 | L76: =ASM_T02_VEGETAL_EQUIPMENT_EUR -> 75000
B77: T03 — Nursery operator training (3 months) | C77: € | D77: =SUM(E77:L77) -> 136000 | E77: =ASM_T03_VEGETAL_PREOP_FORMATION_EUR -> 17000 | F77: =ASM_T03_VEGETAL_PREOP_FORMATION_EUR -> 17000 | G77: =ASM_T03_VEGETAL_PREOP_FORMATION_EUR -> 17000 | H77: =ASM_T03_VEGETAL_PREOP_FORMATION_EUR -> 17000 | I77: =ASM_T03_VEGETAL_PREOP_FORMATION_EUR -> 17000 | J77: =ASM_T03_VEGETAL_PREOP_FORMATION_EUR -> 17000 | K77: =ASM_T03_VEGETAL_PREOP_FORMATION_EUR -> 17000 | L77: =ASM_T03_VEGETAL_PREOP_FORMATION_EUR -> 17000
B78: T04 — Plant partner support (parallel to animal partner) | C78: € | D78: =SUM(E78:L78) -> 192000 | E78: =ASM_T04_VEGETAL_PREOP_ACCOMPANYING_EUR -> 24000 | F78: =ASM_T04_VEGETAL_PREOP_ACCOMPANYING_EUR -> 24000 | G78: =ASM_T04_VEGETAL_PREOP_ACCOMPANYING_EUR -> 24000 | H78: =ASM_T04_VEGETAL_PREOP_ACCOMPANYING_EUR -> 24000 | I78: =ASM_T04_VEGETAL_PREOP_ACCOMPANYING_EUR -> 24000 | J78: =ASM_T04_VEGETAL_PREOP_ACCOMPANYING_EUR -> 24000 | K78: =ASM_T04_VEGETAL_PREOP_ACCOMPANYING_EUR -> 24000 | L78: =ASM_T04_VEGETAL_PREOP_ACCOMPANYING_EUR -> 24000
B79: T05 — Imported foundation seeds (international centres) | C79: € | D79: =SUM(E79:L79) -> 64000 | E79: =ASM_T05_SEEDS_INITIAL_STOCK_EUR -> 8000 | F79: =ASM_T05_SEEDS_INITIAL_STOCK_EUR -> 8000 | G79: =ASM_T05_SEEDS_INITIAL_STOCK_EUR -> 8000 | H79: =ASM_T05_SEEDS_INITIAL_STOCK_EUR -> 8000 | I79: =ASM_T05_SEEDS_INITIAL_STOCK_EUR -> 8000 | J79: =ASM_T05_SEEDS_INITIAL_STOCK_EUR -> 8000 | K79: =ASM_T05_SEEDS_INITIAL_STOCK_EUR -> 8000 | L79: =ASM_T05_SEEDS_INITIAL_STOCK_EUR -> 8000
B80: T06 — Mother trees (acacia / faidherbia / fruit) | C80: € | D80: =SUM(E80:L80) -> 144000 | E80: =ASM_T06_PLANTS_INITIAL_STOCK_EUR -> 18000 | F80: =ASM_T06_PLANTS_INITIAL_STOCK_EUR -> 18000 | G80: =ASM_T06_PLANTS_INITIAL_STOCK_EUR -> 18000 | H80: =ASM_T06_PLANTS_INITIAL_STOCK_EUR -> 18000 | I80: =ASM_T06_PLANTS_INITIAL_STOCK_EUR -> 18000 | J80: =ASM_T06_PLANTS_INITIAL_STOCK_EUR -> 18000 | K80: =ASM_T06_PLANTS_INITIAL_STOCK_EUR -> 18000 | L80: =ASM_T06_PLANTS_INITIAL_STOCK_EUR -> 18000
B81: T07 — Acacia senegal mother nursery (gum arabic) | C81: € | D81: =SUM(E81:L81) -> 48000 | E81: =ASM_T07_GUM_ARABIC_INITIAL_STOCK_EUR -> 6000 | F81: =ASM_T07_GUM_ARABIC_INITIAL_STOCK_EUR -> 6000 | G81: =ASM_T07_GUM_ARABIC_INITIAL_STOCK_EUR -> 6000 | H81: =ASM_T07_GUM_ARABIC_INITIAL_STOCK_EUR -> 6000 | I81: =ASM_T07_GUM_ARABIC_INITIAL_STOCK_EUR -> 6000 | J81: =ASM_T07_GUM_ARABIC_INITIAL_STOCK_EUR -> 6000 | K81: =ASM_T07_GUM_ARABIC_INITIAL_STOCK_EUR -> 6000 | L81: =ASM_T07_GUM_ARABIC_INITIAL_STOCK_EUR -> 6000
B82: T08 — Plant inputs per year (substrate, pots, water) | C82: €/yr | D82: =SUM(E82:L82) -> 144000 | E82: =ASM_T08_VEGETAL_INPUTS_EUR_YR -> 18000 | F82: =ASM_T08_VEGETAL_INPUTS_EUR_YR -> 18000 | G82: =ASM_T08_VEGETAL_INPUTS_EUR_YR -> 18000 | H82: =ASM_T08_VEGETAL_INPUTS_EUR_YR -> 18000 | I82: =ASM_T08_VEGETAL_INPUTS_EUR_YR -> 18000 | J82: =ASM_T08_VEGETAL_INPUTS_EUR_YR -> 18000 | K82: =ASM_T08_VEGETAL_INPUTS_EUR_YR -> 18000 | L82: =ASM_T08_VEGETAL_INPUTS_EUR_YR -> 18000
B83: T09 — Plant centre staff (1 senior + 2 workers + 1 technician) | C83: €/yr | D83: =SUM(E83:L83) -> 128000 | E83: =ASM_T09_VEGETAL_AGRONOMIST_SALARY_EUR_YR -> 16000 | F83: =ASM_T09_VEGETAL_AGRONOMIST_SALARY_EUR_YR -> 16000 | G83: =ASM_T09_VEGETAL_AGRONOMIST_SALARY_EUR_YR -> 16000 | H83: =ASM_T09_VEGETAL_AGRONOMIST_SALARY_EUR_YR -> 16000 | I83: =ASM_T09_VEGETAL_AGRONOMIST_SALARY_EUR_YR -> 16000 | J83: =ASM_T09_VEGETAL_AGRONOMIST_SALARY_EUR_YR -> 16000 | K83: =ASM_T09_VEGETAL_AGRONOMIST_SALARY_EUR_YR -> 16000 | L83: =ASM_T09_VEGETAL_AGRONOMIST_SALARY_EUR_YR -> 16000
B84: T10 — Programme management — plant (Y1+Y2) | C84: €/yr | D84: =SUM(E84:L84) -> 414000 | E84: =ASM_T10_PROGRAMME_MGMT_PLANT_EUR_YR -> 51750 | F84: =ASM_T10_PROGRAMME_MGMT_PLANT_EUR_YR -> 51750 | G84: =ASM_T10_PROGRAMME_MGMT_PLANT_EUR_YR -> 51750 | H84: =ASM_T10_PROGRAMME_MGMT_PLANT_EUR_YR -> 51750 | I84: =ASM_T10_PROGRAMME_MGMT_PLANT_EUR_YR -> 51750 | J84: =ASM_T10_PROGRAMME_MGMT_PLANT_EUR_YR -> 51750 | K84: =ASM_T10_PROGRAMME_MGMT_PLANT_EUR_YR -> 51750 | L84: =ASM_T10_PROGRAMME_MGMT_PLANT_EUR_YR -> 51750
B85: T11 — Consumables — plant (Y1+Y2) | C85: €/yr | D85: =SUM(E85:L85) -> 186000 | E85: =ASM_T11_CONSUMABLES_PLANT_EUR_YR -> 23250 | F85: =ASM_T11_CONSUMABLES_PLANT_EUR_YR -> 23250 | G85: =ASM_T11_CONSUMABLES_PLANT_EUR_YR -> 23250 | H85: =ASM_T11_CONSUMABLES_PLANT_EUR_YR -> 23250 | I85: =ASM_T11_CONSUMABLES_PLANT_EUR_YR -> 23250 | J85: =ASM_T11_CONSUMABLES_PLANT_EUR_YR -> 23250 | K85: =ASM_T11_CONSUMABLES_PLANT_EUR_YR -> 23250 | L85: =ASM_T11_CONSUMABLES_PLANT_EUR_YR -> 23250

Sheet 05_CAPEX
B1: 05 — CAPEX / Capital Investments [€]
D3: Total | E3: Y-1 | F3: Y0 | G3: Y1 | H3: Y2 | I3: Y3 | J3: Y4 | K3: Y5 | L3: Y6
E4: -1 | F4: 0 | G4: 1 | H4: 2 | I4: 3 | J4: 4 | K4: 5 | L4: 6
B6: Summary
B7: 1. The three farms — production assets | C7: € | D7: =SUM(E7:L7) -> 2701585.8 | E7: =E36 -> 0 | F7: =F36 -> 2701585.8 | G7: =G36 -> 0 | H7: =H36 -> 0 | I7: =I36 -> 0 | J7: =J36 -> 0 | K7: =K36 -> 0 | L7: =L36 -> 0
B8: 2. Building the workforce — training cohorts | C8: € | D8: =SUM(E8:L8) -> 1488000 | E8: =E54 -> 628000 | F8: =F54 -> 860000 | G8: =G54 -> 0 | H8: =H54 -> 0 | I8: =I54 -> 0 | J8: =J54 -> 0 | K8: =K54 -> 0 | L8: =L54 -> 0
B9: 3. Genetics platform — animal + plant | C9: € | D9: =SUM(E9:L9) -> 498401 | E9: =E68 -> 0 | F9: =F68 -> 498401 | G9: =G68 -> 0 | H9: =H68 -> 0 | I9: =I68 -> 0 | J9: =J68 -> 0 | K9: =K68 -> 0 | L9: =L68 -> 0
B10: 4. Development & structuring costs | C10: € | D10: =SUM(E10:L10) -> 334147.18 | E10: =E79 -> 0 | F10: =F79 -> 334147.18 | G10: =G79 -> 0 | H10: =H79 -> 0 | I10: =I79 -> 0 | J10: =J79 -> 0 | K10: =K79 -> 0 | L10: =L79 -> 0
B11: 5. Reserves (working capital, DSRA/MMR, contingency) | C11: € | D11: =SUM(E11:L11) -> 544658.36 | E11: =E86 -> 0 | F11: =F86 -> 544658.36 | G11: =G86 -> 0 | H11: =H86 -> 0 | I11: =I86 -> 0 | J11: =J86 -> 0 | K11: =K86 -> 0 | L11: =L86 -> 0
B12: TOTAL CAPITAL INVESTED | C12: € | D12: =SUM(E12:L12) -> 5566792.4 | E12: =E7+E8+E9+E10+E11 -> 628000 | F12: =F7+F8+F9+F10+F11 -> 4938792.4 | G12: =G7+G8+G9+G10+G11 -> 0 | H12: =H7+H8+H9+H10+H11 -> 0 | I12: =I7+I8+I9+I10+I11 -> 0 | J12: =J7+J8+J9+J10+J11 -> 0 | K12: =K7+K8+K9+K10+K11 -> 0 | L12: =L7+L8+L9+L10+L11 -> 0
B14: The three farms — physical CAPEX (Y0 build)
B15: Land & infrastructure
B16: Foncier — land (in-kind, 100 ha/farm) | C16: € | D16: =SUM(E16:L16) -> 448909.09 | E16: =ASM_A01_N_FARMS*E$103*FLAG_CONSTRUCT_YM1 -> 0 | F16: =ASM_A01_N_FARMS*F$103*FLAG_CONSTRUCT_Y0 -> 448909.09 | G16: =ASM_A01_N_FARMS*G$103*FLAG_CONSTRUCT_Y1 -> 0 | H16: =ASM_A01_N_FARMS*H$103*FLAG_CONSTRUCT_Y2 -> 0 | I16: =ASM_A01_N_FARMS*I$103*FLAG_CONSTRUCT_Y3 -> 0 | J16: =ASM_A01_N_FARMS*J$103*FLAG_CONSTRUCT_Y4 -> 0 | K16: =ASM_A01_N_FARMS*K$103*FLAG_CONSTRUCT_Y5 -> 0 | L16: =ASM_A01_N_FARMS*L$103*FLAG_CONSTRUCT_Y6 -> 0
B17: Aménagements — clearing, topography, fencing, VRD | C17: € | D17: =ASM_A01_N_FARMS*ASM_I01A_AMENAGEMENTS_PER_FARM_EUR -> 163767 | E17: =ASM_A01_N_FARMS*ASM_I01A_AMENAGEMENTS_PER_FARM_EUR*FLAG_CONSTRUCT_YM1 -> 0 | F17: =ASM_A01_N_FARMS*ASM_I01A_AMENAGEMENTS_PER_FARM_EUR*FLAG_CONSTRUCT_Y0 -> 163767 | G17: =ASM_A01_N_FARMS*ASM_I01A_AMENAGEMENTS_PER_FARM_EUR*FLAG_CONSTRUCT_Y1 -> 0 | H17: =ASM_A01_N_FARMS*ASM_I01A_AMENAGEMENTS_PER_FARM_EUR*FLAG_CONSTRUCT_Y2 -> 0 | I17: =ASM_A01_N_FARMS*ASM_I01A_AMENAGEMENTS_PER_FARM_EUR*FLAG_CONSTRUCT_Y3 -> 0 | J17: =ASM_A01_N_FARMS*ASM_I01A_AMENAGEMENTS_PER_FARM_EUR*FLAG_CONSTRUCT_Y4 -> 0 | K17: =ASM_A01_N_FARMS*ASM_I01A_AMENAGEMENTS_PER_FARM_EUR*FLAG_CONSTRUCT_Y5 -> 0 | L17: =ASM_A01_N_FARMS*ASM_I01A_AMENAGEMENTS_PER_FARM_EUR*FLAG_CONSTRUCT_Y6 -> 0
B18: Buildings — coop office, storage, warehouse, livestock buildings | C18: € | D18: =SUM(E18:L18) -> 315859.09 | E18: =ASM_A01_N_FARMS*E$100*FLAG_CONSTRUCT_YM1 -> 0 | F18: =ASM_A01_N_FARMS*F$100*FLAG_CONSTRUCT_Y0 -> 315859.09 | G18: =ASM_A01_N_FARMS*G$100*FLAG_CONSTRUCT_Y1 -> 0 | H18: =ASM_A01_N_FARMS*H$100*FLAG_CONSTRUCT_Y2 -> 0 | I18: =ASM_A01_N_FARMS*I$100*FLAG_CONSTRUCT_Y3 -> 0 | J18: =ASM_A01_N_FARMS*J$100*FLAG_CONSTRUCT_Y4 -> 0 | K18: =ASM_A01_N_FARMS*K$100*FLAG_CONSTRUCT_Y5 -> 0 | L18: =ASM_A01_N_FARMS*L$100*FLAG_CONSTRUCT_Y6 -> 0
B19: Agroforestry — 30,000 trees/farm × €0.50 | C19: € | D19: =ASM_A01_N_FARMS*ASM_I05_TREES_PER_FARM*ASM_I06_COST_PER_TREE_EUR -> 45000 | E19: =ASM_A01_N_FARMS*ASM_I05_TREES_PER_FARM*ASM_I06_COST_PER_TREE_EUR*FLAG_CONSTRUCT_YM1 -> 0 | F19: =ASM_A01_N_FARMS*ASM_I05_TREES_PER_FARM*ASM_I06_COST_PER_TREE_EUR*FLAG_CONSTRUCT_Y0 -> 45000 | G19: =ASM_A01_N_FARMS*ASM_I05_TREES_PER_FARM*ASM_I06_COST_PER_TREE_EUR*FLAG_CONSTRUCT_Y1 -> 0 | H19: =ASM_A01_N_FARMS*ASM_I05_TREES_PER_FARM*ASM_I06_COST_PER_TREE_EUR*FLAG_CONSTRUCT_Y2 -> 0 | I19: =ASM_A01_N_FARMS*ASM_I05_TREES_PER_FARM*ASM_I06_COST_PER_TREE_EUR*FLAG_CONSTRUCT_Y3 -> 0 | J19: =ASM_A01_N_FARMS*ASM_I05_TREES_PER_FARM*ASM_I06_COST_PER_TREE_EUR*FLAG_CONSTRUCT_Y4 -> 0 | K19: =ASM_A01_N_FARMS*ASM_I05_TREES_PER_FARM*ASM_I06_COST_PER_TREE_EUR*FLAG_CONSTRUCT_Y5 -> 0 | L19: =ASM_A01_N_FARMS*ASM_I05_TREES_PER_FARM*ASM_I06_COST_PER_TREE_EUR*FLAG_CONSTRUCT_Y6 -> 0
B20: Subtotal — Land & infrastructure | C20: € | D20: =SUM(D16:D19) -> 973535.18 | E20: =SUM(E16:E19) -> 0 | F20: =SUM(F16:F19) -> 973535.18 | G20: =SUM(G16:G19) -> 0 | H20: =SUM(H16:H19) -> 0 | I20: =SUM(I16:I19) -> 0 | J20: =SUM(J16:J19) -> 0 | K20: =SUM(K16:K19) -> 0 | L20: =SUM(L16:L19) -> 0
B22: Livestock
B23: Dairy — infra (building + milking + cooling) | C23: € | D23: =ASM_A01_N_FARMS*ASM_I03A_DAIRY_INFRA_PER_FARM_EUR -> 130365 | E23: =ASM_A01_N_FARMS*ASM_I03A_DAIRY_INFRA_PER_FARM_EUR*FLAG_CONSTRUCT_YM1 -> 0 | F23: =ASM_A01_N_FARMS*ASM_I03A_DAIRY_INFRA_PER_FARM_EUR*FLAG_CONSTRUCT_Y0 -> 130365 | G23: =ASM_A01_N_FARMS*ASM_I03A_DAIRY_INFRA_PER_FARM_EUR*FLAG_CONSTRUCT_Y1 -> 0 | H23: =ASM_A01_N_FARMS*ASM_I03A_DAIRY_INFRA_PER_FARM_EUR*FLAG_CONSTRUCT_Y2 -> 0 | I23: =ASM_A01_N_FARMS*ASM_I03A_DAIRY_INFRA_PER_FARM_EUR*FLAG_CONSTRUCT_Y3 -> 0 | J23: =ASM_A01_N_FARMS*ASM_I03A_DAIRY_INFRA_PER_FARM_EUR*FLAG_CONSTRUCT_Y4 -> 0 | K23: =ASM_A01_N_FARMS*ASM_I03A_DAIRY_INFRA_PER_FARM_EUR*FLAG_CONSTRUCT_Y5 -> 0 | L23: =ASM_A01_N_FARMS*ASM_I03A_DAIRY_INFRA_PER_FARM_EUR*FLAG_CONSTRUCT_Y6 -> 0
B24: Herd — 30 cows (in-kind, Haraz) | C24: € | D24: =ASM_A01_N_FARMS*ASM_I03B_DAIRY_HERD_INKIND_PER_FARM_EUR -> 204546 | E24: =ASM_A01_N_FARMS*ASM_I03B_DAIRY_HERD_INKIND_PER_FARM_EUR*FLAG_CONSTRUCT_YM1 -> 0 | F24: =ASM_A01_N_FARMS*ASM_I03B_DAIRY_HERD_INKIND_PER_FARM_EUR*FLAG_CONSTRUCT_Y0 -> 204546 | G24: =ASM_A01_N_FARMS*ASM_I03B_DAIRY_HERD_INKIND_PER_FARM_EUR*FLAG_CONSTRUCT_Y1 -> 0 | H24: =ASM_A01_N_FARMS*ASM_I03B_DAIRY_HERD_INKIND_PER_FARM_EUR*FLAG_CONSTRUCT_Y2 -> 0 | I24: =ASM_A01_N_FARMS*ASM_I03B_DAIRY_HERD_INKIND_PER_FARM_EUR*FLAG_CONSTRUCT_Y3 -> 0 | J24: =ASM_A01_N_FARMS*ASM_I03B_DAIRY_HERD_INKIND_PER_FARM_EUR*FLAG_CONSTRUCT_Y4 -> 0 | K24: =ASM_A01_N_FARMS*ASM_I03B_DAIRY_HERD_INKIND_PER_FARM_EUR*FLAG_CONSTRUCT_Y5 -> 0 | L24: =ASM_A01_N_FARMS*ASM_I03B_DAIRY_HERD_INKIND_PER_FARM_EUR*FLAG_CONSTRUCT_Y6 -> 0
B25: Feedlot — open pens (30 finished/yr) | C25: € | D25: =SUM(E25:L25) -> 23593.636 | E25: =ASM_A01_N_FARMS*E$102*FLAG_CONSTRUCT_YM1 -> 0 | F25: =ASM_A01_N_FARMS*F$102*FLAG_CONSTRUCT_Y0 -> 23593.636 | G25: =ASM_A01_N_FARMS*G$102*FLAG_CONSTRUCT_Y1 -> 0 | H25: =ASM_A01_N_FARMS*H$102*FLAG_CONSTRUCT_Y2 -> 0 | I25: =ASM_A01_N_FARMS*I$102*FLAG_CONSTRUCT_Y3 -> 0 | J25: =ASM_A01_N_FARMS*J$102*FLAG_CONSTRUCT_Y4 -> 0 | K25: =ASM_A01_N_FARMS*K$102*FLAG_CONSTRUCT_Y5 -> 0 | L25: =ASM_A01_N_FARMS*L$102*FLAG_CONSTRUCT_Y6 -> 0
B26: Subtotal — Livestock | C26: € | D26: =SUM(D23:D25) -> 358504.64 | E26: =SUM(E23:E25) -> 0 | F26: =SUM(F23:F25) -> 358504.64 | G26: =SUM(G23:G25) -> 0 | H26: =SUM(H23:H25) -> 0 | I26: =SUM(I23:I25) -> 0 | J26: =SUM(J23:J25) -> 0 | K26: =SUM(K23:K25) -> 0 | L26: =SUM(L23:L25) -> 0
B28: Power, water & equipment
B29: Irrigation infra — drip 20ha + sprinkler 10ha + piping | C29: € | D29: =ASM_A01_N_FARMS*ASM_I01B_IRRIGATION_PER_FARM_EUR -> 553506 | E29: =ASM_A01_N_FARMS*ASM_I01B_IRRIGATION_PER_FARM_EUR*FLAG_CONSTRUCT_YM1 -> 0 | F29: =ASM_A01_N_FARMS*ASM_I01B_IRRIGATION_PER_FARM_EUR*FLAG_CONSTRUCT_Y0 -> 553506 | G29: =ASM_A01_N_FARMS*ASM_I01B_IRRIGATION_PER_FARM_EUR*FLAG_CONSTRUCT_Y1 -> 0 | H29: =ASM_A01_N_FARMS*ASM_I01B_IRRIGATION_PER_FARM_EUR*FLAG_CONSTRUCT_Y2 -> 0 | I29: =ASM_A01_N_FARMS*ASM_I01B_IRRIGATION_PER_FARM_EUR*FLAG_CONSTRUCT_Y3 -> 0 | J29: =ASM_A01_N_FARMS*ASM_I01B_IRRIGATION_PER_FARM_EUR*FLAG_CONSTRUCT_Y4 -> 0 | K29: =ASM_A01_N_FARMS*ASM_I01B_IRRIGATION_PER_FARM_EUR*FLAG_CONSTRUCT_Y5 -> 0 | L29: =ASM_A01_N_FARMS*ASM_I01B_IRRIGATION_PER_FARM_EUR*FLAG_CONSTRUCT_Y6 -> 0
B30: Water station — wells, pumps, storage, treatment (to confirm) | C30: € | D30: =ASM_A01_N_FARMS*ASM_I07_UOF_WATER_PER_FARM_EUR -> 486000 | E30: =ASM_A01_N_FARMS*ASM_I07_UOF_WATER_PER_FARM_EUR*FLAG_CONSTRUCT_YM1 -> 0 | F30: =ASM_A01_N_FARMS*ASM_I07_UOF_WATER_PER_FARM_EUR*FLAG_CONSTRUCT_Y0 -> 486000 | G30: =ASM_A01_N_FARMS*ASM_I07_UOF_WATER_PER_FARM_EUR*FLAG_CONSTRUCT_Y1 -> 0 | H30: =ASM_A01_N_FARMS*ASM_I07_UOF_WATER_PER_FARM_EUR*FLAG_CONSTRUCT_Y2 -> 0 | I30: =ASM_A01_N_FARMS*ASM_I07_UOF_WATER_PER_FARM_EUR*FLAG_CONSTRUCT_Y3 -> 0 | J30: =ASM_A01_N_FARMS*ASM_I07_UOF_WATER_PER_FARM_EUR*FLAG_CONSTRUCT_Y4 -> 0 | K30: =ASM_A01_N_FARMS*ASM_I07_UOF_WATER_PER_FARM_EUR*FLAG_CONSTRUCT_Y5 -> 0 | L30: =ASM_A01_N_FARMS*ASM_I07_UOF_WATER_PER_FARM_EUR*FLAG_CONSTRUCT_Y6 -> 0
B31: Power station — solar PV + BESS + inverter + 400V (to confirm) | C31: € | D31: =ASM_A01_N_FARMS*ASM_I08_UOF_ENERGY_PER_FARM_EUR -> 70035 | E31: =ASM_A01_N_FARMS*ASM_I08_UOF_ENERGY_PER_FARM_EUR*FLAG_CONSTRUCT_YM1 -> 0 | F31: =ASM_A01_N_FARMS*ASM_I08_UOF_ENERGY_PER_FARM_EUR*FLAG_CONSTRUCT_Y0 -> 70035 | G31: =ASM_A01_N_FARMS*ASM_I08_UOF_ENERGY_PER_FARM_EUR*FLAG_CONSTRUCT_Y1 -> 0 | H31: =ASM_A01_N_FARMS*ASM_I08_UOF_ENERGY_PER_FARM_EUR*FLAG_CONSTRUCT_Y2 -> 0 | I31: =ASM_A01_N_FARMS*ASM_I08_UOF_ENERGY_PER_FARM_EUR*FLAG_CONSTRUCT_Y3 -> 0 | J31: =ASM_A01_N_FARMS*ASM_I08_UOF_ENERGY_PER_FARM_EUR*FLAG_CONSTRUCT_Y4 -> 0 | K31: =ASM_A01_N_FARMS*ASM_I08_UOF_ENERGY_PER_FARM_EUR*FLAG_CONSTRUCT_Y5 -> 0 | L31: =ASM_A01_N_FARMS*ASM_I08_UOF_ENERGY_PER_FARM_EUR*FLAG_CONSTRUCT_Y6 -> 0
B32: Mechanisation — tractors, implements (shared pool, to confirm) | C32: € | D32: =ASM_I09_UOF_MECHANIZATION_PROGRAMME_EUR -> 180000 | E32: =ASM_I09_UOF_MECHANIZATION_PROGRAMME_EUR*FLAG_CONSTRUCT_YM1 -> 0 | F32: =ASM_I09_UOF_MECHANIZATION_PROGRAMME_EUR*FLAG_CONSTRUCT_Y0 -> 180000 | G32: =ASM_I09_UOF_MECHANIZATION_PROGRAMME_EUR*FLAG_CONSTRUCT_Y1 -> 0 | H32: =ASM_I09_UOF_MECHANIZATION_PROGRAMME_EUR*FLAG_CONSTRUCT_Y2 -> 0 | I32: =ASM_I09_UOF_MECHANIZATION_PROGRAMME_EUR*FLAG_CONSTRUCT_Y3 -> 0 | J32: =ASM_I09_UOF_MECHANIZATION_PROGRAMME_EUR*FLAG_CONSTRUCT_Y4 -> 0 | K32: =ASM_I09_UOF_MECHANIZATION_PROGRAMME_EUR*FLAG_CONSTRUCT_Y5 -> 0 | L32: =ASM_I09_UOF_MECHANIZATION_PROGRAMME_EUR*FLAG_CONSTRUCT_Y6 -> 0
B33: Monitoring — piezometers (4/farm) | C33: € | D33: =ASM_H08_N_PIEZOMETERS_PER_FARM*ASM_A01_N_FARMS*ASM_H09_COST_PER_PIEZOMETER_EUR -> 65460 | E33: =ASM_H08_N_PIEZOMETERS_PER_FARM*ASM_A01_N_FARMS*ASM_H09_COST_PER_PIEZOMETER_EUR*FLAG_CONSTRUCT_YM1 -> 0 | F33: =ASM_H08_N_PIEZOMETERS_PER_FARM*ASM_A01_N_FARMS*ASM_H09_COST_PER_PIEZOMETER_EUR*FLAG_CONSTRUCT_Y0 -> 65460 | G33: =ASM_H08_N_PIEZOMETERS_PER_FARM*ASM_A01_N_FARMS*ASM_H09_COST_PER_PIEZOMETER_EUR*FLAG_CONSTRUCT_Y1 -> 0 | H33: =ASM_H08_N_PIEZOMETERS_PER_FARM*ASM_A01_N_FARMS*ASM_H09_COST_PER_PIEZOMETER_EUR*FLAG_CONSTRUCT_Y2 -> 0 | I33: =ASM_H08_N_PIEZOMETERS_PER_FARM*ASM_A01_N_FARMS*ASM_H09_COST_PER_PIEZOMETER_EUR*FLAG_CONSTRUCT_Y3 -> 0 | J33: =ASM_H08_N_PIEZOMETERS_PER_FARM*ASM_A01_N_FARMS*ASM_H09_COST_PER_PIEZOMETER_EUR*FLAG_CONSTRUCT_Y4 -> 0 | K33: =ASM_H08_N_PIEZOMETERS_PER_FARM*ASM_A01_N_FARMS*ASM_H09_COST_PER_PIEZOMETER_EUR*FLAG_CONSTRUCT_Y5 -> 0 | L33: =ASM_H08_N_PIEZOMETERS_PER_FARM*ASM_A01_N_FARMS*ASM_H09_COST_PER_PIEZOMETER_EUR*FLAG_CONSTRUCT_Y6 -> 0
B34: Telemetry & SCADA (programme lump) | C34: € | D34: =ASM_H10_COST_TELEMETRY_LUMP_EUR -> 14545 | E34: =ASM_H10_COST_TELEMETRY_LUMP_EUR*FLAG_CONSTRUCT_YM1 -> 0 | F34: =ASM_H10_COST_TELEMETRY_LUMP_EUR*FLAG_CONSTRUCT_Y0 -> 14545 | G34: =ASM_H10_COST_TELEMETRY_LUMP_EUR*FLAG_CONSTRUCT_Y1 -> 0 | H34: =ASM_H10_COST_TELEMETRY_LUMP_EUR*FLAG_CONSTRUCT_Y2 -> 0 | I34: =ASM_H10_COST_TELEMETRY_LUMP_EUR*FLAG_CONSTRUCT_Y3 -> 0 | J34: =ASM_H10_COST_TELEMETRY_LUMP_EUR*FLAG_CONSTRUCT_Y4 -> 0 | K34: =ASM_H10_COST_TELEMETRY_LUMP_EUR*FLAG_CONSTRUCT_Y5 -> 0 | L34: =ASM_H10_COST_TELEMETRY_LUMP_EUR*FLAG_CONSTRUCT_Y6 -> 0
B35: Subtotal — Power, water & equipment | C35: € | D35: =SUM(D29:D34) -> 1369546 | E35: =SUM(E29:E34) -> 0 | F35: =SUM(F29:F34) -> 1369546 | G35: =SUM(G29:G34) -> 0 | H35: =SUM(H29:H34) -> 0 | I35: =SUM(I29:I34) -> 0 | J35: =SUM(J29:J34) -> 0 | K35: =SUM(K29:K34) -> 0 | L35: =SUM(L29:L34) -> 0
B36: TOTAL — THE THREE FARMS | C36: € | D36: =D20+D26+D35 -> 2701585.8 | E36: =E20+E26+E35 -> 0 | F36: =F20+F26+F35 -> 2701585.8 | G36: =G20+G26+G35 -> 0 | H36: =H20+H26+H35 -> 0 | I36: =I20+I26+I35 -> 0 | J36: =J20+J26+J35 -> 0 | K36: =K20+K26+K35 -> 0 | L36: =L20+L26+L35 -> 0
B38: Training infrastructure — one-time setup
B39: Curriculum & certification
B40: Curriculum & certification | C40: € | D40: =SUM(E40:L40) -> 678000 | E40: =TRAIN_CAP_CURRICULUM_YM1 -> 628000 | F40: =TRAIN_CAP_CURRICULUM_Y0 -> 50000 | G40: =TRAIN_CAP_CURRICULUM_Y1 -> 0 | H40: =TRAIN_CAP_CURRICULUM_Y2 -> 0 | I40: =TRAIN_CAP_CURRICULUM_Y3 -> 0 | J40: =TRAIN_CAP_CURRICULUM_Y4 -> 0 | K40: =TRAIN_CAP_CURRICULUM_Y5 -> 0 | L40: =TRAIN_CAP_CURRICULUM_Y6 -> 0
B41: Subtotal — Curriculum & certification | C41: € | D41: =SUM(D40) -> 678000 | E41: =SUM(E40) -> 628000 | F41: =SUM(F40) -> 50000 | G41: =SUM(G40) -> 0 | H41: =SUM(H40) -> 0 | I41: =SUM(I40) -> 0 | J41: =SUM(J40) -> 0 | K41: =SUM(K40) -> 0 | L41: =SUM(L40) -> 0
B43: Pedagogical plateaux & classroom
B44: Pedagogical plateaux & classroom | C44: € | D44: =SUM(E44:L44) -> 345000 | E44: =TRAIN_CAP_PLATEAUX_YM1 -> 0 | F44: =TRAIN_CAP_PLATEAUX_Y0 -> 345000 | G44: =TRAIN_CAP_PLATEAUX_Y1 -> 0 | H44: =TRAIN_CAP_PLATEAUX_Y2 -> 0 | I44: =TRAIN_CAP_PLATEAUX_Y3 -> 0 | J44: =TRAIN_CAP_PLATEAUX_Y4 -> 0 | K44: =TRAIN_CAP_PLATEAUX_Y5 -> 0 | L44: =TRAIN_CAP_PLATEAUX_Y6 -> 0
B45: Subtotal — Pedagogical plateaux & classroom | C45: € | D45: =SUM(D44) -> 345000 | E45: =SUM(E44) -> 0 | F45: =SUM(F44) -> 345000 | G45: =SUM(G44) -> 0 | H45: =SUM(H44) -> 0 | I45: =SUM(I44) -> 0 | J45: =SUM(J44) -> 0 | K45: =SUM(K44) -> 0 | L45: =SUM(L44) -> 0
B47: Accommodation
B48: Accommodation | C48: € | D48: =SUM(E48:L48) -> 385000 | E48: =TRAIN_CAP_ACCOMMODATION_YM1 -> 0 | F48: =TRAIN_CAP_ACCOMMODATION_Y0 -> 385000 | G48: =TRAIN_CAP_ACCOMMODATION_Y1 -> 0 | H48: =TRAIN_CAP_ACCOMMODATION_Y2 -> 0 | I48: =TRAIN_CAP_ACCOMMODATION_Y3 -> 0 | J48: =TRAIN_CAP_ACCOMMODATION_Y4 -> 0 | K48: =TRAIN_CAP_ACCOMMODATION_Y5 -> 0 | L48: =TRAIN_CAP_ACCOMMODATION_Y6 -> 0
B49: Subtotal — Accommodation | C49: € | D49: =SUM(D48) -> 385000 | E49: =SUM(E48) -> 0 | F49: =SUM(F48) -> 385000 | G49: =SUM(G48) -> 0 | H49: =SUM(H48) -> 0 | I49: =SUM(I48) -> 0 | J49: =SUM(J48) -> 0 | K49: =SUM(K48) -> 0 | L49: =SUM(L48) -> 0
B51: Monitoring & communications
B52: Monitoring & communications | C52: € | D52: =SUM(E52:L52) -> 80000 | E52: =TRAIN_CAP_MONITORING_YM1 -> 0 | F52: =TRAIN_CAP_MONITORING_Y0 -> 80000 | G52: =TRAIN_CAP_MONITORING_Y1 -> 0 | H52: =TRAIN_CAP_MONITORING_Y2 -> 0 | I52: =TRAIN_CAP_MONITORING_Y3 -> 0 | J52: =TRAIN_CAP_MONITORING_Y4 -> 0 | K52: =TRAIN_CAP_MONITORING_Y5 -> 0 | L52: =TRAIN_CAP_MONITORING_Y6 -> 0
B53: Subtotal — Monitoring & communications | C53: € | D53: =SUM(D52) -> 80000 | E53: =SUM(E52) -> 0 | F53: =SUM(F52) -> 80000 | G53: =SUM(G52) -> 0 | H53: =SUM(H52) -> 0 | I53: =SUM(I52) -> 0 | J53: =SUM(J52) -> 0 | K53: =SUM(K52) -> 0 | L53: =SUM(L52) -> 0
B54: TOTAL — WORKFORCE BUILD-UP | C54: € | D54: =D41+D45+D49+D53 -> 1488000 | E54: =E41+E45+E49+E53 -> 628000 | F54: =F41+F45+F49+F53 -> 860000 | G54: =G41+G45+G49+G53 -> 0 | H54: =H41+H45+H49+H53 -> 0 | I54: =I41+I45+I49+I53 -> 0 | J54: =J41+J45+J49+J53 -> 0 | K54: =K41+K45+K49+K53 -> 0 | L54: =L41+L45+L49+L53 -> 0
B56: Genetics platform — animal + plant (hardware)
B57: Animal genetics
B58: Centre veterinary (building) | C58: € | D58: =SUM(E58:L58) -> 125000 | E58: ='04_Genetics'!E16 -> 0 | F58: ='04_Genetics'!F16 -> 125000 | G58: ='04_Genetics'!G16 -> 0 | H58: ='04_Genetics'!H16 -> 0 | I58: ='04_Genetics'!I16 -> 0 | J58: ='04_Genetics'!J16 -> 0 | K58: ='04_Genetics'!K16 -> 0 | L58: ='04_Genetics'!L16 -> 0
B59: Animal equipment (pharma + lab + chute) | C59: € | D59: =SUM(E59:L59) -> 150000 | E59: ='04_Genetics'!E17 -> 0 | F59: ='04_Genetics'!F17 -> 150000 | G59: ='04_Genetics'!G17 -> 0 | H59: ='04_Genetics'!H17 -> 0 | I59: ='04_Genetics'!I17 -> 0 | J59: ='04_Genetics'!J17 -> 0 | K59: ='04_Genetics'!K17 -> 0 | L59: ='04_Genetics'!L17 -> 0
B60: Identification (boucles + bolus + lecteur) per unit | C60: € | D60: =SUM(E60:L60) -> 15000 | E60: ='04_Genetics'!E18 -> 0 | F60: ='04_Genetics'!F18 -> 15000 | G60: ='04_Genetics'!G18 -> 0 | H60: ='04_Genetics'!H18 -> 0 | I60: ='04_Genetics'!I18 -> 0 | J60: ='04_Genetics'!J18 -> 0 | K60: ='04_Genetics'!K18 -> 0 | L60: ='04_Genetics'!L18 -> 0
B61: AI hardware shared (tank + ultrasound + iPad) | C61: € | D61: =SUM(E61:L61) -> 8401 | E61: ='04_Genetics'!E19 -> 0 | F61: ='04_Genetics'!F19 -> 8401 | G61: ='04_Genetics'!G19 -> 0 | H61: ='04_Genetics'!H19 -> 0 | I61: ='04_Genetics'!I19 -> 0 | J61: ='04_Genetics'!J19 -> 0 | K61: ='04_Genetics'!K19 -> 0 | L61: ='04_Genetics'!L19 -> 0
B62: Subtotal — Animal genetics | C62: € | D62: =SUM(D58:D61) -> 298401 | E62: =SUM(E58:E61) -> 0 | F62: =SUM(F58:F61) -> 298401 | G62: =SUM(G58:G61) -> 0 | H62: =SUM(H58:H61) -> 0 | I62: =SUM(I58:I61) -> 0 | J62: =SUM(J58:J61) -> 0 | K62: =SUM(K58:K61) -> 0 | L62: =SUM(L58:L61) -> 0
B64: Plant genetics
B65: Centre végétal building (500 m² covered) | C65: € | D65: =SUM(E65:L65) -> 125000 | E65: ='04_Genetics'!E38 -> 0 | F65: ='04_Genetics'!F38 -> 125000 | G65: ='04_Genetics'!G38 -> 0 | H65: ='04_Genetics'!H38 -> 0 | I65: ='04_Genetics'!I38 -> 0 | J65: ='04_Genetics'!J38 -> 0 | K65: ='04_Genetics'!K38 -> 0 | L65: ='04_Genetics'!L38 -> 0
B66: Vegetal equipment (germinators + drip) | C66: € | D66: =SUM(E66:L66) -> 75000 | E66: ='04_Genetics'!E39 -> 0 | F66: ='04_Genetics'!F39 -> 75000 | G66: ='04_Genetics'!G39 -> 0 | H66: ='04_Genetics'!H39 -> 0 | I66: ='04_Genetics'!I39 -> 0 | J66: ='04_Genetics'!J39 -> 0 | K66: ='04_Genetics'!K39 -> 0 | L66: ='04_Genetics'!L39 -> 0
B67: Subtotal — Plant genetics | C67: € | D67: =SUM(D65:D66) -> 200000 | E67: =SUM(E65:E66) -> 0 | F67: =SUM(F65:F66) -> 200000 | G67: =SUM(G65:G66) -> 0 | H67: =SUM(H65:H66) -> 0 | I67: =SUM(I65:I66) -> 0 | J67: =SUM(J65:J66) -> 0 | K67: =SUM(K65:K66) -> 0 | L67: =SUM(L65:L66) -> 0
B68: TOTAL — GENETICS PLATFORM | C68: € | D68: =D62+D67 -> 498401 | E68: =E62+E67 -> 0 | F68: =F62+F67 -> 498401 | G68: =G62+G67 -> 0 | H68: =H62+H67 -> 0 | I68: =I62+I67 -> 0 | J68: =J62+J67 -> 0 | K68: =K62+K67 -> 0 | L68: =L62+L67 -> 0
B70: Development & structuring costs (Y0)
B71: Pre-FID development
B72: Studies & EIES | C72: € | D72: =ASM_J01_COST_STUDIES_EUR -> 109091 | E72: =ASM_J01_COST_STUDIES_EUR*FLAG_CONSTRUCT_YM1 -> 0 | F72: =ASM_J01_COST_STUDIES_EUR*FLAG_CONSTRUCT_Y0 -> 109091 | G72: =ASM_J01_COST_STUDIES_EUR*FLAG_CONSTRUCT_Y1 -> 0 | H72: =ASM_J01_COST_STUDIES_EUR*FLAG_CONSTRUCT_Y2 -> 0 | I72: =ASM_J01_COST_STUDIES_EUR*FLAG_CONSTRUCT_Y3 -> 0 | J72: =ASM_J01_COST_STUDIES_EUR*FLAG_CONSTRUCT_Y4 -> 0 | K72: =ASM_J01_COST_STUDIES_EUR*FLAG_CONSTRUCT_Y5 -> 0 | L72: =ASM_J01_COST_STUDIES_EUR*FLAG_CONSTRUCT_Y6 -> 0
B73: Legal & advisory | C73: € | D73: =ASM_J03_COST_LEGAL_EUR -> 72727 | E73: =ASM_J03_COST_LEGAL_EUR*FLAG_CONSTRUCT_YM1 -> 0 | F73: =ASM_J03_COST_LEGAL_EUR*FLAG_CONSTRUCT_Y0 -> 72727 | G73: =ASM_J03_COST_LEGAL_EUR*FLAG_CONSTRUCT_Y1 -> 0 | H73: =ASM_J03_COST_LEGAL_EUR*FLAG_CONSTRUCT_Y2 -> 0 | I73: =ASM_J03_COST_LEGAL_EUR*FLAG_CONSTRUCT_Y3 -> 0 | J73: =ASM_J03_COST_LEGAL_EUR*FLAG_CONSTRUCT_Y4 -> 0 | K73: =ASM_J03_COST_LEGAL_EUR*FLAG_CONSTRUCT_Y5 -> 0 | L73: =ASM_J03_COST_LEGAL_EUR*FLAG_CONSTRUCT_Y6 -> 0
B74: Subtotal — Pre-FID development | C74: € | D74: =SUM(D72:D73) -> 181818 | E74: =SUM(E72:E73) -> 0 | F74: =SUM(F72:F73) -> 181818 | G74: =SUM(G72:G73) -> 0 | H74: =SUM(H72:H73) -> 0 | I74: =SUM(I72:I73) -> 0 | J74: =SUM(J72:J73) -> 0 | K74: =SUM(K72:K73) -> 0 | L74: =SUM(L72:L73) -> 0
B76: Construction-phase oversight
B77: Construction supervision (5% of farm CAPEX cash) | C77: € | D77: =SUM(E77:L77) -> 152329.18 | E77: =(ASM_A01_N_FARMS*(E$99+E$100+E$101+E$102+ASM_I07_UOF_WATER_PER_FARM_EUR+ASM_I08_UOF_ENERGY_PER_FARM_EUR)+ASM_I09_UOF_MECHANIZATION_PROGRAMME_EUR+ASM_A01_N_FARMS*ASM_I05_TREES_PER_FARM*ASM_I06_COST_PER_TREE_EUR+ASM_A01_N_FARMS*(ASM_F02_ADDITIONAL_BEDS_PER_FARM*ASM_F03_COST_PER_TRAINEE_BED_EUR+ASM_F04_COST_REFECTOIRE_PER_FARM_EUR)+ASM_H08_N_PIEZOMETERS_PER_FARM*ASM_A01_N_FARMS*ASM_H09_COST_PER_PIEZOMETER_EUR+ASM_H10_COST_TELEMETRY_LUMP_EUR)*ASM_J02_PCT_SUPERVISION_CONSTRUCTION*FLAG_CONSTRUCT_YM1 -> 0 | F77: =(ASM_A01_N_FARMS*(F$99+F$100+F$101+F$102+ASM_I07_UOF_WATER_PER_FARM_EUR+ASM_I08_UOF_ENERGY_PER_FARM_EUR)+ASM_I09_UOF_MECHANIZATION_PROGRAMME_EUR+ASM_A01_N_FARMS*ASM_I05_TREES_PER_FARM*ASM_I06_COST_PER_TREE_EUR+ASM_A01_N_FARMS*(ASM_F02_ADDITIONAL_BEDS_PER_FARM*ASM_F03_COST_PER_TRAINEE_BED_EUR+ASM_F04_COST_REFECTOIRE_PER_FARM_EUR)+ASM_H08_N_PIEZOMETERS_PER_FARM*ASM_A01_N_FARMS*ASM_H09_COST_PER_PIEZOMETER_EUR+ASM_H10_COST_TELEMETRY_LUMP_EUR)*ASM_J02_PCT_SUPERVISION_CONSTRUCTION*FLAG_CONSTRUCT_Y0 -> 152329.18 | G77: =(ASM_A01_N_FARMS*(G$99+G$100+G$101+G$102+ASM_I07_UOF_WATER_PER_FARM_EUR+ASM_I08_UOF_ENERGY_PER_FARM_EUR)+ASM_I09_UOF_MECHANIZATION_PROGRAMME_EUR+ASM_A01_N_FARMS*ASM_I05_TREES_PER_FARM*ASM_I06_COST_PER_TREE_EUR+ASM_A01_N_FARMS*(ASM_F02_ADDITIONAL_BEDS_PER_FARM*ASM_F03_COST_PER_TRAINEE_BED_EUR+ASM_F04_COST_REFECTOIRE_PER_FARM_EUR)+ASM_H08_N_PIEZOMETERS_PER_FARM*ASM_A01_N_FARMS*ASM_H09_COST_PER_PIEZOMETER_EUR+ASM_H10_COST_TELEMETRY_LUMP_EUR)*ASM_J02_PCT_SUPERVISION_CONSTRUCTION*FLAG_CONSTRUCT_Y1 -> 0 | H77: =(ASM_A01_N_FARMS*(H$99+H$100+H$101+H$102+ASM_I07_UOF_WATER_PER_FARM_EUR+ASM_I08_UOF_ENERGY_PER_FARM_EUR)+ASM_I09_UOF_MECHANIZATION_PROGRAMME_EUR+ASM_A01_N_FARMS*ASM_I05_TREES_PER_FARM*ASM_I06_COST_PER_TREE_EUR+ASM_A01_N_FARMS*(ASM_F02_ADDITIONAL_BEDS_PER_FARM*ASM_F03_COST_PER_TRAINEE_BED_EUR+ASM_F04_COST_REFECTOIRE_PER_FARM_EUR)+ASM_H08_N_PIEZOMETERS_PER_FARM*ASM_A01_N_FARMS*ASM_H09_COST_PER_PIEZOMETER_EUR+ASM_H10_COST_TELEMETRY_LUMP_EUR)*ASM_J02_PCT_SUPERVISION_CONSTRUCTION*FLAG_CONSTRUCT_Y2 -> 0 | I77: =(ASM_A01_N_FARMS*(I$99+I$100+I$101+I$102+ASM_I07_UOF_WATER_PER_FARM_EUR+ASM_I08_UOF_ENERGY_PER_FARM_EUR)+ASM_I09_UOF_MECHANIZATION_PROGRAMME_EUR+ASM_A01_N_FARMS*ASM_I05_TREES_PER_FARM*ASM_I06_COST_PER_TREE_EUR+ASM_A01_N_FARMS*(ASM_F02_ADDITIONAL_BEDS_PER_FARM*ASM_F03_COST_PER_TRAINEE_BED_EUR+ASM_F04_COST_REFECTOIRE_PER_FARM_EUR)+ASM_H08_N_PIEZOMETERS_PER_FARM*ASM_A01_N_FARMS*ASM_H09_COST_PER_PIEZOMETER_EUR+ASM_H10_COST_TELEMETRY_LUMP_EUR)*ASM_J02_PCT_SUPERVISION_CONSTRUCTION*FLAG_CONSTRUCT_Y3 -> 0 | J77: =(ASM_A01_N_FARMS*(J$99+J$100+J$101+J$102+ASM_I07_UOF_WATER_PER_FARM_EUR+ASM_I08_UOF_ENERGY_PER_FARM_EUR)+ASM_I09_UOF_MECHANIZATION_PROGRAMME_EUR+ASM_A01_N_FARMS*ASM_I05_TREES_PER_FARM*ASM_I06_COST_PER_TREE_EUR+ASM_A01_N_FARMS*(ASM_F02_ADDITIONAL_BEDS_PER_FARM*ASM_F03_COST_PER_TRAINEE_BED_EUR+ASM_F04_COST_REFECTOIRE_PER_FARM_EUR)+ASM_H08_N_PIEZOMETERS_PER_FARM*ASM_A01_N_FARMS*ASM_H09_COST_PER_PIEZOMETER_EUR+ASM_H10_COST_TELEMETRY_LUMP_EUR)*ASM_J02_PCT_SUPERVISION_CONSTRUCTION*FLAG_CONSTRUCT_Y4 -> 0 | K77: =(ASM_A01_N_FARMS*(K$99+K$100+K$101+K$102+ASM_I07_UOF_WATER_PER_FARM_EUR+ASM_I08_UOF_ENERGY_PER_FARM_EUR)+ASM_I09_UOF_MECHANIZATION_PROGRAMME_EUR+ASM_A01_N_FARMS*ASM_I05_TREES_PER_FARM*ASM_I06_COST_PER_TREE_EUR+ASM_A01_N_FARMS*(ASM_F02_ADDITIONAL_BEDS_PER_FARM*ASM_F03_COST_PER_TRAINEE_BED_EUR+ASM_F04_COST_REFECTOIRE_PER_FARM_EUR)+ASM_H08_N_PIEZOMETERS_PER_FARM*ASM_A01_N_FARMS*ASM_H09_COST_PER_PIEZOMETER_EUR+ASM_H10_COST_TELEMETRY_LUMP_EUR)*ASM_J02_PCT_SUPERVISION_CONSTRUCTION*FLAG_CONSTRUCT_Y5 -> 0 | L77: =(ASM_A01_N_FARMS*(L$99+L$100+L$101+L$102+ASM_I07_UOF_WATER_PER_FARM_EUR+ASM_I08_UOF_ENERGY_PER_FARM_EUR)+ASM_I09_UOF_MECHANIZATION_PROGRAMME_EUR+ASM_A01_N_FARMS*ASM_I05_TREES_PER_FARM*ASM_I06_COST_PER_TREE_EUR+ASM_A01_N_FARMS*(ASM_F02_ADDITIONAL_BEDS_PER_FARM*ASM_F03_COST_PER_TRAINEE_BED_EUR+ASM_F04_COST_REFECTOIRE_PER_FARM_EUR)+ASM_H08_N_PIEZOMETERS_PER_FARM*ASM_A01_N_FARMS*ASM_H09_COST_PER_PIEZOMETER_EUR+ASM_H10_COST_TELEMETRY_LUMP_EUR)*ASM_J02_PCT_SUPERVISION_CONSTRUCTION*FLAG_CONSTRUCT_Y6 -> 0
B78: Subtotal — Construction-phase oversight | C78: € | D78: =SUM(D77) -> 152329.18 | E78: =SUM(E77) -> 0 | F78: =SUM(F77) -> 152329.18 | G78: =SUM(G77) -> 0 | H78: =SUM(H77) -> 0 | I78: =SUM(I77) -> 0 | J78: =SUM(J77) -> 0 | K78: =SUM(K77) -> 0 | L78: =SUM(L77) -> 0
B79: TOTAL — DEVELOPMENT & STRUCTURING | C79: € | D79: =D74+D78 -> 334147.18 | E79: =E74+E78 -> 0 | F79: =F74+F78 -> 334147.18 | G79: =G74+G78 -> 0 | H79: =H74+H78 -> 0 | I79: =I74+I78 -> 0 | J79: =J74+J78 -> 0 | K79: =K74+K78 -> 0 | L79: =L74+L78 -> 0
B81: Reserves (Y0)
B82: Working capital buffer (3 months OpEx) | C82: € | D82: =ASM_K01_N_MONTHS_WC*ASM_K02_MONTHLY_OPEX_PER_FARM_EUR*ASM_A01_N_FARMS -> 180000 | E82: =ASM_K01_N_MONTHS_WC*ASM_K02_MONTHLY_OPEX_PER_FARM_EUR*ASM_A01_N_FARMS*FLAG_CONSTRUCT_YM1 -> 0 | F82: =ASM_K01_N_MONTHS_WC*ASM_K02_MONTHLY_OPEX_PER_FARM_EUR*ASM_A01_N_FARMS*FLAG_CONSTRUCT_Y0 -> 180000 | G82: =ASM_K01_N_MONTHS_WC*ASM_K02_MONTHLY_OPEX_PER_FARM_EUR*ASM_A01_N_FARMS*FLAG_CONSTRUCT_Y1 -> 0 | H82: =ASM_K01_N_MONTHS_WC*ASM_K02_MONTHLY_OPEX_PER_FARM_EUR*ASM_A01_N_FARMS*FLAG_CONSTRUCT_Y2 -> 0 | I82: =ASM_K01_N_MONTHS_WC*ASM_K02_MONTHLY_OPEX_PER_FARM_EUR*ASM_A01_N_FARMS*FLAG_CONSTRUCT_Y3 -> 0 | J82: =ASM_K01_N_MONTHS_WC*ASM_K02_MONTHLY_OPEX_PER_FARM_EUR*ASM_A01_N_FARMS*FLAG_CONSTRUCT_Y4 -> 0 | K82: =ASM_K01_N_MONTHS_WC*ASM_K02_MONTHLY_OPEX_PER_FARM_EUR*ASM_A01_N_FARMS*FLAG_CONSTRUCT_Y5 -> 0 | L82: =ASM_K01_N_MONTHS_WC*ASM_K02_MONTHLY_OPEX_PER_FARM_EUR*ASM_A01_N_FARMS*FLAG_CONSTRUCT_Y6 -> 0
B83: DSRA (LC-funded, off-balance-sheet — face value €227k) | C83: € | D83: =ASM_K05_DSRA_AMOUNT_EUR -> 0 | E83: =ASM_K05_DSRA_AMOUNT_EUR*FLAG_CONSTRUCT_YM1 -> 0 | F83: =ASM_K05_DSRA_AMOUNT_EUR*FLAG_CONSTRUCT_Y0 -> 0 | G83: =ASM_K05_DSRA_AMOUNT_EUR*FLAG_CONSTRUCT_Y1 -> 0 | H83: =ASM_K05_DSRA_AMOUNT_EUR*FLAG_CONSTRUCT_Y2 -> 0 | I83: =ASM_K05_DSRA_AMOUNT_EUR*FLAG_CONSTRUCT_Y3 -> 0 | J83: =ASM_K05_DSRA_AMOUNT_EUR*FLAG_CONSTRUCT_Y4 -> 0 | K83: =ASM_K05_DSRA_AMOUNT_EUR*FLAG_CONSTRUCT_Y5 -> 0 | L83: =ASM_K05_DSRA_AMOUNT_EUR*FLAG_CONSTRUCT_Y6 -> 0
B84: MMR (1 month of farm OpEx, maintenance reserve) | C84: € | D84: =ASM_K06_N_MONTHS_MMR*ASM_K02_MONTHLY_OPEX_PER_FARM_EUR*ASM_A01_N_FARMS -> 60000 | E84: =ASM_K06_N_MONTHS_MMR*ASM_K02_MONTHLY_OPEX_PER_FARM_EUR*ASM_A01_N_FARMS*FLAG_CONSTRUCT_YM1 -> 0 | F84: =ASM_K06_N_MONTHS_MMR*ASM_K02_MONTHLY_OPEX_PER_FARM_EUR*ASM_A01_N_FARMS*FLAG_CONSTRUCT_Y0 -> 60000 | G84: =ASM_K06_N_MONTHS_MMR*ASM_K02_MONTHLY_OPEX_PER_FARM_EUR*ASM_A01_N_FARMS*FLAG_CONSTRUCT_Y1 -> 0 | H84: =ASM_K06_N_MONTHS_MMR*ASM_K02_MONTHLY_OPEX_PER_FARM_EUR*ASM_A01_N_FARMS*FLAG_CONSTRUCT_Y2 -> 0 | I84: =ASM_K06_N_MONTHS_MMR*ASM_K02_MONTHLY_OPEX_PER_FARM_EUR*ASM_A01_N_FARMS*FLAG_CONSTRUCT_Y3 -> 0 | J84: =ASM_K06_N_MONTHS_MMR*ASM_K02_MONTHLY_OPEX_PER_FARM_EUR*ASM_A01_N_FARMS*FLAG_CONSTRUCT_Y4 -> 0 | K84: =ASM_K06_N_MONTHS_MMR*ASM_K02_MONTHLY_OPEX_PER_FARM_EUR*ASM_A01_N_FARMS*FLAG_CONSTRUCT_Y5 -> 0 | L84: =ASM_K06_N_MONTHS_MMR*ASM_K02_MONTHLY_OPEX_PER_FARM_EUR*ASM_A01_N_FARMS*FLAG_CONSTRUCT_Y6 -> 0
B85: Contingency (10% of hard CAPEX) | C85: € | D85: =SUM(E85:L85) -> 304658.36 | E85: =(ASM_A01_N_FARMS*(E$99+E$100+E$101+E$102+ASM_I07_UOF_WATER_PER_FARM_EUR+ASM_I08_UOF_ENERGY_PER_FARM_EUR)+ASM_I09_UOF_MECHANIZATION_PROGRAMME_EUR+ASM_A01_N_FARMS*ASM_I05_TREES_PER_FARM*ASM_I06_COST_PER_TREE_EUR+ASM_A01_N_FARMS*(ASM_F02_ADDITIONAL_BEDS_PER_FARM*ASM_F03_COST_PER_TRAINEE_BED_EUR+ASM_F04_COST_REFECTOIRE_PER_FARM_EUR)+ASM_H08_N_PIEZOMETERS_PER_FARM*ASM_A01_N_FARMS*ASM_H09_COST_PER_PIEZOMETER_EUR+ASM_H10_COST_TELEMETRY_LUMP_EUR)*ASM_K03_PCT_CONTINGENCY_B1*FLAG_CONSTRUCT_YM1 -> 0 | F85: =(ASM_A01_N_FARMS*(F$99+F$100+F$101+F$102+ASM_I07_UOF_WATER_PER_FARM_EUR+ASM_I08_UOF_ENERGY_PER_FARM_EUR)+ASM_I09_UOF_MECHANIZATION_PROGRAMME_EUR+ASM_A01_N_FARMS*ASM_I05_TREES_PER_FARM*ASM_I06_COST_PER_TREE_EUR+ASM_A01_N_FARMS*(ASM_F02_ADDITIONAL_BEDS_PER_FARM*ASM_F03_COST_PER_TRAINEE_BED_EUR+ASM_F04_COST_REFECTOIRE_PER_FARM_EUR)+ASM_H08_N_PIEZOMETERS_PER_FARM*ASM_A01_N_FARMS*ASM_H09_COST_PER_PIEZOMETER_EUR+ASM_H10_COST_TELEMETRY_LUMP_EUR)*ASM_K03_PCT_CONTINGENCY_B1*FLAG_CONSTRUCT_Y0 -> 304658.36 | G85: =(ASM_A01_N_FARMS*(G$99+G$100+G$101+G$102+ASM_I07_UOF_WATER_PER_FARM_EUR+ASM_I08_UOF_ENERGY_PER_FARM_EUR)+ASM_I09_UOF_MECHANIZATION_PROGRAMME_EUR+ASM_A01_N_FARMS*ASM_I05_TREES_PER_FARM*ASM_I06_COST_PER_TREE_EUR+ASM_A01_N_FARMS*(ASM_F02_ADDITIONAL_BEDS_PER_FARM*ASM_F03_COST_PER_TRAINEE_BED_EUR+ASM_F04_COST_REFECTOIRE_PER_FARM_EUR)+ASM_H08_N_PIEZOMETERS_PER_FARM*ASM_A01_N_FARMS*ASM_H09_COST_PER_PIEZOMETER_EUR+ASM_H10_COST_TELEMETRY_LUMP_EUR)*ASM_K03_PCT_CONTINGENCY_B1*FLAG_CONSTRUCT_Y1 -> 0 | H85: =(ASM_A01_N_FARMS*(H$99+H$100+H$101+H$102+ASM_I07_UOF_WATER_PER_FARM_EUR+ASM_I08_UOF_ENERGY_PER_FARM_EUR)+ASM_I09_UOF_MECHANIZATION_PROGRAMME_EUR+ASM_A01_N_FARMS*ASM_I05_TREES_PER_FARM*ASM_I06_COST_PER_TREE_EUR+ASM_A01_N_FARMS*(ASM_F02_ADDITIONAL_BEDS_PER_FARM*ASM_F03_COST_PER_TRAINEE_BED_EUR+ASM_F04_COST_REFECTOIRE_PER_FARM_EUR)+ASM_H08_N_PIEZOMETERS_PER_FARM*ASM_A01_N_FARMS*ASM_H09_COST_PER_PIEZOMETER_EUR+ASM_H10_COST_TELEMETRY_LUMP_EUR)*ASM_K03_PCT_CONTINGENCY_B1*FLAG_CONSTRUCT_Y2 -> 0 | I85: =(ASM_A01_N_FARMS*(I$99+I$100+I$101+I$102+ASM_I07_UOF_WATER_PER_FARM_EUR+ASM_I08_UOF_ENERGY_PER_FARM_EUR)+ASM_I09_UOF_MECHANIZATION_PROGRAMME_EUR+ASM_A01_N_FARMS*ASM_I05_TREES_PER_FARM*ASM_I06_COST_PER_TREE_EUR+ASM_A01_N_FARMS*(ASM_F02_ADDITIONAL_BEDS_PER_FARM*ASM_F03_COST_PER_TRAINEE_BED_EUR+ASM_F04_COST_REFECTOIRE_PER_FARM_EUR)+ASM_H08_N_PIEZOMETERS_PER_FARM*ASM_A01_N_FARMS*ASM_H09_COST_PER_PIEZOMETER_EUR+ASM_H10_COST_TELEMETRY_LUMP_EUR)*ASM_K03_PCT_CONTINGENCY_B1*FLAG_CONSTRUCT_Y3 -> 0 | J85: =(ASM_A01_N_FARMS*(J$99+J$100+J$101+J$102+ASM_I07_UOF_WATER_PER_FARM_EUR+ASM_I08_UOF_ENERGY_PER_FARM_EUR)+ASM_I09_UOF_MECHANIZATION_PROGRAMME_EUR+ASM_A01_N_FARMS*ASM_I05_TREES_PER_FARM*ASM_I06_COST_PER_TREE_EUR+ASM_A01_N_FARMS*(ASM_F02_ADDITIONAL_BEDS_PER_FARM*ASM_F03_COST_PER_TRAINEE_BED_EUR+ASM_F04_COST_REFECTOIRE_PER_FARM_EUR)+ASM_H08_N_PIEZOMETERS_PER_FARM*ASM_A01_N_FARMS*ASM_H09_COST_PER_PIEZOMETER_EUR+ASM_H10_COST_TELEMETRY_LUMP_EUR)*ASM_K03_PCT_CONTINGENCY_B1*FLAG_CONSTRUCT_Y4 -> 0 | K85: =(ASM_A01_N_FARMS*(K$99+K$100+K$101+K$102+ASM_I07_UOF_WATER_PER_FARM_EUR+ASM_I08_UOF_ENERGY_PER_FARM_EUR)+ASM_I09_UOF_MECHANIZATION_PROGRAMME_EUR+ASM_A01_N_FARMS*ASM_I05_TREES_PER_FARM*ASM_I06_COST_PER_TREE_EUR+ASM_A01_N_FARMS*(ASM_F02_ADDITIONAL_BEDS_PER_FARM*ASM_F03_COST_PER_TRAINEE_BED_EUR+ASM_F04_COST_REFECTOIRE_PER_FARM_EUR)+ASM_H08_N_PIEZOMETERS_PER_FARM*ASM_A01_N_FARMS*ASM_H09_COST_PER_PIEZOMETER_EUR+ASM_H10_COST_TELEMETRY_LUMP_EUR)*ASM_K03_PCT_CONTINGENCY_B1*FLAG_CONSTRUCT_Y5 -> 0 | L85: =(ASM_A01_N_FARMS*(L$99+L$100+L$101+L$102+ASM_I07_UOF_WATER_PER_FARM_EUR+ASM_I08_UOF_ENERGY_PER_FARM_EUR)+ASM_I09_UOF_MECHANIZATION_PROGRAMME_EUR+ASM_A01_N_FARMS*ASM_I05_TREES_PER_FARM*ASM_I06_COST_PER_TREE_EUR+ASM_A01_N_FARMS*(ASM_F02_ADDITIONAL_BEDS_PER_FARM*ASM_F03_COST_PER_TRAINEE_BED_EUR+ASM_F04_COST_REFECTOIRE_PER_FARM_EUR)+ASM_H08_N_PIEZOMETERS_PER_FARM*ASM_A01_N_FARMS*ASM_H09_COST_PER_PIEZOMETER_EUR+ASM_H10_COST_TELEMETRY_LUMP_EUR)*ASM_K03_PCT_CONTINGENCY_B1*FLAG_CONSTRUCT_Y6 -> 0
B86: TOTAL — RESERVES | C86: € | D86: =SUM(D82:D85) -> 544658.36 | E86: =SUM(E82:E85) -> 0 | F86: =SUM(F82:F85) -> 544658.36 | G86: =SUM(G82:G85) -> 0 | H86: =SUM(H82:H85) -> 0 | I86: =SUM(I82:I85) -> 0 | J86: =SUM(J82:J85) -> 0 | K86: =SUM(K82:K85) -> 0 | L86: =SUM(L82:L85) -> 0
B89: Inputs from Assumptions
B90: A01 — Number of farms | C90: farms | D90: =SUM(E90:L90) -> 24 | E90: =ASM_A01_N_FARMS -> 3 | F90: =ASM_A01_N_FARMS -> 3 | G90: =ASM_A01_N_FARMS -> 3 | H90: =ASM_A01_N_FARMS -> 3 | I90: =ASM_A01_N_FARMS -> 3 | J90: =ASM_A01_N_FARMS -> 3 | K90: =ASM_A01_N_FARMS -> 3 | L90: =ASM_A01_N_FARMS -> 3
B91: A08 — EUR/USD exchange rate | C91: EUR/USD | D91: =SUM(E91:L91) -> 8.8 | E91: =ASM_A08_EUR_USD -> 1.1 | F91: =ASM_A08_EUR_USD -> 1.1 | G91: =ASM_A08_EUR_USD -> 1.1 | H91: =ASM_A08_EUR_USD -> 1.1 | I91: =ASM_A08_EUR_USD -> 1.1 | J91: =ASM_A08_EUR_USD -> 1.1 | K91: =ASM_A08_EUR_USD -> 1.1 | L91: =ASM_A08_EUR_USD -> 1.1
B92: X17 — USD — uof_land per farm | C92: USD/farm | D92: =SUM(E92:L92) -> 3420800 | E92: =ASM_X17_DOLLAR_UOF_LAND_PER_FARM -> 427600 | F92: =ASM_X17_DOLLAR_UOF_LAND_PER_FARM -> 427600 | G92: =ASM_X17_DOLLAR_UOF_LAND_PER_FARM -> 427600 | H92: =ASM_X17_DOLLAR_UOF_LAND_PER_FARM -> 427600 | I92: =ASM_X17_DOLLAR_UOF_LAND_PER_FARM -> 427600 | J92: =ASM_X17_DOLLAR_UOF_LAND_PER_FARM -> 427600 | K92: =ASM_X17_DOLLAR_UOF_LAND_PER_FARM -> 427600 | L92: =ASM_X17_DOLLAR_UOF_LAND_PER_FARM -> 427600
B93: X18 — USD — uof_buildings per farm | C93: USD/farm | D93: =SUM(E93:L93) -> 926520 | E93: =ASM_X18_DOLLAR_UOF_BUILDINGS_PER_FARM -> 115815 | F93: =ASM_X18_DOLLAR_UOF_BUILDINGS_PER_FARM -> 115815 | G93: =ASM_X18_DOLLAR_UOF_BUILDINGS_PER_FARM -> 115815 | H93: =ASM_X18_DOLLAR_UOF_BUILDINGS_PER_FARM -> 115815 | I93: =ASM_X18_DOLLAR_UOF_BUILDINGS_PER_FARM -> 115815 | J93: =ASM_X18_DOLLAR_UOF_BUILDINGS_PER_FARM -> 115815 | K93: =ASM_X18_DOLLAR_UOF_BUILDINGS_PER_FARM -> 115815 | L93: =ASM_X18_DOLLAR_UOF_BUILDINGS_PER_FARM -> 115815
B94: X19 — USD — uof_dairy per farm | C94: USD/farm | D94: =SUM(E94:L94) -> 982400 | E94: =ASM_X19_DOLLAR_UOF_DAIRY_PER_FARM -> 122800 | F94: =ASM_X19_DOLLAR_UOF_DAIRY_PER_FARM -> 122800 | G94: =ASM_X19_DOLLAR_UOF_DAIRY_PER_FARM -> 122800 | H94: =ASM_X19_DOLLAR_UOF_DAIRY_PER_FARM -> 122800 | I94: =ASM_X19_DOLLAR_UOF_DAIRY_PER_FARM -> 122800 | J94: =ASM_X19_DOLLAR_UOF_DAIRY_PER_FARM -> 122800 | K94: =ASM_X19_DOLLAR_UOF_DAIRY_PER_FARM -> 122800 | L94: =ASM_X19_DOLLAR_UOF_DAIRY_PER_FARM -> 122800
B95: X20 — USD — uof_feedlot per farm | C95: USD/farm | D95: =SUM(E95:L95) -> 69208 | E95: =ASM_X20_DOLLAR_UOF_FEEDLOT_PER_FARM -> 8651 | F95: =ASM_X20_DOLLAR_UOF_FEEDLOT_PER_FARM -> 8651 | G95: =ASM_X20_DOLLAR_UOF_FEEDLOT_PER_FARM -> 8651 | H95: =ASM_X20_DOLLAR_UOF_FEEDLOT_PER_FARM -> 8651 | I95: =ASM_X20_DOLLAR_UOF_FEEDLOT_PER_FARM -> 8651 | J95: =ASM_X20_DOLLAR_UOF_FEEDLOT_PER_FARM -> 8651 | K95: =ASM_X20_DOLLAR_UOF_FEEDLOT_PER_FARM -> 8651 | L95: =ASM_X20_DOLLAR_UOF_FEEDLOT_PER_FARM -> 8651
B96: L07 — L07 — In-kind land TOTAL (programme, for I01c per farm) | C96: € | D96: =SUM(E96:L96) -> 3591272.7 | E96: =ASM_L07_EQUITY_EQ2_INKIND_TERRAIN_EUR -> 448909.09 | F96: =ASM_L07_EQUITY_EQ2_INKIND_TERRAIN_EUR -> 448909.09 | G96: =ASM_L07_EQUITY_EQ2_INKIND_TERRAIN_EUR -> 448909.09 | H96: =ASM_L07_EQUITY_EQ2_INKIND_TERRAIN_EUR -> 448909.09 | I96: =ASM_L07_EQUITY_EQ2_INKIND_TERRAIN_EUR -> 448909.09 | J96: =ASM_L07_EQUITY_EQ2_INKIND_TERRAIN_EUR -> 448909.09 | K96: =ASM_L07_EQUITY_EQ2_INKIND_TERRAIN_EUR -> 448909.09 | L96: =ASM_L07_EQUITY_EQ2_INKIND_TERRAIN_EUR -> 448909.09
B98: Calculated values
B99: I01 — uof_land EUR/farm | C99: €/farm | D99: =SUM(E99:L99) -> 3109818.2 | E99: =E$92/E$91 -> 388727.27 | F99: =F$92/F$91 -> 388727.27 | G99: =G$92/G$91 -> 388727.27 | H99: =H$92/H$91 -> 388727.27 | I99: =I$92/I$91 -> 388727.27 | J99: =J$92/J$91 -> 388727.27 | K99: =K$92/K$91 -> 388727.27 | L99: =L$92/L$91 -> 388727.27
B100: I02 — uof_buildings EUR/farm | C100: €/farm | D100: =SUM(E100:L100) -> 842290.91 | E100: =E$93/E$91 -> 105286.36 | F100: =F$93/F$91 -> 105286.36 | G100: =G$93/G$91 -> 105286.36 | H100: =H$93/H$91 -> 105286.36 | I100: =I$93/I$91 -> 105286.36 | J100: =J$93/J$91 -> 105286.36 | K100: =K$93/K$91 -> 105286.36 | L100: =L$93/L$91 -> 105286.36
B101: I03 — uof_dairy EUR/farm | C101: €/farm | D101: =SUM(E101:L101) -> 893090.91 | E101: =E$94/E$91 -> 111636.36 | F101: =F$94/F$91 -> 111636.36 | G101: =G$94/G$91 -> 111636.36 | H101: =H$94/H$91 -> 111636.36 | I101: =I$94/I$91 -> 111636.36 | J101: =J$94/J$91 -> 111636.36 | K101: =K$94/K$91 -> 111636.36 | L101: =L$94/L$91 -> 111636.36
B102: I04 — uof_feedlot EUR/farm | C102: €/farm | D102: =SUM(E102:L102) -> 62916.364 | E102: =E$95/E$91 -> 7864.5455 | F102: =F$95/F$91 -> 7864.5455 | G102: =G$95/G$91 -> 7864.5455 | H102: =H$95/H$91 -> 7864.5455 | I102: =I$95/I$91 -> 7864.5455 | J102: =J$95/J$91 -> 7864.5455 | K102: =K$95/K$91 -> 7864.5455 | L102: =L$95/L$91 -> 7864.5455
B103: I01c — I01c — In-kind land EUR/farm | C103: €/farm | D103: =SUM(E103:L103) -> 1197090.9 | E103: =E$96/E$90 -> 149636.36 | F103: =F$96/F$90 -> 149636.36 | G103: =G$96/G$90 -> 149636.36 | H103: =H$96/H$90 -> 149636.36 | I103: =I$96/I$90 -> 149636.36 | J103: =J$96/J$90 -> 149636.36 | K103: =K$96/K$90 -> 149636.36 | L103: =L$96/L$90 -> 149636.36

Sheet 06_S&U
B1: 06 — Sources & Uses [€]
D3: Total | E3: Y-1 | F3: Y0 | G3: Y1 | H3: Y2 | I3: Y3 | J3: Y4 | K3: Y5 | L3: Y6
E4: -1 | F4: 0 | G4: 1 | H4: 2 | I4: 3 | J4: 4 | K4: 5 | L4: 6
B6: Summary
B7: USES BY PURPOSE | C7: €
B8: 1. The three farms — production assets | C8: € | D8: =SUM(E8:L8) -> 2746585.8 | E8: =E31 -> 0 | F8: =F31 -> 2746585.8 | G8: =G31 -> 0 | H8: =H31 -> 0 | I8: =I31 -> 0 | J8: =J31 -> 0 | K8: =K31 -> 0 | L8: =L31 -> 0
B9: 2. Workforce build-up — training + cohorts | C9: € | D9: =SUM(E9:L9) -> 2847700 | E9: =E36 -> 628000 | F9: =F36 -> 860000 | G9: =G36 -> 679850 | H9: =H36 -> 679850 | I9: =I36 -> 0 | J9: =J36 -> 0 | K9: =K36 -> 0 | L9: =L36 -> 0
B10: 3. Genetics platform — animal + plant | C10: € | D10: =SUM(E10:L10) -> 1177761 | E10: =E43 -> 0 | F10: =F43 -> 676201 | G10: =G43 -> 250780 | H10: =H43 -> 250780 | I10: =I43 -> 0 | J10: =J43 -> 0 | K10: =K43 -> 0 | L10: =L43 -> 0
B11: 4. Development & structuring costs | C11: € | D11: =SUM(E11:L11) -> 334147.18 | E11: =E47 -> 0 | F11: =F47 -> 334147.18 | G11: =G47 -> 0 | H11: =H47 -> 0 | I11: =I47 -> 0 | J11: =J47 -> 0 | K11: =K47 -> 0 | L11: =L47 -> 0
B12: 5. Reserves (working capital, DSRA/MMR, contingency) | C12: € | D12: =SUM(E12:L12) -> 544658.36 | E12: =E51 -> 0 | F12: =F51 -> 544658.36 | G12: =G51 -> 0 | H12: =H51 -> 0 | I12: =I51 -> 0 | J12: =J51 -> 0 | K12: =K51 -> 0 | L12: =L51 -> 0
B13: TOTAL USES | C13: € | D13: =SUM(D8:D12) -> 7650852.4 | E13: =SUM(E8:E12) -> 628000 | F13: =SUM(F8:F12) -> 5161592.4 | G13: =SUM(G8:G12) -> 930630 | H13: =SUM(H8:H12) -> 930630 | I13: =SUM(I8:I12) -> 0 | J13: =SUM(J8:J12) -> 0 | K13: =SUM(K8:K12) -> 0 | L13: =SUM(L8:L12) -> 0
B15: CAPITAL STACK | C15: €
B16: 1. Equity — sponsor cash + in-kind (mostly land + herd) | C16: € | D16: =SUM(E16:L16) -> 761078.27 | E16: =E59 -> 0 | F16: =F59 -> 761078.27 | G16: =G59 -> 0 | H16: =H59 -> 0 | I16: =I59 -> 0 | J16: =J59 -> 0 | K16: =K59 -> 0 | L16: =L59 -> 0
B17: 2. Debt — senior + junior | C17: € | D17: =SUM(E17:L17) -> 2864313.1 | E17: =E64 -> 0 | F17: =F64 -> 2864313.1 | G17: =G64 -> 0 | H17: =H64 -> 0 | I17: =I64 -> 0 | J17: =J64 -> 0 | K17: =K64 -> 0 | L17: =L64 -> 0
B18: 3. Grants & concessional | C18: € | D18: =SUM(E18:L18) -> 4025461 | E18: =E73 -> 628000 | F18: =F73 -> 1536201 | G18: =G73 -> 930630 | H18: =H73 -> 930630 | I18: =I73 -> 0 | J18: =J73 -> 0 | K18: =K73 -> 0 | L18: =L73 -> 0
B19: 4. Working-capital facility | C19: € | D19: =SUM(E19:L19) -> 0 | E19: =E77 -> 0 | F19: =F77 -> 0 | G19: =G77 -> 0 | H19: =H77 -> 0 | I19: =I77 -> 0 | J19: =J77 -> 0 | K19: =K77 -> 0 | L19: =L77 -> 0
B20: 5. Funding gap (over-/under-) | C20: € | D20: =SUM(E20:L20) -> 0 | E20: =E81 -> 0 | F20: =F81 -> 0 | G20: =G81 -> 0 | H20: =H81 -> 0 | I20: =I81 -> 0 | J20: =J81 -> 0 | K20: =K81 -> 0 | L20: =L81 -> 0
B21: TOTAL SOURCES | C21: € | D21: =SUM(D16:D20) -> 7650852.4 | E21: =SUM(E16:E20) -> 628000 | F21: =SUM(F16:F20) -> 5161592.4 | G21: =SUM(G16:G20) -> 930630 | H21: =SUM(H16:H20) -> 930630 | I21: =SUM(I16:I20) -> 0 | J21: =SUM(J16:J20) -> 0 | K21: =SUM(K16:K20) -> 0 | L21: =SUM(L16:L20) -> 0
B25: Balance check (sources − uses, should = €0) | C25: € | D25: =SUM(E25:L25) -> 0 | E25: =E82-E52 -> 0 | F25: =F82-F52 -> 0 | G25: =G82-G52 -> 0 | H25: =H82-H52 -> 0 | I25: =I82-I52 -> 0 | J25: =J82-J52 -> 0 | K25: =K82-K52 -> 0 | L25: =L82-L52 -> 0
B27: Uses by purpose — detail
B28: Productive assets — three farms
B29: Hard physical CAPEX (land development, buildings, equipment) | C29: € | D29: =SUM(E29:L29) -> 2701585.8 | E29: =CAPEX_B1_YM1 -> 0 | F29: =CAPEX_B1_Y0 -> 2701585.8 | G29: =CAPEX_B1_Y1 -> 0 | H29: =CAPEX_B1_Y2 -> 0 | I29: =CAPEX_B1_Y3 -> 0 | J29: =CAPEX_B1_Y4 -> 0 | K29: =CAPEX_B1_Y5 -> 0 | L29: =CAPEX_B1_Y6 -> 0
B30: Cheptel embouche initial (apport en nature) | C30: € | D30: =SUM(E30:L30) -> 45000 | E30: =ASM_A01_N_FARMS*ASM_E10_N_BEEF_STOCK_PER_FARM*ASM_P14_COST_CALF_PURCHASE_EUR_HEAD*FLAG_CONSTRUCT_YM1 -> 0 | F30: =ASM_A01_N_FARMS*ASM_E10_N_BEEF_STOCK_PER_FARM*ASM_P14_COST_CALF_PURCHASE_EUR_HEAD*FLAG_CONSTRUCT_Y0 -> 45000 | G30: =ASM_A01_N_FARMS*ASM_E10_N_BEEF_STOCK_PER_FARM*ASM_P14_COST_CALF_PURCHASE_EUR_HEAD*FLAG_CONSTRUCT_Y1 -> 0 | H30: =ASM_A01_N_FARMS*ASM_E10_N_BEEF_STOCK_PER_FARM*ASM_P14_COST_CALF_PURCHASE_EUR_HEAD*FLAG_CONSTRUCT_Y2 -> 0 | I30: =ASM_A01_N_FARMS*ASM_E10_N_BEEF_STOCK_PER_FARM*ASM_P14_COST_CALF_PURCHASE_EUR_HEAD*FLAG_CONSTRUCT_Y3 -> 0 | J30: =ASM_A01_N_FARMS*ASM_E10_N_BEEF_STOCK_PER_FARM*ASM_P14_COST_CALF_PURCHASE_EUR_HEAD*FLAG_CONSTRUCT_Y4 -> 0 | K30: =ASM_A01_N_FARMS*ASM_E10_N_BEEF_STOCK_PER_FARM*ASM_P14_COST_CALF_PURCHASE_EUR_HEAD*FLAG_CONSTRUCT_Y5 -> 0 | L30: =ASM_A01_N_FARMS*ASM_E10_N_BEEF_STOCK_PER_FARM*ASM_P14_COST_CALF_PURCHASE_EUR_HEAD*FLAG_CONSTRUCT_Y6 -> 0
B31: Subtotal — Productive assets | C31: € | D31: =SUM(D29:D30) -> 2746585.8 | E31: =SUM(E29:E30) -> 0 | F31: =SUM(F29:F30) -> 2746585.8 | G31: =SUM(G29:G30) -> 0 | H31: =SUM(H29:H30) -> 0 | I31: =SUM(I29:I30) -> 0 | J31: =SUM(J29:J30) -> 0 | K31: =SUM(K29:K30) -> 0 | L31: =SUM(L29:L30) -> 0
B33: Workforce build-up
B34: Training infrastructure (curriculum, ToT, classroom) | C34: € | D34: =SUM(E34:L34) -> 1488000 | E34: =CAPEX_B2_YM1 -> 628000 | F34: =CAPEX_B2_Y0 -> 860000 | G34: =CAPEX_B2_Y1 -> 0 | H34: =CAPEX_B2_Y2 -> 0 | I34: =CAPEX_B2_Y3 -> 0 | J34: =CAPEX_B2_Y4 -> 0 | K34: =CAPEX_B2_Y5 -> 0 | L34: =CAPEX_B2_Y6 -> 0
B35: Recurring training (Y1+Y2 stipends + trainers) | C35: € | D35: =SUM(E35:L35) -> 1359700 | E35: =TRAIN_REC_TOTAL_YM1 -> 0 | F35: =TRAIN_REC_TOTAL_Y0 -> 0 | G35: =TRAIN_REC_TOTAL_Y1 -> 679850 | H35: =TRAIN_REC_TOTAL_Y2 -> 679850 | I35: =TRAIN_REC_TOTAL_Y3 -> 0 | J35: =TRAIN_REC_TOTAL_Y4 -> 0 | K35: =TRAIN_REC_TOTAL_Y5 -> 0 | L35: =TRAIN_REC_TOTAL_Y6 -> 0
B36: Subtotal — Workforce build-up | C36: € | D36: =SUM(D34:D35) -> 2847700 | E36: =SUM(E34:E35) -> 628000 | F36: =SUM(F34:F35) -> 860000 | G36: =SUM(G34:G35) -> 679850 | H36: =SUM(H34:H35) -> 679850 | I36: =SUM(I34:I35) -> 0 | J36: =SUM(J34:J35) -> 0 | K36: =SUM(K34:K35) -> 0 | L36: =SUM(L34:L35) -> 0
B38: Genetics platform — animal + plant
B39: Animal genetics — hardware (vet centre, equipment) | C39: € | D39: =SUM(E39:L39) -> 298401 | E39: =CAPEX_B3A_YM1 -> 0 | F39: =CAPEX_B3A_Y0 -> 298401 | G39: =CAPEX_B3A_Y1 -> 0 | H39: =CAPEX_B3A_Y2 -> 0 | I39: =CAPEX_B3A_Y3 -> 0 | J39: =CAPEX_B3A_Y4 -> 0 | K39: =CAPEX_B3A_Y5 -> 0 | L39: =CAPEX_B3A_Y6 -> 0
B40: Animal genetics — operations (pre-op Y0 + recurring Y1+Y2) | C40: € | D40: =SUM(E40:L40) -> 388360 | E40: =GEN_A_OPEX_TOTAL_YM1 -> 0 | F40: =GEN_A_OPEX_TOTAL_Y0 -> 104800 | G40: =GEN_A_OPEX_TOTAL_Y1 -> 141780 | H40: =GEN_A_OPEX_TOTAL_Y2 -> 141780 | I40: =GEN_A_OPEX_TOTAL_Y3 -> 0 | J40: =GEN_A_OPEX_TOTAL_Y4 -> 0 | K40: =GEN_A_OPEX_TOTAL_Y5 -> 0 | L40: =GEN_A_OPEX_TOTAL_Y6 -> 0
B41: Plant genetics — hardware (nursery, equipment) | C41: € | D41: =SUM(E41:L41) -> 200000 | E41: =CAPEX_B3B_YM1 -> 0 | F41: =CAPEX_B3B_Y0 -> 200000 | G41: =CAPEX_B3B_Y1 -> 0 | H41: =CAPEX_B3B_Y2 -> 0 | I41: =CAPEX_B3B_Y3 -> 0 | J41: =CAPEX_B3B_Y4 -> 0 | K41: =CAPEX_B3B_Y5 -> 0 | L41: =CAPEX_B3B_Y6 -> 0
B42: Plant genetics — operations (pre-op Y0 + recurring Y1+Y2) | C42: € | D42: =SUM(E42:L42) -> 291000 | E42: =GEN_B_OPEX_TOTAL_YM1 -> 0 | F42: =GEN_B_OPEX_TOTAL_Y0 -> 73000 | G42: =GEN_B_OPEX_TOTAL_Y1 -> 109000 | H42: =GEN_B_OPEX_TOTAL_Y2 -> 109000 | I42: =GEN_B_OPEX_TOTAL_Y3 -> 0 | J42: =GEN_B_OPEX_TOTAL_Y4 -> 0 | K42: =GEN_B_OPEX_TOTAL_Y5 -> 0 | L42: =GEN_B_OPEX_TOTAL_Y6 -> 0
B43: Subtotal — Genetics platform | C43: € | D43: =SUM(D39:D42) -> 1177761 | E43: =SUM(E39:E42) -> 0 | F43: =SUM(F39:F42) -> 676201 | G43: =SUM(G39:G42) -> 250780 | H43: =SUM(H39:H42) -> 250780 | I43: =SUM(I39:I42) -> 0 | J43: =SUM(J39:J42) -> 0 | K43: =SUM(K39:K42) -> 0 | L43: =SUM(L39:L42) -> 0
B45: Development & structuring
B46: Studies, advisory, legal, supervision | C46: € | D46: =SUM(E46:L46) -> 334147.18 | E46: =CAPEX_B4_YM1 -> 0 | F46: =CAPEX_B4_Y0 -> 334147.18 | G46: =CAPEX_B4_Y1 -> 0 | H46: =CAPEX_B4_Y2 -> 0 | I46: =CAPEX_B4_Y3 -> 0 | J46: =CAPEX_B4_Y4 -> 0 | K46: =CAPEX_B4_Y5 -> 0 | L46: =CAPEX_B4_Y6 -> 0
B47: Subtotal — Development & structuring | C47: € | D47: =SUM(D46) -> 334147.18 | E47: =SUM(E46) -> 0 | F47: =SUM(F46) -> 334147.18 | G47: =SUM(G46) -> 0 | H47: =SUM(H46) -> 0 | I47: =SUM(I46) -> 0 | J47: =SUM(J46) -> 0 | K47: =SUM(K46) -> 0 | L47: =SUM(L46) -> 0
B49: Reserves & contingency
B50: Working capital buffer + contingency | C50: € | D50: =SUM(E50:L50) -> 544658.36 | E50: =CAPEX_B5_YM1 -> 0 | F50: =CAPEX_B5_Y0 -> 544658.36 | G50: =CAPEX_B5_Y1 -> 0 | H50: =CAPEX_B5_Y2 -> 0 | I50: =CAPEX_B5_Y3 -> 0 | J50: =CAPEX_B5_Y4 -> 0 | K50: =CAPEX_B5_Y5 -> 0 | L50: =CAPEX_B5_Y6 -> 0
B51: Subtotal — Reserves & contingency | C51: € | D51: =SUM(D50) -> 544658.36 | E51: =SUM(E50) -> 0 | F51: =SUM(F50) -> 544658.36 | G51: =SUM(G50) -> 0 | H51: =SUM(H50) -> 0 | I51: =SUM(I50) -> 0 | J51: =SUM(J50) -> 0 | K51: =SUM(K50) -> 0 | L51: =SUM(L50) -> 0
B52: TOTAL USES | C52: € | D52: =D31+D36+D43+D47+D51 -> 7650852.4 | E52: =E31+E36+E43+E47+E51 -> 628000 | F52: =F31+F36+F43+F47+F51 -> 5161592.4 | G52: =G31+G36+G43+G47+G51 -> 930630 | H52: =H31+H36+H43+H47+H51 -> 930630 | I52: =I31+I36+I43+I47+I51 -> 0 | J52: =J31+J36+J43+J47+J51 -> 0 | K52: =K31+K36+K43+K47+K51 -> 0 | L52: =L31+L36+L43+L47+L51 -> 0
B54: Capital stack — detail
B55: Equity
B56: Sponsor cash equity (Y0) | C56: € | D56: =SUM(E56:L56) -> 62623.727 | E56: =E$103*FLAG_CONSTRUCT_YM1 -> 0 | F56: =F$103*FLAG_CONSTRUCT_Y0 -> 62623.727 | G56: =G$103*FLAG_CONSTRUCT_Y1 -> 0 | H56: =H$103*FLAG_CONSTRUCT_Y2 -> 0 | I56: =I$103*FLAG_CONSTRUCT_Y3 -> 0 | J56: =J$103*FLAG_CONSTRUCT_Y4 -> 0 | K56: =K$103*FLAG_CONSTRUCT_Y5 -> 0 | L56: =L$103*FLAG_CONSTRUCT_Y6 -> 0
B57: In-kind equity (land usufruct + dairy herd, Y0) | C57: € | D57: =SUM(E57:L57) -> 653454.55 | E57: =(E$101+E$102)*FLAG_CONSTRUCT_YM1 -> 0 | F57: =(F$101+F$102)*FLAG_CONSTRUCT_Y0 -> 653454.55 | G57: =(G$101+G$102)*FLAG_CONSTRUCT_Y1 -> 0 | H57: =(H$101+H$102)*FLAG_CONSTRUCT_Y2 -> 0 | I57: =(I$101+I$102)*FLAG_CONSTRUCT_Y3 -> 0 | J57: =(J$101+J$102)*FLAG_CONSTRUCT_Y4 -> 0 | K57: =(K$101+K$102)*FLAG_CONSTRUCT_Y5 -> 0 | L57: =(L$101+L$102)*FLAG_CONSTRUCT_Y6 -> 0
B58: Equity — in-kind: cheptel embouche (promoteur) | C58: € | D58: =SUM(E58:L58) -> 45000 | E58: =ASM_A01_N_FARMS*ASM_E10_N_BEEF_STOCK_PER_FARM*ASM_P14_COST_CALF_PURCHASE_EUR_HEAD*FLAG_CONSTRUCT_YM1 -> 0 | F58: =ASM_A01_N_FARMS*ASM_E10_N_BEEF_STOCK_PER_FARM*ASM_P14_COST_CALF_PURCHASE_EUR_HEAD*FLAG_CONSTRUCT_Y0 -> 45000 | G58: =ASM_A01_N_FARMS*ASM_E10_N_BEEF_STOCK_PER_FARM*ASM_P14_COST_CALF_PURCHASE_EUR_HEAD*FLAG_CONSTRUCT_Y1 -> 0 | H58: =ASM_A01_N_FARMS*ASM_E10_N_BEEF_STOCK_PER_FARM*ASM_P14_COST_CALF_PURCHASE_EUR_HEAD*FLAG_CONSTRUCT_Y2 -> 0 | I58: =ASM_A01_N_FARMS*ASM_E10_N_BEEF_STOCK_PER_FARM*ASM_P14_COST_CALF_PURCHASE_EUR_HEAD*FLAG_CONSTRUCT_Y3 -> 0 | J58: =ASM_A01_N_FARMS*ASM_E10_N_BEEF_STOCK_PER_FARM*ASM_P14_COST_CALF_PURCHASE_EUR_HEAD*FLAG_CONSTRUCT_Y4 -> 0 | K58: =ASM_A01_N_FARMS*ASM_E10_N_BEEF_STOCK_PER_FARM*ASM_P14_COST_CALF_PURCHASE_EUR_HEAD*FLAG_CONSTRUCT_Y5 -> 0 | L58: =ASM_A01_N_FARMS*ASM_E10_N_BEEF_STOCK_PER_FARM*ASM_P14_COST_CALF_PURCHASE_EUR_HEAD*FLAG_CONSTRUCT_Y6 -> 0
B59: Subtotal — Equity | C59: € | D59: =SUM(D56:D58) -> 761078.27 | E59: =SUM(E56:E58) -> 0 | F59: =SUM(F56:F58) -> 761078.27 | G59: =SUM(G56:G58) -> 0 | H59: =SUM(H56:H58) -> 0 | I59: =SUM(I56:I58) -> 0 | J59: =SUM(J56:J58) -> 0 | K59: =SUM(K56:K58) -> 0 | L59: =SUM(L56:L58) -> 0
B61: Debt
B62: Senior debt | C62: € | D62: =SUM(E62:L62) -> 2363058.3 | E62: =E$99*FLAG_CONSTRUCT_YM1 -> 0 | F62: =F$99*FLAG_CONSTRUCT_Y0 -> 2363058.3 | G62: =G$99*FLAG_CONSTRUCT_Y1 -> 0 | H62: =H$99*FLAG_CONSTRUCT_Y2 -> 0 | I62: =I$99*FLAG_CONSTRUCT_Y3 -> 0 | J62: =J$99*FLAG_CONSTRUCT_Y4 -> 0 | K62: =K$99*FLAG_CONSTRUCT_Y5 -> 0 | L62: =L$99*FLAG_CONSTRUCT_Y6 -> 0
B63: Junior debt | C63: € | D63: =SUM(E63:L63) -> 501254.79 | E63: =E$100*FLAG_CONSTRUCT_YM1 -> 0 | F63: =F$100*FLAG_CONSTRUCT_Y0 -> 501254.79 | G63: =G$100*FLAG_CONSTRUCT_Y1 -> 0 | H63: =H$100*FLAG_CONSTRUCT_Y2 -> 0 | I63: =I$100*FLAG_CONSTRUCT_Y3 -> 0 | J63: =J$100*FLAG_CONSTRUCT_Y4 -> 0 | K63: =K$100*FLAG_CONSTRUCT_Y5 -> 0 | L63: =L$100*FLAG_CONSTRUCT_Y6 -> 0
B64: Subtotal — Debt | C64: € | D64: =SUM(D62:D63) -> 2864313.1 | E64: =SUM(E62:E63) -> 0 | F64: =SUM(F62:F63) -> 2864313.1 | G64: =SUM(G62:G63) -> 0 | H64: =SUM(H62:H63) -> 0 | I64: =SUM(I62:I63) -> 0 | J64: =SUM(J62:J63) -> 0 | K64: =SUM(K62:K63) -> 0 | L64: =SUM(L62:L63) -> 0
B66: Grants & concessional
B67: Training infrastructure grant (Y-1 + Y0) | C67: € | D67: =SUM(E67:L67) -> 1488000 | E67: =TRAIN_CAP_TOTAL_YM1 -> 628000 | F67: =TRAIN_CAP_TOTAL_Y0 -> 860000 | G67: =TRAIN_CAP_TOTAL_Y1 -> 0 | H67: =TRAIN_CAP_TOTAL_Y2 -> 0 | I67: =TRAIN_CAP_TOTAL_Y3 -> 0 | J67: =TRAIN_CAP_TOTAL_Y4 -> 0 | K67: =TRAIN_CAP_TOTAL_Y5 -> 0 | L67: =TRAIN_CAP_TOTAL_Y6 -> 0
B68: Recurring training grant (Y1 + Y2) | C68: € | D68: =SUM(E68:L68) -> 1359700 | E68: =TRAIN_REC_TOTAL_YM1 -> 0 | F68: =TRAIN_REC_TOTAL_Y0 -> 0 | G68: =TRAIN_REC_TOTAL_Y1 -> 679850 | H68: =TRAIN_REC_TOTAL_Y2 -> 679850 | I68: =TRAIN_REC_TOTAL_Y3 -> 0 | J68: =TRAIN_REC_TOTAL_Y4 -> 0 | K68: =TRAIN_REC_TOTAL_Y5 -> 0 | L68: =TRAIN_REC_TOTAL_Y6 -> 0
B69: Animal-genetics hardware grant | C69: € | D69: =SUM(E69:L69) -> 298401 | E69: =GEN_A_CAP_TOTAL_YM1 -> 0 | F69: =GEN_A_CAP_TOTAL_Y0 -> 298401 | G69: =GEN_A_CAP_TOTAL_Y1 -> 0 | H69: =GEN_A_CAP_TOTAL_Y2 -> 0 | I69: =GEN_A_CAP_TOTAL_Y3 -> 0 | J69: =GEN_A_CAP_TOTAL_Y4 -> 0 | K69: =GEN_A_CAP_TOTAL_Y5 -> 0 | L69: =GEN_A_CAP_TOTAL_Y6 -> 0
B70: Animal-genetics operations grant | C70: € | D70: =SUM(E70:L70) -> 388360 | E70: =GEN_A_OPEX_TOTAL_YM1 -> 0 | F70: =GEN_A_OPEX_TOTAL_Y0 -> 104800 | G70: =GEN_A_OPEX_TOTAL_Y1 -> 141780 | H70: =GEN_A_OPEX_TOTAL_Y2 -> 141780 | I70: =GEN_A_OPEX_TOTAL_Y3 -> 0 | J70: =GEN_A_OPEX_TOTAL_Y4 -> 0 | K70: =GEN_A_OPEX_TOTAL_Y5 -> 0 | L70: =GEN_A_OPEX_TOTAL_Y6 -> 0
B71: Plant-genetics hardware grant | C71: € | D71: =SUM(E71:L71) -> 200000 | E71: =GEN_B_CAP_TOTAL_YM1 -> 0 | F71: =GEN_B_CAP_TOTAL_Y0 -> 200000 | G71: =GEN_B_CAP_TOTAL_Y1 -> 0 | H71: =GEN_B_CAP_TOTAL_Y2 -> 0 | I71: =GEN_B_CAP_TOTAL_Y3 -> 0 | J71: =GEN_B_CAP_TOTAL_Y4 -> 0 | K71: =GEN_B_CAP_TOTAL_Y5 -> 0 | L71: =GEN_B_CAP_TOTAL_Y6 -> 0
B72: Plant-genetics operations grant | C72: € | D72: =SUM(E72:L72) -> 291000 | E72: =GEN_B_OPEX_TOTAL_YM1 -> 0 | F72: =GEN_B_OPEX_TOTAL_Y0 -> 73000 | G72: =GEN_B_OPEX_TOTAL_Y1 -> 109000 | H72: =GEN_B_OPEX_TOTAL_Y2 -> 109000 | I72: =GEN_B_OPEX_TOTAL_Y3 -> 0 | J72: =GEN_B_OPEX_TOTAL_Y4 -> 0 | K72: =GEN_B_OPEX_TOTAL_Y5 -> 0 | L72: =GEN_B_OPEX_TOTAL_Y6 -> 0
B73: Subtotal — Grants & concessional | C73: € | D73: =SUM(D67:D72) -> 4025461 | E73: =SUM(E67:E72) -> 628000 | F73: =SUM(F67:F72) -> 1536201 | G73: =SUM(G67:G72) -> 930630 | H73: =SUM(H67:H72) -> 930630 | I73: =SUM(I67:I72) -> 0 | J73: =SUM(J67:J72) -> 0 | K73: =SUM(K67:K72) -> 0 | L73: =SUM(L67:L72) -> 0
B75: Working-capital facility
B76: Working-capital facility (post-COD, not yet sized) | C76: € | D76: =SUM(E76:L76) -> 0 | E76: =0 -> 0 | F76: =0 -> 0 | G76: =0 -> 0 | H76: =0 -> 0 | I76: =0 -> 0 | J76: =0 -> 0 | K76: =0 -> 0 | L76: =0 -> 0
B77: Subtotal — Working-capital facility | C77: € | D77: =SUM(D76) -> 0 | E77: =SUM(E76) -> 0 | F77: =SUM(F76) -> 0 | G77: =SUM(G76) -> 0 | H77: =SUM(H76) -> 0 | I77: =SUM(I76) -> 0 | J77: =SUM(J76) -> 0 | K77: =SUM(K76) -> 0 | L77: =SUM(L76) -> 0
B79: Funding gap
B80: Programme financing gap (balancing residual) | C80: € | D80: =SUM(E80:L80) -> 0 | E80: =E52-(E59+E64+E73+E77) -> 0 | F80: =F52-(F59+F64+F73+F77) -> 0 | G80: =G52-(G59+G64+G73+G77) -> 0 | H80: =H52-(H59+H64+H73+H77) -> 0 | I80: =I52-(I59+I64+I73+I77) -> 0 | J80: =J52-(J59+J64+J73+J77) -> 0 | K80: =K52-(K59+K64+K73+K77) -> 0 | L80: =L52-(L59+L64+L73+L77) -> 0
B81: Subtotal — Funding gap | C81: € | D81: =SUM(D80) -> 0 | E81: =SUM(E80) -> 0 | F81: =SUM(F80) -> 0 | G81: =SUM(G80) -> 0 | H81: =SUM(H80) -> 0 | I81: =SUM(I80) -> 0 | J81: =SUM(J80) -> 0 | K81: =SUM(K80) -> 0 | L81: =SUM(L80) -> 0
B82: TOTAL SOURCES | C82: € | D82: =D59+D64+D73+D77+D81 -> 7650852.4 | E82: =E59+E64+E73+E77+E81 -> 628000 | F82: =F59+F64+F73+F77+F81 -> 5161592.4 | G82: =G59+G64+G73+G77+G81 -> 930630 | H82: =H59+H64+H73+H77+H81 -> 930630 | I82: =I59+I64+I73+I77+I81 -> 0 | J82: =J59+J64+J73+J77+J81 -> 0 | K82: =K59+K64+K73+K77+K81 -> 0 | L82: =L59+L64+L73+L77+L81 -> 0
B84: BALANCE (sources − uses = 0 when fully funded)
B85: Balance / gap (cash funding needed) | C85: € | D85: =SUM(E85:L85) -> 0 | E85: =E82-E52 -> 0 | F85: =F82-F52 -> 0 | G85: =G82-G52 -> 0 | H85: =H82-H52 -> 0 | I85: =I82-I52 -> 0 | J85: =J82-J52 -> 0 | K85: =K82-K52 -> 0 | L85: =L82-L52 -> 0
B86: Check — balance = 0 when funded | C86: € | D86: =SUM(E86:L86) -> 0 | E86: =IF(ABS(E85)<1,0,1) -> 0 | F86: =IF(ABS(F85)<1,0,1) -> 0 | G86: =IF(ABS(G85)<1,0,1) -> 0 | H86: =IF(ABS(H85)<1,0,1) -> 0 | I86: =IF(ABS(I85)<1,0,1) -> 0 | J86: =IF(ABS(J85)<1,0,1) -> 0 | K86: =IF(ABS(K85)<1,0,1) -> 0 | L86: =IF(ABS(L85)<1,0,1) -> 0
B89: Inputs from Assumptions
B90: A01 — Number of farms | C90: farms | D90: =SUM(E90:L90) -> 24 | E90: =ASM_A01_N_FARMS -> 3 | F90: =ASM_A01_N_FARMS -> 3 | G90: =ASM_A01_N_FARMS -> 3 | H90: =ASM_A01_N_FARMS -> 3 | I90: =ASM_A01_N_FARMS -> 3 | J90: =ASM_A01_N_FARMS -> 3 | K90: =ASM_A01_N_FARMS -> 3 | L90: =ASM_A01_N_FARMS -> 3
B91: A08 — EUR/USD exchange rate | C91: EUR/USD | D91: =SUM(E91:L91) -> 8.8 | E91: =ASM_A08_EUR_USD -> 1.1 | F91: =ASM_A08_EUR_USD -> 1.1 | G91: =ASM_A08_EUR_USD -> 1.1 | H91: =ASM_A08_EUR_USD -> 1.1 | I91: =ASM_A08_EUR_USD -> 1.1 | J91: =ASM_A08_EUR_USD -> 1.1 | K91: =ASM_A08_EUR_USD -> 1.1 | L91: =ASM_A08_EUR_USD -> 1.1
B92: X14 — Senior debt share | C92: % | D92: =SUM(E92:L92) -> 5.28 | E92: =ASM_X14_SENIOR_DEBT_PCT -> 0.66 | F92: =ASM_X14_SENIOR_DEBT_PCT -> 0.66 | G92: =ASM_X14_SENIOR_DEBT_PCT -> 0.66 | H92: =ASM_X14_SENIOR_DEBT_PCT -> 0.66 | I92: =ASM_X14_SENIOR_DEBT_PCT -> 0.66 | J92: =ASM_X14_SENIOR_DEBT_PCT -> 0.66 | K92: =ASM_X14_SENIOR_DEBT_PCT -> 0.66 | L92: =ASM_X14_SENIOR_DEBT_PCT -> 0.66
B93: X15 — Junior debt share (L04b source) | C93: % | D93: =SUM(E93:L93) -> 1.12 | E93: =ASM_X15_JUNIOR_DEBT_PCT -> 0.14 | F93: =ASM_X15_JUNIOR_DEBT_PCT -> 0.14 | G93: =ASM_X15_JUNIOR_DEBT_PCT -> 0.14 | H93: =ASM_X15_JUNIOR_DEBT_PCT -> 0.14 | I93: =ASM_X15_JUNIOR_DEBT_PCT -> 0.14 | J93: =ASM_X15_JUNIOR_DEBT_PCT -> 0.14 | K93: =ASM_X15_JUNIOR_DEBT_PCT -> 0.14 | L93: =ASM_X15_JUNIOR_DEBT_PCT -> 0.14
B94: X21 — X21 — USD source — in-kind land | C94: USD | D94: =SUM(E94:L94) -> 3950400 | E94: =ASM_X21_DOLLAR_INKIND_TERRAIN -> 493800 | F94: =ASM_X21_DOLLAR_INKIND_TERRAIN -> 493800 | G94: =ASM_X21_DOLLAR_INKIND_TERRAIN -> 493800 | H94: =ASM_X21_DOLLAR_INKIND_TERRAIN -> 493800 | I94: =ASM_X21_DOLLAR_INKIND_TERRAIN -> 493800 | J94: =ASM_X21_DOLLAR_INKIND_TERRAIN -> 493800 | K94: =ASM_X21_DOLLAR_INKIND_TERRAIN -> 493800 | L94: =ASM_X21_DOLLAR_INKIND_TERRAIN -> 493800
B95: X22 — X22 — USD source — in-kind herd | C95: USD | D95: =SUM(E95:L95) -> 1800000 | E95: =ASM_X22_DOLLAR_INKIND_HERD -> 225000 | F95: =ASM_X22_DOLLAR_INKIND_HERD -> 225000 | G95: =ASM_X22_DOLLAR_INKIND_HERD -> 225000 | H95: =ASM_X22_DOLLAR_INKIND_HERD -> 225000 | I95: =ASM_X22_DOLLAR_INKIND_HERD -> 225000 | J95: =ASM_X22_DOLLAR_INKIND_HERD -> 225000 | K95: =ASM_X22_DOLLAR_INKIND_HERD -> 225000 | L95: =ASM_X22_DOLLAR_INKIND_HERD -> 225000
B97: Calculated values
B98: farm_capex — farm_capex — Farm CAPEX TOTAL (sum across 8 periods) | C98: € | D98: =SUM(E98:L98) -> 28643131 | E98: =CAPEX_B1_YM1+CAPEX_B1_Y0+CAPEX_B1_Y1+CAPEX_B1_Y2+CAPEX_B1_Y3+CAPEX_B1_Y4+CAPEX_B1_Y5+CAPEX_B1_Y6+CAPEX_B4_YM1+CAPEX_B4_Y0+CAPEX_B4_Y1+CAPEX_B4_Y2+CAPEX_B4_Y3+CAPEX_B4_Y4+CAPEX_B4_Y5+CAPEX_B4_Y6+CAPEX_B5_YM1+CAPEX_B5_Y0+CAPEX_B5_Y1+CAPEX_B5_Y2+CAPEX_B5_Y3+CAPEX_B5_Y4+CAPEX_B5_Y5+CAPEX_B5_Y6 -> 3580391.4 | F98: =CAPEX_B1_YM1+CAPEX_B1_Y0+CAPEX_B1_Y1+CAPEX_B1_Y2+CAPEX_B1_Y3+CAPEX_B1_Y4+CAPEX_B1_Y5+CAPEX_B1_Y6+CAPEX_B4_YM1+CAPEX_B4_Y0+CAPEX_B4_Y1+CAPEX_B4_Y2+CAPEX_B4_Y3+CAPEX_B4_Y4+CAPEX_B4_Y5+CAPEX_B4_Y6+CAPEX_B5_YM1+CAPEX_B5_Y0+CAPEX_B5_Y1+CAPEX_B5_Y2+CAPEX_B5_Y3+CAPEX_B5_Y4+CAPEX_B5_Y5+CAPEX_B5_Y6 -> 3580391.4 | G98: =CAPEX_B1_YM1+CAPEX_B1_Y0+CAPEX_B1_Y1+CAPEX_B1_Y2+CAPEX_B1_Y3+CAPEX_B1_Y4+CAPEX_B1_Y5+CAPEX_B1_Y6+CAPEX_B4_YM1+CAPEX_B4_Y0+CAPEX_B4_Y1+CAPEX_B4_Y2+CAPEX_B4_Y3+CAPEX_B4_Y4+CAPEX_B4_Y5+CAPEX_B4_Y6+CAPEX_B5_YM1+CAPEX_B5_Y0+CAPEX_B5_Y1+CAPEX_B5_Y2+CAPEX_B5_Y3+CAPEX_B5_Y4+CAPEX_B5_Y5+CAPEX_B5_Y6 -> 3580391.4 | H98: =CAPEX_B1_YM1+CAPEX_B1_Y0+CAPEX_B1_Y1+CAPEX_B1_Y2+CAPEX_B1_Y3+CAPEX_B1_Y4+CAPEX_B1_Y5+CAPEX_B1_Y6+CAPEX_B4_YM1+CAPEX_B4_Y0+CAPEX_B4_Y1+CAPEX_B4_Y2+CAPEX_B4_Y3+CAPEX_B4_Y4+CAPEX_B4_Y5+CAPEX_B4_Y6+CAPEX_B5_YM1+CAPEX_B5_Y0+CAPEX_B5_Y1+CAPEX_B5_Y2+CAPEX_B5_Y3+CAPEX_B5_Y4+CAPEX_B5_Y5+CAPEX_B5_Y6 -> 3580391.4 | I98: =CAPEX_B1_YM1+CAPEX_B1_Y0+CAPEX_B1_Y1+CAPEX_B1_Y2+CAPEX_B1_Y3+CAPEX_B1_Y4+CAPEX_B1_Y5+CAPEX_B1_Y6+CAPEX_B4_YM1+CAPEX_B4_Y0+CAPEX_B4_Y1+CAPEX_B4_Y2+CAPEX_B4_Y3+CAPEX_B4_Y4+CAPEX_B4_Y5+CAPEX_B4_Y6+CAPEX_B5_YM1+CAPEX_B5_Y0+CAPEX_B5_Y1+CAPEX_B5_Y2+CAPEX_B5_Y3+CAPEX_B5_Y4+CAPEX_B5_Y5+CAPEX_B5_Y6 -> 3580391.4 | J98: =CAPEX_B1_YM1+CAPEX_B1_Y0+CAPEX_B1_Y1+CAPEX_B1_Y2+CAPEX_B1_Y3+CAPEX_B1_Y4+CAPEX_B1_Y5+CAPEX_B1_Y6+CAPEX_B4_YM1+CAPEX_B4_Y0+CAPEX_B4_Y1+CAPEX_B4_Y2+CAPEX_B4_Y3+CAPEX_B4_Y4+CAPEX_B4_Y5+CAPEX_B4_Y6+CAPEX_B5_YM1+CAPEX_B5_Y0+CAPEX_B5_Y1+CAPEX_B5_Y2+CAPEX_B5_Y3+CAPEX_B5_Y4+CAPEX_B5_Y5+CAPEX_B5_Y6 -> 3580391.4 | K98: =CAPEX_B1_YM1+CAPEX_B1_Y0+CAPEX_B1_Y1+CAPEX_B1_Y2+CAPEX_B1_Y3+CAPEX_B1_Y4+CAPEX_B1_Y5+CAPEX_B1_Y6+CAPEX_B4_YM1+CAPEX_B4_Y0+CAPEX_B4_Y1+CAPEX_B4_Y2+CAPEX_B4_Y3+CAPEX_B4_Y4+CAPEX_B4_Y5+CAPEX_B4_Y6+CAPEX_B5_YM1+CAPEX_B5_Y0+CAPEX_B5_Y1+CAPEX_B5_Y2+CAPEX_B5_Y3+CAPEX_B5_Y4+CAPEX_B5_Y5+CAPEX_B5_Y6 -> 3580391.4 | L98: =CAPEX_B1_YM1+CAPEX_B1_Y0+CAPEX_B1_Y1+CAPEX_B1_Y2+CAPEX_B1_Y3+CAPEX_B1_Y4+CAPEX_B1_Y5+CAPEX_B1_Y6+CAPEX_B4_YM1+CAPEX_B4_Y0+CAPEX_B4_Y1+CAPEX_B4_Y2+CAPEX_B4_Y3+CAPEX_B4_Y4+CAPEX_B4_Y5+CAPEX_B4_Y6+CAPEX_B5_YM1+CAPEX_B5_Y0+CAPEX_B5_Y1+CAPEX_B5_Y2+CAPEX_B5_Y3+CAPEX_B5_Y4+CAPEX_B5_Y5+CAPEX_B5_Y6 -> 3580391.4
B99: L04 — Senior debt T1 | C99: € | D99: =SUM(E99:L99) -> 18904466 | E99: =E$92*E$98 -> 2363058.3 | F99: =F$92*F$98 -> 2363058.3 | G99: =G$92*G$98 -> 2363058.3 | H99: =H$92*H$98 -> 2363058.3 | I99: =I$92*I$98 -> 2363058.3 | J99: =J$92*J$98 -> 2363058.3 | K99: =K$92*K$98 -> 2363058.3 | L99: =L$92*L$98 -> 2363058.3
B100: L04b — Junior debt T2 | C100: € | D100: =SUM(E100:L100) -> 4010038.3 | E100: =E$93*E$98 -> 501254.79 | F100: =F$93*F$98 -> 501254.79 | G100: =G$93*G$98 -> 501254.79 | H100: =H$93*H$98 -> 501254.79 | I100: =I$93*I$98 -> 501254.79 | J100: =J$93*J$98 -> 501254.79 | K100: =K$93*K$98 -> 501254.79 | L100: =L$93*L$98 -> 501254.79
B101: L07 — L07 — Equity in-kind land | C101: € | D101: =SUM(E101:L101) -> 3591272.7 | E101: =E$94/E$91 -> 448909.09 | F101: =F$94/F$91 -> 448909.09 | G101: =G$94/G$91 -> 448909.09 | H101: =H$94/H$91 -> 448909.09 | I101: =I$94/I$91 -> 448909.09 | J101: =J$94/J$91 -> 448909.09 | K101: =K$94/K$91 -> 448909.09 | L101: =L$94/L$91 -> 448909.09
B102: L08 — L08 — Equity in-kind herd | C102: € | D102: =SUM(E102:L102) -> 1636363.6 | E102: =E$95/E$91 -> 204545.45 | F102: =F$95/F$91 -> 204545.45 | G102: =G$95/G$91 -> 204545.45 | H102: =H$95/H$91 -> 204545.45 | I102: =I$95/I$91 -> 204545.45 | J102: =J$95/J$91 -> 204545.45 | K102: =K$95/K$91 -> 204545.45 | L102: =L$95/L$91 -> 204545.45
B103: L06 — Sponsor cash equity = (1−X14−X15) × farm_capex_total − L07 − L08 | C103: € | D103: =SUM(E103:L103) -> 500989.82 | E103: =(1-E$92-E$93)*E$98-E$101-E$102 -> 62623.727 | F103: =(1-F$92-F$93)*F$98-F$101-F$102 -> 62623.727 | G103: =(1-G$92-G$93)*G$98-G$101-G$102 -> 62623.727 | H103: =(1-H$92-H$93)*H$98-H$101-H$102 -> 62623.727 | I103: =(1-I$92-I$93)*I$98-I$101-I$102 -> 62623.727 | J103: =(1-J$92-J$93)*J$98-J$101-J$102 -> 62623.727 | K103: =(1-K$92-K$93)*K$98-K$101-K$102 -> 62623.727 | L103: =(1-L$92-L$93)*L$98-L$101-L$102 -> 62623.727
B104: L05 — L05 — Grant envelope FULL (TRAIN + GENETICS, summed) | C104: € | D104: =SUM(E104:L104) -> 32203688 | E104: =TRAIN_CAP_TOTAL_YM1+TRAIN_CAP_TOTAL_Y0+TRAIN_CAP_TOTAL_Y1+TRAIN_CAP_TOTAL_Y2+TRAIN_CAP_TOTAL_Y3+TRAIN_CAP_TOTAL_Y4+TRAIN_CAP_TOTAL_Y5+TRAIN_CAP_TOTAL_Y6+TRAIN_REC_TOTAL_YM1+TRAIN_REC_TOTAL_Y0+TRAIN_REC_TOTAL_Y1+TRAIN_REC_TOTAL_Y2+TRAIN_REC_TOTAL_Y3+TRAIN_REC_TOTAL_Y4+TRAIN_REC_TOTAL_Y5+TRAIN_REC_TOTAL_Y6+GEN_A_CAP_TOTAL_YM1+GEN_A_CAP_TOTAL_Y0+GEN_A_CAP_TOTAL_Y1+GEN_A_CAP_TOTAL_Y2+GEN_A_CAP_TOTAL_Y3+GEN_A_CAP_TOTAL_Y4+GEN_A_CAP_TOTAL_Y5+GEN_A_CAP_TOTAL_Y6+GEN_A_OPEX_TOTAL_YM1+GEN_A_OPEX_TOTAL_Y0+GEN_A_OPEX_TOTAL_Y1+GEN_A_OPEX_TOTAL_Y2+GEN_A_OPEX_TOTAL_Y3+GEN_A_OPEX_TOTAL_Y4+GEN_A_OPEX_TOTAL_Y5+GEN_A_OPEX_TOTAL_Y6+GEN_B_CAP_TOTAL_YM1+GEN_B_CAP_TOTAL_Y0+GEN_B_CAP_TOTAL_Y1+GEN_B_CAP_TOTAL_Y2+GEN_B_CAP_TOTAL_Y3+GEN_B_CAP_TOTAL_Y4+GEN_B_CAP_TOTAL_Y5+GEN_B_CAP_TOTAL_Y6+GEN_B_OPEX_TOTAL_YM1+GEN_B_OPEX_TOTAL_Y0+GEN_B_OPEX_TOTAL_Y1+GEN_B_OPEX_TOTAL_Y2+GEN_B_OPEX_TOTAL_Y3+GEN_B_OPEX_TOTAL_Y4+GEN_B_OPEX_TOTAL_Y5+GEN_B_OPEX_TOTAL_Y6 -> 4025461 | F104: =TRAIN_CAP_TOTAL_YM1+TRAIN_CAP_TOTAL_Y0+TRAIN_CAP_TOTAL_Y1+TRAIN_CAP_TOTAL_Y2+TRAIN_CAP_TOTAL_Y3+TRAIN_CAP_TOTAL_Y4+TRAIN_CAP_TOTAL_Y5+TRAIN_CAP_TOTAL_Y6+TRAIN_REC_TOTAL_YM1+TRAIN_REC_TOTAL_Y0+TRAIN_REC_TOTAL_Y1+TRAIN_REC_TOTAL_Y2+TRAIN_REC_TOTAL_Y3+TRAIN_REC_TOTAL_Y4+TRAIN_REC_TOTAL_Y5+TRAIN_REC_TOTAL_Y6+GEN_A_CAP_TOTAL_YM1+GEN_A_CAP_TOTAL_Y0+GEN_A_CAP_TOTAL_Y1+GEN_A_CAP_TOTAL_Y2+GEN_A_CAP_TOTAL_Y3+GEN_A_CAP_TOTAL_Y4+GEN_A_CAP_TOTAL_Y5+GEN_A_CAP_TOTAL_Y6+GEN_A_OPEX_TOTAL_YM1+GEN_A_OPEX_TOTAL_Y0+GEN_A_OPEX_TOTAL_Y1+GEN_A_OPEX_TOTAL_Y2+GEN_A_OPEX_TOTAL_Y3+GEN_A_OPEX_TOTAL_Y4+GEN_A_OPEX_TOTAL_Y5+GEN_A_OPEX_TOTAL_Y6+GEN_B_CAP_TOTAL_YM1+GEN_B_CAP_TOTAL_Y0+GEN_B_CAP_TOTAL_Y1+GEN_B_CAP_TOTAL_Y2+GEN_B_CAP_TOTAL_Y3+GEN_B_CAP_TOTAL_Y4+GEN_B_CAP_TOTAL_Y5+GEN_B_CAP_TOTAL_Y6+GEN_B_OPEX_TOTAL_YM1+GEN_B_OPEX_TOTAL_Y0+GEN_B_OPEX_TOTAL_Y1+GEN_B_OPEX_TOTAL_Y2+GEN_B_OPEX_TOTAL_Y3+GEN_B_OPEX_TOTAL_Y4+GEN_B_OPEX_TOTAL_Y5+GEN_B_OPEX_TOTAL_Y6 -> 4025461 | G104: =TRAIN_CAP_TOTAL_YM1+TRAIN_CAP_TOTAL_Y0+TRAIN_CAP_TOTAL_Y1+TRAIN_CAP_TOTAL_Y2+TRAIN_CAP_TOTAL_Y3+TRAIN_CAP_TOTAL_Y4+TRAIN_CAP_TOTAL_Y5+TRAIN_CAP_TOTAL_Y6+TRAIN_REC_TOTAL_YM1+TRAIN_REC_TOTAL_Y0+TRAIN_REC_TOTAL_Y1+TRAIN_REC_TOTAL_Y2+TRAIN_REC_TOTAL_Y3+TRAIN_REC_TOTAL_Y4+TRAIN_REC_TOTAL_Y5+TRAIN_REC_TOTAL_Y6+GEN_A_CAP_TOTAL_YM1+GEN_A_CAP_TOTAL_Y0+GEN_A_CAP_TOTAL_Y1+GEN_A_CAP_TOTAL_Y2+GEN_A_CAP_TOTAL_Y3+GEN_A_CAP_TOTAL_Y4+GEN_A_CAP_TOTAL_Y5+GEN_A_CAP_TOTAL_Y6+GEN_A_OPEX_TOTAL_YM1+GEN_A_OPEX_TOTAL_Y0+GEN_A_OPEX_TOTAL_Y1+GEN_A_OPEX_TOTAL_Y2+GEN_A_OPEX_TOTAL_Y3+GEN_A_OPEX_TOTAL_Y4+GEN_A_OPEX_TOTAL_Y5+GEN_A_OPEX_TOTAL_Y6+GEN_B_CAP_TOTAL_YM1+GEN_B_CAP_TOTAL_Y0+GEN_B_CAP_TOTAL_Y1+GEN_B_CAP_TOTAL_Y2+GEN_B_CAP_TOTAL_Y3+GEN_B_CAP_TOTAL_Y4+GEN_B_CAP_TOTAL_Y5+GEN_B_CAP_TOTAL_Y6+GEN_B_OPEX_TOTAL_YM1+GEN_B_OPEX_TOTAL_Y0+GEN_B_OPEX_TOTAL_Y1+GEN_B_OPEX_TOTAL_Y2+GEN_B_OPEX_TOTAL_Y3+GEN_B_OPEX_TOTAL_Y4+GEN_B_OPEX_TOTAL_Y5+GEN_B_OPEX_TOTAL_Y6 -> 4025461 | H104: =TRAIN_CAP_TOTAL_YM1+TRAIN_CAP_TOTAL_Y0+TRAIN_CAP_TOTAL_Y1+TRAIN_CAP_TOTAL_Y2+TRAIN_CAP_TOTAL_Y3+TRAIN_CAP_TOTAL_Y4+TRAIN_CAP_TOTAL_Y5+TRAIN_CAP_TOTAL_Y6+TRAIN_REC_TOTAL_YM1+TRAIN_REC_TOTAL_Y0+TRAIN_REC_TOTAL_Y1+TRAIN_REC_TOTAL_Y2+TRAIN_REC_TOTAL_Y3+TRAIN_REC_TOTAL_Y4+TRAIN_REC_TOTAL_Y5+TRAIN_REC_TOTAL_Y6+GEN_A_CAP_TOTAL_YM1+GEN_A_CAP_TOTAL_Y0+GEN_A_CAP_TOTAL_Y1+GEN_A_CAP_TOTAL_Y2+GEN_A_CAP_TOTAL_Y3+GEN_A_CAP_TOTAL_Y4+GEN_A_CAP_TOTAL_Y5+GEN_A_CAP_TOTAL_Y6+GEN_A_OPEX_TOTAL_YM1+GEN_A_OPEX_TOTAL_Y0+GEN_A_OPEX_TOTAL_Y1+GEN_A_OPEX_TOTAL_Y2+GEN_A_OPEX_TOTAL_Y3+GEN_A_OPEX_TOTAL_Y4+GEN_A_OPEX_TOTAL_Y5+GEN_A_OPEX_TOTAL_Y6+GEN_B_CAP_TOTAL_YM1+GEN_B_CAP_TOTAL_Y0+GEN_B_CAP_TOTAL_Y1+GEN_B_CAP_TOTAL_Y2+GEN_B_CAP_TOTAL_Y3+GEN_B_CAP_TOTAL_Y4+GEN_B_CAP_TOTAL_Y5+GEN_B_CAP_TOTAL_Y6+GEN_B_OPEX_TOTAL_YM1+GEN_B_OPEX_TOTAL_Y0+GEN_B_OPEX_TOTAL_Y1+GEN_B_OPEX_TOTAL_Y2+GEN_B_OPEX_TOTAL_Y3+GEN_B_OPEX_TOTAL_Y4+GEN_B_OPEX_TOTAL_Y5+GEN_B_OPEX_TOTAL_Y6 -> 4025461 | I104: =TRAIN_CAP_TOTAL_YM1+TRAIN_CAP_TOTAL_Y0+TRAIN_CAP_TOTAL_Y1+TRAIN_CAP_TOTAL_Y2+TRAIN_CAP_TOTAL_Y3+TRAIN_CAP_TOTAL_Y4+TRAIN_CAP_TOTAL_Y5+TRAIN_CAP_TOTAL_Y6+TRAIN_REC_TOTAL_YM1+TRAIN_REC_TOTAL_Y0+TRAIN_REC_TOTAL_Y1+TRAIN_REC_TOTAL_Y2+TRAIN_REC_TOTAL_Y3+TRAIN_REC_TOTAL_Y4+TRAIN_REC_TOTAL_Y5+TRAIN_REC_TOTAL_Y6+GEN_A_CAP_TOTAL_YM1+GEN_A_CAP_TOTAL_Y0+GEN_A_CAP_TOTAL_Y1+GEN_A_CAP_TOTAL_Y2+GEN_A_CAP_TOTAL_Y3+GEN_A_CAP_TOTAL_Y4+GEN_A_CAP_TOTAL_Y5+GEN_A_CAP_TOTAL_Y6+GEN_A_OPEX_TOTAL_YM1+GEN_A_OPEX_TOTAL_Y0+GEN_A_OPEX_TOTAL_Y1+GEN_A_OPEX_TOTAL_Y2+GEN_A_OPEX_TOTAL_Y3+GEN_A_OPEX_TOTAL_Y4+GEN_A_OPEX_TOTAL_Y5+GEN_A_OPEX_TOTAL_Y6+GEN_B_CAP_TOTAL_YM1+GEN_B_CAP_TOTAL_Y0+GEN_B_CAP_TOTAL_Y1+GEN_B_CAP_TOTAL_Y2+GEN_B_CAP_TOTAL_Y3+GEN_B_CAP_TOTAL_Y4+GEN_B_CAP_TOTAL_Y5+GEN_B_CAP_TOTAL_Y6+GEN_B_OPEX_TOTAL_YM1+GEN_B_OPEX_TOTAL_Y0+GEN_B_OPEX_TOTAL_Y1+GEN_B_OPEX_TOTAL_Y2+GEN_B_OPEX_TOTAL_Y3+GEN_B_OPEX_TOTAL_Y4+GEN_B_OPEX_TOTAL_Y5+GEN_B_OPEX_TOTAL_Y6 -> 4025461 | J104: =TRAIN_CAP_TOTAL_YM1+TRAIN_CAP_TOTAL_Y0+TRAIN_CAP_TOTAL_Y1+TRAIN_CAP_TOTAL_Y2+TRAIN_CAP_TOTAL_Y3+TRAIN_CAP_TOTAL_Y4+TRAIN_CAP_TOTAL_Y5+TRAIN_CAP_TOTAL_Y6+TRAIN_REC_TOTAL_YM1+TRAIN_REC_TOTAL_Y0+TRAIN_REC_TOTAL_Y1+TRAIN_REC_TOTAL_Y2+TRAIN_REC_TOTAL_Y3+TRAIN_REC_TOTAL_Y4+TRAIN_REC_TOTAL_Y5+TRAIN_REC_TOTAL_Y6+GEN_A_CAP_TOTAL_YM1+GEN_A_CAP_TOTAL_Y0+GEN_A_CAP_TOTAL_Y1+GEN_A_CAP_TOTAL_Y2+GEN_A_CAP_TOTAL_Y3+GEN_A_CAP_TOTAL_Y4+GEN_A_CAP_TOTAL_Y5+GEN_A_CAP_TOTAL_Y6+GEN_A_OPEX_TOTAL_YM1+GEN_A_OPEX_TOTAL_Y0+GEN_A_OPEX_TOTAL_Y1+GEN_A_OPEX_TOTAL_Y2+GEN_A_OPEX_TOTAL_Y3+GEN_A_OPEX_TOTAL_Y4+GEN_A_OPEX_TOTAL_Y5+GEN_A_OPEX_TOTAL_Y6+GEN_B_CAP_TOTAL_YM1+GEN_B_CAP_TOTAL_Y0+GEN_B_CAP_TOTAL_Y1+GEN_B_CAP_TOTAL_Y2+GEN_B_CAP_TOTAL_Y3+GEN_B_CAP_TOTAL_Y4+GEN_B_CAP_TOTAL_Y5+GEN_B_CAP_TOTAL_Y6+GEN_B_OPEX_TOTAL_YM1+GEN_B_OPEX_TOTAL_Y0+GEN_B_OPEX_TOTAL_Y1+GEN_B_OPEX_TOTAL_Y2+GEN_B_OPEX_TOTAL_Y3+GEN_B_OPEX_TOTAL_Y4+GEN_B_OPEX_TOTAL_Y5+GEN_B_OPEX_TOTAL_Y6 -> 4025461 | K104: =TRAIN_CAP_TOTAL_YM1+TRAIN_CAP_TOTAL_Y0+TRAIN_CAP_TOTAL_Y1+TRAIN_CAP_TOTAL_Y2+TRAIN_CAP_TOTAL_Y3+TRAIN_CAP_TOTAL_Y4+TRAIN_CAP_TOTAL_Y5+TRAIN_CAP_TOTAL_Y6+TRAIN_REC_TOTAL_YM1+TRAIN_REC_TOTAL_Y0+TRAIN_REC_TOTAL_Y1+TRAIN_REC_TOTAL_Y2+TRAIN_REC_TOTAL_Y3+TRAIN_REC_TOTAL_Y4+TRAIN_REC_TOTAL_Y5+TRAIN_REC_TOTAL_Y6+GEN_A_CAP_TOTAL_YM1+GEN_A_CAP_TOTAL_Y0+GEN_A_CAP_TOTAL_Y1+GEN_A_CAP_TOTAL_Y2+GEN_A_CAP_TOTAL_Y3+GEN_A_CAP_TOTAL_Y4+GEN_A_CAP_TOTAL_Y5+GEN_A_CAP_TOTAL_Y6+GEN_A_OPEX_TOTAL_YM1+GEN_A_OPEX_TOTAL_Y0+GEN_A_OPEX_TOTAL_Y1+GEN_A_OPEX_TOTAL_Y2+GEN_A_OPEX_TOTAL_Y3+GEN_A_OPEX_TOTAL_Y4+GEN_A_OPEX_TOTAL_Y5+GEN_A_OPEX_TOTAL_Y6+GEN_B_CAP_TOTAL_YM1+GEN_B_CAP_TOTAL_Y0+GEN_B_CAP_TOTAL_Y1+GEN_B_CAP_TOTAL_Y2+GEN_B_CAP_TOTAL_Y3+GEN_B_CAP_TOTAL_Y4+GEN_B_CAP_TOTAL_Y5+GEN_B_CAP_TOTAL_Y6+GEN_B_OPEX_TOTAL_YM1+GEN_B_OPEX_TOTAL_Y0+GEN_B_OPEX_TOTAL_Y1+GEN_B_OPEX_TOTAL_Y2+GEN_B_OPEX_TOTAL_Y3+GEN_B_OPEX_TOTAL_Y4+GEN_B_OPEX_TOTAL_Y5+GEN_B_OPEX_TOTAL_Y6 -> 4025461 | L104: =TRAIN_CAP_TOTAL_YM1+TRAIN_CAP_TOTAL_Y0+TRAIN_CAP_TOTAL_Y1+TRAIN_CAP_TOTAL_Y2+TRAIN_CAP_TOTAL_Y3+TRAIN_CAP_TOTAL_Y4+TRAIN_CAP_TOTAL_Y5+TRAIN_CAP_TOTAL_Y6+TRAIN_REC_TOTAL_YM1+TRAIN_REC_TOTAL_Y0+TRAIN_REC_TOTAL_Y1+TRAIN_REC_TOTAL_Y2+TRAIN_REC_TOTAL_Y3+TRAIN_REC_TOTAL_Y4+TRAIN_REC_TOTAL_Y5+TRAIN_REC_TOTAL_Y6+GEN_A_CAP_TOTAL_YM1+GEN_A_CAP_TOTAL_Y0+GEN_A_CAP_TOTAL_Y1+GEN_A_CAP_TOTAL_Y2+GEN_A_CAP_TOTAL_Y3+GEN_A_CAP_TOTAL_Y4+GEN_A_CAP_TOTAL_Y5+GEN_A_CAP_TOTAL_Y6+GEN_A_OPEX_TOTAL_YM1+GEN_A_OPEX_TOTAL_Y0+GEN_A_OPEX_TOTAL_Y1+GEN_A_OPEX_TOTAL_Y2+GEN_A_OPEX_TOTAL_Y3+GEN_A_OPEX_TOTAL_Y4+GEN_A_OPEX_TOTAL_Y5+GEN_A_OPEX_TOTAL_Y6+GEN_B_CAP_TOTAL_YM1+GEN_B_CAP_TOTAL_Y0+GEN_B_CAP_TOTAL_Y1+GEN_B_CAP_TOTAL_Y2+GEN_B_CAP_TOTAL_Y3+GEN_B_CAP_TOTAL_Y4+GEN_B_CAP_TOTAL_Y5+GEN_B_CAP_TOTAL_Y6+GEN_B_OPEX_TOTAL_YM1+GEN_B_OPEX_TOTAL_Y0+GEN_B_OPEX_TOTAL_Y1+GEN_B_OPEX_TOTAL_Y2+GEN_B_OPEX_TOTAL_Y3+GEN_B_OPEX_TOTAL_Y4+GEN_B_OPEX_TOTAL_Y5+GEN_B_OPEX_TOTAL_Y6 -> 4025461

Sheet 07_Revenue
B1: 07 — Revenue [€]
D3: Total | E3: Y-1 | F3: Y0 | G3: Y1 | H3: Y2 | I3: Y3 | J3: Y4 | K3: Y5 | L3: Y6
E4: -1 | F4: 0 | G4: 1 | H4: 2 | I4: 3 | J4: 4 | K4: 5 | L4: 6
B6: Summary
B7: Farming revenue (dairy + beef + market garden + cereals) | C7: € | D7: =SUM(E7:L7) -> 8072640.5 | E7: =E17+E27+E35+E42 -> 0 | F7: =F17+F27+F35+F42 -> 0 | G7: =G17+G27+G35+G42 -> 627001.2 | H7: =H17+H27+H35+H42 -> 1175627.2 | I7: =I17+I27+I35+I42 -> 1567503 | J7: =J17+J27+J35+J42 -> 1567503 | K7: =K17+K27+K35+K42 -> 1567503 | L7: =L17+L27+L35+L42 -> 1567503
B8: Training revenue | C8: € | D8: =SUM(E8:L8) -> 0 | E8: =E45 -> 0 | F8: =F45 -> 0 | G8: =G45 -> 0 | H8: =H45 -> 0 | I8: =I45 -> 0 | J8: =J45 -> 0 | K8: =K45 -> 0 | L8: =L45 -> 0
B9: Genetics revenue | C9: € | D9: =SUM(E9:L9) -> 0 | E9: =E48 -> 0 | F9: =F48 -> 0 | G9: =G48 -> 0 | H9: =H48 -> 0 | I9: =I48 -> 0 | J9: =J48 -> 0 | K9: =K48 -> 0 | L9: =L48 -> 0
B10: TOTAL REVENUE | C10: € | D10: =SUM(D7:D9) -> 8072640.5 | E10: =SUM(E7:E9) -> 0 | F10: =SUM(F7:F9) -> 0 | G10: =SUM(G7:G9) -> 627001.2 | H10: =SUM(H7:H9) -> 1175627.2 | I10: =SUM(I7:I9) -> 1567503 | J10: =SUM(J7:J9) -> 1567503 | K10: =SUM(K7:K9) -> 1567503 | L10: =SUM(L7:L9) -> 1567503
B12: Dairy — milk chain
B13: Dairy herd (head) | C13: têtes | D13: =SUM(E13:L13) -> 720 | E13: =ASM_A01_N_FARMS*ASM_E08_N_COWS_DAIRY_PER_FARM -> 90 | F13: =ASM_A01_N_FARMS*ASM_E08_N_COWS_DAIRY_PER_FARM -> 90 | G13: =ASM_A01_N_FARMS*ASM_E08_N_COWS_DAIRY_PER_FARM -> 90 | H13: =ASM_A01_N_FARMS*ASM_E08_N_COWS_DAIRY_PER_FARM -> 90 | I13: =ASM_A01_N_FARMS*ASM_E08_N_COWS_DAIRY_PER_FARM -> 90 | J13: =ASM_A01_N_FARMS*ASM_E08_N_COWS_DAIRY_PER_FARM -> 90 | K13: =ASM_A01_N_FARMS*ASM_E08_N_COWS_DAIRY_PER_FARM -> 90 | L13: =ASM_A01_N_FARMS*ASM_E08_N_COWS_DAIRY_PER_FARM -> 90
B14: Yield per cow (L/head/yr) | C14: L/tête | D14: =SUM(E14:L14) -> 44800 | E14: =ASM_E09_YIELD_DAIRY_L_PER_COW -> 5600 | F14: =ASM_E09_YIELD_DAIRY_L_PER_COW -> 5600 | G14: =ASM_E09_YIELD_DAIRY_L_PER_COW -> 5600 | H14: =ASM_E09_YIELD_DAIRY_L_PER_COW -> 5600 | I14: =ASM_E09_YIELD_DAIRY_L_PER_COW -> 5600 | J14: =ASM_E09_YIELD_DAIRY_L_PER_COW -> 5600 | K14: =ASM_E09_YIELD_DAIRY_L_PER_COW -> 5600 | L14: =ASM_E09_YIELD_DAIRY_L_PER_COW -> 5600
B15: Volume produced (L/yr) | C15: L/an | D15: =SUM(E15:L15) -> 4032000 | E15: =E13*E14 -> 504000 | F15: =F13*F14 -> 504000 | G15: =G13*G14 -> 504000 | H15: =H13*H14 -> 504000 | I15: =I13*I14 -> 504000 | J15: =J13*J14 -> 504000 | K15: =K13*K14 -> 504000 | L15: =L13*L14 -> 504000
B16: Price (€/L) | C16: €/L | D16: =SUM(E16:L16) -> 2.8 | E16: =ASM_E16_PRICE_DAIRY_EUR_PER_L -> 0.35 | F16: =ASM_E16_PRICE_DAIRY_EUR_PER_L -> 0.35 | G16: =ASM_E16_PRICE_DAIRY_EUR_PER_L -> 0.35 | H16: =ASM_E16_PRICE_DAIRY_EUR_PER_L -> 0.35 | I16: =ASM_E16_PRICE_DAIRY_EUR_PER_L -> 0.35 | J16: =ASM_E16_PRICE_DAIRY_EUR_PER_L -> 0.35 | K16: =ASM_E16_PRICE_DAIRY_EUR_PER_L -> 0.35 | L16: =ASM_E16_PRICE_DAIRY_EUR_PER_L -> 0.35
B17: Dairy revenue (€/yr) | C17: €/an | D17: =SUM(E17:L17) -> 908460 | E17: =E15*E16*IF(E$4=ASM_A04_COD_YEAR,ASM_E20_RAMP_Y1_PCT,IF(E$4=ASM_A04_COD_YEAR+1,ASM_E21_RAMP_Y2_PCT,IF(E$4>ASM_A04_COD_YEAR+1,1,0))) -> 0 | F17: =F15*F16*IF(F$4=ASM_A04_COD_YEAR,ASM_E20_RAMP_Y1_PCT,IF(F$4=ASM_A04_COD_YEAR+1,ASM_E21_RAMP_Y2_PCT,IF(F$4>ASM_A04_COD_YEAR+1,1,0))) -> 0 | G17: =G15*G16*IF(G$4=ASM_A04_COD_YEAR,ASM_E20_RAMP_Y1_PCT,IF(G$4=ASM_A04_COD_YEAR+1,ASM_E21_RAMP_Y2_PCT,IF(G$4>ASM_A04_COD_YEAR+1,1,0))) -> 70560 | H17: =H15*H16*IF(H$4=ASM_A04_COD_YEAR,ASM_E20_RAMP_Y1_PCT,IF(H$4=ASM_A04_COD_YEAR+1,ASM_E21_RAMP_Y2_PCT,IF(H$4>ASM_A04_COD_YEAR+1,1,0))) -> 132300 | I17: =I15*I16*IF(I$4=ASM_A04_COD_YEAR,ASM_E20_RAMP_Y1_PCT,IF(I$4=ASM_A04_COD_YEAR+1,ASM_E21_RAMP_Y2_PCT,IF(I$4>ASM_A04_COD_YEAR+1,1,0))) -> 176400 | J17: =J15*J16*IF(J$4=ASM_A04_COD_YEAR,ASM_E20_RAMP_Y1_PCT,IF(J$4=ASM_A04_COD_YEAR+1,ASM_E21_RAMP_Y2_PCT,IF(J$4>ASM_A04_COD_YEAR+1,1,0))) -> 176400 | K17: =K15*K16*IF(K$4=ASM_A04_COD_YEAR,ASM_E20_RAMP_Y1_PCT,IF(K$4=ASM_A04_COD_YEAR+1,ASM_E21_RAMP_Y2_PCT,IF(K$4>ASM_A04_COD_YEAR+1,1,0))) -> 176400 | L17: =L15*L16*IF(L$4=ASM_A04_COD_YEAR,ASM_E20_RAMP_Y1_PCT,IF(L$4=ASM_A04_COD_YEAR+1,ASM_E21_RAMP_Y2_PCT,IF(L$4>ASM_A04_COD_YEAR+1,1,0))) -> 176400
B19: Beef — cow-calf chain
B20: Cow-calf herd (head) | C20: têtes | D20: =SUM(E20:L20) -> 1800 | E20: =ASM_A01_N_FARMS*ASM_E10_N_BEEF_STOCK_PER_FARM -> 225 | F20: =ASM_A01_N_FARMS*ASM_E10_N_BEEF_STOCK_PER_FARM -> 225 | G20: =ASM_A01_N_FARMS*ASM_E10_N_BEEF_STOCK_PER_FARM -> 225 | H20: =ASM_A01_N_FARMS*ASM_E10_N_BEEF_STOCK_PER_FARM -> 225 | I20: =ASM_A01_N_FARMS*ASM_E10_N_BEEF_STOCK_PER_FARM -> 225 | J20: =ASM_A01_N_FARMS*ASM_E10_N_BEEF_STOCK_PER_FARM -> 225 | K20: =ASM_A01_N_FARMS*ASM_E10_N_BEEF_STOCK_PER_FARM -> 225 | L20: =ASM_A01_N_FARMS*ASM_E10_N_BEEF_STOCK_PER_FARM -> 225
B21: Offtake rate | C21: %/an | D21: =SUM(E21:L21) -> 6.4 | E21: =ASM_E11_OFFTAKE_RATE_BEEF -> 0.8 | F21: =ASM_E11_OFFTAKE_RATE_BEEF -> 0.8 | G21: =ASM_E11_OFFTAKE_RATE_BEEF -> 0.8 | H21: =ASM_E11_OFFTAKE_RATE_BEEF -> 0.8 | I21: =ASM_E11_OFFTAKE_RATE_BEEF -> 0.8 | J21: =ASM_E11_OFFTAKE_RATE_BEEF -> 0.8 | K21: =ASM_E11_OFFTAKE_RATE_BEEF -> 0.8 | L21: =ASM_E11_OFFTAKE_RATE_BEEF -> 0.8
B22: Animals sold (head/yr) | C22: têtes | D22: =SUM(E22:L22) -> 1440 | E22: =E20*E21 -> 180 | F22: =F20*F21 -> 180 | G22: =G20*G21 -> 180 | H22: =H20*H21 -> 180 | I22: =I20*I21 -> 180 | J22: =J20*J21 -> 180 | K22: =K20*K21 -> 180 | L22: =L20*L21 -> 180
B23: Liveweight (kg/head) | C23: kg/tête | D23: =SUM(E23:L23) -> 2240 | E23: =ASM_E12_LIVEWEIGHT_BEEF_KG -> 280 | F23: =ASM_E12_LIVEWEIGHT_BEEF_KG -> 280 | G23: =ASM_E12_LIVEWEIGHT_BEEF_KG -> 280 | H23: =ASM_E12_LIVEWEIGHT_BEEF_KG -> 280 | I23: =ASM_E12_LIVEWEIGHT_BEEF_KG -> 280 | J23: =ASM_E12_LIVEWEIGHT_BEEF_KG -> 280 | K23: =ASM_E12_LIVEWEIGHT_BEEF_KG -> 280 | L23: =ASM_E12_LIVEWEIGHT_BEEF_KG -> 280
B24: Dressing percentage | C24: % | D24: =SUM(E24:L24) -> 4.16 | E24: =ASM_E13_DRESSING_PCT_BEEF -> 0.52 | F24: =ASM_E13_DRESSING_PCT_BEEF -> 0.52 | G24: =ASM_E13_DRESSING_PCT_BEEF -> 0.52 | H24: =ASM_E13_DRESSING_PCT_BEEF -> 0.52 | I24: =ASM_E13_DRESSING_PCT_BEEF -> 0.52 | J24: =ASM_E13_DRESSING_PCT_BEEF -> 0.52 | K24: =ASM_E13_DRESSING_PCT_BEEF -> 0.52 | L24: =ASM_E13_DRESSING_PCT_BEEF -> 0.52
B25: Carcass weight sold (kg/yr) | C25: kg/an | D25: =SUM(E25:L25) -> 209664 | E25: =E22*E23*E24 -> 26208 | F25: =F22*F23*F24 -> 26208 | G25: =G22*G23*G24 -> 26208 | H25: =H22*H23*H24 -> 26208 | I25: =I22*I23*I24 -> 26208 | J25: =J22*J23*J24 -> 26208 | K25: =K22*K23*K24 -> 26208 | L25: =L22*L23*L24 -> 26208
B26: Price (€/kg carcass) | C26: €/kg | D26: =SUM(E26:L26) -> 28 | E26: =ASM_E17_PRICE_BEEF_EUR_PER_KG_CARC -> 3.5 | F26: =ASM_E17_PRICE_BEEF_EUR_PER_KG_CARC -> 3.5 | G26: =ASM_E17_PRICE_BEEF_EUR_PER_KG_CARC -> 3.5 | H26: =ASM_E17_PRICE_BEEF_EUR_PER_KG_CARC -> 3.5 | I26: =ASM_E17_PRICE_BEEF_EUR_PER_KG_CARC -> 3.5 | J26: =ASM_E17_PRICE_BEEF_EUR_PER_KG_CARC -> 3.5 | K26: =ASM_E17_PRICE_BEEF_EUR_PER_KG_CARC -> 3.5 | L26: =ASM_E17_PRICE_BEEF_EUR_PER_KG_CARC -> 3.5
B27: Beef revenue (€/yr) | C27: €/an | D27: =SUM(E27:L27) -> 472399.2 | E27: =E25*E26*IF(E$4=ASM_A04_COD_YEAR,ASM_E20_RAMP_Y1_PCT,IF(E$4=ASM_A04_COD_YEAR+1,ASM_E21_RAMP_Y2_PCT,IF(E$4>ASM_A04_COD_YEAR+1,1,0))) -> 0 | F27: =F25*F26*IF(F$4=ASM_A04_COD_YEAR,ASM_E20_RAMP_Y1_PCT,IF(F$4=ASM_A04_COD_YEAR+1,ASM_E21_RAMP_Y2_PCT,IF(F$4>ASM_A04_COD_YEAR+1,1,0))) -> 0 | G27: =G25*G26*IF(G$4=ASM_A04_COD_YEAR,ASM_E20_RAMP_Y1_PCT,IF(G$4=ASM_A04_COD_YEAR+1,ASM_E21_RAMP_Y2_PCT,IF(G$4>ASM_A04_COD_YEAR+1,1,0))) -> 36691.2 | H27: =H25*H26*IF(H$4=ASM_A04_COD_YEAR,ASM_E20_RAMP_Y1_PCT,IF(H$4=ASM_A04_COD_YEAR+1,ASM_E21_RAMP_Y2_PCT,IF(H$4>ASM_A04_COD_YEAR+1,1,0))) -> 68796 | I27: =I25*I26*IF(I$4=ASM_A04_COD_YEAR,ASM_E20_RAMP_Y1_PCT,IF(I$4=ASM_A04_COD_YEAR+1,ASM_E21_RAMP_Y2_PCT,IF(I$4>ASM_A04_COD_YEAR+1,1,0))) -> 91728 | J27: =J25*J26*IF(J$4=ASM_A04_COD_YEAR,ASM_E20_RAMP_Y1_PCT,IF(J$4=ASM_A04_COD_YEAR+1,ASM_E21_RAMP_Y2_PCT,IF(J$4>ASM_A04_COD_YEAR+1,1,0))) -> 91728 | K27: =K25*K26*IF(K$4=ASM_A04_COD_YEAR,ASM_E20_RAMP_Y1_PCT,IF(K$4=ASM_A04_COD_YEAR+1,ASM_E21_RAMP_Y2_PCT,IF(K$4>ASM_A04_COD_YEAR+1,1,0))) -> 91728 | L27: =L25*L26*IF(L$4=ASM_A04_COD_YEAR,ASM_E20_RAMP_Y1_PCT,IF(L$4=ASM_A04_COD_YEAR+1,ASM_E21_RAMP_Y2_PCT,IF(L$4>ASM_A04_COD_YEAR+1,1,0))) -> 91728
B29: Market garden — irrigated horticulture
B30: Market garden surface (ha) | C30: ha | D30: =SUM(E30:L30) -> 600 | E30: =ASM_A01_N_FARMS*ASM_E04_SURFACE_MARAICHER_HA -> 75 | F30: =ASM_A01_N_FARMS*ASM_E04_SURFACE_MARAICHER_HA -> 75 | G30: =ASM_A01_N_FARMS*ASM_E04_SURFACE_MARAICHER_HA -> 75 | H30: =ASM_A01_N_FARMS*ASM_E04_SURFACE_MARAICHER_HA -> 75 | I30: =ASM_A01_N_FARMS*ASM_E04_SURFACE_MARAICHER_HA -> 75 | J30: =ASM_A01_N_FARMS*ASM_E04_SURFACE_MARAICHER_HA -> 75 | K30: =ASM_A01_N_FARMS*ASM_E04_SURFACE_MARAICHER_HA -> 75 | L30: =ASM_A01_N_FARMS*ASM_E04_SURFACE_MARAICHER_HA -> 75
B31: Yield (t/ha/cycle) | C31: t/ha | D31: =SUM(E31:L31) -> 120 | E31: =ASM_E15_YIELD_MARAICH_T_PER_HA -> 15 | F31: =ASM_E15_YIELD_MARAICH_T_PER_HA -> 15 | G31: =ASM_E15_YIELD_MARAICH_T_PER_HA -> 15 | H31: =ASM_E15_YIELD_MARAICH_T_PER_HA -> 15 | I31: =ASM_E15_YIELD_MARAICH_T_PER_HA -> 15 | J31: =ASM_E15_YIELD_MARAICH_T_PER_HA -> 15 | K31: =ASM_E15_YIELD_MARAICH_T_PER_HA -> 15 | L31: =ASM_E15_YIELD_MARAICH_T_PER_HA -> 15
B32: Cycles per year | C32: cycles | D32: =SUM(E32:L32) -> 24 | E32: =ASM_E07_N_CYCLES_MARAICHER -> 3 | F32: =ASM_E07_N_CYCLES_MARAICHER -> 3 | G32: =ASM_E07_N_CYCLES_MARAICHER -> 3 | H32: =ASM_E07_N_CYCLES_MARAICHER -> 3 | I32: =ASM_E07_N_CYCLES_MARAICHER -> 3 | J32: =ASM_E07_N_CYCLES_MARAICHER -> 3 | K32: =ASM_E07_N_CYCLES_MARAICHER -> 3 | L32: =ASM_E07_N_CYCLES_MARAICHER -> 3
B33: Volume (t/yr) | C33: t/an | D33: =SUM(E33:L33) -> 27000 | E33: =E30*E31*E32 -> 3375 | F33: =F30*F31*F32 -> 3375 | G33: =G30*G31*G32 -> 3375 | H33: =H30*H31*H32 -> 3375 | I33: =I30*I31*I32 -> 3375 | J33: =J30*J31*J32 -> 3375 | K33: =K30*K31*K32 -> 3375 | L33: =L30*L31*L32 -> 3375
B34: Price (€/t) | C34: €/t | D34: =SUM(E34:L34) -> 2888 | E34: =ASM_E19_PRICE_MARAICH_EUR_PER_T -> 361 | F34: =ASM_E19_PRICE_MARAICH_EUR_PER_T -> 361 | G34: =ASM_E19_PRICE_MARAICH_EUR_PER_T -> 361 | H34: =ASM_E19_PRICE_MARAICH_EUR_PER_T -> 361 | I34: =ASM_E19_PRICE_MARAICH_EUR_PER_T -> 361 | J34: =ASM_E19_PRICE_MARAICH_EUR_PER_T -> 361 | K34: =ASM_E19_PRICE_MARAICH_EUR_PER_T -> 361 | L34: =ASM_E19_PRICE_MARAICH_EUR_PER_T -> 361
B35: Market garden revenue (€/yr) | C35: €/an | D35: =SUM(E35:L35) -> 6274631.2 | E35: =E33*E34*IF(E$4=ASM_A04_COD_YEAR,ASM_E20_RAMP_Y1_PCT,IF(E$4=ASM_A04_COD_YEAR+1,ASM_E21_RAMP_Y2_PCT,IF(E$4>ASM_A04_COD_YEAR+1,1,0))) -> 0 | F35: =F33*F34*IF(F$4=ASM_A04_COD_YEAR,ASM_E20_RAMP_Y1_PCT,IF(F$4=ASM_A04_COD_YEAR+1,ASM_E21_RAMP_Y2_PCT,IF(F$4>ASM_A04_COD_YEAR+1,1,0))) -> 0 | G35: =G33*G34*IF(G$4=ASM_A04_COD_YEAR,ASM_E20_RAMP_Y1_PCT,IF(G$4=ASM_A04_COD_YEAR+1,ASM_E21_RAMP_Y2_PCT,IF(G$4>ASM_A04_COD_YEAR+1,1,0))) -> 487350 | H35: =H33*H34*IF(H$4=ASM_A04_COD_YEAR,ASM_E20_RAMP_Y1_PCT,IF(H$4=ASM_A04_COD_YEAR+1,ASM_E21_RAMP_Y2_PCT,IF(H$4>ASM_A04_COD_YEAR+1,1,0))) -> 913781.25 | I35: =I33*I34*IF(I$4=ASM_A04_COD_YEAR,ASM_E20_RAMP_Y1_PCT,IF(I$4=ASM_A04_COD_YEAR+1,ASM_E21_RAMP_Y2_PCT,IF(I$4>ASM_A04_COD_YEAR+1,1,0))) -> 1218375 | J35: =J33*J34*IF(J$4=ASM_A04_COD_YEAR,ASM_E20_RAMP_Y1_PCT,IF(J$4=ASM_A04_COD_YEAR+1,ASM_E21_RAMP_Y2_PCT,IF(J$4>ASM_A04_COD_YEAR+1,1,0))) -> 1218375 | K35: =K33*K34*IF(K$4=ASM_A04_COD_YEAR,ASM_E20_RAMP_Y1_PCT,IF(K$4=ASM_A04_COD_YEAR+1,ASM_E21_RAMP_Y2_PCT,IF(K$4>ASM_A04_COD_YEAR+1,1,0))) -> 1218375 | L35: =L33*L34*IF(L$4=ASM_A04_COD_YEAR,ASM_E20_RAMP_Y1_PCT,IF(L$4=ASM_A04_COD_YEAR+1,ASM_E21_RAMP_Y2_PCT,IF(L$4>ASM_A04_COD_YEAR+1,1,0))) -> 1218375
B37: Cereals — sorghum + maize
B38: Cereal surface (ha) | C38: ha | D38: =SUM(E38:L38) -> 1200 | E38: =ASM_A01_N_FARMS*ASM_E05_SURFACE_CEREALS_HA -> 150 | F38: =ASM_A01_N_FARMS*ASM_E05_SURFACE_CEREALS_HA -> 150 | G38: =ASM_A01_N_FARMS*ASM_E05_SURFACE_CEREALS_HA -> 150 | H38: =ASM_A01_N_FARMS*ASM_E05_SURFACE_CEREALS_HA -> 150 | I38: =ASM_A01_N_FARMS*ASM_E05_SURFACE_CEREALS_HA -> 150 | J38: =ASM_A01_N_FARMS*ASM_E05_SURFACE_CEREALS_HA -> 150 | K38: =ASM_A01_N_FARMS*ASM_E05_SURFACE_CEREALS_HA -> 150 | L38: =ASM_A01_N_FARMS*ASM_E05_SURFACE_CEREALS_HA -> 150
B39: Yield (t/ha) | C39: t/ha | D39: =SUM(E39:L39) -> 24 | E39: =ASM_E14_YIELD_CEREAL_T_PER_HA -> 3 | F39: =ASM_E14_YIELD_CEREAL_T_PER_HA -> 3 | G39: =ASM_E14_YIELD_CEREAL_T_PER_HA -> 3 | H39: =ASM_E14_YIELD_CEREAL_T_PER_HA -> 3 | I39: =ASM_E14_YIELD_CEREAL_T_PER_HA -> 3 | J39: =ASM_E14_YIELD_CEREAL_T_PER_HA -> 3 | K39: =ASM_E14_YIELD_CEREAL_T_PER_HA -> 3 | L39: =ASM_E14_YIELD_CEREAL_T_PER_HA -> 3
B40: Volume (t/yr) | C40: t/an | D40: =SUM(E40:L40) -> 3600 | E40: =E38*E39 -> 450 | F40: =F38*F39 -> 450 | G40: =G38*G39 -> 450 | H40: =H38*H39 -> 450 | I40: =I38*I39 -> 450 | J40: =J38*J39 -> 450 | K40: =K38*K39 -> 450 | L40: =L38*L39 -> 450
B41: Price (€/t) | C41: €/t | D41: =SUM(E41:L41) -> 1440 | E41: =ASM_E18_PRICE_CEREAL_EUR_PER_T -> 180 | F41: =ASM_E18_PRICE_CEREAL_EUR_PER_T -> 180 | G41: =ASM_E18_PRICE_CEREAL_EUR_PER_T -> 180 | H41: =ASM_E18_PRICE_CEREAL_EUR_PER_T -> 180 | I41: =ASM_E18_PRICE_CEREAL_EUR_PER_T -> 180 | J41: =ASM_E18_PRICE_CEREAL_EUR_PER_T -> 180 | K41: =ASM_E18_PRICE_CEREAL_EUR_PER_T -> 180 | L41: =ASM_E18_PRICE_CEREAL_EUR_PER_T -> 180
B42: Cereal revenue (€/yr) | C42: €/an | D42: =SUM(E42:L42) -> 417150 | E42: =E40*E41*IF(E$4=ASM_A04_COD_YEAR,ASM_E20_RAMP_Y1_PCT,IF(E$4=ASM_A04_COD_YEAR+1,ASM_E21_RAMP_Y2_PCT,IF(E$4>ASM_A04_COD_YEAR+1,1,0))) -> 0 | F42: =F40*F41*IF(F$4=ASM_A04_COD_YEAR,ASM_E20_RAMP_Y1_PCT,IF(F$4=ASM_A04_COD_YEAR+1,ASM_E21_RAMP_Y2_PCT,IF(F$4>ASM_A04_COD_YEAR+1,1,0))) -> 0 | G42: =G40*G41*IF(G$4=ASM_A04_COD_YEAR,ASM_E20_RAMP_Y1_PCT,IF(G$4=ASM_A04_COD_YEAR+1,ASM_E21_RAMP_Y2_PCT,IF(G$4>ASM_A04_COD_YEAR+1,1,0))) -> 32400 | H42: =H40*H41*IF(H$4=ASM_A04_COD_YEAR,ASM_E20_RAMP_Y1_PCT,IF(H$4=ASM_A04_COD_YEAR+1,ASM_E21_RAMP_Y2_PCT,IF(H$4>ASM_A04_COD_YEAR+1,1,0))) -> 60750 | I42: =I40*I41*IF(I$4=ASM_A04_COD_YEAR,ASM_E20_RAMP_Y1_PCT,IF(I$4=ASM_A04_COD_YEAR+1,ASM_E21_RAMP_Y2_PCT,IF(I$4>ASM_A04_COD_YEAR+1,1,0))) -> 81000 | J42: =J40*J41*IF(J$4=ASM_A04_COD_YEAR,ASM_E20_RAMP_Y1_PCT,IF(J$4=ASM_A04_COD_YEAR+1,ASM_E21_RAMP_Y2_PCT,IF(J$4>ASM_A04_COD_YEAR+1,1,0))) -> 81000 | K42: =K40*K41*IF(K$4=ASM_A04_COD_YEAR,ASM_E20_RAMP_Y1_PCT,IF(K$4=ASM_A04_COD_YEAR+1,ASM_E21_RAMP_Y2_PCT,IF(K$4>ASM_A04_COD_YEAR+1,1,0))) -> 81000 | L42: =L40*L41*IF(L$4=ASM_A04_COD_YEAR,ASM_E20_RAMP_Y1_PCT,IF(L$4=ASM_A04_COD_YEAR+1,ASM_E21_RAMP_Y2_PCT,IF(L$4>ASM_A04_COD_YEAR+1,1,0))) -> 81000
B44: Training revenue
B45: Training services revenue | C45: €/yr | D45: =SUM(E45:L45) -> 0 | E45: =TRAIN_REVENUE_YM1 -> 0 | F45: =TRAIN_REVENUE_Y0 -> 0 | G45: =TRAIN_REVENUE_Y1 -> 0 | H45: =TRAIN_REVENUE_Y2 -> 0 | I45: =TRAIN_REVENUE_Y3 -> 0 | J45: =TRAIN_REVENUE_Y4 -> 0 | K45: =TRAIN_REVENUE_Y5 -> 0 | L45: =TRAIN_REVENUE_Y6 -> 0
B47: Genetics revenue (Phase A: pure cost centre, = 0)
B48: Genetics services revenue (currently grant-funded) | C48: €/yr | D48: =SUM(E48:L48) -> 0 | E48: =GEN_REVENUE_YM1 -> 0 | F48: =GEN_REVENUE_Y0 -> 0 | G48: =GEN_REVENUE_Y1 -> 0 | H48: =GEN_REVENUE_Y2 -> 0 | I48: =GEN_REVENUE_Y3 -> 0 | J48: =GEN_REVENUE_Y4 -> 0 | K48: =GEN_REVENUE_Y5 -> 0 | L48: =GEN_REVENUE_Y6 -> 0
B50: Total revenue
B51: TOTAL REVENUE | C51: €/an | D51: =SUM(E51:L51) -> 8072640.5 | E51: =E17+E27+E35+E42+E45+E48 -> 0 | F51: =F17+F27+F35+F42+F45+F48 -> 0 | G51: =G17+G27+G35+G42+G45+G48 -> 627001.2 | H51: =H17+H27+H35+H42+H45+H48 -> 1175627.2 | I51: =I17+I27+I35+I42+I45+I48 -> 1567503 | J51: =J17+J27+J35+J42+J45+J48 -> 1567503 | K51: =K17+K27+K35+K42+K45+K48 -> 1567503 | L51: =L17+L27+L35+L42+L45+L48 -> 1567503

Sheet 08_OpEx
B1: 08 — Operating Expenses [€]
D3: Total | E3: Y-1 | F3: Y0 | G3: Y1 | H3: Y2 | I3: Y3 | J3: Y4 | K3: Y5 | L3: Y6
E4: -1 | F4: 0 | G4: 1 | H4: 2 | I4: 3 | J4: 4 | K4: 5 | L4: 6
B6: Summary
B7: Farming operations | C7: € | D7: =SUM(E7:L7) -> 3140891.8 | E7: =E39+E49+E63+E16 -> 0 | F7: =F39+F49+F63+F16 -> 0 | G7: =G39+G49+G63+G16 -> 345081.34 | H7: =H39+H49+H63+H16 -> 481314.55 | I7: =I39+I49+I63+I16 -> 578623.98 | J7: =J39+J49+J63+J16 -> 578623.98 | K7: =K39+K49+K63+K16 -> 578623.98 | L7: =L39+L49+L63+L16 -> 578623.98
B8: Training operations | C8: € | D8: =SUM(E8:L8) -> 1359700 | E8: =E13 -> 0 | F8: =F13 -> 0 | G8: =G13 -> 679850 | H8: =H13 -> 679850 | I8: =I13 -> 0 | J8: =J13 -> 0 | K8: =K13 -> 0 | L8: =L13 -> 0
B9: Genetics operations | C9: € | D9: =SUM(E9:L9) -> 679360 | E9: =E68 -> 0 | F9: =F68 -> 177800 | G9: =G68 -> 250780 | H9: =H68 -> 250780 | I9: =I68 -> 0 | J9: =J68 -> 0 | K9: =K68 -> 0 | L9: =L68 -> 0
B10: TOTAL OPEX | C10: € | D10: =SUM(D7:D9) -> 5179951.8 | E10: =SUM(E7:E9) -> 0 | F10: =SUM(F7:F9) -> 177800 | G10: =SUM(G7:G9) -> 1275711.3 | H10: =SUM(H7:H9) -> 1411944.5 | I10: =SUM(I7:I9) -> 578623.98 | J10: =SUM(J7:J9) -> 578623.98 | K10: =SUM(K7:K9) -> 578623.98 | L10: =SUM(L7:L9) -> 578623.98
B12: Recurring training costs
B13: Trainers + trainee stipends + monitoring/comms | C13: €/yr | D13: =SUM(E13:L13) -> 1359700 | E13: =TRAIN_REC_TOTAL_YM1 -> 0 | F13: =TRAIN_REC_TOTAL_Y0 -> 0 | G13: =TRAIN_REC_TOTAL_Y1 -> 679850 | H13: =TRAIN_REC_TOTAL_Y2 -> 679850 | I13: =TRAIN_REC_TOTAL_Y3 -> 0 | J13: =TRAIN_REC_TOTAL_Y4 -> 0 | K13: =TRAIN_REC_TOTAL_Y5 -> 0 | L13: =TRAIN_REC_TOTAL_Y6 -> 0
B15: Annual audit & financing fees
B16: Annual audit (Y1–Y6) | C16: €/yr | D16: =SUM(E16:L16) -> 81816 | E16: =ASM_J04_COST_AUDIT_YEAR_EUR*IF(AND(E$4>=ASM_A04_COD_YEAR,E$4<ASM_A04_COD_YEAR+ASM_J05_N_YEARS_AUDIT),1,0) -> 0 | F16: =ASM_J04_COST_AUDIT_YEAR_EUR*IF(AND(F$4>=ASM_A04_COD_YEAR,F$4<ASM_A04_COD_YEAR+ASM_J05_N_YEARS_AUDIT),1,0) -> 0 | G16: =ASM_J04_COST_AUDIT_YEAR_EUR*IF(AND(G$4>=ASM_A04_COD_YEAR,G$4<ASM_A04_COD_YEAR+ASM_J05_N_YEARS_AUDIT),1,0) -> 13636 | H16: =ASM_J04_COST_AUDIT_YEAR_EUR*IF(AND(H$4>=ASM_A04_COD_YEAR,H$4<ASM_A04_COD_YEAR+ASM_J05_N_YEARS_AUDIT),1,0) -> 13636 | I16: =ASM_J04_COST_AUDIT_YEAR_EUR*IF(AND(I$4>=ASM_A04_COD_YEAR,I$4<ASM_A04_COD_YEAR+ASM_J05_N_YEARS_AUDIT),1,0) -> 13636 | J16: =ASM_J04_COST_AUDIT_YEAR_EUR*IF(AND(J$4>=ASM_A04_COD_YEAR,J$4<ASM_A04_COD_YEAR+ASM_J05_N_YEARS_AUDIT),1,0) -> 13636 | K16: =ASM_J04_COST_AUDIT_YEAR_EUR*IF(AND(K$4>=ASM_A04_COD_YEAR,K$4<ASM_A04_COD_YEAR+ASM_J05_N_YEARS_AUDIT),1,0) -> 13636 | L16: =ASM_J04_COST_AUDIT_YEAR_EUR*IF(AND(L$4>=ASM_A04_COD_YEAR,L$4<ASM_A04_COD_YEAR+ASM_J05_N_YEARS_AUDIT),1,0) -> 13636
B17: DSRA LC fee (annual, ~1% × face value) | C17: €/yr | D17: =SUM(E17:L17) -> 13620 | E17: =ASM_K07_DSRA_LC_FEE_EUR_YR*FLAG_POST_COD_YM1 -> 0 | F17: =ASM_K07_DSRA_LC_FEE_EUR_YR*FLAG_POST_COD_Y0 -> 0 | G17: =ASM_K07_DSRA_LC_FEE_EUR_YR*FLAG_POST_COD_Y1 -> 2270 | H17: =ASM_K07_DSRA_LC_FEE_EUR_YR*FLAG_POST_COD_Y2 -> 2270 | I17: =ASM_K07_DSRA_LC_FEE_EUR_YR*FLAG_POST_COD_Y3 -> 2270 | J17: =ASM_K07_DSRA_LC_FEE_EUR_YR*FLAG_POST_COD_Y4 -> 2270 | K17: =ASM_K07_DSRA_LC_FEE_EUR_YR*FLAG_POST_COD_Y5 -> 2270 | L17: =ASM_K07_DSRA_LC_FEE_EUR_YR*FLAG_POST_COD_Y6 -> 2270
B19: Farming direct inputs (crops + herd + supervision)
B20: Market garden surface (ha) | C20: ha | D20: =SUM(E20:L20) -> 600 | E20: =ASM_A01_N_FARMS*ASM_E04_SURFACE_MARAICHER_HA -> 75 | F20: =ASM_A01_N_FARMS*ASM_E04_SURFACE_MARAICHER_HA -> 75 | G20: =ASM_A01_N_FARMS*ASM_E04_SURFACE_MARAICHER_HA -> 75 | H20: =ASM_A01_N_FARMS*ASM_E04_SURFACE_MARAICHER_HA -> 75 | I20: =ASM_A01_N_FARMS*ASM_E04_SURFACE_MARAICHER_HA -> 75 | J20: =ASM_A01_N_FARMS*ASM_E04_SURFACE_MARAICHER_HA -> 75 | K20: =ASM_A01_N_FARMS*ASM_E04_SURFACE_MARAICHER_HA -> 75 | L20: =ASM_A01_N_FARMS*ASM_E04_SURFACE_MARAICHER_HA -> 75
B21: ha-cycles/yr (surface × cycles) | C21: ha-cycles | D21: =SUM(E21:L21) -> 1800 | E21: =E20*ASM_E07_N_CYCLES_MARAICHER -> 225 | F21: =F20*ASM_E07_N_CYCLES_MARAICHER -> 225 | G21: =G20*ASM_E07_N_CYCLES_MARAICHER -> 225 | H21: =H20*ASM_E07_N_CYCLES_MARAICHER -> 225 | I21: =I20*ASM_E07_N_CYCLES_MARAICHER -> 225 | J21: =J20*ASM_E07_N_CYCLES_MARAICHER -> 225 | K21: =K20*ASM_E07_N_CYCLES_MARAICHER -> 225 | L21: =L20*ASM_E07_N_CYCLES_MARAICHER -> 225
B22: Seeds — market garden | C22: €/an | D22: =SUM(E22:L22) -> 139050 | E22: =E21*ASM_P01_COST_SEED_MARAICH_EUR_HA_CYCLE*IF(E$4=ASM_A04_COD_YEAR,ASM_E20_RAMP_Y1_PCT,IF(E$4=ASM_A04_COD_YEAR+1,ASM_E21_RAMP_Y2_PCT,IF(E$4>ASM_A04_COD_YEAR+1,1,0))) -> 0 | F22: =F21*ASM_P01_COST_SEED_MARAICH_EUR_HA_CYCLE*IF(F$4=ASM_A04_COD_YEAR,ASM_E20_RAMP_Y1_PCT,IF(F$4=ASM_A04_COD_YEAR+1,ASM_E21_RAMP_Y2_PCT,IF(F$4>ASM_A04_COD_YEAR+1,1,0))) -> 0 | G22: =G21*ASM_P01_COST_SEED_MARAICH_EUR_HA_CYCLE*IF(G$4=ASM_A04_COD_YEAR,ASM_E20_RAMP_Y1_PCT,IF(G$4=ASM_A04_COD_YEAR+1,ASM_E21_RAMP_Y2_PCT,IF(G$4>ASM_A04_COD_YEAR+1,1,0))) -> 10800 | H22: =H21*ASM_P01_COST_SEED_MARAICH_EUR_HA_CYCLE*IF(H$4=ASM_A04_COD_YEAR,ASM_E20_RAMP_Y1_PCT,IF(H$4=ASM_A04_COD_YEAR+1,ASM_E21_RAMP_Y2_PCT,IF(H$4>ASM_A04_COD_YEAR+1,1,0))) -> 20250 | I22: =I21*ASM_P01_COST_SEED_MARAICH_EUR_HA_CYCLE*IF(I$4=ASM_A04_COD_YEAR,ASM_E20_RAMP_Y1_PCT,IF(I$4=ASM_A04_COD_YEAR+1,ASM_E21_RAMP_Y2_PCT,IF(I$4>ASM_A04_COD_YEAR+1,1,0))) -> 27000 | J22: =J21*ASM_P01_COST_SEED_MARAICH_EUR_HA_CYCLE*IF(J$4=ASM_A04_COD_YEAR,ASM_E20_RAMP_Y1_PCT,IF(J$4=ASM_A04_COD_YEAR+1,ASM_E21_RAMP_Y2_PCT,IF(J$4>ASM_A04_COD_YEAR+1,1,0))) -> 27000 | K22: =K21*ASM_P01_COST_SEED_MARAICH_EUR_HA_CYCLE*IF(K$4=ASM_A04_COD_YEAR,ASM_E20_RAMP_Y1_PCT,IF(K$4=ASM_A04_COD_YEAR+1,ASM_E21_RAMP_Y2_PCT,IF(K$4>ASM_A04_COD_YEAR+1,1,0))) -> 27000 | L22: =L21*ASM_P01_COST_SEED_MARAICH_EUR_HA_CYCLE*IF(L$4=ASM_A04_COD_YEAR,ASM_E20_RAMP_Y1_PCT,IF(L$4=ASM_A04_COD_YEAR+1,ASM_E21_RAMP_Y2_PCT,IF(L$4>ASM_A04_COD_YEAR+1,1,0))) -> 27000
B23: Fertilizer — market garden | C23: €/an | D23: =SUM(E23:L23) -> 173812.5 | E23: =E21*ASM_P02_COST_FERT_MARAICH_EUR_HA_CYCLE*IF(E$4=ASM_A04_COD_YEAR,ASM_E20_RAMP_Y1_PCT,IF(E$4=ASM_A04_COD_YEAR+1,ASM_E21_RAMP_Y2_PCT,IF(E$4>ASM_A04_COD_YEAR+1,1,0))) -> 0 | F23: =F21*ASM_P02_COST_FERT_MARAICH_EUR_HA_CYCLE*IF(F$4=ASM_A04_COD_YEAR,ASM_E20_RAMP_Y1_PCT,IF(F$4=ASM_A04_COD_YEAR+1,ASM_E21_RAMP_Y2_PCT,IF(F$4>ASM_A04_COD_YEAR+1,1,0))) -> 0 | G23: =G21*ASM_P02_COST_FERT_MARAICH_EUR_HA_CYCLE*IF(G$4=ASM_A04_COD_YEAR,ASM_E20_RAMP_Y1_PCT,IF(G$4=ASM_A04_COD_YEAR+1,ASM_E21_RAMP_Y2_PCT,IF(G$4>ASM_A04_COD_YEAR+1,1,0))) -> 13500 | H23: =H21*ASM_P02_COST_FERT_MARAICH_EUR_HA_CYCLE*IF(H$4=ASM_A04_COD_YEAR,ASM_E20_RAMP_Y1_PCT,IF(H$4=ASM_A04_COD_YEAR+1,ASM_E21_RAMP_Y2_PCT,IF(H$4>ASM_A04_COD_YEAR+1,1,0))) -> 25312.5 | I23: =I21*ASM_P02_COST_FERT_MARAICH_EUR_HA_CYCLE*IF(I$4=ASM_A04_COD_YEAR,ASM_E20_RAMP_Y1_PCT,IF(I$4=ASM_A04_COD_YEAR+1,ASM_E21_RAMP_Y2_PCT,IF(I$4>ASM_A04_COD_YEAR+1,1,0))) -> 33750 | J23: =J21*ASM_P02_COST_FERT_MARAICH_EUR_HA_CYCLE*IF(J$4=ASM_A04_COD_YEAR,ASM_E20_RAMP_Y1_PCT,IF(J$4=ASM_A04_COD_YEAR+1,ASM_E21_RAMP_Y2_PCT,IF(J$4>ASM_A04_COD_YEAR+1,1,0))) -> 33750 | K23: =K21*ASM_P02_COST_FERT_MARAICH_EUR_HA_CYCLE*IF(K$4=ASM_A04_COD_YEAR,ASM_E20_RAMP_Y1_PCT,IF(K$4=ASM_A04_COD_YEAR+1,ASM_E21_RAMP_Y2_PCT,IF(K$4>ASM_A04_COD_YEAR+1,1,0))) -> 33750 | L23: =L21*ASM_P02_COST_FERT_MARAICH_EUR_HA_CYCLE*IF(L$4=ASM_A04_COD_YEAR,ASM_E20_RAMP_Y1_PCT,IF(L$4=ASM_A04_COD_YEAR+1,ASM_E21_RAMP_Y2_PCT,IF(L$4>ASM_A04_COD_YEAR+1,1,0))) -> 33750
B24: Pesticides — market garden | C24: €/an | D24: =SUM(E24:L24) -> 92700 | E24: =E21*ASM_P03_COST_PHYTO_MARAICH_EUR_HA_CYCLE*IF(E$4=ASM_A04_COD_YEAR,ASM_E20_RAMP_Y1_PCT,IF(E$4=ASM_A04_COD_YEAR+1,ASM_E21_RAMP_Y2_PCT,IF(E$4>ASM_A04_COD_YEAR+1,1,0))) -> 0 | F24: =F21*ASM_P03_COST_PHYTO_MARAICH_EUR_HA_CYCLE*IF(F$4=ASM_A04_COD_YEAR,ASM_E20_RAMP_Y1_PCT,IF(F$4=ASM_A04_COD_YEAR+1,ASM_E21_RAMP_Y2_PCT,IF(F$4>ASM_A04_COD_YEAR+1,1,0))) -> 0 | G24: =G21*ASM_P03_COST_PHYTO_MARAICH_EUR_HA_CYCLE*IF(G$4=ASM_A04_COD_YEAR,ASM_E20_RAMP_Y1_PCT,IF(G$4=ASM_A04_COD_YEAR+1,ASM_E21_RAMP_Y2_PCT,IF(G$4>ASM_A04_COD_YEAR+1,1,0))) -> 7200 | H24: =H21*ASM_P03_COST_PHYTO_MARAICH_EUR_HA_CYCLE*IF(H$4=ASM_A04_COD_YEAR,ASM_E20_RAMP_Y1_PCT,IF(H$4=ASM_A04_COD_YEAR+1,ASM_E21_RAMP_Y2_PCT,IF(H$4>ASM_A04_COD_YEAR+1,1,0))) -> 13500 | I24: =I21*ASM_P03_COST_PHYTO_MARAICH_EUR_HA_CYCLE*IF(I$4=ASM_A04_COD_YEAR,ASM_E20_RAMP_Y1_PCT,IF(I$4=ASM_A04_COD_YEAR+1,ASM_E21_RAMP_Y2_PCT,IF(I$4>ASM_A04_COD_YEAR+1,1,0))) -> 18000 | J24: =J21*ASM_P03_COST_PHYTO_MARAICH_EUR_HA_CYCLE*IF(J$4=ASM_A04_COD_YEAR,ASM_E20_RAMP_Y1_PCT,IF(J$4=ASM_A04_COD_YEAR+1,ASM_E21_RAMP_Y2_PCT,IF(J$4>ASM_A04_COD_YEAR+1,1,0))) -> 18000 | K24: =K21*ASM_P03_COST_PHYTO_MARAICH_EUR_HA_CYCLE*IF(K$4=ASM_A04_COD_YEAR,ASM_E20_RAMP_Y1_PCT,IF(K$4=ASM_A04_COD_YEAR+1,ASM_E21_RAMP_Y2_PCT,IF(K$4>ASM_A04_COD_YEAR+1,1,0))) -> 18000 | L24: =L21*ASM_P03_COST_PHYTO_MARAICH_EUR_HA_CYCLE*IF(L$4=ASM_A04_COD_YEAR,ASM_E20_RAMP_Y1_PCT,IF(L$4=ASM_A04_COD_YEAR+1,ASM_E21_RAMP_Y2_PCT,IF(L$4>ASM_A04_COD_YEAR+1,1,0))) -> 18000
B25: Cereal surface (ha) | C25: ha | D25: =SUM(E25:L25) -> 1200 | E25: =ASM_A01_N_FARMS*ASM_E05_SURFACE_CEREALS_HA -> 150 | F25: =ASM_A01_N_FARMS*ASM_E05_SURFACE_CEREALS_HA -> 150 | G25: =ASM_A01_N_FARMS*ASM_E05_SURFACE_CEREALS_HA -> 150 | H25: =ASM_A01_N_FARMS*ASM_E05_SURFACE_CEREALS_HA -> 150 | I25: =ASM_A01_N_FARMS*ASM_E05_SURFACE_CEREALS_HA -> 150 | J25: =ASM_A01_N_FARMS*ASM_E05_SURFACE_CEREALS_HA -> 150 | K25: =ASM_A01_N_FARMS*ASM_E05_SURFACE_CEREALS_HA -> 150 | L25: =ASM_A01_N_FARMS*ASM_E05_SURFACE_CEREALS_HA -> 150
B26: Seeds — cereals | C26: €/an | D26: =SUM(E26:L26) -> 34762.5 | E26: =E25*ASM_P04_COST_SEED_CEREAL_EUR_HA*IF(E$4=ASM_A04_COD_YEAR,ASM_E20_RAMP_Y1_PCT,IF(E$4=ASM_A04_COD_YEAR+1,ASM_E21_RAMP_Y2_PCT,IF(E$4>ASM_A04_COD_YEAR+1,1,0))) -> 0 | F26: =F25*ASM_P04_COST_SEED_CEREAL_EUR_HA*IF(F$4=ASM_A04_COD_YEAR,ASM_E20_RAMP_Y1_PCT,IF(F$4=ASM_A04_COD_YEAR+1,ASM_E21_RAMP_Y2_PCT,IF(F$4>ASM_A04_COD_YEAR+1,1,0))) -> 0 | G26: =G25*ASM_P04_COST_SEED_CEREAL_EUR_HA*IF(G$4=ASM_A04_COD_YEAR,ASM_E20_RAMP_Y1_PCT,IF(G$4=ASM_A04_COD_YEAR+1,ASM_E21_RAMP_Y2_PCT,IF(G$4>ASM_A04_COD_YEAR+1,1,0))) -> 2700 | H26: =H25*ASM_P04_COST_SEED_CEREAL_EUR_HA*IF(H$4=ASM_A04_COD_YEAR,ASM_E20_RAMP_Y1_PCT,IF(H$4=ASM_A04_COD_YEAR+1,ASM_E21_RAMP_Y2_PCT,IF(H$4>ASM_A04_COD_YEAR+1,1,0))) -> 5062.5 | I26: =I25*ASM_P04_COST_SEED_CEREAL_EUR_HA*IF(I$4=ASM_A04_COD_YEAR,ASM_E20_RAMP_Y1_PCT,IF(I$4=ASM_A04_COD_YEAR+1,ASM_E21_RAMP_Y2_PCT,IF(I$4>ASM_A04_COD_YEAR+1,1,0))) -> 6750 | J26: =J25*ASM_P04_COST_SEED_CEREAL_EUR_HA*IF(J$4=ASM_A04_COD_YEAR,ASM_E20_RAMP_Y1_PCT,IF(J$4=ASM_A04_COD_YEAR+1,ASM_E21_RAMP_Y2_PCT,IF(J$4>ASM_A04_COD_YEAR+1,1,0))) -> 6750 | K26: =K25*ASM_P04_COST_SEED_CEREAL_EUR_HA*IF(K$4=ASM_A04_COD_YEAR,ASM_E20_RAMP_Y1_PCT,IF(K$4=ASM_A04_COD_YEAR+1,ASM_E21_RAMP_Y2_PCT,IF(K$4>ASM_A04_COD_YEAR+1,1,0))) -> 6750 | L26: =L25*ASM_P04_COST_SEED_CEREAL_EUR_HA*IF(L$4=ASM_A04_COD_YEAR,ASM_E20_RAMP_Y1_PCT,IF(L$4=ASM_A04_COD_YEAR+1,ASM_E21_RAMP_Y2_PCT,IF(L$4>ASM_A04_COD_YEAR+1,1,0))) -> 6750
B27: Fertilizer — cereals | C27: €/an | D27: =SUM(E27:L27) -> 92700 | E27: =E25*ASM_P05_COST_FERT_CEREAL_EUR_HA*IF(E$4=ASM_A04_COD_YEAR,ASM_E20_RAMP_Y1_PCT,IF(E$4=ASM_A04_COD_YEAR+1,ASM_E21_RAMP_Y2_PCT,IF(E$4>ASM_A04_COD_YEAR+1,1,0))) -> 0 | F27: =F25*ASM_P05_COST_FERT_CEREAL_EUR_HA*IF(F$4=ASM_A04_COD_YEAR,ASM_E20_RAMP_Y1_PCT,IF(F$4=ASM_A04_COD_YEAR+1,ASM_E21_RAMP_Y2_PCT,IF(F$4>ASM_A04_COD_YEAR+1,1,0))) -> 0 | G27: =G25*ASM_P05_COST_FERT_CEREAL_EUR_HA*IF(G$4=ASM_A04_COD_YEAR,ASM_E20_RAMP_Y1_PCT,IF(G$4=ASM_A04_COD_YEAR+1,ASM_E21_RAMP_Y2_PCT,IF(G$4>ASM_A04_COD_YEAR+1,1,0))) -> 7200 | H27: =H25*ASM_P05_COST_FERT_CEREAL_EUR_HA*IF(H$4=ASM_A04_COD_YEAR,ASM_E20_RAMP_Y1_PCT,IF(H$4=ASM_A04_COD_YEAR+1,ASM_E21_RAMP_Y2_PCT,IF(H$4>ASM_A04_COD_YEAR+1,1,0))) -> 13500 | I27: =I25*ASM_P05_COST_FERT_CEREAL_EUR_HA*IF(I$4=ASM_A04_COD_YEAR,ASM_E20_RAMP_Y1_PCT,IF(I$4=ASM_A04_COD_YEAR+1,ASM_E21_RAMP_Y2_PCT,IF(I$4>ASM_A04_COD_YEAR+1,1,0))) -> 18000 | J27: =J25*ASM_P05_COST_FERT_CEREAL_EUR_HA*IF(J$4=ASM_A04_COD_YEAR,ASM_E20_RAMP_Y1_PCT,IF(J$4=ASM_A04_COD_YEAR+1,ASM_E21_RAMP_Y2_PCT,IF(J$4>ASM_A04_COD_YEAR+1,1,0))) -> 18000 | K27: =K25*ASM_P05_COST_FERT_CEREAL_EUR_HA*IF(K$4=ASM_A04_COD_YEAR,ASM_E20_RAMP_Y1_PCT,IF(K$4=ASM_A04_COD_YEAR+1,ASM_E21_RAMP_Y2_PCT,IF(K$4>ASM_A04_COD_YEAR+1,1,0))) -> 18000 | L27: =L25*ASM_P05_COST_FERT_CEREAL_EUR_HA*IF(L$4=ASM_A04_COD_YEAR,ASM_E20_RAMP_Y1_PCT,IF(L$4=ASM_A04_COD_YEAR+1,ASM_E21_RAMP_Y2_PCT,IF(L$4>ASM_A04_COD_YEAR+1,1,0))) -> 18000
B28: Pesticides — cereals | C28: €/an | D28: =SUM(E28:L28) -> 30900 | E28: =E25*ASM_P06_COST_PHYTO_CEREAL_EUR_HA*IF(E$4=ASM_A04_COD_YEAR,ASM_E20_RAMP_Y1_PCT,IF(E$4=ASM_A04_COD_YEAR+1,ASM_E21_RAMP_Y2_PCT,IF(E$4>ASM_A04_COD_YEAR+1,1,0))) -> 0 | F28: =F25*ASM_P06_COST_PHYTO_CEREAL_EUR_HA*IF(F$4=ASM_A04_COD_YEAR,ASM_E20_RAMP_Y1_PCT,IF(F$4=ASM_A04_COD_YEAR+1,ASM_E21_RAMP_Y2_PCT,IF(F$4>ASM_A04_COD_YEAR+1,1,0))) -> 0 | G28: =G25*ASM_P06_COST_PHYTO_CEREAL_EUR_HA*IF(G$4=ASM_A04_COD_YEAR,ASM_E20_RAMP_Y1_PCT,IF(G$4=ASM_A04_COD_YEAR+1,ASM_E21_RAMP_Y2_PCT,IF(G$4>ASM_A04_COD_YEAR+1,1,0))) -> 2400 | H28: =H25*ASM_P06_COST_PHYTO_CEREAL_EUR_HA*IF(H$4=ASM_A04_COD_YEAR,ASM_E20_RAMP_Y1_PCT,IF(H$4=ASM_A04_COD_YEAR+1,ASM_E21_RAMP_Y2_PCT,IF(H$4>ASM_A04_COD_YEAR+1,1,0))) -> 4500 | I28: =I25*ASM_P06_COST_PHYTO_CEREAL_EUR_HA*IF(I$4=ASM_A04_COD_YEAR,ASM_E20_RAMP_Y1_PCT,IF(I$4=ASM_A04_COD_YEAR+1,ASM_E21_RAMP_Y2_PCT,IF(I$4>ASM_A04_COD_YEAR+1,1,0))) -> 6000 | J28: =J25*ASM_P06_COST_PHYTO_CEREAL_EUR_HA*IF(J$4=ASM_A04_COD_YEAR,ASM_E20_RAMP_Y1_PCT,IF(J$4=ASM_A04_COD_YEAR+1,ASM_E21_RAMP_Y2_PCT,IF(J$4>ASM_A04_COD_YEAR+1,1,0))) -> 6000 | K28: =K25*ASM_P06_COST_PHYTO_CEREAL_EUR_HA*IF(K$4=ASM_A04_COD_YEAR,ASM_E20_RAMP_Y1_PCT,IF(K$4=ASM_A04_COD_YEAR+1,ASM_E21_RAMP_Y2_PCT,IF(K$4>ASM_A04_COD_YEAR+1,1,0))) -> 6000 | L28: =L25*ASM_P06_COST_PHYTO_CEREAL_EUR_HA*IF(L$4=ASM_A04_COD_YEAR,ASM_E20_RAMP_Y1_PCT,IF(L$4=ASM_A04_COD_YEAR+1,ASM_E21_RAMP_Y2_PCT,IF(L$4>ASM_A04_COD_YEAR+1,1,0))) -> 6000
B29: Forage surface (ha) | C29: ha | D29: =SUM(E29:L29) -> 240 | E29: =ASM_A01_N_FARMS*ASM_E22_SURFACE_FOURRAGE_HA -> 30 | F29: =ASM_A01_N_FARMS*ASM_E22_SURFACE_FOURRAGE_HA -> 30 | G29: =ASM_A01_N_FARMS*ASM_E22_SURFACE_FOURRAGE_HA -> 30 | H29: =ASM_A01_N_FARMS*ASM_E22_SURFACE_FOURRAGE_HA -> 30 | I29: =ASM_A01_N_FARMS*ASM_E22_SURFACE_FOURRAGE_HA -> 30 | J29: =ASM_A01_N_FARMS*ASM_E22_SURFACE_FOURRAGE_HA -> 30 | K29: =ASM_A01_N_FARMS*ASM_E22_SURFACE_FOURRAGE_HA -> 30 | L29: =ASM_A01_N_FARMS*ASM_E22_SURFACE_FOURRAGE_HA -> 30
B30: Fertilizer — alfalfa | C30: €/an | D30: =SUM(E30:L30) -> 15450 | E30: =E29*ASM_P07_COST_FERT_FOURRAGE_EUR_HA*IF(E$4=ASM_A04_COD_YEAR,ASM_E20_RAMP_Y1_PCT,IF(E$4=ASM_A04_COD_YEAR+1,ASM_E21_RAMP_Y2_PCT,IF(E$4>ASM_A04_COD_YEAR+1,1,0))) -> 0 | F30: =F29*ASM_P07_COST_FERT_FOURRAGE_EUR_HA*IF(F$4=ASM_A04_COD_YEAR,ASM_E20_RAMP_Y1_PCT,IF(F$4=ASM_A04_COD_YEAR+1,ASM_E21_RAMP_Y2_PCT,IF(F$4>ASM_A04_COD_YEAR+1,1,0))) -> 0 | G30: =G29*ASM_P07_COST_FERT_FOURRAGE_EUR_HA*IF(G$4=ASM_A04_COD_YEAR,ASM_E20_RAMP_Y1_PCT,IF(G$4=ASM_A04_COD_YEAR+1,ASM_E21_RAMP_Y2_PCT,IF(G$4>ASM_A04_COD_YEAR+1,1,0))) -> 1200 | H30: =H29*ASM_P07_COST_FERT_FOURRAGE_EUR_HA*IF(H$4=ASM_A04_COD_YEAR,ASM_E20_RAMP_Y1_PCT,IF(H$4=ASM_A04_COD_YEAR+1,ASM_E21_RAMP_Y2_PCT,IF(H$4>ASM_A04_COD_YEAR+1,1,0))) -> 2250 | I30: =I29*ASM_P07_COST_FERT_FOURRAGE_EUR_HA*IF(I$4=ASM_A04_COD_YEAR,ASM_E20_RAMP_Y1_PCT,IF(I$4=ASM_A04_COD_YEAR+1,ASM_E21_RAMP_Y2_PCT,IF(I$4>ASM_A04_COD_YEAR+1,1,0))) -> 3000 | J30: =J29*ASM_P07_COST_FERT_FOURRAGE_EUR_HA*IF(J$4=ASM_A04_COD_YEAR,ASM_E20_RAMP_Y1_PCT,IF(J$4=ASM_A04_COD_YEAR+1,ASM_E21_RAMP_Y2_PCT,IF(J$4>ASM_A04_COD_YEAR+1,1,0))) -> 3000 | K30: =K29*ASM_P07_COST_FERT_FOURRAGE_EUR_HA*IF(K$4=ASM_A04_COD_YEAR,ASM_E20_RAMP_Y1_PCT,IF(K$4=ASM_A04_COD_YEAR+1,ASM_E21_RAMP_Y2_PCT,IF(K$4>ASM_A04_COD_YEAR+1,1,0))) -> 3000 | L30: =L29*ASM_P07_COST_FERT_FOURRAGE_EUR_HA*IF(L$4=ASM_A04_COD_YEAR,ASM_E20_RAMP_Y1_PCT,IF(L$4=ASM_A04_COD_YEAR+1,ASM_E21_RAMP_Y2_PCT,IF(L$4>ASM_A04_COD_YEAR+1,1,0))) -> 3000
B31: Total forage requirement (t DM/yr) | C31: t MS | D31: =SUM(E31:L31) -> 5385.6 | E31: =ASM_A01_N_FARMS*(ASM_E08_N_COWS_DAIRY_PER_FARM*ASM_E24_FEED_RATE_DAIRY_T_MS_YR+ASM_E10_N_BEEF_STOCK_PER_FARM*ASM_E25_FEED_RATE_BEEF_T_MS_YR) -> 673.2 | F31: =ASM_A01_N_FARMS*(ASM_E08_N_COWS_DAIRY_PER_FARM*ASM_E24_FEED_RATE_DAIRY_T_MS_YR+ASM_E10_N_BEEF_STOCK_PER_FARM*ASM_E25_FEED_RATE_BEEF_T_MS_YR) -> 673.2 | G31: =ASM_A01_N_FARMS*(ASM_E08_N_COWS_DAIRY_PER_FARM*ASM_E24_FEED_RATE_DAIRY_T_MS_YR+ASM_E10_N_BEEF_STOCK_PER_FARM*ASM_E25_FEED_RATE_BEEF_T_MS_YR) -> 673.2 | H31: =ASM_A01_N_FARMS*(ASM_E08_N_COWS_DAIRY_PER_FARM*ASM_E24_FEED_RATE_DAIRY_T_MS_YR+ASM_E10_N_BEEF_STOCK_PER_FARM*ASM_E25_FEED_RATE_BEEF_T_MS_YR) -> 673.2 | I31: =ASM_A01_N_FARMS*(ASM_E08_N_COWS_DAIRY_PER_FARM*ASM_E24_FEED_RATE_DAIRY_T_MS_YR+ASM_E10_N_BEEF_STOCK_PER_FARM*ASM_E25_FEED_RATE_BEEF_T_MS_YR) -> 673.2 | J31: =ASM_A01_N_FARMS*(ASM_E08_N_COWS_DAIRY_PER_FARM*ASM_E24_FEED_RATE_DAIRY_T_MS_YR+ASM_E10_N_BEEF_STOCK_PER_FARM*ASM_E25_FEED_RATE_BEEF_T_MS_YR) -> 673.2 | K31: =ASM_A01_N_FARMS*(ASM_E08_N_COWS_DAIRY_PER_FARM*ASM_E24_FEED_RATE_DAIRY_T_MS_YR+ASM_E10_N_BEEF_STOCK_PER_FARM*ASM_E25_FEED_RATE_BEEF_T_MS_YR) -> 673.2 | L31: =ASM_A01_N_FARMS*(ASM_E08_N_COWS_DAIRY_PER_FARM*ASM_E24_FEED_RATE_DAIRY_T_MS_YR+ASM_E10_N_BEEF_STOCK_PER_FARM*ASM_E25_FEED_RATE_BEEF_T_MS_YR) -> 673.2
B32: Internal production (t DM/yr) | C32: t MS | D32: =SUM(E32:L32) -> 2880 | E32: =ASM_A01_N_FARMS*ASM_E22_SURFACE_FOURRAGE_HA*ASM_E23_YIELD_FOURRAGE_T_MS_HA -> 360 | F32: =ASM_A01_N_FARMS*ASM_E22_SURFACE_FOURRAGE_HA*ASM_E23_YIELD_FOURRAGE_T_MS_HA -> 360 | G32: =ASM_A01_N_FARMS*ASM_E22_SURFACE_FOURRAGE_HA*ASM_E23_YIELD_FOURRAGE_T_MS_HA -> 360 | H32: =ASM_A01_N_FARMS*ASM_E22_SURFACE_FOURRAGE_HA*ASM_E23_YIELD_FOURRAGE_T_MS_HA -> 360 | I32: =ASM_A01_N_FARMS*ASM_E22_SURFACE_FOURRAGE_HA*ASM_E23_YIELD_FOURRAGE_T_MS_HA -> 360 | J32: =ASM_A01_N_FARMS*ASM_E22_SURFACE_FOURRAGE_HA*ASM_E23_YIELD_FOURRAGE_T_MS_HA -> 360 | K32: =ASM_A01_N_FARMS*ASM_E22_SURFACE_FOURRAGE_HA*ASM_E23_YIELD_FOURRAGE_T_MS_HA -> 360 | L32: =ASM_A01_N_FARMS*ASM_E22_SURFACE_FOURRAGE_HA*ASM_E23_YIELD_FOURRAGE_T_MS_HA -> 360
B33: Purchased deficit (t DM/yr) | C33: t MS | D33: =SUM(E33:L33) -> 2505.6 | E33: =MAX(0,E31-E32) -> 313.2 | F33: =MAX(0,F31-F32) -> 313.2 | G33: =MAX(0,G31-G32) -> 313.2 | H33: =MAX(0,H31-H32) -> 313.2 | I33: =MAX(0,I31-I32) -> 313.2 | J33: =MAX(0,J31-J32) -> 313.2 | K33: =MAX(0,K31-K32) -> 313.2 | L33: =MAX(0,L31-L32) -> 313.2
B34: Purchased feed (concentrate) | C34: €/an | D34: =SUM(E34:L34) -> 469230.55 | E34: =E33*$F$80*IF(E$4=ASM_A04_COD_YEAR,ASM_E20_RAMP_Y1_PCT,IF(E$4=ASM_A04_COD_YEAR+1,ASM_E21_RAMP_Y2_PCT,IF(E$4>ASM_A04_COD_YEAR+1,1,0))) -> 0 | F34: =F33*$F$80*IF(F$4=ASM_A04_COD_YEAR,ASM_E20_RAMP_Y1_PCT,IF(F$4=ASM_A04_COD_YEAR+1,ASM_E21_RAMP_Y2_PCT,IF(F$4>ASM_A04_COD_YEAR+1,1,0))) -> 0 | G34: =G33*$F$80*IF(G$4=ASM_A04_COD_YEAR,ASM_E20_RAMP_Y1_PCT,IF(G$4=ASM_A04_COD_YEAR+1,ASM_E21_RAMP_Y2_PCT,IF(G$4>ASM_A04_COD_YEAR+1,1,0))) -> 36445.091 | H34: =H33*$F$80*IF(H$4=ASM_A04_COD_YEAR,ASM_E20_RAMP_Y1_PCT,IF(H$4=ASM_A04_COD_YEAR+1,ASM_E21_RAMP_Y2_PCT,IF(H$4>ASM_A04_COD_YEAR+1,1,0))) -> 68334.545 | I34: =I33*$F$80*IF(I$4=ASM_A04_COD_YEAR,ASM_E20_RAMP_Y1_PCT,IF(I$4=ASM_A04_COD_YEAR+1,ASM_E21_RAMP_Y2_PCT,IF(I$4>ASM_A04_COD_YEAR+1,1,0))) -> 91112.727 | J34: =J33*$F$80*IF(J$4=ASM_A04_COD_YEAR,ASM_E20_RAMP_Y1_PCT,IF(J$4=ASM_A04_COD_YEAR+1,ASM_E21_RAMP_Y2_PCT,IF(J$4>ASM_A04_COD_YEAR+1,1,0))) -> 91112.727 | K34: =K33*$F$80*IF(K$4=ASM_A04_COD_YEAR,ASM_E20_RAMP_Y1_PCT,IF(K$4=ASM_A04_COD_YEAR+1,ASM_E21_RAMP_Y2_PCT,IF(K$4>ASM_A04_COD_YEAR+1,1,0))) -> 91112.727 | L34: =L33*$F$80*IF(L$4=ASM_A04_COD_YEAR,ASM_E20_RAMP_Y1_PCT,IF(L$4=ASM_A04_COD_YEAR+1,ASM_E21_RAMP_Y2_PCT,IF(L$4>ASM_A04_COD_YEAR+1,1,0))) -> 91112.727
B35: Animal health / veterinary | C35: €/an | D35: =SUM(E35:L35) -> 162225 | E35: =ASM_A01_N_FARMS*(ASM_E08_N_COWS_DAIRY_PER_FARM*ASM_P09_COST_VET_DAIRY_EUR_HEAD_YR+ASM_E10_N_BEEF_STOCK_PER_FARM*ASM_P10_COST_VET_BEEF_EUR_HEAD_YR)*IF(E$4=ASM_A04_COD_YEAR,ASM_E20_RAMP_Y1_PCT,IF(E$4=ASM_A04_COD_YEAR+1,ASM_E21_RAMP_Y2_PCT,IF(E$4>ASM_A04_COD_YEAR+1,1,0))) -> 0 | F35: =ASM_A01_N_FARMS*(ASM_E08_N_COWS_DAIRY_PER_FARM*ASM_P09_COST_VET_DAIRY_EUR_HEAD_YR+ASM_E10_N_BEEF_STOCK_PER_FARM*ASM_P10_COST_VET_BEEF_EUR_HEAD_YR)*IF(F$4=ASM_A04_COD_YEAR,ASM_E20_RAMP_Y1_PCT,IF(F$4=ASM_A04_COD_YEAR+1,ASM_E21_RAMP_Y2_PCT,IF(F$4>ASM_A04_COD_YEAR+1,1,0))) -> 0 | G35: =ASM_A01_N_FARMS*(ASM_E08_N_COWS_DAIRY_PER_FARM*ASM_P09_COST_VET_DAIRY_EUR_HEAD_YR+ASM_E10_N_BEEF_STOCK_PER_FARM*ASM_P10_COST_VET_BEEF_EUR_HEAD_YR)*IF(G$4=ASM_A04_COD_YEAR,ASM_E20_RAMP_Y1_PCT,IF(G$4=ASM_A04_COD_YEAR+1,ASM_E21_RAMP_Y2_PCT,IF(G$4>ASM_A04_COD_YEAR+1,1,0))) -> 12600 | H35: =ASM_A01_N_FARMS*(ASM_E08_N_COWS_DAIRY_PER_FARM*ASM_P09_COST_VET_DAIRY_EUR_HEAD_YR+ASM_E10_N_BEEF_STOCK_PER_FARM*ASM_P10_COST_VET_BEEF_EUR_HEAD_YR)*IF(H$4=ASM_A04_COD_YEAR,ASM_E20_RAMP_Y1_PCT,IF(H$4=ASM_A04_COD_YEAR+1,ASM_E21_RAMP_Y2_PCT,IF(H$4>ASM_A04_COD_YEAR+1,1,0))) -> 23625 | I35: =ASM_A01_N_FARMS*(ASM_E08_N_COWS_DAIRY_PER_FARM*ASM_P09_COST_VET_DAIRY_EUR_HEAD_YR+ASM_E10_N_BEEF_STOCK_PER_FARM*ASM_P10_COST_VET_BEEF_EUR_HEAD_YR)*IF(I$4=ASM_A04_COD_YEAR,ASM_E20_RAMP_Y1_PCT,IF(I$4=ASM_A04_COD_YEAR+1,ASM_E21_RAMP_Y2_PCT,IF(I$4>ASM_A04_COD_YEAR+1,1,0))) -> 31500 | J35: =ASM_A01_N_FARMS*(ASM_E08_N_COWS_DAIRY_PER_FARM*ASM_P09_COST_VET_DAIRY_EUR_HEAD_YR+ASM_E10_N_BEEF_STOCK_PER_FARM*ASM_P10_COST_VET_BEEF_EUR_HEAD_YR)*IF(J$4=ASM_A04_COD_YEAR,ASM_E20_RAMP_Y1_PCT,IF(J$4=ASM_A04_COD_YEAR+1,ASM_E21_RAMP_Y2_PCT,IF(J$4>ASM_A04_COD_YEAR+1,1,0))) -> 31500 | K35: =ASM_A01_N_FARMS*(ASM_E08_N_COWS_DAIRY_PER_FARM*ASM_P09_COST_VET_DAIRY_EUR_HEAD_YR+ASM_E10_N_BEEF_STOCK_PER_FARM*ASM_P10_COST_VET_BEEF_EUR_HEAD_YR)*IF(K$4=ASM_A04_COD_YEAR,ASM_E20_RAMP_Y1_PCT,IF(K$4=ASM_A04_COD_YEAR+1,ASM_E21_RAMP_Y2_PCT,IF(K$4>ASM_A04_COD_YEAR+1,1,0))) -> 31500 | L35: =ASM_A01_N_FARMS*(ASM_E08_N_COWS_DAIRY_PER_FARM*ASM_P09_COST_VET_DAIRY_EUR_HEAD_YR+ASM_E10_N_BEEF_STOCK_PER_FARM*ASM_P10_COST_VET_BEEF_EUR_HEAD_YR)*IF(L$4=ASM_A04_COD_YEAR,ASM_E20_RAMP_Y1_PCT,IF(L$4=ASM_A04_COD_YEAR+1,ASM_E21_RAMP_Y2_PCT,IF(L$4>ASM_A04_COD_YEAR+1,1,0))) -> 31500
B36: Dairy insemination | C36: €/an | D36: =SUM(E36:L36) -> 46350 | E36: =ASM_A01_N_FARMS*ASM_E08_N_COWS_DAIRY_PER_FARM*ASM_P11_COST_INSEM_EUR_COW_YR*IF(E$4=ASM_A04_COD_YEAR,ASM_E20_RAMP_Y1_PCT,IF(E$4=ASM_A04_COD_YEAR+1,ASM_E21_RAMP_Y2_PCT,IF(E$4>ASM_A04_COD_YEAR+1,1,0))) -> 0 | F36: =ASM_A01_N_FARMS*ASM_E08_N_COWS_DAIRY_PER_FARM*ASM_P11_COST_INSEM_EUR_COW_YR*IF(F$4=ASM_A04_COD_YEAR,ASM_E20_RAMP_Y1_PCT,IF(F$4=ASM_A04_COD_YEAR+1,ASM_E21_RAMP_Y2_PCT,IF(F$4>ASM_A04_COD_YEAR+1,1,0))) -> 0 | G36: =ASM_A01_N_FARMS*ASM_E08_N_COWS_DAIRY_PER_FARM*ASM_P11_COST_INSEM_EUR_COW_YR*IF(G$4=ASM_A04_COD_YEAR,ASM_E20_RAMP_Y1_PCT,IF(G$4=ASM_A04_COD_YEAR+1,ASM_E21_RAMP_Y2_PCT,IF(G$4>ASM_A04_COD_YEAR+1,1,0))) -> 3600 | H36: =ASM_A01_N_FARMS*ASM_E08_N_COWS_DAIRY_PER_FARM*ASM_P11_COST_INSEM_EUR_COW_YR*IF(H$4=ASM_A04_COD_YEAR,ASM_E20_RAMP_Y1_PCT,IF(H$4=ASM_A04_COD_YEAR+1,ASM_E21_RAMP_Y2_PCT,IF(H$4>ASM_A04_COD_YEAR+1,1,0))) -> 6750 | I36: =ASM_A01_N_FARMS*ASM_E08_N_COWS_DAIRY_PER_FARM*ASM_P11_COST_INSEM_EUR_COW_YR*IF(I$4=ASM_A04_COD_YEAR,ASM_E20_RAMP_Y1_PCT,IF(I$4=ASM_A04_COD_YEAR+1,ASM_E21_RAMP_Y2_PCT,IF(I$4>ASM_A04_COD_YEAR+1,1,0))) -> 9000 | J36: =ASM_A01_N_FARMS*ASM_E08_N_COWS_DAIRY_PER_FARM*ASM_P11_COST_INSEM_EUR_COW_YR*IF(J$4=ASM_A04_COD_YEAR,ASM_E20_RAMP_Y1_PCT,IF(J$4=ASM_A04_COD_YEAR+1,ASM_E21_RAMP_Y2_PCT,IF(J$4>ASM_A04_COD_YEAR+1,1,0))) -> 9000 | K36: =ASM_A01_N_FARMS*ASM_E08_N_COWS_DAIRY_PER_FARM*ASM_P11_COST_INSEM_EUR_COW_YR*IF(K$4=ASM_A04_COD_YEAR,ASM_E20_RAMP_Y1_PCT,IF(K$4=ASM_A04_COD_YEAR+1,ASM_E21_RAMP_Y2_PCT,IF(K$4>ASM_A04_COD_YEAR+1,1,0))) -> 9000 | L36: =ASM_A01_N_FARMS*ASM_E08_N_COWS_DAIRY_PER_FARM*ASM_P11_COST_INSEM_EUR_COW_YR*IF(L$4=ASM_A04_COD_YEAR,ASM_E20_RAMP_Y1_PCT,IF(L$4=ASM_A04_COD_YEAR+1,ASM_E21_RAMP_Y2_PCT,IF(L$4>ASM_A04_COD_YEAR+1,1,0))) -> 9000
B37: Achat cheptel embouche (renouvellement) | C37: €/an | D37: =SUM(E37:L37) -> 185400 | E37: =ASM_A01_N_FARMS*ASM_E10_N_BEEF_STOCK_PER_FARM*ASM_E11_OFFTAKE_RATE_BEEF*ASM_P14_COST_CALF_PURCHASE_EUR_HEAD*IF(E$4=ASM_A04_COD_YEAR,ASM_E20_RAMP_Y1_PCT,IF(E$4=ASM_A04_COD_YEAR+1,ASM_E21_RAMP_Y2_PCT,IF(E$4>ASM_A04_COD_YEAR+1,1,0))) -> 0 | F37: =ASM_A01_N_FARMS*ASM_E10_N_BEEF_STOCK_PER_FARM*ASM_E11_OFFTAKE_RATE_BEEF*ASM_P14_COST_CALF_PURCHASE_EUR_HEAD*IF(F$4=ASM_A04_COD_YEAR,ASM_E20_RAMP_Y1_PCT,IF(F$4=ASM_A04_COD_YEAR+1,ASM_E21_RAMP_Y2_PCT,IF(F$4>ASM_A04_COD_YEAR+1,1,0))) -> 0 | G37: =ASM_A01_N_FARMS*ASM_E10_N_BEEF_STOCK_PER_FARM*ASM_E11_OFFTAKE_RATE_BEEF*ASM_P14_COST_CALF_PURCHASE_EUR_HEAD*IF(G$4=ASM_A04_COD_YEAR,ASM_E20_RAMP_Y1_PCT,IF(G$4=ASM_A04_COD_YEAR+1,ASM_E21_RAMP_Y2_PCT,IF(G$4>ASM_A04_COD_YEAR+1,1,0))) -> 14400 | H37: =ASM_A01_N_FARMS*ASM_E10_N_BEEF_STOCK_PER_FARM*ASM_E11_OFFTAKE_RATE_BEEF*ASM_P14_COST_CALF_PURCHASE_EUR_HEAD*IF(H$4=ASM_A04_COD_YEAR,ASM_E20_RAMP_Y1_PCT,IF(H$4=ASM_A04_COD_YEAR+1,ASM_E21_RAMP_Y2_PCT,IF(H$4>ASM_A04_COD_YEAR+1,1,0))) -> 27000 | I37: =ASM_A01_N_FARMS*ASM_E10_N_BEEF_STOCK_PER_FARM*ASM_E11_OFFTAKE_RATE_BEEF*ASM_P14_COST_CALF_PURCHASE_EUR_HEAD*IF(I$4=ASM_A04_COD_YEAR,ASM_E20_RAMP_Y1_PCT,IF(I$4=ASM_A04_COD_YEAR+1,ASM_E21_RAMP_Y2_PCT,IF(I$4>ASM_A04_COD_YEAR+1,1,0))) -> 36000 | J37: =ASM_A01_N_FARMS*ASM_E10_N_BEEF_STOCK_PER_FARM*ASM_E11_OFFTAKE_RATE_BEEF*ASM_P14_COST_CALF_PURCHASE_EUR_HEAD*IF(J$4=ASM_A04_COD_YEAR,ASM_E20_RAMP_Y1_PCT,IF(J$4=ASM_A04_COD_YEAR+1,ASM_E21_RAMP_Y2_PCT,IF(J$4>ASM_A04_COD_YEAR+1,1,0))) -> 36000 | K37: =ASM_A01_N_FARMS*ASM_E10_N_BEEF_STOCK_PER_FARM*ASM_E11_OFFTAKE_RATE_BEEF*ASM_P14_COST_CALF_PURCHASE_EUR_HEAD*IF(K$4=ASM_A04_COD_YEAR,ASM_E20_RAMP_Y1_PCT,IF(K$4=ASM_A04_COD_YEAR+1,ASM_E21_RAMP_Y2_PCT,IF(K$4>ASM_A04_COD_YEAR+1,1,0))) -> 36000 | L37: =ASM_A01_N_FARMS*ASM_E10_N_BEEF_STOCK_PER_FARM*ASM_E11_OFFTAKE_RATE_BEEF*ASM_P14_COST_CALF_PURCHASE_EUR_HEAD*IF(L$4=ASM_A04_COD_YEAR,ASM_E20_RAMP_Y1_PCT,IF(L$4=ASM_A04_COD_YEAR+1,ASM_E21_RAMP_Y2_PCT,IF(L$4>ASM_A04_COD_YEAR+1,1,0))) -> 36000
B38: Managers / supervisors | C38: €/an | D38: =SUM(E38:L38) -> 270000 | E38: =ASM_A01_N_FARMS*ASM_P12_N_FARM_MANAGERS*ASM_P13_COST_FARM_MANAGER_EUR_YR*FLAG_POST_COD_YM1 -> 0 | F38: =ASM_A01_N_FARMS*ASM_P12_N_FARM_MANAGERS*ASM_P13_COST_FARM_MANAGER_EUR_YR*FLAG_POST_COD_Y0 -> 0 | G38: =ASM_A01_N_FARMS*ASM_P12_N_FARM_MANAGERS*ASM_P13_COST_FARM_MANAGER_EUR_YR*FLAG_POST_COD_Y1 -> 45000 | H38: =ASM_A01_N_FARMS*ASM_P12_N_FARM_MANAGERS*ASM_P13_COST_FARM_MANAGER_EUR_YR*FLAG_POST_COD_Y2 -> 45000 | I38: =ASM_A01_N_FARMS*ASM_P12_N_FARM_MANAGERS*ASM_P13_COST_FARM_MANAGER_EUR_YR*FLAG_POST_COD_Y3 -> 45000 | J38: =ASM_A01_N_FARMS*ASM_P12_N_FARM_MANAGERS*ASM_P13_COST_FARM_MANAGER_EUR_YR*FLAG_POST_COD_Y4 -> 45000 | K38: =ASM_A01_N_FARMS*ASM_P12_N_FARM_MANAGERS*ASM_P13_COST_FARM_MANAGER_EUR_YR*FLAG_POST_COD_Y5 -> 45000 | L38: =ASM_A01_N_FARMS*ASM_P12_N_FARM_MANAGERS*ASM_P13_COST_FARM_MANAGER_EUR_YR*FLAG_POST_COD_Y6 -> 45000
