Workbook
Name Début_Prêt: '[1]Plan d''amortissement'!$D$9
Name Dernière_Ligne: IF('CA Agriculture'!Valeurs_Entrées,Ligne_EnTête+'CA Agriculture'!Nbre_de_Paiements,Ligne_EnTête)
Name Dernière_Ligne: IF('Matière 1é & fourni Agriculture'!Valeurs_Entrées,Ligne_EnTête+'Matière 1é & fourni Agriculture'!Nbre_de_Paiements,Ligne_EnTête)
Name Dernière_Ligne: IF(Valeurs_Entrées,Ligne_EnTête+Nbre_de_Paiements,Ligne_EnTête)
Name Durée_Prêt: '[1]Plan d''amortissement'!$D$7
Name Ent: #REF!
Name Ligne_EnTête: ROW('[1]Plan d''amortissement'!$17:$17)
Name Montant_Prêt: '[1]Plan d''amortissement'!$D$5
Name Nbre_de_Paiements: MATCH(0.01,Solde_Final,-1)+1
Name Nbre_de_Paiements: MATCH(0.01,Solde_Final,-1)+1
Name Nbre_de_Paiements: MATCH(0.01,Solde_Final,-1)+1
Name Nbre_Pmt: #REF!
Name Nbre_Pmt_Par_An: #REF!
Name Nbre_Pmt_Par_An: #REF!
Name Pmt_Mensuel_Programmé: #REF!
Name Pmt_Mensuel_Programmé: #REF!
Name Pmt_Programmé: #REF!
Name Pmt_Programmé: #REF!
Name Pmt_Supplémentaire: #REF!
Name Pmt_Supplémentaire: #REF!
Name Pmt_Total: #REF!
Name Pmt_Total: #REF!
Name Pmts_Supplémentaires_Programmés: #REF!
Name Pmts_Supplémentaires_Programmés: #REF!
Name Princ: #REF!
Name Princ: #REF!
Name Solde_Départ: #REF!
Name Solde_Départ: #REF!
Name Solde_Final: '[1]Plan d''amortissement'!$I$18:$I$497
Name Taux_Intérêt: '[1]Plan d''amortissement'!$D$6
Name Valeurs_Entrées: IF(Montant_Prêt*Taux_Intérêt*Durée_Prêt*Début_Prêt>0,1,0)
Name Valeurs_Entrées: IF(Montant_Prêt*Taux_Intérêt*Durée_Prêt*Début_Prêt>0,1,0)
Name Valeurs_Entrées: IF(Montant_Prêt*Taux_Intérêt*Durée_Prêt*Début_Prêt>0,1,0)

Sheet Amenag, Infrastr et Equipemt 
B3: AMENAGEMENTS & CONSTRUCTIONS - Bureau cooperative pour 10 unités de 100 ha | J3: EQUIPEMENTS & INFRASTRUCTURES COMMUNES POUR 10 UNITES DE 100 HA
B4: Nature | C4: Fonction | D4: Superficie | E4: Coût unitaire | F4: Nombre | G4: Cout total | J4: LIBELLE | K4: FONCTION | L4: Coût unitaire | M4: Nombre | N4: Cout total
B5: Foncier | C5: Bureau de gestion pour les 10 CAP | D5: 1 Ha | E5: 1000000 | F5: 0 | G5: =+F5*E5 -> 0 | J5: INFRASTRUCTURES | K5: Tank de stockage et unité de maintenance | L5: 4000000 | M5: 1 | N5: =+M5*L5 -> 4000000
B6: Aménagement | C6: VRD & réseau Eau, Electricité | D6: 350 m² | E6: 3500000 | F6: 1 | G6: =+F6*E6 -> 3500000 | J6: EQUIPEMENTS | K6: Moissonneuses-batteuses | L6: 30000000 | M6: 1 | N6: =+M6*L6 -> 30000000
B7: Construction | C7: Bureau CAP | D7: 100 m² | E7: 18500000 | F7: 1 | G7: =SUM(E7)*F7 -> 18500000 | J7: EQUIPEMENTS | K7: Décorticeur d’arachide | L7: 15000000 | M7: 1 | N7: =+M7*L7 -> 15000000
B8: Entrepots | C8: Premier stockage | D8: 2000 m² | E8: 125000000 | F8: 0 | G8: =SUM(E8)*F8 -> 0 | J8: EQUIPEMENTS | K8: Planteur de pommes de terre | L8: 1500000 | M8: 2 | N8: =+M8*L8 -> 3000000
F9: TOTAL | G9: =+SUM(G2:G8) -> 22000000 | J9: EQUIPEMENTS | K9: Récolteuse de pommes de terre | L9: 1700000 | M9: 2 | N9: =+M9*L9 -> 3400000
M10: TOTAL | N10: =+SUM(N5:N7) -> 49000000
C11: valeur de prise en compte pour une unité coopérative 1/10 de la charge globale | F11: TOTAL | G11: =SUM(G9)/10 -> 2200000 | K11: valeur de prise en compte pour une unité coopérative 1/10 de la charge globale | M11: TOTAL | N11: =SUM(N10)/10 -> 4900000
B18: AMENAGEMENTS & CONSTRUCTIONS - CAP de 100 ha | J18: EQUIPEMENTS & INFRASTRUCTURES POUR L'UNITE DE 100 HA
B19: Nature | C19: Fonction | D19: Superficie | E19: Coût unitaire | F19: Nombre | G19: Cout total | J19: LIBELLE | K19: FONCTION | L19: Coût unitaire | M19: Nombre | N19: Cout total
B20: Foncier | C20: Mise à disposition du site d'exploitation (5 ha par coopérateur / 20 personnes) | D20: 100 Ha | E20: 1000000 | G20: =+F20*E20 -> 0 | J20: EQUIPEMENTS | K20: Tracteurs de grande taille 75 à 90 CV | L20: 12000000 | M20: 1 | N20: =+M20*L20 -> 12000000
B21: Cartographie | C21: Délimitation et levé topographique du terrain | D21: 100 Ha | E21: 67000 | F21: 100 | G21: =+F21*E21 -> 6700000 | J21: EQUIPEMENTS | K21: Tracteurs de petite taille 40 à 45 HP | L21: 7000000 | M21: 1 | N21: =+M21*L21 -> 7000000
B22: Cloture | C22: Clôture du site grillage et piquets métalliques | D22: 4000 ml | E22: 8500 | F22: 4000 | G22: =+F22*E22 -> 34000000 | J22: EQUIPEMENTS | K22: Charrue Ripper/ Cultivateur / Charrue à disques / Rotavator | L22: 2000000 | M22: 2 | N22: =+M22*L22 -> 4000000
B23: Aménagement | C23: Aménagement hydroagricole (agroforesterie & haie vive) | D23: 5 Ha | E23: 1500000 | F23: 5 | G23: =+F23*E23 -> 7500000 | J23: EQUIPEMENTS | K23: Recoltant cueilleur / moissonneurs mixte | L23: 3000000 | M23: 1 | N23: =+M23*L23 -> 3000000
B24: Aménagement | C24: Aménagement hydroagricole (verger pour arbre fruitier) | D24: 5 Ha | E24: 2500000 | F24: 5 | G24: =+F24*E24 -> 12500000 | J24: EQUIPEMENTS | K24: Semoir à céréale / semoir petit grain mixte | L24: 3000000 | M24: 1 | N24: =+M24*L24 -> 3000000
B25: Aménagement | C25: Aménagement hydroagricole (irrigation pour culture de contre-saison) | D25: 15 Ha | E25: 4000000 | F25: 15 | G25: =+F25*E25 -> 60000000 | J25: INFRASTRUCTURES | K25: Puits tubulaires, y compris forage et pompes | L25: 10000000 | M25: 4 | N25: =+M25*L25 -> 40000000
B26: Aménagement | C26: Aménagement hydroagricole (irrigation pour culture fourragère) | D26: 10 Ha | E26: 3500000 | F26: 10 | G26: =+F26*E26 -> 35000000 | J26: INFRASTRUCTURES | K26: Panneaux solaires avec onduleur et batterie 25 KVA | L26: 6000000 | M26: 4 | N26: =+M26*L26 -> 24000000
B27: Aménagement | C27: Défrichage - débroussaillage, enlèvement de la masse racinaire | D27: 60 Ha | E27: 325000 | F27: 60 | G27: =+F27*E27 -> 19500000 | N27: =+M27*L27 -> 0
B28: Construction | C28: Première préparation (hangar et aire de stockage) | D28: 300 m² | E28: 65000 | F28: 200 | G28: =+F28*E28 -> 13000000
B29: Construction | C29: Magasin du groupement | D29: 100 m² | E29: 85000 | F29: 100 | G29: =+F29*E29 -> 8500000
B30: Construction | C30: local et petit bureau | D30: 70 m² | E30: 90000 | F30: 70 | G30: =+F30*E30 -> 6300000
F32: TOTAL | G32: =+SUM(G19:G31) -> 203000000 | M32: TOTAL | N32: =+SUM(N20:N30) -> 93000000
B36: AMENAGEMENTS & CONSTRUCTIONS - Volet élevage | J36: EQUIPEMENTS & INFRASTRUCTURES VOLET ELEVAGE
B37: Nature | C37: Fonction | D37: Superficie | E37: Coût unitaire | F37: Nombre | G37: Cout total | J37: LIBELLE | K37: FONCTION | L37: Coût unitaire | M37: Nombre | N37: Cout total
B38: Foncier | C38: Site d'élevage sous 4 formes (laitière, ambouche, pondeuse et chaire) | D38: 5 Ha | E38: 1000000 | G38: =+F38*E38 -> 0 | J38: INFRASTRUCTURES | K38: Aérateur et humidificateur d'air | L38: 5000000 | M38: 1 | N38: =+M38*L38 -> 5000000
B39: Aménagement | C39: VRD & réseau Eau, électricité | D39: FF | E39: 1500000 | F39: 4 | G39: =+F39*E39 -> 6000000 | J39: INFRASTRUCTURES | K39: Equipement réseau Eau & électricité | L39: 2500000 | M39: 4 | N39: =SUM(L39*M39) -> 10000000
B40: Construction | C40: Bâtiment d'élevage pour vache laitière | D40: 300 m² | E40: 65000 | F40: 300 | G40: =+F40*E40 -> 19500000 | J40: EQUIPEMENTS | K40: Equipements d'élevage pour vache laitière | L40: 8500000 | M40: 1 | N40: =+M40*L40 -> 8500000
B41: Construction | C41: Bâtiment d'élevage pour bovin d'ambouche | D41: 200 m² | E41: 45000 | F41: 200 | G41: =+F41*E41 -> 9000000 | J41: EQUIPEMENTS | K41: Equipements d'élevage pour bovin d'ambouche | L41: 5500000 | M41: 1 | N41: =+M41*L41 -> 5500000
B42: Construction | C42: Bâtiment d'élevage pour poule pondeuse | D42: 100 m² | E42: 65000 | F42: 100 | G42: =+F42*E42 -> 6500000 | J42: EQUIPEMENTS | K42: Equipements d'élevage pour poule pondeuse | L42: 3000000 | M42: 1 | N42: =SUM(L42*M42) -> 3000000
B43: Construction | C43: Bâtiment d'élevage pour poulet de chair | D43: 500 m² | E43: 45000 | F43: 100 | G43: =+F43*E43 -> 4500000 | J43: EQUIPEMENTS | K43: Equipements d'élevage pour poulet de chair | L43: 2000000 | M43: 1 | N43: =+M43*L43 -> 2000000
B44: Local | C44: locale pour équipement d'élevage | D44: 70 m² | E44: 90000 | F44: 70 | G44: =+F44*E44 -> 6300000 | J44: EQUIPEMENTS | K44: Divers équipement d'élevage | L44: 3000000 | M44: 1 | N44: =+M44*L44 -> 3000000
J45: INSTALLATION | K45: Déplacement de techniciens formation | L45: 5500000 | M45: 1 | N45: =SUM(L45*M45) -> 5500000
F46: TOTAL | G46: =+SUM(G37:G45) -> 51800000 | N46: =+M46*L46 -> 0
M47: TOTAL | N47: =+SUM(N38:N45) -> 42500000
C53: TOTAUX AMENAGEMENTS & CONSTRUCTIONS | K53: TOTAUX EQUIPEMENTS INDUSTRIELS
C54: Unité | D54: Montant | K54: Unité | L54: Montant
C55: CHARGES BUREAU DES COOPERATIVES 1/10 | D55: =SUM(G11) -> 2200000 | K55: EQUIPEMENTS & INFRASTRUCTURES COMMUNES POUR 10 UNITES DE 100 HA | L55: =SUM(N11) -> 4900000
C56: AMENAGEMENTS & CONSTRUCTION CAP 100 HA | D56: =+G32 -> 203000000 | K56: EQUIPEMENTS & INFRASTRUCTURES POUR L'UNITE DE 100 HA | L56: =+N32 -> 93000000
C57: AMENAGEMENTS & CONSTRUCTION VOLET ELEVAGE | D57: =+G46 -> 51800000 | K57: EQUIPEMENTS & INFRASTRUCTURES VOLET ELEVAGE | L57: =+N47 -> 42500000
G58: =SUM(D59+L59) -> 397400000
C59: TOTAUX | D59: =SUM(D55:D58) -> 257000000 | K59: TOTAUX | L59: =SUM(L55:L58) -> 140400000

Sheet Mat bureau & Mat roulants
C4: MATERIELS DE BUREAU - DIRECTION | I4: MOYENS ROULANTS - DIRECTION | O4: INFORMATIQUE DIRECTION GENERALE
C5: Désignation | D5: Unité | E5: Prix unitaire | F5: Prix total | I5: Désignation | J5: Unité | K5: Prix unitaire | L5: Prix total | O5: Désignation | P5: Unité | Q5: Prix unitaire | R5: Prix total
C6: Table de réunion | D6: 3 | E6: 250000 | F6: =+E6*D6 -> 750000 | I6: Véhicule Prado | J6: 0 | K6: 25000000 | L6: =+K6*J6 -> 0 | O6: Micro-ordinateurs | P6: 6 | Q6: 450000 | R6: =+Q6*P6 -> 2700000
C7: Chaise | D7: 12 | E7: 70000 | F7: =+E7*D7 -> 840000 | I7: Véhicule Pick Up (double cabine) | J7: 1 | K7: 19000000 | L7: =+K7*J7 -> 19000000 | O7: Imprimantes | P7: 3 | Q7: 250000 | R7: =+Q7*P7 -> 750000
C8: Bureau direction | D8: 1 | E8: 450000 | F8: =+E8*D8 -> 450000 | I8: Moto | J8: 4 | K8: 500000 | L8: =+K8*J8 -> 2000000 | O8: Autre scanner/photocopieurs | P8: 1 | Q8: 750000 | R8: =+Q8*P8 -> 750000
C9: Fauteuil direction | D9: 3 | E9: 150000 | F9: =+E9*D9 -> 450000 | I9: Camion de transport | J9: 0 | K9: 85000000 | L9: =+K9*J9 -> 0 | Q9: TOTAUX | R9: =+SUM(R5:R7) -> 3450000
C10: Bureau assistante | D10: 1 | E10: 150000 | F10: =+E10*D10 -> 150000 | I10: Porte - charge Manitou | J10: 0 | K10: 22000000 | L10: =+K10*J10 -> 0 | O10: La coopérative 1/10 de la charge globale | R10: =SUM(R9)/10 -> 345000
C11: Fauteuil | D11: 1 | E11: 70000 | F11: =+E11*D11 -> 70000 | K11: TOTAUX | L11: =SUM(L5:L10) -> 21000000
C12: Autre bureau | D12: 4 | E12: 150000 | F12: =+E12*D12 -> 600000 | I12: La coopérative 1/10 de la charge globale | L12: =SUM(L11)/10 -> 2100000
C13: Fauteuil | D13: 12 | E13: 70000 | F13: =+E13*D13 -> 840000
C14: Armoires | D14: 5 | E14: 175000 | F14: =+E14*D14 -> 875000
C15: Banc d'attente | D15: 3 | E15: 200000 | F15: =+E15*D15 -> 600000
C16: Autres matériels | D16: 1 | E16: 150000 | F16: =+E16*D16 -> 150000
E17: TOTAUX | F17: =+SUM(F5:F16) -> 5775000
C18: La coopérative 1/10 de la charge globale | F18: =SUM(F17)/10 -> 577500
C23: MATERIELS DE BUREAU - UNITE AGRICOLE | I23: MOYENS ROULANTS - UNITE AGRICOLE | O23: INFORMATIQUE UNITE AGRICOLE
C24: Désignation | D24: Unité | E24: Prix unitaire | F24: Prix total | I24: Désignation | J24: Unité | K24: Prix unitaire | L24: Prix total | O24: Désignation | P24: Unité | Q24: Prix unitaire | R24: Prix total
C25: Table de réunion | D25: 1 | E25: 250000 | F25: =+E25*D25 -> 250000 | I25: Véhicule Pick Up (double cabine) | J25: 0 | K25: 19000000 | L25: =+K25*J25 -> 0 | O25: Micro-ordinateurs | P25: 1 | Q25: 450000 | R25: =+Q25*P25 -> 450000
C26: Chaise | D26: 8 | E26: 70000 | F26: =+E26*D26 -> 560000 | I26: Camionnette de transport | J26: 0 | K26: 25000000 | L26: =+K26*J26 -> 0 | O26: Imprimantes | P26: 1 | Q26: 250000 | R26: =+Q26*P26 -> 250000
C27: Bureau Chef d'unité | D27: 1 | E27: 250000 | F27: =+E27*D27 -> 250000 | I27: Porte - charge tricycle | J27: 1 | K27: 850000 | L27: =+K27*J27 -> 850000 | O27: Autres photocopieurs | P27: 0 | Q27: 500000 | R27: =+Q27*P27 -> 0
C28: Fauteuil | D28: 3 | E28: 150000 | F28: =+E28*D28 -> 450000 | I28: Moto | J28: 1 | K28: 500000 | L28: =+K28*J28 -> 500000
C29: Bureau assistante | D29: 0 | E29: 150000 | F29: =+E29*D29 -> 0 | Q29: TOTAUX | R29: =+SUM(R25:R27) -> 700000
C30: Fauteuil | D30: 0 | E30: 70000 | F30: =+E30*D30 -> 0 | K30: TOTAUX | L30: =+SUM(L25:L28) -> 1350000
C31: Autre bureau | D31: 0 | E31: 150000 | F31: =+E31*D31 -> 0
C32: Fauteuil | D32: 0 | E32: 70000 | F32: =+E32*D32 -> 0
C33: Armoires | D33: 0 | E33: 175000 | F33: =+E33*D33 -> 0
C34: Banc d'attente | D34: 0 | E34: 200000 | F34: =+E34*D34 -> 0
C35: Autres matériels | D35: 0 | E35: 300000 | F35: =+E35*D35 -> 0
E37: TOTAUX | F37: =+SUM(F25:F36) -> 1510000
C42: MATERIELS DE BUREAU - UNITE ELEVAGE | I42: MOYENS ROULANTS - UNITE ELEVAGE | O42: INFORMATIQUE UNITE ELEVAGE
C43: Désignation | D43: Unité | E43: Prix unitaire | F43: Prix total | I43: Désignation | J43: Unité | K43: Prix unitaire | L43: Prix total | O43: Désignation | P43: Unité | Q43: Prix unitaire | R43: Prix total
C44: Table de réunion | D44: 1 | E44: 250000 | F44: =+E44*D44 -> 250000 | I44: Véhicule Pick Up (double cabine) | J44: 0 | K44: 19000000 | L44: =+K44*J44 -> 0 | O44: Micro-ordinateurs | P44: 1 | Q44: 450000 | R44: =+Q44*P44 -> 450000
C45: Chaise | D45: 8 | E45: 70000 | F45: =+E45*D45 -> 560000 | I45: Camionnette de transport | J45: 0 | K45: 25000000 | L45: =+K45*J45 -> 0 | O45: Imprimantes | P45: 1 | Q45: 250000 | R45: =+Q45*P45 -> 250000
C46: Bureau Chef d'unité | D46: 1 | E46: 250000 | F46: =+E46*D46 -> 250000 | I46: Porte - charge tricycle | J46: 1 | K46: 850000 | L46: =+K46*J46 -> 850000 | O46: Autres photocopieurs | P46: 0 | Q46: 500000 | R46: =+Q46*P46 -> 0
C47: Fauteuil | D47: 3 | E47: 150000 | F47: =+E47*D47 -> 450000 | I47: Moto | J47: 1 | K47: 500000 | L47: =+K47*J47 -> 500000
C48: Bureau assistante | D48: 0 | E48: 150000 | F48: =+E48*D48 -> 0 | Q48: TOTAUX | R48: =+SUM(R44:R46) -> 700000
C49: Fauteuil | D49: 0 | E49: 70000 | F49: =+E49*D49 -> 0 | K49: TOTAUX | L49: =+SUM(L44:L47) -> 1350000
C50: Autre bureau | D50: 0 | E50: 150000 | F50: =+E50*D50 -> 0
C51: Fauteuil | D51: 0 | E51: 70000 | F51: =+E51*D51 -> 0
C52: Armoires | D52: 0 | E52: 175000 | F52: =+E52*D52 -> 0
C53: Banc d'attente | D53: 0 | E53: 200000 | F53: =+E53*D53 -> 0
C54: Autres matériels | D54: 0 | E54: 300000 | F54: =+E54*D54 -> 0
E56: TOTAUX | F56: =+SUM(F44:F55) -> 1510000
C62: TOTAUX MATERIELS DE BUREAU | I62: TOTAUX MATERIELS ROULANTS | O62: TOTAUX MATERIELS INFORMATIQUES & REPROGRAPHIE
C63: DESIGNATION | F63: MONTANT | I63: DESIGNATION | L63: MONTANT | O63: DESIGNATION | R63: MONTANT
C64: =+C4 -> MATERIELS DE BUREAU - DIRECTION | F64: =+F18 -> 577500 | I64: =+I4 -> MOYENS ROULANTS - DIRECTION | L64: =+L12 -> 2100000 | O64: INFORMATIQUE DIRECTION | R64: =+R10 -> 345000
C65: =+C23 -> MATERIELS DE BUREAU - UNITE AGRICOLE | F65: =+F37 -> 1510000 | I65: =+I23 -> MOYENS ROULANTS - UNITE AGRICOLE | L65: =+L30 -> 1350000 | O65: INFORMATIQUE UNITE SESAME & ARACHIDE | R65: =+R29 -> 700000
C66: =+C42 -> MATERIELS DE BUREAU - UNITE ELEVAGE | F66: =SUM(F56) -> 1510000 | I66: =+I42 -> MOYENS ROULANTS - UNITE ELEVAGE | L66: =+L49 -> 1350000 | O66: INFORMATIQUE UNITE GOMME | R66: =+R48 -> 700000
E68: TOTAUX | F68: =+SUM(F64:F67) -> 3597500 | K68: TOTAUX | L68: =+SUM(L64:L67) -> 4800000 | Q68: TOTAUX | R68: =+SUM(R64:R67) -> 1745000
I76: =SUM(F68)+L68+R68 -> 10142500

Sheet Salaires & Avantages
B6: DIRECTION
B7: POSTE | C7: Effectif à terme | D7: Base de rémunération | F7: 2026 | G7: 2027 | H7: 2028 | I7: 2029 | J7: 2030
B8: Directeur | D8: Salaire | E8: 550000 | F8: =SUM(E8)*6 -> 3300000 | G8: =+E8*12 -> 6600000 | H8: =+G8*1.1 -> 7260000 | I8: =+H8*1.05 -> 7623000 | J8: =+I8*1 -> 7623000
C9: 1 | D9: Avantage | E9: 50000 | F9: =SUM(E9)*6 -> 300000 | G9: =+E9*12 -> 600000 | H9: =+G9*1.05 -> 630000 | I9: =+H9*1.05 -> 661500 | J9: =+I9*1 -> 661500
D10: Ch Sociale | E10: =+E8*20% -> 110000 | F10: =SUM(E10)*6 -> 660000 | G10: =+G8*20% -> 1320000 | H10: =+H8*20% -> 1452000 | I10: =+I8*20% -> 1524600 | J10: =+J8*20% -> 1524600
B11: Assistante de direction | D11: Salaire | E11: 150000 | F11: =SUM(E11)*6 -> 900000 | G11: =+E11*12 -> 1800000 | H11: =+G11*1.1 -> 1980000 | I11: =+H11*1.05 -> 2079000 | J11: =+I11*1 -> 2079000
C12: 1 | D12: Avantage | E12: 25000 | F12: =SUM(E12)*6 -> 150000 | G12: =+E12*12 -> 300000 | H12: =+G12*1.05 -> 315000 | I12: =+H12*1.05 -> 330750 | J12: =+I12*1 -> 330750
D13: Ch Sociale | E13: =+E11*20% -> 30000 | F13: =SUM(E13)*6 -> 180000 | G13: =+G11*20% -> 360000 | H13: =+H11*20% -> 396000 | I13: =+I11*20% -> 415800 | J13: =+J11*20% -> 415800
B14: Conseiller Action Solidaire (partiel) | D14: Salaire | E14: 150000 | I14: =SUM(E14)*12 -> 1800000 | J14: =+I14*1 -> 1800000
C15: 1 | D15: Avantage | E15: 25000 | I15: =SUM(E15)*12 -> 300000 | J15: =+I15*1 -> 300000
D16: Ch Sociale | E16: =+E14*20% -> 30000 | G16: =+G14*20% -> 0 | I16: =+I14*20% -> 360000 | J16: =+J14*20% -> 360000
B17: Chef département administration compta finances | D17: Salaire | E17: 350000 | G17: =+E17*6 -> 2100000 | H17: =+E17*12*1.1 -> 4620000 | I17: =+H17*1.05 -> 4851000 | J17: =+I17*1 -> 4851000
C18: 1 | D18: Avantage | E18: 25000 | G18: =+E18*6 -> 150000 | H18: =+E18*12*1.05 -> 315000 | I18: =+H18*1.05 -> 330750 | J18: =+I18*1 -> 330750
D19: Ch Sociale | E19: =+E17*20% -> 70000 | G19: =+G17*20% -> 420000 | H19: =+H17*20% -> 924000 | I19: =+I17*20% -> 970200 | J19: =+J17*20% -> 970200
B20: Comptable | D20: Salaire | E20: 250000 | F20: =SUM(E20)*12 -> 3000000 | G20: =+E20*12 -> 3000000 | H20: =+E20*12*1.1 -> 3300000 | I20: =+H20*1.05 -> 3465000 | J20: =+I20*1 -> 3465000
C21: 1 | D21: Avantage | E21: 25000 | F21: =SUM(E21)*6 -> 150000 | G21: =+E21*12 -> 300000 | H21: =+E21*1.05*12 -> 315000 | I21: =+H21*1.05 -> 330750 | J21: =+I21*1 -> 330750
D22: Ch Sociale | E22: =+E20*20% -> 50000 | F22: =SUM(F20)*0.2 -> 600000 | G22: =+G20*20% -> 600000 | H22: =+H20*20% -> 660000 | I22: =+I20*20% -> 693000 | J22: =+J20*20% -> 693000
B23: Resp Ressources humaines & Matériels | D23: Salaire | E23: 200000 | G23: =+E23*6 -> 1200000 | H23: =+E23*12*1.1 -> 2640000 | I23: =+H23*1.05 -> 2772000 | J23: =+I23*1 -> 2772000
C24: 1 | D24: Avantage | E24: 25000 | G24: =+E24*6 -> 150000 | H24: =+E24*12*1.05 -> 315000 | I24: =+H24*1.05 -> 330750 | J24: =+I24*1 -> 330750
D25: Ch Sociale | E25: =+E23*20% -> 40000 | G25: =+G23*20% -> 240000 | H25: =+H23*20% -> 528000 | I25: =+I23*20% -> 554400 | J25: =+J23*20% -> 554400
B26: Chef de département production | D26: Salaire | E26: 250000 | G26: =+E26*6 -> 1500000 | H26: =+E26*12 -> 3000000 | I26: =+H26*1.05 -> 3150000 | J26: =+I26*1 -> 3150000
C27: 1 | D27: Avantage | E27: 25000 | G27: =+E27*6 -> 150000 | H27: =+E27*12 -> 300000 | I27: =+H27*1.05 -> 315000 | J27: =+I27*1 -> 315000
D28: Ch Sociale | E28: =+E26*20% -> 50000 | G28: =+G26*20% -> 300000 | H28: =+H26*20% -> 600000 | I28: =+I26*20% -> 630000 | J28: =+J26*20% -> 630000
B29: Responsable approvisionnement | D29: Salaire | E29: 200000 | H29: =+E29*12*1.1 -> 2640000 | I29: =+H29*1.05 -> 2772000 | J29: =+I29*1 -> 2772000
C30: 1 | D30: Avantage | E30: 25000 | H30: =+E30*12*1.05 -> 315000 | I30: =+H30*1.05 -> 330750 | J30: =+I30*1 -> 330750
D31: Ch Sociale | E31: =+E29*20% -> 40000 | H31: =+H29*20% -> 528000 | I31: =+I29*20% -> 554400 | J31: =+J29*20% -> 554400
B32: Responsable Maintenance technique | D32: Salaire | E32: 200000 | H32: =+E32*12 -> 2400000 | I32: =+H32*1.05 -> 2520000 | J32: =+I32*1 -> 2520000
C33: 1 | D33: Avantage | E33: 25000 | H33: =+E33*12 -> 300000 | I33: =+H33*1.05 -> 315000 | J33: =+I33*1 -> 315000
D34: Ch Sociale | E34: =+E32*20% -> 40000 | G34: =+G32*20% -> 0 | H34: =+H32*20% -> 480000 | I34: =+I32*20% -> 504000 | J34: =+J32*20% -> 504000
B35: Chauffeur | D35: Salaire | E35: 120000 | F35: =SUM(E35)*C36*12 -> 1440000 | G35: =+E35*12*C36 -> 1440000 | H35: =+E35*12*C36*1.1 -> 1584000 | I35: =+H35*1.05 -> 1663200 | J35: =+I35*1 -> 1663200
C36: 1 | D36: Avantage | E36: 15000 | F36: =SUM(E36)*12 -> 180000 | G36: =+E36*12*C36 -> 180000 | H36: =+E36*12*C36*1.05 -> 189000 | I36: =+H36*1.05 -> 198450 | J36: =+I36*1 -> 198450
D37: Ch Sociale | E37: =+E35*20% -> 24000 | F37: =SUM(F35)*0.2 -> 288000 | G37: =+G35*20% -> 288000 | H37: =+H35*20% -> 316800 | I37: =+I35*20% -> 332640 | J37: =+J35*20% -> 332640
B38: Planton coursier | D38: Salaire | E38: 90000 | G38: =+E38*12*C39 -> 1080000 | H38: =+E38*12*C39*1.5 -> 1620000 | I38: =+H38*1.05 -> 1701000 | J38: =+I38*1 -> 1701000
C39: 1 | D39: Avantage | E39: 15000 | G39: =+E39*C39*12 -> 180000 | H39: =+E39*C39*12*1.05 -> 189000 | I39: =+H39*1.05 -> 198450 | J39: =+I39*1 -> 198450
D40: Ch Sociale | E40: =+E38*20% -> 18000 | G40: =+G38*20% -> 216000 | H40: =+H38*20% -> 324000 | I40: =+I38*20% -> 340200 | J40: =+J38*20% -> 340200
B41: Nettoyage ménage & jardinier | D41: Salaire | E41: 75000 | G41: =+E41*C42*12 -> 1800000 | H41: =+E41*12*C42*1.1 -> 1980000 | I41: =+H41*1.05 -> 2079000 | J41: =+I41*1 -> 2079000
C42: 2 | D42: Avantage | E42: 10000 | G42: =+E42*C42*12 -> 240000 | H42: =+E42*C42*12*1.05 -> 252000 | I42: =+H42*1.05 -> 264600 | J42: =+I42*1 -> 264600
D43: Ch Sociale | E43: =+E41*20% -> 15000 | G43: =+G41*20% -> 360000 | H43: =+H41*20% -> 396000 | I43: =+I41*20% -> 415800 | J43: =+J41*20% -> 415800
B44: Gardien/ Sécurité | D44: Salaire | E44: 70000 | F44: =SUM(E44)*12 -> 840000 | G44: =+E44*C45*12 -> 1680000 | H44: =+E44*12*C45*1.1 -> 1848000 | I44: =+H44*1.05 -> 1940400 | J44: =+I44*1 -> 1940400
C45: 2 | D45: Avantage | E45: 10000 | F45: =SUM(E45)*12 -> 120000 | G45: =+E45*12*C45 -> 240000 | H45: =+E45*12*C45*1.05 -> 252000 | I45: =+H45*1.05 -> 264600 | J45: =+I45*1 -> 264600
D46: Ch Sociale | E46: =+E44*20% -> 14000 | F46: =SUM(F44)*0.2 -> 168000 | G46: =+G44*20% -> 336000 | H46: =+H44*20% -> 369600 | I46: =+I44*20% -> 388080 | J46: =+J44*20% -> 388080
B48: EFFECTIF A TERME | C48: =+SUM(C8:C47) -> 15
B49: TOTAUX SALAIRES DE BASE | F49: =SUM(F8)+F11+F20+F35+F44 -> 9480000 | G49: =SUM(G8)+G11+G17+G23+G26+G26+G35+G41+G44 -> 19620000 | H49: =SUM(H8+H11+H17+H23+H29+H35+H38+H41+H44) -> 26172000 | I49: =SUM(I8+I11+I14+I17+I20+I23+I26+I29+I32+I35+I38+I44+I41) -> 38415600 | J49: =SUM(J8+J11+J14+J17+J20+J23+J26+J29+J32+J35+J38+J41+J44) -> 38415600
B50: TOTAUX AVANTAGES | F50: =SUM(F9)+F12+F21+F36+F45 -> 900000 | G50: =SUM(G9+G12+G18+G24+G27+G36+G39+G42+G45) -> 2190000 | H50: =SUM(H9+H12+H18+H21+H24+H27+H30+H33+H36+H39+H42+H45) -> 3687000 | I50: =SUM(I9+I12+I15+I18+I21+I24+I27+I30+I33+I36+I39+I42+I45) -> 4171350 | J50: =SUM(J9+J12+J15+J18+J21+J24+J27+J30+J30+J33+J36+J39+J42+J45) -> 4502100
B51: TOTALES CHARGES SOCIALES | F51: =SUM(F34+F31+F28+F22+F13+F10)+F46 -> 1608000 | G51: =SUM(G10+G13+G19+G22+G25+G28+G37+G40+G43+G46) -> 4440000 | H51: =SUM(H10+H13+H19+H22+H25+H28+H31+H34+H37+H40+H43+H46) -> 6974400 | I51: =SUM(I10+I13+I16+I19+I22+I25+I28+I31+I34+I37+I43+I46) -> 7342920 | J51: =SUM(J10+J13+J16+J19+J22+J25+J28+J31+J34+J37+J40+J43+J46) -> 7683120
B52: TOTALES CHARGES SALARIALES | F52: =SUM(F49:F51) -> 11988000 | G52: =+G51+G50+G49 -> 26250000 | H52: =+H51+H50+H49 -> 36833400 | I52: =+I51+I50+I49 -> 49929870 | J52: =+J51+J50+J49 -> 50600820
C53: La coopérative 1/10 de la charge globale | F53: =SUM(F52)/10 -> 1198800 | G53: =SUM(G52)/10 -> 2625000 | H53: =SUM(H52)/10 -> 3683340 | I53: =SUM(I52)/10 -> 4992987 | J53: =SUM(J52)/10 -> 5060082
B58: UNITE AGRICULTURE
B59: POSTE | C59: Effectif à terme | D59: Base de rémunération | F59: 2026 | G59: 2027 | H59: 2028 | I59: 2029 | J59: 2030
B60: Chef d'unité (y compris activités administratives) | D60: Salaire | E60: 225000 | F60: =+E60*12*1 -> 2700000 | G60: =+E60*12*1 -> 2700000 | H60: =+E60*12*1 -> 2700000 | I60: =+H60*1.05 -> 2835000 | J60: =+I60*1 -> 2835000
C61: 1 | D61: Avantage | E61: 25000 | F61: =SUM(C61)*E61*12 -> 300000 | G61: =SUM(E61)*12 -> 300000 | H61: =+E61*12*1 -> 300000 | I61: =+H61*1.05 -> 315000 | J61: =+I61*1 -> 315000
D62: Ch Sociale | E62: =+E60*20% -> 45000 | F62: =SUM(F60)*0.2 -> 540000 | G62: =SUM(G60)*0.2 -> 540000 | H62: =+H60*20% -> 540000 | I62: =+I60*20% -> 567000 | J62: =+J60*20% -> 567000
B63: Responsable de production agricole | D63: Salaire | E63: 215000 | F63: =SUM(E63)*12 -> 2580000 | G63: =+E63*12 -> 2580000 | H63: =+E63*12*1 -> 2580000 | I63: =+H63*1.05 -> 2709000 | J63: =+I63*1 -> 2709000
C64: 1 | D64: Avantage | E64: 20000 | F64: =SUM(E64)*12 -> 240000 | G64: =+E64*6 -> 120000 | H64: =+E64*12*1 -> 240000 | I64: =+H64*1.05 -> 252000 | J64: =+I64*1 -> 252000
D65: Ch Sociale | E65: =+E63*20% -> 43000 | F65: =SUM(F63)*0.2 -> 516000 | G65: =+G63*20% -> 516000 | H65: =+H63*20% -> 516000 | I65: =+I63*20% -> 541800 | J65: =+J63*20% -> 541800
B66: Technicien production / opérateur engin | D66: Salaire | E66: 205000 | H66: =+E66*12*C67*1 -> 4920000 | I66: =+H66*1.05 -> 5166000 | J66: =+I66*1 -> 5166000
C67: 2 | D67: Avantage | E67: 15000 | H67: =+E67*C67*1*12 -> 360000 | I67: =+H67*1.05 -> 378000 | J67: =+I67*1 -> 378000
D68: Ch Sociale | E68: =+E66*20% -> 41000 | H68: =+H66*20% -> 984000 | I68: =+I66*20% -> 1033200 | J68: =+J66*20% -> 1033200
B69: Magasinier | D69: Salaire | E69: 190000 | G69: =+E69*C70*8 -> 1520000 | H69: =+E69*C70*12*1 -> 2280000 | I69: =+H69*1.05 -> 2394000 | J69: =+I69*1 -> 2394000
C70: 1 | D70: Avantage | E70: 15000 | G70: =+E70*C70*8 -> 120000 | H70: =+E70*1*12 -> 180000 | I70: =+H70*1.05 -> 189000 | J70: =+I70*1 -> 189000
D71: Ch Sociale | E71: =+E69*20% -> 38000 | G71: =+G69*20% -> 304000 | H71: =+H69*20% -> 456000 | I71: =+I69*20% -> 478800 | J71: =+J69*20% -> 478800
B72: Secrétaire comptable | D72: Salaire | E72: 125000 | H72: =+E72*1*12 -> 1500000 | I72: =+H72*1.05 -> 1575000 | J72: =+I72*1 -> 1575000
C73: 1 | D73: Avantage | E73: 15000 | H73: =+E73*12*1 -> 180000 | I73: =+H73*1.05 -> 189000 | J73: =+I73*1 -> 189000
D74: Ch Sociale | E74: =+E72*20% -> 25000 | H74: =+H72*20% -> 300000 | I74: =+I72*20% -> 315000 | J74: =+J72*20% -> 315000
B75: Conducteur de porte-charge & tractoriste | D75: Salaire | E75: 125000 | G75: =+E75*C76*8 -> 2000000 | H75: =+E75*C76*12*1 -> 3000000 | I75: =+H75*1.05 -> 3150000 | J75: =+I75*1 -> 3150000
C76: 2 | D76: Avantage | E76: 25000 | G76: =+E76*C76*8 -> 400000 | H76: =+E76*C76*12*1 -> 600000 | I76: =+H76*1.05 -> 630000 | J76: =+I76*1 -> 630000
D77: Ch Sociale | E77: =+E75*20% -> 25000 | G77: =+G75*20% -> 400000 | H77: =+H75*20% -> 600000 | I77: =+I75*20% -> 630000 | J77: =+J75*20% -> 630000
B78: Manœuvre (manutention sur site d'exploitation) | D78: Salaire | E78: 70000 | F78: =SUM(E78)*2*12 -> 1680000 | G78: =+E78*C79*8 -> 2240000 | H78: =+E78*C79*1*12 -> 3360000 | I78: =+H78*1.05 -> 3528000 | J78: =+I78*1 -> 3528000
C79: 4 | D79: Avantage | E79: 10000 | F79: =SUM(E79)*2*12 -> 240000 | G79: =+E79*C79*8 -> 320000 | H79: =+E79*C79*12*1 -> 480000 | I79: =+H79*1.05 -> 504000 | J79: =+I79*1 -> 504000
D80: Ch Sociale | E80: =+E78*20% -> 14000 | F80: =SUM(F78)*0.2 -> 336000 | G80: =+G78*20% -> 448000 | H80: =+H78*20% -> 672000 | I80: =+I78*20% -> 705600 | J80: =+J78*20% -> 705600
B81: Chauffeur | D81: Salaire | E81: 100000 | G81: =+E81*C82*8 -> 0 | H81: =+E81*C82*12 -> 0 | I81: =+H81*1.1 -> 0 | J81: =+I81*1.1 -> 0
D82: Avantage | E82: 10000 | G82: =+E82*C82*8 -> 0 | H82: =+E82*C82*12*1.1 -> 0 | I82: =+H82*1.05 -> 0 | J82: =+I82*1.05 -> 0
D83: Ch Sociale | E83: =+E81*20% -> 20000 | G83: =+G81*20% -> 0 | H83: =+H81*20% -> 0 | I83: =+I81*20% -> 0 | J83: =+J81*20% -> 0
B84: Chef de zone d'exploitation (producteur agricole reconnu, responsable de groupe) | D84: Salaire | E84: 100000 | G84: =+E84*C85*12 -> 4800000 | H84: =+E84*C85*12*1 -> 4800000 | I84: =+H84*1.05 -> 5040000 | J84: =+I84*1 -> 5040000
C85: 4 | D85: Avantage | E85: 10000 | G85: =+E85*C85*12 -> 480000 | H85: =+E85*C85*12*1 -> 480000 | I85: =+H85*1.05 -> 504000 | J85: =+I85*1 -> 504000
D86: Ch Sociale | E86: =+E84*20% -> 20000 | G86: =+G84*20% -> 960000 | H86: =+H84*20% -> 960000 | I86: =+I84*20% -> 1008000 | J86: =+J84*20% -> 1008000
B87: Ouvrier d'appoint de zone et unité (manutention, récolte, contrôle de tri) | D87: Salaire | E87: 70000 | F87: =SUM(E87)*4*12 -> 3360000 | G87: =+E87*C88*12 -> 6720000 | H87: =+E87*C88*12*1 -> 6720000 | I87: =+H87*1.05 -> 7056000 | J87: =+I87*1 -> 7056000
C88: 8 | D88: Avantage | E88: 5000 | F88: =SUM(E88)*4*12 -> 240000 | G88: =+E88*C88*8 -> 320000 | H88: =+E88*C88*12*1 -> 480000 | I88: =+H88*1.05 -> 504000 | J88: =+I88*1 -> 504000
D89: Ch Sociale | E89: =+E87*20% -> 14000 | F89: =SUM(F87)*0.2 -> 672000 | G89: =+G87*20% -> 1344000 | H89: =+H87*20% -> 1344000 | I89: =+I87*20% -> 1411200 | J89: =+J87*20% -> 1411200
B90: Gardien/ Sécurité | D90: Salaire | E90: 65000 | F90: =SUM(E90)*12 -> 780000 | G90: =+E90*C91*12 -> 1560000 | H90: =+E90*C91*12*1 -> 1560000 | I90: =+H90*1.05 -> 1638000 | J90: =+I90*1 -> 1638000
C91: 2 | D91: Avantage | E91: 5000 | F91: =SUM(E91)*12 -> 60000 | G91: =+E91*C91*12 -> 120000 | H91: =+E91*C91*12*1 -> 120000 | I91: =+H91*1.05 -> 126000 | J91: =+I91*1 -> 126000
D92: Ch Sociale | E92: =+E90*20% -> 13000 | F92: =SUM(F90)*0.2 -> 156000 | G92: =+G90*20% -> 312000 | H92: =+H90*20% -> 312000 | I92: =+I90*20% -> 327600 | J92: =+J90*20% -> 327600
B99: EFFECTIF A TERME | C99: =+SUM(C60:C98) -> 26
B100: TOTAUX SALAIRES DE BASE | F100: =SUM(F60)+F63+F78+F87 -> 10320000 | G100: =SUM(G63+G69+G75+G78+G84+G87+G90) -> 21420000 | H100: =SUM(H60+H63+H66+H69+H72+H75+H78+H84+H87+H90) -> 33420000 | I100: =SUM(I60+I63+I66+I69+I72+I75+I78+I84+I87+I90) -> 35091000 | J100: =SUM(J90+J87+J84+J78+J75+J72+J69+J66+J63+J60) -> 35091000
B101: TOTAUX AVANTAGES | F101: =SUM(F91)+F88+F79+F64+F61 -> 1080000 | G101: =SUM(G64+G70+G76+G79+G85+G88+G91) -> 1880000 | H101: =SUM(H61+H64+H67+H70+H73+H76+H79+H85+H88+H91) -> 3420000 | I101: =SUM(I61+I64+I67+I70+I73+I76+I79+I85+I88+I91) -> 3591000 | J101: =SUM(J61+J64+J67+J70+J73+J76+J79+J85+J88+J91) -> 3591000
B102: TOTALES CHARGES SOCIALES | F102: =SUM(F92)+F89+F80+F65+F62 -> 2220000 | G102: =SUM(G65+G71+G77+G80+G86+G89+G92) -> 4284000 | H102: =SUM(H62+H65+H68+H71+H74+H77+H80+H86+H89+H92) -> 6684000 | I102: =SUM(I62+I65+I68+I71+I74+I77+I80+I86+I89+I92) -> 7018200 | J102: =SUM(J62+J65+J68+J71+J74+J77+J80+J86+J89+J92) -> 7018200
B103: TOTALES CHARGES SALARIALES | G103: =+G102+G101+G100 -> 27584000 | H103: =+H102+H101+H100 -> 43524000 | I103: =+I102+I101+I100 -> 45700200 | J103: =+J102+J101+J100 -> 45700200
B108: UNITE ELEVAGE
B109: POSTE | C109: Effectif à terme | D109: Base de rémunération | F109: 2026 | G109: 2027 | H109: 2028 | I109: 2029 | J109: 2030
B110: Chef d'unité (y compris activités administratives) | D110: Salaire | E110: 225000 | F110: =SUM(E110)*12 -> 2700000 | G110: =+E110*C111*12 -> 2700000 | H110: =+E110*12 -> 2700000 | I110: =+H110*1 -> 2700000 | J110: =+I110*1.1 -> 2970000
C111: 1 | D111: Avantage | E111: 25000 | F111: =SUM(E111)*12 -> 300000 | G111: =+E111*C111*12 -> 300000 | H111: =+E111*12 -> 300000 | I111: =+H111*1 -> 300000 | J111: =+I111*1.05 -> 315000
D112: Ch Sociale | E112: =+E110*20% -> 45000 | F112: =SUM(F110)*0.2 -> 540000 | G112: =+G110*20% -> 540000 | H112: =+H110*20% -> 540000 | I112: =+I110*20% -> 540000 | J112: =+J110*20% -> 594000
B113: Magasinier | D113: Salaire | E113: 190000 | F113: =SUM(E113)*12 -> 2280000 | G113: =+E113*C114*12 -> 2280000 | H113: =+E113*C114*12 -> 2280000 | I113: =+H113*1 -> 2280000 | J113: =+I113*1.1 -> 2508000
C114: 1 | D114: Avantage | E114: 15000 | F114: =SUM(E114)*12 -> 180000 | G114: =+E114*C114*12 -> 180000 | H114: =+E114*12 -> 180000 | I114: =+H114*1 -> 180000 | J114: =+I114*1.05 -> 189000
D115: Ch Sociale | E115: =+E113*20% -> 38000 | F115: =SUM(F113)*0.2 -> 456000 | G115: =+G113*20% -> 456000 | H115: =+H113*20% -> 456000 | I115: =+I113*20% -> 456000 | J115: =+J113*20% -> 501600
B116: Secrétaire comptable | D116: Salaire | E116: 125000 | H116: =+E116*12 -> 1500000 | I116: =+H116*1 -> 1500000 | J116: =+I116*1.1 -> 1650000
C117: 1 | D117: Avantage | E117: 15000 | H117: =+E117*12 -> 180000 | I117: =+H117*1 -> 180000 | J117: =+I117*1.05 -> 189000
D118: Ch Sociale | E118: =+E116*20% -> 25000 | H118: =+H116*20% -> 300000 | I118: =+I116*20% -> 300000 | J118: =+J116*20% -> 330000
B119: Conducteur de porte-charge (Manitou) | D119: Salaire | E119: 125000 | H119: =+E119*C120*12 -> 3000000 | I119: =+H119*1 -> 3000000 | J119: =+I119*1.1 -> 3300000
C120: 2 | D120: Avantage | E120: 25000 | H120: =+E120*C120*12 -> 600000 | I120: =+H120*1 -> 600000 | J120: =+I120*1.05 -> 630000
...

Sheet Exploitation
E5: CHARGE D'EXPLOITATION DIRECTION
E6: Désignation | F6: 2026 | G6: 2027 | H6: 2028 | I6: 2029 | J6: 2030
E7: Frais de téléphone | F7: =1000*10*6 -> 60000 | G7: =SUM(F7)*2 -> 120000 | H7: =+G7*1.1 -> 132000 | I7: =+H7*1.1 -> 145200 | J7: =+I7*1.1 -> 159720
E8: Connexion internet | F8: =5500*12 -> 66000 | G8: =SUM(F8)*2 -> 132000 | H8: =+G8*1.1 -> 145200 | I8: =+H8*1.1 -> 159720 | J8: =+I8*1.1 -> 175692
E9: Frais de carburant | F9: =50*500*15*6 -> 2250000 | G9: =SUM(F9)*1.2 -> 2700000 | H9: =+G9*1.1 -> 2970000 | I9: =+H9*1.1 -> 3267000 | J9: =+I9*1.1 -> 3593700
E10: Fournitures de bureau | F10: =50000*6 -> 300000 | G10: =SUM(F10)*2 -> 600000 | H10: =+G10*1.1 -> 660000 | I10: =+H10*1.1 -> 726000 | J10: =+I10*1.1 -> 798600
E11: Achat de petits matériels | F11: 150000 | G11: =SUM(F11)*2 -> 300000 | H11: =+G11*1.1 -> 330000 | I11: =+H11*1.1 -> 363000 | J11: =+I11*1.1 -> 399300
E12: Frais de transport | F12: =10*500*30*6 -> 900000 | G12: =SUM(F12)*2 -> 1800000 | H12: =+G12*1.1 -> 1980000 | I12: =+H12*1.1 -> 2178000 | J12: =+I12*1.1 -> 2395800
E13: Voyages et déplacements | F13: 600000 | G13: =SUM(F13)*2 -> 1200000 | H13: =+G13*1.1 -> 1320000 | I13: =+H13*1.1 -> 1452000 | J13: =+I13*1.1 -> 1597200
E14: Loyers et charges locatives | F14: =+(3000*2)+(12000*3) -> 42000 | G14: =SUM(F14)*2 -> 84000 | H14: =+G14*1.1 -> 92400 | I14: =+H14*1.1 -> 101640 | J14: =+I14*1.1 -> 111804
E15: Entretien (locaux, matériel) | F15: =2000*120 -> 240000 | G15: =SUM(F15)*2 -> 480000 | H15: =+G15*1.1 -> 528000 | I15: =+H15*1.1 -> 580800 | J15: =+I15*1.1 -> 638880
E16: Documentation | F16: 150000 | G16: =SUM(F16)*2 -> 300000 | H16: =+G16*1.1 -> 330000 | I16: =+H16*1.1 -> 363000 | J16: =+I16*1.1 -> 399300
E17: Marketing Com/RP -R&D | F17: 500000 | G17: =SUM(F17)*2 -> 1000000 | H17: =+G17*1.1 -> 1100000 | I17: =+H17*1.1 -> 1210000 | J17: =+I17*1.1 -> 1331000
E18: Frais de formation | F18: 500000 | G18: =SUM(F18)*2 -> 1000000 | H18: =+G18*1.1 -> 1100000 | I18: =+H18*1.1 -> 1210000 | J18: =+I18*1.1 -> 1331000
E19: Redevances diverses | F19: 150000 | G19: =SUM(F19)*2 -> 300000 | H19: =+G19*1.1 -> 330000 | I19: =+H19*1.1 -> 363000 | J19: =+I19*1.1 -> 399300
E20: Assistance contrats int, Assurances diverses | F20: 250000 | G20: =SUM(F20)*2 -> 500000 | H20: =+G20*1.1 -> 550000 | I20: =+H20*1.1 -> 605000 | J20: =+I20*1.1 -> 665500
E21: Assurances locaux et moyens roulants | F21: 100000 | G21: =SUM(F21)*2 -> 200000 | H21: =+G21*1.1 -> 220000 | I21: =+H21*1.1 -> 242000 | J21: =+I21*1.1 -> 266200
E22: Autres charges externes | F22: 200000 | G22: =SUM(F22)*2 -> 400000 | H22: =+G22*1.1 -> 440000 | I22: =+H22*1.1 -> 484000 | J22: =+I22*1.1 -> 532400
J23: =+I23*1.1 -> 0
E24: TOTAL | F24: =SUM(F7:F22) -> 6458000 | G24: =SUM(G7:G22) -> 11116000 | H24: =SUM(H7:H22) -> 12227600 | I24: =SUM(I7:I22) -> 13450360 | J24: =SUM(J7:J22) -> 14795396
E25: La coopérative 1/10 de la charge globale | F25: =SUM(F24)/10 -> 645800 | G25: =SUM(G24)/10 -> 1111600 | H25: =SUM(H24)/10 -> 1222760 | I25: =SUM(I24)/10 -> 1345036 | J25: =SUM(J24)/10 -> 1479539.6
E29: CHARGE D'EXPLOITATION UNITE AGRICULTURE
E30: Désignation | F30: 2026 | G30: 2027 | H30: 2028 | I30: 2029 | J30: 2030
E31: Frais de téléphone | F31: =SUM(F7)/2 -> 30000 | G31: =SUM(F31)*2 -> 60000 | H31: =+G31*1.1 -> 66000 | I31: =+H31*1.1 -> 72600 | J31: =+I31*1.1 -> 79860
E32: Connexion internet | F32: =SUM(F8)/2 -> 33000 | G32: =SUM(F32)*2 -> 66000 | H32: =SUM(G32)*1.1 -> 72600 | I32: =+H32*1.1 -> 79860 | J32: =+I32*1.1 -> 87846
E33: Eau & Electricité | F33: 500000 | G33: =SUM(F33) -> 500000 | H33: =SUM(F33)*1.1 -> 550000 | I33: =SUM(F33)*1.1 -> 550000 | J33: =SUM(I33)*1.1 -> 605000
E34: Frais de carburant | F34: =50*500*15*6 -> 2250000 | G34: =SUM(F34)*2 -> 4500000 | H34: =+G34*1.1 -> 4950000 | I34: =+H34*1.1 -> 5445000 | J34: =+I34*1.1 -> 5989500
E35: Fournitures de bureau | F35: =SUM(F10)/2 -> 150000 | G35: =SUM(F35)*2 -> 300000 | H35: =+G35*1.1 -> 330000 | I35: =+H35*1.1 -> 363000 | J35: =+I35*1.1 -> 399300
E36: Achat de petits matériels | F36: =SUM(F11)/2 -> 75000 | G36: =SUM(F36)*2 -> 150000 | H36: =+G36*1.1 -> 165000 | I36: =+H36*1.1 -> 181500 | J36: =+I36*1.1 -> 199650
E37: Frais de transport | F37: =SUM(F12)/4 -> 225000 | G37: =SUM(F37)*2 -> 450000 | H37: =SUM(G37)*1.1 -> 495000 | I37: =+H37*1.1 -> 544500 | J37: =+I37*1.1 -> 598950
E38: Voyages et déplacements | F38: 0 | G38: 250000 | H38: =SUM(G38)*1.1 -> 275000 | I38: =+H38*1.1 -> 302500 | J38: =+I38*1.1 -> 332750
E39: Loyers et charges locatives | F39: 0 | G39: 0 | H39: 0 | I39: 0 | J39: 0
E40: Entretien (locaux, matériel) | F40: =SUM(F15)/2 -> 120000 | G40: =SUM(F40)*2 -> 240000 | H40: =SUM(G40)*1.1 -> 264000 | I40: =+H40*1.1 -> 290400 | J40: =+I40*1.1 -> 319440
E41: Documentation | F41: =SUM(F16)/2 -> 75000 | G41: =SUM(F41*2) -> 150000 | H41: =+G41*1.1 -> 165000 | I41: =+H41*1.1 -> 181500 | J41: =+I41*1.1 -> 199650
E42: Frais de formation | F42: =SUM(F18)/4 -> 125000 | G42: =SUM(F42)*2 -> 250000 | H42: =+G42*1.1 -> 275000 | I42: =+H42*1.1 -> 302500 | J42: =+I42*1.1 -> 332750
E43: Redevances diverses | F43: 0 | G43: 0 | H43: =+G43*1.1 -> 0 | I43: =+H43*1.1 -> 0 | J43: =+I43*1.1 -> 0
E44: Assistance extérieure | F44: =+'CA Elevage'!C220 -> 0 | G44: 0 | H44: =SUM(G44)*1.3 -> 0 | I44: =SUM(H44)*2 -> 0 | J44: =SUM(I44)*1.3 -> 0
E45: Assurances locaux et moyens roulants | F45: =SUM(F21)/2 -> 50000 | G45: =SUM(F45)*2 -> 100000 | H45: =SUM(G45)*1.1 -> 110000 | I45: =+H45*1.1 -> 121000 | J45: =+I45*1.1 -> 133100
E46: Autres charges externes | F46: =SUM(F22)/2 -> 100000 | G46: =SUM(F46)*2 -> 200000 | H46: =+G46*1.1 -> 220000 | I46: =+H46*1.1 -> 242000 | J46: =+I46*1.1 -> 266200
E48: TOTAL | F48: =SUM(F31:F47) -> 3733000 | G48: =SUM(G31:G47) -> 7216000 | H48: =SUM(H31:H47) -> 7937600 | I48: =SUM(I31:I47) -> 8676360 | J48: =SUM(J31:J47) -> 9543996
E53: CHARGE D'EXPLOITATION UNITE ELEVAGE
E54: Désignation | F54: 2026 | G54: 2027 | H54: 2028 | I54: 2029 | J54: 2030
E55: Frais de téléphone | F55: =SUM(F31)/2 -> 15000 | G55: =SUM(F55)*2 -> 30000 | H55: =+G55*1.1 -> 33000 | I55: =+H55*1.1 -> 36300 | J55: =+I55*1.1 -> 39930
E56: Connexion internet | F56: =SUM(F32)/2 -> 16500 | G56: =SUM(F56)*2 -> 33000 | H56: =SUM(G56)*1.1 -> 36300 | I56: =+H56*1.1 -> 39930 | J56: =+I56*1.1 -> 43923
E57: Eau & Electricité | F57: 500000 | G57: =SUM(F57) -> 500000 | H57: =SUM(F57)*1.1 -> 550000 | I57: =SUM(F57)*1.1 -> 550000 | J57: =SUM(I57)*1.1 -> 605000
E58: Frais de carburant | F58: =25*500*15*6 -> 1125000 | G58: =SUM(F58)*2 -> 2250000 | H58: =+G58*1.1 -> 2475000 | I58: =+H58*1.1 -> 2722500 | J58: =+I58*1.1 -> 2994750
E59: Fournitures de bureau | F59: =SUM(F35) -> 150000 | G59: =SUM(F59)*2 -> 300000 | H59: =+G59*1.1 -> 330000 | I59: =+H59*1.1 -> 363000 | J59: =+I59*1.1 -> 399300
E60: Achat de petits matériels | F60: =SUM(F35)/2 -> 75000 | G60: =SUM(F60)*2 -> 150000 | H60: =+G60*1.1 -> 165000 | I60: =+H60*1.1 -> 181500 | J60: =+I60*1.1 -> 199650
E61: Frais de transport | F61: =SUM(F36)/2 -> 37500 | G61: =SUM(F61)*2 -> 75000 | H61: =SUM(G61)*1.1 -> 82500 | I61: =+H61*1.1 -> 90750 | J61: =+I61*1.1 -> 99825
E62: Voyages et déplacements | F62: 0 | G62: 250000 | H62: =SUM(G62)*1.1 -> 275000 | I62: =+H62*1.1 -> 302500 | J62: =+I62*1.1 -> 332750
E63: Loyers et charges locatives | F63: 0 | G63: 0 | H63: 0 | I63: 0 | J63: 0
E64: Entretien (locaux, matériel) | F64: =SUM(F39)/2 -> 0 | G64: =SUM(F64)*2 -> 0 | H64: =SUM(G64)*1.1 -> 0 | I64: =+H64*1.1 -> 0 | J64: =+I64*1.1 -> 0
E65: Documentation | F65: =SUM(F40)/2 -> 60000 | G65: =SUM(F65*2) -> 120000 | H65: =+G65*1.1 -> 132000 | I65: =+H65*1.1 -> 145200 | J65: =+I65*1.1 -> 159720
E66: Frais de formation | F66: =SUM(F42)/4 -> 31250 | G66: =SUM(F66)*2 -> 62500 | H66: =+G66*1.1 -> 68750 | I66: =+H66*1.1 -> 75625 | J66: =+I66*1.1 -> 83187.5
E67: Redevances diverses | F67: 0 | G67: 0 | H67: =+G67*1.1 -> 0 | I67: =+H67*1.1 -> 0 | J67: =+I67*1.1 -> 0
E68: Assistance extérieure | F68: =+'CA Elevage'!C244 -> 0 | G68: 0 | H68: =SUM(G68)*1.3 -> 0 | I68: =SUM(H68)*2 -> 0 | J68: =SUM(I68)*1.3 -> 0
E69: Assurances locaux et moyens roulants | F69: =SUM(F45)/2 -> 25000 | G69: =SUM(F69)*2 -> 50000 | H69: =SUM(G69)*1.1 -> 55000 | I69: =+H69*1.1 -> 60500 | J69: =+I69*1.1 -> 66550
E70: Autres charges externes | F70: =SUM(F46)/2 -> 50000 | G70: =SUM(F70)*2 -> 100000 | H70: =+G70*1.1 -> 110000 | I70: =+H70*1.1 -> 121000 | J70: =+I70*1.1 -> 133100
E72: TOTAL | F72: =SUM(F54:F71) -> 2087276 | G72: =SUM(G55:G71) -> 3920500 | H72: =SUM(H54:H71) -> 4314578 | I72: =SUM(I55:I71) -> 4688805 | J72: =SUM(J54:J71) -> 5159715.5
E76: CHARGES D'EXPLOITATION TOTALES
E77: UNITE | F77: 2026 | G77: 2027 | H77: 2028 | I77: 2029 | J77: 2030
E78: CHARGE D'EXPLOITATION DIRECTION | F78: =SUM(F25) -> 645800 | G78: =SUM(G25) -> 1111600 | H78: =SUM(H25) -> 1222760 | I78: =SUM(I25) -> 1345036 | J78: =SUM(J25) -> 1479539.6
E79: CHARGE D'EXPLOITATION UNITE AGRICULTURE | F79: =+F48 -> 3733000 | G79: =+G48 -> 7216000 | H79: =+H48 -> 7937600 | I79: =+I48 -> 8676360 | J79: =+J48 -> 9543996
E80: CHARGE D'EXPLOITATION UNITE ELEVAGE | F80: =+F72 -> 2087276 | G80: =+G72 -> 3920500 | H80: =+H72 -> 4314578 | I80: =+I72 -> 4688805 | J80: =+J72 -> 5159715.5
E82: TOTAUX | F82: =+SUM(F78:F81) -> 6466076 | G82: =+SUM(G78:G81) -> 12248100 | H82: =+SUM(H78:H81) -> 13474938 | I82: =+SUM(I78:I81) -> 14710201 | J82: =+SUM(J78:J81) -> 16183251

Sheet Diverses charges immobilisées
C5: CHARGES IMMOBILISEES
C6: Désignation | D6: Unité | E6: Montant Unit. | F6: Montant total
C7: Constitution cooperative | D7: 1 | E7: 250000 | F7: =+E7*D7 -> 250000
C8: Charge enregistrement au programme Baghara | D8: 1 | E8: 150000 | F8: =+E8*D8 -> 150000
C9: Charge enregistrement au projet 3Moissons | D9: 1 | E9: 450000 | F9: =+E9*D9 -> 450000
C10: Etudes & montage du projet coopératif | D10: 1 | E10: 1650000 | F10: =+E10*D10 -> 1650000
C11: Missions et Etudes techniques sur site | D11: 2 | E11: 750000 | F11: =+E11*D11 -> 1500000
C12: Missions à l'extérieur | D12: 0 | E12: 5000000 | F12: =+E12*D12 -> 0
C13: Communication publicité | D13: 0 | E13: 1000000 | F13: =+E13*D13 -> 0
C14: Agréments divers | D14: 1 | E14: 1000000 | F14: =+E14*D14 -> 1000000
E16: TOTAL | F16: =+SUM(F7:F14) -> 5000000
C21: IMMOBILISATIONS INCORPORELLES - TOTAL DU GROUPE HARAZ
C22: Désignation | D22: Unité | E22: Montant Unit. | F22: Montant total
C23: Marque et dépôt (forfait) | D23: 0 | E23: 5000000 | F23: =+E23*D23 -> 0
C24: Logiciel de Gestion commerciale 1/10 | D24: 1 | E24: 3000000 | F24: =SUM(E24)/10 -> 300000
C25: Suite de Gestion collaborative / ERP Formation 1/10 | D25: 1 | E25: 6000000 | F25: =SUM(E25)/10 -> 600000
C26: Site Internet / Intranet global 1/10 | D26: 1 | E26: 4000000 | F26: =SUM(E26)/10 -> 400000
C27: manuel de procédures 1/10 | D27: 4 | E27: 300000 | F27: =SUM(D27*E27)/10 -> 120000
C28: manuel technique de production industrie 1/10 | D28: 4 | E28: 300000 | F28: =SUM(D28*E28)/10 -> 120000
C29: Kompass 1/10 | D29: 1 | E29: 800000 | F29: =SUM(D29*E29)/10 -> 80000
C30: Formations administration & management 1/10 | D30: 4 | E30: 350000 | F30: =SUM(D30*E30)/10 -> 140000
C31: Autre formation HACCP & Normes 1/10 | D31: 4 | E31: 200000 | F31: =SUM(D31*E31)/10 -> 80000
E33: TOTAL | F33: =+SUM(F23:F31) -> 1840000
C40: IMMOBILISATIONS CORPORELLES - TOTAL DU GROUPE HARAZ
C41: Désignation | F41: Montant total
C42: TOTAUX AMENAGEMENT & INFRASTRUCTURES | F42: =+'Amenag, Infrastr et Equipemt '!D59 -> 257000000
C43: TOTAUX EQUIPEMENTS INDUSTRIELS | F43: =+'Amenag, Infrastr et Equipemt '!L59 -> 140400000
C44: TOTAUX MOYENS ROULANTS | F44: =+'Mat bureau & Mat roulants'!L68 -> 4800000
C45: TOTAUX MATERIELS INFORMATIQUES & REPROGRAPHIE | F45: =SUM('Mat bureau & Mat roulants'!R68) -> 1745000
C46: TOTAUX MATERIELS DE BUREAU | F46: =+'Mat bureau & Mat roulants'!F68 -> 3597500
E48: TOTAL | F48: =+SUM(F42:F47) -> 407542500
C54: TOTAL DES INVESTISSEMENTS DE BASE
C55: Désignation | F55: Prix total
C56: =+C5 -> CHARGES IMMOBILISEES | F56: =+F16 -> 5000000
C57: =+C21 -> IMMOBILISATIONS INCORPORELLES - TOTAL DU GROUPE HARAZ | F57: =+F33 -> 1840000
C58: =+C40 -> IMMOBILISATIONS CORPORELLES - TOTAL DU GROUPE HARAZ | F58: =+F48 -> 407542500
E60: TOTAL | F60: =+SUM(F56:F59) -> 414382500

Sheet Amort technique
C2: TABLEAU D'AMORTISSEMENTS TECHNIQUES
C3: Investissement | D3: Montant initial | E3: Durée | F3: 2026 | G3: 2027 | H3: 2028 | I3: 2029 | J3: 2030
C4: Charges immobilisées | D4: =+'Diverses charges immobilisées'!F16 -> 5000000 | E4: 3 | G4: =+D4/E4 -> 1666666.7 | H4: =+G4 -> 1666666.7 | I4: =+H4 -> 1666666.7
C5: Immobilisations incorporelles | D5: =+'Diverses charges immobilisées'!F33 -> 1840000 | E5: 10 | G5: =+D5/E5 -> 184000 | H5: =+G5 -> 184000 | I5: =+H5 -> 184000 | J5: =+I5 -> 184000
C6: Fonciers | D6: 100000000 | E6: 30 | G6: =SUM(D6)/30 -> 3333333.3 | H6: =+G6 -> 3333333.3 | I6: =+H6 -> 3333333.3 | J6: =+I6 -> 3333333.3
C7: Aménagements et constructions | D7: =SUM('Amenag, Infrastr et Equipemt '!D59) -> 257000000 | E7: 20 | G7: =+D7/E7 -> 12850000 | H7: =+G7 -> 12850000 | I7: =+H7 -> 12850000 | J7: =+I7 -> 12850000
C8: Matériels et équipements industriels | D8: =+'Amenag, Infrastr et Equipemt '!L59 -> 140400000 | E8: 10 | G8: =+D8/E8 -> 14040000 | H8: =+G8 -> 14040000 | I8: =+H8 -> 14040000 | J8: =+I8 -> 14040000
C9: Moyens roulants | D9: =+'Mat bureau & Mat roulants'!L68 -> 4800000 | E9: 5 | G9: =+D9/E9 -> 960000 | H9: =+G9 -> 960000 | I9: =+H9 -> 960000 | J9: =+I9 -> 960000
C10: Matériels de bureau | D10: =+'Mat bureau & Mat roulants'!F68 -> 3597500 | E10: 5 | G10: =+D10/E10 -> 719500 | H10: =+G10 -> 719500 | I10: =+H10 -> 719500 | J10: =+I10 -> 719500
C11: Informatiques et reproduction | D11: =+'Mat bureau & Mat roulants'!R68 -> 1745000 | E11: 3 | G11: =+D11/E11 -> 581666.67 | H11: =+G11 -> 581666.67 | I11: =+H11 -> 581666.67 | J11: =+I11 -> 581666.67
D13: =SUM(D4:D12) -> 514382500 | E13: TOTAUX | F13: =+SUM(F4:F12) -> 0 | G13: =+SUM(G4:G12) -> 34335167 | H13: =+SUM(H4:H12) -> 34335167 | I13: =+SUM(I4:I12) -> 34335167 | J13: =+SUM(J4:J12) -> 32668500

Sheet Coûts de product° Agricole
D2: Coûts de production agricoles en €
D4: Year 1 | E4: Year 2 | F4: Year 3 | G4: Year 4 | H4: Year 5 | I4: Year 6 | J4: Year 7 | K4: Year 8 | L4: Year 9 | M4: Year 10
B6: Arachide (Groundnut)
A7: 1 | B7: Description | C7: Coût/ Ha € | D7: 20 | E7: =D7 -> 20 | F7: =E7 -> 20 | G7: =F7 -> 20 | H7: =G7 -> 20 | I7: =H7 -> 20 | J7: =I7 -> 20 | K7: =J7 -> 20 | L7: =K7 -> 20 | M7: =L7 -> 20
B8: Préparation du sol | C8: 19.56 | D8: =$C8*D$7 -> 391.2 | E8: =$C8*E$7 -> 391.2 | F8: =$C8*F$7 -> 391.2 | G8: =$C8*G$7 -> 391.2 | H8: =$C8*H$7 -> 391.2 | I8: =$C8*I$7 -> 391.2 | J8: =$C8*J$7 -> 391.2 | K8: =$C8*K$7 -> 391.2 | ... M8: =$C8*M$7 -> 391.2 | O8: =64000/2.5 -> 25600 | Q8: Litre
B9: Coût des semences | C9: =100*120/88 -> 136.36364 | D9: =$C9*D$7 -> 2727.2727 | E9: =$C9*E$7 -> 2727.2727 | F9: =$C9*F$7 -> 2727.2727 | G9: =$C9*G$7 -> 2727.2727 | H9: =$C9*H$7 -> 2727.2727 | I9: =$C9*I$7 -> 2727.2727 | J9: =$C9*J$7 -> 2727.2727 | K9: =$C9*K$7 -> 2727.2727 | ... M9: =$C9*M$7 -> 2727.2727 | P9: Diesel consumption per hour | Q9: 10
B10: Coût du traitement des semences | C10: =1350*1.5*2.5/88 -> 57.528409 | D10: =$C10*D$7 -> 1150.5682 | E10: =$C10*E$7 -> 1150.5682 | F10: =$C10*F$7 -> 1150.5682 | G10: =$C10*G$7 -> 1150.5682 | H10: =$C10*H$7 -> 1150.5682 | I10: =$C10*I$7 -> 1150.5682 | J10: =$C10*J$7 -> 1150.5682 | K10: =$C10*K$7 -> 1150.5682 | ... M10: =$C10*M$7 -> 1150.5682 | P10: Diesel’s price | Q10: =75/88 -> 0.85227273
B11: Coût du semis | C11: =C8 -> 19.56 | D11: =$C11*D$7 -> 391.2 | E11: =$C11*E$7 -> 391.2 | F11: =$C11*F$7 -> 391.2 | G11: =$C11*G$7 -> 391.2 | H11: =$C11*H$7 -> 391.2 | I11: =$C11*I$7 -> 391.2 | J11: =$C11*J$7 -> 391.2 | K11: =$C11*K$7 -> 391.2 | ... M11: =$C11*M$7 -> 391.2 | P11: Diesel; cost /hour | Q11: =Q10*Q9 -> 8.5227273
B12: Engrais urée en 2 doses | C12: =R19 -> 36.409091 | D12: =$C12*D$7 -> 728.18182 | E12: =$C12*E$7 -> 728.18182 | F12: =$C12*F$7 -> 728.18182 | G12: =$C12*G$7 -> 728.18182 | H12: =$C12*H$7 -> 728.18182 | I12: =$C12*I$7 -> 728.18182 | J12: =$C12*J$7 -> 728.18182 | K12: =$C12*K$7 -> 728.18182 | ... M12: =$C12*M$7 -> 728.18182 | P12: Diesel cost / Ha/ hour | Q12: =Q11*25/33 -> 6.4566116
B13: Pulvérisation d’herbicide de prélevée | C13: =500*1.5*2.5/88 -> 21.306818 | D13: =$C13*D$7 -> 426.13636 | E13: =$C13*E$7 -> 426.13636 | F13: =$C13*F$7 -> 426.13636 | G13: =$C13*G$7 -> 426.13636 | H13: =$C13*H$7 -> 426.13636 | I13: =$C13*I$7 -> 426.13636 | J13: =$C13*J$7 -> 426.13636 | K13: =$C13*K$7 -> 426.13636 | ... M13: =$C13*M$7 -> 426.13636 | P13: No. of irrigations / season | Q13: 5
B14: Pulvérisation de fongicide et d’insecticide | C14: =(2500*1.5*2.5)/88 -> 106.53409 | D14: =$C14*D$7 -> 2130.6818 | E14: =$C14*E$7 -> 2130.6818 | F14: =$C14*F$7 -> 2130.6818 | G14: =$C14*G$7 -> 2130.6818 | H14: =$C14*H$7 -> 2130.6818 | I14: =$C14*I$7 -> 2130.6818 | J14: =$C14*J$7 -> 2130.6818 | K14: =$C14*K$7 -> 2130.6818 | ... M14: =$C14*M$7 -> 2130.6818 | P14: Total diesel cost per season per Ha | Q14: =Q13*Q12*2 -> 64.566116
B15: Gazole pour l’irrigation | C15: =Q14 -> 64.566116 | D15: =C15*D7 -> 1291.3223 | E15: =D15 -> 1291.3223 | F15: =E15 -> 1291.3223 | G15: =F15 -> 1291.3223 | H15: =G15 -> 1291.3223 | I15: =H15 -> 1291.3223 | J15: =I15 -> 1291.3223 | K15: =J15 -> 1291.3223 | L15: =K15 -> 1291.3223 | M15: =L15 -> 1291.3223
B16: Récolte (y compris la main-d’œuvre) | C16: =1500*2.5/88 -> 42.613636 | D16: =$C16*D$7 -> 852.27273 | E16: =$C16*E$7 -> 852.27273 | F16: =$C16*F$7 -> 852.27273 | G16: =$C16*G$7 -> 852.27273 | H16: =$C16*H$7 -> 852.27273 | I16: =$C16*I$7 -> 852.27273 | J16: =$C16*J$7 -> 852.27273 | K16: =$C16*K$7 -> 852.27273 | ... M16: =$C16*M$7 -> 852.27273 | O16: Fertiliser basal/ Ha | P16: QTY | Q16: Price | R16: Val/ Ha
B17: Coût total | C17: =SUM(C8:C16) -> 504.4418 | D17: =SUM(D7:D16) -> 10108.836 | E17: =SUM(E7:E16) -> 10108.836 | F17: =SUM(F7:F16) -> 10108.836 | G17: =SUM(G7:G16) -> 10108.836 | H17: =SUM(H7:H16) -> 10108.836 | I17: =SUM(I7:I16) -> 10108.836 | J17: =SUM(J7:J16) -> 10108.836 | K17: =SUM(K7:K16) -> 10108.836 | ... M17: =SUM(M7:M16) -> 10108.836 | O17: DAP | P17: 100 | Q17: =1200/50/88 -> 0.27272727 | R17: =Q17*P17 -> 27.272727
B18: Rendement | D18: =700*1.5*2.5 -> 2625 | E18: =750*1.5*2.5 -> 2812.5 | F18: =775*1.5*2.5 -> 2906.25 | G18: =850*1.5*2.5 -> 3187.5 | H18: =1000*1.5*2.5 -> 3750 | I18: =H18 -> 3750 | J18: =I18 -> 3750 | K18: =J18 -> 3750 | L18: =K18 -> 3750 | M18: =L18 -> 3750 | O18: Urea in two doses | P18: =40*1.5*2.5 -> 150 | Q18: =268/50/88 -> 0.060909091 | R18: =Q18*P18 -> 9.1363636
B19: Prix / kg | D19: 0.5 | E19: 0.5 | F19: =E19 -> 0.5 | G19: =F19 -> 0.5 | H19: =G19 -> 0.5 | I19: =H19 -> 0.5 | J19: =I19 -> 0.5 | K19: =J19 -> 0.5 | L19: =K19 -> 0.5 | M19: =L19 -> 0.5 | R19: =SUM(R17:R18) -> 36.409091
B20: Réalisation | D20: =D19*D18*D7 -> 26250 | E20: =E19*E18*E7 -> 28125 | F20: =F19*F18*F7 -> 29062.5 | G20: =G19*G18*G7 -> 31875 | H20: =H19*H18*H7 -> 37500 | I20: =I19*I18*I7 -> 37500 | J20: =J19*J18*J7 -> 37500 | K20: =K19*K18*K7 -> 37500 | ... M20: =M19*M18*M7 -> 37500
B22: Marge opérationnelle | D22: =D20-D17 -> 16141.164 | E22: =E20-E17 -> 18016.164 | F22: =F20-F17 -> 18953.664 | G22: =G20-G17 -> 21766.164 | H22: =H20-H17 -> 27391.164 | I22: =I20-I17 -> 27391.164 | J22: =J20-J17 -> 27391.164 | K22: =K20-K17 -> 27391.164 | ... M22: =M20-M17 -> 27391.164
A24: 2 | B24: Niébé (Cowpea)
B25: Description | C25: Coût/ Ha € | D25: 10 | E25: =D25 -> 10 | F25: =E25 -> 10 | G25: =F25 -> 10 | H25: =G25 -> 10 | I25: =H25 -> 10 | J25: =I25 -> 10 | K25: =J25 -> 10 | L25: =K25 -> 10 | M25: =L25 -> 10
B26: Préparation du sol | C26: =C44 -> 19.56 | D26: =D$25*$C26 -> 195.6 | E26: =E$25*$C26 -> 195.6 | F26: =F$25*$C26 -> 195.6 | G26: =G$25*$C26 -> 195.6 | H26: =H$25*$C26 -> 195.6 | I26: =I$25*$C26 -> 195.6 | J26: =J$25*$C26 -> 195.6 | K26: =K$25*$C26 -> 195.6 | ... M26: =M$25*$C26 -> 195.6
B27: Coût des semences | C27: =30*100/88 -> 34.090909 | D27: =D$25*$C27 -> 340.90909 | E27: =E$25*$C27 -> 340.90909 | F27: =F$25*$C27 -> 340.90909 | G27: =G$25*$C27 -> 340.90909 | H27: =H$25*$C27 -> 340.90909 | I27: =I$25*$C27 -> 340.90909 | J27: =J$25*$C27 -> 340.90909 | K27: =K$25*$C27 -> 340.90909 | ... M27: =M$25*$C27 -> 340.90909
B28: Coût du traitement des semences | C28: =35 -> 35 | D28: =D$25*$C28 -> 350 | E28: =E$25*$C28 -> 350 | F28: =F$25*$C28 -> 350 | G28: =G$25*$C28 -> 350 | H28: =H$25*$C28 -> 350 | I28: =I$25*$C28 -> 350 | J28: =J$25*$C28 -> 350 | K28: =K$25*$C28 -> 350 | ... M28: =M$25*$C28 -> 350
B29: Coût du semis | C29: =C47 -> 56.818182 | D29: =D$25*$C29 -> 568.18182 | E29: =E$25*$C29 -> 568.18182 | F29: =F$25*$C29 -> 568.18182 | G29: =G$25*$C29 -> 568.18182 | H29: =H$25*$C29 -> 568.18182 | I29: =I$25*$C29 -> 568.18182 | J29: =J$25*$C29 -> 568.18182 | K29: =K$25*$C29 -> 568.18182 | ... M29: =M$25*$C29 -> 568.18182
B30: Engrais urée en 2 doses | C30: =C12 -> 36.409091 | D30: =D$25*$C30 -> 364.09091 | E30: =E$25*$C30 -> 364.09091 | F30: =F$25*$C30 -> 364.09091 | G30: =G$25*$C30 -> 364.09091 | H30: =H$25*$C30 -> 364.09091 | I30: =I$25*$C30 -> 364.09091 | J30: =J$25*$C30 -> 364.09091 | K30: =K$25*$C30 -> 364.09091 | ... M30: =M$25*$C30 -> 364.09091
B31: Pulvérisation d’herbicide de prélevée | C31: =10000/88 -> 113.63636 | D31: =D$25*$C31 -> 1136.3636 | E31: =E$25*$C31 -> 1136.3636 | F31: =F$25*$C31 -> 1136.3636 | G31: =G$25*$C31 -> 1136.3636 | H31: =H$25*$C31 -> 1136.3636 | I31: =I$25*$C31 -> 1136.3636 | J31: =J$25*$C31 -> 1136.3636 | K31: =K$25*$C31 -> 1136.3636 | ... M31: =M$25*$C31 -> 1136.3636
B32: Pulvérisation de fongicide et d’insecticide | C32: =34 -> 34 | D32: =D$25*$C32 -> 340 | E32: =E$25*$C32 -> 340 | F32: =F$25*$C32 -> 340 | G32: =G$25*$C32 -> 340 | H32: =H$25*$C32 -> 340 | I32: =I$25*$C32 -> 340 | J32: =J$25*$C32 -> 340 | K32: =K$25*$C32 -> 340 | ... M32: =M$25*$C32 -> 340
B33: Gazole pour l’irrigation | C33: =C15/2 -> 32.283058 | D33: =D$25*$C33 -> 322.83058 | E33: =E$25*$C33 -> 322.83058 | F33: =F$25*$C33 -> 322.83058 | G33: =G$25*$C33 -> 322.83058 | H33: =H$25*$C33 -> 322.83058 | I33: =I$25*$C33 -> 322.83058 | J33: =J$25*$C33 -> 322.83058 | K33: =K$25*$C33 -> 322.83058 | ... M33: =M$25*$C33 -> 322.83058
B34: Récolte (y compris la main-d’œuvre) | C34: =137 -> 137 | D34: =D$25*$C34 -> 1370 | E34: =E$25*$C34 -> 1370 | F34: =F$25*$C34 -> 1370 | G34: =G$25*$C34 -> 1370 | H34: =H$25*$C34 -> 1370 | I34: =I$25*$C34 -> 1370 | J34: =J$25*$C34 -> 1370 | K34: =K$25*$C34 -> 1370 | ... M34: =M$25*$C34 -> 1370
B35: Coût total | C35: =SUM(C26:C34) -> 498.7976 | D35: =SUM(D26:D34) -> 4987.976 | E35: =SUM(E26:E34) -> 4987.976 | F35: =SUM(F26:F34) -> 4987.976 | G35: =SUM(G26:G34) -> 4987.976 | H35: =SUM(H26:H34) -> 4987.976 | I35: =SUM(I26:I34) -> 4987.976 | J35: =SUM(J26:J34) -> 4987.976 | ... M35: =SUM(M26:M34) -> 4987.976
B36: Rendement | D36: 900 | E36: 1000 | F36: =1100 -> 1100 | G36: =F36 -> 1100 | H36: =G36 -> 1100 | I36: =H36 -> 1100 | J36: =I36 -> 1100 | K36: =J36 -> 1100 | L36: =K36 -> 1100 | M36: =L36 -> 1100
B37: Prix / kg | D37: 1.3 | E37: =D37 -> 1.3 | F37: =E37 -> 1.3 | G37: =F37 -> 1.3 | H37: =G37 -> 1.3 | I37: =H37 -> 1.3 | J37: =I37 -> 1.3 | K37: =J37 -> 1.3 | L37: =K37 -> 1.3 | M37: =L37 -> 1.3
B38: Réalisation | D38: =D37*D36*D25 -> 11700 | E38: =E37*E36*E25 -> 13000 | F38: =F37*F36*F25 -> 14300 | G38: =G37*G36*G25 -> 14300 | H38: =H37*H36*H25 -> 14300 | I38: =I37*I36*I25 -> 14300 | J38: =J37*J36*J25 -> 14300 | K38: =K37*K36*K25 -> 14300 | ... M38: =M37*M36*M25 -> 14300
B40: Marge opérationnelle | D40: =D38-D35 -> 6712.024 | E40: =E38-E35 -> 8012.024 | F40: =F38-F35 -> 9312.024 | G40: =G38-G35 -> 9312.024 | H40: =H38-H35 -> 9312.024 | I40: =I38-I35 -> 9312.024 | J40: =J38-J35 -> 9312.024 | K40: =K38-K35 -> 9312.024 | ... M40: =M38-M35 -> 9312.024
A42: 3 | B42: Céréale, blé, mais (Wheat, corne, )
B43: Description | C43: Coût/ Ha € | D43: 20 | E43: =D43 -> 20 | F43: =E43 -> 20 | G43: =F43 -> 20 | H43: =G43 -> 20 | I43: =H43 -> 20 | J43: =I43 -> 20 | K43: =J43 -> 20 | L43: =K43 -> 20 | M43: =L43 -> 20
B44: Préparation du sol | C44: =C62 -> 19.56 | D44: =$C44*D$43 -> 391.2 | E44: =$C44*E$43 -> 391.2 | F44: =$C44*F$43 -> 391.2 | G44: =$C44*G$43 -> 391.2 | H44: =$C44*H$43 -> 391.2 | I44: =$C44*I$43 -> 391.2 | J44: =$C44*J$43 -> 391.2 | K44: =$C44*K$43 -> 391.2 | ... M44: =$C44*M$43 -> 391.2
B45: Coût des semences | C45: =100*75/88 -> 85.227273 | D45: =$C45*D$43 -> 1704.5455 | E45: =$C45*E$43 -> 1704.5455 | F45: =$C45*F$43 -> 1704.5455 | G45: =$C45*G$43 -> 1704.5455 | H45: =$C45*H$43 -> 1704.5455 | I45: =$C45*I$43 -> 1704.5455 | J45: =$C45*J$43 -> 1704.5455 | K45: =$C45*K$43 -> 1704.5455 | ... M45: =$C45*M$43 -> 1704.5455
B46: Coût du traitement des semences | D46: =$C46*D$43 -> 0 | E46: =$C46*E$43 -> 0 | F46: =$C46*F$43 -> 0 | G46: =$C46*G$43 -> 0 | H46: =$C46*H$43 -> 0 | I46: =$C46*I$43 -> 0 | J46: =$C46*J$43 -> 0 | K46: =$C46*K$43 -> 0 | ... M46: =$C46*M$43 -> 0
B47: Coût du semis | C47: =5000/88 -> 56.818182 | D47: =$C47*D$43 -> 1136.3636 | E47: =$C47*E$43 -> 1136.3636 | F47: =$C47*F$43 -> 1136.3636 | G47: =$C47*G$43 -> 1136.3636 | H47: =$C47*H$43 -> 1136.3636 | I47: =$C47*I$43 -> 1136.3636 | J47: =$C47*J$43 -> 1136.3636 | K47: =$C47*K$43 -> 1136.3636 | ... M47: =$C47*M$43 -> 1136.3636
B48: Engrais urée en 2 doses | C48: =10000/88 -> 113.63636 | D48: =$C48*D$43 -> 2272.7273 | E48: =$C48*E$43 -> 2272.7273 | F48: =$C48*F$43 -> 2272.7273 | G48: =$C48*G$43 -> 2272.7273 | H48: =$C48*H$43 -> 2272.7273 | I48: =$C48*I$43 -> 2272.7273 | J48: =$C48*J$43 -> 2272.7273 | K48: =$C48*K$43 -> 2272.7273 | ... M48: =$C48*M$43 -> 2272.7273
B49: Pulvérisation d’herbicide de prélevée | C49: =C47+2500/88 -> 85.227273 | D49: =$C49*D$43 -> 1704.5455 | E49: =$C49*E$43 -> 1704.5455 | F49: =$C49*F$43 -> 1704.5455 | G49: =$C49*G$43 -> 1704.5455 | H49: =$C49*H$43 -> 1704.5455 | I49: =$C49*I$43 -> 1704.5455 | J49: =$C49*J$43 -> 1704.5455 | K49: =$C49*K$43 -> 1704.5455 | ... M49: =$C49*M$43 -> 1704.5455
B50: Pulvérisation de fongicide et d’insecticide | C50: =C49 -> 85.227273 | D50: =$C50*D$43 -> 1704.5455 | E50: =$C50*E$43 -> 1704.5455 | F50: =$C50*F$43 -> 1704.5455 | G50: =$C50*G$43 -> 1704.5455 | H50: =$C50*H$43 -> 1704.5455 | I50: =$C50*I$43 -> 1704.5455 | J50: =$C50*J$43 -> 1704.5455 | K50: =$C50*K$43 -> 1704.5455 | ... M50: =$C50*M$43 -> 1704.5455
B51: Gazole pour l’irrigation | C51: =C15*2 -> 129.13223 | D51: =$C51*D$43 -> 2582.6446 | E51: =$C51*E$43 -> 2582.6446 | F51: =$C51*F$43 -> 2582.6446 | G51: =$C51*G$43 -> 2582.6446 | H51: =$C51*H$43 -> 2582.6446 | I51: =$C51*I$43 -> 2582.6446 | J51: =$C51*J$43 -> 2582.6446 | K51: =$C51*K$43 -> 2582.6446 | ... M51: =$C51*M$43 -> 2582.6446
B52: Récolte (y compris la main-d’œuvre) | C52: =10000/88 -> 113.63636 | D52: =$C52*D$43 -> 2272.7273 | E52: =$C52*E$43 -> 2272.7273 | F52: =$C52*F$43 -> 2272.7273 | G52: =$C52*G$43 -> 2272.7273 | H52: =$C52*H$43 -> 2272.7273 | I52: =$C52*I$43 -> 2272.7273 | J52: =$C52*J$43 -> 2272.7273 | K52: =$C52*K$43 -> 2272.7273 | ... M52: =$C52*M$43 -> 2272.7273
B53: Coût total | C53: =SUM(C44:C52) -> 688.46496 | D53: =$C53*D$43 -> 13769.299 | E53: =$C53*E$43 -> 13769.299 | F53: =$C53*F$43 -> 13769.299 | G53: =$C53*G$43 -> 13769.299 | H53: =$C53*H$43 -> 13769.299 | I53: =$C53*I$43 -> 13769.299 | J53: =$C53*J$43 -> 13769.299 | K53: =$C53*K$43 -> 13769.299 | ... M53: =$C53*M$43 -> 13769.299
B54: Rendement | D54: 3750 | E54: 4000 | F54: 4250 | G54: 4500 | H54: 5000 | I54: =H54 -> 5000 | J54: =I54 -> 5000 | K54: =J54 -> 5000 | L54: =K54 -> 5000 | M54: =L54 -> 5000
B55: Prix / kg | D55: 0.28 | E55: =D55 -> 0.28 | F55: =E55 -> 0.28 | G55: =F55 -> 0.28 | H55: =G55 -> 0.28 | I55: =H55 -> 0.28 | J55: =I55 -> 0.28 | K55: =J55 -> 0.28 | L55: =K55 -> 0.28 | M55: =L55 -> 0.28
B56: Réalisation | D56: =D55*D54*D43 -> 21000 | E56: =E55*E54*E43 -> 22400 | F56: =F55*F54*F43 -> 23800 | G56: =G55*G54*G43 -> 25200 | H56: =H55*H54*H43 -> 28000 | I56: =I55*I54*I43 -> 28000 | J56: =J55*J54*J43 -> 28000 | K56: =K55*K54*K43 -> 28000 | ... M56: =M55*M54*M43 -> 28000
B58: Marge opérationnelle | D58: =D56-D53 -> 7230.7008 | E58: =E56-E53 -> 8630.7008 | F58: =F56-F53 -> 10030.701 | G58: =G56-G53 -> 11430.701 | H58: =H56-H53 -> 14230.701 | I58: =I56-I53 -> 14230.701 | J58: =J56-J53 -> 14230.701 | K58: =K56-K53 -> 14230.701 | ... M58: =M56-M53 -> 14230.701
A60: 4 | B60: Sesame
B61: Description | C61: Coût/ Ha € | D61: 10 | E61: =D61 -> 10 | F61: =E61 -> 10 | G61: =F61 -> 10 | H61: =G61 -> 10 | I61: =H61 -> 10 | J61: =I61 -> 10 | K61: =J61 -> 10 | L61: =K61 -> 10 | M61: =L61 -> 10
B62: Préparation du sol | C62: 19.56 | D62: =$C62*D$7 -> 391.2 | E62: =$C62*E$7 -> 391.2 | F62: =$C62*F$7 -> 391.2 | G62: =$C62*G$7 -> 391.2 | H62: =$C62*H$7 -> 391.2 | I62: =$C62*I$7 -> 391.2 | J62: =$C62*J$7 -> 391.2 | K62: =$C62*K$7 -> 391.2 | ... M62: =$C62*M$7 -> 391.2 | Q62: Litre
B63: Coût des semences | C63: =300*6/88 -> 20.454545 | D63: =$C63*D$7 -> 409.09091 | E63: =$C63*E$7 -> 409.09091 | F63: =$C63*F$7 -> 409.09091 | G63: =$C63*G$7 -> 409.09091 | H63: =$C63*H$7 -> 409.09091 | I63: =$C63*I$7 -> 409.09091 | J63: =$C63*J$7 -> 409.09091 | K63: =$C63*K$7 -> 409.09091 | ... M63: =$C63*M$7 -> 409.09091 | P63: Diesel consumption per hour | Q63: 10
B64: Coût du traitement des semences | C64: =150*1.5*2.5/88 -> 6.3920455 | D64: =$C64*D$7 -> 127.84091 | E64: =$C64*E$7 -> 127.84091 | F64: =$C64*F$7 -> 127.84091 | G64: =$C64*G$7 -> 127.84091 | H64: =$C64*H$7 -> 127.84091 | I64: =$C64*I$7 -> 127.84091 | J64: =$C64*J$7 -> 127.84091 | K64: =$C64*K$7 -> 127.84091 | ... M64: =$C64*M$7 -> 127.84091 | P64: Diesel’s price | Q64: =75/88 -> 0.85227273
B65: Coût du semis | C65: =C62 -> 19.56 | D65: =$C65*D$7 -> 391.2 | E65: =$C65*E$7 -> 391.2 | F65: =$C65*F$7 -> 391.2 | G65: =$C65*G$7 -> 391.2 | H65: =$C65*H$7 -> 391.2 | I65: =$C65*I$7 -> 391.2 | J65: =$C65*J$7 -> 391.2 | K65: =$C65*K$7 -> 391.2 | ... M65: =$C65*M$7 -> 391.2 | P65: Diesel; cost /hour | Q65: =Q64*Q63 -> 8.5227273
B66: Engrais urée en 2 doses | C66: =R19 -> 36.409091 | D66: =$C66*D$7 -> 728.18182 | E66: =$C66*E$7 -> 728.18182 | F66: =$C66*F$7 -> 728.18182 | G66: =$C66*G$7 -> 728.18182 | H66: =$C66*H$7 -> 728.18182 | I66: =$C66*I$7 -> 728.18182 | J66: =$C66*J$7 -> 728.18182 | K66: =$C66*K$7 -> 728.18182 | ... M66: =$C66*M$7 -> 728.18182 | P66: Diesel cost / Ha/ hour | Q66: =Q65*25/33 -> 6.4566116
B67: Pulvérisation d’herbicide de prélevée | C67: =500*1.5*2.5/88 -> 21.306818 | D67: =$C67*D$7 -> 426.13636 | E67: =$C67*E$7 -> 426.13636 | F67: =$C67*F$7 -> 426.13636 | G67: =$C67*G$7 -> 426.13636 | H67: =$C67*H$7 -> 426.13636 | I67: =$C67*I$7 -> 426.13636 | J67: =$C67*J$7 -> 426.13636 | K67: =$C67*K$7 -> 426.13636 | ... M67: =$C67*M$7 -> 426.13636 | P67: No. of irrigations / season | Q67: 3
B68: Pulvérisation de fongicide et d’insecticide | C68: =(1000*1.5*2.5)/88 -> 42.613636 | D68: =$C68*D$7 -> 852.27273 | E68: =$C68*E$7 -> 852.27273 | F68: =$C68*F$7 -> 852.27273 | G68: =$C68*G$7 -> 852.27273 | H68: =$C68*H$7 -> 852.27273 | I68: =$C68*I$7 -> 852.27273 | J68: =$C68*J$7 -> 852.27273 | K68: =$C68*K$7 -> 852.27273 | ... M68: =$C68*M$7 -> 852.27273 | P68: Total diesel cost per season per Ha | Q68: =Q67*Q66*2 -> 38.739669
B69: Gazole pour l’irrigation | C69: =Q68 -> 38.739669 | D69: =C69*D7 -> 774.79339 | E69: =D69 -> 774.79339 | F69: =E69 -> 774.79339 | G69: =F69 -> 774.79339 | H69: =G69 -> 774.79339 | I69: =H69 -> 774.79339 | J69: =I69 -> 774.79339 | K69: =J69 -> 774.79339 | L69: =K69 -> 774.79339 | M69: =L69 -> 774.79339
B70: Récolte (y compris la main-d’œuvre) | C70: =1000*2.5/88 -> 28.409091 | D70: =$C70*D$7 -> 568.18182 | E70: =$C70*E$7 -> 568.18182 | F70: =$C70*F$7 -> 568.18182 | G70: =$C70*G$7 -> 568.18182 | H70: =$C70*H$7 -> 568.18182 | I70: =$C70*I$7 -> 568.18182 | J70: =$C70*J$7 -> 568.18182 | K70: =$C70*K$7 -> 568.18182 | ... M70: =$C70*M$7 -> 568.18182
B71: Coût total | C71: =SUM(C62:C70) -> 233.4449 | D71: =$C71*D$7 -> 4668.8979 | E71: =$C71*E$7 -> 4668.8979 | F71: =$C71*F$7 -> 4668.8979 | G71: =$C71*G$7 -> 4668.8979 | H71: =$C71*H$7 -> 4668.8979 | I71: =$C71*I$7 -> 4668.8979 | J71: =$C71*J$7 -> 4668.8979 | K71: =$C71*K$7 -> 4668.8979 | ... M71: =$C71*M$7 -> 4668.8979
B72: Rendement | D72: 800 | E72: 900 | F72: 1000 | G72: =F72 -> 1000 | H72: =G72 -> 1000 | I72: =H72 -> 1000 | J72: =I72 -> 1000 | K72: =J72 -> 1000 | L72: =K72 -> 1000 | M72: =L72 -> 1000
B73: Prix / kg | D73: 0.55 | E73: =D73 -> 0.55 | F73: =E73 -> 0.55 | G73: =F73 -> 0.55 | H73: =G73 -> 0.55 | I73: =H73 -> 0.55 | J73: =I73 -> 0.55 | K73: =J73 -> 0.55 | L73: =K73 -> 0.55 | M73: =L73 -> 0.55
B74: Réalisation | D74: =D73*D72*D7 -> 8800 | E74: =E73*E72*E7 -> 9900 | F74: =F73*F72*F7 -> 11000 | G74: =G73*G72*G7 -> 11000 | H74: =H73*H72*H7 -> 11000 | I74: =I73*I72*I7 -> 11000 | J74: =J73*J72*J7 -> 11000 | K74: =K73*K72*K7 -> 11000 | ... M74: =M73*M72*M7 -> 11000
B76: Marge opérationnelle | D76: =D74-D71 -> 4131.1021 | E76: =E74-E71 -> 5231.1021 | F76: =F74-F71 -> 6331.1021 | G76: =G74-G71 -> 6331.1021 | H76: =H74-H71 -> 6331.1021 | I76: =I74-I71 -> 6331.1021 | J76: =J74-J71 -> 6331.1021 | K76: =K74-K71 -> 6331.1021 | ... M76: =M74-M71 -> 6331.1021
A79: 5 | B79: Gombo - avec goutte-à-goutte (Okra - with drip)
B80: Description | C80: Coût/ Ha € | D80: 5 | E80: =D80 -> 5 | F80: =E80 -> 5 | G80: =F80 -> 5 | H80: =G80 -> 5 | I80: =H80 -> 5 | J80: =I80 -> 5 | K80: =J80 -> 5 | L80: =K80 -> 5 | M80: =L80 -> 5
O81: Diesel consumption per hour | P81: 10
B82: Préparation du sol | C82: =1500*2.5/88 -> 42.613636 | D82: =$C82*D$80 -> 213.06818 | E82: =$C82*E$80 -> 213.06818 | F82: =$C82*F$80 -> 213.06818 | G82: =$C82*G$80 -> 213.06818 | H82: =$C82*H$80 -> 213.06818 | I82: =$C82*I$80 -> 213.06818 | J82: =$C82*J$80 -> 213.06818 | K82: =$C82*K$80 -> 213.06818 | ... M82: =$C82*M$80 -> 213.06818 | O82: Diesel price | P82: =75/88 -> 0.85227273
B83: Coût des semences | C83: =4000*2.5/88 -> 113.63636 | D83: =$C83*D$80 -> 568.18182 | E83: =$C83*E$80 -> 568.18182 | F83: =$C83*F$80 -> 568.18182 | G83: =$C83*G$80 -> 568.18182 | H83: =$C83*H$80 -> 568.18182 | I83: =$C83*I$80 -> 568.18182 | J83: =$C83*J$80 -> 568.18182 | K83: =$C83*K$80 -> 568.18182 | ... M83: =$C83*M$80 -> 568.18182 | O83: Diese; cost /hour | P83: =P82*P81 -> 8.5227273
B84: Coût du traitement des semences | D84: =$C84*D$80 -> 0 | E84: =$C84*E$80 -> 0 | F84: =$C84*F$80 -> 0 | G84: =$C84*G$80 -> 0 | H84: =$C84*H$80 -> 0 | I84: =$C84*I$80 -> 0 | J84: =$C84*J$80 -> 0 | K84: =$C84*K$80 -> 0 | ... M84: =$C84*M$80 -> 0 | O84: Diesel cost / Ha/ hour | P84: =P83*25/66 -> 3.2283058
B85: Coût du semis | C85: =18000*2.5/88 -> 511.36364 | D85: =$C85*D$80 -> 2556.8182 | E85: =$C85*E$80 -> 2556.8182 | F85: =$C85*F$80 -> 2556.8182 | G85: =$C85*G$80 -> 2556.8182 | H85: =$C85*H$80 -> 2556.8182 | I85: =$C85*I$80 -> 2556.8182 | J85: =$C85*J$80 -> 2556.8182 | K85: =$C85*K$80 -> 2556.8182 | ... M85: =$C85*M$80 -> 2556.8182 | O85: No. of irrigations / season | P85: 9
B86: Engrais urée en 2 doses | C86: =20000*2.5/88 -> 568.18182 | D86: =$C86*D$80 -> 2840.9091 | E86: =$C86*E$80 -> 2840.9091 | F86: =$C86*F$80 -> 2840.9091 | G86: =$C86*G$80 -> 2840.9091 | H86: =$C86*H$80 -> 2840.9091 | I86: =$C86*I$80 -> 2840.9091 | J86: =$C86*J$80 -> 2840.9091 | K86: =$C86*K$80 -> 2840.9091 | ... M86: =$C86*M$80 -> 2840.9091 | O86: Total diesel cost per season per Ha | P86: =P85*P84*2 -> 58.109504
B87: Pulvérisation d’herbicide de prélevée | D87: =$C87*D$80 -> 0 | E87: =$C87*E$80 -> 0 | F87: =$C87*F$80 -> 0 | G87: =$C87*G$80 -> 0 | H87: =$C87*H$80 -> 0 | I87: =$C87*I$80 -> 0 | J87: =$C87*J$80 -> 0 | K87: =$C87*K$80 -> 0 | ... M87: =$C87*M$80 -> 0
B88: Pulvérisation de fongicide et d’insecticide | C88: =15000*2.5/88 -> 426.13636 | D88: =$C88*D$80 -> 2130.6818 | E88: =$C88*E$80 -> 2130.6818 | F88: =$C88*F$80 -> 2130.6818 | G88: =$C88*G$80 -> 2130.6818 | H88: =$C88*H$80 -> 2130.6818 | I88: =$C88*I$80 -> 2130.6818 | J88: =$C88*J$80 -> 2130.6818 | K88: =$C88*K$80 -> 2130.6818 | ... M88: =$C88*M$80 -> 2130.6818
B89: Gazole pour l’irrigation | C89: =P86 -> 58.109504 | D89: =$C89*D$80 -> 290.54752 | E89: =$C89*E$80 -> 290.54752 | F89: =$C89*F$80 -> 290.54752 | G89: =$C89*G$80 -> 290.54752 | H89: =$C89*H$80 -> 290.54752 | I89: =$C89*I$80 -> 290.54752 | J89: =$C89*J$80 -> 290.54752 | K89: =$C89*K$80 -> 290.54752 | ... M89: =$C89*M$80 -> 290.54752
B90: Récolte (y compris la main-d’œuvre) | C90: =18500*2.5/88 -> 525.56818 | D90: =$C90*D$80 -> 2627.8409 | E90: =$C90*E$80 -> 2627.8409 | F90: =$C90*F$80 -> 2627.8409 | G90: =$C90*G$80 -> 2627.8409 | H90: =$C90*H$80 -> 2627.8409 | I90: =$C90*I$80 -> 2627.8409 | J90: =$C90*J$80 -> 2627.8409 | K90: =$C90*K$80 -> 2627.8409 | ... M90: =$C90*M$80 -> 2627.8409
B91: Coût total | C91: =SUM(C82:C90) -> 2245.6095 | D91: =SUM(D82:D90) -> 11228.048 | E91: =SUM(E82:E90) -> 11228.048 | F91: =SUM(F82:F90) -> 11228.048 | G91: =SUM(G82:G90) -> 11228.048 | H91: =SUM(H82:H90) -> 11228.048 | I91: =SUM(I82:I90) -> 11228.048 | J91: =SUM(J82:J90) -> 11228.048 | ... M91: =SUM(M82:M90) -> 11228.048
B92: Rendement | D92: 8000 | E92: =D92+1000 -> 9000 | F92: =E92+1000 -> 10000 | G92: =F92+1000 -> 11000 | H92: =G92+1000 -> 12000 | I92: =H92 -> 12000 | J92: =I92 -> 12000 | K92: =J92 -> 12000 | L92: =K92 -> 12000 | M92: =L92 -> 12000
B93: Prix / kg | D93: 0.35 | E93: =D93 -> 0.35 | F93: =E93 -> 0.35 | G93: =F93 -> 0.35 | H93: =G93 -> 0.35 | I93: =H93 -> 0.35 | J93: =I93 -> 0.35 | K93: =J93 -> 0.35 | L93: =K93 -> 0.35 | M93: =L93 -> 0.35
B94: Réalisation | D94: =D93*D92*D80 -> 14000 | E94: =E93*E92*E80 -> 15750 | F94: =F93*F92*F80 -> 17500 | G94: =G93*G92*G80 -> 19250 | H94: =H93*H92*H80 -> 21000 | I94: =I93*I92*I80 -> 21000 | J94: =J93*J92*J80 -> 21000 | K94: =K93*K92*K80 -> 21000 | ... M94: =M93*M92*M80 -> 21000
B96: Marge opérationnelle | D96: =D94-D91 -> 2771.9525 | E96: =E94-E91 -> 4521.9525 | F96: =F94-F91 -> 6271.9525 | G96: =G94-G91 -> 8021.9525 | H96: =H94-H91 -> 9771.9525 | I96: =I94-I91 -> 9771.9525 | J96: =J94-J91 -> 9771.9525 | K96: =K94-K91 -> 9771.9525 | ... M96: =M94-M91 -> 9771.9525
A98: 6 | B98: Sorgho pour graine (Sorghum for Seed)
B99: Description | C99: Coût/ Ha € | D99: 10 | E99: =D99 -> 10 | F99: =E99 -> 10 | G99: =F99 -> 10 | H99: =G99 -> 10 | I99: =H99 -> 10 | J99: =I99 -> 10 | K99: =J99 -> 10 | L99: =K99 -> 10 | M99: =L99 -> 10
B100: Préparation du sol | C100: =C82 -> 42.613636 | D100: =$C100*D$99 -> 426.13636 | E100: =$C100*E$99 -> 426.13636 | F100: =$C100*F$99 -> 426.13636 | G100: =$C100*G$99 -> 426.13636 | H100: =$C100*H$99 -> 426.13636 | I100: =$C100*I$99 -> 426.13636 | J100: =$C100*J$99 -> 426.13636 | K100: =$C100*K$99 -> 426.13636 | ... M100: =$C100*M$99 -> 426.13636
B101: Coût des semences | C101: =2000/88 -> 22.727273 | D101: =$C101*D$99 -> 227.27273 | E101: =$C101*E$99 -> 227.27273 | F101: =$C101*F$99 -> 227.27273 | G101: =$C101*G$99 -> 227.27273 | H101: =$C101*H$99 -> 227.27273 | I101: =$C101*I$99 -> 227.27273 | J101: =$C101*J$99 -> 227.27273 | K101: =$C101*K$99 -> 227.27273 | ... M101: =$C101*M$99 -> 227.27273
B102: Coût du traitement des semences | C102: =C64 -> 6.3920455 | D102: =$C102*D$99 -> 63.920455 | E102: =$C102*E$99 -> 63.920455 | F102: =$C102*F$99 -> 63.920455 | G102: =$C102*G$99 -> 63.920455 | H102: =$C102*H$99 -> 63.920455 | I102: =$C102*I$99 -> 63.920455 | J102: =$C102*J$99 -> 63.920455 | K102: =$C102*K$99 -> 63.920455 | ... M102: =$C102*M$99 -> 63.920455
B103: Coût du semis | C103: =C65*2 -> 39.12 | D103: =$C103*D$99 -> 391.2 | E103: =$C103*E$99 -> 391.2 | F103: =$C103*F$99 -> 391.2 | G103: =$C103*G$99 -> 391.2 | H103: =$C103*H$99 -> 391.2 | I103: =$C103*I$99 -> 391.2 | J103: =$C103*J$99 -> 391.2 | K103: =$C103*K$99 -> 391.2 | ... M103: =$C103*M$99 -> 391.2
B104: Engrais urée en 2 doses | C104: =C66 -> 36.409091 | D104: =$C104*D$99 -> 364.09091 | E104: =$C104*E$99 -> 364.09091 | F104: =$C104*F$99 -> 364.09091 | G104: =$C104*G$99 -> 364.09091 | H104: =$C104*H$99 -> 364.09091 | I104: =$C104*I$99 -> 364.09091 | J104: =$C104*J$99 -> 364.09091 | K104: =$C104*K$99 -> 364.09091 | ... M104: =$C104*M$99 -> 364.09091
B105: Pulvérisation d’herbicide de prélevée | C105: =C67*0.7 -> 14.914773 | D105: =$C105*D$99 -> 149.14773 | E105: =$C105*E$99 -> 149.14773 | F105: =$C105*F$99 -> 149.14773 | G105: =$C105*G$99 -> 149.14773 | H105: =$C105*H$99 -> 149.14773 | I105: =$C105*I$99 -> 149.14773 | J105: =$C105*J$99 -> 149.14773 | K105: =$C105*K$99 -> 149.14773 | ... M105: =$C105*M$99 -> 149.14773
B106: Pulvérisation de fongicide et d’insecticide | C106: =C68*1.5 -> 63.920455 | D106: =$C106*D$99 -> 639.20455 | E106: =$C106*E$99 -> 639.20455 | F106: =$C106*F$99 -> 639.20455 | G106: =$C106*G$99 -> 639.20455 | H106: =$C106*H$99 -> 639.20455 | I106: =$C106*I$99 -> 639.20455 | J106: =$C106*J$99 -> 639.20455 | K106: =$C106*K$99 -> 639.20455 | ... M106: =$C106*M$99 -> 639.20455
B107: Gazole pour l’irrigation | C107: =C69 -> 38.739669 | D107: =$C107*D$99 -> 387.39669 | E107: =$C107*E$99 -> 387.39669 | F107: =$C107*F$99 -> 387.39669 | G107: =$C107*G$99 -> 387.39669 | H107: =$C107*H$99 -> 387.39669 | I107: =$C107*I$99 -> 387.39669 | J107: =$C107*J$99 -> 387.39669 | K107: =$C107*K$99 -> 387.39669 | ... M107: =$C107*M$99 -> 387.39669
B108: Récolte (y compris la main-d’œuvre) | C108: 45 | D108: =$C108*D$99 -> 450 | E108: =$C108*E$99 -> 450 | F108: =$C108*F$99 -> 450 | G108: =$C108*G$99 -> 450 | H108: =$C108*H$99 -> 450 | I108: =$C108*I$99 -> 450 | J108: =$C108*J$99 -> 450 | K108: =$C108*K$99 -> 450 | ... M108: =$C108*M$99 -> 450
B109: Coût total | C109: =SUM(C99:C108) -> 309.83694 | D109: =SUM(D99:D108) -> 3108.3694 | E109: =SUM(E99:E108) -> 3108.3694 | F109: =SUM(F99:F108) -> 3108.3694 | G109: =SUM(G99:G108) -> 3108.3694 | H109: =SUM(H99:H108) -> 3108.3694 | I109: =SUM(I99:I108) -> 3108.3694 | J109: =SUM(J99:J108) -> 3108.3694 | ... M109: =SUM(M99:M108) -> 3108.3694
B110: Rendement | D110: 2000 | E110: =D110*1.1 -> 2200 | F110: =E110*1.1 -> 2420 | G110: =F110*1.1 -> 2662 | H110: =G110*1.1 -> 2928.2 | I110: =H110 -> 2928.2 | J110: =I110 -> 2928.2 | K110: =J110 -> 2928.2 | L110: =K110 -> 2928.2 | M110: =L110 -> 2928.2
B111: Prix / kg | D111: =(0.4/75)*88 -> 0.46933333 | E111: =D111 -> 0.46933333 | F111: =E111 -> 0.46933333 | G111: =F111 -> 0.46933333 | H111: =G111 -> 0.46933333 | I111: =H111 -> 0.46933333 | J111: =I111 -> 0.46933333 | K111: =J111 -> 0.46933333 | L111: =K111 -> 0.46933333 | M111: =L111 -> 0.46933333
B112: Réalisation | D112: =D111*D110*D99 -> 9386.6667 | E112: =E111*E110*E99 -> 10325.333 | F112: =F111*F110*F99 -> 11357.867 | G112: =G111*G110*G99 -> 12493.653 | H112: =H111*H110*H99 -> 13743.019 | I112: =I111*I110*I99 -> 13743.019 | J112: =J111*J110*J99 -> 13743.019 | K112: =K111*K110*K99 -> 13743.019 | ... M112: =M111*M110*M99 -> 13743.019
B114: Marge opérationnelle | D114: =D112-D109 -> 6278.2972 | E114: =E112-E109 -> 7216.9639 | F114: =F112-F109 -> 8249.4972 | G114: =G112-G109 -> 9385.2839 | H114: =H112-H109 -> 10634.649 | I114: =I112-I109 -> 10634.649 | J114: =J112-J109 -> 10634.649 | K114: =K112-K109 -> 10634.649 | ... M114: =M112-M109 -> 10634.649
A116: 7 | B116: Oignon - avec goutte-à-goutte (Onion - with drip)
...

Sheet Matière 1é & fourni Agriculture
C3: 1 Arachide (Groundnut) | K3: 2 Niébé (Cowpea) | T3: 3 Céréale, blé, mais (Wheat, corne) | AB3: 4 Sesame | AI3: 5 Gombo - avec goutte-à-goutte | AP3: 6 Sorgho pour graine | AW3: 7 Oignon - avec goutte-à-goutte | BD3: 8 Aubergine - avec goutte-à-goutte et paillage | BK3: 9 Tomate - avec goutte-à-goutte et paillage | BR3: 10 Pomme de terre en hiver avec irrigation | BY3: 11 Luzerne (Alfa Alfa) en irrigation | CF3: 12 Verget pour arbre fruitiers | CN3: 13 Agroforesterie & haie vive
C4: Arachide (Groundnut) | K4: Niébé (Cowpea) | T4: Céréale, blé, mais (Wheat, corne, ) | AB4: Sesame | AI4: Gombo - avec goutte-à-goutte (Okra - with drip) | AP4: Sorgho pour graine (Sorghum for Seed) | AW4: Oignon - avec goutte-à-goutte (Onion - with drip) | BD4: Aubergine - avec goutte-à-goutte et paillage | BK4: Tomate - avec goutte-à-goutte et paillage | BR4: Pomme de terre en hiver avec irrigation | BY4: Luzerne (Alfa Alfa) en irrigation | CF4: Verget pour arbre fruitiers | CN4: Agroforesterie & haie vive
C5: Matière première | D5: Octobre | E5: Novembre | F5: Décembre | G5: Total vendu | K5: Matière première | L5: Octobre | M5: Novembre | N5: Décembre | O5: Total vendu | T5: Matière première | U5: Octobre | V5: Novembre | W5: Décembre | X5: Total vendu | AB5: Matière première | AC5: Octobre | AD5: Novembre | AE5: Décembre | AF5: Total vendu | AI5: Matière première | AJ5: Octobre | AK5: Novembre | AL5: Décembre | AM5: Total vendu | AP5: Matière première | AQ5: Octobre | AR5: Novembre | AS5: Décembre | AT5: Total vendu | AW5: Matière première | AX5: Octobre | AY5: Novembre | AZ5: Décembre | BA5: Total vendu | BD5: Matière première | BE5: Octobre | BF5: Novembre | BG5: Décembre | BH5: Total vendu | BK5: Matière première | BL5: Octobre | BM5: Novembre | BN5: Décembre | BO5: Total vendu | BR5: Matière première | BS5: Octobre | BT5: Novembre | BU5: Décembre | BV5: Total vendu | BY5: Matière première | BZ5: Octobre | CA5: Novembre | CB5: Décembre | CC5: Total vendu | CF5: Matière première | CG5: Octobre | CH5: Novembre | CI5: Décembre | CJ5: Total vendu | CN5: Matière première | CO5: Octobre | CP5: Novembre | CQ5: Décembre | CR5: Total vendu
C6: Superficie cultivée en pluviale | D6: =+'[2]Ca...'!C6+'[2]Ca...'!C11+'[2]Ca...'!C17 -> 0 | F6: 0 | G6: =+SUM(C6:F6) -> 0 | K6: Superficie cultivée en pluviale | L6: =+'[2]Ca...'!K6+'[2]Ca...'!K11+'[2]Ca...'!K17 -> 0 | O6: =+SUM(K6:N6) -> 0 | T6: Superficie cultivée en pluviale | X6: =+SUM(T6:W6) -> 0 | AB6: Superficie cultivée en pluviale | AE6: 0 | AF6: =+SUM(AB6:AE6) -> 0 | AI6: Superficie cultivée en irriguation | AL6: 0 | AM6: =+SUM(AI6:AL6) -> 0 | AP6: Superficie cultivée en irriguation | AS6: 0 | AT6: =+SUM(AP6:AS6) -> 0 | AW6: Superficie cultivée en irriguation | AZ6: 0 | BA6: =+SUM(AW6:AZ6) -> 0 | BD6: Superficie cultivée en irriguation | BG6: 0 | BH6: =+SUM(BD6:BG6) -> 0 | BK6: Superficie cultivée en irriguation | BN6: 0 | BO6: =+SUM(BK6:BN6) -> 0 | BR6: Superficie cultivée en irriguation | BU6: 0 | BV6: =+SUM(BR6:BU6) -> 0 | BY6: Superficie cultivée en irriguation | CB6: 0 | CC6: =+SUM(BY6:CB6) -> 0 | CF6: Superficie cultivée en irriguation | CI6: 0 | CJ6: =+SUM(CF6:CI6) -> 0 | CN6: Superficie cultivée en irriguation | CQ6: 0 | CR6: =+SUM(CN6:CQ6) -> 0
C7: Coût unitaire par hectare (504€/H) | E7: =SUM('Coûts de product° Agricole'!C17)*657 -> 331418.26 | F7: =SUM(E7) -> 331418.26 | K7: Coût unitaire par hectare (498€/H) | L7: =SUM('Coûts de product° Agricole'!C35)*657 -> 327710.03 | M7: =SUM(L7) -> 327710.03 | N7: =SUM(M7) -> 327710.03 | T7: Coût unitaire par hectare (688€/H) | U7: =SUM('Coûts de product° Agricole'!C53)*657 -> 452321.48 | V7: =SUM(U7) -> 452321.48 | W7: =SUM(V7) -> 452321.48 | AB7: Coût unitaire par hectare (233€/H) | AC7: =SUM('Coûts de product° Agricole'!C71)*657 -> 153373.3 | AE7: 0 | AI7: Coût unitaire par hectare (2245€/H) | AJ7: =SUM('Coûts de product° Agricole'!C91)*657 -> 1475365.4 | AL7: 0 | AP7: Coût unitaire par hectare (309€/H) | AQ7: =SUM('Coûts de product° Agricole'!C109)*657 -> 203562.87 | AS7: 0 | AW7: Coût unitaire par hectare (1364€/H) | AX7: =SUM('Coûts de product° Agricole'!C127)*657 -> 896757.49 | AZ7: 0 | BD7: Coût unitaire par hectare (4398€/H) | BE7: =SUM('Coûts de product° Agricole'!C145)*657 -> 2890070.4 | BG7: 0 | BK7: Coût unitaire par hectare (4725€/H) | BL7: =SUM('Coûts de product° Agricole'!C163)*657 -> 3104715.3 | BN7: 0 | BR7: Coût unitaire par hectare (1603€/H) | BS7: =SUM('Coûts de product° Agricole'!C181)*657 -> 1053822.6 | BU7: 0 | BY7: Coût unitaire par hectare (834€/H) | BZ7: =SUM('Coûts de product° Agricole'!C199)*657 -> 548466.59 | CB7: 0 | CF7: Coût unitaire par hectare (1900€/H) | CG7: =SUM(CE12)*CE13 -> 1250000 | CI7: 0 | CN7: Coût unitaire par hectare (914€/H) | CO7: =SUM(CM12)*CM13 -> 600000 | CQ7: 0
C8: Sous-total | D8: =+D7*D6 -> 0 | E8: =+E7*E6 -> 0 | F8: =+F7*F6 -> 0 | K8: Sous-total | L8: =+L7*L6 -> 0 | M8: =+M7*M6 -> 0 | N8: =+N7*N6 -> 0 | T8: Sous-total | U8: =+U7*U6 -> 0 | V8: =+V7*V6 -> 0 | W8: =+W7*W6 -> 0 | AB8: Sous-total | AC8: =+AC7*AC6 -> 0 | AD8: =+AD7*AD6 -> 0 | AE8: =+AE7*AE6 -> 0 | AI8: Sous-total | AJ8: =+AJ7*AJ6 -> 0 | AK8: =+AK7*AK6 -> 0 | AL8: =+AL7*AL6 -> 0 | AP8: Sous-total | AQ8: =+AQ7*AQ6 -> 0 | AR8: =+AR7*AR6 -> 0 | AS8: =+AS7*AS6 -> 0 | AW8: Sous-total | AX8: =+AX7*AX6 -> 0 | AY8: =+AY7*AY6 -> 0 | AZ8: =+AZ7*AZ6 -> 0 | BD8: Sous-total | BE8: =+BE7*BE6 -> 0 | BF8: =+BF7*BF6 -> 0 | BG8: =+BG7*BG6 -> 0 | BK8: Sous-total | BL8: =+BL7*BL6 -> 0 | BM8: =+BM7*BM6 -> 0 | BN8: =+BN7*BN6 -> 0 | BR8: Sous-total | BS8: =+BS7*BS6 -> 0 | BT8: =+BT7*BT6 -> 0 | BU8: =+BU7*BU6 -> 0 | BY8: Sous-total | BZ8: =+BZ7*BZ6 -> 0 | CA8: =+CA7*CA6 -> 0 | CB8: =+CB7*CB6 -> 0 | CF8: Sous-total | CG8: =+CG7*CG6 -> 0 | CH8: =+CH7*CH6 -> 0 | CI8: =+CI7*CI6 -> 0 | CN8: Sous-total | CO8: =+CO7*CO6 -> 0 | CP8: =+CP7*CP6 -> 0 | CQ8: =+CQ7*CQ6 -> 0
C9: Sous-total cumulé | D9: =+D8 -> 0 | E9: =+D9+E8 -> 0 | F9: =+E9+F8 -> 0 | K9: Sous-total cumulé | L9: =+L8 -> 0 | M9: =+L9+M8 -> 0 | N9: =+M9+N8 -> 0 | T9: Sous-total cumulé | U9: =+U8 -> 0 | V9: =+U9+V8 -> 0 | W9: =+V9+W8 -> 0 | AB9: Sous-total cumulé | AC9: =+AC8 -> 0 | AD9: =+AC9+AD8 -> 0 | AE9: =+AD9+AE8 -> 0 | AI9: Sous-total cumulé | AJ9: =+AJ8 -> 0 | AK9: =+AJ9+AK8 -> 0 | AL9: =+AK9+AL8 -> 0 | AP9: Sous-total cumulé | AQ9: =+AQ8 -> 0 | AR9: =+AQ9+AR8 -> 0 | AS9: =+AR9+AS8 -> 0 | AW9: Sous-total cumulé | AX9: =+AX8 -> 0 | AY9: =+AX9+AY8 -> 0 | AZ9: =+AY9+AZ8 -> 0 | BD9: Sous-total cumulé | BE9: =+BE8 -> 0 | BF9: =+BE9+BF8 -> 0 | BG9: =+BF9+BG8 -> 0 | BK9: Sous-total cumulé | BL9: =+BL8 -> 0 | BM9: =+BL9+BM8 -> 0 | BN9: =+BM9+BN8 -> 0 | BR9: Sous-total cumulé | BS9: =+BS8 -> 0 | BT9: =+BS9+BT8 -> 0 | BU9: =+BT9+BU8 -> 0 | BY9: Sous-total cumulé | BZ9: =+BZ8 -> 0 | CA9: =+BZ9+CA8 -> 0 | CB9: =+CA9+CB8 -> 0 | CF9: Sous-total cumulé | CG9: =+CG8 -> 0 | CH9: =+CG9+CH8 -> 0 | CI9: =+CH9+CI8 -> 0 | CN9: Sous-total cumulé | CO9: =+CO8 -> 0 | CP9: =+CO9+CP8 -> 0 | CQ9: =+CP9+CQ8 -> 0
D11: =+'[2]Ca...'!C11 -> 0 | E11: =+'[2]Ca...'!D11 -> 0 | F11: =+'[2]Ca...'!E11 -> 0 | L11: =+'[2]Ca...'!K11 -> 0 | M11: =+'[2]Ca...'!L11 -> 0 | N11: =+'[2]Ca...'!M11 -> 0 | W11: =+'[2]Ca...'!V11 -> 0
G12: =+SUM(C12:F12) -> 0 | O12: =+SUM(K12:N12) -> 0 | X12: =+SUM(T12:W12) -> 0 | AF12: =+SUM(AB12:AE12) -> 0 | AM12: =+SUM(AI12:AL12) -> 0 | AT12: =+SUM(AP12:AS12) -> 0 | BA12: =+SUM(AW12:AZ12) -> 0 | BH12: =+SUM(BD12:BG12) -> 0 | BO12: =+SUM(BK12:BN12) -> 0 | BV12: =+SUM(BR12:BU12) -> 0 | CC12: =+SUM(BY12:CB12) -> 0 | CE12: 500 | CF12: 500 pieds de fruitier à l'hectare | CJ12: =+SUM(CF12:CI12) -> 0 | CM12: 2000 | CN12: 2000 pieds d'acacia au kilometre | CR12: =+SUM(CN12:CQ12) -> 0
CE13: 2500 | CF13: Prix unitaire de la pepiniere 2500 Fr | CM13: 300 | CN13: Prix unitaire de la pepiniere 300 Fr
D14: =+D13*D12 -> 0 | E14: =+E13*E12 -> 0 | F14: =+F13*F12 -> 0 | L14: =+L13*L12 -> 0 | M14: =+M13*M12 -> 0 | N14: =+N13*N12 -> 0 | U14: =+U13*U12 -> 0 | V14: =+V13*V12 -> 0 | W14: =+W13*W12 -> 0 | AC14: =+AC13*AC12 -> 0 | AD14: =+AD13*AD12 -> 0 | AE14: =+AE13*AE12 -> 0 | AJ14: =+AJ13*AJ12 -> 0 | AK14: =+AK13*AK12 -> 0 | AL14: =+AL13*AL12 -> 0 | AQ14: =+AQ13*AQ12 -> 0 | AR14: =+AR13*AR12 -> 0 | AS14: =+AS13*AS12 -> 0 | AX14: =+AX13*AX12 -> 0 | AY14: =+AY13*AY12 -> 0 | AZ14: =+AZ13*AZ12 -> 0 | BE14: =+BE13*BE12 -> 0 | BF14: =+BF13*BF12 -> 0 | BG14: =+BG13*BG12 -> 0 | BL14: =+BL13*BL12 -> 0 | BM14: =+BM13*BM12 -> 0 | BN14: =+BN13*BN12 -> 0 | BS14: =+BS13*BS12 -> 0 | BT14: =+BT13*BT12 -> 0 | BU14: =+BU13*BU12 -> 0 | BZ14: =+BZ13*BZ12 -> 0 | CA14: =+CA13*CA12 -> 0 | CB14: =+CB13*CB12 -> 0 | CG14: =+CG13*CG12 -> 0 | CH14: =+CH13*CH12 -> 0 | CI14: =+CI13*CI12 -> 0 | CO14: =+CO13*CO12 -> 0 | CP14: =+CP13*CP12 -> 0 | CQ14: =+CQ13*CQ12 -> 0
D15: =+D14 -> 0 | E15: =+D15+E14 -> 0 | F15: =+E15+F14 -> 0 | L15: =+L14 -> 0 | M15: =+L15+M14 -> 0 | N15: =+M15+N14 -> 0 | U15: =+U14 -> 0 | V15: =+U15+V14 -> 0 | W15: =+V15+W14 -> 0 | AC15: =+AC14 -> 0 | AD15: =+AC15+AD14 -> 0 | AE15: =+AD15+AE14 -> 0 | AJ15: =+AJ14 -> 0 | AK15: =+AJ15+AK14 -> 0 | AL15: =+AK15+AL14 -> 0 | AQ15: =+AQ14 -> 0 | AR15: =+AQ15+AR14 -> 0 | AS15: =+AR15+AS14 -> 0 | AX15: =+AX14 -> 0 | AY15: =+AX15+AY14 -> 0 | AZ15: =+AY15+AZ14 -> 0 | BE15: =+BE14 -> 0 | BF15: =+BE15+BF14 -> 0 | BG15: =+BF15+BG14 -> 0 | BL15: =+BL14 -> 0 | BM15: =+BL15+BM14 -> 0 | BN15: =+BM15+BN14 -> 0 | BS15: =+BS14 -> 0 | BT15: =+BS15+BT14 -> 0 | BU15: =+BT15+BU14 -> 0 | BZ15: =+BZ14 -> 0 | CA15: =+BZ15+CA14 -> 0 | CB15: =+CA15+CB14 -> 0 | CG15: =+CG14 -> 0 | CH15: =+CG15+CH14 -> 0 | CI15: =+CH15+CI14 -> 0 | CO15: =+CO14 -> 0 | CP15: =+CO15+CP14 -> 0 | CQ15: =+CP15+CQ14 -> 0
D17: =+'[2]Ca...'!C17 -> 0 | E17: =+'[2]Ca...'!D17 -> 0 | F17: =+'[2]Ca...'!E17 -> 0 | L17: =+'[2]Ca...'!K17 -> 0 | M17: =+'[2]Ca...'!L17 -> 0 | N17: =+'[2]Ca...'!M17 -> 0 | W17: =+'[2]Ca...'!V28 -> 0
F18: 0 | G18: =+SUM(C18:F18) -> 0 | N18: 0 | O18: =+SUM(K18:N18) -> 0 | W18: 0 | X18: =+SUM(T18:W18) -> 0 | AE18: 0 | AF18: =+SUM(AB18:AE18) -> 0 | AL18: 0 | AM18: =+SUM(AI18:AL18) -> 0 | AS18: 0 | AT18: =+SUM(AP18:AS18) -> 0 | AZ18: 0 | BA18: =+SUM(AW18:AZ18) -> 0 | BG18: 0 | BH18: =+SUM(BD18:BG18) -> 0 | BN18: 0 | BO18: =+SUM(BK18:BN18) -> 0 | BU18: 0 | BV18: =+SUM(BR18:BU18) -> 0 | CB18: 0 | CC18: =+SUM(BY18:CB18) -> 0 | CI18: 0 | CJ18: =+SUM(CF18:CI18) -> 0 | CQ18: 0 | CR18: =+SUM(CN18:CQ18) -> 0
F19: 0 | N19: 0 | W19: 0 | AE19: 0 | AL19: 0 | AS19: 0 | AZ19: 0 | BG19: 0 | BN19: 0 | BU19: 0 | CB19: 0 | CI19: 0 | CQ19: 0
D20: =+D19*D18 -> 0 | F20: =+F19*F18 -> 0 | L20: =+L19*L18 -> 0 | N20: =+N19*N18 -> 0 | U20: =+U19*U18 -> 0 | W20: =+W19*W18 -> 0 | AC20: =+AC19*AC18 -> 0 | AE20: =+AE19*AE18 -> 0 | AJ20: =+AJ19*AJ18 -> 0 | AL20: =+AL19*AL18 -> 0 | AQ20: =+AQ19*AQ18 -> 0 | AS20: =+AS19*AS18 -> 0 | AX20: =+AX19*AX18 -> 0 | AZ20: =+AZ19*AZ18 -> 0 | BE20: =+BE19*BE18 -> 0 | BG20: =+BG19*BG18 -> 0 | BL20: =+BL19*BL18 -> 0 | BN20: =+BN19*BN18 -> 0 | BS20: =+BS19*BS18 -> 0 | BU20: =+BU19*BU18 -> 0 | BZ20: =+BZ19*BZ18 -> 0 | CB20: =+CB19*CB18 -> 0 | CG20: =+CG19*CG18 -> 0 | CI20: =+CI19*CI18 -> 0 | CO20: =+CO19*CO18 -> 0 | CQ20: =+CQ19*CQ18 -> 0
D21: =+D20 -> 0 | E21: =+D21+E20 -> 0 | F21: =+E21+F20 -> 0 | L21: =+L20 -> 0 | M21: =+L21+M20 -> 0 | N21: =+M21+N20 -> 0 | U21: =+U20 -> 0 | V21: =+U21+V20 -> 0 | W21: =+V21+W20 -> 0 | AC21: =+AC20 -> 0 | AD21: =+AC21+AD20 -> 0 | AE21: =+AD21+AE20 -> 0 | AJ21: =+AJ20 -> 0 | AK21: =+AJ21+AK20 -> 0 | AL21: =+AK21+AL20 -> 0 | AQ21: =+AQ20 -> 0 | AR21: =+AQ21+AR20 -> 0 | AS21: =+AR21+AS20 -> 0 | AX21: =+AX20 -> 0 | AY21: =+AX21+AY20 -> 0 | AZ21: =+AY21+AZ20 -> 0 | BE21: =+BE20 -> 0 | BF21: =+BE21+BF20 -> 0 | BG21: =+BF21+BG20 -> 0 | BL21: =+BL20 -> 0 | BM21: =+BL21+BM20 -> 0 | BN21: =+BM21+BN20 -> 0 | BS21: =+BS20 -> 0 | BT21: =+BS21+BT20 -> 0 | BU21: =+BT21+BU20 -> 0 | BZ21: =+BZ20 -> 0 | CA21: =+BZ21+CA20 -> 0 | CB21: =+CA21+CB20 -> 0 | CG21: =+CG20 -> 0 | CH21: =+CG21+CH20 -> 0 | CI21: =+CH21+CI20 -> 0 | CO21: =+CO20 -> 0 | CP21: =+CO21+CP20 -> 0 | CQ21: =+CP21+CQ20 -> 0
C23: Totaux | D23: =+D8+D14+D20 -> 0 | E23: =+E20+E14+E8 -> 0 | F23: =+F20+F14+F8 -> 0 | G23: =+SUM(G6:G22) -> 0 | K23: Totaux | L23: =+L8+L14+L20 -> 0 | M23: =+M20+M14+M8 -> 0 | N23: =+N20+N14+N8 -> 0 | O23: =+SUM(O6:O22) -> 0 | T23: Totaux | U23: =+U8+U14+U20 -> 0 | V23: =+V20+V14+V8 -> 0 | W23: =+W20+W14+W8 -> 0 | X23: =+SUM(X6:X22) -> 0 | AB23: Totaux | AC23: =+AC8+AC14+AC20 -> 0 | AD23: =+AD20+AD14+AD8 -> 0 | AE23: =+AE20+AE14+AE8 -> 0 | AF23: =+SUM(AF6:AF22) -> 0 | AI23: Totaux | AJ23: =+AJ8+AJ14+AJ20 -> 0 | AK23: =+AK20+AK14+AK8 -> 0 | AL23: =+AL20+AL14+AL8 -> 0 | AM23: =+SUM(AM6:AM22) -> 0 | AP23: Totaux | AQ23: =+AQ8+AQ14+AQ20 -> 0 | AR23: =+AR20+AR14+AR8 -> 0 | AS23: =+AS20+AS14+AS8 -> 0 | AT23: =+SUM(AT6:AT22) -> 0 | AW23: Totaux | AX23: =+AX8+AX14+AX20 -> 0 | AY23: =+AY20+AY14+AY8 -> 0 | AZ23: =+AZ20+AZ14+AZ8 -> 0 | BA23: =+SUM(BA6:BA22) -> 0 | BD23: Totaux | BE23: =+BE8+BE14+BE20 -> 0 | BF23: =+BF20+BF14+BF8 -> 0 | BG23: =+BG20+BG14+BG8 -> 0 | BH23: =+SUM(BH6:BH22) -> 0 | BK23: Totaux | BL23: =+BL8+BL14+BL20 -> 0 | BM23: =+BM20+BM14+BM8 -> 0 | BN23: =+BN20+BN14+BN8 -> 0 | BO23: =+SUM(BO6:BO22) -> 0 | BR23: Totaux | BS23: =+BS8+BS14+BS20 -> 0 | BT23: =+BT20+BT14+BT8 -> 0 | BU23: =+BU20+BU14+BU8 -> 0 | BV23: =+SUM(BV6:BV22) -> 0 | BY23: Totaux | BZ23: =+BZ8+BZ14+BZ20 -> 0 | CA23: =+CA20+CA14+CA8 -> 0 | CB23: =+CB20+CB14+CB8 -> 0 | CC23: =+SUM(CC6:CC22) -> 0 | CF23: Totaux | CG23: =+CG8+CG14+CG20 -> 0 | CH23: =+CH20+CH14+CH8 -> 0 | CI23: =+CI20+CI14+CI8 -> 0 | CJ23: =+SUM(CJ6:CJ22) -> 0 | CN23: Totaux | CO23: =+CO8+CO14+CO20 -> 0 | CP23: =+CP20+CP14+CP8 -> 0 | CQ23: =+CQ20+CQ14+CQ8 -> 0 | CR23: =+SUM(CR6:CR22) -> 0
C24: Totaux cumulés | D24: =+D23 -> 0 | E24: =+D24+E23 -> 0 | F24: =+E24+F23 -> 0 | K24: Totaux cumulés | L24: =+L23 -> 0 | M24: =+L24+M23 -> 0 | N24: =+M24+N23 -> 0 | T24: Totaux cumulés | U24: =+U23 -> 0 | V24: =+U24+V23 -> 0 | W24: =+V24+W23 -> 0 | AB24: Totaux cumulés | AC24: =+AC23 -> 0 | AD24: =+AC24+AD23 -> 0 | AE24: =+AD24+AE23 -> 0 | AI24: Totaux cumulés | AJ24: =+AJ23 -> 0 | AK24: =+AJ24+AK23 -> 0 | AL24: =+AK24+AL23 -> 0 | AP24: Totaux cumulés | AQ24: =+AQ23 -> 0 | AR24: =+AQ24+AR23 -> 0 | AS24: =+AR24+AS23 -> 0 | AW24: Totaux cumulés | AX24: =+AX23 -> 0 | AY24: =+AX24+AY23 -> 0 | AZ24: =+AY24+AZ23 -> 0 | BD24: Totaux cumulés | BE24: =+BE23 -> 0 | BF24: =+BE24+BF23 -> 0 | BG24: =+BF24+BG23 -> 0 | BK24: Totaux cumulés | BL24: =+BL23 -> 0 | BM24: =+BL24+BM23 -> 0 | BN24: =+BM24+BN23 -> 0 | BR24: Totaux cumulés | BS24: =+BS23 -> 0 | BT24: =+BS24+BT23 -> 0 | BU24: =+BT24+BU23 -> 0 | BY24: Totaux cumulés | BZ24: =+BZ23 -> 0 | CA24: =+BZ24+CA23 -> 0 | CB24: =+CA24+CB23 -> 0 | CF24: Totaux cumulés | CG24: =+CG23 -> 0 | CH24: =+CG24+CH23 -> 0 | CI24: =+CH24+CI23 -> 0 | CN24: Totaux cumulés | CO24: =+CO23 -> 0 | CP24: =+CO24+CP23 -> 0 | CQ24: =+CP24+CQ23 -> 0
C27: Arachide (Groundnut) 2026 | K27: Niébé (Cowpea) 2026 | T27: Céréale, blé, mais (Wheat, corne, ) 2026 | Y27: Total acheté | AB27: Sesame 2026 | AG27: Total acheté | AI27: Gombo - avec goutte-à-goutte (Okra - with drip) 2026 | AN27: Total acheté | AP27: Sorgho pour graine (Sorghum for Seed) 2026 | AU27: Total acheté | AW27: Oignon - avec goutte-à-goutte (Onion - with drip) 2026 | BB27: Total acheté | BD27: Aubergine - avec goutte-à-goutte et paillage 2026 | BI27: Total acheté | BK27: Tomate - avec goutte-à-goutte et paillage 2026 | BP27: Total acheté | BR27: Pomme de terre en hiver avec irrigation 2026 | BW27: Total acheté | BY27: Luzerne (Alfa Alfa) en irrigation 2026 | CD27: Total acheté | CF27: Verget pour arbre fruitiers 2026 | CK27: Total acheté | CN27: Verget pour arbre fruitiers 2026 | CS27: Total acheté
C28: Matière première | D28: 1er trimestre | E28: 2ème trimestre | F28: 3ème trimestre | G28: 4ème trimestre | H28: Total Acheté | K28: Matière première | L28: 1er trimestre | M28: 2ème trimestre | N28: 3ème trimestre | O28: 4ème trimestre | P28: Total Acheté | T28: Achat de production | U28: 1er trimestre | V28: 2ème trimestre | W28: 3ème trimestre | X28: 4ème trimestre | Y28: Total Acheté | AB28: Achat de production | AC28: 1er trimestre | AD28: 2ème trimestre | AE28: 3ème trimestre | AF28: 4ème trimestre | AG28: Total acheté | AI28: Achat de production | AJ28: 1er trimestre | AK28: 2ème trimestre | AL28: 3ème trimestre | AM28: 4ème trimestre | AN28: Total acheté | AP28: Achat de production | AQ28: 1er trimestre | AR28: 2ème trimestre | AS28: 3ème trimestre | AT28: 4ème trimestre | AU28: Total acheté | AW28: Achat de production | AX28: 1er trimestre | AY28: 2ème trimestre | AZ28: 3ème trimestre | BA28: 4ème trimestre | BB28: Total acheté | BD28: Achat de production | BE28: 1er trimestre | BF28: 2ème trimestre | BG28: 3ème trimestre | BH28: 4ème trimestre | BI28: Total acheté | BK28: Achat de production | BL28: 1er trimestre | BM28: 2ème trimestre | BN28: 3ème trimestre | BO28: 4ème trimestre | BP28: Total acheté | BR28: Achat de production | BS28: 1er trimestre | BT28: 2ème trimestre | BU28: 3ème trimestre | BV28: 4ème trimestre | BW28: Total acheté | BY28: Achat de production | BZ28: 1er trimestre | CA28: 2ème trimestre | CB28: 3ème trimestre | CC28: 4ème trimestre | CD28: Total acheté | CF28: Achat de production | CG28: 1er trimestre | CH28: 2ème trimestre | CI28: 3ème trimestre | CJ28: 4ème trimestre | CK28: Total acheté | CN28: Achat de production | CO28: 1er trimestre | CP28: 2ème trimestre | CQ28: 3ème trimestre | CR28: 4ème trimestre | CS28: Total acheté
C29: Superficie cultivée en pluviale | E29: 20 | H29: =+SUM(D29:G29) -> 20 | K29: Superficie cultivée en pluviale | M29: 10 | P29: =+SUM(L29:O29) -> 10 | T29: Superficie cultivée en pluviale | V29: 20 | Y29: =+SUM(U29:X29) -> 20 | AB29: Superficie cultivée en pluviale | AD29: 10 | AG29: =SUM(AC29:AF29) -> 10 | AI29: Superficie cultivée en irriguation | AM29: 5 | AN29: =SUM(AJ29:AM29) -> 5 | AP29: Superficie cultivée en irriguation | AT29: 10 | AU29: =SUM(AQ29:AT29) -> 10 | AW29: Superficie cultivée en irriguation | AX29: 10 | BB29: =SUM(AX29:BA29) -> 10 | BD29: Superficie cultivée en irriguation | BE29: 5 | BI29: =SUM(BE29:BH29) -> 5 | BK29: Superficie cultivée en irriguation | BN29: 10 | BP29: =SUM(BL29:BO29) -> 10 | BR29: Superficie cultivée en irriguation | BU29: 5 | BW29: =SUM(BS29:BV29) -> 5 | BY29: Superficie cultivée en irriguation | CC29: 10 | CD29: =SUM(BZ29:CC29) -> 10 | CF29: Superficie cultivée en irriguation | CG29: 5 | CK29: =SUM(CG29:CJ29) -> 5 | CN29: Superficie cultivée en irriguation | CO29: 5 | CS29: =SUM(CO29:CR29) -> 5
C30: Coût unitaire par hectare (504€/H) | D30: =SUM(F7) -> 331418.26 | E30: =+D30 -> 331418.26 | F30: =+E30 -> 331418.26 | G30: =SUM(F7) -> 331418.26 | K30: Coût unitaire par hectare (498€/H) | L30: =SUM(L7) -> 327710.03 | M30: =+L30 -> 327710.03 | N30: =+M30 -> 327710.03 | O30: =SUM(N30) -> 327710.03 | T30: Coût unitaire par hectare (688€/H) | U30: =SUM(U7) -> 452321.48 | V30: =SUM(U30) -> 452321.48 | W30: =SUM(V30) -> 452321.48 | X30: =SUM(W30) -> 452321.48 | AB30: Coût unitaire par hectare (233€/H) | AC30: =SUM(AC7) -> 153373.3 | AD30: =SUM(AC30) -> 153373.3 | AE30: =SUM(AD30) -> 153373.3 | AF30: =SUM(AE30) -> 153373.3 | AI30: Coût unitaire par hectare (2245€/H) | AJ30: =SUM(AJ7) -> 1475365.4 | AK30: =SUM(AJ30) -> 1475365.4 | AL30: =SUM(AK30) -> 1475365.4 | AM30: =SUM(AL30) -> 1475365.4 | AP30: Coût unitaire par hectare (233€/H) | AQ30: =SUM(AQ7) -> 203562.87 | AR30: =SUM(AQ30) -> 203562.87 | AS30: =SUM(AR30) -> 203562.87 | AT30: =SUM(AS30) -> 203562.87 | AW30: Coût unitaire par hectare ((1364€/H) | AX30: =SUM(AX7) -> 896757.49 | AY30: =SUM(AX30) -> 896757.49 | AZ30: =SUM(AY30) -> 896757.49 | BA30: =SUM(AZ30) -> 896757.49 | BD30: Coût unitaire par hectare ((4398€/H) | BE30: =SUM(BE7) -> 2890070.4 | BF30: =SUM(BE30) -> 2890070.4 | BG30: =SUM(BF30) -> 2890070.4 | BH30: =SUM(BG30) -> 2890070.4 | BK30: Coût unitaire par hectare (4725€/H) | BL30: =SUM(BL7) -> 3104715.3 | BM30: =SUM(BL30) -> 3104715.3 | BN30: =SUM(BM30) -> 3104715.3 | BO30: =SUM(BN30) -> 3104715.3 | BR30: Coût unitaire par hectare (1603€/H) | BS30: =SUM(BS7) -> 1053822.6 | BT30: =SUM(BS30) -> 1053822.6 | BU30: =SUM(BT30) -> 1053822.6 | BV30: =SUM(BU30) -> 1053822.6 | BY30: Coût unitaire par hectare (834€/H) | BZ30: =SUM(BZ7) -> 548466.59 | CA30: =SUM(BZ30) -> 548466.59 | CB30: =SUM(CA30) -> 548466.59 | CC30: =SUM(CB30) -> 548466.59 | CF30: Coût unitaire par hectare (1900€/H) | CG30: =SUM(CG7) -> 1250000 | CH30: =SUM(CG30) -> 1250000 | CI30: =SUM(CH30) -> 1250000 | CJ30: =SUM(CI30) -> 1250000 | CN30: Coût unitaire par hectare (834€/H) | CO30: =SUM(CO7) -> 600000 | CP30: =SUM(CO30) -> 600000 | CQ30: =SUM(CP30) -> 600000 | CR30: =SUM(CQ30) -> 600000
C31: Sous-total | D31: =+D30*D29 -> 0 | E31: =+E30*E29 -> 6628365.2 | F31: =+F30*F29 -> 0 | G31: =+G30*G29 -> 0 | K31: Sous-total | L31: =+L30*L29 -> 0 | M31: =+M30*M29 -> 3277100.3 | N31: =+N30*N29 -> 0 | O31: =+O30*O29 -> 0 | T31: Sous-total | U31: =+U30*U29 -> 0 | V31: =+V30*V29 -> 9046429.6 | W31: =+W30*W29 -> 0 | X31: =+X30*X29 -> 0 | AB31: Sous-total | AC31: =+AC30*AC29 -> 0 | AD31: =+AD30*AD29 -> 1533733 | AE31: =+AE30*AE29 -> 0 | AF31: =+AF30*AF29 -> 0 | AI31: Sous-total | AJ31: =+AJ30*AJ29 -> 0 | AK31: =+AK30*AK29 -> 0 | AL31: =+AL30*AL29 -> 0 | AM31: =+AM30*AM29 -> 7376827.2 | AP31: Sous-total | AQ31: =+AQ30*AQ29 -> 0 | AR31: =+AR30*AR29 -> 0 | AS31: =+AS30*AS29 -> 0 | AT31: =+AT30*AT29 -> 2035628.7 | AW31: Sous-total | AX31: =+AX30*AX29 -> 8967574.9 | AY31: =+AY30*AY29 -> 0 | AZ31: =+AZ30*AZ29 -> 0 | BA31: =+BA30*BA29 -> 0 | BD31: Sous-total | BE31: =+BE30*BE29 -> 14450352 | BF31: =+BF30*BF29 -> 0 | BG31: =+BG30*BG29 -> 0 | BH31: =+BH30*BH29 -> 0 | BK31: Sous-total | BL31: =+BL30*BL29 -> 0 | BM31: =+BM30*BM29 -> 0 | BN31: =+BN30*BN29 -> 31047153 | BO31: =+BO30*BO29 -> 0 | BR31: Sous-total | BS31: =+BS30*BS29 -> 0 | BT31: =+BT30*BT29 -> 0 | BU31: =+BU30*BU29 -> 5269112.9 | BV31: =+BV30*BV29 -> 0 | BY31: Sous-total | BZ31: =+BZ30*BZ29 -> 0 | CA31: =+CA30*CA29 -> 0 | CB31: =+CB30*CB29 -> 0 | CC31: =+CC30*CC29 -> 5484665.9 | CF31: Sous-total | CG31: =+CG30*CG29 -> 6250000 | CH31: =+CH30*CH29 -> 0 | CI31: =+CI30*CI29 -> 0 | CJ31: =+CJ30*CJ29 -> 0 | CN31: Sous-total | CO31: =+CO30*CO29 -> 3000000 | CP31: =+CP30*CP29 -> 0 | CQ31: =+CQ30*CQ29 -> 0 | CR31: =+CR30*CR29 -> 0
C32: Sous-total cumulé | D32: =+D31 -> 0 | E32: =+D32+E31 -> 6628365.2 | F32: =+E32+F31 -> 6628365.2 | G32: =+F32+G31 -> 6628365.2 | K32: Sous-total cumulé | L32: =+L31 -> 0 | M32: =+L32+M31 -> 3277100.3 | N32: =+M32+N31 -> 3277100.3 | O32: =+N32+O31 -> 3277100.3 | T32: Sous-total cumulé | U32: =+U31 -> 0 | V32: =+U32+V31 -> 9046429.6 | W32: =+V32+W31 -> 9046429.6 | X32: =+W32+X31 -> 9046429.6 | AB32: Sous-total cumulé | AC32: =+AC31 -> 0 | AD32: =+AC32+AD31 -> 1533733 | AE32: =+AD32+AE31 -> 1533733 | AF32: =+AE32+AF31 -> 1533733 | AI32: Sous-total cumulé | AJ32: =+AJ31 -> 0 | AK32: =+AJ32+AK31 -> 0 | AL32: =+AK32+AL31 -> 0 | AM32: =+AL32+AM31 -> 7376827.2 | AP32: Sous-total cumulé | AQ32: =+AQ31 -> 0 | AR32: =+AQ32+AR31 -> 0 | AS32: =+AR32+AS31 -> 0 | AT32: =+AS32+AT31 -> 2035628.7 | AW32: Sous-total cumulé | AX32: =+AX31 -> 8967574.9 | AY32: =+AX32+AY31 -> 8967574.9 | AZ32: =+AY32+AZ31 -> 8967574.9 | BA32: =+AZ32+BA31 -> 8967574.9 | BD32: Sous-total cumulé | BE32: =+BE31 -> 14450352 | BF32: =+BE32+BF31 -> 14450352 | BG32: =+BF32+BG31 -> 14450352 | BH32: =+BG32+BH31 -> 14450352 | BK32: Sous-total cumulé | BL32: =+BL31 -> 0 | BM32: =+BL32+BM31 -> 0 | BN32: =+BM32+BN31 -> 31047153 | BO32: =+BN32+BO31 -> 31047153 | BR32: Sous-total cumulé | BS32: =+BS31 -> 0 | BT32: =+BS32+BT31 -> 0 | BU32: =+BT32+BU31 -> 5269112.9 | BV32: =+BU32+BV31 -> 5269112.9 | BY32: Sous-total cumulé | BZ32: =+BZ31 -> 0 | CA32: =+BZ32+CA31 -> 0 | CB32: =+CA32+CB31 -> 0 | CC32: =+CB32+CC31 -> 5484665.9 | CF32: Sous-total cumulé | CG32: =+CG31 -> 6250000 | CH32: =+CG32+CH31 -> 6250000 | CI32: =+CH32+CI31 -> 6250000 | CJ32: =+CI32+CJ31 -> 6250000 | CN32: Sous-total cumulé | CO32: =+CO31 -> 3000000 | CP32: =+CO32+CP31 -> 3000000 | CQ32: =+CP32+CQ31 -> 3000000 | CR32: =+CQ32+CR31 -> 3000000
C34: Ensachage et autres frais & fournitures | K34: Ensachage et autres frais & fournitures | T34: Ensachage et autres frais & fournitures | AB34: Ensachage et autres frais & fournitures | AI34: Ensachage et autres frais & fournitures | AP34: Ensachage et autres frais & fournitures | AW34: Ensachage et autres frais & fournitures | BD34: Ensachage et autres frais & fournitures | BK34: Ensachage et autres frais & fournitures | BR34: Ensachage et autres frais & fournitures | BY34: Ensachage et autres frais & fournitures | CF34: charge d'arosage et autres frais d'entretien | CN34: charge d'arosage et autres frais d'entretien
C35: Production brute (tonne) | D35: =+D29 -> 0 | E35: =+E29 -> 20 | F35: =+F29 -> 0 | G35: =+G29 -> 0 | K35: Production brute (tonne) | L35: =+L29 -> 0 | M35: =+M29 -> 10 | N35: =+N29 -> 0 | O35: =+O29 -> 0 | T35: Production brute | U35: =+U29 -> 0 | V35: =+V29 -> 20 | W35: =+W29 -> 0 | X35: =+X29 -> 0 | AB35: Production brute | AC35: =+AC29 -> 0 | AD35: =+AD29 -> 10 | AE35: =+AE29 -> 0 | AF35: =+AF29 -> 0 | AI35: Production brute | AJ35: =+AJ29 -> 0 | AK35: =+AK29 -> 0 | AL35: =+AL29 -> 0 | AM35: =+AM29 -> 5 | AP35: Production brute | AQ35: =+AQ29 -> 0 | AR35: =+AR29 -> 0 | AS35: =+AS29 -> 0 | AT35: =+AT29 -> 10 | AW35: Production brute | AX35: =+AX29 -> 10 | AY35: =+AY29 -> 0 | AZ35: =+AZ29 -> 0 | BA35: =+BA29 -> 0 | BD35: Production brute | BE35: =+BE29 -> 5 | BF35: =+BF29 -> 0 | BG35: =+BG29 -> 0 | BH35: =+BH29 -> 0 | BK35: Production brute | BL35: =+BL29 -> 0 | BM35: =+BM29 -> 0 | BN35: =+BN29 -> 10 | BO35: =+BO29 -> 0 | BR35: Production brute | BS35: =+BS29 -> 0 | BT35: =+BT29 -> 0 | BU35: =+BU29 -> 5 | BV35: =+BV29 -> 0 | BY35: Production brute | BZ35: =+BZ29 -> 0 | CA35: =+CA29 -> 0 | CB35: =+CB29 -> 0 | CC35: =+CC29 -> 10 | CF35: Production brute | CG35: =+CG29 -> 5 | CH35: 5 | CI35: 5 | CJ35: 5 | CN35: Production brute | CO35: =+CO29 -> 5 | CP35: 5
C36: Coût Unitaire | D36: 35000 | E36: =+D36 -> 35000 | F36: =+E36 -> 35000 | G36: =+F36 -> 35000 | K36: Coût Unitaire | L36: 35000 | M36: =+L36 -> 35000 | N36: =+M36 -> 35000 | O36: =+N36 -> 35000 | T36: Coût Unitaire | U36: =SUM(L36) -> 35000 | V36: =SUM(U36) -> 35000 | W36: =SUM(V36) -> 35000 | X36: =SUM(W36) -> 35000 | AB36: Coût Unitaire | AC36: =SUM(U36) -> 35000 | AD36: =SUM(AC36) -> 35000 | AE36: =SUM(AD36) -> 35000 | AF36: =SUM(AE36) -> 35000 | AI36: Coût Unitaire | AJ36: =SUM(AC36) -> 35000 | AK36: =SUM(AJ36) -> 35000 | AL36: =SUM(AK36) -> 35000 | AM36: =SUM(AL36) -> 35000 | AP36: Coût Unitaire | AQ36: =SUM(AJ36) -> 35000 | AR36: =SUM(AQ36) -> 35000 | AS36: =SUM(AR36) -> 35000 | AT36: =SUM(AS36) -> 35000 | AW36: Coût Unitaire | AX36: =SUM(AQ36) -> 35000 | AY36: =SUM(AX36) -> 35000 | AZ36: =SUM(AY36) -> 35000 | BA36: =SUM(AZ36) -> 35000 | BD36: Coût Unitaire | BE36: =SUM(AX36) -> 35000 | BF36: =SUM(BE36) -> 35000 | BG36: =SUM(BF36) -> 35000 | BH36: =SUM(BG36) -> 35000 | BK36: Coût Unitaire | BL36: =SUM(BE36) -> 35000 | BM36: =SUM(BL36) -> 35000 | BN36: =SUM(BM36) -> 35000 | BO36: =SUM(BN36) -> 35000 | BR36: Coût Unitaire | BS36: =SUM(BL36) -> 35000 | BT36: =SUM(BS36) -> 35000 | BU36: =SUM(BT36) -> 35000 | BV36: =SUM(BU36) -> 35000 | BY36: Coût Unitaire | BZ36: =SUM(BS36) -> 35000 | CA36: =SUM(BZ36) -> 35000 | CB36: =SUM(CA36) -> 35000 | CC36: =SUM(CB36) -> 35000 | CF36: Coût Unitaire | CG36: 180000 | CH36: =SUM(CG36) -> 180000 | CI36: =SUM(CH36) -> 180000 | CJ36: =SUM(CG36) -> 180000 | CN36: Coût Unitaire | CO36: 180000 | CP36: =SUM(CO36) -> 180000 | CQ36: =SUM(CP36) -> 180000 | CR36: =SUM(CO36) -> 180000
C37: Sous-total | D37: =+D36*D35 -> 0 | E37: =+E36*E35 -> 700000 | F37: =+F36*F35 -> 0 | G37: =+G36*G35 -> 0 | K37: Sous-total | L37: =+L36*L35 -> 0 | M37: =+M36*M35 -> 350000 | N37: =+N36*N35 -> 0 | O37: =+O36*O35 -> 0 | T37: Sous-total | U37: =+U36*U35 -> 0 | V37: =+V36*V35 -> 700000 | W37: =+W36*W35 -> 0 | X37: =+X36*X35 -> 0 | AB37: Sous-total | AC37: =+AC36*AC35 -> 0 | AD37: =+AD36*AD35 -> 350000 | AE37: =+AE36*AE35 -> 0 | AF37: =+AF36*AF35 -> 0 | AI37: Sous-total | AJ37: =+AJ36*AJ35 -> 0 | AK37: =+AK36*AK35 -> 0 | AL37: =+AL36*AL35 -> 0 | AM37: =+AM36*AM35 -> 175000 | AP37: Sous-total | AQ37: =+AQ36*AQ35 -> 0 | AR37: =+AR36*AR35 -> 0 | AS37: =+AS36*AS35 -> 0 | AT37: =+AT36*AT35 -> 350000 | AW37: Sous-total | AX37: =+AX36*AX35 -> 350000 | AY37: =+AY36*AY35 -> 0 | AZ37: =+AZ36*AZ35 -> 0 | BA37: =+BA36*BA35 -> 0 | BD37: Sous-total | BE37: =+BE36*BE35 -> 175000 | BF37: =+BF36*BF35 -> 0 | BG37: =+BG36*BG35 -> 0 | BH37: =+BH36*BH35 -> 0 | BK37: Sous-total | BL37: =+BL36*BL35 -> 0 | BM37: =+BM36*BM35 -> 0 | BN37: =+BN36*BN35 -> 350000 | BO37: =+BO36*BO35 -> 0 | BR37: Sous-total | BS37: =+BS36*BS35 -> 0 | BT37: =+BT36*BT35 -> 0 | BU37: =+BU36*BU35 -> 175000 | BV37: =+BV36*BV35 -> 0 | BY37: Sous-total | BZ37: =+BZ36*BZ35 -> 0 | CA37: =+CA36*CA35 -> 0 | CB37: =+CB36*CB35 -> 0 | CC37: =+CC36*CC35 -> 350000 | CF37: Sous-total | CG37: =+CG36*CG35 -> 900000 | CH37: =+CH36*CH35 -> 900000 | CI37: =+CI36*CI35 -> 900000 | CJ37: =+CJ36*CJ35 -> 900000 | CN37: Sous-total | CO37: =+CO36*CO35 -> 900000 | CP37: =+CP36*CP35 -> 900000 | CQ37: =+CQ36*CQ35 -> 0 | CR37: =+CR36*CR35 -> 0
C38: Sous-total cumulé | D38: =+D37 -> 0 | E38: =+D38+E37 -> 700000 | F38: =+E38+F37 -> 700000 | G38: =+F38+G37 -> 700000 | K38: Sous-total cumulé | L38: =+L37 -> 0 | M38: =+L38+M37 -> 350000 | N38: =+M38+N37 -> 350000 | O38: =+N38+O37 -> 350000 | T38: Sous-total cumulé | U38: =+U37 -> 0 | V38: =+U38+V37 -> 700000 | W38: =+V38+W37 -> 700000 | X38: =+W38+X37 -> 700000 | AB38: Sous-total cumulé | AC38: =+AC37 -> 0 | AD38: =+AC38+AD37 -> 350000 | AE38: =+AD38+AE37 -> 350000 | AF38: =+AE38+AF37 -> 350000 | AI38: Sous-total cumulé | AJ38: =+AJ37 -> 0 | AK38: =+AJ38+AK37 -> 0 | AL38: =+AK38+AL37 -> 0 | AM38: =+AL38+AM37 -> 175000 | AP38: Sous-total cumulé | AQ38: =+AQ37 -> 0 | AR38: =+AQ38+AR37 -> 0 | AS38: =+AR38+AS37 -> 0 | AT38: =+AS38+AT37 -> 350000 | AW38: Sous-total cumulé | AX38: =+AX37 -> 350000 | AY38: =+AX38+AY37 -> 350000 | AZ38: =+AY38+AZ37 -> 350000 | BA38: =+AZ38+BA37 -> 350000 | BD38: Sous-total cumulé | BE38: =+BE37 -> 175000 | BF38: =+BE38+BF37 -> 175000 | BG38: =+BF38+BG37 -> 175000 | BH38: =+BG38+BH37 -> 175000 | BK38: Sous-total cumulé | BL38: =+BL37 -> 0 | BM38: =+BL38+BM37 -> 0 | BN38: =+BM38+BN37 -> 350000 | BO38: =+BN38+BO37 -> 350000 | BR38: Sous-total cumulé | BS38: =+BS37 -> 0 | BT38: =+BS38+BT37 -> 0 | BU38: =+BT38+BU37 -> 175000 | BV38: =+BU38+BV37 -> 175000 | BY38: Sous-total cumulé | BZ38: =+BZ37 -> 0 | CA38: =+BZ38+CA37 -> 0 | CB38: =+CA38+CB37 -> 0 | CC38: =+CB38+CC37 -> 350000 | CF38: Sous-total cumulé | CG38: =+CG37 -> 900000 | CH38: =+CG38+CH37 -> 1800000 | CI38: =+CH38+CI37 -> 2700000 | CJ38: =+CI38+CJ37 -> 3600000 | CN38: Sous-total cumulé | CO38: =+CO37 -> 900000 | CP38: =+CO38+CP37 -> 1800000 | CQ38: =+CP38+CQ37 -> 1800000 | CR38: =+CQ38+CR37 -> 1800000
C40: Transports, manutention, stock des intrants (coût /hectare) | D40: 25000 | E40: =SUM(D40) -> 25000 | F40: =SUM(D40) -> 25000 | G40: =SUM(D40) -> 25000 | K40: Transports, manutention, stock des intrants (coût /hectare) | L40: 25000 | M40: =SUM(L40) -> 25000 | N40: =SUM(L40) -> 25000 | O40: =SUM(L40) -> 25000 | T40: Transports, manutention, stock des intrants (coût /hectare) | U40: =SUM(L40) -> 25000 | V40: =SUM(U40) -> 25000 | W40: =SUM(U40) -> 25000 | X40: =SUM(U40) -> 25000 | AB40: Transports, manutention, stock des intrants (coût /hectare) | AC40: =SUM(U40) -> 25000 | AD40: =SUM(AC40) -> 25000 | AE40: =SUM(AC40) -> 25000 | AF40: =SUM(AC40) -> 25000 | AI40: Transports, manutention, stock des intrants (coût /hectare) | AJ40: =SUM(AC40) -> 25000 | AK40: =SUM(AJ40) -> 25000 | AL40: =SUM(AJ40) -> 25000 | AM40: =SUM(AJ40) -> 25000 | AP40: Transports, manutention, stock des intrants (coût /hectare) | AQ40: =SUM(AJ40) -> 25000 | AR40: =SUM(AQ40) -> 25000 | AS40: =SUM(AQ40) -> 25000 | AT40: =SUM(AQ40) -> 25000 | AW40: Transports, manutention, stock des intrants (coût /hectare) | AX40: =SUM(AQ40) -> 25000 | AY40: =SUM(AX40) -> 25000 | AZ40: =SUM(AX40) -> 25000 | BA40: =SUM(AX40) -> 25000 | BD40: Transports, manutention, stock des intrants (coût /hectare) | BE40: =SUM(AX40) -> 25000 | BF40: =SUM(BE40) -> 25000 | BG40: =SUM(BE40) -> 25000 | BH40: =SUM(BE40) -> 25000 | BK40: Transports, manutention, stock des intrants (coût /hectare) | BL40: =SUM(BE40) -> 25000 | BM40: =SUM(BL40) -> 25000 | BN40: =SUM(BL40) -> 25000 | BO40: =SUM(BL40) -> 25000 | BR40: Transports, manutention, stock des intrants (coût /hectare) | BS40: =SUM(BL40) -> 25000 | BT40: =SUM(BS40) -> 25000 | BU40: =SUM(BS40) -> 25000 | BV40: =SUM(BS40) -> 25000 | BY40: Transports, manutention, stock des intrants (coût /hectare) | BZ40: =SUM(BS40) -> 25000 | CA40: =SUM(BZ40) -> 25000 | CB40: =SUM(BZ40) -> 25000 | CC40: =SUM(BZ40) -> 25000 | CF40: Transports, manutention, stock des intrants (coût /hectare) | CG40: =SUM(BZ40) -> 25000 | CJ40: =SUM(CG40) -> 25000 | CN40: Transports, manutention et recolte Gome | CO40: =SUM(CH40) -> 0 | CR40: =SUM(CO40) -> 0
C41: Montant total (sur base total achat) | D41: =+D29*D40 -> 0 | E41: =+E29*E40 -> 500000 | F41: =+F29*F40 -> 0 | G41: =+G29*G40 -> 0 | K41: Montant total (sur base total achat) | L41: =+L29*L40 -> 0 | M41: =+M29*M40 -> 250000 | N41: =+N29*N40 -> 0 | O41: =+O29*O40 -> 0 | T41: Montant total (sur base total achat) | U41: =+U29*U40 -> 0 | V41: =+V29*V40 -> 500000 | W41: =+W29*W40 -> 0 | X41: =+X29*X40 -> 0 | AB41: Montant total (sur base total achat) | AC41: =+AC29*AC40 -> 0 | AD41: =+AD29*AD40 -> 250000 | AE41: =+AE29*AE40 -> 0 | AF41: =+AF29*AF40 -> 0 | AI41: Montant total (sur base total achat) | AJ41: =+AJ29*AJ40 -> 0 | AK41: =+AK29*AK40 -> 0 | AL41: =+AL29*AL40 -> 0 | AM41: =+AM29*AM40 -> 125000 | AP41: Montant total (sur base total achat) | AQ41: =+AQ29*AQ40 -> 0 | AR41: =+AR29*AR40 -> 0 | AS41: =+AS29*AS40 -> 0 | AT41: =+AT29*AT40 -> 250000 | AW41: Montant total (sur base total achat) | AX41: =+AX29*AX40 -> 250000 | AY41: =+AY29*AY40 -> 0 | AZ41: =+AZ29*AZ40 -> 0 | BA41: =+BA29*BA40 -> 0 | BD41: Montant total (sur base total achat) | BE41: =+BE29*BE40 -> 125000 | BF41: =+BF29*BF40 -> 0 | BG41: =+BG29*BG40 -> 0 | BH41: =+BH29*BH40 -> 0 | BK41: Montant total (sur base total achat) | BL41: =+BL29*BL40 -> 0 | BM41: =+BM29*BM40 -> 0 | BN41: =+BN29*BN40 -> 250000 | BO41: =+BO29*BO40 -> 0 | BR41: Montant total (sur base total achat) | BS41: =+BS29*BS40 -> 0 | BT41: =+BT29*BT40 -> 0 | BU41: =+BU29*BU40 -> 125000 | BV41: =+BV29*BV40 -> 0 | BY41: Montant total (sur base total achat) | BZ41: =+BZ29*BZ40 -> 0 | CA41: =+CA29*CA40 -> 0 | CB41: =+CB29*CB40 -> 0 | CC41: =+CC29*CC40 -> 250000 | CF41: Montant total (sur base total achat) | CG41: =+CG29*CG40 -> 125000 | CH41: =+CH29*CH40 -> 0 | CI41: =+CI29*CI40 -> 0 | CJ41: =+CJ29*CJ40 -> 0 | CN41: Montant total (sur base total achat) | CO41: =+CO29*CO40 -> 0 | CP41: =+CP29*CP40 -> 0 | CQ41: =+CQ29*CQ40 -> 0 | CR41: =+CR29*CR40 -> 0
C42: Sous-total cumulé | D42: =+D41 -> 0 | E42: =+D42+E41 -> 500000 | F42: =+E42+F41 -> 500000 | G42: =+F42+G41 -> 500000 | K42: Sous-total cumulé | L42: =+L41 -> 0 | M42: =+L42+M41 -> 250000 | N42: =+M42+N41 -> 250000 | O42: =+N42+O41 -> 250000 | T42: Sous-total cumulé | U42: =+U41 -> 0 | V42: =+U42+V41 -> 500000 | W42: =+V42+W41 -> 500000 | X42: =+W42+X41 -> 500000 | AB42: Sous-total cumulé | AC42: =+AC41 -> 0 | AD42: =+AC42+AD41 -> 250000 | AE42: =+AD42+AE41 -> 250000 | AF42: =+AE42+AF41 -> 250000 | AI42: Sous-total cumulé | AJ42: =+AJ41 -> 0 | AK42: =+AJ42+AK41 -> 0 | AL42: =+AK42+AL41 -> 0 | AM42: =+AL42+AM41 -> 125000 | AP42: Sous-total cumulé | AQ42: =+AQ41 -> 0 | AR42: =+AQ42+AR41 -> 0 | AS42: =+AR42+AS41 -> 0 | AT42: =+AS42+AT41 -> 250000 | AW42: Sous-total cumulé | AX42: =+AX41 -> 250000 | AY42: =+AX42+AY41 -> 250000 | AZ42: =+AY42+AZ41 -> 250000 | BA42: =+AZ42+BA41 -> 250000 | BD42: Sous-total cumulé | BE42: =+BE41 -> 125000 | BF42: =+BE42+BF41 -> 125000 | BG42: =+BF42+BG41 -> 125000 | BH42: =+BG42+BH41 -> 125000 | BK42: Sous-total cumulé | BL42: =+BL41 -> 0 | BM42: =+BL42+BM41 -> 0 | BN42: =+BM42+BN41 -> 250000 | BO42: =+BN42+BO41 -> 250000 | BR42: Sous-total cumulé | BS42: =+BS41 -> 0 | BT42: =+BS42+BT41 -> 0 | BU42: =+BT42+BU41 -> 125000 | BV42: =+BU42+BV41 -> 125000 | BY42: Sous-total cumulé | BZ42: =+BZ41 -> 0 | CA42: =+BZ42+CA41 -> 0 | CB42: =+CA42+CB41 -> 0 | CC42: =+CB42+CC41 -> 250000 | CF42: Sous-total cumulé | CG42: =+CG41 -> 125000 | CH42: =+CG42+CH41 -> 125000 | CI42: =+CH42+CI41 -> 125000 | CJ42: =+CI42+CJ41 -> 125000 | CN42: Sous-total cumulé | CO42: =+CO41 -> 0 | CP42: =+CO42+CP41 -> 0 | CQ42: =+CP42+CQ41 -> 0 | CR42: =+CQ42+CR41 -> 0
H44: Px Rv / hectare | P44: Px Rv / hectare | Y44: Px Rv / hectare | AG44: Px Rv / hectare | AN44: Px Rv / hectare | AU44: Px Rv / hectare | BB44: Px Rv / hectare | BI44: Px Rv / hectare | BP44: Px Rv / hectare | BW44: Px Rv / hectare | CD44: Px Rv / hectare | CK44: Px Rv / hectare | CS44: Px Rv / hectare
H45: =SUM(G47)/H29 -> 391418.26 | P45: =SUM(O47)/P29 -> 387710.03 | Y45: =SUM(X47)/Y29 -> 512321.48 | AG45: =SUM(AF47)/AG29 -> 213373.3 | AN45: =SUM(AM47)/AN29 -> 1535365.4 | AU45: =SUM(AT47)/AU29 -> 263562.87 | BB45: =SUM(BA47)/BB29 -> 956757.49 | BI45: =SUM(BH47)/BI29 -> 2950070.4 | BP45: =SUM(BO47)/BP29 -> 3164715.3 | BW45: =SUM(BV47)/BW29 -> 1113822.6 | CD45: =SUM(CC47)/CD29 -> 608466.59 | CK45: =SUM(CJ47)/CK29 -> 1995000 | CS45: =SUM(CR47)/CS29 -> 960000
C46: Totaux | D46: =+D31+D37+D41 -> 0 | E46: =+E31+E37+E41 -> 7828365.2 | F46: =+F31+F37+F41 -> 0 | G46: =+G31+G37+G41 -> 0 | H46: =SUM(H29:H42) -> 20 | K46: Totaux | L46: =+L31+L37+L41 -> 0 | M46: =+M31+M37+M41 -> 3877100.3 | N46: =+N31+N37+N41 -> 0 | O46: =+O31+O37+O41 -> 0 | P46: =SUM(P29:P42) -> 10 | T46: Totaux | U46: =+U31+U37+U41 -> 0 | V46: =+V31+V37+V41 -> 10246430 | W46: =+W31+W37+W41 -> 0 | X46: =+X31+X37+X41 -> 0 | Y46: =SUM(Y29:Y42) -> 20 | AB46: Totaux | AC46: =+AC31+AC37+AC41 -> 0 | AD46: =+AD31+AD37+AD41 -> 2133733 | AE46: =+AE31+AE37+AE41 -> 0 | AF46: =+AF31+AF37+AF41 -> 0 | AG46: =SUM(AG29:AG42) -> 10 | AI46: Totaux | AJ46: =+AJ31+AJ37+AJ41 -> 0 | AK46: =+AK31+AK37+AK41 -> 0 | AL46: =+AL31+AL37+AL41 -> 0 | AM46: =+AM31+AM37+AM41 -> 7676827.2 | AN46: =SUM(AN29:AN42) -> 5 | AP46: Totaux | AQ46: =+AQ31+AQ37+AQ41 -> 0 | AR46: =+AR31+AR37+AR41 -> 0 | AS46: =+AS31+AS37+AS41 -> 0 | AT46: =+AT31+AT37+AT41 -> 2635628.7 | AU46: =SUM(AU29:AU42) -> 10 | AW46: Totaux | AX46: =+AX31+AX37+AX41 -> 9567574.9 | AY46: =+AY31+AY37+AY41 -> 0 | AZ46: =+AZ31+AZ37+AZ41 -> 0 | BA46: =+BA31+BA37+BA41 -> 0 | BB46: =SUM(BB29:BB42) -> 10 | BD46: Totaux | BE46: =+BE31+BE37+BE41 -> 14750352 | BF46: =+BF31+BF37+BF41 -> 0 | BG46: =+BG31+BG37+BG41 -> 0 | BH46: =+BH31+BH37+BH41 -> 0 | BI46: =SUM(BI29:BI42) -> 5 | BK46: Totaux | BL46: =+BL31+BL37+BL41 -> 0 | BM46: =+BM31+BM37+BM41 -> 0 | BN46: =+BN31+BN37+BN41 -> 31647153 | BO46: =+BO31+BO37+BO41 -> 0 | BP46: =SUM(BP29:BP42) -> 10 | BR46: Totaux | BS46: =+BS31+BS37+BS41 -> 0 | BT46: =+BT31+BT37+BT41 -> 0 | BU46: =+BU31+BU37+BU41 -> 5569112.9 | BV46: =+BV31+BV37+BV41 -> 0 | BW46: =SUM(BW29:BW42) -> 5 | BY46: Totaux | BZ46: =+BZ31+BZ37+BZ41 -> 0 | CA46: =+CA31+CA37+CA41 -> 0 | CB46: =+CB31+CB37+CB41 -> 0 | CC46: =+CC31+CC37+CC41 -> 6084665.9 | CD46: =SUM(CD29:CD42) -> 10 | CF46: Totaux | CG46: =+CG31+CG37+CG41 -> 7275000 | CH46: =+CH31+CH37+CH41 -> 900000 | CI46: =+CI31+CI37+CI41 -> 900000 | CJ46: =+CJ31+CJ37+CJ41 -> 900000 | CK46: =SUM(CK29:CK42) -> 5 | CN46: Totaux | CO46: =+CO31+CO37+CO41 -> 3900000 | CP46: =+CP31+CP37+CP41 -> 900000 | CQ46: =+CQ31+CQ37+CQ41 -> 0 | CR46: =+CR31+CR37+CR41 -> 0 | CS46: =SUM(CS29:CS42) -> 5
C47: Totaux cumulés | D47: =+D46 -> 0 | E47: =+D47+E46 -> 7828365.2 | F47: =+E47+F46 -> 7828365.2 | G47: =+F47+G46 -> 7828365.2 | K47: Totaux cumulés | L47: =+L46 -> 0 | M47: =+L47+M46 -> 3877100.3 | N47: =+M47+N46 -> 3877100.3 | O47: =+N47+O46 -> 3877100.3 | T47: Totaux cumulés | U47: =+U46 -> 0 | V47: =+U47+V46 -> 10246430 | W47: =+V47+W46 -> 10246430 | X47: =+W47+X46 -> 10246430 | AB47: Totaux cumulés | AC47: =+AC46 -> 0 | AD47: =+AC47+AD46 -> 2133733 | AE47: =+AD47+AE46 -> 2133733 | AF47: =+AE47+AF46 -> 2133733 | AI47: Totaux cumulés | AJ47: =+AJ46 -> 0 | AK47: =+AJ47+AK46 -> 0 | AL47: =+AK47+AL46 -> 0 | AM47: =+AL47+AM46 -> 7676827.2 | AP47: Totaux cumulés | AQ47: =+AQ46 -> 0 | AR47: =+AQ47+AR46 -> 0 | AS47: =+AR47+AS46 -> 0 | AT47: =+AS47+AT46 -> 2635628.7 | AW47: Totaux cumulés | AX47: =+AX46 -> 9567574.9 | AY47: =+AX47+AY46 -> 9567574.9 | AZ47: =+AY47+AZ46 -> 9567574.9 | BA47: =+AZ47+BA46 -> 9567574.9 | BD47: Totaux cumulés | BE47: =+BE46 -> 14750352 | BF47: =+BE47+BF46 -> 14750352 | BG47: =+BF47+BG46 -> 14750352 | BH47: =+BG47+BH46 -> 14750352 | BK47: Totaux cumulés | BL47: =+BL46 -> 0 | BM47: =+BL47+BM46 -> 0 | BN47: =+BM47+BN46 -> 31647153 | BO47: =+BN47+BO46 -> 31647153 | BR47: Totaux cumulés | BS47: =+BS46 -> 0 | BT47: =+BS47+BT46 -> 0 | BU47: =+BT47+BU46 -> 5569112.9 | BV47: =+BU47+BV46 -> 5569112.9 | BY47: Totaux cumulés | BZ47: =+BZ46 -> 0 | CA47: =+BZ47+CA46 -> 0 | CB47: =+CA47+CB46 -> 0 | CC47: =+CB47+CC46 -> 6084665.9 | CF47: Totaux cumulés | CG47: =+CG46 -> 7275000 | CH47: =+CG47+CH46 -> 8175000 | CI47: =+CH47+CI46 -> 9075000 | CJ47: =+CI47+CJ46 -> 9975000 | CN47: Totaux cumulés | CO47: =+CO46 -> 3900000 | CP47: =+CO47+CP46 -> 4800000 | CQ47: =+CP47+CQ46 -> 4800000 | CR47: =+CQ47+CR46 -> 4800000
C51: Arachide (Groundnut) 2027 | K51: Niébé (Cowpea) 2027 | T51: Céréale, blé, mais (Wheat, corne, ) 2027 | Y51: Total acheté | AB51: Sesame 2027 | AG51: Total acheté | AI51: Gombo - avec goutte-à-goutte (Okra - with drip) 2027 | AN51: Total acheté | AP51: Sorgho pour graine (Sorghum for Seed) 2028 | AU51: Total acheté | AW51: Oignon - avec goutte-à-goutte (Onion - with drip) 2027 | BB51: Total acheté | BD51: Aubergine - avec goutte-à-goutte et paillage 2027 | BI51: Total acheté | BK51: Tomate - avec goutte-à-goutte et paillage 2027 | BP51: Total acheté | BR51: Pomme de terre en hiver avec irrigation 2027 | BW51: Total acheté | BY51: Luzerne (Alfa Alfa) en irrigation 2027 | CD51: Total acheté | CF51: Verget pour arbre fruitiers 2026 | CK51: Total acheté | CN51: Verget pour arbre fruitiers 2027 | CS51: Total acheté
C52: Matière première | D52: 1er trimestre | E52: 2ème trimestre | F52: 3ème trimestre | G52: 4ème trimestre | H52: Total Acheté | K52: Matière première | L52: 1er trimestre | M52: 2ème trimestre | N52: 3ème trimestre | O52: 4ème trimestre | P52: Total Acheté | T52: Achat de production | U52: 1er trimestre | V52: 2ème trimestre | W52: 3ème trimestre | X52: 4ème trimestre | Y52: Total acheté | AB52: Achat de production | AC52: 1er trimestre | AD52: 2ème trimestre | AE52: 3ème trimestre | AF52: 4ème trimestre | AG52: Total acheté | AI52: Achat de production | AJ52: 1er trimestre | AK52: 2ème trimestre | AL52: 3ème trimestre | AM52: 4ème trimestre | AN52: Total acheté | AP52: Achat de production | AQ52: 1er trimestre | AR52: 2ème trimestre | AS52: 3ème trimestre | AT52: 4ème trimestre | AU52: Total acheté | AW52: Achat de production | AX52: 1er trimestre | AY52: 2ème trimestre | AZ52: 3ème trimestre | BA52: 4ème trimestre | BB52: Total acheté | BD52: Achat de production | BE52: 1er trimestre | BF52: 2ème trimestre | BG52: 3ème trimestre | BH52: 4ème trimestre | BI52: Total acheté | BK52: Achat de production | BL52: 1er trimestre | BM52: 2ème trimestre | BN52: 3ème trimestre | BO52: 4ème trimestre | BP52: Total acheté | BR52: Achat de production | BS52: 1er trimestre | BT52: 2ème trimestre | BU52: 3ème trimestre | BV52: 4ème trimestre | BW52: Total acheté | BY52: Achat de production | BZ52: 1er trimestre | CA52: 2ème trimestre | CB52: 3ème trimestre | CC52: 4ème trimestre | CD52: Total acheté | CF52: Achat de production | CG52: 1er trimestre | CH52: 2ème trimestre | CI52: 3ème trimestre | CJ52: 4ème trimestre | CK52: Total acheté | CN52: Achat de production | CO52: 1er trimestre | CP52: 2ème trimestre | CQ52: 3ème trimestre | CR52: 4ème trimestre | CS52: Total acheté
C53: Superficie cultivée en pluviale | E53: 20 | F53: =(+'[2]Ca...'!E53+'[2]Ca...'!E59+'[2]Ca...'!E65)*1.05 -> 0 | H53: =+SUM(D53:G53) -> 20 | K53: Superficie cultivée en pluviale | M53: 10 | P53: =+SUM(L53:O53) -> 10 | T53: Superficie cultivée en pluviale | V53: 20 | Y53: =+SUM(U53:X53) -> 20 | AB53: Superficie cultivée en pluviale | AD53: 10 | AG53: =+SUM(AC53:AF53) -> 10 | AI53: Superficie cultivée en irriguation | AM53: 5 | AN53: =+SUM(AJ53:AM53) -> 5 | AP53: Superficie cultivée en irriguation | AT53: 10 | AU53: =+SUM(AQ53:AT53) -> 10 | AW53: Superficie cultivée en irriguation | AX53: 10 | BB53: =+SUM(AX53:BA53) -> 10 | BD53: Superficie cultivée en irriguation | BE53: 5 | BI53: =+SUM(BE53:BH53) -> 5 | BK53: Superficie cultivée en irriguation | BN53: 10 | BP53: =+SUM(BL53:BO53) -> 10 | BR53: Superficie cultivée en irriguation | BU53: 5 | BW53: =+SUM(BS53:BV53) -> 5 | BY53: Superficie cultivée en irriguation | CC53: 10 | CD53: =+SUM(BZ53:CC53) -> 10 | CF53: Superficie cultivée en irriguation | CK53: =+SUM(CG53:CJ53) -> 0 | CN53: Superficie cultivée en irriguation | CS53: =+SUM(CO53:CR53) -> 0
C54: Coût unitaire par hectare | D54: =SUM(D30) -> 331418.26 | E54: =+D54 -> 331418.26 | F54: =+E54 -> 331418.26 | G54: =+F54 -> 331418.26 | K54: Coût unitaire par hectare | L54: =SUM(L30) -> 327710.03 | M54: =+L54 -> 327710.03 | N54: =+M54 -> 327710.03 | O54: =+N54 -> 327710.03 | T54: Coût unitaire par hectare | U54: =SUM(X30) -> 452321.48 | V54: =SUM(U54) -> 452321.48 | W54: =SUM(U54) -> 452321.48 | X54: =SUM(U54) -> 452321.48 | AB54: Coût unitaire par hectare | AC54: =SUM(AF30) -> 153373.3 | AD54: =SUM(AC54) -> 153373.3 | AE54: =SUM(AC54) -> 153373.3 | AF54: =SUM(AC54) -> 153373.3 | AI54: Coût unitaire par hectare | AJ54: =SUM(AM30) -> 1475365.4 | AK54: =SUM(AJ54) -> 1475365.4 | AL54: =SUM(AJ54) -> 1475365.4 | AM54: =SUM(AJ54) -> 1475365.4 | AP54: Coût unitaire par hectare | AQ54: =SUM(AT30) -> 203562.87 | AR54: =SUM(AQ54) -> 203562.87 | AS54: =SUM(AQ54) -> 203562.87 | AT54: =SUM(AQ54) -> 203562.87 | AW54: Coût unitaire par hectare | AX54: =SUM(BA30) -> 896757.49 | AY54: =SUM(AX54) -> 896757.49 | AZ54: =SUM(AX54) -> 896757.49 | BA54: =SUM(AX54) -> 896757.49 | BD54: Coût unitaire par hectare | BE54: =SUM(BH30) -> 2890070.4 | BF54: =SUM(BE54) -> 2890070.4 | BG54: =SUM(BE54) -> 2890070.4 | BH54: =SUM(BE54) -> 2890070.4 | BK54: Coût unitaire par hectare | BL54: =SUM(BO30) -> 3104715.3 | BM54: =SUM(BL54) -> 3104715.3 | BN54: =SUM(BL54) -> 3104715.3 | BO54: =SUM(BL54) -> 3104715.3 | BR54: Coût unitaire par hectare | BS54: =SUM(BV30) -> 1053822.6 | BT54: =SUM(BS54) -> 1053822.6 | BU54: =SUM(BS54) -> 1053822.6 | BV54: =SUM(BS54) -> 1053822.6 | BY54: Coût unitaire par hectare | BZ54: =SUM(CC30) -> 548466.59 | CA54: =SUM(BZ54) -> 548466.59 | CB54: =SUM(BZ54) -> 548466.59 | CC54: =SUM(BZ54) -> 548466.59 | CF54: Coût unitaire par hectare | CG54: =SUM(CJ30) -> 1250000 | CH54: =SUM(CG54) -> 1250000 | CI54: =SUM(CG54) -> 1250000 | CJ54: =SUM(CG54) -> 1250000 | CN54: Coût unitaire par hectare | CO54: =SUM(CR30) -> 600000 | CP54: =SUM(CO54) -> 600000 | CQ54: =SUM(CO54) -> 600000 | CR54: =SUM(CO54) -> 600000
C55: Sous-total | D55: =+D54*D53 -> 0 | E55: =+E54*E53 -> 6628365.2 | F55: =+F54*F53 -> 0 | G55: =+G54*G53 -> 0 | K55: Sous-total | L55: =+L54*L53 -> 0 | M55: =+M54*M53 -> 3277100.3 | N55: =+N54*N53 -> 0 | O55: =+O54*O53 -> 0 | T55: Sous-total | U55: =+U54*U53 -> 0 | V55: =+V54*V53 -> 9046429.6 | W55: =+W54*W53 -> 0 | X55: =+X54*X53 -> 0 | AB55: Sous-total | AC55: =+AC54*AC53 -> 0 | AD55: =+AD54*AD53 -> 1533733 | AE55: =+AE54*AE53 -> 0 | AF55: =+AF54*AF53 -> 0 | AI55: Sous-total | AJ55: =+AJ54*AJ53 -> 0 | AK55: =+AK54*AK53 -> 0 | AL55: =+AL54*AL53 -> 0 | AM55: =+AM54*AM53 -> 7376827.2 | AP55: Sous-total | AQ55: =+AQ54*AQ53 -> 0 | AR55: =+AR54*AR53 -> 0 | AS55: =+AS54*AS53 -> 0 | AT55: =+AT54*AT53 -> 2035628.7 | AW55: Sous-total | AX55: =+AX54*AX53 -> 8967574.9 | AY55: =+AY54*AY53 -> 0 | AZ55: =+AZ54*AZ53 -> 0 | BA55: =+BA54*BA53 -> 0 | BD55: Sous-total | BE55: =+BE54*BE53 -> 14450352 | BF55: =+BF54*BF53 -> 0 | BG55: =+BG54*BG53 -> 0 | BH55: =+BH54*BH53 -> 0 | BK55: Sous-total | BL55: =+BL54*BL53 -> 0 | BM55: =+BM54*BM53 -> 0 | BN55: =+BN54*BN53 -> 31047153 | BO55: =+BO54*BO53 -> 0 | BR55: Sous-total | BS55: =+BS54*BS53 -> 0 | BT55: =+BT54*BT53 -> 0 | BU55: =+BU54*BU53 -> 5269112.9 | BV55: =+BV54*BV53 -> 0 | BY55: Sous-total | BZ55: =+BZ54*BZ53 -> 0 | CA55: =+CA54*CA53 -> 0 | CB55: =+CB54*CB53 -> 0 | CC55: =+CC54*CC53 -> 5484665.9 | CF55: Sous-total | CG55: =+CG54*CG53 -> 0 | CH55: =+CH54*CH53 -> 0 | CI55: =+CI54*CI53 -> 0 | CJ55: =+CJ54*CJ53 -> 0 | CN55: Sous-total | CO55: =+CO54*CO53 -> 0 | CP55: =+CP54*CP53 -> 0 | CQ55: =+CQ54*CQ53 -> 0 | CR55: =+CR54*CR53 -> 0
C56: Sous-total cumulé | D56: =+D55 -> 0 | E56: =+D56+E55 -> 6628365.2 | F56: =+E56+F55 -> 6628365.2 | G56: =+F56+G55 -> 6628365.2 | K56: Sous-total cumulé | L56: =+L55 -> 0 | M56: =+L56+M55 -> 3277100.3 | N56: =+M56+N55 -> 3277100.3 | O56: =+N56+O55 -> 3277100.3 | T56: Sous-total cumulé | U56: =+U55 -> 0 | V56: =+U56+V55 -> 9046429.6 | W56: =+V56+W55 -> 9046429.6 | X56: =+W56+X55 -> 9046429.6 | AB56: Sous-total cumulé | AC56: =+AC55 -> 0 | AD56: =+AC56+AD55 -> 1533733 | AE56: =+AD56+AE55 -> 1533733 | AF56: =+AE56+AF55 -> 1533733 | AI56: Sous-total cumulé | AJ56: =+AJ55 -> 0 | AK56: =+AJ56+AK55 -> 0 | AL56: =+AK56+AL55 -> 0 | AM56: =+AL56+AM55 -> 7376827.2 | AP56: Sous-total cumulé | AQ56: =+AQ55 -> 0 | AR56: =+AQ56+AR55 -> 0 | AS56: =+AR56+AS55 -> 0 | AT56: =+AS56+AT55 -> 2035628.7 | AW56: Sous-total cumulé | AX56: =+AX55 -> 8967574.9 | AY56: =+AX56+AY55 -> 8967574.9 | AZ56: =+AY56+AZ55 -> 8967574.9 | BA56: =+AZ56+BA55 -> 8967574.9 | BD56: Sous-total cumulé | BE56: =+BE55 -> 14450352 | BF56: =+BE56+BF55 -> 14450352 | BG56: =+BF56+BG55 -> 14450352 | BH56: =+BG56+BH55 -> 14450352 | BK56: Sous-total cumulé | BL56: =+BL55 -> 0 | BM56: =+BL56+BM55 -> 0 | BN56: =+BM56+BN55 -> 31047153 | BO56: =+BN56+BO55 -> 31047153 | BR56: Sous-total cumulé | BS56: =+BS55 -> 0 | BT56: =+BS56+BT55 -> 0 | BU56: =+BT56+BU55 -> 5269112.9 | BV56: =+BU56+BV55 -> 5269112.9 | BY56: Sous-total cumulé | BZ56: =+BZ55 -> 0 | CA56: =+BZ56+CA55 -> 0 | CB56: =+CA56+CB55 -> 0 | CC56: =+CB56+CC55 -> 5484665.9 | CF56: Sous-total cumulé | CG56: =+CG55 -> 0 | CH56: =+CG56+CH55 -> 0 | CI56: =+CH56+CI55 -> 0 | CJ56: =+CI56+CJ55 -> 0 | CN56: Sous-total cumulé | CO56: =+CO55 -> 0 | CP56: =+CO56+CP55 -> 0 | CQ56: =+CP56+CQ55 -> 0 | CR56: =+CQ56+CR55 -> 0
C58: Ensachage et autres fournitures | K58: Ensachage et autres fournitures | T58: Transports mis en Fob et SGS (coût /tonne) | AB58: Transports mis en Fob et SGS (coût /tonne) | AI58: Transports mis en Fob et SGS (coût /tonne) | AP58: Transports mis en Fob et SGS (coût /tonne) | AW58: Transports mis en Fob et SGS (coût /tonne) | BD58: Transports mis en Fob et SGS (coût /tonne) | BK58: Transports mis en Fob et SGS (coût /tonne) | BR58: Transports mis en Fob et SGS (coût /tonne) | BY58: Transports mis en Fob et SGS (coût /tonne) | CF58: charge d'arosage et autres frais d'entretien | CN58: charge d'arosage et autres frais d'entretien
C59: Production brute (tonne) | D59: =+D53 -> 0 | E59: =+E53 -> 20 | F59: =+F53 -> 0 | G59: =+G53 -> 0 | K59: Production brute (tonne) | L59: =+L53 -> 0 | M59: =+M53 -> 10 | N59: =+N53 -> 0 | O59: =+O53 -> 0 | T59: Production brute | U59: =+U53 -> 0 | V59: =+V53 -> 20 | W59: =+W53 -> 0 | X59: =+X53 -> 0 | AB59: Production brute | AC59: =+AC53 -> 0 | AD59: =+AD53 -> 10 | AE59: =+AE53 -> 0 | AF59: =+AF53 -> 0 | AI59: Production brute | AJ59: =+AJ53 -> 0 | AK59: =+AK53 -> 0 | AL59: =+AL53 -> 0 | AM59: =+AM53 -> 5 | AP59: Production brute | AQ59: =+AQ53 -> 0 | AR59: =+AR53 -> 0 | AS59: =+AS53 -> 0 | AT59: =+AT53 -> 10 | AW59: Production brute | AX59: =+AX53 -> 10 | AY59: =+AY53 -> 0 | AZ59: =+AZ53 -> 0 | BA59: =+BA53 -> 0 | BD59: Production brute | BE59: =+BE53 -> 5 | BF59: =+BF53 -> 0 | BG59: =+BG53 -> 0 | BH59: =+BH53 -> 0 | BK59: Production brute | BL59: =+BL53 -> 0 | BM59: =+BM53 -> 0 | BN59: =+BN53 -> 10 | BO59: =+BO53 -> 0 | BR59: Production brute | BS59: =+BS53 -> 0 | BT59: =+BT53 -> 0 | BU59: =+BU53 -> 5 | BV59: =+BV53 -> 0 | BY59: Production brute | BZ59: =+BZ53 -> 0 | CA59: =+CA53 -> 0 | CB59: =+CB53 -> 0 | CC59: =+CC53 -> 10 | CF59: Production brute | CG59: 5 | CH59: 5 | CI59: 5 | CJ59: 5 | CN59: Production brute | CP59: 5
C60: Coût Unitaire / tonne | D60: =SUM(D36) -> 35000 | E60: =+D60 -> 35000 | F60: =+E60 -> 35000 | G60: =+F60 -> 35000 | K60: Coût Unitaire / tonne | L60: =SUM(L36) -> 35000 | M60: =+L60 -> 35000 | N60: =+M60 -> 35000 | O60: =+N60 -> 35000 | T60: Coût Unitaire | U60: =+D60 -> 35000 | V60: =+U60 -> 35000 | W60: =+V60 -> 35000 | X60: =+W60 -> 35000 | AB60: Coût Unitaire | AC60: =SUM(AF36) -> 35000 | AD60: =+AC60 -> 35000 | AE60: =+AD60 -> 35000 | AF60: =+AE60 -> 35000 | AI60: Coût Unitaire | AJ60: =SUM(AC60) -> 35000 | AK60: =+AJ60 -> 35000 | AL60: =+AK60 -> 35000 | AM60: =+AL60 -> 35000 | AP60: Coût Unitaire | AQ60: =SUM(AJ60) -> 35000 | AR60: =+AQ60 -> 35000 | AS60: =+AR60 -> 35000 | AT60: =+AS60 -> 35000 | AW60: Coût Unitaire | AX60: =SUM(AQ60) -> 35000 | AY60: =+AX60 -> 35000 | AZ60: =+AY60 -> 35000 | BA60: =+AZ60 -> 35000 | BD60: Coût Unitaire | BE60: =SUM(AX60) -> 35000 | BF60: =+BE60 -> 35000 | BG60: =+BF60 -> 35000 | BH60: =+BG60 -> 35000 | BK60: Coût Unitaire | BL60: =SUM(BE60) -> 35000 | BM60: =+BL60 -> 35000 | BN60: =+BM60 -> 35000 | BO60: =+BN60 -> 35000 | BR60: Coût Unitaire | BS60: =SUM(BL60) -> 35000 | BT60: =+BS60 -> 35000 | BU60: =+BT60 -> 35000 | BV60: =+BU60 -> 35000 | BY60: Coût Unitaire | BZ60: =SUM(BS60) -> 35000 | CA60: =+BZ60 -> 35000 | CB60: =+CA60 -> 35000 | CC60: =+CB60 -> 35000 | CF60: Coût Unitaire | CG60: =SUM(CG36) -> 180000 | CH60: =+CG60 -> 180000 | CI60: =+CH60 -> 180000 | CJ60: =+CI60 -> 180000 | CN60: Coût Unitaire | CO60: =SUM(CO36) -> 180000 | CP60: =+CO60 -> 180000 | CQ60: =+CP60 -> 180000 | CR60: =+CQ60 -> 180000
C61: Sous-total | D61: =+D60*D59 -> 0 | E61: =+E60*E59 -> 700000 | F61: =+F60*F59 -> 0 | G61: =+G60*G59 -> 0 | K61: Sous-total | L61: =+L60*L59 -> 0 | M61: =+M60*M59 -> 350000 | N61: =+N60*N59 -> 0 | O61: =+O60*O59 -> 0 | T61: Sous-total | U61: =+U60*U59 -> 0 | V61: =+V60*V59 -> 700000 | W61: =+W60*W59 -> 0 | X61: =+X60*X59 -> 0 | AB61: Sous-total | AC61: =+AC60*AC59 -> 0 | AD61: =+AD60*AD59 -> 350000 | AE61: =+AE60*AE59 -> 0 | AF61: =+AF60*AF59 -> 0 | AI61: Sous-total | AJ61: =+AJ60*AJ59 -> 0 | AK61: =+AK60*AK59 -> 0 | AL61: =+AL60*AL59 -> 0 | AM61: =+AM60*AM59 -> 175000 | AP61: Sous-total | AQ61: =+AQ60*AQ59 -> 0 | AR61: =+AR60*AR59 -> 0 | AS61: =+AS60*AS59 -> 0 | AT61: =+AT60*AT59 -> 350000 | AW61: Sous-total | AX61: =+AX60*AX59 -> 350000 | AY61: =+AY60*AY59 -> 0 | AZ61: =+AZ60*AZ59 -> 0 | BA61: =+BA60*BA59 -> 0 | BD61: Sous-total | BE61: =+BE60*BE59 -> 175000 | BF61: =+BF60*BF59 -> 0 | BG61: =+BG60*BG59 -> 0 | BH61: =+BH60*BH59 -> 0 | BK61: Sous-total | BL61: =+BL60*BL59 -> 0 | BM61: =+BM60*BM59 -> 0 | BN61: =+BN60*BN59 -> 350000 | BO61: =+BO60*BO59 -> 0 | BR61: Sous-total | BS61: =+BS60*BS59 -> 0 | BT61: =+BT60*BT59 -> 0 | BU61: =+BU60*BU59 -> 175000 | BV61: =+BV60*BV59 -> 0 | BY61: Sous-total | BZ61: =+BZ60*BZ59 -> 0 | CA61: =+CA60*CA59 -> 0 | CB61: =+CB60*CB59 -> 0 | CC61: =+CC60*CC59 -> 350000 | CF61: Sous-total | CG61: =+CG60*CG59 -> 900000 | CH61: =+CH60*CH59 -> 900000 | CI61: =+CI60*CI59 -> 900000 | CJ61: =+CJ60*CJ59 -> 900000 | CN61: Sous-total | CO61: =+CO60*CO59 -> 0 | CP61: =+CP60*CP59 -> 900000 | CQ61: =+CQ60*CQ59 -> 0 | CR61: =+CR60*CR59 -> 0
C62: Sous-total cumulé | D62: =+D61 -> 0 | E62: =+D62+E61 -> 700000 | F62: =+E62+F61 -> 700000 | G62: =+F62+G61 -> 700000 | K62: Sous-total cumulé | L62: =+L61 -> 0 | M62: =+L62+M61 -> 350000 | N62: =+M62+N61 -> 350000 | O62: =+N62+O61 -> 350000 | T62: Sous-total cumulé | U62: =+U61 -> 0 | V62: =+U62+V61 -> 700000 | W62: =+V62+W61 -> 700000 | X62: =+W62+X61 -> 700000 | AB62: Sous-total cumulé | AC62: =+AC61 -> 0 | AD62: =+AC62+AD61 -> 350000 | AE62: =+AD62+AE61 -> 350000 | AF62: =+AE62+AF61 -> 350000 | AI62: Sous-total cumulé | AJ62: =+AJ61 -> 0 | AK62: =+AJ62+AK61 -> 0 | AL62: =+AK62+AL61 -> 0 | AM62: =+AL62+AM61 -> 175000 | AP62: Sous-total cumulé | AQ62: =+AQ61 -> 0 | AR62: =+AQ62+AR61 -> 0 | AS62: =+AR62+AS61 -> 0 | AT62: =+AS62+AT61 -> 350000 | AW62: Sous-total cumulé | AX62: =+AX61 -> 350000 | AY62: =+AX62+AY61 -> 350000 | AZ62: =+AY62+AZ61 -> 350000 | BA62: =+AZ62+BA61 -> 350000 | BD62: Sous-total cumulé | BE62: =+BE61 -> 175000 | BF62: =+BE62+BF61 -> 175000 | BG62: =+BF62+BG61 -> 175000 | BH62: =+BG62+BH61 -> 175000 | BK62: Sous-total cumulé | BL62: =+BL61 -> 0 | BM62: =+BL62+BM61 -> 0 | BN62: =+BM62+BN61 -> 350000 | BO62: =+BN62+BO61 -> 350000 | BR62: Sous-total cumulé | BS62: =+BS61 -> 0 | BT62: =+BS62+BT61 -> 0 | BU62: =+BT62+BU61 -> 175000 | BV62: =+BU62+BV61 -> 175000 | BY62: Sous-total cumulé | BZ62: =+BZ61 -> 0 | CA62: =+BZ62+CA61 -> 0 | CB62: =+CA62+CB61 -> 0 | CC62: =+CB62+CC61 -> 350000 | CF62: Sous-total cumulé | CG62: =+CG61 -> 900000 | CH62: =+CG62+CH61 -> 1800000 | CI62: =+CH62+CI61 -> 2700000 | CJ62: =+CI62+CJ61 -> 3600000 | CN62: Sous-total cumulé | CO62: =+CO61 -> 0 | CP62: =+CO62+CP61 -> 900000 | CQ62: =+CP62+CQ61 -> 900000 | CR62: =+CQ62+CR61 -> 900000
C64: Transports, manutention, stock des intrants (coût /hectare) | D64: =SUM(D40) -> 25000 | E64: =SUM(D64) -> 25000 | F64: =SUM(D64) -> 25000 | G64: =SUM(D64) -> 25000 | K64: Transports, manutention, stock des intrants (coût /hectare) | L64: =SUM(L40) -> 25000 | M64: =SUM(L64) -> 25000 | N64: =SUM(L64) -> 25000 | O64: =SUM(L64) -> 25000 | T64: Transports, manutention, stock des intrants (coût /hectare) | U64: =+D64 -> 25000 | V64: =+E64 -> 25000 | W64: =+F64 -> 25000 | X64: =+G64 -> 25000 | AB64: Transports, manutention, stock des intrants (coût /hectare) | AC64: =+L64 -> 25000 | AD64: =+M64 -> 25000 | AE64: =+N64 -> 25000 | AF64: =+O64 -> 25000 | AI64: Transports, manutention, stock des intrants (coût /hectare) | AJ64: =SUM(AC64) -> 25000 | AL64: =+U64 -> 25000 | AM64: =+V64 -> 25000 | AP64: Transports, manutention, stock des intrants (coût /hectare) | AQ64: =SUM(AJ64) -> 25000 | AR64: =SUM(AQ64) -> 25000 | AS64: =SUM(AQ64) -> 25000 | AT64: =+AC64 -> 25000 | AW64: Transports, manutention, stock des intrants (coût /hectare) | AX64: =SUM(AQ64) -> 25000 | BA64: =+AJ64 -> 25000 | BD64: Transports, manutention, stock des intrants (coût /hectare) | BE64: =SUM(AX64) -> 25000 | BF64: =SUM(BE64) -> 25000 | BG64: =SUM(BF64) -> 25000 | BH64: =+AQ64 -> 25000 | BK64: Transports, manutention, stock des intrants (coût /hectare) | BL64: =SUM(BE64) -> 25000 | BM64: =SUM(BL64) -> 25000 | BN64: =SUM(BM64) -> 25000 | BO64: =+AX64 -> 25000 | BR64: Transports, manutention, stock des intrants (coût /hectare) | BS64: =SUM(BL64) -> 25000 | BT64: =SUM(BS64) -> 25000 | BU64: =SUM(BT64) -> 25000 | BV64: =+BE64 -> 25000 | BY64: Transports, manutention, stock des intrants (coût /hectare) | BZ64: =SUM(BS64) -> 25000 | CA64: =SUM(BZ64) -> 25000 | CB64: =SUM(CA64) -> 25000 | CC64: =+BL64 -> 25000 | CF64: Transports, manutention, stock des intrants (coût /hectare) | CG64: =SUM(BZ64) -> 25000 | CH64: =SUM(CG64) -> 25000 | CI64: =SUM(CH64) -> 25000 | CJ64: =+BS64 -> 25000 | CN64: Transports, manutention et recolte Gome | CO64: =SUM(CH64) -> 25000 | CP64: =SUM(CO64) -> 25000 | CQ64: =SUM(CP64) -> 25000 | CR64: =+CA64 -> 25000
C65: Montant total (sur base total achat) | D65: =+D53*D64 -> 0 | E65: =+E53*E64 -> 500000 | F65: =+F53*F64 -> 0 | G65: =+G53*G64 -> 0 | K65: Montant total (sur base total achat) | L65: =+L53*L64 -> 0 | M65: =+M53*M64 -> 250000 | N65: =+N53*N64 -> 0 | O65: =+O53*O64 -> 0 | T65: Montant total (sur base total achat) | U65: =+U53*U64 -> 0 | V65: =+V53*V64 -> 500000 | W65: =+W53*W64 -> 0 | X65: =+X53*X64 -> 0 | AB65: Montant total (sur base total achat) | AC65: =+AC53*AC64 -> 0 | AD65: =+AD53*AD64 -> 250000 | AE65: =+AE53*AE64 -> 0 | AF65: =+AF53*AF64 -> 0 | AI65: Montant total (sur base total achat) | AJ65: =+AJ53*AJ64 -> 0 | AK65: =+AK53*AK64 -> 0 | AL65: =+AL53*AL64 -> 0 | AM65: =+AM53*AM64 -> 125000 | AP65: Montant total (sur base total achat) | AQ65: =+AQ53*AQ64 -> 0 | AR65: =+AR53*AR64 -> 0 | AS65: =+AS53*AS64 -> 0 | AT65: =+AT53*AT64 -> 250000 | AW65: Montant total (sur base total achat) | AX65: =+AX53*AX64 -> 250000 | AY65: =+AY53*AY64 -> 0 | AZ65: =+AZ53*AZ64 -> 0 | BA65: =+BA53*BA64 -> 0 | BD65: Montant total (sur base total achat) | BE65: =+BE53*BE64 -> 125000 | BF65: =+BF53*BF64 -> 0 | BG65: =+BG53*BG64 -> 0 | BH65: =+BH53*BH64 -> 0 | BK65: Montant total (sur base total achat) | BL65: =+BL53*BL64 -> 0 | BM65: =+BM53*BM64 -> 0 | BN65: =+BN53*BN64 -> 250000 | BO65: =+BO53*BO64 -> 0 | BR65: Montant total (sur base total achat) | BS65: =+BS53*BS64 -> 0 | BT65: =+BT53*BT64 -> 0 | BU65: =+BU53*BU64 -> 125000 | BV65: =+BV53*BV64 -> 0 | BY65: Montant total (sur base total achat) | BZ65: =+BZ53*BZ64 -> 0 | CA65: =+CA53*CA64 -> 0 | CB65: =+CB53*CB64 -> 0 | CC65: =+CC53*CC64 -> 250000 | CF65: Montant total (sur base total achat) | CG65: =+CG53*CG64 -> 0 | CH65: =+CH53*CH64 -> 0 | CI65: =+CI53*CI64 -> 0 | CJ65: =+CJ53*CJ64 -> 0 | CN65: Montant total (sur base total achat) | CO65: =+CO53*CO64 -> 0 | CP65: =+CP53*CP64 -> 0 | CQ65: =+CQ53*CQ64 -> 0 | CR65: =+CR53*CR64 -> 0
C66: Sous-total cumulé | D66: =+D65 -> 0 | E66: =+D66+E65 -> 500000 | F66: =+E66+F65 -> 500000 | G66: =+F66+G65 -> 500000 | K66: Sous-total cumulé | L66: =+L65 -> 0 | M66: =+L66+M65 -> 250000 | N66: =+M66+N65 -> 250000 | O66: =+N66+O65 -> 250000 | T66: Sous-total cumulé | U66: =+U65 -> 0 | V66: =+U66+V65 -> 500000 | W66: =+V66+W65 -> 500000 | X66: =+W66+X65 -> 500000 | AB66: Sous-total cumulé | AC66: =+AC65 -> 0 | AD66: =+AC66+AD65 -> 250000 | AE66: =+AD66+AE65 -> 250000 | AF66: =+AE66+AF65 -> 250000 | AI66: Sous-total cumulé | AJ66: =+AJ65 -> 0 | AK66: =+AJ66+AK65 -> 0 | AL66: =+AK66+AL65 -> 0 | AM66: =+AL66+AM65 -> 125000 | AP66: Sous-total cumulé | AQ66: =+AQ65 -> 0 | AR66: =+AQ66+AR65 -> 0 | AS66: =+AR66+AS65 -> 0 | AT66: =+AS66+AT65 -> 250000 | AW66: Sous-total cumulé | AX66: =+AX65 -> 250000 | AY66: =+AX66+AY65 -> 250000 | AZ66: =+AY66+AZ65 -> 250000 | BA66: =+AZ66+BA65 -> 250000 | BD66: Sous-total cumulé | BE66: =+BE65 -> 125000 | BF66: =+BE66+BF65 -> 125000 | BG66: =+BF66+BG65 -> 125000 | BH66: =+BG66+BH65 -> 125000 | BK66: Sous-total cumulé | BL66: =+BL65 -> 0 | BM66: =+BL66+BM65 -> 0 | BN66: =+BM66+BN65 -> 250000 | BO66: =+BN66+BO65 -> 250000 | BR66: Sous-total cumulé | BS66: =+BS65 -> 0 | BT66: =+BS66+BT65 -> 0 | BU66: =+BT66+BU65 -> 125000 | BV66: =+BU66+BV65 -> 125000 | BY66: Sous-total cumulé | BZ66: =+BZ65 -> 0 | CA66: =+BZ66+CA65 -> 0 | CB66: =+CA66+CB65 -> 0 | CC66: =+CB66+CC65 -> 250000 | CF66: Sous-total cumulé | CG66: =+CG65 -> 0 | CH66: =+CG66+CH65 -> 0 | CI66: =+CH66+CI65 -> 0 | CJ66: =+CI66+CJ65 -> 0 | CN66: Sous-total cumulé | CO66: =+CO65 -> 0 | CP66: =+CO66+CP65 -> 0 | CQ66: =+CP66+CQ65 -> 0 | CR66: =+CQ66+CR65 -> 0
H68: Px Rv / hectare | P68: Px Rv / hectare | Y68: Px Rv / hectare | AG68: Px Rv / hectare | AN68: Px Rv / hectare | AU68: Px Rv / hectare | BB68: Px Rv / hectare | BI68: Px Rv / hectare | BP68: Px Rv / hectare | BW68: Px Rv / hectare | CD68: Px Rv / hectare | CK68: Px Rv / hectare | CS68: Px Rv / hectare
H69: =SUM(G71)/H53 -> 391418.26 | P69: =SUM(O71)/P53 -> 387710.03 | Y69: =SUM(X71)/Y53 -> 512321.48 | AG69: =SUM(AF71)/AG53 -> 213373.3 | AN69: =SUM(AM71)/AN53 -> 1535365.4 | AU69: =SUM(AT71)/AU53 -> 263562.87 | BB69: =SUM(BA71)/BB53 -> 956757.49 | BI69: =SUM(BH71)/BI53 -> 2950070.4 | BP69: =SUM(BO71)/BP53 -> 3164715.3 | BW69: =SUM(BV71)/BW53 -> 1113822.6 | CD69: =SUM(CC71)/CD53 -> 608466.59 | CK69: =SUM(CJ71)/CJ59 -> 720000 | CS69: =SUM(CR71)/CP59 -> 180000
C70: Totaux | D70: =+D55+D61+D65 -> 0 | E70: =+E55+E61+E65 -> 7828365.2 | F70: =+F55+F61+F65 -> 0 | G70: =+G55+G61+G65 -> 0 | H70: =SUM(H53:H66) -> 20 | K70: Totaux | L70: =+L55+L61+L65 -> 0 | M70: =+M55+M61+M65 -> 3877100.3 | N70: =+N55+N61+N65 -> 0 | O70: =+O55+O61+O65 -> 0 | P70: =SUM(P53:P66) -> 10 | T70: Totaux | U70: =+U55+U61+U65 -> 0 | V70: =+V55+V61+V65 -> 10246430 | W70: =+W55+W61+W65 -> 0 | X70: =+X55+X61+X65 -> 0 | Y70: =SUM(Y53:Y66) -> 20 | AB70: Totaux | AC70: =+AC55+AC61+AC65 -> 0 | AD70: =+AD55+AD61+AD65 -> 2133733 | AE70: =+AE55+AE61+AE65 -> 0 | AF70: =+AF55+AF61+AF65 -> 0 | AG70: =SUM(AG53:AG66) -> 10 | AI70: Totaux | AJ70: =+AJ55+AJ61+AJ65 -> 0 | AK70: =+AK55+AK61+AK65 -> 0 | AL70: =+AL55+AL61+AL65 -> 0 | AM70: =+AM55+AM61+AM65 -> 7676827.2 | AN70: =SUM(AN53:AN66) -> 5 | AP70: Totaux | AQ70: =+AQ55+AQ61+AQ65 -> 0 | AR70: =+AR55+AR61+AR65 -> 0 | AS70: =+AS55+AS61+AS65 -> 0 | AT70: =+AT55+AT61+AT65 -> 2635628.7 | AU70: =SUM(AU53:AU66) -> 10 | AW70: Totaux | AX70: =+AX55+AX61+AX65 -> 9567574.9 | AY70: =+AY55+AY61+AY65 -> 0 | AZ70: =+AZ55+AZ61+AZ65 -> 0 | BA70: =+BA55+BA61+BA65 -> 0 | BB70: =SUM(BB53:BB66) -> 10 | BD70: Totaux | BE70: =+BE55+BE61+BE65 -> 14750352 | BF70: =+BF55+BF61+BF65 -> 0 | BG70: =+BG55+BG61+BG65 -> 0 | BH70: =+BH55+BH61+BH65 -> 0 | BI70: =SUM(BI53:BI66) -> 5 | BK70: Totaux | BL70: =+BL55+BL61+BL65 -> 0 | BM70: =+BM55+BM61+BM65 -> 0 | BN70: =+BN55+BN61+BN65 -> 31647153 | BO70: =+BO55+BO61+BO65 -> 0 | BP70: =SUM(BP53:BP66) -> 10 | BR70: Totaux | BS70: =+BS55+BS61+BS65 -> 0 | BT70: =+BT55+BT61+BT65 -> 0 | BU70: =+BU55+BU61+BU65 -> 5569112.9 | BV70: =+BV55+BV61+BV65 -> 0 | BW70: =SUM(BW53:BW66) -> 5 | BY70: Totaux | BZ70: =+BZ55+BZ61+BZ65 -> 0 | CA70: =+CA55+CA61+CA65 -> 0 | CB70: =+CB55+CB61+CB65 -> 0 | CC70: =+CC55+CC61+CC65 -> 6084665.9 | CD70: =SUM(CD53:CD66) -> 10 | CF70: Totaux | CG70: =+CG55+CG61+CG65 -> 900000 | CH70: =+CH55+CH61+CH65 -> 900000 | CI70: =+CI55+CI61+CI65 -> 900000 | CJ70: =+CJ55+CJ61+CJ65 -> 900000 | CK70: =SUM(CK53:CK66) -> 0 | CN70: Totaux | CO70: =+CO55+CO61+CO65 -> 0 | CP70: =+CP55+CP61+CP65 -> 900000 | CQ70: =+CQ55+CQ61+CQ65 -> 0 | CR70: =+CR55+CR61+CR65 -> 0 | CS70: =SUM(CS53:CS66) -> 0
C71: Totaux cumulés | D71: =+D70 -> 0 | E71: =+D71+E70 -> 7828365.2 | F71: =+E71+F70 -> 7828365.2 | G71: =+F71+G70 -> 7828365.2 | K71: Totaux cumulés | L71: =+L70 -> 0 | M71: =+L71+M70 -> 3877100.3 | N71: =+M71+N70 -> 3877100.3 | O71: =+N71+O70 -> 3877100.3 | T71: Totaux cumulés | U71: =+U70 -> 0 | V71: =+U71+V70 -> 10246430 | W71: =+V71+W70 -> 10246430 | X71: =+W71+X70 -> 10246430 | AB71: Totaux cumulés | AC71: =+AC70 -> 0 | AD71: =+AC71+AD70 -> 2133733 | AE71: =+AD71+AE70 -> 2133733 | AF71: =+AE71+AF70 -> 2133733 | AI71: Totaux cumulés | AJ71: =+AJ70 -> 0 | AK71: =+AJ71+AK70 -> 0 | AL71: =+AK71+AL70 -> 0 | AM71: =+AL71+AM70 -> 7676827.2 | AP71: Totaux cumulés | AQ71: =+AQ70 -> 0 | AR71: =+AQ71+AR70 -> 0 | AS71: =+AR71+AS70 -> 0 | AT71: =+AS71+AT70 -> 2635628.7 | AW71: Totaux cumulés | AX71: =+AX70 -> 9567574.9 | AY71: =+AX71+AY70 -> 9567574.9 | AZ71: =+AY71+AZ70 -> 9567574.9 | BA71: =+AZ71+BA70 -> 9567574.9 | BD71: Totaux cumulés | BE71: =+BE70 -> 14750352 | BF71: =+BE71+BF70 -> 14750352 | BG71: =+BF71+BG70 -> 14750352 | BH71: =+BG71+BH70 -> 14750352 | BK71: Totaux cumulés | BL71: =+BL70 -> 0 | BM71: =+BL71+BM70 -> 0 | BN71: =+BM71+BN70 -> 31647153 | BO71: =+BN71+BO70 -> 31647153 | BR71: Totaux cumulés | BS71: =+BS70 -> 0 | BT71: =+BS71+BT70 -> 0 | BU71: =+BT71+BU70 -> 5569112.9 | BV71: =+BU71+BV70 -> 5569112.9 | BY71: Totaux cumulés | BZ71: =+BZ70 -> 0 | CA71: =+BZ71+CA70 -> 0 | CB71: =+CA71+CB70 -> 0 | CC71: =+CB71+CC70 -> 6084665.9 | CF71: Totaux cumulés | CG71: =+CG70 -> 900000 | CH71: =+CG71+CH70 -> 1800000 | CI71: =+CH71+CI70 -> 2700000 | CJ71: =+CI71+CJ70 -> 3600000 | CN71: Totaux cumulés | CO71: =+CO70 -> 0 | CP71: =+CO71+CP70 -> 900000 | CQ71: =+CP71+CQ70 -> 900000 | CR71: =+CQ71+CR70 -> 900000
C74: Arachide (Groundnut) 2028 | K74: Niébé (Cowpea) 2028 | T74: Céréale, blé, mais (Wheat, corne, ) 2028 | Y74: Total acheté | AB74: Sesame 2028 | AG74: Total acheté | AI74: Gombo - avec goutte-à-goutte (Okra - with drip) 2028 | AN74: Total acheté | AP74: Sorgho pour graine (Sorghum for Seed) 2029 | AU74: Total acheté | AW74: Oignon - avec goutte-à-goutte (Onion - with drip) 2028 | BB74: Total acheté | BD74: Aubergine - avec goutte-à-goutte et paillage 2028 | BI74: Total acheté | BK74: Tomate - avec goutte-à-goutte et paillage 2028 | BP74: Total acheté | BR74: Pomme de terre en hiver avec irrigation 2028 | BW74: Total acheté | BY74: Luzerne (Alfa Alfa) en irrigation 2028 | CD74: Total acheté | CF74: Verget pour arbre fruitiers 2026 | CK74: Total acheté | CN74: Verget pour arbre fruitiers 2028 | CS74: Total acheté
C75: Matière première | D75: 1er trimestre | E75: 2ème trimestre | F75: 3ème trimestre | G75: 4ème trimestre | H75: Total Acheté | K75: Matière première | L75: 1er trimestre | M75: 2ème trimestre | N75: 3ème trimestre | O75: 4ème trimestre | P75: Total Acheté | T75: Achat de production | U75: 1er trimestre | V75: 2ème trimestre | W75: 3ème trimestre | X75: 4ème trimestre | Y75: Total acheté | AB75: Achat de production | AC75: 1er trimestre | AD75: 2ème trimestre | AE75: 3ème trimestre | AF75: 4ème trimestre | AI75: Achat de production | AJ75: 1er trimestre | AK75: 2ème trimestre | AL75: 3ème trimestre | AM75: 4ème trimestre | AP75: Achat de production | AQ75: 1er trimestre | AR75: 2ème trimestre | AS75: 3ème trimestre | AT75: 4ème trimestre | AW75: Achat de production | AX75: 1er trimestre | AY75: 2ème trimestre | AZ75: 3ème trimestre | BA75: 4ème trimestre | BD75: Achat de production | BE75: 1er trimestre | BF75: 2ème trimestre | BG75: 3ème trimestre | BH75: 4ème trimestre | BK75: Achat de production | BL75: 1er trimestre | BM75: 2ème trimestre | BN75: 3ème trimestre | BO75: 4ème trimestre | BR75: Achat de production | BS75: 1er trimestre | BT75: 2ème trimestre | BU75: 3ème trimestre | BV75: 4ème trimestre | BY75: Achat de production | BZ75: 1er trimestre | CA75: 2ème trimestre | CB75: 3ème trimestre | CC75: 4ème trimestre | CF75: Achat de production | CG75: 1er trimestre | CH75: 2ème trimestre | CI75: 3ème trimestre | CJ75: 4ème trimestre | CN75: Achat de production | CO75: 1er trimestre | CP75: 2ème trimestre | CQ75: 3ème trimestre | CR75: 4ème trimestre
C76: Superficie cultivée en pluviale | E76: 20 | F76: =(+'[2]Ca...'!E76+'[2]Ca...'!E82+'[2]Ca...'!E88)*1.05 -> 0 | H76: =+SUM(D76:G76) -> 20 | K76: Superficie cultivée en pluviale | M76: 10 | P76: =+SUM(L76:O76) -> 10 | T76: Superficie cultivée en pluviale | V76: 20 | Y76: =+SUM(U76:X76) -> 20 | AB76: Superficie cultivée en pluviale | AD76: 10 | AG76: =+SUM(AC76:AF76) -> 10 | AI76: Superficie cultivée en irriguation | AM76: 5 | AN76: =+SUM(AJ76:AM76) -> 5 | AP76: Superficie cultivée en irriguation | AT76: 10 | AU76: =+SUM(AQ76:AT76) -> 10 | AW76: Superficie cultivée en irriguation | AX76: 10 | BB76: =+SUM(AX76:BA76) -> 10 | BD76: Superficie cultivée en irriguation | BE76: 5 | BI76: =+SUM(BE76:BH76) -> 5 | BK76: Superficie cultivée en irriguation | BN76: 10 | BP76: =+SUM(BL76:BO76) -> 10 | BR76: Superficie cultivée en irriguation | BU76: 5 | BW76: =+SUM(BS76:BV76) -> 5 | BY76: Superficie cultivée en irriguation | CC76: 10 | CD76: =+SUM(BZ76:CC76) -> 10 | CF76: Superficie cultivée en irriguation | CK76: =+SUM(CG76:CJ76) -> 0 | CN76: Superficie cultivée en irriguation | CS76: =+SUM(CO76:CR76) -> 0
C77: Coût unitaire par hectare | D77: =SUM(D54) -> 331418.26 | E77: =+D77 -> 331418.26 | F77: =+E77 -> 331418.26 | G77: =+F77 -> 331418.26 | K77: Coût unitaire par hectare | L77: =SUM(L54)*1.1 -> 360481.03 | M77: =+L77 -> 360481.03 | N77: =+M77 -> 360481.03 | O77: =+N77 -> 360481.03 | T77: Coût unitaire par hectare | U77: =SUM(U54)*1.1 -> 497553.63 | V77: =SUM(V54)*1.1 -> 497553.63 | W77: =SUM(W54)*1.1 -> 497553.63 | X77: =SUM(X54)*1.1 -> 497553.63 | AB77: Coût unitaire par hectare | AC77: =SUM(AC54)*1.1 -> 168710.63 | AD77: =SUM(AD54)*1.1 -> 168710.63 | AE77: =SUM(AE54)*1.1 -> 168710.63 | AF77: =SUM(AF54)*1.1 -> 168710.63 | AI77: Coût unitaire par hectare | AJ77: =SUM(AJ54)*1.1 -> 1622902 | AK77: =SUM(AK54)*1.1 -> 1622902 | AL77: =SUM(AL54)*1.1 -> 1622902 | AM77: =SUM(AM54)*1.1 -> 1622902 | AP77: Coût unitaire par hectare | AQ77: =SUM(AQ54)*1.1 -> 223919.16 | AR77: =SUM(AR54)*1.1 -> 223919.16 | AS77: =SUM(AS54)*1.1 -> 223919.16 | AT77: =SUM(AT54)*1.1 -> 223919.16 | AW77: Coût unitaire par hectare | AX77: =SUM(AX54)*1.1 -> 986433.24 | AY77: =SUM(AY54)*1.1 -> 986433.24 | AZ77: =SUM(AZ54)*1.1 -> 986433.24 | BA77: =SUM(BA54)*1.1 -> 986433.24 | BD77: Coût unitaire par hectare | BE77: =SUM(BE54)*1.1 -> 3179077.4 | BF77: =SUM(BF54)*1.1 -> 3179077.4 | BG77: =SUM(BG54)*1.1 -> 3179077.4 | BH77: =SUM(BH54)*1.1 -> 3179077.4 | BK77: Coût unitaire par hectare | BL77: =SUM(BL54)*1.1 -> 3415186.8 | BM77: =SUM(BM54)*1.1 -> 3415186.8 | BN77: =SUM(BN54)*1.1 -> 3415186.8 | BO77: =SUM(BO54)*1.1 -> 3415186.8 | BR77: Coût unitaire par hectare | BS77: =SUM(BS54)*1.1 -> 1159204.8 | BT77: =SUM(BT54)*1.1 -> 1159204.8 | BU77: =SUM(BU54)*1.1 -> 1159204.8 | BV77: =SUM(BV54)*1.1 -> 1159204.8 | BY77: Coût unitaire par hectare | BZ77: =SUM(BZ54)*1.1 -> 603313.24 | CA77: =SUM(CA54)*1.1 -> 603313.24 | CB77: =SUM(CB54)*1.1 -> 603313.24 | CC77: =SUM(CC54)*1.1 -> 603313.24 | CF77: Coût unitaire par hectare | CG77: =SUM(CG54)*1.1 -> 1375000 | CH77: =SUM(CH54)*1.1 -> 1375000 | CI77: =SUM(CI54)*1.1 -> 1375000 | CJ77: =SUM(CJ54)*1.1 -> 1375000 | CN77: Coût unitaire par hectare | CO77: =SUM(CO54)*1.1 -> 660000 | CP77: =SUM(CP54)*1.1 -> 660000 | CQ77: =SUM(CQ54)*1.1 -> 660000 | CR77: =SUM(CR54)*1.1 -> 660000
C78: Sous-total | D78: =+D77*D76 -> 0 | E78: =+E77*E76 -> 6628365.2 | F78: =+F77*F76 -> 0 | G78: =+G77*G76 -> 0 | K78: Sous-total | L78: =+L77*L76 -> 0 | M78: =+M77*M76 -> 3604810.3 | N78: =+N77*N76 -> 0 | O78: =+O77*O76 -> 0 | T78: Sous-total | U78: =+U77*U76 -> 0 | V78: =+V77*V76 -> 9951072.5 | W78: =+W77*W76 -> 0 | X78: =+X77*X76 -> 0 | AB78: Sous-total | AC78: =+AC77*AC76 -> 0 | AD78: =+AD77*AD76 -> 1687106.3 | AE78: =+AE77*AE76 -> 0 | AF78: =+AF77*AF76 -> 0 | AI78: Sous-total | AJ78: =+AJ77*AJ76 -> 0 | AK78: =+AK77*AK76 -> 0 | AL78: =+AL77*AL76 -> 0 | AM78: =+AM77*AM76 -> 8114509.9 | AP78: Sous-total | AQ78: =+AQ77*AQ76 -> 0 | AR78: =+AR77*AR76 -> 0 | AS78: =+AS77*AS76 -> 0 | AT78: =+AT77*AT76 -> 2239191.6 | AW78: Sous-total | AX78: =+AX77*AX76 -> 9864332.4 | AY78: =+AY77*AY76 -> 0 | AZ78: =+AZ77*AZ76 -> 0 | BA78: =+BA77*BA76 -> 0 | BD78: Sous-total | BE78: =+BE77*BE76 -> 15895387 | BF78: =+BF77*BF76 -> 0 | BG78: =+BG77*BG76 -> 0 | BH78: =+BH77*BH76 -> 0 | BK78: Sous-total | BL78: =+BL77*BL76 -> 0 | BM78: =+BM77*BM76 -> 0 | BN78: =+BN77*BN76 -> 34151868 | BO78: =+BO77*BO76 -> 0 | BR78: Sous-total | BS78: =+BS77*BS76 -> 0 | BT78: =+BT77*BT76 -> 0 | BU78: =+BU77*BU76 -> 5796024.1 | BV78: =+BV77*BV76 -> 0 | BY78: Sous-total | BZ78: =+BZ77*BZ76 -> 0 | CA78: =+CA77*CA76 -> 0 | CB78: =+CB77*CB76 -> 0 | CC78: =+CC77*CC76 -> 6033132.5 | CF78: Sous-total | CG78: =+CG77*CG76 -> 0 | CH78: =+CH77*CH76 -> 0 | CI78: =+CI77*CI76 -> 0 | CJ78: =+CJ77*CJ76 -> 0 | CN78: Sous-total | CO78: =+CO77*CO76 -> 0 | CP78: =+CP77*CP76 -> 0 | CQ78: =+CQ77*CQ76 -> 0 | CR78: =+CR77*CR76 -> 0
C79: Sous-total cumulé | D79: =+D78 -> 0 | E79: =+D79+E78 -> 6628365.2 | F79: =+E79+F78 -> 6628365.2 | G79: =+F79+G78 -> 6628365.2 | K79: Sous-total cumulé | L79: =+L78 -> 0 | M79: =+L79+M78 -> 3604810.3 | N79: =+M79+N78 -> 3604810.3 | O79: =+N79+O78 -> 3604810.3 | T79: Sous-total cumulé | U79: =+U78 -> 0 | V79: =+U79+V78 -> 9951072.5 | W79: =+V79+W78 -> 9951072.5 | X79: =+W79+X78 -> 9951072.5 | AB79: Sous-total cumulé | AC79: =+AC78 -> 0 | AD79: =+AC79+AD78 -> 1687106.3 | AE79: =+AD79+AE78 -> 1687106.3 | AF79: =+AE79+AF78 -> 1687106.3 | AI79: Sous-total cumulé | AJ79: =+AJ78 -> 0 | AK79: =+AJ79+AK78 -> 0 | AL79: =+AK79+AL78 -> 0 | AM79: =+AL79+AM78 -> 8114509.9 | AP79: Sous-total cumulé | AQ79: =+AQ78 -> 0 | AR79: =+AQ79+AR78 -> 0 | AS79: =+AR79+AS78 -> 0 | AT79: =+AS79+AT78 -> 2239191.6 | AW79: Sous-total cumulé | AX79: =+AX78 -> 9864332.4 | AY79: =+AX79+AY78 -> 9864332.4 | AZ79: =+AY79+AZ78 -> 9864332.4 | BA79: =+AZ79+BA78 -> 9864332.4 | BD79: Sous-total cumulé | BE79: =+BE78 -> 15895387 | BF79: =+BE79+BF78 -> 15895387 | BG79: =+BF79+BG78 -> 15895387 | BH79: =+BG79+BH78 -> 15895387 | BK79: Sous-total cumulé | BL79: =+BL78 -> 0 | BM79: =+BL79+BM78 -> 0 | BN79: =+BM79+BN78 -> 34151868 | BO79: =+BN79+BO78 -> 34151868 | BR79: Sous-total cumulé | BS79: =+BS78 -> 0 | BT79: =+BS79+BT78 -> 0 | BU79: =+BT79+BU78 -> 5796024.1 | BV79: =+BU79+BV78 -> 5796024.1 | BY79: Sous-total cumulé | BZ79: =+BZ78 -> 0 | CA79: =+BZ79+CA78 -> 0 | CB79: =+CA79+CB78 -> 0 | CC79: =+CB79+CC78 -> 6033132.5 | CF79: Sous-total cumulé | CG79: =+CG78 -> 0 | CH79: =+CG79+CH78 -> 0 | CI79: =+CH79+CI78 -> 0 | CJ79: =+CI79+CJ78 -> 0 | CN79: Sous-total cumulé | CO79: =+CO78 -> 0 | CP79: =+CO79+CP78 -> 0 | CQ79: =+CP79+CQ78 -> 0 | CR79: =+CQ79+CR78 -> 0
C81: Ensachage et autres fournitures | K81: Ensachage et autres fournitures | T81: Transports mis en Fob et SGS (coût /tonne) | AB81: Transports mis en Fob et SGS (coût /tonne) | AI81: Transports mis en Fob et SGS (coût /tonne) | AP81: Transports mis en Fob et SGS (coût /tonne) | AW81: Transports mis en Fob et SGS (coût /tonne) | BD81: Transports mis en Fob et SGS (coût /tonne) | BK81: Transports mis en Fob et SGS (coût /tonne) | BR81: Transports mis en Fob et SGS (coût /tonne) | BY81: Transports mis en Fob et SGS (coût /tonne) | CF81: charge d'arosage et autres frais d'entretien | CN81: charge d'arosage et autres frais d'entretien
C82: Production brute (tonne) | D82: =+D76 -> 0 | E82: =+E76 -> 20 | F82: =+F76 -> 0 | G82: =+G76 -> 0 | K82: Production brute (tonne) | L82: =+L76 -> 0 | M82: =+M76 -> 10 | N82: =+N76 -> 0 | O82: =+O76 -> 0 | T82: Production brute | U82: =+U76 -> 0 | V82: =+V76 -> 20 | W82: =+W76 -> 0 | X82: =+X76 -> 0 | AB82: Production brute | AC82: =+AC76 -> 0 | AD82: =+AD76 -> 10 | AE82: =+AE76 -> 0 | AF82: =+AF76 -> 0 | AI82: Production brute | AJ82: =+AJ76 -> 0 | AK82: =+AK76 -> 0 | AL82: =+AL76 -> 0 | AM82: =+AM76 -> 5 | AP82: Production brute | AQ82: =+AQ76 -> 0 | AR82: =+AR76 -> 0 | AS82: =+AS76 -> 0 | AT82: =+AT76 -> 10 | AW82: Production brute | AX82: =+AX76 -> 10 | AY82: =+AY76 -> 0 | AZ82: =+AZ76 -> 0 | BA82: =+BA76 -> 0 | BD82: Production brute | BE82: =+BE76 -> 5 | BF82: =+BF76 -> 0 | BG82: =+BG76 -> 0 | BH82: =+BH76 -> 0 | BK82: Production brute | BL82: =+BL76 -> 0 | BM82: =+BM76 -> 0 | BN82: =+BN76 -> 10 | BO82: =+BO76 -> 0 | BR82: Production brute | BS82: =+BS76 -> 0 | BT82: =+BT76 -> 0 | BU82: =+BU76 -> 5 | BV82: =+BV76 -> 0 | BY82: Production brute | BZ82: =+BZ76 -> 0 | CA82: =+CA76 -> 0 | CB82: =+CB76 -> 0 | CC82: =+CC76 -> 10 | CF82: Production brute | CG82: 5 | CH82: =SUM(CG82) -> 5 | CI82: =SUM(CH82) -> 5 | CJ82: =SUM(CI82) -> 5 | CN82: Production brute | CP82: 5
C83: Coût Unitaire | D83: =+D60*1.1 -> 38500 | E83: =+D83 -> 38500 | F83: =+E83 -> 38500 | G83: =+F83 -> 38500 | K83: Coût Unitaire | L83: =+L60*1.1 -> 38500 | M83: =+L83 -> 38500 | N83: =+M83 -> 38500 | O83: =+N83 -> 38500 | T83: Coût Unitaire | U83: =+X60*1.1 -> 38500 | V83: =+U83 -> 38500 | W83: =+V83 -> 38500 | X83: =+W83 -> 38500 | AB83: Coût Unitaire | AC83: =+AF60*1.1 -> 38500 | AD83: =+AC83 -> 38500 | AE83: =+AD83 -> 38500 | AF83: =+AE83 -> 38500 | AI83: Coût Unitaire | AJ83: =+AM60*1.1 -> 38500 | AK83: =+AJ83 -> 38500 | AL83: =+AK83 -> 38500 | AM83: =+AL83 -> 38500 | AP83: Coût Unitaire | AQ83: =+AT60*1.1 -> 38500 | AR83: =+AQ83 -> 38500 | AS83: =+AR83 -> 38500 | AT83: =+AS83 -> 38500 | AW83: Coût Unitaire | AX83: =+BA60*1.1 -> 38500 | AY83: =+AX83 -> 38500 | AZ83: =+AY83 -> 38500 | BA83: =+AZ83 -> 38500 | BD83: Coût Unitaire | BE83: =+BH60*1.1 -> 38500 | BF83: =+BE83 -> 38500 | BG83: =+BF83 -> 38500 | BH83: =+BG83 -> 38500 | BK83: Coût Unitaire | BL83: =+BO60*1.1 -> 38500 | BM83: =+BL83 -> 38500 | BN83: =+BM83 -> 38500 | BO83: =+BN83 -> 38500 | BR83: Coût Unitaire | BS83: =+BV60*1.1 -> 38500 | BT83: =+BS83 -> 38500 | BU83: =+BT83 -> 38500 | BV83: =+BU83 -> 38500 | BY83: Coût Unitaire | BZ83: =+CC60*1.1 -> 38500 | CA83: =+BZ83 -> 38500 | CB83: =+CA83 -> 38500 | CC83: =+CB83 -> 38500 | CF83: Coût Unitaire | CG83: =+CJ60*1.1 -> 198000 | CH83: =+CG83 -> 198000 | CI83: =+CH83 -> 198000 | CJ83: =+CI83 -> 198000 | CN83: Coût Unitaire | CO83: =+CR60*1.1 -> 198000 | CP83: =+CO83 -> 198000 | CQ83: =+CP83 -> 198000 | CR83: =+CQ83 -> 198000
C84: Sous-total | D84: =+D83*D82 -> 0 | E84: =+E83*E82 -> 770000 | F84: =+F83*F82 -> 0 | G84: =+G83*G82 -> 0 | K84: Sous-total | L84: =+L83*L82 -> 0 | M84: =+M83*M82 -> 385000 | N84: =+N83*N82 -> 0 | O84: =+O83*O82 -> 0 | T84: Sous-total | U84: =+U83*U82 -> 0 | V84: =+V83*V82 -> 770000 | W84: =+W83*W82 -> 0 | X84: =+X83*X82 -> 0 | AB84: Sous-total | AC84: =+AC83*AC82 -> 0 | AD84: =+AD83*AD82 -> 385000 | AE84: =+AE83*AE82 -> 0 | AF84: =+AF83*AF82 -> 0 | AI84: Sous-total | AJ84: =+AJ83*AJ82 -> 0 | AK84: =+AK83*AK82 -> 0 | AL84: =+AL83*AL82 -> 0 | AM84: =+AM83*AM82 -> 192500 | AP84: Sous-total | AQ84: =+AQ83*AQ82 -> 0 | AR84: =+AR83*AR82 -> 0 | AS84: =+AS83*AS82 -> 0 | AT84: =+AT83*AT82 -> 385000 | AW84: Sous-total | AX84: =+AX83*AX82 -> 385000 | AY84: =+AY83*AY82 -> 0 | AZ84: =+AZ83*AZ82 -> 0 | BA84: =+BA83*BA82 -> 0 | BD84: Sous-total | BE84: =+BE83*BE82 -> 192500 | BF84: =+BF83*BF82 -> 0 | BG84: =+BG83*BG82 -> 0 | BH84: =+BH83*BH82 -> 0 | BK84: Sous-total | BL84: =+BL83*BL82 -> 0 | BM84: =+BM83*BM82 -> 0 | BN84: =+BN83*BN82 -> 385000 | BO84: =+BO83*BO82 -> 0 | BR84: Sous-total | BS84: =+BS83*BS82 -> 0 | BT84: =+BT83*BT82 -> 0 | BU84: =+BU83*BU82 -> 192500 | BV84: =+BV83*BV82 -> 0 | BY84: Sous-total | BZ84: =+BZ83*BZ82 -> 0 | CA84: =+CA83*CA82 -> 0 | CB84: =+CB83*CB82 -> 0 | CC84: =+CC83*CC82 -> 385000 | CF84: Sous-total | CG84: =+CG83*CG82 -> 990000 | CH84: =+CH83*CH82 -> 990000 | CI84: =+CI83*CI82 -> 990000 | CJ84: =+CJ83*CJ82 -> 990000 | CN84: Sous-total | CO84: =+CO83*CO82 -> 0 | CP84: =+CP83*CP82 -> 990000 | CQ84: =+CQ83*CQ82 -> 0 | CR84: =+CR83*CR82 -> 0
C85: Sous-total cumulé | D85: =+D84 -> 0 | E85: =+D85+E84 -> 770000 | F85: =+E85+F84 -> 770000 | G85: =+F85+G84 -> 770000 | K85: Sous-total cumulé | L85: =+L84 -> 0 | M85: =+L85+M84 -> 385000 | N85: =+M85+N84 -> 385000 | O85: =+N85+O84 -> 385000 | T85: Sous-total cumulé | U85: =+U84 -> 0 | V85: =+U85+V84 -> 770000 | W85: =+V85+W84 -> 770000 | X85: =+W85+X84 -> 770000 | AB85: Sous-total cumulé | AC85: =+AC84 -> 0 | AD85: =+AC85+AD84 -> 385000 | AE85: =+AD85+AE84 -> 385000 | AF85: =+AE85+AF84 -> 385000 | AI85: Sous-total cumulé | AJ85: =+AJ84 -> 0 | AK85: =+AJ85+AK84 -> 0 | AL85: =+AK85+AL84 -> 0 | AM85: =+AL85+AM84 -> 192500 | AP85: Sous-total cumulé | AQ85: =+AQ84 -> 0 | AR85: =+AQ85+AR84 -> 0 | AS85: =+AR85+AS84 -> 0 | AT85: =+AS85+AT84 -> 385000 | AW85: Sous-total cumulé | AX85: =+AX84 -> 385000 | AY85: =+AX85+AY84 -> 385000 | AZ85: =+AY85+AZ84 -> 385000 | BA85: =+AZ85+BA84 -> 385000 | BD85: Sous-total cumulé | BE85: =+BE84 -> 192500 | BF85: =+BE85+BF84 -> 192500 | BG85: =+BF85+BG84 -> 192500 | BH85: =+BG85+BH84 -> 192500 | BK85: Sous-total cumulé | BL85: =+BL84 -> 0 | BM85: =+BL85+BM84 -> 0 | BN85: =+BM85+BN84 -> 385000 | BO85: =+BN85+BO84 -> 385000 | BR85: Sous-total cumulé | BS85: =+BS84 -> 0 | BT85: =+BS85+BT84 -> 0 | BU85: =+BT85+BU84 -> 192500 | BV85: =+BU85+BV84 -> 192500 | BY85: Sous-total cumulé | BZ85: =+BZ84 -> 0 | CA85: =+BZ85+CA84 -> 0 | CB85: =+CA85+CB84 -> 0 | CC85: =+CB85+CC84 -> 385000 | CF85: Sous-total cumulé | CG85: =+CG84 -> 990000 | CH85: =+CG85+CH84 -> 1980000 | CI85: =+CH85+CI84 -> 2970000 | CJ85: =+CI85+CJ84 -> 3960000 | CN85: Sous-total cumulé | CO85: =+CO84 -> 0 | CP85: =+CO85+CP84 -> 990000 | CQ85: =+CP85+CQ84 -> 990000 | CR85: =+CQ85+CR84 -> 990000
C87: Transports, manutention, stock des intrants (coût /hectare) | D87: =+D64*1.1 -> 27500 | E87: =+D87 -> 27500 | F87: =+E87 -> 27500 | G87: =+F87 -> 27500 | K87: Transports, manutention, stock des intrants (coût /hectare) | L87: =+L64*1.1 -> 27500 | M87: =+L87 -> 27500 | N87: =+M87 -> 27500 | O87: =+N87 -> 27500 | T87: Transports, manutention, stock des intrants (coût /hectare) | U87: =SUM(U64)*1.1 -> 27500 | V87: =+U87 -> 27500 | W87: =+V87 -> 27500 | X87: =+W87 -> 27500 | AB87: Transports, manutention, stock des intrants (coût /hectare) | AC87: =SUM(AC64)*1.1 -> 27500 | AD87: =+AC87 -> 27500 | AE87: =+AD87 -> 27500 | AF87: =+AE87 -> 27500 | AI87: Transports, manutention, stock des intrants (coût /hectare) | AJ87: =SUM(AJ64)*1.1 -> 27500 | AK87: =+AJ87 -> 27500 | AL87: =+AK87 -> 27500 | AM87: =+AL87 -> 27500 | AP87: Transports, manutention, stock des intrants (coût /hectare) | AQ87: =SUM(AQ64)*1.1 -> 27500 | AR87: =+AQ87 -> 27500 | AS87: =+AR87 -> 27500 | AT87: =+AS87 -> 27500 | AW87: Transports, manutention, stock des intrants (coût /hectare) | AX87: =SUM(AX64)*1.1 -> 27500 | AY87: =+AX87 -> 27500 | AZ87: =+AY87 -> 27500 | BA87: =+AZ87 -> 27500 | BD87: Transports, manutention, stock des intrants (coût /hectare) | BE87: =SUM(BE64)*1.1 -> 27500 | BF87: =+BE87 -> 27500 | BG87: =+BF87 -> 27500 | BH87: =+BG87 -> 27500 | BK87: Transports, manutention, stock des intrants (coût /hectare) | BL87: =SUM(BL64)*1.1 -> 27500 | BM87: =+BL87 -> 27500 | BN87: =+BM87 -> 27500 | BO87: =+BN87 -> 27500 | BR87: Transports, manutention, stock des intrants (coût /hectare) | BS87: =SUM(BS64)*1.1 -> 27500 | BT87: =+BS87 -> 27500 | BU87: =+BT87 -> 27500 | BV87: =+BU87 -> 27500 | BY87: Transports, manutention, stock des intrants (coût /hectare) | BZ87: =SUM(BZ64)*1.1 -> 27500 | CA87: =+BZ87 -> 27500 | CB87: =+CA87 -> 27500 | CC87: =+CB87 -> 27500 | CF87: Transports, manutention, stock des intrants (coût /hectare) | CG87: =SUM(CG64)*1.1 -> 27500 | CH87: =+CG87 -> 27500 | CI87: =+CH87 -> 27500 | CJ87: =+CI87 -> 27500 | CN87: Transports, manutention et recolte Gome | CO87: =SUM(CO64)*1.1 -> 27500 | CP87: =+CO87 -> 27500 | CQ87: =+CP87 -> 27500 | CR87: =+CQ87 -> 27500
C88: Montant total (sur base total achat) | D88: =+D76*D87 -> 0 | E88: =+E76*E87 -> 550000 | F88: =+F76*F87 -> 0 | G88: =+G76*G87 -> 0 | K88: Montant total (sur base total achat) | L88: =+L76*L87 -> 0 | M88: =+M76*M87 -> 275000 | N88: =+N76*N87 -> 0 | O88: =+O76*O87 -> 0 | T88: Montant total (sur base total achat) | U88: =+U76*U87 -> 0 | V88: =+V76*V87 -> 550000 | W88: =+W76*W87 -> 0 | X88: =+X76*X87 -> 0 | AB88: Montant total (sur base total achat) | AC88: =+AC76*AC87 -> 0 | AD88: =+AD76*AD87 -> 275000 | AE88: =+AE76*AE87 -> 0 | AF88: =+AF76*AF87 -> 0 | AI88: Montant total (sur base total achat) | AJ88: =+AJ76*AJ87 -> 0 | AK88: =+AK76*AK87 -> 0 | AL88: =+AL76*AL87 -> 0 | AM88: =+AM76*AM87 -> 137500 | AP88: Montant total (sur base total achat) | AQ88: =+AQ76*AQ87 -> 0 | AR88: =+AR76*AR87 -> 0 | AS88: =+AS76*AS87 -> 0 | AT88: =+AT76*AT87 -> 275000 | AW88: Montant total (sur base total achat) | AX88: =+AX76*AX87 -> 275000 | AY88: =+AY76*AY87 -> 0 | AZ88: =+AZ76*AZ87 -> 0 | BA88: =+BA76*BA87 -> 0 | BD88: Montant total (sur base total achat) | BE88: =+BE76*BE87 -> 137500 | BF88: =+BF76*BF87 -> 0 | BG88: =+BG76*BG87 -> 0 | BH88: =+BH76*BH87 -> 0 | BK88: Montant total (sur base total achat) | BL88: =+BL76*BL87 -> 0 | BM88: =+BM76*BM87 -> 0 | BN88: =+BN76*BN87 -> 275000 | BO88: =+BO76*BO87 -> 0 | BR88: Montant total (sur base total achat) | BS88: =+BS76*BS87 -> 0 | BT88: =+BT76*BT87 -> 0 | BU88: =+BU76*BU87 -> 137500 | BV88: =+BV76*BV87 -> 0 | BY88: Montant total (sur base total achat) | BZ88: =+BZ76*BZ87 -> 0 | CA88: =+CA76*CA87 -> 0 | CB88: =+CB76*CB87 -> 0 | CC88: =+CC76*CC87 -> 275000 | CF88: Montant total (sur base total achat) | CG88: =+CG76*CG87 -> 0 | CH88: =+CH76*CH87 -> 0 | CI88: =+CI76*CI87 -> 0 | CJ88: =+CJ76*CJ87 -> 0 | CN88: Montant total (sur base total achat) | CO88: =+CO76*CO87 -> 0 | CP88: =+CP76*CP87 -> 0 | CQ88: =+CQ76*CQ87 -> 0 | CR88: =+CR76*CR87 -> 0
C89: Sous-total cumulé | D89: =+D88 -> 0 | E89: =+D89+E88 -> 550000 | F89: =+E89+F88 -> 550000 | G89: =+F89+G88 -> 550000 | K89: Sous-total cumulé | L89: =+L88 -> 0 | M89: =+L89+M88 -> 275000 | N89: =+M89+N88 -> 275000 | O89: =+N89+O88 -> 275000 | T89: Sous-total cumulé | U89: =+U88 -> 0 | V89: =+U89+V88 -> 550000 | W89: =+V89+W88 -> 550000 | X89: =+W89+X88 -> 550000 | AB89: Sous-total cumulé | AC89: =+AC88 -> 0 | AD89: =+AC89+AD88 -> 275000 | AE89: =+AD89+AE88 -> 275000 | AF89: =+AE89+AF88 -> 275000 | AI89: Sous-total cumulé | AJ89: =+AJ88 -> 0 | AK89: =+AJ89+AK88 -> 0 | AL89: =+AK89+AL88 -> 0 | AM89: =+AL89+AM88 -> 137500 | AP89: Sous-total cumulé | AQ89: =+AQ88 -> 0 | AR89: =+AQ89+AR88 -> 0 | AS89: =+AR89+AS88 -> 0 | AT89: =+AS89+AT88 -> 275000 | AW89: Sous-total cumulé | AX89: =+AX88 -> 275000 | AY89: =+AX89+AY88 -> 275000 | AZ89: =+AY89+AZ88 -> 275000 | BA89: =+AZ89+BA88 -> 275000 | BD89: Sous-total cumulé | BE89: =+BE88 -> 137500 | BF89: =+BE89+BF88 -> 137500 | BG89: =+BF89+BG88 -> 137500 | BH89: =+BG89+BH88 -> 137500 | BK89: Sous-total cumulé | BL89: =+BL88 -> 0 | BM89: =+BL89+BM88 -> 0 | BN89: =+BM89+BN88 -> 275000 | BO89: =+BN89+BO88 -> 275000 | BR89: Sous-total cumulé | BS89: =+BS88 -> 0 | BT89: =+BS89+BT88 -> 0 | BU89: =+BT89+BU88 -> 137500 | BV89: =+BU89+BV88 -> 137500 | BY89: Sous-total cumulé | BZ89: =+BZ88 -> 0 | CA89: =+BZ89+CA88 -> 0 | CB89: =+CA89+CB88 -> 0 | CC89: =+CB89+CC88 -> 275000 | CF89: Sous-total cumulé | CG89: =+CG88 -> 0 | CH89: =+CG89+CH88 -> 0 | CI89: =+CH89+CI88 -> 0 | CJ89: =+CI89+CJ88 -> 0 | CN89: Sous-total cumulé | CO89: =+CO88 -> 0 | CP89: =+CO89+CP88 -> 0 | CQ89: =+CP89+CQ88 -> 0 | CR89: =+CQ89+CR88 -> 0
H91: Px Rv / hectare | P91: Px Rv / hectare | Y91: Px Rv / hectare | AG91: Px Rv / hectare | AN91: Px Rv / hectare | AU91: Px Rv / hectare | BB91: Px Rv / hectare | BI91: Px Rv / hectare | BP91: Px Rv / hectare | BW91: Px Rv / hectare | CD91: Px Rv / hectare | CK91: Px Rv / hectare | CS91: Px Rv / hectare
H92: =SUM(G94)/H76 -> 397418.26 | P92: =SUM(O94)/P76 -> 426481.03 | Y92: =SUM(X94)/Y76 -> 563553.63 | AG92: =SUM(AF94)/AG76 -> 234710.63 | AN92: =SUM(AM94)/AN76 -> 1688902 | AU92: =SUM(AT94)/AU76 -> 289919.16 | BB92: =SUM(BA94)/BB76 -> 1052433.2 | BI92: =SUM(BH94)/BI76 -> 3245077.4 | BP92: =SUM(BO94)/BP76 -> 3481186.8 | BW92: =SUM(BV94)/BW76 -> 1225204.8 | CD92: =SUM(CC94)/CD76 -> 669313.24 | CK92: =SUM(CJ94)/CJ82 -> 792000 | CS92: =SUM(CR94)/CR82 -> #DIV/0!
C93: Totaux | D93: =+D78+D84+D88 -> 0 | E93: =+E78+E84+E88 -> 7948365.2 | F93: =+F78+F84+F88 -> 0 | G93: =+G78+G84+G88 -> 0 | H93: =SUM(H76:H89) -> 20 | K93: Totaux | L93: =+L78+L84+L88 -> 0 | M93: =+M78+M84+M88 -> 4264810.3 | N93: =+N78+N84+N88 -> 0 | O93: =+O78+O84+O88 -> 0 | P93: =SUM(P76:P89) -> 10 | T93: Totaux | U93: =+U78+U84+U88 -> 0 | V93: =+V78+V84+V88 -> 11271073 | W93: =+W78+W84+W88 -> 0 | X93: =+X78+X84+X88 -> 0 | Y93: =SUM(Y76:Y89) -> 20 | AB93: Totaux | AC93: =+AC78+AC84+AC88 -> 0 | AD93: =+AD78+AD84+AD88 -> 2347106.3 | AE93: =+AE78+AE84+AE88 -> 0 | AF93: =+AF78+AF84+AF88 -> 0 | AG93: =SUM(AG76:AG89) -> 10 | AI93: Totaux | AJ93: =+AJ78+AJ84+AJ88 -> 0 | AK93: =+AK78+AK84+AK88 -> 0 | AL93: =+AL78+AL84+AL88 -> 0 | AM93: =+AM78+AM84+AM88 -> 8444509.9 | AN93: =SUM(AN76:AN89) -> 5 | AP93: Totaux | AQ93: =+AQ78+AQ84+AQ88 -> 0 | AR93: =+AR78+AR84+AR88 -> 0 | AS93: =+AS78+AS84+AS88 -> 0 | AT93: =+AT78+AT84+AT88 -> 2899191.6 | AU93: =SUM(AU76:AU89) -> 10 | AW93: Totaux | AX93: =+AX78+AX84+AX88 -> 10524332 | AY93: =+AY78+AY84+AY88 -> 0 | AZ93: =+AZ78+AZ84+AZ88 -> 0 | BA93: =+BA78+BA84+BA88 -> 0 | BB93: =SUM(BB76:BB89) -> 10 | BD93: Totaux | BE93: =+BE78+BE84+BE88 -> 16225387 | BF93: =+BF78+BF84+BF88 -> 0 | BG93: =+BG78+BG84+BG88 -> 0 | BH93: =+BH78+BH84+BH88 -> 0 | BI93: =SUM(BI76:BI89) -> 5 | BK93: Totaux | BL93: =+BL78+BL84+BL88 -> 0 | BM93: =+BM78+BM84+BM88 -> 0 | BN93: =+BN78+BN84+BN88 -> 34811868 | BO93: =+BO78+BO84+BO88 -> 0 | BP93: =SUM(BP76:BP89) -> 10 | BR93: Totaux | BS93: =+BS78+BS84+BS88 -> 0 | BT93: =+BT78+BT84+BT88 -> 0 | BU93: =+BU78+BU84+BU88 -> 6126024.1 | BV93: =+BV78+BV84+BV88 -> 0 | BW93: =SUM(BW76:BW89) -> 5 | BY93: Totaux | BZ93: =+BZ78+BZ84+BZ88 -> 0 | CA93: =+CA78+CA84+CA88 -> 0 | CB93: =+CB78+CB84+CB88 -> 0 | CC93: =+CC78+CC84+CC88 -> 6693132.5 | CD93: =SUM(CD76:CD89) -> 10 | CF93: Totaux | CG93: =+CG78+CG84+CG88 -> 990000 | CH93: =+CH78+CH84+CH88 -> 990000 | CI93: =+CI78+CI84+CI88 -> 990000 | CJ93: =+CJ78+CJ84+CJ88 -> 990000 | CK93: =SUM(CK76:CK89) -> 0 | CN93: Totaux | CO93: =+CO78+CO84+CO88 -> 0 | CP93: =+CP78+CP84+CP88 -> 990000 | CQ93: =+CQ78+CQ84+CQ88 -> 0 | CR93: =+CR78+CR84+CR88 -> 0 | CS93: =SUM(CS76:CS89) -> 0
C94: Totaux cumulés | D94: =+D93 -> 0 | E94: =+D94+E93 -> 7948365.2 | F94: =+E94+F93 -> 7948365.2 | G94: =+F94+G93 -> 7948365.2 | K94: Totaux cumulés | L94: =+L93 -> 0 | M94: =+L94+M93 -> 4264810.3 | N94: =+M94+N93 -> 4264810.3 | O94: =+N94+O93 -> 4264810.3 | T94: Totaux cumulés | U94: =+U93 -> 0 | V94: =+U94+V93 -> 11271073 | W94: =+V94+W93 -> 11271073 | X94: =+W94+X93 -> 11271073 | AB94: Totaux cumulés | AC94: =+AC93 -> 0 | AD94: =+AC94+AD93 -> 2347106.3 | AE94: =+AD94+AE93 -> 2347106.3 | AF94: =+AE94+AF93 -> 2347106.3 | AI94: Totaux cumulés | AJ94: =+AJ93 -> 0 | AK94: =+AJ94+AK93 -> 0 | AL94: =+AK94+AL93 -> 0 | AM94: =+AL94+AM93 -> 8444509.9 | AP94: Totaux cumulés | AQ94: =+AQ93 -> 0 | AR94: =+AQ94+AR93 -> 0 | AS94: =+AR94+AS93 -> 0 | AT94: =+AS94+AT93 -> 2899191.6 | AW94: Totaux cumulés | AX94: =+AX93 -> 10524332 | AY94: =+AX94+AY93 -> 10524332 | AZ94: =+AY94+AZ93 -> 10524332 | BA94: =+AZ94+BA93 -> 10524332 | BD94: Totaux cumulés | BE94: =+BE93 -> 16225387 | BF94: =+BE94+BF93 -> 16225387 | BG94: =+BF94+BG93 -> 16225387 | BH94: =+BG94+BH93 -> 16225387 | BK94: Totaux cumulés | BL94: =+BL93 -> 0 | BM94: =+BL94+BM93 -> 0 | BN94: =+BM94+BN93 -> 34811868 | BO94: =+BN94+BO93 -> 34811868 | BR94: Totaux cumulés | BS94: =+BS93 -> 0 | BT94: =+BS94+BT93 -> 0 | BU94: =+BT94+BU93 -> 6126024.1 | BV94: =+BU94+BV93 -> 6126024.1 | BY94: Totaux cumulés | BZ94: =+BZ93 -> 0 | CA94: =+BZ94+CA93 -> 0 | CB94: =+CA94+CB93 -> 0 | CC94: =+CB94+CC93 -> 6693132.5 | CF94: Totaux cumulés | CG94: =+CG93 -> 990000 | CH94: =+CG94+CH93 -> 1980000 | CI94: =+CH94+CI93 -> 2970000 | CJ94: =+CI94+CJ93 -> 3960000 | CN94: Totaux cumulés | CO94: =+CO93 -> 0 | CP94: =+CO94+CP93 -> 990000 | CQ94: =+CP94+CQ93 -> 990000 | CR94: =+CQ94+CR93 -> 990000
C97: Arachide (Groundnut) 2029 | K97: Niébé (Cowpea) 2029 | T97: Céréale, blé, mais (Wheat, corne, ) 2029 | Y97: Total acheté | AB97: Sesame 2029 | AG97: Total acheté | AI97: Gombo - avec goutte-à-goutte (Okra - with drip) 2029 | AN97: Total acheté | AP97: Sorgho pour graine (Sorghum for Seed) 2027 | AU97: Total acheté | AW97: Oignon - avec goutte-à-goutte (Onion - with drip) 2029 | BB97: Total acheté | BD97: Aubergine - avec goutte-à-goutte et paillage 2029 | BI97: Total acheté | BK97: Tomate - avec goutte-à-goutte et paillage 2029 | BP97: Total acheté | BR97: Pomme de terre en hiver avec irrigation 2029 | BW97: Total acheté | BY97: Luzerne (Alfa Alfa) en irrigation 2029 | CD97: Total acheté | CF97: Verget pour arbre fruitiers 2026 | CK97: Total acheté | CN97: Verget pour arbre fruitiers 2029 | CS97: Total acheté
C98: Matière première | D98: 1er trimestre | E98: 2ème trimestre | F98: 3ème trimestre | G98: 4ème trimestre | H98: Total Acheté | K98: Matière première | L98: 1er trimestre | M98: 2ème trimestre | N98: 3ème trimestre | O98: 4ème trimestre | P98: Total Acheté | T98: Achat de production | U98: 1er trimestre | V98: 2ème trimestre | W98: 3ème trimestre | X98: 4ème trimestre | Y98: Total acheté | AB98: Achat de production | AC98: 1er trimestre | AD98: 2ème trimestre | AE98: 3ème trimestre | AF98: 4ème trimestre | AG98: Total acheté | AI98: Achat de production | AJ98: 1er trimestre | AK98: 2ème trimestre | AL98: 3ème trimestre | AM98: 4ème trimestre | AN98: Total acheté | AP98: Achat de production | AQ98: 1er trimestre | AR98: 2ème trimestre | AS98: 3ème trimestre | AT98: 4ème trimestre | AU98: Total acheté | AW98: Achat de production | AX98: 1er trimestre | AY98: 2ème trimestre | AZ98: 3ème trimestre | BA98: 4ème trimestre | BB98: Total acheté | BD98: Achat de production | BE98: 1er trimestre | BF98: 2ème trimestre | BG98: 3ème trimestre | BH98: 4ème trimestre | BI98: Total acheté | BK98: Achat de production | BL98: 1er trimestre | BM98: 2ème trimestre | BN98: 3ème trimestre | BO98: 4ème trimestre | BP98: Total acheté | BR98: Achat de production | BS98: 1er trimestre | BT98: 2ème trimestre | BU98: 3ème trimestre | BV98: 4ème trimestre | BW98: Total acheté | BY98: Achat de production | BZ98: 1er trimestre | CA98: 2ème trimestre | CB98: 3ème trimestre | CC98: 4ème trimestre | CD98: Total acheté | CF98: Achat de production | CG98: 1er trimestre | CH98: 2ème trimestre | CI98: 3ème trimestre | CJ98: 4ème trimestre | CK98: Total acheté | CN98: Achat de production | CO98: 1er trimestre | CP98: 2ème trimestre | CQ98: 3ème trimestre | CR98: 4ème trimestre | CS98: Total acheté
C99: Superficie cultivée en pluviale | E99: 20 | F99: =(+'[2]Ca...'!E99+'[2]Ca...'!E105+'[2]Ca...'!E111)*1.05 -> 0 | H99: =+SUM(D99:G99) -> 20 | K99: Superficie cultivée en pluviale | M99: 10 | P99: =+SUM(L99:O99) -> 10 | T99: Superficie cultivée en pluviale | V99: 20 | Y99: =+SUM(U99:X99) -> 20 | AB99: Superficie cultivée en pluviale | AD99: 10 | AG99: =+SUM(AC99:AF99) -> 10 | AI99: Superficie cultivée en irriguation | AM99: 5 | AN99: =+SUM(AJ99:AM99) -> 5 | AP99: Superficie cultivée en irriguation | AT99: 10 | AU99: =+SUM(AQ99:AT99) -> 10 | AW99: Superficie cultivée en irriguation | AX99: 10 | BB99: =+SUM(AX99:BA99) -> 10 | BD99: Superficie cultivée en irriguation | BE99: 5 | BI99: =+SUM(BE99:BH99) -> 5 | BK99: Superficie cultivée en irriguation | BN99: 10 | BP99: =+SUM(BL99:BO99) -> 10 | BR99: Superficie cultivée en irriguation | BU99: 5 | BW99: =+SUM(BS99:BV99) -> 5 | BY99: Superficie cultivée en irriguation | CC99: 10 | CD99: =+SUM(BZ99:CC99) -> 10 | CF99: Superficie cultivée en irriguation | CK99: =+SUM(CG99:CJ99) -> 0 | CN99: Superficie cultivée en irriguation | CS99: =+SUM(CO99:CR99) -> 0
C100: Coût unitaire par hectare | D100: =SUM(D77)*1.1 -> 364560.09 | E100: =+D100 -> 364560.09 | F100: =+E100 -> 364560.09 | G100: =+F100 -> 364560.09 | K100: Coût unitaire par hectare | L100: =SUM(L77)*1.1 -> 396529.13 | M100: =+L100 -> 396529.13 | N100: =+M100 -> 396529.13 | O100: =+N100 -> 396529.13 | T100: Coût unitaire par hectare | U100: =SUM(U77) -> 497553.63 | V100: =SUM(V77) -> 497553.63 | W100: =SUM(W77) -> 497553.63 | X100: =SUM(X77) -> 497553.63 | AB100: Coût unitaire par hectare | AC100: =SUM(AC77) -> 168710.63 | AD100: =SUM(AD77) -> 168710.63 | AE100: =SUM(AE77) -> 168710.63 | AF100: =SUM(AF77) -> 168710.63 | AI100: Coût unitaire par hectare | AJ100: =SUM(AJ77) -> 1622902 | AK100: =SUM(AK77) -> 1622902 | AL100: =SUM(AL77) -> 1622902 | AM100: =SUM(AM77) -> 1622902 | AP100: Coût unitaire par hectare | AQ100: =SUM(AQ77) -> 223919.16 | AR100: =SUM(AR77) -> 223919.16 | AS100: =SUM(AS77) -> 223919.16 | AT100: =SUM(AT77) -> 223919.16 | AW100: Coût unitaire par hectare | AX100: =SUM(AX77) -> 986433.24 | AY100: =SUM(AY77) -> 986433.24 | AZ100: =SUM(AZ77) -> 986433.24 | BA100: =SUM(BA77) -> 986433.24 | BD100: Coût unitaire par hectare | BE100: =SUM(BE77) -> 3179077.4 | BF100: =SUM(BF77) -> 3179077.4 | BG100: =SUM(BG77) -> 3179077.4 | BH100: =SUM(BH77) -> 3179077.4 | BK100: Coût unitaire par hectare | BL100: =SUM(BL77) -> 3415186.8 | BM100: =SUM(BM77) -> 3415186.8 | BN100: =SUM(BN77) -> 3415186.8 | BO100: =SUM(BO77) -> 3415186.8 | BR100: Coût unitaire par hectare | BS100: =SUM(BS77) -> 1159204.8 | BT100: =SUM(BT77) -> 1159204.8 | BU100: =SUM(BU77) -> 1159204.8 | BV100: =SUM(BV77) -> 1159204.8 | BY100: Coût unitaire par hectare | BZ100: =SUM(BZ77) -> 603313.24 | CA100: =SUM(CA77) -> 603313.24 | CB100: =SUM(CB77) -> 603313.24 | CC100: =SUM(CC77) -> 603313.24 | CF100: Coût unitaire par hectare | CG100: =SUM(CG77) -> 1375000 | CH100: =SUM(CH77) -> 1375000 | CI100: =SUM(CI77) -> 1375000 | CJ100: =SUM(CJ77) -> 1375000 | CN100: Coût unitaire par hectare | CO100: =SUM(CO77) -> 660000 | CP100: =SUM(CP77) -> 660000 | CQ100: =SUM(CQ77) -> 660000 | CR100: =SUM(CR77) -> 660000
C101: Sous-total | D101: =+D100*D99 -> 0 | E101: =+E100*E99 -> 7291201.7 | F101: =+F100*F99 -> 0 | G101: =+G100*G99 -> 0 | K101: Sous-total | L101: =+L100*L99 -> 0 | M101: =+M100*M99 -> 3965291.3 | N101: =+N100*N99 -> 0 | O101: =+O100*O99 -> 0 | T101: Sous-total | U101: =+U100*U99 -> 0 | V101: =+V100*V99 -> 9951072.5 | W101: =+W100*W99 -> 0 | X101: =+X100*X99 -> 0 | AB101: Sous-total | AC101: =+AC100*AC99 -> 0 | AD101: =+AD100*AD99 -> 1687106.3 | AE101: =+AE100*AE99 -> 0 | AF101: =+AF100*AF99 -> 0 | AI101: Sous-total | AJ101: =+AJ100*AJ99 -> 0 | AK101: =+AK100*AK99 -> 0 | AL101: =+AL100*AL99 -> 0 | AM101: =+AM100*AM99 -> 8114509.9 | AP101: Sous-total | AQ101: =+AQ100*AQ99 -> 0 | AR101: =+AR100*AR99 -> 0 | AS101: =+AS100*AS99 -> 0 | AT101: =+AT100*AT99 -> 2239191.6 | AW101: Sous-total | AX101: =+AX100*AX99 -> 9864332.4 | AY101: =+AY100*AY99 -> 0 | AZ101: =+AZ100*AZ99 -> 0 | BA101: =+BA100*BA99 -> 0 | BD101: Sous-total | BE101: =+BE100*BE99 -> 15895387 | BF101: =+BF100*BF99 -> 0 | BG101: =+BG100*BG99 -> 0 | BH101: =+BH100*BH99 -> 0 | BK101: Sous-total | BL101: =+BL100*BL99 -> 0 | BM101: =+BM100*BM99 -> 0 | BN101: =+BN100*BN99 -> 34151868 | BO101: =+BO100*BO99 -> 0 | BR101: Sous-total | BS101: =+BS100*BS99 -> 0 | BT101: =+BT100*BT99 -> 0 | BU101: =+BU100*BU99 -> 5796024.1 | BV101: =+BV100*BV99 -> 0 | BY101: Sous-total | BZ101: =+BZ100*BZ99 -> 0 | CA101: =+CA100*CA99 -> 0 | CB101: =+CB100*CB99 -> 0 | CC101: =+CC100*CC99 -> 6033132.5 | CF101: Sous-total | CG101: =+CG100*CG99 -> 0 | CH101: =+CH100*CH99 -> 0 | CI101: =+CI100*CI99 -> 0 | CJ101: =+CJ100*CJ99 -> 0 | CN101: Sous-total | CO101: =+CO100*CO99 -> 0 | CP101: =+CP100*CP99 -> 0 | CQ101: =+CQ100*CQ99 -> 0 | CR101: =+CR100*CR99 -> 0
C102: Sous-total cumulé | D102: =+D101 -> 0 | E102: =+D102+E101 -> 7291201.7 | F102: =+E102+F101 -> 7291201.7 | G102: =+F102+G101 -> 7291201.7 | K102: Sous-total cumulé | L102: =+L101 -> 0 | M102: =+L102+M101 -> 3965291.3 | N102: =+M102+N101 -> 3965291.3 | O102: =+N102+O101 -> 3965291.3 | T102: Sous-total cumulé | U102: =+U101 -> 0 | V102: =+U102+V101 -> 9951072.5 | W102: =+V102+W101 -> 9951072.5 | X102: =+W102+X101 -> 9951072.5 | AB102: Sous-total cumulé | AC102: =+AC101 -> 0 | AD102: =+AC102+AD101 -> 1687106.3 | AE102: =+AD102+AE101 -> 1687106.3 | AF102: =+AE102+AF101 -> 1687106.3 | AI102: Sous-total cumulé | AJ102: =+AJ101 -> 0 | AK102: =+AJ102+AK101 -> 0 | AL102: =+AK102+AL101 -> 0 | AM102: =+AL102+AM101 -> 8114509.9 | AP102: Sous-total cumulé | AQ102: =+AQ101 -> 0 | AR102: =+AQ102+AR101 -> 0 | AS102: =+AR102+AS101 -> 0 | AT102: =+AS102+AT101 -> 2239191.6 | AW102: Sous-total cumulé | AX102: =+AX101 -> 9864332.4 | AY102: =+AX102+AY101 -> 9864332.4 | AZ102: =+AY102+AZ101 -> 9864332.4 | BA102: =+AZ102+BA101 -> 9864332.4 | BD102: Sous-total cumulé | BE102: =+BE101 -> 15895387 | BF102: =+BE102+BF101 -> 15895387 | BG102: =+BF102+BG101 -> 15895387 | BH102: =+BG102+BH101 -> 15895387 | BK102: Sous-total cumulé | BL102: =+BL101 -> 0 | BM102: =+BL102+BM101 -> 0 | BN102: =+BM102+BN101 -> 34151868 | BO102: =+BN102+BO101 -> 34151868 | BR102: Sous-total cumulé | BS102: =+BS101 -> 0 | BT102: =+BS102+BT101 -> 0 | BU102: =+BT102+BU101 -> 5796024.1 | BV102: =+BU102+BV101 -> 5796024.1 | BY102: Sous-total cumulé | BZ102: =+BZ101 -> 0 | CA102: =+BZ102+CA101 -> 0 | CB102: =+CA102+CB101 -> 0 | CC102: =+CB102+CC101 -> 6033132.5 | CF102: Sous-total cumulé | CG102: =+CG101 -> 0 | CH102: =+CG102+CH101 -> 0 | CI102: =+CH102+CI101 -> 0 | CJ102: =+CI102+CJ101 -> 0 | CN102: Sous-total cumulé | CO102: =+CO101 -> 0 | CP102: =+CO102+CP101 -> 0 | CQ102: =+CP102+CQ101 -> 0 | CR102: =+CQ102+CR101 -> 0
C104: Ensachage et autres fournitures | K104: Ensachage et autres fournitures | T104: Transports mis en Fob et SGS (coût /tonne) | AB104: Transports mis en Fob et SGS (coût /tonne) | AI104: Transports mis en Fob et SGS (coût /tonne) | AP104: Transports mis en Fob et SGS (coût /tonne) | AW104: Transports mis en Fob et SGS (coût /tonne) | BD104: Transports mis en Fob et SGS (coût /tonne) | BK104: Transports mis en Fob et SGS (coût /tonne) | BR104: Transports mis en Fob et SGS (coût /tonne) | BY104: Transports mis en Fob et SGS (coût /tonne) | CF104: charge d'arosage et autres frais d'entretien | CN104: charge d'arosage et autres frais d'entretien
C105: Production brute (tonne) | D105: =+D99 -> 0 | E105: =+E99 -> 20 | F105: =+F99 -> 0 | G105: =+G99 -> 0 | K105: Production brute (tonne) | L105: =+L99 -> 0 | M105: =+M99 -> 10 | N105: =+N99 -> 0 | O105: =+O99 -> 0 | T105: Production brute | U105: =+U99 -> 0 | V105: =+V99 -> 20 | W105: =+W99 -> 0 | X105: =+X99 -> 0 | AB105: Production brute | AC105: =+AC99 -> 0 | AD105: =+AD99 -> 10 | AE105: =+AE99 -> 0 | AF105: =+AF99 -> 0 | AI105: Production brute | AJ105: =+AJ99 -> 0 | AK105: =+AK99 -> 0 | AL105: =+AL99 -> 0 | AM105: =+AM99 -> 5 | AP105: Production brute | AQ105: =+AQ99 -> 0 | AR105: =+AR99 -> 0 | AS105: =+AS99 -> 0 | AT105: =+AT99 -> 10 | AW105: Production brute | AX105: =+AX99 -> 10 | AY105: =+AY99 -> 0 | AZ105: =+AZ99 -> 0 | BA105: =+BA99 -> 0 | BD105: Production brute | BE105: =+BE99 -> 5 | BF105: =+BF99 -> 0 | BG105: =+BG99 -> 0 | BH105: =+BH99 -> 0 | BK105: Production brute | BL105: =+BL99 -> 0 | BM105: =+BM99 -> 0 | BN105: =+BN99 -> 10 | BO105: =+BO99 -> 0 | BR105: Production brute | BS105: =+BS99 -> 0 | BT105: =+BT99 -> 0 | BU105: =+BU99 -> 5 | BV105: =+BV99 -> 0 | BY105: Production brute | BZ105: =+BZ99 -> 0 | CA105: =+CA99 -> 0 | CB105: =+CB99 -> 0 | CC105: =+CC99 -> 10 | CF105: Production brute | CG105: 5 | CH105: 5 | CI105: 5 | CJ105: 5 | CN105: Production brute
C106: Coût Unitaire | D106: =+D83*1.1 -> 42350 | E106: =+D106 -> 42350 | F106: =+E106 -> 42350 | G106: =+F106 -> 42350 | K106: Coût Unitaire | L106: =+L83*1.1 -> 42350 | M106: =+L106 -> 42350 | N106: =+M106 -> 42350 | O106: =+N106 -> 42350 | T106: Coût Unitaire | U106: =+X83*1.1 -> 42350 | V106: =+U106 -> 42350 | W106: =+V106 -> 42350 | X106: =+W106 -> 42350 | AB106: Coût Unitaire | AC106: =+AF83*1.1 -> 42350 | AD106: =+AC106 -> 42350 | AE106: =+AD106 -> 42350 | AF106: =+AE106 -> 42350 | AI106: Coût Unitaire | AJ106: =+AM83*1.1 -> 42350 | AK106: =+AJ106 -> 42350 | AL106: =+AK106 -> 42350 | AM106: =+AL106 -> 42350 | AP106: Coût Unitaire | AQ106: =+AT83*1.1 -> 42350 | AR106: =+AQ106 -> 42350 | AS106: =+AR106 -> 42350 | AT106: =+AS106 -> 42350 | AW106: Coût Unitaire | AX106: =+BA83*1.1 -> 42350 | AY106: =+AX106 -> 42350 | AZ106: =+AY106 -> 42350 | BA106: =+AZ106 -> 42350 | BD106: Coût Unitaire | BE106: =+BH83*1.1 -> 42350 | BF106: =+BE106 -> 42350 | BG106: =+BF106 -> 42350 | BH106: =+BG106 -> 42350 | BK106: Coût Unitaire | BL106: =+BO83*1.1 -> 42350 | BM106: =+BL106 -> 42350 | BN106: =+BM106 -> 42350 | BO106: =+BN106 -> 42350 | BR106: Coût Unitaire | BS106: =+BV83*1.1 -> 42350 | BT106: =+BS106 -> 42350 | BU106: =+BT106 -> 42350 | BV106: =+BU106 -> 42350 | BY106: Coût Unitaire | BZ106: =+CC83*1.1 -> 42350 | CA106: =+BZ106 -> 42350 | CB106: =+CA106 -> 42350 | CC106: =+CB106 -> 42350 | CF106: Coût Unitaire | CG106: =+CJ83*1.1 -> 217800 | CH106: =+CG106 -> 217800 | CI106: =+CH106 -> 217800 | CJ106: =+CI106 -> 217800 | CN106: Coût Unitaire | CO106: =+CR83*1.1 -> 217800 | CP106: =+CO106 -> 217800 | CQ106: =+CP106 -> 217800 | CR106: =+CQ106 -> 217800
C107: Sous-total | D107: =+D106*D105 -> 0 | E107: =+E106*E105 -> 847000 | F107: =+F106*F105 -> 0 | G107: =+G106*G105 -> 0 | K107: Sous-total | L107: =+L106*L105 -> 0 | M107: =+M106*M105 -> 423500 | N107: =+N106*N105 -> 0 | O107: =+O106*O105 -> 0 | T107: Sous-total | U107: =+U106*U105 -> 0 | V107: =+V106*V105 -> 847000 | W107: =+W106*W105 -> 0 | X107: =+X106*X105 -> 0 | AB107: Sous-total | AC107: =+AC106*AC105 -> 0 | AD107: =+AD106*AD105 -> 423500 | AE107: =+AE106*AE105 -> 0 | AF107: =+AF106*AF105 -> 0 | AI107: Sous-total | AJ107: =+AJ106*AJ105 -> 0 | AK107: =+AK106*AK105 -> 0 | AL107: =+AL106*AL105 -> 0 | AM107: =+AM106*AM105 -> 211750 | AP107: Sous-total | AQ107: =+AQ106*AQ105 -> 0 | AR107: =+AR106*AR105 -> 0 | AS107: =+AS106*AS105 -> 0 | AT107: =+AT106*AT105 -> 423500 | AW107: Sous-total | AX107: =+AX106*AX105 -> 423500 | AY107: =+AY106*AY105 -> 0 | AZ107: =+AZ106*AZ105 -> 0 | BA107: =+BA106*BA105 -> 0 | BD107: Sous-total | BE107: =+BE106*BE105 -> 211750 | BF107: =+BF106*BF105 -> 0 | BG107: =+BG106*BG105 -> 0 | BH107: =+BH106*BH105 -> 0 | BK107: Sous-total | BL107: =+BL106*BL105 -> 0 | BM107: =+BM106*BM105 -> 0 | BN107: =+BN106*BN105 -> 423500 | BO107: =+BO106*BO105 -> 0 | BR107: Sous-total | BS107: =+BS106*BS105 -> 0 | BT107: =+BT106*BT105 -> 0 | BU107: =+BU106*BU105 -> 211750 | BV107: =+BV106*BV105 -> 0 | BY107: Sous-total | BZ107: =+BZ106*BZ105 -> 0 | CA107: =+CA106*CA105 -> 0 | CB107: =+CB106*CB105 -> 0 | CC107: =+CC106*CC105 -> 423500 | CF107: Sous-total | CG107: =+CG106*CG105 -> 1089000 | CH107: =+CH106*CH105 -> 1089000 | CI107: =+CI106*CI105 -> 1089000 | CJ107: =+CJ106*CJ105 -> 1089000 | CN107: Sous-total | CO107: =+CO106*CO105 -> 0 | CP107: =+CP106*CP105 -> 0 | CQ107: =+CQ106*CQ105 -> 0 | CR107: =+CR106*CR105 -> 0
C108: Sous-total cumulé | D108: =+D107 -> 0 | E108: =+D108+E107 -> 847000 | F108: =+E108+F107 -> 847000 | G108: =+F108+G107 -> 847000 | K108: Sous-total cumulé | L108: =+L107 -> 0 | M108: =+L108+M107 -> 423500 | N108: =+M108+N107 -> 423500 | O108: =+N108+O107 -> 423500 | T108: Sous-total cumulé | U108: =+U107 -> 0 | V108: =+U108+V107 -> 847000 | W108: =+V108+W107 -> 847000 | X108: =+W108+X107 -> 847000 | AB108: Sous-total cumulé | AC108: =+AC107 -> 0 | AD108: =+AC108+AD107 -> 423500 | AE108: =+AD108+AE107 -> 423500 | AF108: =+AE108+AF107 -> 423500 | AI108: Sous-total cumulé | AJ108: =+AJ107 -> 0 | AK108: =+AJ108+AK107 -> 0 | AL108: =+AK108+AL107 -> 0 | AM108: =+AL108+AM107 -> 211750 | AP108: Sous-total cumulé | AQ108: =+AQ107 -> 0 | AR108: =+AQ108+AR107 -> 0 | AS108: =+AR108+AS107 -> 0 | AT108: =+AS108+AT107 -> 423500 | AW108: Sous-total cumulé | AX108: =+AX107 -> 423500 | AY108: =+AX108+AY107 -> 423500 | AZ108: =+AY108+AZ107 -> 423500 | BA108: =+AZ108+BA107 -> 423500 | BD108: Sous-total cumulé | BE108: =+BE107 -> 211750 | BF108: =+BE108+BF107 -> 211750 | BG108: =+BF108+BG107 -> 211750 | BH108: =+BG108+BH107 -> 211750 | BK108: Sous-total cumulé | BL108: =+BL107 -> 0 | BM108: =+BL108+BM107 -> 0 | BN108: =+BM108+BN107 -> 423500 | BO108: =+BN108+BO107 -> 423500 | BR108: Sous-total cumulé | BS108: =+BS107 -> 0 | BT108: =+BS108+BT107 -> 0 | BU108: =+BT108+BU107 -> 211750 | BV108: =+BU108+BV107 -> 211750 | BY108: Sous-total cumulé | BZ108: =+BZ107 -> 0 | CA108: =+BZ108+CA107 -> 0 | CB108: =+CA108+CB107 -> 0 | CC108: =+CB108+CC107 -> 423500 | CF108: Sous-total cumulé | CG108: =+CG107 -> 1089000 | CH108: =+CG108+CH107 -> 2178000 | CI108: =+CH108+CI107 -> 3267000 | CJ108: =+CI108+CJ107 -> 4356000 | CN108: Sous-total cumulé | CO108: =+CO107 -> 0 | CP108: =+CO108+CP107 -> 0 | CQ108: =+CP108+CQ107 -> 0 | CR108: =+CQ108+CR107 -> 0
C110: Transports, manutention, stock des intrants (coût /hectare) | D110: =SUM(D87)*1.1 -> 30250 | E110: =+D110 -> 30250 | F110: =+E110 -> 30250 | G110: =+F110 -> 30250 | K110: Transports, manutention, stock des intrants (coût /hectare) | L110: =SUM(L87)*1.1 -> 30250 | M110: =+L110 -> 30250 | N110: =+M110 -> 30250 | O110: =+N110 -> 30250 | T110: Transports, manutention, stock des intrants (coût /hectare) | U110: =+D110 -> 30250 | V110: =+U110 -> 30250 | W110: =+V110 -> 30250 | X110: =+W110 -> 30250 | AB110: Transports, manutention, stock des intrants (coût /hectare) | AC110: =+L110 -> 30250 | AD110: =+AC110 -> 30250 | AE110: =+AD110 -> 30250 | AF110: =+AE110 -> 30250 | AI110: Transports, manutention, stock des intrants (coût /hectare) | AJ110: =SUM(AJ87)*1.1 -> 30250 | AK110: =+AJ110 -> 30250 | AL110: =+AK110 -> 30250 | AM110: =+AL110 -> 30250 | AP110: Transports, manutention, stock des intrants (coût /hectare) | AQ110: =SUM(AQ87)*1.1 -> 30250 | AR110: =+AQ110 -> 30250 | AS110: =+AR110 -> 30250 | AT110: =+AS110 -> 30250 | AW110: Transports, manutention, stock des intrants (coût /hectare) | AX110: =SUM(AX87)*1.1 -> 30250 | AY110: =+AX110 -> 30250 | AZ110: =+AY110 -> 30250 | BA110: =+AZ110 -> 30250 | BD110: Transports, manutention, stock des intrants (coût /hectare) | BE110: =SUM(BE87)*1.1 -> 30250 | BF110: =+BE110 -> 30250 | BG110: =+BF110 -> 30250 | BH110: =+BG110 -> 30250 | BK110: Transports, manutention, stock des intrants (coût /hectare) | BL110: =SUM(BL87)*1.1 -> 30250 | BM110: =+BL110 -> 30250 | BN110: =+BM110 -> 30250 | BO110: =+BN110 -> 30250 | BR110: Transports, manutention, stock des intrants (coût /hectare) | BS110: =SUM(BS87)*1.1 -> 30250 | BT110: =+BS110 -> 30250 | BU110: =+BT110 -> 30250 | BV110: =+BU110 -> 30250 | BY110: Transports, manutention, stock des intrants (coût /hectare) | BZ110: =SUM(BZ87)*1.1 -> 30250 | CA110: =+BZ110 -> 30250 | CB110: =+CA110 -> 30250 | CC110: =+CB110 -> 30250 | CF110: Transports, manutention, stock des intrants (coût /hectare) | CG110: =SUM(CG87)*1.1 -> 30250 | CH110: =+CG110 -> 30250 | CI110: =+CH110 -> 30250 | CJ110: =+CI110 -> 30250 | CN110: Transports, manutention, stock des intrants (coût /hectare) | CO110: =SUM(CO87)*1.1 -> 30250 | CP110: =+CO110 -> 30250 | CQ110: =+CP110 -> 30250 | CR110: =+CQ110 -> 30250
C111: Montant total (sur base total achat) | D111: =+D99*D110 -> 0 | E111: =+E99*E110 -> 605000 | F111: =+F99*F110 -> 0 | G111: =+G99*G110 -> 0 | K111: Montant total (sur base total achat) | L111: =+L99*L110 -> 0 | M111: =+M99*M110 -> 302500 | N111: =+N99*N110 -> 0 | O111: =+O99*O110 -> 0 | T111: Montant total (sur base total achat) | U111: =+U99*U110 -> 0 | V111: =+V99*V110 -> 605000 | W111: =+W99*W110 -> 0 | X111: =+X99*X110 -> 0 | AB111: Montant total (sur base total achat) | AC111: =+AC99*AC110 -> 0 | AD111: =+AD99*AD110 -> 302500 | AE111: =+AE99*AE110 -> 0 | AF111: =+AF99*AF110 -> 0 | AI111: Montant total (sur base total achat) | AJ111: =+AJ99*AJ110 -> 0 | AK111: =+AK99*AK110 -> 0 | AL111: =+AL99*AL110 -> 0 | AM111: =+AM99*AM110 -> 151250 | AP111: Montant total (sur base total achat) | AQ111: =+AQ99*AQ110 -> 0 | AR111: =+AR99*AR110 -> 0 | AS111: =+AS99*AS110 -> 0 | AT111: =+AT99*AT110 -> 302500 | AW111: Montant total (sur base total achat) | AX111: =+AX99*AX110 -> 302500 | AY111: =+AY99*AY110 -> 0 | AZ111: =+AZ99*AZ110 -> 0 | BA111: =+BA99*BA110 -> 0 | BD111: Montant total (sur base total achat) | BE111: =+BE99*BE110 -> 151250 | BF111: =+BF99*BF110 -> 0 | BG111: =+BG99*BG110 -> 0 | BH111: =+BH99*BH110 -> 0 | BK111: Montant total (sur base total achat) | BL111: =+BL99*BL110 -> 0 | BM111: =+BM99*BM110 -> 0 | BN111: =+BN99*BN110 -> 302500 | BO111: =+BO99*BO110 -> 0 | BR111: Montant total (sur base total achat) | BS111: =+BS99*BS110 -> 0 | BT111: =+BT99*BT110 -> 0 | BU111: =+BU99*BU110 -> 151250 | BV111: =+BV99*BV110 -> 0 | BY111: Montant total (sur base total achat) | BZ111: =+BZ99*BZ110 -> 0 | CA111: =+CA99*CA110 -> 0 | CB111: =+CB99*CB110 -> 0 | CC111: =+CC99*CC110 -> 302500 | CF111: Montant total (sur base total achat) | CG111: =+CG99*CG110 -> 0 | CH111: =+CH99*CH110 -> 0 | CI111: =+CI99*CI110 -> 0 | CJ111: =+CJ99*CJ110 -> 0 | CN111: Montant total (f) | CP111: =+CP99*CP110 -> 0 | CQ111: =+CQ99*CQ110 -> 0 | CR111: 600000
C112: Sous-total cumulé | D112: =+D111 -> 0 | E112: =+D112+E111 -> 605000 | F112: =+E112+F111 -> 605000 | G112: =+F112+G111 -> 605000 | K112: Sous-total cumulé | L112: =+L111 -> 0 | M112: =+L112+M111 -> 302500 | N112: =+M112+N111 -> 302500 | O112: =+N112+O111 -> 302500 | T112: Sous-total cumulé | U112: =+U111 -> 0 | V112: =+U112+V111 -> 605000 | W112: =+V112+W111 -> 605000 | X112: =+W112+X111 -> 605000 | AB112: Sous-total cumulé | AC112: =+AC111 -> 0 | AD112: =+AC112+AD111 -> 302500 | AE112: =+AD112+AE111 -> 302500 | AF112: =+AE112+AF111 -> 302500 | AI112: Sous-total cumulé | AJ112: =+AJ111 -> 0 | AK112: =+AJ112+AK111 -> 0 | AL112: =+AK112+AL111 -> 0 | AM112: =+AL112+AM111 -> 151250 | AP112: Sous-total cumulé | AQ112: =+AQ111 -> 0 | AR112: =+AQ112+AR111 -> 0 | AS112: =+AR112+AS111 -> 0 | AT112: =+AS112+AT111 -> 302500 | AW112: Sous-total cumulé | AX112: =+AX111 -> 302500 | AY112: =+AX112+AY111 -> 302500 | AZ112: =+AY112+AZ111 -> 302500 | BA112: =+AZ112+BA111 -> 302500 | BD112: Sous-total cumulé | BE112: =+BE111 -> 151250 | BF112: =+BE112+BF111 -> 151250 | BG112: =+BF112+BG111 -> 151250 | BH112: =+BG112+BH111 -> 151250 | BK112: Sous-total cumulé | BL112: =+BL111 -> 0 | BM112: =+BL112+BM111 -> 0 | BN112: =+BM112+BN111 -> 302500 | BO112: =+BN112+BO111 -> 302500 | BR112: Sous-total cumulé | BS112: =+BS111 -> 0 | BT112: =+BS112+BT111 -> 0 | BU112: =+BT112+BU111 -> 151250 | BV112: =+BU112+BV111 -> 151250 | BY112: Sous-total cumulé | BZ112: =+BZ111 -> 0 | CA112: =+BZ112+CA111 -> 0 | CB112: =+CA112+CB111 -> 0 | CC112: =+CB112+CC111 -> 302500 | CF112: Sous-total cumulé | CG112: =+CG111 -> 0 | CH112: =+CG112+CH111 -> 0 | CI112: =+CH112+CI111 -> 0 | CJ112: =+CI112+CJ111 -> 0 | CN112: Sous-total cumulé | CO112: =+CO111 -> 0 | CP112: =+CO112+CP111 -> 0 | CQ112: =+CP112+CQ111 -> 0 | CR112: =+CQ112+CR111 -> 600000
H114: Px Rv / hectare | P114: Px Rv / hectare | Y114: Px Rv / hectare | AG114: Px Rv / hectare | AN114: Px Rv / hectare | AU114: Px Rv / hectare | BB114: Px Rv / hectare | BI114: Px Rv / hectare | BP114: Px Rv / hectare | BW114: Px Rv / hectare | CD114: Px Rv / hectare | CK114: Px Rv / hectare | CS114: Px Rv / hectare
H115: =SUM(G117)/H99 -> 437160.09 | P115: =SUM(O117)/P99 -> 469129.13 | Y115: =SUM(X117)/Y99 -> 570153.63 | AG115: =SUM(AF117)/AG99 -> 241310.63 | AN115: =SUM(AM117)/AN99 -> 1695502 | AU115: =SUM(AT117)/AU99 -> 296519.16 | BB115: =SUM(BA117)/BB99 -> 1059033.2 | BI115: =SUM(BH117)/BI99 -> 3251677.4 | BP115: =SUM(BO117)/BP99 -> 3487786.8 | BW115: =SUM(BV117)/BW99 -> 1231804.8 | CD115: =SUM(CC117)/CD99 -> 675913.24 | CK115: =SUM(CJ117)/CJ105 -> 871200 | CS115: =SUM(CR117)/CR105 -> #DIV/0!
C116: Totaux | D116: =+D101+D107+D111 -> 0 | E116: =+E101+E107+E111 -> 8743201.7 | F116: =+F101+F107+F111 -> 0 | G116: =+G101+G107+G111 -> 0 | H116: =SUM(H99:H112) -> 20 | K116: Totaux | L116: =+L101+L107+L111 -> 0 | M116: =+M101+M107+M111 -> 4691291.3 | N116: =+N101+N107+N111 -> 0 | O116: =+O101+O107+O111 -> 0 | P116: =SUM(P99:P112) -> 10 | T116: Totaux | U116: =+U101+U107+U111 -> 0 | V116: =+V101+V107+V111 -> 11403073 | W116: =+W101+W107+W111 -> 0 | X116: =+X101+X107+X111 -> 0 | Y116: =SUM(Y99:Y112) -> 20 | AB116: Totaux | AC116: =+AC101+AC107+AC111 -> 0 | AD116: =+AD101+AD107+AD111 -> 2413106.3 | AE116: =+AE101+AE107+AE111 -> 0 | AF116: =+AF101+AF107+AF111 -> 0 | AG116: =SUM(AG99:AG112) -> 10 | AI116: Totaux | AJ116: =+AJ101+AJ107+AJ111 -> 0 | AK116: =+AK101+AK107+AK111 -> 0 | AL116: =+AL101+AL107+AL111 -> 0 | AM116: =+AM101+AM107+AM111 -> 8477509.9 | AN116: =SUM(AN99:AN112) -> 5 | AP116: Totaux | AQ116: =+AQ101+AQ107+AQ111 -> 0 | AR116: =+AR101+AR107+AR111 -> 0 | AS116: =+AS101+AS107+AS111 -> 0 | AT116: =+AT101+AT107+AT111 -> 2965191.6 | AU116: =SUM(AU99:AU112) -> 10 | AW116: Totaux | AX116: =+AX101+AX107+AX111 -> 10590332 | AY116: =+AY101+AY107+AY111 -> 0 | AZ116: =+AZ101+AZ107+AZ111 -> 0 | BA116: =+BA101+BA107+BA111 -> 0 | BB116: =SUM(BB99:BB112) -> 10 | BD116: Totaux | BE116: =+BE101+BE107+BE111 -> 16258387 | BF116: =+BF101+BF107+BF111 -> 0 | BG116: =+BG101+BG107+BG111 -> 0 | BH116: =+BH101+BH107+BH111 -> 0 | BI116: =SUM(BI99:BI112) -> 5 | BK116: Totaux | BL116: =+BL101+BL107+BL111 -> 0 | BM116: =+BM101+BM107+BM111 -> 0 | BN116: =+BN101+BN107+BN111 -> 34877868 | BO116: =+BO101+BO107+BO111 -> 0 | BP116: =SUM(BP99:BP112) -> 10 | BR116: Totaux | BS116: =+BS101+BS107+BS111 -> 0 | BT116: =+BT101+BT107+BT111 -> 0 | BU116: =+BU101+BU107+BU111 -> 6159024.1 | BV116: =+BV101+BV107+BV111 -> 0 | BW116: =SUM(BW99:BW112) -> 5 | BY116: Totaux | BZ116: =+BZ101+BZ107+BZ111 -> 0 | CA116: =+CA101+CA107+CA111 -> 0 | CB116: =+CB101+CB107+CB111 -> 0 | CC116: =+CC101+CC107+CC111 -> 6759132.5 | CD116: =SUM(CD99:CD112) -> 10 | CF116: Totaux | CG116: =+CG101+CG107+CG111 -> 1089000 | CH116: =+CH101+CH107+CH111 -> 1089000 | CI116: =+CI101+CI107+CI111 -> 1089000 | CJ116: =+CJ101+CJ107+CJ111 -> 1089000 | CK116: =SUM(CK99:CK112) -> 0 | CN116: Totaux | CO116: =+CO101+CO107+CO111 -> 0 | CP116: =+CP101+CP107+CP111 -> 0 | CQ116: =+CQ101+CQ107+CQ111 -> 0 | CR116: =+CR101+CR107+CR111 -> 600000 | CS116: =SUM(CS99:CS112) -> 0
C117: Totaux cumulés | D117: =+D116 -> 0 | E117: =+D117+E116 -> 8743201.7 | F117: =+E117+F116 -> 8743201.7 | G117: =+F117+G116 -> 8743201.7 | K117: Totaux cumulés | L117: =+L116 -> 0 | M117: =+L117+M116 -> 4691291.3 | N117: =+M117+N116 -> 4691291.3 | O117: =+N117+O116 -> 4691291.3 | T117: Totaux cumulés | U117: =+U116 -> 0 | V117: =+U117+V116 -> 11403073 | W117: =+V117+W116 -> 11403073 | X117: =+W117+X116 -> 11403073 | AB117: Totaux cumulés | AC117: =+AC116 -> 0 | AD117: =+AC117+AD116 -> 2413106.3 | AE117: =+AD117+AE116 -> 2413106.3 | AF117: =+AE117+AF116 -> 2413106.3 | AI117: Totaux cumulés | AJ117: =+AJ116 -> 0 | AK117: =+AJ117+AK116 -> 0 | AL117: =+AK117+AL116 -> 0 | AM117: =+AL117+AM116 -> 8477509.9 | AP117: Totaux cumulés | AQ117: =+AQ116 -> 0 | AR117: =+AQ117+AR116 -> 0 | AS117: =+AR117+AS116 -> 0 | AT117: =+AS117+AT116 -> 2965191.6 | AW117: Totaux cumulés | AX117: =+AX116 -> 10590332 | AY117: =+AX117+AY116 -> 10590332 | AZ117: =+AY117+AZ116 -> 10590332 | BA117: =+AZ117+BA116 -> 10590332 | BD117: Totaux cumulés | BE117: =+BE116 -> 16258387 | BF117: =+BE117+BF116 -> 16258387 | BG117: =+BF117+BG116 -> 16258387 | BH117: =+BG117+BH116 -> 16258387 | BK117: Totaux cumulés | BL117: =+BL116 -> 0 | BM117: =+BL117+BM116 -> 0 | BN117: =+BM117+BN116 -> 34877868 | BO117: =+BN117+BO116 -> 34877868 | BR117: Totaux cumulés | BS117: =+BS116 -> 0 | BT117: =+BS117+BT116 -> 0 | BU117: =+BT117+BU116 -> 6159024.1 | BV117: =+BU117+BV116 -> 6159024.1 | BY117: Totaux cumulés | BZ117: =+BZ116 -> 0 | CA117: =+BZ117+CA116 -> 0 | CB117: =+CA117+CB116 -> 0 | CC117: =+CB117+CC116 -> 6759132.5 | CF117: Totaux cumulés | CG117: =+CG116 -> 1089000 | CH117: =+CG117+CH116 -> 2178000 | CI117: =+CH117+CI116 -> 3267000 | CJ117: =+CI117+CJ116 -> 4356000 | CN117: Totaux cumulés | CO117: =+CO116 -> 0 | CP117: =+CO117+CP116 -> 0 | CQ117: =+CP117+CQ116 -> 0 | CR117: =+CQ117+CR116 -> 600000
C121: Arachide (Groundnut) 2030 | K121: Niébé (Cowpea) 2030 | T121: Céréale, blé, mais (Wheat, corne, ) 2030 | Y121: Total acheté | AB121: Sesame 2030 | AG121: Total acheté | AI121: Gombo - avec goutte-à-goutte (Okra - with drip) 2030 | AN121: Total acheté | AP121: Sorgho pour graine (Sorghum for Seed) 2030 | AU121: Total acheté | AW121: Oignon - avec goutte-à-goutte (Onion - with drip) 2030 | BB121: Total acheté | BD121: Aubergine - avec goutte-à-goutte et paillage 2030 | BI121: Total acheté | BK121: Tomate - avec goutte-à-goutte et paillage 2030 | BP121: Total acheté | BR121: Pomme de terre en hiver avec irrigation 2030 | BW121: Total acheté | BY121: Luzerne (Alfa Alfa) en irrigation 2030 | CD121: Total acheté | CF121: Verget pour arbre fruitiers 2026 | CK121: Total acheté | CN121: Verget pour arbre fruitiers 2030 | CS121: Total acheté
C122: Matière première | D122: 1er trimestre | E122: 2ème trimestre | F122: 3ème trimestre | G122: 4ème trimestre | H122: Total Acheté | K122: Matière première | L122: 1er trimestre | M122: 2ème trimestre | N122: 3ème trimestre | O122: 4ème trimestre | P122: Total Acheté | T122: Achat de production | U122: 1er trimestre | V122: 2ème trimestre | W122: 3ème trimestre | X122: 4ème trimestre | Y122: Total acheté | AB122: Achat de production | AC122: 1er trimestre | AD122: 2ème trimestre | AE122: 3ème trimestre | AF122: 4ème trimestre | AI122: Achat de production | AJ122: 1er trimestre | AK122: 2ème trimestre | AL122: 3ème trimestre | AM122: 4ème trimestre | AP122: Achat de production | AQ122: 1er trimestre | AR122: 2ème trimestre | AS122: 3ème trimestre | AT122: 4ème trimestre | AW122: Achat de production | AX122: 1er trimestre | AY122: 2ème trimestre | AZ122: 3ème trimestre | BA122: 4ème trimestre | BD122: Achat de production | BE122: 1er trimestre | BF122: 2ème trimestre | BG122: 3ème trimestre | BH122: 4ème trimestre | BK122: Achat de production | BL122: 1er trimestre | BM122: 2ème trimestre | BN122: 3ème trimestre | BO122: 4ème trimestre | BR122: Achat de production | BS122: 1er trimestre | BT122: 2ème trimestre | BU122: 3ème trimestre | BV122: 4ème trimestre | BY122: Achat de production | BZ122: 1er trimestre | CA122: 2ème trimestre | CB122: 3ème trimestre | CC122: 4ème trimestre | CF122: Achat de production | CG122: 1er trimestre | CH122: 2ème trimestre | CI122: 3ème trimestre | CJ122: 4ème trimestre | CN122: Achat de production | CO122: 1er trimestre | CP122: 2ème trimestre | CQ122: 3ème trimestre | CR122: 4ème trimestre
