Workbook
Name EuroDollarRatio: #REF!
Name LempiraDollarFx: [1]Assumptions!$D$32
Name QuanzaDollarFx: #REF!
Name QuanzaFx: #REF!
Name Scenarios: #REF!
Name Tax: [1]Assumptions!$D$33
Name taxholiday: #REF!
Name Update: "1.8.18"
Name wacc: #REF!

Sheet Cover
C3: Cattle Integration, Baghara, Chad
C5: Financial Model
C9: Submitted to
C10: Mr. Amir Artine
C12: Last Update
C13: =TODAY() -> 45763
C26: Disclaimer:
C27: Except for statements of historical fact, information contained herein constitutes forward-looking statements. Such forward-looking statements necessarily involve known and unknown risks and uncertainties, which may cause actual performance and financial results in future periods to differ materially from any projections of future performance or result expressed or implied by such forward-looking statements.
C28: All rights reserved. No part of this financial model may be reproduced, distributed, or transmitted in any form or by any means, without the prior written permission of the publisher.

Sheet Data Input
B1: Company/Project: | C1: =Cover!$C$10 -> Mr. Amir Artine | D1: =Cover!$C$3 -> Cattle Integration, Baghara, Chad | G1: Last Update: | H1: =Cover!$C$13 -> 45763
B3: Operation - Annual Distribution (Before Inflation) | C3: 2018 | D3: 2019 | E3: 2020 | F3: 2021 | G3: 2022 | H3: 2023 | I3: 2024 | J3: 2025 | K3: 2026 | L3: 2027 | M3: 2028 | N3: 2029 | O3: 2030 | P3: 2031 | Q3: 2032 | R3: 2033 | S3: 2034 | T3: 2035 | U3: 2036 | V3: 2037
C4: 0 | D4: 1 | E4: 2 | F4: 3 | G4: 4 | H4: 5 | I4: 6 | J4: 7 | K4: 8 | L4: 9 | M4: 10 | N4: 11 | O4: 12 | P4: 13 | Q4: 14 | R4: 15 | S4: 16 | T4: 17 | U4: 18 | V4: 19
B5: Total Revenues | D5: =Revenues!C23 -> 9047287.3 | E5: =Revenues!D23 -> 16863223 | F5: =Revenues!E23 -> 19790786 | G5: =Revenues!F23 -> 22734686 | H5: =Revenues!G23 -> 27021648 | I5: =Revenues!H23 -> 31835737 | J5: =Revenues!I23 -> 34497379 | K5: =Revenues!J23 -> 35816607 | ... O5: =Revenues!N23 -> 37105101 | P5: =O5 -> 37105101 | Q5: =P5 -> 37105101 | R5: =Q5 -> 37105101 | S5: =R5 -> 37105101 | T5: =S5 -> 37105101 | U5: =T5 -> 37105101 | V5: =U5 -> 37105101
B6: Total Cost of Goods Sold (COGS) | D6: =OPEX!H110 -> 6987857.2 | E6: =OPEX!I110 -> 11350188 | F6: =OPEX!J110 -> 12096703 | G6: =OPEX!K110 -> 12620686 | H6: =OPEX!L110 -> 13489559 | I6: =OPEX!M110 -> 14246266 | J6: =OPEX!N110 -> 14487410 | K6: =OPEX!O110 -> 14616737 | ... O6: =OPEX!S110 -> 14702408 | P6: =O6 -> 14702408 | Q6: =P6 -> 14702408 | R6: =Q6 -> 14702408 | S6: =R6 -> 14702408 | T6: =S6 -> 14702408 | U6: =T6 -> 14702408 | V6: =U6 -> 14702408
B7: Total Sales, General & Administration (SG&A) | D7: =OPEX!H111 -> 2294976.8 | E7: =OPEX!I111 -> 2409450.5 | F7: =OPEX!J111 -> 2413590.9 | G7: =OPEX!K111 -> 2417969.5 | H7: =OPEX!L111 -> 2424097.1 | I7: =OPEX!M111 -> 2052614.8 | J7: =OPEX!N111 -> 2056397.7 | K7: =OPEX!O111 -> 2058277.3 | ... O7: =OPEX!S111 -> 2060090.5 | P7: =O7 -> 2060090.5 | Q7: =P7 -> 2060090.5 | R7: =Q7 -> 2060090.5 | S7: =R7 -> 2060090.5 | T7: =S7 -> 2060090.5 | U7: =T7 -> 2060090.5 | V7: =U7 -> 2060090.5
B10: CAPEX | D10: 2018 | E10: 2019 | F10: 2020 | G10: 2021 | H10: 2022
C11: Depreciation | D11: 0 | E11: 1 | F11: 2 | G11: 3 | H11: 4 | I11: Reinvestment*
B12: Establishment cost | C12: 20 | D12: =CAPEX!E249 -> 37124290 | E12: =CAPEX!F249 -> 13382679 | F12: =CAPEX!G249 -> 0 | G12: =CAPEX!H249 -> 0 | H12: =CAPEX!I249 -> 0 | I12: 0
B13: Total | D13: =SUM(D12:D12) -> 37124290 | E13: =SUM(E12:E12) -> 13382679 | F13: =SUM(F12:F12) -> 0 | G13: =SUM(G12:G12) -> 0 | H13: =SUM(H12:H12) -> 0
I14: * 1-Yes; 2-No
B16: Financial Assumptions
B17: Item | C17: Unit | D17: Amount | E17: Comments
B18: CAPEX Loan Terms
B19: Loan Interest Rate | C19: % | D19: 0.06
B20: Term | C20: Years | D20: 13
B21: Grace | C21: Years | D21: 3 | E21: Incl. Year 0
B22: Loan/Equity | C22: % Equity | D22: =Dashboard!C103 -> 0.33333333
B23: No. of Payments | C23: Payments/Year | D23: 4
B24: Interest During Construction (IDC) | C24: Yes/No | D24: 1 | E24: 1=Yes; 0=No
B25: Debt Service Reserve Account (DSRA) | C25: Yes/No | D25: 1 | E25: 1=Yes; 0=No
B26: Fees | C26: % CAPEX | D26: 0.02 | E26: Management/Commitment/Commission
B27: Working Capital Loan Terms
B28: Raise Working Capital? | C28: Yes/No | D28: 1 | E28: 1=Yes; 0=No
B29: Loan Interest Rate | C29: % | D29: 0.1
B30: Term | C30: Years | D30: 1
B31: Grace | C31: Years | D31: 0
B32: Loan/Equity | C32: % Equity | D32: 0
B33: Taxes
B34: Tax Holiday | C34: Years | D34: 5
B35: Corporate Tax | C35: % | D35: 0.35
B36: Financial Statement Assumptions
B37: Minimum Cash | C37: Currency | D37: 0
B38: Inflation Rate | C38: % | D38: 0.03
B39: Equity Interest Rate | C39: % | D39: 0.1
B40: WACC | C40: % | D40: =D39*D22+D19*(1-D35)*(1-D22) -> 0.059333333
B41: Terminal Growth Rate | C41: % | D41: 0.02
B42: Minimum Debt Service Coverage Ratio (DSCR) | C42: Ratio | D42: 1.2
B43: Working Capital Drivers
D44: 1 | E44: 2 | F44: 3 | G44: 4 | H44: 5 | I44: 6 | J44: 7 | K44: 8 | L44: 9 | M44: 10 | N44: 11 | O44: 12
B45: Inventory | C45: % COGS | D45: 0.1 | E45: 0.1 | F45: 0.1 | G45: 0.1 | H45: 0.1 | I45: 0.1 | J45: 0.1 | K45: 0.1 | L45: 0.1 | M45: 0.1 | N45: 0.1 | O45: 0.1
B46: Accounts receivable | C46: % Sales | D46: 0.3 | E46: =1/12 -> 0.083333333 | F46: =1/12 -> 0.083333333 | G46: =1/12 -> 0.083333333 | H46: =1/12 -> 0.083333333 | I46: =1/12 -> 0.083333333 | J46: =1/12 -> 0.083333333 | K46: =1/12 -> 0.083333333 | L46: =1/12 -> 0.083333333 | ... O46: =1/12 -> 0.083333333
B47: Accounts payable | C47: % COGS | D47: =1/12 -> 0.083333333 | E47: =1/12 -> 0.083333333 | F47: =1/12 -> 0.083333333 | G47: =1/12 -> 0.083333333 | H47: =1/12 -> 0.083333333 | I47: =1/12 -> 0.083333333 | J47: =1/12 -> 0.083333333 | K47: =1/12 -> 0.083333333 | ... O47: =1/12 -> 0.083333333

Sheet Dashboard
B1: Company/Project: | C1: =Cover!$C$10 -> Mr. Amir Artine | D1: =Cover!$C$3 -> Cattle Integration, Baghara, Chad | G1: Last Update: | H1: =Cover!$C$13 -> 45763
B4: Main Financial Results
C5: Equity | D5: Firm
B6: NPV (20 Years; WACC) | C6: =Fin.Statements!C105/1000 -> 115391.96 | D6: =Fin.Statements!D105/1000 -> 97128.474
B7: IRR (20 Years) | C7: =Fin.Statements!C106 -> 0.2905722 | D7: =Fin.Statements!D106 -> 0.16573041
B8: Return Period | C8: =Fin.Statements!C107 -> 6.9 | D8: =Fin.Statements!D107 -> 8.6
B9: Discounted Return Period | C9: =Fin.Statements!C108 -> 7.5 | D9: =Fin.Statements!D108 -> 10.1
B10: Real Revenues (Year 12) | C10: ='Data Input'!O5/1000 -> 37105.101
B11: Real EBITDA (Year 12) | C11: =('Data Input'!O5-SUM('Data Input'!O6:O7))/1000 -> 20342.603
B12: % EBITDA | C12: =C11/C10 -> 0.54824275
B13: Total Capital Requirements | C13: =C23/1000 -> 54721.415
B14: ROI (Year 12) | C14: =Q43 -> 0.90716364
B17: Sources and Uses | AB17: Sources and Uses
B18: Item | C18: Amount | D18: % | E18: Year 0 | F18: Year 1 | G18: Year 2 | H18: Year 3 | I18: Year 4 | J18: Year 5 | K18: Year 6 | L18: Year 7 | M18: Year 8 | N18: Year 9 | O18: Year 10 | P18: Year 11 | Q18: Year 12 | R18: Year 13 | S18: Year 14 | T18: Year 15 | U18: Year 16 | V18: Year 17 | W18: Year 18 | X18: Year 19 | Y18: Year 20 | AB18: Item | AC18: Amount | AD18: % | AE18: Year 0 | AF18: Year 1 | AG18: Year 2 | AH18: Year 3 | AI18: Year 4
B19: Sources | AB19: Sources
B20: Establishment Equity | C20: =SUM(E20:Y20) -> 18240472 | D20: =C20/$C$23 -> 0.33333333 | E20: ='CAPEX Financing'!C18+'WC Financing'!C23 -> 13407347 | F20: ='CAPEX Financing'!D18+'WC Financing'!D23 -> 4833124.7 | G20: ='CAPEX Financing'!E18+'WC Financing'!E23 -> 2.718339e-138 | H20: ='CAPEX Financing'!F18+'WC Financing'!F23 -> 2.8769344e-138 | I20: ='CAPEX Financing'!G18+'WC Financing'!G23 -> 0 | J20: ='CAPEX Financing'!H18+'WC Financing'!H23 -> 0 | K20: ='CAPEX Financing'!I18+'WC Financing'!I23 -> 0 | L20: ='CAPEX Financing'!J18+'WC Financing'!J23 -> 0 | ... Y20: ='CAPEX Financing'!W18+'WC Financing'!W23 -> 0 | Z20: =ROUND(C20-SUM(E20:J20),0) -> 0 | AB20: Establishment Equity | AC20: =C20/1000 -> 18240.472 | AD20: =D20 -> 0.33333333 | AE20: =E20/1000 -> 13407.347 | AF20: =F20/1000 -> 4833.1247 | AG20: =G20/1000 -> 2.718339e-141 | AH20: =H20/1000 -> 2.8769344e-141 | AI20: =I20/1000 -> 0
B21: Establishment Loan (+ IDC, DSRA & Fees) | C21: =SUM(E21:Y21) -> 36480944 | D21: =C21/$C$23 -> 0.66666667 | E21: =SUM('CAPEX Financing'!C19:C20) -> 26814694 | F21: =SUM('CAPEX Financing'!D19:D20) -> 9666249.4 | G21: =SUM('CAPEX Financing'!E19:E20) -> 5.4366779e-138 | H21: =SUM('CAPEX Financing'!F19:F20) -> 5.7538687e-138 | I21: =SUM('CAPEX Financing'!G19:G20) -> 0 | J21: =SUM('CAPEX Financing'!H19:H20) -> 0 | K21: =SUM('CAPEX Financing'!I19:I20) -> 0 | L21: =SUM('CAPEX Financing'!J19:J20) -> 0 | ... Y21: =SUM('CAPEX Financing'!W19:W20) -> 0 | Z21: =ROUND(C21-SUM(E21:J21),0) -> 0 | AB21: Establishment Loan | AC21: =C21/1000 -> 36480.944 | AD21: =D21 -> 0.66666667 | AE21: =E21/1000 -> 26814.694 | AF21: =F21/1000 -> 9666.2494 | AG21: =G21/1000 -> 5.4366779e-141 | AH21: =H21/1000 -> 5.7538687e-141 | AI21: =I21/1000 -> 0
B22: Operations Loan | C22: =SUM(E22:Y22) -> 11975508 | D22: =C22/$C$23 -> 0.21884499 | E22: ='WC Financing'!C24 -> 0 | F22: =+'WC Financing'!D24 -> 5194550.7 | G22: =+'WC Financing'!E24 -> 3908927.2 | H22: =+'WC Financing'!F24 -> 2872029.9 | I22: =+'WC Financing'!G24 -> 0 | J22: =+'WC Financing'!H24 -> 0 | K22: =+'WC Financing'!I24 -> 0 | L22: =+'WC Financing'!J24 -> 0 | M22: =+'WC Financing'!K24 -> 0 | ... Y22: =+'WC Financing'!W24 -> 0 | AB22: Total Sources | AC22: =C23/1000 -> 54721.415 | AD22: =D23 -> 1 | AE22: =E23/1000 -> 40222.041 | AF22: =F23/1000 -> 14499.374 | AG22: =G23/1000 -> 8.1550169e-141 | AH22: =H23/1000 -> 8.6308031e-141 | AI22: =I23/1000 -> 0
B23: Total Sources | C23: =SUM(C20:C21) -> 54721415 | D23: =C23/$C$23 -> 1 | E23: =SUM(E20:E21) -> 40222041 | F23: =SUM(F20:F21) -> 14499374 | G23: =SUM(G20:G21) -> 8.1550169e-138 | H23: =SUM(H20:H21) -> 8.6308031e-138 | I23: =SUM(I20:I21) -> 0 | J23: =SUM(J20:J21) -> 0 | K23: =SUM(K20:K21) -> 0 | L23: =SUM(L20:L21) -> 0 | ... Y23: =SUM(Y20:Y21) -> 0 | Z23: =ROUND(C23-SUM(E23:J23),0) -> 0 | AB23: Uses
B24: Uses | Z24: =ROUND(C24-SUM(E24:J24),0) -> 0 | AB24: CAPEX | AC24: =C25/1000 -> 50506.97 | AD24: =D25 -> 0.92298361 | AE24: =E25/1000 -> 37124.29 | AF24: =F25/1000 -> 13382.679 | AG24: =G25/1000 -> 0 | AH24: =H25/1000 -> 0 | AI24: =I25/1000 -> 0
B25: CAPEX | C25: =SUM(E25:Y25) -> 50506970 | D25: =C25/$C$30 -> 0.92298361 | E25: ='CAPEX Financing'!C16 -> 37124290 | F25: ='CAPEX Financing'!D16 -> 13382679 | G25: ='CAPEX Financing'!E16 -> 0 | H25: ='CAPEX Financing'!F16 -> 0 | I25: ='CAPEX Financing'!G16 -> 0 | J25: ='CAPEX Financing'!H16 -> 0 | K25: ='CAPEX Financing'!I16 -> 0 | L25: ='CAPEX Financing'!J16 -> 0 | ... Y25: ='CAPEX Financing'!W16 -> 0 | Z25: =ROUND(C25-SUM(E25:J25),0) -> 0 | AB25: DSRA | AC25: =C26/1000 -> 1015.3948 | AD25: =D26 -> 0.018555712 | AE25: =E26/1000 -> 746.34689 | AF25: =F26/1000 -> 269.04796 | AG25: =G26/1000 -> 2.584198e-141 | AH25: =H26/1000 -> 2.7349672e-141 | AI25: =I26/1000 -> 0
B26: DSRA | C26: =SUM(E26:Y26) -> 1015394.8 | D26: =C26/$C$30 -> 0.018555712 | E26: ='CAPEX Financing'!C20 -> 746346.89 | F26: ='CAPEX Financing'!D20 -> 269047.96 | G26: ='CAPEX Financing'!E20 -> 2.584198e-138 | H26: ='CAPEX Financing'!F20 -> 2.7349672e-138 | I26: ='CAPEX Financing'!G20 -> 0 | J26: ='CAPEX Financing'!H20 -> 0 | K26: ='CAPEX Financing'!I20 -> 0 | L26: ='CAPEX Financing'!J20 -> 0 | ... Y26: ='CAPEX Financing'!W20 -> 0 | Z26: =ROUND(C26-SUM(E26:J26),0) -> 0 | AB26: Fees | AC26: =C27/1000 -> 1010.1394 | AD26: =D27 -> 0.018459672 | AE26: =E27/1000 -> 742.48581 | AF26: =F27/1000 -> 267.65359 | AG26: =G27/1000 -> 0 | AH26: =H27/1000 -> 0 | AI26: =I27/1000 -> 0
B27: Fees | C27: =SUM(E27:Y27) -> 1010139.4 | D27: =C27/$C$30 -> 0.018459672 | E27: ='CAPEX Financing'!$E$5 -> 742485.81 | F27: ='CAPEX Financing'!$E$6 -> 267653.59 | G27: ='CAPEX Financing'!$E$7 -> 0 | H27: ='CAPEX Financing'!$E$8 -> 0 | I27: ='CAPEX Financing'!$E$9 -> 0 | Z27: =ROUND(C27-SUM(E27:J27),0) -> 0 | AB27: IDC | AC27: =C28/1000 -> 2188.9116 | AD27: =D28 -> 0.040001004 | AE27: =E28/1000 -> 1608.9183 | AF27: =F28/1000 -> 579.99328 | AG27: =G28/1000 -> 5.5708189e-141 | AH27: =H28/1000 -> 5.8958359e-141 | AI27: =I28/1000 -> 0
B28: IDC | C28: =SUM(E28:Y28) -> 2188911.6 | D28: =C28/$C$30 -> 0.040001004 | E28: ='CAPEX Financing'!$F$5 -> 1608918.3 | F28: ='CAPEX Financing'!$F$6 -> 579993.28 | G28: ='CAPEX Financing'!$F$7 -> 5.5708189e-138 | H28: ='CAPEX Financing'!$F$8 -> 5.8958359e-138 | I28: ='CAPEX Financing'!$F$9 -> 0 | Z28: =ROUND(C28-SUM(E28:J28),0) -> 0 | AB28: Total Uses | AC28: =C30/1000 -> 54721.415 | AD28: =D30 -> 1 | AE28: =E30/1000 -> 40222.041 | AF28: =F30/1000 -> 14499.374 | AG28: =G30/1000 -> 8.1550169e-141 | AH28: =H30/1000 -> 8.6308031e-141 | AI28: =I30/1000 -> 0
B29: Operations | C29: =SUM(E29:Y29) -> 11975508 | D29: =C29/$C$30 -> 0.21884499 | E29: ='WC Financing'!C21 -> 0 | F29: ='WC Financing'!D21 -> 5194550.7 | G29: ='WC Financing'!E21 -> 3908927.2 | H29: ='WC Financing'!F21 -> 2872029.9 | I29: ='WC Financing'!G21 -> 0 | J29: ='WC Financing'!H21 -> 0 | K29: ='WC Financing'!I21 -> 0 | L29: ='WC Financing'!J21 -> 0 | ... Y29: ='WC Financing'!W21 -> 0 | Z29: =ROUND(C29-SUM(E29:J29),0) -> 0
B30: Total Uses | C30: =SUM(C25:C28) -> 54721415 | D30: =C30/$C$30 -> 1 | E30: =SUM(E25:E28) -> 40222041 | F30: =SUM(F25:F28) -> 14499374 | G30: =SUM(G25:G28) -> 8.1550169e-138 | H30: =SUM(H25:H28) -> 8.6308031e-138 | I30: =SUM(I25:I28) -> 0 | J30: =SUM(J25:J29) -> 0 | K30: =SUM(K25:K29) -> 0 | L30: =SUM(L25:L29) -> 0 | M30: =SUM(M25:M29) -> 0 | N30: =SUM(N25:N29) -> 0 | O30: =SUM(O25:O29) -> 0 | P30: =SUM(P25:P29) -> 0 | Q30: =SUM(Q25:Q29) -> 0 | ... Y30: =SUM(Y25:Y29) -> 0 | Z30: =ROUND(C30-SUM(E30:J30),0) -> 0
B31: Check | C31: =ROUND(C30-C23,0) -> 0 | D31: =ROUND(D30-D23,0) -> 0 | E31: =ROUND(E30-E23,0) -> 0 | F31: =ROUND(F30-F23,0) -> 0 | G31: =ROUND(G30-G23,0) -> 0 | H31: =ROUND(H30-H23,0) -> 0 | I31: =ROUND(I30-I23,0) -> 0 | J31: =ROUND(J30-J23,0) -> 0 | ... Y31: =ROUND(Y30-Y23,0) -> 0
B33: Financial Ratios
E34: 0 | F34: 1 | G34: 2 | H34: 3 | I34: 4 | J34: 5 | K34: 6 | L34: 7 | M34: 8 | N34: 9 | O34: 10 | P34: 11 | Q34: 12 | R34: 13 | S34: 14 | T34: 15 | U34: 16 | V34: 17 | W34: 18 | X34: 19 | Y34: 20
B35: Working Capital
B36: Working Capital | E36: =Fin.Statements!C77-Fin.Statements!C86 -> 36.632162 | F36: =Fin.Statements!D77-Fin.Statements!D86 -> -2363828.5 | G36: =Fin.Statements!E77-Fin.Statements!E86 -> -3674059.8 | H36: =Fin.Statements!F77-Fin.Statements!F86 -> -2909217.3 | I36: =Fin.Statements!G77-Fin.Statements!G86 -> 1028940 | J36: =Fin.Statements!H77-Fin.Statements!H86 -> 9339245.3 | K36: =Fin.Statements!I77-Fin.Statements!I86 -> 17319701 | L36: =Fin.Statements!J77-Fin.Statements!J86 -> 28513555 | ... Y36: =Fin.Statements!W77-Fin.Statements!W86 -> 2.6164273e+08
B37: Debt Service Coverage Ratio (DSCR)
B38: EBIDTA - TAX | E38: =Fin.Statements!C16+Fin.Statements!C13 -> 0 | F38: =Fin.Statements!D16+Fin.Statements!D13 -> -235546.73 | G38: =Fin.Statements!E16+Fin.Statements!E13 -> 3196691.7 | H38: =Fin.Statements!F16+Fin.Statements!F13 -> 5602074.4 | I38: =Fin.Statements!G16+Fin.Statements!G13 -> 8409660.6 | J38: =Fin.Statements!H16+Fin.Statements!H13 -> 12502142 | K38: =Fin.Statements!I16+Fin.Statements!I13 -> 12180292 | L38: =Fin.Statements!J16+Fin.Statements!J13 -> 15402180 | ... Y38: =Fin.Statements!W16+Fin.Statements!W13 -> 883871.97
B39: Total Debt Service | E39: =SUM('CAPEX Financing'!C23:C24)+SUM('WC Financing'!C28:C29) -> 1608881.6 | F39: =SUM('CAPEX Financing'!D23:D24)+SUM('WC Financing'!D28:D29) -> 2708311.7 | G39: =SUM('CAPEX Financing'!E23:E24)+SUM('WC Financing'!E28:E29) -> 8293755.1 | H39: =SUM('CAPEX Financing'!F23:F24)+SUM('WC Financing'!F28:F29) -> 8152317.4 | I39: =SUM('CAPEX Financing'!G23:G24)+SUM('WC Financing'!G28:G29) -> 7220710.3 | J39: =SUM('CAPEX Financing'!H23:H24)+SUM('WC Financing'!H28:H29) -> 4061477.4 | K39: =SUM('CAPEX Financing'!I23:I24)+SUM('WC Financing'!I28:I29) -> 4061477.4 | L39: =SUM('CAPEX Financing'!J23:J24)+SUM('WC Financing'!J28:J29) -> 4061477.4 | ... Y39: =SUM('CAPEX Financing'!W23:W24)+SUM('WC Financing'!W28:W29) -> 0
B40: DSCR | E40: =IF(E39<1,0,E38/E39) -> 0 | F40: =IF(F39<1,0,F38/F39) -> -0.086971796 | G40: =IF(G39<1,0,G38/G39) -> 0.38543358 | H40: =IF(H39<1,0,H38/H39) -> 0.6871757 | I40: =IF(I39<1,0,I38/I39) -> 1.1646584 | J40: =IF(J39<1,0,J38/J39) -> 3.0782253 | K40: =IF(K39<1,0,K38/K39) -> 2.9989807 | L40: =IF(L39<1,0,L38/L39) -> 3.7922605 | ... Y40: =IF(Y39<1,0,Y38/Y39) -> 0
B41: Minimum | E41: ='Data Input'!$D$42 -> 1.2 | F41: ='Data Input'!$D$42 -> 1.2 | G41: ='Data Input'!$D$42 -> 1.2 | H41: ='Data Input'!$D$42 -> 1.2 | I41: ='Data Input'!$D$42 -> 1.2 | J41: ='Data Input'!$D$42 -> 1.2 | K41: ='Data Input'!$D$42 -> 1.2 | L41: ='Data Input'!$D$42 -> 1.2 | ... Y41: ='Data Input'!$D$42 -> 1.2
B42: Financial Ratios
B43: ROI | E43: =(Fin.Statements!C15+SUM(Fin.Statements!$C$39:C39))/(-SUM(Fin.Statements!$C$39:C39)) -> -1.0433377 | F43: =(Fin.Statements!D15+SUM(Fin.Statements!$C$39:D39))/(-SUM(Fin.Statements!$C$39:D39)) -> -1.1268925 | G43: =(Fin.Statements!E15+SUM(Fin.Statements!$C$39:E39))/(-SUM(Fin.Statements!$C$39:E39)) -> -1.1749623 | H43: =(Fin.Statements!F15+SUM(Fin.Statements!$C$39:F39))/(-SUM(Fin.Statements!$C$39:F39)) -> -1.1701896 | I43: =(Fin.Statements!G15+SUM(Fin.Statements!$C$39:G39))/(-SUM(Fin.Statements!$C$39:G39)) -> -1.1001559 | J43: =(Fin.Statements!H15+SUM(Fin.Statements!$C$39:H39))/(-SUM(Fin.Statements!$C$39:H39)) -> -0.94097586 | K43: =(Fin.Statements!I15+SUM(Fin.Statements!$C$39:I39))/(-SUM(Fin.Statements!$C$39:I39)) -> -0.78558722 | L43: =(Fin.Statements!J15+SUM(Fin.Statements!$C$39:J39))/(-SUM(Fin.Statements!$C$39:J39)) -> -0.56366822 | ... Y43: =(Fin.Statements!W15+SUM(Fin.Statements!$C$39:W39))/(-SUM(Fin.Statements!$C$39:W39)) -> 3.5072794
B44: Operating Profit Margin (% EBITDA) | E44: =IFERROR(Fin.Statements!C16/Fin.Statements!C5,0) -> 0 | F44: =IFERROR(Fin.Statements!D16/Fin.Statements!D5,0) -> -0.026035067 | G44: =IFERROR(Fin.Statements!E16/Fin.Statements!E5,0) -> 0.18404455 | H44: =IFERROR(Fin.Statements!F16/Fin.Statements!F5,0) -> 0.2668157 | I44: =IFERROR(Fin.Statements!G16/Fin.Statements!G5,0) -> 0.33851494 | J44: =IFERROR(Fin.Statements!H16/Fin.Statements!H5,0) -> 0.41107751 | K44: =IFERROR(Fin.Statements!I16/Fin.Statements!I5,0) -> 0.48803194 | L44: =IFERROR(Fin.Statements!J16/Fin.Statements!J5,0) -> 0.52043292 | ... Y44: =IFERROR(Fin.Statements!W16/Fin.Statements!W5,0) -> 0
B45: Net Profit Margin | E45: =IFERROR(Fin.Statements!C14/Fin.Statements!C5,0) -> 0 | F45: =IFERROR(Fin.Statements!D14/Fin.Statements!D5,0) -> -0.53055383 | G45: =IFERROR(Fin.Statements!E14/Fin.Statements!E5,0) -> -0.13978032 | H45: =IFERROR(Fin.Statements!F14/Fin.Statements!F5,0) -> 0.01148094 | I45: =IFERROR(Fin.Statements!G14/Fin.Statements!G5,0) -> 0.14238296 | J45: =IFERROR(Fin.Statements!H14/Fin.Statements!H5,0) -> 0.26434987 | K45: =IFERROR(Fin.Statements!I14/Fin.Statements!I5,0) -> 0.21265203 | L45: =IFERROR(Fin.Statements!J14/Fin.Statements!J5,0) -> 0.2721049 | ... Y45: =IFERROR(Fin.Statements!W14/Fin.Statements!W5,0) -> 0
B46: Return on Capital Employed (ROCE) | E46: =SUM(Fin.Statements!C14,-Fin.Statements!C13,-Fin.Statements!C11)/SUM(Fin.Statements!C82,-Fin.Statements!C86) -> 0 | F46: =SUM(Fin.Statements!D14,-Fin.Statements!D13,-Fin.Statements!D11)/SUM(Fin.Statements!D82,-Fin.Statements!D86) -> -0.044221112 | G46: =SUM(Fin.Statements!E14,-Fin.Statements!E13,-Fin.Statements!E11)/SUM(Fin.Statements!E82,-Fin.Statements!E86) -> 0.015444987 | H46: =SUM(Fin.Statements!F14,-Fin.Statements!F13,-Fin.Statements!F11)/SUM(Fin.Statements!F82,-Fin.Statements!F86) -> 0.073771365 | I46: =SUM(Fin.Statements!G14,-Fin.Statements!G13,-Fin.Statements!G11)/SUM(Fin.Statements!G82,-Fin.Statements!G86) -> 0.13646666 | J46: =SUM(Fin.Statements!H14,-Fin.Statements!H13,-Fin.Statements!H11)/SUM(Fin.Statements!H82,-Fin.Statements!H86) -> 0.20400772 | K46: =SUM(Fin.Statements!I14,-Fin.Statements!I13,-Fin.Statements!I11)/SUM(Fin.Statements!I82,-Fin.Statements!I86) -> 0.28488559 | L46: =SUM(Fin.Statements!J14,-Fin.Statements!J13,-Fin.Statements!J11)/SUM(Fin.Statements!J82,-Fin.Statements!J86) -> 0.30006141 | ... Y46: =SUM(Fin.Statements!W14,-Fin.Statements!W13,-Fin.Statements!W11)/SUM(Fin.Statements!W82,-Fin.Statements!W86) -> -0.0096272751
B47: Cash Flow / Debt Service Ratio | E47: =E40 -> 0 | F47: =F40 -> -0.086971796 | G47: =G40 -> 0.38543358 | H47: =H40 -> 0.6871757 | I47: =I40 -> 1.1646584 | J47: =J40 -> 3.0782253 | K47: =K40 -> 2.9989807 | L47: =L40 -> 3.7922605 | ... Y47: =Y40 -> 0
B48: Current Ratio | E48: =IFERROR(Fin.Statements!C77/Fin.Statements!C86,0) -> 0 | F48: =IFERROR(Fin.Statements!D77/Fin.Statements!D86,0) -> 0.5908117 | G48: =IFERROR(Fin.Statements!E77/Fin.Statements!E86,0) -> 0.41596955 | H48: =IFERROR(Fin.Statements!F77/Fin.Statements!F86,0) -> 0.51048326 | I48: =IFERROR(Fin.Statements!G77/Fin.Statements!G86,0) -> 1.3143116 | J48: =IFERROR(Fin.Statements!H77/Fin.Statements!H86,0) -> 3.6532241 | K48: =IFERROR(Fin.Statements!I77/Fin.Statements!I86,0) -> 5.5948419 | L48: =IFERROR(Fin.Statements!J77/Fin.Statements!J86,0) -> 8.16149 | ... Y48: =IFERROR(Fin.Statements!W77/Fin.Statements!W86,0) -> 0
B49: Debt to Equity Ratio | E49: =(Fin.Statements!C86+Fin.Statements!C88)/Fin.Statements!C91 -> 2.4253567 | F49: =(Fin.Statements!D86+Fin.Statements!D88)/Fin.Statements!D91 -> 3.905031 | G49: =(Fin.Statements!E86+Fin.Statements!E88)/Fin.Statements!E91 -> 4.9281007 | H49: =(Fin.Statements!F86+Fin.Statements!F88)/Fin.Statements!F91 -> 4.5184299 | I49: =(Fin.Statements!G86+Fin.Statements!G88)/Fin.Statements!G91 -> 2.8115 | J49: =(Fin.Statements!H86+Fin.Statements!H88)/Fin.Statements!H91 -> 1.5937738 | K49: =(Fin.Statements!I86+Fin.Statements!I88)/Fin.Statements!I91 -> 1.0716025 | L49: =(Fin.Statements!J86+Fin.Statements!J88)/Fin.Statements!J91 -> 0.70645071 | ... Y49: =(Fin.Statements!W86+Fin.Statements!W88)/Fin.Statements!W91 -> 0.071188157
B50: Debt to Tangible Net Worth Ratio | E50: =IFERROR(SUM(Fin.Statements!C86,Fin.Statements!C88)/Fin.Statements!C89,0) -> 2 | F50: =IFERROR(SUM(Fin.Statements!D86,Fin.Statements!D88)/Fin.Statements!D89,0) -> 2.3167063 | G50: =IFERROR(SUM(Fin.Statements!E86,Fin.Statements!E88)/Fin.Statements!E89,0) -> 2.2677097 | H50: =IFERROR(SUM(Fin.Statements!F86,Fin.Statements!F88)/Fin.Statements!F89,0) -> 2.1389087 | I50: =IFERROR(SUM(Fin.Statements!G86,Fin.Statements!G88)/Fin.Statements!G89,0) -> 1.8760979 | J50: =IFERROR(SUM(Fin.Statements!H86,Fin.Statements!H88)/Fin.Statements!H89,0) -> 1.7659905 | K50: =IFERROR(SUM(Fin.Statements!I86,Fin.Statements!I88)/Fin.Statements!I89,0) -> 1.648467 | L50: =IFERROR(SUM(Fin.Statements!J86,Fin.Statements!J88)/Fin.Statements!J89,0) -> 1.5208487 | ... Y50: =IFERROR(SUM(Fin.Statements!W86,Fin.Statements!W88)/Fin.Statements!W89,0) -> 0.95570498
B51: Cash Flow Available for Debt Service (CFADS)
B52: Cash Available to Equity | E52: =Fin.Statements!C40 -> 746383.52 | F52: =Fin.Statements!D40 -> 269083.04 | G52: =Fin.Statements!E40 -> 242.77091 | H52: =Fin.Statements!F40 -> 498.09615 | I52: =Fin.Statements!G40 -> 852427.41 | J52: =Fin.Statements!H40 -> 7953279.3 | K52: =Fin.Statements!I40 -> 7555499.5 | L52: =Fin.Statements!J40 -> 10970536 | ... Y52: =Fin.Statements!W40 -> 6565115.7
B53: Interest | E53: =-Fin.Statements!C11 -> 1608881.6 | F53: =-Fin.Statements!D11 -> 2708311.7 | G53: =-Fin.Statements!E11 -> 3099204.4 | H53: =-Fin.Statements!F11 -> 2835671.6 | I53: =-Fin.Statements!G11 -> 2347120.1 | J53: =-Fin.Statements!H11 -> 1937094.3 | K53: =-Fin.Statements!I11 -> 1806734.6 | L53: =-Fin.Statements!J11 -> 1668375.5 | ... Y53: =-Fin.Statements!W11 -> 0
B54: Principal | E54: =-Fin.Statements!C32 -> 0 | F54: =-Fin.Statements!D32 -> 0 | G54: =-Fin.Statements!E32 -> 5194550.7 | H54: =-Fin.Statements!F32 -> 5316645.8 | I54: =-Fin.Statements!G32 -> 4873590.2 | J54: =-Fin.Statements!H32 -> 2124383.2 | K54: =-Fin.Statements!I32 -> 2254742.9 | L54: =-Fin.Statements!J32 -> 2393101.9 | ... Y54: =-Fin.Statements!W32 -> 0
B55: CFADS | E55: =SUM(E52:E54) -> 2355265.2 | F55: =SUM(F52:F54) -> 2977394.7 | G55: =SUM(G52:G54) -> 8293997.9 | H55: =SUM(H52:H54) -> 8152815.5 | I55: =SUM(I52:I54) -> 8073137.7 | J55: =SUM(J52:J54) -> 12014757 | K55: =SUM(K52:K54) -> 11616977 | L55: =SUM(L52:L54) -> 15032013 | ... Y55: =SUM(Y52:Y54) -> 6565115.7
B56: Accumulated CFADS | E56: =E55 -> 2355265.2 | F56: =F55+E56 -> 5332659.9 | G56: =G55+F56 -> 13626658 | H56: =H55+G56 -> 21779473 | I56: =I55+H56 -> 29852611 | J56: =J55+I56 -> 41867368 | K56: =K55+J56 -> 53484345 | L56: =L55+K56 -> 68516358 | M56: =M55+L56 -> 84985412 | ... Y56: =Y55+X56 -> 3.1405633e+08
B60: Illustrations
B97: Sensitivity Analysis
B99: Sensitivity Analysis Engines
B100: Prices/Yields | C100: 1
B101: OPEX | C101: 1
B102: CAPEX | C102: 1
B103: Equity | C103: =1/3 -> 0.33333333
B106: Sensitivity to Output Prices or Yields
C107: =C100 -> 1 | D107: 0.8 | E107: 0.9 | F107: 1 | G107: 1.1 | H107: 1.2
B108: NPV (WACC) | C108: =Fin.Statements!$C$105 -> 1.1539196e+08 | D108: 57955803 | E108: 86766481 | F108: 1.1539156e+08 | G108: 1.4401663e+08 | H108: 1.7264171e+08
B109: IRR | C109: =Fin.Statements!$C$106 -> 0.2905722 | D109: 0.17455249 | E109: 0.23234634 | F109: 0.29057437 | G109: 0.35155956 | H109: 0.4158531
B110: Return Period | C110: =Fin.Statements!$C$107 -> 6.9 | D110: 9.5 | E110: 7.9 | F110: 6.9 | G110: 5.7 | H110: 5.1
B111: Discounted Return Period | C111: =Fin.Statements!$C$108 -> 7.5 | D111: 11.2 | E111: 8.8 | F111: 7.5 | G111: 6.1 | H111: 5.3
D112: =IF(D110=21,"Over 20 Years",D110) -> 9.5 | E112: =IF(E110=21,"Over 20 Years",E110) -> 7.9 | F112: =IF(F110=21,"Over 20 Years",F110) -> 6.9 | G112: =IF(G110=21,"Over 20 Years",G110) -> 5.7 | H112: =IF(H110=21,"Over 20 Years",H110) -> 5.1
B114: Sensitivity to OPEX
C115: =C101 -> 1 | D115: 0.8 | E115: 0.9 | F115: 1 | G115: 1.1 | H115: 1.2
B116: NPV (WACC) | C116: =Fin.Statements!$C$105 -> 1.1539196e+08 | D116: 1.4484155e+08 | E116: 1.3011655e+08 | F116: 1.1539156e+08 | G116: 1.0066656e+08 | H116: 85917170
B117: IRR | C117: =Fin.Statements!$C$106 -> 0.2905722 | D117: 0.37404065 | E117: 0.33039661 | F117: 0.29057437 | G117: 0.25414252 | H117: 0.22041463
B118: Return Period | C118: =Fin.Statements!$C$107 -> 6.9 | D118: 5.4 | E118: 6 | F118: 6.9 | G118: 7.5 | H118: 8.2
B119: Discounted Return Period | C119: =Fin.Statements!$C$108 -> 7.5 | D119: 5.7 | E119: 6.6 | F119: 7.5 | G119: 8.3 | H119: 9.2
D120: =IF(D118=21,"Over 20 Years",D118) -> 5.4 | E120: =IF(E118=21,"Over 20 Years",E118) -> 6 | F120: =IF(F118=21,"Over 20 Years",F118) -> 6.9 | G120: =IF(G118=21,"Over 20 Years",G118) -> 7.5 | H120: =IF(H118=21,"Over 20 Years",H118) -> 8.2
B122: Sensitivity to CAPEX
C123: =C102 -> 1 | D123: 0.8 | E123: 0.9 | F123: 1 | G123: 1.1 | H123: 1.2
B124: NPV (WACC) | C124: =Fin.Statements!$C$105 -> 1.1539196e+08 | D124: 1.1987793e+08 | E124: 1.1763474e+08 | F124: 1.1539156e+08 | G124: 1.1314837e+08 | H124: 1.1090519e+08
B125: IRR | C125: =Fin.Statements!$C$106 -> 0.2905722 | D125: 0.34507344 | E125: 0.31509712 | F125: 0.29057437 | G125: 0.27002082 | H125: 0.2524647
B126: Return Period | C126: =Fin.Statements!$C$107 -> 6.9 | D126: 6 | E126: 6.5 | F126: 6.9 | G126: 7.2 | H126: 7.4
B127: Discounted Return Period | C127: =Fin.Statements!$C$108 -> 7.5 | D127: 6.6 | E127: 7.1 | F127: 7.5 | G127: 7.8 | H127: 8.2
D128: =IF(D126=21,"Over 20 Years",D126) -> 6 | E128: =IF(E126=21,"Over 20 Years",E126) -> 6.5 | F128: =IF(F126=21,"Over 20 Years",F126) -> 6.9 | G128: =IF(G126=21,"Over 20 Years",G126) -> 7.2 | H128: =IF(H126=21,"Over 20 Years",H126) -> 7.4
B130: Sensitivity to Equity Share
C131: =C103 -> 0.33333333 | D131: 0.2 | E131: 0.4 | F131: 0.6 | G131: 0.8 | H131: 0.999
B132: NPV (WACC) | C132: =Fin.Statements!$C$105 -> 1.1539196e+08 | D132: 1.3338144e+08 | E132: 1.0732589e+08 | F132: 85692192 | G132: 66863539 | H132: 50156041
B133: IRR | C133: =Fin.Statements!$C$106 -> 0.2905722 | D133: 0.35292377 | E133: 0.27049282 | F133: 0.22957754 | G133: 0.20350943 | H133: 0.18498782
B134: Return Period | C134: =Fin.Statements!$C$107 -> 6.9 | D134: 6.4 | E134: 7.1 | F134: 7.5 | G134: 7.9 | H134: 8.2
B135: Discounted Return Period | C135: =Fin.Statements!$C$108 -> 7.5 | D135: 6.8 | E135: 7.8 | F135: 8.7 | G135: 9.6 | H135: 10.7
D136: =IF(D134=21,"Over 20 Years",D134) -> 6.4 | E136: =IF(E134=21,"Over 20 Years",E134) -> 7.1 | F136: =IF(F134=21,"Over 20 Years",F134) -> 7.5 | G136: =IF(G134=21,"Over 20 Years",G134) -> 7.9 | H136: =IF(H134=21,"Over 20 Years",H134) -> 8.2

Sheet Fin.Statements
B1: Company/Project: | C1: =Cover!$C$10 -> Mr. Amir Artine | G1: Last Update: | H1: =Cover!$C$13 -> 45763
B3: Income Statement | Z3: Income Statement
C4: 0 | D4: 1 | E4: 2 | F4: 3 | G4: 4 | H4: 5 | I4: 6 | J4: 7 | K4: 8 | L4: 9 | M4: 10 | N4: 11 | O4: 12 | P4: 13 | Q4: 14 | R4: 15 | S4: 16 | T4: 17 | U4: 18 | V4: 19 | W4: 20 | AA4: 0 | AB4: 1 | AC4: 2 | AD4: 3 | AE4: 4 | AF4: 5 | AG4: 6 | AH4: 7 | AI4: 8 | AJ4: 9 | AK4: 10 | AL4: 11 | AM4: 12 | AN4: 13 | AO4: 14 | AP4: 15 | AQ4: 16 | AR4: 17 | AS4: 18 | AT4: 19 | AU4: 20
B5: Revenues | C5: ='Data Input'!C5*(1+'Data Input'!$D$38)^(C$4-1)*Dashboard!$C$100 -> 0 | D5: ='Data Input'!D5*(1+'Data Input'!$D$38)^(D$4-1)*Dashboard!$C$100 -> 9047287.3 | E5: ='Data Input'!E5*(1+'Data Input'!$D$38)^(E$4-1)*Dashboard!$C$100 -> 17369120 | F5: ='Data Input'!F5*(1+'Data Input'!$D$38)^(F$4-1)*Dashboard!$C$100 -> 20996045 | G5: ='Data Input'!G5*(1+'Data Input'!$D$38)^(G$4-1)*Dashboard!$C$100 -> 24842805 | H5: ='Data Input'!H5*(1+'Data Input'!$D$38)^(H$4-1)*Dashboard!$C$100 -> 30413102 | I5: ='Data Input'!I5*(1+'Data Input'!$D$38)^(I$4-1)*Dashboard!$C$100 -> 36906345 | J5: ='Data Input'!J5*(1+'Data Input'!$D$38)^(J$4-1)*Dashboard!$C$100 -> 41191674 | ... W5: ='Data Input'!W5*(1+'Data Input'!$D$38)^(W$4-1)*Dashboard!$C$100 -> 0 | Z5: Revenues | AA5: =C5/1000 -> 0 | AB5: =D5/1000 -> 9047.2873 | AC5: =E5/1000 -> 17369.12 | AD5: =F5/1000 -> 20996.045 | AE5: =G5/1000 -> 24842.805 | AF5: =H5/1000 -> 30413.102 | AG5: =I5/1000 -> 36906.345 | AH5: =J5/1000 -> 41191.674 | ... AU5: =W5/1000 -> 0
B6: COGS | C6: =-'Data Input'!C6*(1+'Data Input'!$D$38)^(C$4-1)*Dashboard!$C$101 -> 0 | D6: =-'Data Input'!D6*(1+'Data Input'!$D$38)^(D$4-1)*Dashboard!$C$101 -> -6987857.2 | E6: =-'Data Input'!E6*(1+'Data Input'!$D$38)^(E$4-1)*Dashboard!$C$101 -> -11690694 | F6: =-'Data Input'!F6*(1+'Data Input'!$D$38)^(F$4-1)*Dashboard!$C$101 -> -12833392 | G6: =-'Data Input'!G6*(1+'Data Input'!$D$38)^(G$4-1)*Dashboard!$C$101 -> -13790964 | H6: =-'Data Input'!H6*(1+'Data Input'!$D$38)^(H$4-1)*Dashboard!$C$101 -> -15182617 | I6: =-'Data Input'!I6*(1+'Data Input'!$D$38)^(I$4-1)*Dashboard!$C$101 -> -16515326 | J6: =-'Data Input'!J6*(1+'Data Input'!$D$38)^(J$4-1)*Dashboard!$C$101 -> -17298725 | ... W6: =-'Data Input'!W6*(1+'Data Input'!$D$38)^(W$4-1)*Dashboard!$C$101 -> 0 | Z6: COGS | AA6: =C6/1000 -> 0 | AB6: =D6/1000 -> -6987.8572 | AC6: =E6/1000 -> -11690.694 | AD6: =F6/1000 -> -12833.392 | AE6: =G6/1000 -> -13790.964 | AF6: =H6/1000 -> -15182.617 | AG6: =I6/1000 -> -16515.326 | AH6: =J6/1000 -> -17298.725 | ... AU6: =W6/1000 -> 0
B7: Gross Profit | C7: =SUM(C5:C6) -> 0 | D7: =SUM(D5:D6) -> 2059430.1 | E7: =SUM(E5:E6) -> 5678425.8 | F7: =SUM(F5:F6) -> 8162653 | G7: =SUM(G5:G6) -> 11051841 | H7: =SUM(H5:H6) -> 15230485 | I7: =SUM(I5:I6) -> 20391018 | J7: =SUM(J5:J6) -> 23892950 | ... W7: =SUM(W5:W6) -> 0 | Z7: Gross Profit | AA7: =C7/1000 -> 0 | AB7: =D7/1000 -> 2059.4301 | AC7: =E7/1000 -> 5678.4258 | AD7: =F7/1000 -> 8162.653 | AE7: =G7/1000 -> 11051.841 | AF7: =H7/1000 -> 15230.485 | AG7: =I7/1000 -> 20391.018 | AH7: =J7/1000 -> 23892.95 | ... AU7: =W7/1000 -> 0
B8: SG&A | C8: =-'Data Input'!C7*(1+'Data Input'!$D$38)^(C$4-1)*Dashboard!$C$101 -> 0 | D8: =-'Data Input'!D7*(1+'Data Input'!$D$38)^(D$4-1)*Dashboard!$C$101 -> -2294976.8 | E8: =-'Data Input'!E7*(1+'Data Input'!$D$38)^(E$4-1)*Dashboard!$C$101 -> -2481734 | F8: =-'Data Input'!F7*(1+'Data Input'!$D$38)^(F$4-1)*Dashboard!$C$101 -> -2560578.6 | G8: =-'Data Input'!G7*(1+'Data Input'!$D$38)^(G$4-1)*Dashboard!$C$101 -> -2642180.6 | H8: =-'Data Input'!H7*(1+'Data Input'!$D$38)^(H$4-1)*Dashboard!$C$101 -> -2728342.6 | I8: =-'Data Input'!I7*(1+'Data Input'!$D$38)^(I$4-1)*Dashboard!$C$101 -> -2379543.2 | J8: =-'Data Input'!J7*(1+'Data Input'!$D$38)^(J$4-1)*Dashboard!$C$101 -> -2455446.4 | ... W8: =-'Data Input'!W7*(1+'Data Input'!$D$38)^(W$4-1)*Dashboard!$C$101 -> 0 | Z8: SG&A | AA8: =C8/1000 -> 0 | AB8: =D8/1000 -> -2294.9768 | AC8: =E8/1000 -> -2481.734 | AD8: =F8/1000 -> -2560.5786 | AE8: =G8/1000 -> -2642.1806 | AF8: =H8/1000 -> -2728.3426 | AG8: =I8/1000 -> -2379.5432 | AH8: =J8/1000 -> -2455.4464 | ... AU8: =W8/1000 -> 0
B9: Depreciation | D9: =-Depreciation!D29 -> -1856214.5 | E9: =-Depreciation!E29 -> -2525348.5 | F9: =-Depreciation!F29 -> -2525348.5 | G9: =-Depreciation!G29 -> -2525348.5 | H9: =-Depreciation!H29 -> -2525348.5 | I9: =-Depreciation!I29 -> -2525348.5 | J9: =-Depreciation!J29 -> -2525348.5 | K9: =-Depreciation!K29 -> -2525348.5 | ... W9: =-Depreciation!W29 -> -2525348.5 | Z9: Depreciation | AA9: =C9/1000 -> 0 | AB9: =D9/1000 -> -1856.2145 | AC9: =E9/1000 -> -2525.3485 | AD9: =F9/1000 -> -2525.3485 | AE9: =G9/1000 -> -2525.3485 | AF9: =H9/1000 -> -2525.3485 | AG9: =I9/1000 -> -2525.3485 | AH9: =J9/1000 -> -2525.3485 | ... AU9: =W9/1000 -> -2525.3485
B10: Operating Profit | C10: =SUM(C7:C9) -> 0 | D10: =SUM(D7:D9) -> -2091761.2 | E10: =SUM(E7:E9) -> 671343.26 | F10: =SUM(F7:F9) -> 3076725.9 | G10: =SUM(G7:G9) -> 5884312.1 | H10: =SUM(H7:H9) -> 9976794 | I10: =SUM(I7:I9) -> 15486127 | J10: =SUM(J7:J9) -> 18912155 | ... W10: =SUM(W7:W9) -> -2525348.5 | Z10: Operating Profit | AA10: =C10/1000 -> 0 | AB10: =D10/1000 -> -2091.7612 | AC10: =E10/1000 -> 671.34326 | AD10: =F10/1000 -> 3076.7259 | AE10: =G10/1000 -> 5884.3121 | AF10: =H10/1000 -> 9976.794 | AG10: =I10/1000 -> 15486.127 | AH10: =J10/1000 -> 18912.155 | ... AU10: =W10/1000 -> -2525.3485
B11: Interest Payments | C11: =-'CAPEX Financing'!C23-'WC Financing'!C28 -> -1608881.6 | D11: =-'CAPEX Financing'!D23-'WC Financing'!D28 -> -2708311.7 | E11: =-'CAPEX Financing'!E23-'WC Financing'!E28 -> -3099204.4 | F11: =-'CAPEX Financing'!F23-'WC Financing'!F28 -> -2835671.6 | G11: =-'CAPEX Financing'!G23-'WC Financing'!G28 -> -2347120.1 | H11: =-'CAPEX Financing'!H23-'WC Financing'!H28 -> -1937094.3 | I11: =-'CAPEX Financing'!I23-'WC Financing'!I28 -> -1806734.6 | J11: =-'CAPEX Financing'!J23-'WC Financing'!J28 -> -1668375.5 | ... W11: =-'CAPEX Financing'!W23-'WC Financing'!W28 -> 0 | Z11: Interest Payments | AA11: =C11/1000 -> -1608.8816 | AB11: =D11/1000 -> -2708.3117 | AC11: =E11/1000 -> -3099.2044 | AD11: =F11/1000 -> -2835.6716 | AE11: =G11/1000 -> -2347.1201 | AF11: =H11/1000 -> -1937.0943 | AG11: =I11/1000 -> -1806.7346 | AH11: =J11/1000 -> -1668.3755 | ... AU11: =W11/1000 -> 0
B12: Profit Before Tax | C12: =SUM(C10:C11) -> -1608881.6 | D12: =SUM(D10:D11) -> -4800072.9 | E12: =SUM(E10:E11) -> -2427861.1 | F12: =SUM(F10:F11) -> 241054.33 | G12: =SUM(G10:G11) -> 3537192 | H12: =SUM(H10:H11) -> 8039699.7 | I12: =SUM(I10:I11) -> 13679392 | J12: =SUM(J10:J11) -> 17243779 | ... W12: =SUM(W10:W11) -> -2525348.5 | Z12: Profit Before Tax | AA12: =C12/1000 -> -1608.8816 | AB12: =D12/1000 -> -4800.0729 | AC12: =E12/1000 -> -2427.8611 | AD12: =F12/1000 -> 241.05433 | AE12: =G12/1000 -> 3537.192 | AF12: =H12/1000 -> 8039.6997 | AG12: =I12/1000 -> 13679.392 | AH12: =J12/1000 -> 17243.779 | ... AU12: =W12/1000 -> -2525.3485
B13: Tax | C13: =-IF(C4>'Data Input'!$D$34,IF(SUM($C12:C$12)>0,(SUM($C12:C$12)*'Data Input'!$D$35+SUM(B13:$C$13)),0),0) -> 0 | D13: =-IF(D4>'Data Input'!$D$34,IF(SUM($C12:D$12)>0,(SUM($C12:D$12)*'Data Input'!$D$35+SUM(C13:$C$13)),0),0) -> 0 | E13: =-IF(E4>'Data Input'!$D$34,IF(SUM($C12:E$12)>0,(SUM($C12:E$12)*'Data Input'!$D$35+SUM($C13:D$13)),0),0) -> 0 | F13: =-IF(F4>'Data Input'!$D$34,IF(SUM($C12:F$12)>0,(SUM($C12:F$12)*'Data Input'!$D$35+SUM($C13:E$13)),0),0) -> 0 | G13: =-IF(G4>'Data Input'!$D$34,IF(SUM($C12:G$12)>0,(SUM($C12:G$12)*'Data Input'!$D$35+SUM($C13:F$13)),0),0) -> 0 | H13: =-IF(H4>'Data Input'!$D$34,IF(SUM($C12:H$12)>0,(SUM($C12:H$12)*'Data Input'!$D$35+SUM($C13:G$13)),0),0) -> 0 | I13: =-IF(I4>'Data Input'!$D$34,IF(SUM($C12:I$12)>0,(SUM($C12:I$12)*'Data Input'!$D$35+SUM($C13:H$13)),0),0) -> -5831182.8 | J13: =-IF(J4>'Data Input'!$D$34,IF(SUM($C12:J$12)>0,(SUM($C12:J$12)*'Data Input'!$D$35+SUM($C13:I$13)),0),0) -> -6035322.7 | K13: =-IF(K4>'Data Input'!$D$34,IF(SUM($C12:K$12)>0,(SUM($C12:K$12)*'Data Input'!$D$35+SUM($C13:J$13)),0),0) -> -6823204.6 | L13: =-IF(L4>'Data Input'!$D$34,IF(SUM($C12:L$12)>0,(SUM($C12:L$12)*'Data Input'!$D$35+SUM($C13:K$13)),0),0) -> -7650132.3 | ... W13: =-IF(W4>'Data Input'!$D$34,IF(SUM($C12:W$12)>0,(SUM($C12:W$12)*'Data Input'!$D$35+SUM($C13:V$13)),0),0) -> 883871.97 | Z13: Tax | AA13: =C13/1000 -> 0 | AB13: =D13/1000 -> 0 | AC13: =E13/1000 -> 0 | AD13: =F13/1000 -> 0 | AE13: =G13/1000 -> 0 | AF13: =H13/1000 -> 0 | AG13: =I13/1000 -> -5831.1828 | AH13: =J13/1000 -> -6035.3227 | ... AU13: =W13/1000 -> 883.87197
B14: Net Operating Profit After Tax | C14: =SUM(C12:C13) -> -1608881.6 | D14: =SUM(D12:D13) -> -4800072.9 | E14: =SUM(E12:E13) -> -2427861.1 | F14: =SUM(F12:F13) -> 241054.33 | G14: =SUM(G12:G13) -> 3537192 | H14: =SUM(H12:H13) -> 8039699.7 | I14: =SUM(I12:I13) -> 7848209.3 | J14: =SUM(J12:J13) -> 11208456 | ... W14: =SUM(W12:W13) -> -1641476.5 | Z14: Net Operating Profit After Tax | AA14: =C14/1000 -> -1608.8816 | AB14: =D14/1000 -> -4800.0729 | AC14: =E14/1000 -> -2427.8611 | AD14: =F14/1000 -> 241.05433 | AE14: =G14/1000 -> 3537.192 | AF14: =H14/1000 -> 8039.6997 | AG14: =I14/1000 -> 7848.2093 | AH14: =J14/1000 -> 11208.456 | ... AU14: =W14/1000 -> -1641.4765
B15: Net Accumulated Profit After Tax | C15: =C14 -> -1608881.6 | D15: =D14+C15 -> -6408954.6 | E15: =E14+D15 -> -8836815.7 | F15: =F14+E15 -> -8595761.4 | G15: =G14+F15 -> -5058569.4 | H15: =H14+G15 -> 2981130.3 | I15: =I14+H15 -> 10829340 | J15: =J14+I15 -> 22037796 | K15: =K14+J15 -> 34709462 | ... W15: =W14+V15 -> 2.2764902e+08 | Z15: Net Accumulated Profit | AA15: =C15/1000 -> -1608.8816 | AB15: =D15/1000 -> -6408.9546 | AC15: =E15/1000 -> -8836.8157 | AD15: =F15/1000 -> -8595.7614 | AE15: =G15/1000 -> -5058.5694 | AF15: =H15/1000 -> 2981.1303 | AG15: =I15/1000 -> 10829.34 | AH15: =J15/1000 -> 22037.796 | ... AU15: =W15/1000 -> 227649.02
B16: EBITDA | C16: =C10-C9 -> 0 | D16: =D10-D9 -> -235546.73 | E16: =E10-E9 -> 3196691.7 | F16: =F10-F9 -> 5602074.4 | G16: =G10-G9 -> 8409660.6 | H16: =H10-H9 -> 12502142 | I16: =I10-I9 -> 18011475 | J16: =J10-J9 -> 21437503 | ... W16: =W10-W9 -> 0 | Z16: EBITDA | AA16: =C16/1000 -> 0 | AB16: =D16/1000 -> -235.54673 | AC16: =E16/1000 -> 3196.6917 | AD16: =F16/1000 -> 5602.0744 | AE16: =G16/1000 -> 8409.6606 | AF16: =H16/1000 -> 12502.142 | AG16: =I16/1000 -> 18011.475 | AH16: =J16/1000 -> 21437.503 | ... AU16: =W16/1000 -> 0
B17: EBITDA Margin | C17: =IFERROR(C16/C5,"-") -> - | D17: =IFERROR(D16/D5,"-") -> -0.026035067 | E17: =IFERROR(E16/E5,"-") -> 0.18404455 | F17: =IFERROR(F16/F5,"-") -> 0.2668157 | G17: =IFERROR(G16/G5,"-") -> 0.33851494 | H17: =IFERROR(H16/H5,"-") -> 0.41107751 | I17: =IFERROR(I16/I5,"-") -> 0.48803194 | J17: =IFERROR(J16/J5,"-") -> 0.52043292 | ... W17: =IFERROR(W16/W5,"-") -> - | Z17: EBITDA Margin | AA17: =C17 -> - | AB17: =D17 -> -0.026035067 | AC17: =E17 -> 0.18404455 | AD17: =F17 -> 0.2668157 | AE17: =G17 -> 0.33851494 | AF17: =H17 -> 0.41107751 | AG17: =I17 -> 0.48803194 | AH17: =J17 -> 0.52043292 | ... AU17: =W17 -> -
B20: Cash Flow | Z20: Cash Flow
C21: 0 | D21: 1 | E21: 2 | F21: 3 | G21: 4 | H21: 5 | I21: 6 | J21: 7 | K21: 8 | L21: 9 | M21: 10 | N21: 11 | O21: 12 | P21: 13 | Q21: 14 | R21: 15 | S21: 16 | T21: 17 | U21: 18 | V21: 19 | W21: 20 | AA21: 0 | AB21: 1 | AC21: 2 | AD21: 3 | AE21: 4 | AF21: 5 | AG21: 6 | AH21: 7 | AI21: 8 | AJ21: 9 | AK21: 10 | AL21: 11 | AM21: 12 | AN21: 13 | AO21: 14 | AP21: 15 | AQ21: 16 | AR21: 17 | AS21: 18 | AT21: 19 | AU21: 20
B22: Operating Activities | Z22: Operating Activities
B23: Net Operating Profit after Tax | C23: =C14 -> -1608881.6 | D23: =D14 -> -4800072.9 | E23: =E14 -> -2427861.1 | F23: =F14 -> 241054.33 | G23: =G14 -> 3537192 | H23: =H14 -> 8039699.7 | I23: =I14 -> 7848209.3 | J23: =J14 -> 11208456 | ... W23: =W14 -> -1641476.5 | Z23: Net Operating Profit after Tax | AA23: =C23/1000 -> -1608.8816 | AB23: =D23/1000 -> -4800.0729 | AC23: =E23/1000 -> -2427.8611 | AD23: =F23/1000 -> 241.05433 | AE23: =G23/1000 -> 3537.192 | AF23: =H23/1000 -> 8039.6997 | AG23: =I23/1000 -> 7848.2093 | AH23: =J23/1000 -> 11208.456 | ... AU23: =W23/1000 -> -1641.4765
B24: Depreciation | C24: =-C9 -> 0 | D24: =-D9 -> 1856214.5 | E24: =-E9 -> 2525348.5 | F24: =-F9 -> 2525348.5 | G24: =-G9 -> 2525348.5 | H24: =-H9 -> 2525348.5 | I24: =-I9 -> 2525348.5 | J24: =-J9 -> 2525348.5 | ... W24: =-W9 -> 2525348.5 | Z24: Depreciation | AA24: =C24/1000 -> 0 | AB24: =D24/1000 -> 1856.2145 | AC24: =E24/1000 -> 2525.3485 | AD24: =F24/1000 -> 2525.3485 | AE24: =G24/1000 -> 2525.3485 | AF24: =H24/1000 -> 2525.3485 | AG24: =I24/1000 -> 2525.3485 | AH24: =J24/1000 -> 2525.3485 | ... AU24: =W24/1000 -> 2525.3485
B25: Increase in inventory | D25: =C75-D75 -> -698785.72 | E25: =D75-E75 -> -470283.66 | F25: =E75-F75 -> -114269.81 | G25: =F75-G75 -> -95757.193 | H25: =G75-H75 -> -139165.35 | I25: =H75-I75 -> -133270.91 | J25: =I75-J75 -> -78339.817 | K25: =J75-K75 -> -67801.813 | ... W25: =V75-W75 -> 2502986.6 | Z25: Increase in inventory | AA25: =C25/1000 -> 0 | AB25: =D25/1000 -> -698.78572 | AC25: =E25/1000 -> -470.28366 | AD25: =F25/1000 -> -114.26981 | AE25: =G25/1000 -> -95.757193 | AF25: =H25/1000 -> -139.16535 | AG25: =I25/1000 -> -133.27091 | AH25: =J25/1000 -> -78.339817 | ... AU25: =W25/1000 -> 2502.9866
B26: Increase in accounts receivable | D26: =C76-D76 -> -2714186.2 | E26: =D76-E76 -> 1266759.5 | F26: =E76-F76 -> -302243.77 | G26: =F76-G76 -> -320563.34 | H26: =G76-H76 -> -464191.45 | I26: =H76-I76 -> -541103.53 | J26: =I76-J76 -> -357110.79 | K26: =J76-K76 -> -238186.25 | ... W26: =V76-W76 -> 5264079.3 | Z26: Increase in accounts receivable | AA26: =C26/1000 -> 0 | AB26: =D26/1000 -> -2714.1862 | AC26: =E26/1000 -> 1266.7595 | AD26: =F26/1000 -> -302.24377 | AE26: =G26/1000 -> -320.56334 | AF26: =H26/1000 -> -464.19145 | AG26: =I26/1000 -> -541.10353 | AH26: =J26/1000 -> -357.11079 | ... AU26: =W26/1000 -> 5264.0793
B27: Increase in accounts payable | D27: =D84-C84 -> 582321.43 | E27: =E84-D84 -> 391903.05 | F27: =F84-E84 -> 95224.839 | G27: =G84-F84 -> 79797.661 | H27: =H84-G84 -> 115971.13 | I27: =I84-H84 -> 111059.09 | J27: =J84-I84 -> 65283.181 | K27: =K84-J84 -> 56501.51 | ... W27: =W84-V84 -> -2085822.2 | Z27: Increase in accounts payable | AA27: =C27/1000 -> 0 | AB27: =D27/1000 -> 582.32143 | AC27: =E27/1000 -> 391.90305 | AD27: =F27/1000 -> 95.224839 | AE27: =G27/1000 -> 79.797661 | AF27: =H27/1000 -> 115.97113 | AG27: =I27/1000 -> 111.05909 | AH27: =J27/1000 -> 65.283181 | ... AU27: =W27/1000 -> -2085.8222
B28: Cash Flow From Operations | C28: =SUM(C23:C27) -> -1608881.6 | D28: =SUM(D23:D27) -> -5774508.9 | E28: =SUM(E23:E27) -> 1285866.3 | F28: =SUM(F23:F27) -> 2445114.1 | G28: =SUM(G23:G27) -> 5726017.6 | H28: =SUM(H23:H27) -> 10077662 | I28: =SUM(I23:I27) -> 9810242.4 | J28: =SUM(J23:J27) -> 13363638 | ... W28: =SUM(W23:W27) -> 6565115.7 | Z28: Cash Flow From Operations | AA28: =C28/1000 -> -1608.8816 | AB28: =D28/1000 -> -5774.5089 | AC28: =E28/1000 -> 1285.8663 | AD28: =F28/1000 -> 2445.1141 | AE28: =G28/1000 -> 5726.0176 | AF28: =H28/1000 -> 10077.662 | AG28: =I28/1000 -> 9810.2424 | AH28: =J28/1000 -> 13363.638 | ... AU28: =W28/1000 -> 6565.1157
B29: Financing Activities | Z29: Financing Activities
B30: Equity | C30: ='CAPEX Financing'!C18+'WC Financing'!C23 -> 13407347 | D30: ='CAPEX Financing'!D18+'WC Financing'!D23 -> 4833124.7 | E30: ='CAPEX Financing'!E18+'WC Financing'!E23 -> 2.718339e-138 | F30: ='CAPEX Financing'!F18+'WC Financing'!F23 -> 2.8769344e-138 | G30: ='CAPEX Financing'!G18+'WC Financing'!G23 -> 0 | H30: ='CAPEX Financing'!H18+'WC Financing'!H23 -> 0 | I30: ='CAPEX Financing'!I18+'WC Financing'!I23 -> 0 | J30: ='CAPEX Financing'!J18+'WC Financing'!J23 -> 0 | ... W30: ='CAPEX Financing'!W18+'WC Financing'!W23 -> 0 | Z30: Equity | AA30: =C30/1000 -> 13407.347 | AB30: =D30/1000 -> 4833.1247 | AC30: =E30/1000 -> 2.718339e-141 | AD30: =F30/1000 -> 2.8769344e-141 | AE30: =G30/1000 -> 0 | AF30: =H30/1000 -> 0 | AG30: =I30/1000 -> 0 | AH30: =J30/1000 -> 0 | ... AU30: =W30/1000 -> 0
B31: Loans Received | C31: ='CAPEX Financing'!C19+'WC Financing'!C24 -> 26068347 | D31: ='CAPEX Financing'!D19+'WC Financing'!D24 -> 14591752 | E31: ='CAPEX Financing'!E19+'WC Financing'!E24 -> 3908927.2 | F31: ='CAPEX Financing'!F19+'WC Financing'!F24 -> 2872029.9 | G31: ='CAPEX Financing'!G19+'WC Financing'!G24 -> 0 | H31: ='CAPEX Financing'!H19+'WC Financing'!H24 -> 0 | I31: ='CAPEX Financing'!I19+'WC Financing'!I24 -> 0 | J31: ='CAPEX Financing'!J19+'WC Financing'!J24 -> 0 | ... W31: ='CAPEX Financing'!W19+'WC Financing'!W24 -> 0 | Z31: Loans Received | AA31: =C31/1000 -> 26068.347 | AB31: =D31/1000 -> 14591.752 | AC31: =E31/1000 -> 3908.9272 | AD31: =F31/1000 -> 2872.0299 | AE31: =G31/1000 -> 0 | AF31: =H31/1000 -> 0 | AG31: =I31/1000 -> 0 | AH31: =J31/1000 -> 0 | ... AU31: =W31/1000 -> 0
B32: Principal Payments | C32: =-'CAPEX Financing'!C24-'WC Financing'!C29 -> 0 | D32: =-'CAPEX Financing'!D24-'WC Financing'!D29 -> 0 | E32: =-'CAPEX Financing'!E24-'WC Financing'!E29 -> -5194550.7 | F32: =-'CAPEX Financing'!F24-'WC Financing'!F29 -> -5316645.8 | G32: =-'CAPEX Financing'!G24-'WC Financing'!G29 -> -4873590.2 | H32: =-'CAPEX Financing'!H24-'WC Financing'!H29 -> -2124383.2 | I32: =-'CAPEX Financing'!I24-'WC Financing'!I29 -> -2254742.9 | J32: =-'CAPEX Financing'!J24-'WC Financing'!J29 -> -2393101.9 | ... W32: =-'CAPEX Financing'!W24-'WC Financing'!W29 -> 0 | Z32: Principal Payments | AA32: =C32/1000 -> 0 | AB32: =D32/1000 -> 0 | AC32: =E32/1000 -> -5194.5507 | AD32: =F32/1000 -> -5316.6458 | AE32: =G32/1000 -> -4873.5902 | AF32: =H32/1000 -> -2124.3832 | AG32: =I32/1000 -> -2254.7429 | AH32: =J32/1000 -> -2393.1019 | ... AU32: =W32/1000 -> 0
B33: Fees | C33: =-'CAPEX Financing'!E5 -> -742485.81 | D33: =-'CAPEX Financing'!E6 -> -267653.59 | E33: =-'CAPEX Financing'!E7 -> 0 | F33: =-'CAPEX Financing'!E8 -> 0 | G33: =-'CAPEX Financing'!E9 -> 0 | Z33: Fees | AA33: =C33/1000 -> -742.48581 | AB33: =D33/1000 -> -267.65359 | AC33: =E33/1000 -> 0 | AD33: =F33/1000 -> 0 | AE33: =G33/1000 -> 0 | AF33: =H33/1000 -> 0 | AG33: =I33/1000 -> 0 | AH33: =J33/1000 -> 0 | ... AU33: =W33/1000 -> 0
B34: DSRA | C34: ='CAPEX Financing'!C20+'CAPEX Financing'!C21 -> 746346.89 | D34: ='CAPEX Financing'!D20+'CAPEX Financing'!D21 -> 269047.96 | E34: ='CAPEX Financing'!E20+'CAPEX Financing'!E21 -> 2.584198e-138 | F34: ='CAPEX Financing'!F20+'CAPEX Financing'!F21 -> 2.7349672e-138 | G34: ='CAPEX Financing'!G20+'CAPEX Financing'!G21 -> 0 | H34: ='CAPEX Financing'!H20+'CAPEX Financing'!H21 -> 0 | I34: ='CAPEX Financing'!I20+'CAPEX Financing'!I21 -> 0 | J34: ='CAPEX Financing'!J20+'CAPEX Financing'!J21 -> 0 | ... W34: ='CAPEX Financing'!W20+'CAPEX Financing'!W21 -> 0 | Z34: DSRA | AA34: =C34/1000 -> 746.34689 | AB34: =D34/1000 -> 269.04796 | AC34: =E34/1000 -> 2.584198e-141 | AD34: =F34/1000 -> 2.7349672e-141 | AE34: =G34/1000 -> 0 | AF34: =H34/1000 -> 0 | AG34: =I34/1000 -> 0 | AH34: =J34/1000 -> 0 | ... AU34: =W34/1000 -> 0
B35: Cash Flow from Financing | C35: =SUM(C30:C34) -> 39479555 | D35: =SUM(D30:D34) -> 19426271 | E35: =SUM(E30:E34) -> -1285623.5 | F35: =SUM(F30:F34) -> -2444616 | G35: =SUM(G30:G34) -> -4873590.2 | H35: =SUM(H30:H34) -> -2124383.2 | I35: =SUM(I30:I34) -> -2254742.9 | J35: =SUM(J30:J34) -> -2393101.9 | ... W35: =SUM(W30:W34) -> 0 | Z35: Cash Flow from Financing | AA35: =C35/1000 -> 39479.555 | AB35: =D35/1000 -> 19426.271 | AC35: =E35/1000 -> -1285.6235 | AD35: =F35/1000 -> -2444.616 | AE35: =G35/1000 -> -4873.5902 | AF35: =H35/1000 -> -2124.3832 | AG35: =I35/1000 -> -2254.7429 | AH35: =J35/1000 -> -2393.1019 | ... AU35: =W35/1000 -> 0
B36: Investing Activities | Z36: Investing Activities
B37: Initial Investment | C37: =-'CAPEX Financing'!C16 -> -37124290 | D37: =-'CAPEX Financing'!D16 -> -13382679 | E37: =-'CAPEX Financing'!E16 -> 0 | F37: =-'CAPEX Financing'!F16 -> 0 | G37: =-'CAPEX Financing'!G16 -> 0 | H37: =-'CAPEX Financing'!H16 -> 0 | I37: =-'CAPEX Financing'!I16 -> 0 | J37: =-'CAPEX Financing'!J16 -> 0 | ... W37: =-'CAPEX Financing'!W16 -> 0 | Z37: Initial Investment | AA37: =C37/1000 -> -37124.29 | AB37: =D37/1000 -> -13382.679 | AC37: =E37/1000 -> 0 | AD37: =F37/1000 -> 0 | AE37: =G37/1000 -> 0 | AF37: =H37/1000 -> 0 | AG37: =I37/1000 -> 0 | AH37: =J37/1000 -> 0 | ... AU37: =W37/1000 -> 0
B38: Reinvestment | D38: =-Depreciation!D49*(1+'Data Input'!$D$38)^(D$21-1) -> 0 | E38: =-Depreciation!E49*(1+'Data Input'!$D$38)^(E$21-1) -> 0 | F38: =-Depreciation!F49*(1+'Data Input'!$D$38)^(F$21-1) -> 0 | G38: =-Depreciation!G49*(1+'Data Input'!$D$38)^(G$21-1) -> 0 | H38: =-Depreciation!H49*(1+'Data Input'!$D$38)^(H$21-1) -> 0 | I38: =-Depreciation!I49*(1+'Data Input'!$D$38)^(I$21-1) -> 0 | J38: =-Depreciation!J49*(1+'Data Input'!$D$38)^(J$21-1) -> 0 | K38: =-Depreciation!K49*(1+'Data Input'!$D$38)^(K$21-1) -> 0 | ... W38: =-Depreciation!W49*(1+'Data Input'!$D$38)^(W$21-1) -> 0 | Z38: Reinvestment | AA38: =C38/1000 -> 0 | AB38: =D38/1000 -> 0 | AC38: =E38/1000 -> 0 | AD38: =F38/1000 -> 0 | AE38: =G38/1000 -> 0 | AF38: =H38/1000 -> 0 | AG38: =I38/1000 -> 0 | AH38: =J38/1000 -> 0 | ... AU38: =W38/1000 -> 0
B39: Cash Flow From Investment | C39: =SUM(C37:C38) -> -37124290 | D39: =SUM(D37:D38) -> -13382679 | E39: =SUM(E37:E38) -> 0 | F39: =SUM(F37:F38) -> 0 | G39: =SUM(G37:G38) -> 0 | H39: =SUM(H37:H38) -> 0 | I39: =SUM(I37:I38) -> 0 | J39: =SUM(J37:J38) -> 0 | ... W39: =SUM(W37:W38) -> 0 | Z39: Cash Flow From Investment | AA39: =C39/1000 -> -37124.29 | AB39: =D39/1000 -> -13382.679 | AC39: =E39/1000 -> 0 | AD39: =F39/1000 -> 0 | AE39: =G39/1000 -> 0 | AF39: =H39/1000 -> 0 | AG39: =I39/1000 -> 0 | AH39: =J39/1000 -> 0 | ... AU39: =W39/1000 -> 0
B40: Net Cash Flow | C40: =SUM(C28+C35+C39) -> 746383.52 | D40: =SUM(D28+D35+D39) -> 269083.04 | E40: =SUM(E28+E35+E39) -> 242.77091 | F40: =SUM(F28+F35+F39) -> 498.09615 | G40: =SUM(G28+G35+G39) -> 852427.41 | H40: =SUM(H28+H35+H39) -> 7953279.3 | I40: =SUM(I28+I35+I39) -> 7555499.5 | J40: =SUM(J28+J35+J39) -> 10970536 | ... W40: =SUM(W28+W35+W39) -> 6565115.7 | Z40: Net Cash Flow | AA40: =C40/1000 -> 746.38352 | AB40: =D40/1000 -> 269.08304 | AC40: =E40/1000 -> 0.24277091 | AD40: =F40/1000 -> 0.49809615 | AE40: =G40/1000 -> 852.42741 | AF40: =H40/1000 -> 7953.2793 | AG40: =I40/1000 -> 7555.4995 | AH40: =J40/1000 -> 10970.536 | ... AU40: =W40/1000 -> 6565.1157
B41: Net Accumulated Cash Flow | C41: =C40 -> 746383.52 | D41: =D40+C41 -> 1015466.6 | E41: =E40+D41 -> 1015709.3 | F41: =F40+E41 -> 1016207.4 | G41: =G40+F41 -> 1868634.8 | H41: =H40+G41 -> 9821914.2 | I41: =I40+H41 -> 17377414 | J41: =J40+I41 -> 28347949 | K41: =K40+J41 -> 40755526 | ... W41: =W40+V41 -> 2.6062733e+08 | Z41: Net Accumulated Cash Flow | AA41: =C41/1000 -> 746.38352 | AB41: =D41/1000 -> 1015.4666 | AC41: =E41/1000 -> 1015.7093 | AD41: =F41/1000 -> 1016.2074 | AE41: =G41/1000 -> 1868.6348 | AF41: =H41/1000 -> 9821.9142 | AG41: =I41/1000 -> 17377.414 | AH41: =J41/1000 -> 28347.949 | ... AU41: =W41/1000 -> 260627.33
B42: Net Cash Flow - DSRA | C42: =C40-C34 -> 36.632162 | D42: =D40-D34 -> 35.085878 | E42: =E40-E34 -> 242.77091 | F42: =F40-F34 -> 498.09615 | G42: =G40-G34 -> 852427.41 | H42: =H40-H34 -> 7953279.3 | I42: =I40-I34 -> 7555499.5 | J42: =J40-J34 -> 10970536 | ... W42: =W40-W34 -> 6565115.7 | Z42: Net Cash Flow | AA42: =C42/1000 -> 0.036632162 | AB42: =D42/1000 -> 0.035085878 | AC42: =E42/1000 -> 0.24277091 | AD42: =F42/1000 -> 0.49809615 | AE42: =G42/1000 -> 852.42741 | AF42: =H42/1000 -> 7953.2793 | AG42: =I42/1000 -> 7555.4995 | AH42: =J42/1000 -> 10970.536 | ... AU42: =W42/1000 -> 6565.1157
B43: Net Accumulated Cash Flow - DSRA | C43: =C42 -> 36.632162 | D43: =D42+C43 -> 71.718041 | E43: =E42+D43 -> 314.48895 | F43: =F42+E43 -> 812.5851 | G43: =G42+F43 -> 853239.99 | H43: =H42+G43 -> 8806519.3 | I43: =I42+H43 -> 16362019 | J43: =J42+I43 -> 27332554 | K43: =K42+J43 -> 39740131 | ... W43: =W42+V43 -> 2.6062733e+08 | Z43: Net Accumulated Cash Flow | AA43: =C43/1000 -> 0.036632162 | AB43: =D43/1000 -> 0.071718041 | AC43: =E43/1000 -> 0.31448895 | AD43: =F43/1000 -> 0.8125851 | AE43: =G43/1000 -> 853.23999 | AF43: =H43/1000 -> 8806.5193 | AG43: =I43/1000 -> 16362.019 | AH43: =J43/1000 -> 27332.554 | ... AU43: =W43/1000 -> 260627.33
B46: Free Cash Flow | Z46: Free Cash Flow
C47: 0 | D47: 1 | E47: 2 | F47: 3 | G47: 4 | H47: 5 | I47: 6 | J47: 7 | K47: 8 | L47: 9 | M47: 10 | N47: 11 | O47: 12 | P47: 13 | Q47: 14 | R47: 15 | S47: 16 | T47: 17 | U47: 18 | V47: 19 | W47: 20 | X47: Terminal | AA47: 0 | AB47: 1 | AC47: 2 | AD47: 3 | AE47: 4 | AF47: 5 | AG47: 6 | AH47: 7 | AI47: 8 | AJ47: 9 | AK47: 10 | AL47: 11 | AM47: 12 | AN47: 13 | AO47: 14 | AP47: 15 | AQ47: 16 | AR47: 17 | AS47: 18 | AT47: 19 | AU47: 20
B48: Free Cash Flow to Firm | Z48: Free Cash Flow to Firm
B49: Net Operating Profit after Tax | C49: =C14 -> -1608881.6 | D49: =D14 -> -4800072.9 | E49: =E14 -> -2427861.1 | F49: =F14 -> 241054.33 | G49: =G14 -> 3537192 | H49: =H14 -> 8039699.7 | I49: =I14 -> 7848209.3 | J49: =J14 -> 11208456 | ... W49: =W14 -> -1641476.5 | Z49: Net Operating Profit after Tax | AA49: =C49/1000 -> -1608.8816 | AB49: =D49/1000 -> -4800.0729 | AC49: =E49/1000 -> -2427.8611 | AD49: =F49/1000 -> 241.05433 | AE49: =G49/1000 -> 3537.192 | AF49: =H49/1000 -> 8039.6997 | AG49: =I49/1000 -> 7848.2093 | AH49: =J49/1000 -> 11208.456 | ... AU49: =W49/1000 -> -1641.4765
B50: Depreciation | C50: =C9 -> 0 | D50: =-D9 -> 1856214.5 | E50: =-E9 -> 2525348.5 | F50: =-F9 -> 2525348.5 | G50: =-G9 -> 2525348.5 | H50: =-H9 -> 2525348.5 | I50: =-I9 -> 2525348.5 | J50: =-J9 -> 2525348.5 | K50: =-K9 -> 2525348.5 | ... W50: =-W9 -> 2525348.5 | Z50: Depreciation | AA50: =C50/1000 -> 0 | AB50: =D50/1000 -> 1856.2145 | AC50: =E50/1000 -> 2525.3485 | AD50: =F50/1000 -> 2525.3485 | AE50: =G50/1000 -> 2525.3485 | AF50: =H50/1000 -> 2525.3485 | AG50: =I50/1000 -> 2525.3485 | AH50: =J50/1000 -> 2525.3485 | ... AU50: =W50/1000 -> 2525.3485
B51: Interest (1-tax) | C51: =IF(C13=0,-C11,-C11*(1-'Data Input'!$D$35)) -> 1608881.6 | D51: =IF(D13=0,-D11,-D11*(1-'Data Input'!$D$35)) -> 2708311.7 | E51: =IF(E13=0,-E11,-E11*(1-'Data Input'!$D$35)) -> 3099204.4 | F51: =IF(F13=0,-F11,-F11*(1-'Data Input'!$D$35)) -> 2835671.6 | G51: =IF(G13=0,-G11,-G11*(1-'Data Input'!$D$35)) -> 2347120.1 | H51: =IF(H13=0,-H11,-H11*(1-'Data Input'!$D$35)) -> 1937094.3 | I51: =IF(I13=0,-I11,-I11*(1-'Data Input'!$D$35)) -> 1174377.5 | J51: =IF(J13=0,-J11,-J11*(1-'Data Input'!$D$35)) -> 1084444.1 | ... W51: =IF(W13=0,-W11,-W11*(1-'Data Input'!$D$35)) -> 0 | Z51: Interest (1-tax) | AA51: =C51/1000 -> 1608.8816 | AB51: =D51/1000 -> 2708.3117 | AC51: =E51/1000 -> 3099.2044 | AD51: =F51/1000 -> 2835.6716 | AE51: =G51/1000 -> 2347.1201 | AF51: =H51/1000 -> 1937.0943 | AG51: =I51/1000 -> 1174.3775 | AH51: =J51/1000 -> 1084.4441 | ... AU51: =W51/1000 -> 0
B52: Long-Term Investments | C52: =-SUM(C30:C31)+SUM('CAPEX Financing'!$F$5) -> -37866776 | D52: =-SUM(D30:D31)+SUM('CAPEX Financing'!$F$6) -> -18844884 | E52: =-SUM(E30:E31)+SUM('CAPEX Financing'!$F$7) -> -3908927.2 | F52: =-SUM(F30:F31)+SUM('CAPEX Financing'!$F$8) -> -2872029.9 | G52: =-SUM(G30:G31)+SUM('CAPEX Financing'!$F$9) -> 0 | H52: =-SUM(H30:H31) -> 0 | I52: =-SUM(I30:I31) -> 0 | J52: =-SUM(J30:J31) -> 0 | K52: =-SUM(K30:K31) -> 0 | L52: =-SUM(L30:L31) -> 0 | M52: =-SUM(M30:M31) -> 0 | N52: =-SUM(N30:N31) -> 0 | O52: =-SUM(O30:O31) -> 0 | ... W52: =-SUM(W30:W31) -> 0 | Z52: Long-Term Investments | AA52: =C52/1000 -> -37866.776 | AB52: =D52/1000 -> -18844.884 | AC52: =E52/1000 -> -3908.9272 | AD52: =F52/1000 -> -2872.0299 | AE52: =G52/1000 -> 0 | AF52: =H52/1000 -> 0 | AG52: =I52/1000 -> 0 | AH52: =J52/1000 -> 0 | ... AU52: =W52/1000 -> 0
B53: DSRA | C53: =-C34 -> -746346.89 | D53: =-D34 -> -269047.96 | E53: =-E34 -> -2.584198e-138 | F53: =-F34 -> -2.7349672e-138 | G53: =-G34 -> 0 | H53: =-H34 -> 0 | I53: =-I34 -> 0 | J53: =-J34 -> 0 | ... W53: =-W34 -> 0 | Z53: DSRA | AA53: =C53/1000 -> -746.34689 | AB53: =D53/1000 -> -269.04796 | AC53: =E53/1000 -> -2.584198e-141 | AD53: =F53/1000 -> -2.7349672e-141 | AE53: =G53/1000 -> 0 | AF53: =H53/1000 -> 0 | AG53: =I53/1000 -> 0 | AH53: =J53/1000 -> 0 | ... AU53: =W53/1000 -> 0
B54: Free Cash Flow to Firm | C54: =SUM(C49:C53) -> -38613123 | D54: =SUM(D49:D53) -> -19349478 | E54: =SUM(E49:E53) -> -712235.45 | F54: =SUM(F49:F53) -> 2730044.6 | G54: =SUM(G49:G53) -> 8409660.6 | H54: =SUM(H49:H53) -> 12502142 | I54: =SUM(I49:I53) -> 11547935 | J54: =SUM(J49:J53) -> 14818249 | ... W54: =SUM(W49:W53) -> 883871.97 | X54: =(W54*(1+'Data Input'!$D$41))/('Data Input'!$D$40-'Data Input'!$D$41) -> 22920748 | Z54: Free Cash Flow to Firm | AA54: =C54/1000 -> -38613.123 | AB54: =D54/1000 -> -19349.478 | AC54: =E54/1000 -> -712.23545 | AD54: =F54/1000 -> 2730.0446 | AE54: =G54/1000 -> 8409.6606 | AF54: =H54/1000 -> 12502.142 | AG54: =I54/1000 -> 11547.935 | AH54: =J54/1000 -> 14818.249 | ... AU54: =W54/1000 -> 883.87197
B55: Cumulative FCFF | C55: =C54 -> -38613123 | D55: =D54+C55 -> -57962601 | E55: =E54+D55 -> -58674837 | F55: =F54+E55 -> -55944792 | G55: =G54+F55 -> -47535132 | H55: =H54+G55 -> -35032989 | I55: =I54+H55 -> -23485054 | J55: =J54+I55 -> -8666804.8 | K55: =K54+J55 -> 7519201.4 | ... X55: =X54+W55 -> 2.5656597e+08 | Z55: Cumulative FCFF | AA55: =C55/1000 -> -38613.123 | AB55: =D55/1000 -> -57962.601 | AC55: =E55/1000 -> -58674.837 | AD55: =F55/1000 -> -55944.792 | AE55: =G55/1000 -> -47535.132 | AF55: =H55/1000 -> -35032.989 | AG55: =I55/1000 -> -23485.054 | AH55: =J55/1000 -> -8666.8048 | ... AU55: =W55/1000 -> 233645.23
B56: DCF to Firm at WACC | C56: =C54/(1+'Data Input'!$D$40)^C47 -> -38613123 | D56: =D54/(1+'Data Input'!$D$40)^D47 -> -18265713 | E56: =E54/(1+'Data Input'!$D$40)^E47 -> -634685.11 | F56: =F54/(1+'Data Input'!$D$40)^F47 -> 2296528.4 | G56: =G54/(1+'Data Input'!$D$40)^G47 -> 6678023.1 | H56: =H54/(1+'Data Input'!$D$40)^H47 -> 9371762 | I56: =I54/(1+'Data Input'!$D$40)^I47 -> 8171626.5 | J56: =J54/(1+'Data Input'!$D$40)^J47 -> 9898478 | ... W56: =W54/(1+'Data Input'!$D$40)^W47 -> 279085.07 | X56: =(W56*(1+'Data Input'!$D$41))/('Data Input'!$D$40-'Data Input'!$D$41) -> 7237290.7 | Z56: DCF to Firm at WACC | AA56: =C56/1000 -> -38613.123 | AB56: =D56/1000 -> -18265.713 | AC56: =E56/1000 -> -634.68511 | AD56: =F56/1000 -> 2296.5284 | AE56: =G56/1000 -> 6678.0231 | AF56: =H56/1000 -> 9371.762 | AG56: =I56/1000 -> 8171.6265 | AH56: =J56/1000 -> 9898.478 | ... AU56: =W56/1000 -> 279.08507
B57: Cumulative DCF to Firm | C57: =C56 -> -38613123 | D57: =D56+C57 -> -56878836 | E57: =E56+D57 -> -57513521 | F57: =F56+E57 -> -55216992 | G57: =G56+F57 -> -48538969 | H57: =H56+G57 -> -39167207 | I57: =I56+H57 -> -30995581 | J57: =J56+I57 -> -21097103 | K57: =K56+J57 -> -10890561 | ... X57: =X56+W57 -> 97128474 | Z57: Cumulative DCF to Firm | AA57: =C57/1000 -> -38613.123 | AB57: =D57/1000 -> -56878.836 | AC57: =E57/1000 -> -57513.521 | AD57: =F57/1000 -> -55216.992 | AE57: =G57/1000 -> -48538.969 | AF57: =H57/1000 -> -39167.207 | AG57: =I57/1000 -> -30995.581 | AH57: =J57/1000 -> -21097.103 | ... AU57: =W57/1000 -> 89891.184
B58: Free Cash Flow to Equity | Z58: Free Cash Flow to Equity
B59: Net Operating Profit after Tax | C59: =C49 -> -1608881.6 | D59: =D49 -> -4800072.9 | E59: =E49 -> -2427861.1 | F59: =F49 -> 241054.33 | G59: =G49 -> 3537192 | H59: =H49 -> 8039699.7 | I59: =I49 -> 7848209.3 | J59: =J49 -> 11208456 | ... W59: =W49 -> -1641476.5 | Z59: Net Operating Profit after Tax | AA59: =C59/1000 -> -1608.8816 | AB59: =D59/1000 -> -4800.0729 | AC59: =E59/1000 -> -2427.8611 | AD59: =F59/1000 -> 241.05433 | AE59: =G59/1000 -> 3537.192 | AF59: =H59/1000 -> 8039.6997 | AG59: =I59/1000 -> 7848.2093 | AH59: =J59/1000 -> 11208.456 | ... AU59: =W59/1000 -> -1641.4765
B60: Depreciation | C60: =C50 -> 0 | D60: =D50 -> 1856214.5 | E60: =E50 -> 2525348.5 | F60: =F50 -> 2525348.5 | G60: =G50 -> 2525348.5 | H60: =H50 -> 2525348.5 | I60: =I50 -> 2525348.5 | J60: =J50 -> 2525348.5 | ... W60: =W50 -> 2525348.5 | Z60: Depreciation | AA60: =C60/1000 -> 0 | AB60: =D60/1000 -> 1856.2145 | AC60: =E60/1000 -> 2525.3485 | AD60: =F60/1000 -> 2525.3485 | AE60: =G60/1000 -> 2525.3485 | AF60: =H60/1000 -> 2525.3485 | AG60: =I60/1000 -> 2525.3485 | AH60: =J60/1000 -> 2525.3485 | ... AU60: =W60/1000 -> 2525.3485
B61: Long-Term Investments | C61: =-SUM(C30:C31)+SUM('CAPEX Financing'!$F$5)+'WC Financing'!C24 -> -37866776 | D61: =-SUM(D30:D31)+SUM('CAPEX Financing'!$F$6)+'WC Financing'!D24 -> -13650333 | E61: =-SUM(E30:E31)+SUM('CAPEX Financing'!$F$7)+'WC Financing'!E24 -> 0 | F61: =-SUM(F30:F31)+SUM('CAPEX Financing'!$F$8)+'WC Financing'!F24 -> 0 | G61: =-SUM(G30:G31)+SUM('CAPEX Financing'!$F$9)+'WC Financing'!G24 -> 0 | H61: =-SUM(H30:H31)+'WC Financing'!H24 -> 0 | I61: =-SUM(I30:I31)+'WC Financing'!I24 -> 0 | J61: =-SUM(J30:J31)+'WC Financing'!J24 -> 0 | K61: =-SUM(K30:K31)+'WC Financing'!K24 -> 0 | L61: =-SUM(L30:L31)+'WC Financing'!L24 -> 0 | M61: =-SUM(M30:M31)+'WC Financing'!M24 -> 0 | N61: =-SUM(N30:N31)+'WC Financing'!N24 -> 0 | O61: =-SUM(O30:O31)+'WC Financing'!O24 -> 0 | ... W61: =-SUM(W30:W31)+'WC Financing'!W24 -> 0 | Z61: Long-Term Investments | AA61: =C61/1000 -> -37866.776 | AB61: =D61/1000 -> -13650.333 | AC61: =E61/1000 -> 0 | AD61: =F61/1000 -> 0 | AE61: =G61/1000 -> 0 | AF61: =H61/1000 -> 0 | AG61: =I61/1000 -> 0 | AH61: =J61/1000 -> 0 | ... AU61: =W61/1000 -> 0
B62: DSRA | C62: =C53 -> -746346.89 | D62: =D53 -> -269047.96 | E62: =E53 -> -2.584198e-138 | F62: =F53 -> -2.7349672e-138 | G62: =G53 -> 0 | H62: =H53 -> 0 | I62: =I53 -> 0 | J62: =J53 -> 0 | ... W62: =W53 -> 0 | Z62: DSRA | AA62: =C62/1000 -> -746.34689 | AB62: =D62/1000 -> -269.04796 | AC62: =E62/1000 -> -2.584198e-141 | AD62: =F62/1000 -> -2.7349672e-141 | AE62: =G62/1000 -> 0 | AF62: =H62/1000 -> 0 | AG62: =I62/1000 -> 0 | AH62: =J62/1000 -> 0 | ... AU62: =W62/1000 -> 0
B63: New Debt | C63: =C31+C34 -> 26814694 | D63: =D31+D34 -> 14860800 | E63: =E31+E34 -> 3908927.2 | F63: =F31+F34 -> 2872029.9 | G63: =G31+G34 -> 0 | H63: =H31+H34 -> 0 | I63: =I31+I34 -> 0 | J63: =J31+J34 -> 0 | ... W63: =W31+W34 -> 0 | Z63: New Debt | AA63: =C63/1000 -> 26814.694 | AB63: =D63/1000 -> 14860.8 | AC63: =E63/1000 -> 3908.9272 | AD63: =F63/1000 -> 2872.0299 | AE63: =G63/1000 -> 0 | AF63: =H63/1000 -> 0 | AG63: =I63/1000 -> 0 | AH63: =J63/1000 -> 0 | ... AU63: =W63/1000 -> 0
B64: Debt Repayment | C64: =C32 -> 0 | D64: =D32 -> 0 | E64: =E32 -> -5194550.7 | F64: =F32 -> -5316645.8 | G64: =G32 -> -4873590.2 | H64: =H32 -> -2124383.2 | I64: =I32 -> -2254742.9 | J64: =J32 -> -2393101.9 | ... W64: =W32 -> 0 | Z64: Debt Repayment | AA64: =C64/1000 -> 0 | AB64: =D64/1000 -> 0 | AC64: =E64/1000 -> -5194.5507 | AD64: =F64/1000 -> -5316.6458 | AE64: =G64/1000 -> -4873.5902 | AF64: =H64/1000 -> -2124.3832 | AG64: =I64/1000 -> -2254.7429 | AH64: =J64/1000 -> -2393.1019 | ... AU64: =W64/1000 -> 0
B65: Free Cash Flow to Equity | C65: =SUM(C58:C64) -> -13407310 | D65: =SUM(D58:D64) -> -2002439.1 | E65: =SUM(E58:E64) -> -1188136.2 | F65: =SUM(F58:F64) -> 321786.84 | G65: =SUM(G58:G64) -> 1188950.3 | H65: =SUM(H58:H64) -> 8440665 | I65: =SUM(I58:I64) -> 8118814.9 | J65: =SUM(J58:J64) -> 11340703 | ... W65: =SUM(W58:W64) -> 883871.97 | X65: =(W65*(1+'Data Input'!$D$41))/('Data Input'!$D$40-'Data Input'!$D$41) -> 22920748 | Z65: Cash Flow to Equity | AA65: =C65/1000 -> -13407.31 | AB65: =D65/1000 -> -2002.4391 | AC65: =E65/1000 -> -1188.1362 | AD65: =F65/1000 -> 321.78684 | AE65: =G65/1000 -> 1188.9503 | AF65: =H65/1000 -> 8440.665 | AG65: =I65/1000 -> 8118.8149 | AH65: =J65/1000 -> 11340.703 | ... AU65: =W65/1000 -> 883.87197
B66: Cumulative Cash Flow to Equity | C66: =C65 -> -13407310 | D66: =D65+C66 -> -15409750 | E66: =E65+D66 -> -16597886 | F66: =F65+E66 -> -16276099 | G66: =G65+F66 -> -15087149 | H66: =H65+G66 -> -6646483.6 | I66: =I65+H66 -> 1472331.2 | J66: =J65+I66 -> 12813034 | K66: =K65+J66 -> 25470097 | ... X66: =X65+W66 -> 2.6530761e+08 | Z66: Cumulative Cash Flow to Equity | AA66: =C66/1000 -> -13407.31 | AB66: =D66/1000 -> -15409.75 | AC66: =E66/1000 -> -16597.886 | AD66: =F66/1000 -> -16276.099 | AE66: =G66/1000 -> -15087.149 | AF66: =H66/1000 -> -6646.4836 | AG66: =I66/1000 -> 1472.3312 | AH66: =J66/1000 -> 12813.034 | ... AU66: =W66/1000 -> 242386.86
B67: DCF to Equity at WACC | C67: =C65/(1+'Data Input'!$D$40)^C47 -> -13407310 | D67: =D65/(1+'Data Input'!$D$40)^D47 -> -1890282.4 | E67: =E65/(1+'Data Input'!$D$40)^E47 -> -1058768.3 | F67: =F65/(1+'Data Input'!$D$40)^F47 -> 270688.85 | G67: =G65/(1+'Data Input'!$D$40)^G47 -> 944132.92 | H67: =H65/(1+'Data Input'!$D$40)^H47 -> 6327227.8 | I67: =I65/(1+'Data Input'!$D$40)^I47 -> 5745089.6 | J67: =J65/(1+'Data Input'!$D$40)^J47 -> 7575503.7 | ... W67: =W65/(1+'Data Input'!$D$40)^W47 -> 279085.07 | X67: =(W67*(1+'Data Input'!$D$41))/('Data Input'!$D$40-'Data Input'!$D$41) -> 7237290.7 | Z67: DCF to Equity at WACC | AA67: =C67/1000 -> -13407.31 | AB67: =D67/1000 -> -1890.2824 | AC67: =E67/1000 -> -1058.7683 | AD67: =F67/1000 -> 270.68885 | AE67: =G67/1000 -> 944.13292 | AF67: =H67/1000 -> 6327.2278 | AG67: =I67/1000 -> 5745.0896 | AH67: =J67/1000 -> 7575.5037 | ... AU67: =W67/1000 -> 279.08507
B68: Cumulative DCF to Equity | C68: =C67 -> -13407310 | D68: =D67+C68 -> -15297593 | E68: =E67+D68 -> -16356361 | F68: =F67+E68 -> -16085672 | G68: =G67+F68 -> -15141539 | H68: =H67+G68 -> -8814311.5 | I68: =I67+H68 -> -3069221.9 | J68: =J67+I68 -> 4506281.8 | K68: =K67+J68 -> 12487549 | ... X68: =X67+W68 -> 1.1539196e+08 | Z68: Cumulative DCF to Equity | AA68: =C68/1000 -> -13407.31 | AB68: =D68/1000 -> -15297.593 | AC68: =E68/1000 -> -16356.361 | AD68: =F68/1000 -> -16085.672 | AE68: =G68/1000 -> -15141.539 | AF68: =H68/1000 -> -8814.3115 | AG68: =I68/1000 -> -3069.2219 | AH68: =J68/1000 -> 4506.2818 | ... AU68: =W68/1000 -> 108154.67
B71: Balance of Payments | Z71: Balance of Payments
C72: 0 | D72: 1 | E72: 2 | F72: 3 | G72: 4 | H72: 5 | I72: 6 | J72: 7 | K72: 8 | L72: 9 | M72: 10 | N72: 11 | O72: 12 | P72: 13 | Q72: 14 | R72: 15 | S72: 16 | T72: 17 | U72: 18 | V72: 19 | W72: 20 | AA72: 0 | AB72: 1 | AC72: 2 | AD72: 3 | AE72: 4 | AF72: 5 | AG72: 6 | AH72: 7 | AI72: 8 | AJ72: 9 | AK72: 10 | AL72: 11 | AM72: 12 | AN72: 13 | AO72: 14 | AP72: 15 | AQ72: 16 | AR72: 17 | AS72: 18 | AT72: 19 | AU72: 20
B73: Assets | Z73: Assets
B74: Cash | C74: =Fin.Statements!C41-C80-SUM('CAPEX Financing'!$C$21:C21) -> 36.632162 | D74: =Fin.Statements!D41-D80-SUM('CAPEX Financing'!$C$21:D21) -> 71.718041 | E74: =Fin.Statements!E41-E80-SUM('CAPEX Financing'!$C$21:E21) -> 314.48895 | F74: =Fin.Statements!F41-F80-SUM('CAPEX Financing'!$C$21:F21) -> 812.5851 | G74: =Fin.Statements!G41-G80-SUM('CAPEX Financing'!$C$21:G21) -> 853239.99 | H74: =Fin.Statements!H41-H80-SUM('CAPEX Financing'!$C$21:H21) -> 8806519.3 | I74: =Fin.Statements!I41-I80-SUM('CAPEX Financing'!$C$21:I21) -> 16362019 | J74: =Fin.Statements!J41-J80-SUM('CAPEX Financing'!$C$21:J21) -> 27332554 | ... W74: =Fin.Statements!W41-W80-SUM('CAPEX Financing'!$C$21:W21) -> 2.6164273e+08 | Z74: Cash | AA74: =C74/1000 -> 0.036632162 | AB74: =D74/1000 -> 0.071718041 | AC74: =E74/1000 -> 0.31448895 | AD74: =F74/1000 -> 0.8125851 | AE74: =G74/1000 -> 853.23999 | AF74: =H74/1000 -> 8806.5193 | AG74: =I74/1000 -> 16362.019 | AH74: =J74/1000 -> 27332.554 | ... AU74: =W74/1000 -> 261642.73
B75: Inventory | D75: =-D6*'Data Input'!D$45 -> 698785.72 | E75: =-E6*'Data Input'!E$45 -> 1169069.4 | F75: =-F6*'Data Input'!F$45 -> 1283339.2 | G75: =-G6*'Data Input'!G$45 -> 1379096.4 | H75: =-H6*'Data Input'!H$45 -> 1518261.7 | I75: =-I6*'Data Input'!I$45 -> 1651532.6 | J75: =-J6*'Data Input'!J$45 -> 1729872.5 | K75: =-K6*'Data Input'!K$45 -> 1797674.3 | ... N75: =-N6*'Data Input'!N$45 -> 1977745.4 | O75: =-O6*'Data Input'!$O$45 -> 2035157.2 | P75: =-P6*'Data Input'!$O$45 -> 2096211.9 | Q75: =-Q6*'Data Input'!$O$45 -> 2159098.2 | R75: =-R6*'Data Input'!$O$45 -> 2223871.2 | S75: =-S6*'Data Input'!$O$45 -> 2290587.3 | T75: =-T6*'Data Input'!$O$45 -> 2359304.9 | U75: =-U6*'Data Input'!$O$45 -> 2430084.1 | V75: =-V6*'Data Input'!$O$45 -> 2502986.6 | W75: =-W6*'Data Input'!$O$45 -> 0 | Z75: Inventory | AA75: =C75/1000 -> 0 | AB75: =D75/1000 -> 698.78572 | AC75: =E75/1000 -> 1169.0694 | AD75: =F75/1000 -> 1283.3392 | AE75: =G75/1000 -> 1379.0964 | AF75: =H75/1000 -> 1518.2617 | AG75: =I75/1000 -> 1651.5326 | AH75: =J75/1000 -> 1729.8725 | ... AU75: =W75/1000 -> 0
B76: Accounts Receivable | D76: =D5*'Data Input'!D$46 -> 2714186.2 | E76: =E5*'Data Input'!E$46 -> 1447426.6 | F76: =F5*'Data Input'!F$46 -> 1749670.4 | G76: =G5*'Data Input'!G$46 -> 2070233.7 | H76: =H5*'Data Input'!H$46 -> 2534425.2 | I76: =I5*'Data Input'!I$46 -> 3075528.7 | J76: =J5*'Data Input'!J$46 -> 3432639.5 | K76: =K5*'Data Input'!K$46 -> 3670825.8 | ... N76: =N5*'Data Input'!N$46 -> 4156444.2 | O76: =O5*'Data Input'!$O$46 -> 4280178.2 | P76: =P5*'Data Input'!$O$46 -> 4408583.5 | Q76: =Q5*'Data Input'!$O$46 -> 4540841 | R76: =R5*'Data Input'!$O$46 -> 4677066.3 | S76: =S5*'Data Input'!$O$46 -> 4817378.3 | T76: =T5*'Data Input'!$O$46 -> 4961899.6 | U76: =U5*'Data Input'!$O$46 -> 5110756.6 | V76: =V5*'Data Input'!$O$46 -> 5264079.3 | W76: =W5*'Data Input'!$O$46 -> 0 | Z76: Accounts Receivable | AA76: =C76/1000 -> 0 | AB76: =D76/1000 -> 2714.1862 | AC76: =E76/1000 -> 1447.4266 | AD76: =F76/1000 -> 1749.6704 | AE76: =G76/1000 -> 2070.2337 | AF76: =H76/1000 -> 2534.4252 | AG76: =I76/1000 -> 3075.5287 | AH76: =J76/1000 -> 3432.6395 | ... AU76: =W76/1000 -> 0
B77: Total Current assets | C77: =SUM(C74:C76) -> 36.632162 | D77: =SUM(D74:D76) -> 3413043.6 | E77: =SUM(E74:E76) -> 2616810.5 | F77: =SUM(F74:F76) -> 3033822.2 | G77: =SUM(G74:G76) -> 4302570.1 | H77: =SUM(H74:H76) -> 12859206 | I77: =SUM(I74:I76) -> 21089080 | J77: =SUM(J74:J76) -> 32495066 | ... W77: =SUM(W74:W76) -> 2.6164273e+08 | Z77: Total Current assets | AA77: =C77/1000 -> 0.036632162 | AB77: =D77/1000 -> 3413.0436 | AC77: =E77/1000 -> 2616.8105 | AD77: =F77/1000 -> 3033.8222 | AE77: =G77/1000 -> 4302.5701 | AF77: =H77/1000 -> 12859.206 | AG77: =I77/1000 -> 21089.08 | AH77: =J77/1000 -> 32495.066 | ... AU77: =W77/1000 -> 261642.73
B78: Fixed Assets | C78: =-C39 -> 37124290 | D78: =C78-D39 -> 50506970 | E78: =D78-E39 -> 50506970 | F78: =E78-F39 -> 50506970 | G78: =F78-G39 -> 50506970 | H78: =G78-H39 -> 50506970 | I78: =H78-I39 -> 50506970 | J78: =I78-J39 -> 50506970 | K78: =J78-K39 -> 50506970 | ... W78: =V78-W39 -> 50506970 | Z78: Fixed Assets | AA78: =C78/1000 -> 37124.29 | AB78: =D78/1000 -> 50506.97 | AC78: =E78/1000 -> 50506.97 | AD78: =F78/1000 -> 50506.97 | AE78: =G78/1000 -> 50506.97 | AF78: =H78/1000 -> 50506.97 | AG78: =I78/1000 -> 50506.97 | AH78: =J78/1000 -> 50506.97 | ... AU78: =W78/1000 -> 50506.97
B79: Accumulated Depreciation | C79: =C9 -> 0 | D79: =D9+C79 -> -1856214.5 | E79: =E9+D79 -> -4381563 | F79: =F9+E79 -> -6906911.5 | G79: =G9+F79 -> -9432259.9 | H79: =H9+G79 -> -11957608 | I79: =I9+H79 -> -14482957 | J79: =J9+I79 -> -17008305 | K79: =K9+J79 -> -19533654 | ... W79: =W9+V79 -> -49837836 | Z79: Accumulated Depreciation | AA79: =C79/1000 -> 0 | AB79: =D79/1000 -> -1856.2145 | AC79: =E79/1000 -> -4381.563 | AD79: =F79/1000 -> -6906.9115 | AE79: =G79/1000 -> -9432.2599 | AF79: =H79/1000 -> -11957.608 | AG79: =I79/1000 -> -14482.957 | AH79: =J79/1000 -> -17008.305 | ... AU79: =W79/1000 -> -49837.836
B80: DSRA | C80: =C34 -> 746346.89 | D80: =D34+C80 -> 1015394.8 | E80: =E34+D80 -> 1015394.8 | F80: =F34+E80 -> 1015394.8 | G80: =G34+F80 -> 1015394.8 | H80: =H34+G80 -> 1015394.8 | I80: =I34+H80 -> 1015394.8 | J80: =J34+I80 -> 1015394.8 | K80: =K34+J80 -> 1015394.8 | ... W80: =W34+V80 -> -5.3191652e-138 | Z80: DSRA | AA80: =C80/1000 -> 746.34689 | AB80: =D80/1000 -> 1015.3948 | AC80: =E80/1000 -> 1015.3948 | AD80: =F80/1000 -> 1015.3948 | AE80: =G80/1000 -> 1015.3948 | AF80: =H80/1000 -> 1015.3948 | AG80: =I80/1000 -> 1015.3948 | AH80: =J80/1000 -> 1015.3948 | ... AU80: =W80/1000 -> -5.3191652e-141
B81: Total Long-Term Assets | C81: =SUM(C78:C80) -> 37870637 | D81: =SUM(D78:D80) -> 49666150 | E81: =SUM(E78:E80) -> 47140801 | F81: =SUM(F78:F80) -> 44615453 | G81: =SUM(G78:G80) -> 42090104 | H81: =SUM(H78:H80) -> 39564756 | I81: =SUM(I78:I80) -> 37039407 | J81: =SUM(J78:J80) -> 34514059 | ... W81: =SUM(W78:W80) -> 669133.96 | Z81: Total Long-Term Assets | AA81: =C81/1000 -> 37870.637 | AB81: =D81/1000 -> 49666.15 | AC81: =E81/1000 -> 47140.801 | AD81: =F81/1000 -> 44615.453 | AE81: =G81/1000 -> 42090.104 | AF81: =H81/1000 -> 39564.756 | AG81: =I81/1000 -> 37039.407 | AH81: =J81/1000 -> 34514.059 | ... AU81: =W81/1000 -> 669.13396
B82: Total Assets | C82: =SUM(C77,C81) -> 37870674 | D82: =SUM(D77,D81) -> 53079193 | E82: =SUM(E77,E81) -> 49757612 | F82: =SUM(F77,F81) -> 47649275 | G82: =SUM(G77,G81) -> 46392675 | H82: =SUM(H77,H81) -> 52423962 | I82: =SUM(I77,I81) -> 58128488 | J82: =SUM(J77,J81) -> 67009125 | ... W82: =SUM(W77,W81) -> 2.6231186e+08 | Z82: Total Assets | AA82: =C82/1000 -> 37870.674 | AB82: =D82/1000 -> 53079.193 | AC82: =E82/1000 -> 49757.612 | AD82: =F82/1000 -> 47649.275 | AE82: =G82/1000 -> 46392.675 | AF82: =H82/1000 -> 52423.962 | AG82: =I82/1000 -> 58128.488 | AH82: =J82/1000 -> 67009.125 | ... AU82: =W82/1000 -> 262311.86
B83: Liabilities & Shareholders' Equity | Z83: Liabilities & Shareholders' Equity
B84: Accounts Payable | D84: =-'Data Input'!D$47*D6 -> 582321.43 | E84: =-'Data Input'!E$47*E6 -> 974224.49 | F84: =-'Data Input'!F$47*F6 -> 1069449.3 | G84: =-'Data Input'!G$47*G6 -> 1149247 | H84: =-'Data Input'!H$47*H6 -> 1265218.1 | I84: =-'Data Input'!I$47*I6 -> 1376277.2 | J84: =-'Data Input'!J$47*J6 -> 1441560.4 | K84: =-'Data Input'!K$47*K6 -> 1498061.9 | ... N84: =-'Data Input'!N$47*N6 -> 1648121.2 | O84: =-'Data Input'!$O$47*O6 -> 1695964.3 | P84: =-'Data Input'!$O$47*P6 -> 1746843.2 | Q84: =-'Data Input'!$O$47*Q6 -> 1799248.5 | R84: =-'Data Input'!$O$47*R6 -> 1853226 | S84: =-'Data Input'!$O$47*S6 -> 1908822.8 | T84: =-'Data Input'!$O$47*T6 -> 1966087.4 | U84: =-'Data Input'!$O$47*U6 -> 2025070.1 | V84: =-'Data Input'!$O$47*V6 -> 2085822.2 | W84: =-'Data Input'!$O$47*W6 -> 0 | Z84: Accounts Payable | AA84: =C84/1000 -> 0 | AB84: =D84/1000 -> 582.32143 | AC84: =E84/1000 -> 974.22449 | AD84: =F84/1000 -> 1069.4493 | AE84: =G84/1000 -> 1149.247 | AF84: =H84/1000 -> 1265.2181 | AG84: =I84/1000 -> 1376.2772 | AH84: =J84/1000 -> 1441.5604 | ... AU84: =W84/1000 -> 0
B85: Current portion of long-term debt | C85: ='CAPEX Financing'!C26+'WC Financing'!C31 -> 0 | D85: ='CAPEX Financing'!D26+'WC Financing'!D31 -> 5194550.7 | E85: ='CAPEX Financing'!E26+'WC Financing'!E31 -> 5316645.8 | F85: ='CAPEX Financing'!F26+'WC Financing'!F31 -> 4873590.2 | G85: ='CAPEX Financing'!G26+'WC Financing'!G31 -> 2124383.2 | H85: ='CAPEX Financing'!H26+'WC Financing'!H31 -> 2254742.9 | I85: ='CAPEX Financing'!I26+'WC Financing'!I31 -> 2393101.9 | J85: ='CAPEX Financing'!J26+'WC Financing'!J31 -> 2539951.1 | ... W85: ='CAPEX Financing'!W26+'WC Financing'!W31 -> 0 | Z85: Current portion of long-term debt | AA85: =C85/1000 -> 0 | AB85: =D85/1000 -> 5194.5507 | AC85: =E85/1000 -> 5316.6458 | AD85: =F85/1000 -> 4873.5902 | AE85: =G85/1000 -> 2124.3832 | AF85: =H85/1000 -> 2254.7429 | AG85: =I85/1000 -> 2393.1019 | AH85: =J85/1000 -> 2539.9511 | ... AU85: =W85/1000 -> 0
B86: Total Current Liabilities | C86: =SUM(C84:C85) -> 0 | D86: =SUM(D84:D85) -> 5776872.1 | E86: =SUM(E84:E85) -> 6290870.3 | F86: =SUM(F84:F85) -> 5943039.5 | G86: =SUM(G84:G85) -> 3273630.2 | H86: =SUM(H84:H85) -> 3519961 | I86: =SUM(I84:I85) -> 3769379.1 | J86: =SUM(J84:J85) -> 3981511.5 | ... W86: =SUM(W84:W85) -> 0 | Z86: Total Current Liabilities | AA86: =C86/1000 -> 0 | AB86: =D86/1000 -> 5776.8721 | AC86: =E86/1000 -> 6290.8703 | AD86: =F86/1000 -> 5943.0395 | AE86: =G86/1000 -> 3273.6302 | AF86: =H86/1000 -> 3519.961 | AG86: =I86/1000 -> 3769.3791 | AH86: =J86/1000 -> 3981.5115 | ... AU86: =W86/1000 -> 0
B87: Long Term Liabilities | C87: ='CAPEX Financing'!C27+'WC Financing'!C32 -> 26814694 | D87: ='CAPEX Financing'!D27+'WC Financing'!D32 -> 36480944 | E87: ='CAPEX Financing'!E27+'WC Financing'!E32 -> 35073225 | F87: ='CAPEX Financing'!F27+'WC Financing'!F32 -> 33071665 | G87: ='CAPEX Financing'!G27+'WC Financing'!G32 -> 30947281 | H87: ='CAPEX Financing'!H27+'WC Financing'!H32 -> 28692539 | I87: ='CAPEX Financing'!I27+'WC Financing'!I32 -> 26299437 | J87: ='CAPEX Financing'!J27+'WC Financing'!J32 -> 23759486 | ... W87: ='CAPEX Financing'!W27+'WC Financing'!W32 -> 17432510 | Z87: Long Term Liabilities | AA87: =C87/1000 -> 26814.694 | AB87: =D87/1000 -> 36480.944 | AC87: =E87/1000 -> 35073.225 | AD87: =F87/1000 -> 33071.665 | AE87: =G87/1000 -> 30947.281 | AF87: =H87/1000 -> 28692.539 | AG87: =I87/1000 -> 26299.437 | AH87: =J87/1000 -> 23759.486 | ... AU87: =W87/1000 -> 17432.51
B88: Total Long Term Liabilities | C88: =SUM(C87) -> 26814694 | D88: =SUM(D87) -> 36480944 | E88: =SUM(E87) -> 35073225 | F88: =SUM(F87) -> 33071665 | G88: =SUM(G87) -> 30947281 | H88: =SUM(H87) -> 28692539 | I88: =SUM(I87) -> 26299437 | J88: =SUM(J87) -> 23759486 | ... W88: =SUM(W87) -> 17432510 | Z88: Total Long Term Liabilities | AA88: =C88/1000 -> 26814.694 | AB88: =D88/1000 -> 36480.944 | AC88: =E88/1000 -> 35073.225 | AD88: =F88/1000 -> 33071.665 | AE88: =G88/1000 -> 30947.281 | AF88: =H88/1000 -> 28692.539 | AG88: =I88/1000 -> 26299.437 | AH88: =J88/1000 -> 23759.486 | ... AU88: =W88/1000 -> 17432.51
B89: Equity | C89: =C30 -> 13407347 | D89: =D30+C89 -> 18240472 | E89: =E30+D89 -> 18240472 | F89: =F30+E89 -> 18240472 | G89: =G30+F89 -> 18240472 | H89: =H30+G89 -> 18240472 | I89: =I30+H89 -> 18240472 | J89: =J30+I89 -> 18240472 | K89: =K30+J89 -> 18240472 | ... W89: =W30+V89 -> 18240472 | Z89: Equity | AA89: =C89/1000 -> 13407.347 | AB89: =D89/1000 -> 18240.472 | AC89: =E89/1000 -> 18240.472 | AD89: =F89/1000 -> 18240.472 | AE89: =G89/1000 -> 18240.472 | AF89: =H89/1000 -> 18240.472 | AG89: =I89/1000 -> 18240.472 | AH89: =J89/1000 -> 18240.472 | ... AU89: =W89/1000 -> 18240.472
B90: Retained Earnings | C90: =C15-SUM(Dashboard!$E$27:E27) -> -2351367.5 | D90: =D15-SUM(Dashboard!$E$27:F27) -> -7419094 | E90: =E15-SUM(Dashboard!$E$27:G27) -> -9846955.1 | F90: =F15-SUM(Dashboard!$E$27:H27) -> -9605900.8 | G90: =G15-SUM(Dashboard!$E$27:I27) -> -6068708.8 | H90: =H15-SUM(Dashboard!$E$27:J27) -> 1970990.9 | I90: =I15-SUM(Dashboard!$E$27:Z27) -> 9819200.2 | J90: =J15-SUM(Dashboard!$E$27:L27) -> 21027657 | K90: =K15-SUM(Dashboard!$E$27:M27) -> 33699322 | L90: =L15-SUM(Dashboard!$E$27:N27) -> 47906711 | M90: =M15-SUM(Dashboard!$E$27:O27) -> 62728303 | N90: =N15-SUM(Dashboard!$E$27:P27) -> 78653095 | O90: =O15-SUM(Dashboard!$E$27:Q27) -> 95314917 | P90: =P15-SUM(Dashboard!$E$27:R27) -> 1.1252584e+08 | Q90: =Q15-SUM(Dashboard!$E$27:S27) -> 1.3030233e+08 | ... U90: =U15-SUM(Dashboard!$E$27:W27) -> 2.0741109e+08 | V90: =V15-SUM(Dashboard!$E$27:Z27) -> 2.2828036e+08 | W90: =W15-SUM(Dashboard!$E$27:Y27) -> 2.2663888e+08 | Z90: Retained Earnings | AA90: =C90/1000 -> -2351.3675 | AB90: =D90/1000 -> -7419.094 | AC90: =E90/1000 -> -9846.9551 | AD90: =F90/1000 -> -9605.9008 | AE90: =G90/1000 -> -6068.7088 | AF90: =H90/1000 -> 1970.9909 | AG90: =I90/1000 -> 9819.2002 | AH90: =J90/1000 -> 21027.657 | ... AU90: =W90/1000 -> 226638.88
B91: Total Shareholder's Equity | C91: =SUM(C89:C90) -> 11055980 | D91: =SUM(D89:D90) -> 10821378 | E91: =SUM(E89:E90) -> 8393516.7 | F91: =SUM(F89:F90) -> 8634571 | G91: =SUM(G89:G90) -> 12171763 | H91: =SUM(H89:H90) -> 20211463 | I91: =SUM(I89:I90) -> 28059672 | J91: =SUM(J89:J90) -> 39268128 | ... W91: =SUM(W89:W90) -> 2.4487935e+08 | Z91: Total Shareholder's Equity | AA91: =C91/1000 -> 11055.98 | AB91: =D91/1000 -> 10821.378 | AC91: =E91/1000 -> 8393.5167 | AD91: =F91/1000 -> 8634.571 | AE91: =G91/1000 -> 12171.763 | AF91: =H91/1000 -> 20211.463 | AG91: =I91/1000 -> 28059.672 | AH91: =J91/1000 -> 39268.128 | ... AU91: =W91/1000 -> 244879.35
B92: Total Liabilities + Shareholder's Equity | C92: =SUM(C86,C88,C91) -> 37870674 | D92: =SUM(D86,D88,D91) -> 53079193 | E92: =SUM(E86,E88,E91) -> 49757612 | F92: =SUM(F86,F88,F91) -> 47649275 | G92: =SUM(G86,G88,G91) -> 46392675 | H92: =SUM(H86,H88,H91) -> 52423962 | I92: =SUM(I86,I88,I91) -> 58128488 | J92: =SUM(J86,J88,J91) -> 67009125 | ... W92: =SUM(W86,W88,W91) -> 2.6231186e+08 | Z92: Total Liabilities | AA92: =C92/1000 -> 37870.674 | AB92: =D92/1000 -> 53079.193 | AC92: =E92/1000 -> 49757.612 | AD92: =F92/1000 -> 47649.275 | AE92: =G92/1000 -> 46392.675 | AF92: =H92/1000 -> 52423.962 | AG92: =I92/1000 -> 58128.488 | AH92: =J92/1000 -> 67009.125 | ... AU92: =W92/1000 -> 262311.86
B93: Balance Check | C93: =ROUND(C92-C82,0) -> 0 | D93: =ROUND(D92-D82,0) -> 0 | E93: =ROUND(E92-E82,0) -> 0 | F93: =ROUND(F92-F82,0) -> 0 | G93: =ROUND(G92-G82,0) -> 0 | H93: =ROUND(H92-H82,0) -> 0 | I93: =ROUND(I92-I82,0) -> 0 | J93: =ROUND(J92-J82,0) -> 0 | ... W93: =ROUND(W92-W82,0) -> 0
B95: Cash Requirements Calculation
D96: 1 | E96: 2 | F96: 3 | G96: 4 | H96: 5 | I96: 6 | J96: 7 | K96: 8 | L96: 9 | M96: 10 | N96: 11 | O96: 12 | P96: 13 | Q96: 14 | R96: 15 | S96: 16 | T96: 17 | U96: 18 | V96: 19 | W96: 20
B98: Net Accumulated Cash Flow - DSRA | D98: =D74 -> 71.718041 | E98: =E74 -> 314.48895 | F98: =F74 -> 812.5851 | G98: =G74 -> 853239.99 | H98: =H74 -> 8806519.3 | I98: =I74 -> 16362019 | J98: =J74 -> 27332554 | K98: =K74 -> 39740131 | ... W98: =W74 -> 2.6164273e+08
B99: Cash Required | D99: =MAX(D101+'Data Input'!$D$37,0) -> 5194550.7 | E99: =MAX(E101+'Data Input'!$D$37,0) -> 3908927.2 | F99: =MAX(F101+'Data Input'!$D$37,0) -> 2872029.9 | G99: =MAX(G101+'Data Input'!$D$37,0) -> 0 | H99: =MAX(H101+'Data Input'!$D$37,0) -> 0 | I99: =MAX(I101+'Data Input'!$D$37,0) -> 0 | J99: =MAX(J101+'Data Input'!$D$37,0) -> 0 | K99: =MAX(K101+'Data Input'!$D$37,0) -> 0 | ... W99: =MAX(W101+'Data Input'!$D$37,0) -> 0
D100: =-D98+'WC Financing'!$C5 -> 5194479 | E100: =-E98+'WC Financing'!$C6 -> 3908612.7 | F100: =-F98+'WC Financing'!$C7 -> 2871217.3 | G100: =-G98+'WC Financing'!$C8 -> -853239.99 | H100: =-H98+'WC Financing'!$C9 -> -8806519.3 | I100: =-I98+'WC Financing'!$C10 -> -16362019 | J100: =-J98+'WC Financing'!$C11 -> -27332554 | K100: =-K98+'WC Financing'!$C12 -> -39740131 | L100: =-L98+'WC Financing'!$C13 -> -53516593 | M100: =-M98+'WC Financing'!$C14 -> -67876583
D101: 5194550.7 | E101: 3908927.2 | F101: 2872029.9 | G101: -852100.37 | H101: -8805379.7 | I101: -16361278 | J101: -27331814 | K101: -39739390 | L101: -53515852 | M101: -67875843
B103: Main Financial Results
C104: Equity | D104: Firm
B105: NPV (WACC) | C105: =X68 -> 1.1539196e+08 | D105: =X57 -> 97128474
B106: IRR | C106: =IRR(C65:X65) -> 0.2905722 | D106: =IRR(C54:X54) -> 0.16573041
B107: Return Period | C107: =IFERROR(IF(COUNTIF(C66:W66,"<0")>20,21,COUNTIF(C66:W66,"<0")+C122),"--") -> 6.9 | D107: =IF(COUNTIF(C55:W55,"<0")>20,21,COUNTIF(C55:W55,"<0")+C118) -> 8.6
B108: Discounted Return Period | C108: =IFERROR(IF(COUNTIF(C68:W68,"<0")>20,21,COUNTIF(C68:W68,"<0")+D122),"--") -> 7.5 | D108: =IF(COUNTIF(C57:W57,"<0")>20,21,COUNTIF(C57:W57,"<0")+D118) -> 10.1
B111: Return Period Decimal Calculation
B112: Calculate Decimal? (Linear CF Assumption)* | C112: 1
...

Sheet CAPEX Financing
B1: Company/Project: | C1: =Cover!$C$10 -> Mr. Amir Artine | D1: =Cover!$C$3 -> Cattle Integration, Baghara, Chad | G1: Last Update: | H1: =Cover!$C$13 -> 45763
B3: Financial Assumptions
B4: Year | C4: CAPEX | D4: DSRA | E4: Fees | F4: IDC | G4: Total Funding | H4: Loan % | I4: Loan | J4: Interest Rate | K4: Term | L4: Grace | M4: Payments per Year | N4: IDC? | O4: DSRA?
B5: =0 -> 0 | C5: =Depreciation!D7 -> 37124290 | D5: =A55 -> 746346.89 | E5: ='Data Input'!$D$26*C5 -> 742485.81 | F5: =A54 -> 1608918.3 | G5: =SUM(C5:F5) -> 40222041 | H5: =1-'Data Input'!$D$22 -> 0.66666667 | I5: =SUM(C5:F5)*H5 -> 26814694 | J5: ='Data Input'!D$19 -> 0.06 | K5: ='Data Input'!D$20 -> 13 | L5: ='Data Input'!D$21 -> 3 | M5: ='Data Input'!D$23 -> 4 | N5: ='Data Input'!$D$24 -> 1 | O5: ='Data Input'!$D$25 -> 1
B6: =1 -> 1 | C6: =Depreciation!E7 -> 13382679 | D6: =A84 -> 269047.96 | E6: ='Data Input'!$D$26*C6 -> 267653.59 | F6: =A83 -> 579993.28 | G6: =SUM(C6:F6) -> 14499374 | H6: =1-'Data Input'!$D$22 -> 0.66666667 | I6: =SUM(C6:F6)*H6 -> 9666249.4 | J6: ='Data Input'!D$19 -> 0.06 | K6: ='Data Input'!D$20 -> 13 | L6: ='Data Input'!D$21 -> 3 | M6: ='Data Input'!D$23 -> 4 | N6: ='Data Input'!$D$24 -> 1 | O6: ='Data Input'!$D$25 -> 1
B7: =2 -> 2 | C7: =Depreciation!F7 -> 0 | D7: =A113 -> 2.584198e-138 | E7: ='Data Input'!$D$26*C7 -> 0 | F7: =A112 -> 5.5708189e-138 | G7: =SUM(C7:F7) -> 8.1550169e-138 | H7: =1-'Data Input'!$D$22 -> 0.66666667 | I7: =SUM(C7:F7)*H7 -> 5.4366779e-138 | J7: ='Data Input'!D$19 -> 0.06 | K7: ='Data Input'!D$20 -> 13 | L7: ='Data Input'!D$21 -> 3 | M7: ='Data Input'!D$23 -> 4 | N7: ='Data Input'!$D$24 -> 1 | O7: ='Data Input'!$D$25 -> 1
B8: =3 -> 3 | C8: =Depreciation!G7 -> 0 | D8: =A142 -> 2.7349672e-138 | E8: ='Data Input'!$D$26*C8 -> 0 | F8: =A141 -> 5.8958359e-138 | G8: =SUM(C8:F8) -> 8.6308031e-138 | H8: =1-'Data Input'!$D$22 -> 0.66666667 | I8: =SUM(C8:F8)*H8 -> 5.7538687e-138 | J8: ='Data Input'!D$19 -> 0.06 | K8: ='Data Input'!D$20 -> 13 | L8: ='Data Input'!D$21 -> 3 | M8: ='Data Input'!D$23 -> 4 | N8: ='Data Input'!$D$24 -> 1 | O8: ='Data Input'!$D$25 -> 1
B9: =4 -> 4 | C9: =Depreciation!H7 -> 0 | D9: =A171 -> 0 | E9: ='Data Input'!$D$26*C9 -> 0 | F9: =A170 -> 0 | G9: =SUM(C9:F9) -> 0 | H9: =1-'Data Input'!$D$22 -> 0.66666667 | I9: =SUM(C9:F9)*H9 -> 0 | J9: ='Data Input'!D$19 -> 0.06 | K9: ='Data Input'!D$20 -> 13 | L9: ='Data Input'!D$21 -> 3 | M9: ='Data Input'!D$23 -> 4 | N9: 0 | O9: 0
B10: Total | C10: =SUM(C5:C9) -> 50506970 | D10: =SUM(D5:D9) -> 1015394.8 | E10: =SUM(E5:E9) -> 1010139.4 | F10: =SUM(F5:F9) -> 2188911.6 | G10: =SUM(G5:G9) -> 54721415 | H10: =IFERROR(I10/G10,0) -> 0.66666667 | I10: =SUM(I5:I9) -> 36480944
I11: =I10/G10 -> 0.66666667
B13: Investment Financing
C14: 0 | D14: 1 | E14: 2 | F14: 3 | G14: 4 | H14: 5 | I14: 6 | J14: 7 | K14: 8 | L14: 9 | M14: 10 | N14: 11 | O14: 12 | P14: 13 | Q14: 14 | R14: 15 | S14: 16 | T14: 17 | U14: 18 | V14: 19 | W14: 20
B15: Investment
C16: =C5 -> 37124290 | D16: =C6 -> 13382679 | E16: =C7 -> 0 | F16: =C8 -> 0 | G16: =C9 -> 0
B17: Financing
B18: Equity | C18: =G5-I5 -> 13407347 | D18: =G6-I6 -> 4833124.7 | E18: =G7-I7 -> 2.718339e-138 | F18: =G8-I8 -> 2.8769344e-138 | G18: =G9-I9 -> 0
B19: Bank Loan | C19: =I5-D5 -> 26068347 | D19: =I6-D6 -> 9397201.4 | E19: =I7-D7 -> 2.8524799e-138 | F19: =I8-D8 -> 3.0189015e-138 | G19: =I9-D9 -> 0
B20: DSRA | C20: =D5 -> 746346.89 | D20: =D6 -> 269047.96 | E20: =D7 -> 2.584198e-138 | F20: =D8 -> 2.7349672e-138 | G20: =D9 -> 0
B21: DSRA Repayment | C21: =-IF(C14=SUM($K$5:$L$5)-1,$D$5,0) -> 0 | D21: =-IF(D14=SUM($K$5:$L$5)-1,$D$5,0)-IF(C14=SUM($K$6:$L$6)-1,$D$6,0) -> 0 | E21: =-IF(E14=SUM($K$5:$L$5)-1,$D$5,0)-IF(D14=SUM($K$6:$L$6)-1,$D$6,0)-IF(C14=SUM($K$7:$L$7)-1,$D$7,0) -> 0 | F21: =-IF(F14=SUM($K$5:$L$5)-1,$D$5,0)-IF(E14=SUM($K$6:$L$6)-1,$D$6,0)-IF(D14=SUM($K$7:$L$7)-1,$D$7,0)-IF(C14=SUM($K$8:$L$8)-1,$D$8,0) -> 0 | G21: =-IF(G14=SUM($K$5:$L$5)-1,$D$5,0)-IF(F14=SUM($K$6:$L$6)-1,$D$6,0)-IF(E14=SUM($K$7:$L$7)-1,$D$7,0)-IF(D14=SUM($K$8:$L$8)-1,$D$8,0)-IF(C14=SUM($K$9:$L$9)-1,$D$9,0) -> 0 | H21: =-IF(H14=SUM($K$5:$L$5)-1,$D$5,0)-IF(G14=SUM($K$6:$L$6)-1,$D$6,0)-IF(F14=SUM($K$7:$L$7)-1,$D$7,0)-IF(E14=SUM($K$8:$L$8)-1,$D$8,0)-IF(D14=SUM($K$9:$L$9)-1,$D$9,0) -> 0 | I21: =-IF(I14=SUM($K$5:$L$5)-1,$D$5,0)-IF(H14=SUM($K$6:$L$6)-1,$D$6,0)-IF(G14=SUM($K$7:$L$7)-1,$D$7,0)-IF(F14=SUM($K$8:$L$8)-1,$D$8,0)-IF(E14=SUM($K$9:$L$9)-1,$D$9,0) -> 0 | J21: =-IF(J14=SUM($K$5:$L$5)-1,$D$5,0)-IF(I14=SUM($K$6:$L$6)-1,$D$6,0)-IF(H14=SUM($K$7:$L$7)-1,$D$7,0)-IF(G14=SUM($K$8:$L$8)-1,$D$8,0)-IF(F14=SUM($K$9:$L$9)-1,$D$9,0) -> 0 | K21: =-IF(K14=SUM($K$5:$L$5)-1,$D$5,0)-IF(J14=SUM($K$6:$L$6)-1,$D$6,0)-IF(I14=SUM($K$7:$L$7)-1,$D$7,0)-IF(H14=SUM($K$8:$L$8)-1,$D$8,0)-IF(G14=SUM($K$9:$L$9)-1,$D$9,0) -> 0 | L21: =-IF(L14=SUM($K$5:$L$5)-1,$D$5,0)-IF(K14=SUM($K$6:$L$6)-1,$D$6,0)-IF(J14=SUM($K$7:$L$7)-1,$D$7,0)-IF(I14=SUM($K$8:$L$8)-1,$D$8,0)-IF(H14=SUM($K$9:$L$9)-1,$D$9,0) -> 0 | M21: =-IF(M14=SUM($K$5:$L$5)-1,$D$5,0)-IF(L14=SUM($K$6:$L$6)-1,$D$6,0)-IF(K14=SUM($K$7:$L$7)-1,$D$7,0)-IF(J14=SUM($K$8:$L$8)-1,$D$8,0)-IF(I14=SUM($K$9:$L$9)-1,$D$9,0) -> 0 | N21: =-IF(N14=SUM($K$5:$L$5)-1,$D$5,0)-IF(M14=SUM($K$6:$L$6)-1,$D$6,0)-IF(L14=SUM($K$7:$L$7)-1,$D$7,0)-IF(K14=SUM($K$8:$L$8)-1,$D$8,0)-IF(J14=SUM($K$9:$L$9)-1,$D$9,0) -> 0 | ... W21: =-IF(W14=SUM($K$5:$L$5)-1,$D$5,0)-IF(V14=SUM($K$6:$L$6)-1,$D$6,0)-IF(U14=SUM($K$7:$L$7)-1,$D$7,0)-IF(T14=SUM($K$8:$L$8)-1,$D$8,0)-IF(S14=SUM($K$9:$L$9)-1,$D$9,0) -> 0
B22: Interest & Principal by Payment
B23: Interest Payment | C23: =C43 -> 1608881.6 | D23: =SUM(D43,C72) -> 2188856.6 | E23: =SUM(E43,D72,C101) -> 2188856.6 | F23: =SUM(F43,E72,D101,C130) -> 2157575.9 | G23: =SUM(G43,F72,E101,D130,C159) -> 2059917.1 | H23: =SUM(H43,G72,F101,E130,D159) -> 1937094.3 | I23: =SUM(I43,H72,G101,F130,E159) -> 1806734.6 | J23: =SUM(J43,I72,H101,G130,F159) -> 1668375.5 | K23: =SUM(K43,J72,I101,H130,G159) -> 1521526.3 | L23: =SUM(L43,K72,J101,I130,H159) -> 1365665.9 | M23: =SUM(M43,L72,K101,J130,I159) -> 1200241.3 | N23: =SUM(N43,M72,L101,K130,J159) -> 306229.71 | ... W23: =SUM(W43,V72,U101,T130,S159) -> 0
B24: Principal Payment | C24: =C44 -> 0 | D24: =SUM(D44,C73) -> 0 | E24: =SUM(E44,D73,C102) -> 0 | F24: =SUM(F44,E73,D102,C131) -> 1407718.6 | G24: =SUM(G44,F73,E102,D131,C160) -> 2001560.3 | H24: =SUM(H44,G73,F102,E131,D160) -> 2124383.2 | I24: =SUM(I44,H73,G102,F131,E160) -> 2254742.9 | J24: =SUM(J44,I73,H102,G131,F160) -> 2393101.9 | K24: =SUM(K44,J73,I102,H131,G160) -> 2539951.1 | L24: =SUM(L44,K73,J102,I131,H160) -> 2695811.5 | M24: =SUM(M44,L73,K102,J131,I160) -> 2861236.1 | N24: =SUM(N44,M73,L102,K131,J160) -> 769928.14 | ... W24: =SUM(W44,V73,U102,T131,S160) -> 0
B25: Current and Long-Term Liabilities
B26: Current Liabilities | C26: =SUM(C58) -> 0 | D26: =SUM(D58,C87) -> 0 | E26: =SUM(E58,D87,C116) -> 1407718.6 | F26: =SUM(F58,E87,D116,C145) -> 2001560.3 | G26: =SUM(G58,F87,E116,D145,C174) -> 2124383.2 | H26: =SUM(H58,G87,F116,E145,D174) -> 2254742.9 | I26: =SUM(I58,H87,G116,F145,E174) -> 2393101.9 | J26: =SUM(J58,I87,H116,G145,F174) -> 2539951.1 | K26: =SUM(K58,J87,I116,H145,G174) -> 2695811.5 | L26: =SUM(L58,K87,J116,I145,H174) -> 2861236.1 | M26: =SUM(M58,L87,K116,J145,I174) -> 769928.14 | N26: =SUM(N58,M87,L116,K145,J174) -> 8.6484311e-139 | ... W26: =SUM(W58,V87,U116,T145,S174) -> 0
B27: Long-Term Liabilities | C27: =SUM(C59) -> 26814694 | D27: =SUM(D59,C88) -> 36480944 | E27: =SUM(E59,D88,C117) -> 35073225 | F27: =SUM(F59,E88,D117,C146) -> 33071665 | G27: =SUM(G59,F88,E117,D146,C175) -> 30947281 | H27: =SUM(H59,G88,F117,E146,D175) -> 28692539 | I27: =SUM(I59,H88,G117,F146,E175) -> 26299437 | J27: =SUM(J59,I88,H117,G146,F175) -> 23759486 | K27: =SUM(K59,J88,I117,H146,G175) -> 21063674 | L27: =SUM(L59,K88,J117,I146,H175) -> 18202438 | M27: =SUM(M59,L88,K117,J146,I175) -> 17432510 | N27: =SUM(N59,M88,L117,K146,J175) -> 17432510 | ... W27: =SUM(W59,V88,U117,T146,S175) -> 17432510
B33: Year 0 Investment
B34: Interest & Principal by Payment
B35: Interest Pmt. | C35: 1 | D35: 2 | E35: 3 | F35: 4 | G35: 5 | H35: 6 | I35: 7 | J35: 8 | K35: 9 | L35: 10 | M35: 11 | N35: 12 | O35: 13 | P35: 14 | Q35: 15 | R35: 16 | S35: 17 | T35: 18 | U35: 19 | V35: 20 | W35: 21 | X35: 22 | Y35: 23 | Z35: 24 | AA35: 25 | AB35: 26 | AC35: 27 | AD35: 28 | AE35: 29 | AF35: 30 | AG35: 31 | AH35: 32 | AI35: 33 | AJ35: 34 | AK35: 35 | AL35: 36 | AM35: 37 | AN35: 38 | AO35: 39 | AP35: 40
B36: Principal Pmt. | C36: =MAX(C35-($L$5-1)*$M$5,0) -> 0 | D36: =MAX(D35-($L$5-1)*$M$5,0) -> 0 | E36: =MAX(E35-($L$5-1)*$M$5,0) -> 0 | F36: =MAX(F35-($L$5-1)*$M$5,0) -> 0 | G36: =MAX(G35-($L$5-1)*$M$5,0) -> 0 | H36: =MAX(H35-($L$5-1)*$M$5,0) -> 0 | I36: =MAX(I35-($L$5-1)*$M$5,0) -> 0 | J36: =MAX(J35-($L$5-1)*$M$5,0) -> 0 | ... AP36: =MAX(AP35-($L$5-1)*$M$5,0) -> 32
B37: Year | C37: =ROUNDUP(C35/$M$5,0) -> 1 | D37: =ROUNDUP(D35/$M$5,0) -> 1 | E37: =ROUNDUP(E35/$M$5,0) -> 1 | F37: =ROUNDUP(F35/$M$5,0) -> 1 | G37: =ROUNDUP(G35/$M$5,0) -> 2 | H37: =ROUNDUP(H35/$M$5,0) -> 2 | I37: =ROUNDUP(I35/$M$5,0) -> 2 | J37: =ROUNDUP(J35/$M$5,0) -> 2 | ... AP37: =ROUNDUP(AP35/$M$5,0) -> 10
B38: Interest | C38: =-IFERROR(IPMT($J$5/$M$5,MAX(C36,1),$K$5*$M$5,$I$5),0) -> 402220.41 | D38: =-IFERROR(IPMT($J$5/$M$5,MAX(D36,1),$K$5*$M$5,$I$5),0) -> 402220.41 | E38: =-IFERROR(IPMT($J$5/$M$5,MAX(E36,1),$K$5*$M$5,$I$5),0) -> 402220.41 | F38: =-IFERROR(IPMT($J$5/$M$5,MAX(F36,1),$K$5*$M$5,$I$5),0) -> 402220.41 | G38: =-IFERROR(IPMT($J$5/$M$5,MAX(G36,1),$K$5*$M$5,$I$5),0) -> 402220.41 | H38: =-IFERROR(IPMT($J$5/$M$5,MAX(H36,1),$K$5*$M$5,$I$5),0) -> 402220.41 | I38: =-IFERROR(IPMT($J$5/$M$5,MAX(I36,1),$K$5*$M$5,$I$5),0) -> 402220.41 | J38: =-IFERROR(IPMT($J$5/$M$5,MAX(J36,1),$K$5*$M$5,$I$5),0) -> 402220.41 | ... AP38: =-IFERROR(IPMT($J$5/$M$5,MAX(AP36,1),$K$5*$M$5,$I$5),0) -> 200391.11
B39: Principal | C39: =-IFERROR(PPMT($J$5/$M$5,C36,$K$5*$M$5,$I$5),0) -> 0 | D39: =-IFERROR(PPMT($J$5/$M$5,D36,$K$5*$M$5,$I$5),0) -> 0 | E39: =-IFERROR(PPMT($J$5/$M$5,E36,$K$5*$M$5,$I$5),0) -> 0 | F39: =-IFERROR(PPMT($J$5/$M$5,F36,$K$5*$M$5,$I$5),0) -> 0 | G39: =-IFERROR(PPMT($J$5/$M$5,G36,$K$5*$M$5,$I$5),0) -> 0 | H39: =-IFERROR(PPMT($J$5/$M$5,H36,$K$5*$M$5,$I$5),0) -> 0 | I39: =-IFERROR(PPMT($J$5/$M$5,I36,$K$5*$M$5,$I$5),0) -> 0 | J39: =-IFERROR(PPMT($J$5/$M$5,J36,$K$5*$M$5,$I$5),0) -> 0 | ... AP39: =-IFERROR(PPMT($J$5/$M$5,AP36,$K$5*$M$5,$I$5),0) -> 545938.79
B40: Total | C40: =SUM(C38:C39) -> 402220.41 | D40: =SUM(D38:D39) -> 402220.41 | E40: =SUM(E38:E39) -> 402220.41 | F40: =SUM(F38:F39) -> 402220.41 | G40: =SUM(G38:G39) -> 402220.41 | H40: =SUM(H38:H39) -> 402220.41 | I40: =SUM(I38:I39) -> 402220.41 | J40: =SUM(J38:J39) -> 402220.41 | ... AP40: =SUM(AP38:AP39) -> 746329.9
B41: Interest & Principal by Year
C42: 0 | D42: 1 | E42: 2 | F42: 3 | G42: 4 | H42: 5 | I42: 6 | J42: 7 | K42: 8 | L42: 9 | M42: 10 | N42: 11 | O42: 12 | P42: 13 | Q42: 14 | R42: 15 | S42: 16 | T42: 17 | U42: 18 | V42: 19 | W42: 20
B43: Interest | C43: =O51 -> 1608881.6 | D43: =SUMIF($C$37:$AP$37,D$42,$C38:$AP38) -> 1608881.6 | E43: =SUMIF($C$37:$AP$37,E$42,$C38:$AP38) -> 1608881.6 | F43: =SUMIF($C$37:$AP$37,F$42,$C38:$AP38) -> 1577600.9 | G43: =SUMIF($C$37:$AP$37,G$42,$C38:$AP38) -> 1491218.3 | H43: =SUMIF($C$37:$AP$37,H$42,$C38:$AP38) -> 1399535 | I43: =SUMIF($C$37:$AP$37,I$42,$C38:$AP38) -> 1302225.6 | J43: =SUMIF($C$37:$AP$37,J$42,$C38:$AP38) -> 1198945 | K43: =SUMIF($C$37:$AP$37,K$42,$C38:$AP38) -> 1089326.7 | ... W43: =SUMIF($C$37:$AP$37,W$42,$C38:$AP38) -> 0
B44: Principal | D44: =SUMIF($C$37:$AP$37,D$42,$C39:$AP39) -> 0 | E44: =SUMIF($C$37:$AP$37,E$42,$C39:$AP39) -> 0 | F44: =SUMIF($C$37:$AP$37,F$42,$C39:$AP39) -> 1407718.6 | G44: =SUMIF($C$37:$AP$37,G$42,$C39:$AP39) -> 1494101.3 | H44: =SUMIF($C$37:$AP$37,H$42,$C39:$AP39) -> 1585784.6 | I44: =SUMIF($C$37:$AP$37,I$42,$C39:$AP39) -> 1683094 | J44: =SUMIF($C$37:$AP$37,J$42,$C39:$AP39) -> 1786374.6 | K44: =SUMIF($C$37:$AP$37,K$42,$C39:$AP39) -> 1895992.9 | ... W44: =SUMIF($C$37:$AP$37,W$42,$C39:$AP39) -> 0
B45: Total | C45: =SUM(C43:C44) -> 1608881.6 | D45: =SUM(D43:D44) -> 1608881.6 | E45: =SUM(E43:E44) -> 1608881.6 | F45: =SUM(F43:F44) -> 2985319.6 | G45: =SUM(G43:G44) -> 2985319.6 | H45: =SUM(H43:H44) -> 2985319.6 | I45: =SUM(I43:I44) -> 2985319.6 | J45: =SUM(J43:J44) -> 2985319.6 | ... W45: =SUM(W43:W44) -> 0
B46: Interest During Construction (IDC)
C47: 1 | D47: 2 | E47: 3 | F47: 4 | G47: 5 | H47: 6 | I47: 7 | J47: 8 | K47: 9 | L47: 10 | M47: 11 | N47: 12 | O47: Total
B48: Withdrawal | C48: 1 | D48: 0 | E48: 0 | F48: 0 | G48: 0 | H48: 0 | I48: 0 | J48: 0 | K48: 0 | L48: 0 | M48: 0 | N48: 0
B49: Principal | C49: =$I$5*C48 -> 26814694 | D49: =$I$5*D48 -> 0 | E49: =$I$5*E48 -> 0 | F49: =$I$5*F48 -> 0 | G49: =$I$5*G48 -> 0 | H49: =$I$5*H48 -> 0 | I49: =$I$5*I48 -> 0 | J49: =$I$5*J48 -> 0 | ... N49: =$I$5*N48 -> 0
B50: Accumulated Principal | C50: =C49 -> 26814694 | D50: =D49+C50 -> 26814694 | E50: =E49+D50 -> 26814694 | F50: =F49+E50 -> 26814694 | G50: =G49+F50 -> 26814694 | H50: =H49+G50 -> 26814694 | I50: =I49+H50 -> 26814694 | J50: =J49+I50 -> 26814694 | K50: =K49+J50 -> 26814694 | ... N50: =N49+M50 -> 26814694
B51: Interest | C51: =C50*$J$5/12 -> 134073.47 | D51: =D50*$J$5/12 -> 134073.47 | E51: =E50*$J$5/12 -> 134073.47 | F51: =F50*$J$5/12 -> 134073.47 | G51: =G50*$J$5/12 -> 134073.47 | H51: =H50*$J$5/12 -> 134073.47 | I51: =I50*$J$5/12 -> 134073.47 | J51: =J50*$J$5/12 -> 134073.47 | ... N51: =N50*$J$5/12 -> 134073.47 | O51: =SUM(C51:N51) -> 1608881.6
B52: DSRA & IDC Calculation (to avoid circular references)
A53: =0% -> 0 | B53: % Loan | D53: =$A$53 -> 0 | E53: =D53+5% -> 0.05 | F53: =E53+5% -> 0.1 | G53: =F53+5% -> 0.15 | H53: =G53+5% -> 0.2 | I53: =H53+5% -> 0.25 | J53: =I53+5% -> 0.3 | K53: =J53+5% -> 0.35 | L53: =K53+5% -> 0.4 | ... P53: =O53+5% -> 0.6 | Q53: 0.66666667 | R53: 0.7 | S53: =R53+5% -> 0.75 | T53: =S53+5% -> 0.8 | U53: =T53+5% -> 0.85 | V53: =U53+5% -> 0.9 | W53: =V53+5% -> 0.95 | X53: =W53+5% -> 1
A54: =HLOOKUP($H$5+1%,D53:X55,2,TRUE)*$N$5 -> 1608918.3 | B54: IDC | C54: =O51 -> 1608881.6 | D54: 0 | E54: 114101.63 | F54: 229214.74 | G54: 345352.84 | H54: 462529.67 | I54: 580759.23 | J54: 700055.76 | K54: 820433.76 | L54: 941908.01 | M54: 1064493.5 | N54: 1188205.6 | O54: 1313059.9 | P54: 1439072.3 | Q54: 1608918.3 | R54: 1694636.3 | S54: 1824221.2 | T54: 1955030.8 | U54: 2087082.4 | V54: 2220393.9 | W54: 2354983.3 | X54: 2490869.2
A55: =HLOOKUP($H$5+1%,D53:X55,3,TRUE)*$O$5 -> 746346.89 | B55: DSRA | C55: =-PMT($J$5/$M$5,$K$5*$M$5,$I$5) -> 746329.9 | D55: 0 | E55: 52929.596 | F55: 106328.4 | G55: 160202.68 | H55: 214558.8 | I55: 269403.27 | J55: 324742.68 | K55: 380583.77 | L55: 436933.38 | M55: 493798.5 | N55: 551186.22 | O55: 609103.78 | P55: 667558.55 | Q55: 746346.89 | R55: 786109.87 | S55: 846221.87 | T55: 906901.95 | U55: 968158.22 | V55: 1029998.9 | W55: 1092432.4 | X55: 1155467.3
B56: Current and Long-Term Liabilities
C57: 0 | D57: 1 | E57: 2 | F57: 3 | G57: 4 | H57: 5 | I57: 6 | J57: 7 | K57: 8 | L57: 9 | M57: 10 | N57: 11 | O57: 12 | P57: 13 | Q57: 14 | R57: 15 | S57: 16 | T57: 17 | U57: 18 | V57: 19 | W57: 20
B58: Current Liabilities | C58: =D44 -> 0 | D58: =E44 -> 0 | E58: =F44 -> 1407718.6 | F58: =G44 -> 1494101.3 | G58: =H44 -> 1585784.6 | H58: =I44 -> 1683094 | I58: =J44 -> 1786374.6 | J58: =K44 -> 1895992.9 | ... W58: =X44 -> 0
B59: Long-Term Liabilities | C59: =I5-C58 -> 26814694 | D59: =C59-D58 -> 26814694 | E59: =D59-E58 -> 25406976 | F59: =E59-F58 -> 23912874 | G59: =F59-G58 -> 22327090 | H59: =G59-H58 -> 20643996 | I59: =H59-I58 -> 18857621 | J59: =I59-J58 -> 16961628 | K59: =J59-K58 -> 14949290 | ... W59: =V59-W58 -> 12813468
B62: Year 1 Investment
B63: Interest & Principal by Payment
B64: Interest Pmt. | C64: 1 | D64: 2 | E64: 3 | F64: 4 | G64: 5 | H64: 6 | I64: 7 | J64: 8 | K64: 9 | L64: 10 | M64: 11 | N64: 12 | O64: 13 | P64: 14 | Q64: 15 | R64: 16 | S64: 17 | T64: 18 | U64: 19 | V64: 20 | W64: 21 | X64: 22 | Y64: 23 | Z64: 24 | AA64: 25 | AB64: 26 | AC64: 27 | AD64: 28 | AE64: 29 | AF64: 30 | AG64: 31 | AH64: 32 | AI64: 33 | AJ64: 34 | AK64: 35 | AL64: 36 | AM64: 37 | AN64: 38 | AO64: 39 | AP64: 40
B65: Principal Pmt. | C65: =MAX(C64-($L$6-1)*$M$6,0) -> 0 | D65: =MAX(D64-($L$6-1)*$M$6,0) -> 0 | E65: =MAX(E64-($L$6-1)*$M$6,0) -> 0 | F65: =MAX(F64-($L$6-1)*$M$6,0) -> 0 | G65: =MAX(G64-($L$6-1)*$M$6,0) -> 0 | H65: =MAX(H64-($L$6-1)*$M$6,0) -> 0 | I65: =MAX(I64-($L$6-1)*$M$6,0) -> 0 | J65: =MAX(J64-($L$6-1)*$M$6,0) -> 0 | ... AP65: =MAX(AP64-($L$6-1)*$M$6,0) -> 32
B66: Year | C66: =ROUNDUP(C64/$M$6,0) -> 1 | D66: =ROUNDUP(D64/$M$6,0) -> 1 | E66: =ROUNDUP(E64/$M$6,0) -> 1 | F66: =ROUNDUP(F64/$M$6,0) -> 1 | G66: =ROUNDUP(G64/$M$6,0) -> 2 | H66: =ROUNDUP(H64/$M$6,0) -> 2 | I66: =ROUNDUP(I64/$M$6,0) -> 2 | J66: =ROUNDUP(J64/$M$6,0) -> 2 | ... AP66: =ROUNDUP(AP64/$M$6,0) -> 10
B67: Interest | C67: =-IFERROR(IPMT($J$6/$M$6,MAX(C65,1),$K$6*$M$6,$I$6),0) -> 144993.74 | D67: =-IFERROR(IPMT($J$6/$M$6,MAX(D65,1),$K$6*$M$6,$I$6),0) -> 144993.74 | E67: =-IFERROR(IPMT($J$6/$M$6,MAX(E65,1),$K$6*$M$6,$I$6),0) -> 144993.74 | F67: =-IFERROR(IPMT($J$6/$M$6,MAX(F65,1),$K$6*$M$6,$I$6),0) -> 144993.74 | G67: =-IFERROR(IPMT($J$6/$M$6,MAX(G65,1),$K$6*$M$6,$I$6),0) -> 144993.74 | H67: =-IFERROR(IPMT($J$6/$M$6,MAX(H65,1),$K$6*$M$6,$I$6),0) -> 144993.74 | I67: =-IFERROR(IPMT($J$6/$M$6,MAX(I65,1),$K$6*$M$6,$I$6),0) -> 144993.74 | J67: =-IFERROR(IPMT($J$6/$M$6,MAX(J65,1),$K$6*$M$6,$I$6),0) -> 144993.74 | ... AP67: =-IFERROR(IPMT($J$6/$M$6,MAX(AP65,1),$K$6*$M$6,$I$6),0) -> 72237.647
B68: Principal | C68: =-IFERROR(PPMT($J$6/$M$6,C65,$K$6*$M$6,$I$6),0) -> 0 | D68: =-IFERROR(PPMT($J$6/$M$6,D65,$K$6*$M$6,$I$6),0) -> 0 | E68: =-IFERROR(PPMT($J$6/$M$6,E65,$K$6*$M$6,$I$6),0) -> 0 | F68: =-IFERROR(PPMT($J$6/$M$6,F65,$K$6*$M$6,$I$6),0) -> 0 | G68: =-IFERROR(PPMT($J$6/$M$6,G65,$K$6*$M$6,$I$6),0) -> 0 | H68: =-IFERROR(PPMT($J$6/$M$6,H65,$K$6*$M$6,$I$6),0) -> 0 | I68: =-IFERROR(PPMT($J$6/$M$6,I65,$K$6*$M$6,$I$6),0) -> 0 | J68: =-IFERROR(PPMT($J$6/$M$6,J65,$K$6*$M$6,$I$6),0) -> 0 | ... AP68: =-IFERROR(PPMT($J$6/$M$6,AP65,$K$6*$M$6,$I$6),0) -> 196801.81
B69: Total | C69: =SUM(C67:C68) -> 144993.74 | D69: =SUM(D67:D68) -> 144993.74 | E69: =SUM(E67:E68) -> 144993.74 | F69: =SUM(F67:F68) -> 144993.74 | G69: =SUM(G67:G68) -> 144993.74 | H69: =SUM(H67:H68) -> 144993.74 | I69: =SUM(I67:I68) -> 144993.74 | J69: =SUM(J67:J68) -> 144993.74 | ... AP69: =SUM(AP67:AP68) -> 269039.46
B70: Interest & Principal by Year
C71: 0 | D71: 1 | E71: 2 | F71: 3 | G71: 4 | H71: 5 | I71: 6 | J71: 7 | K71: 8 | L71: 9 | M71: 10 | N71: 11 | O71: 12 | P71: 13 | Q71: 14 | R71: 15 | S71: 16 | T71: 17 | U71: 18 | V71: 19 | W71: 20
B72: Interest | C72: =O80 -> 579974.96 | D72: =SUMIF($C$66:$AP$66,D$71,$C67:$AP67) -> 579974.96 | E72: =SUMIF($C$66:$AP$66,E$71,$C67:$AP67) -> 579974.96 | F72: =SUMIF($C$66:$AP$66,F$71,$C67:$AP67) -> 568698.79 | G72: =SUMIF($C$66:$AP$66,G$71,$C67:$AP67) -> 537559.3 | H72: =SUMIF($C$66:$AP$66,H$71,$C67:$AP67) -> 504508.98 | I72: =SUMIF($C$66:$AP$66,I$71,$C67:$AP67) -> 469430.58 | J72: =SUMIF($C$66:$AP$66,J$71,$C67:$AP67) -> 432199.64 | K72: =SUMIF($C$66:$AP$66,K$71,$C67:$AP67) -> 392684.07 | ... W72: =SUMIF($C$66:$AP$66,W$71,$C67:$AP67) -> 0
B73: Principal | D73: =SUMIF($C66:$AP66,D$42,$C68:$AP68) -> 0 | E73: =SUMIF($C66:$AP66,E$42,$C68:$AP68) -> 0 | F73: =SUMIF($C66:$AP66,F$42,$C68:$AP68) -> 507459.06 | G73: =SUMIF($C66:$AP66,G$42,$C68:$AP68) -> 538598.55 | H73: =SUMIF($C66:$AP66,H$42,$C68:$AP68) -> 571648.87 | I73: =SUMIF($C66:$AP66,I$42,$C68:$AP68) -> 606727.27 | J73: =SUMIF($C66:$AP66,J$42,$C68:$AP68) -> 643958.21 | K73: =SUMIF($C66:$AP66,K$42,$C68:$AP68) -> 683473.78 | ... W73: =SUMIF($C66:$AP66,W$42,$C68:$AP68) -> 0
B74: Total | C74: =SUM(C72:C73) -> 579974.96 | D74: =SUM(D72:D73) -> 579974.96 | E74: =SUM(E72:E73) -> 579974.96 | F74: =SUM(F72:F73) -> 1076157.8 | G74: =SUM(G72:G73) -> 1076157.8 | H74: =SUM(H72:H73) -> 1076157.8 | I74: =SUM(I72:I73) -> 1076157.8 | J74: =SUM(J72:J73) -> 1076157.8 | ... W74: =SUM(W72:W73) -> 0
B75: Interest During Construction (IDC)
C76: 1 | D76: 2 | E76: 3 | F76: 4 | G76: 5 | H76: 6 | I76: 7 | J76: 8 | K76: 9 | L76: 10 | M76: 11 | N76: 12 | O76: Total
B77: Withdrawal | C77: 1 | D77: 0 | E77: 0 | F77: 0 | G77: 0 | H77: 0 | I77: 0 | J77: 0 | K77: 0 | L77: 0 | M77: 0 | N77: 0
B78: Principal | C78: =$I$6*C77 -> 9666249.4 | D78: =$I$6*D77 -> 0 | E78: =$I$6*E77 -> 0 | F78: =$I$6*F77 -> 0 | G78: =$I$6*G77 -> 0 | H78: =$I$6*H77 -> 0 | I78: =$I$6*I77 -> 0 | J78: =$I$6*J77 -> 0 | ... N78: =$I$6*N77 -> 0
B79: Accumulated Principal | C79: =C78 -> 9666249.4 | D79: =D78+C79 -> 9666249.4 | E79: =E78+D79 -> 9666249.4 | F79: =F78+E79 -> 9666249.4 | G79: =G78+F79 -> 9666249.4 | H79: =H78+G79 -> 9666249.4 | I79: =I78+H79 -> 9666249.4 | J79: =J78+I79 -> 9666249.4 | K79: =K78+J79 -> 9666249.4 | ... N79: =N78+M79 -> 9666249.4
B80: Interest | C80: =C79*$J$6/12 -> 48331.247 | D80: =D79*$J$6/12 -> 48331.247 | E80: =E79*$J$6/12 -> 48331.247 | F80: =F79*$J$6/12 -> 48331.247 | G80: =G79*$J$6/12 -> 48331.247 | H80: =H79*$J$6/12 -> 48331.247 | I80: =I79*$J$6/12 -> 48331.247 | J80: =J79*$J$6/12 -> 48331.247 | ... N80: =N79*$J$6/12 -> 48331.247 | O80: =SUM(C80:N80) -> 579974.96
B81: DSRA & IDC Calculation (to avoid circular references)
B82: % Loan | D82: =$A$53 -> 0 | E82: =D82+5% -> 0.05 | F82: =E82+5% -> 0.1 | G82: =F82+5% -> 0.15 | H82: =G82+5% -> 0.2 | I82: =H82+5% -> 0.25 | J82: =I82+5% -> 0.3 | K82: =J82+5% -> 0.35 | L82: =K82+5% -> 0.4 | ... P82: =O82+5% -> 0.6 | Q82: 0.66666667 | R82: 0.7 | S82: =R82+5% -> 0.75 | T82: =S82+5% -> 0.8 | U82: =T82+5% -> 0.85 | V82: =U82+5% -> 0.9 | W82: =V82+5% -> 0.95 | X82: =W82+5% -> 1
A83: =HLOOKUP($H$6+1%,D82:X84,2,TRUE)*$N$6 -> 579993.28 | B83: IDC | C83: =O80 -> 579974.96 | D83: 0 | E83: 41131.738 | F83: 82628.156 | G83: 124494.12 | H83: 166734.6 | I83: 209354.62 | J83: 252359.33 | K83: 295753.96 | L83: 339543.83 | M83: 383734.35 | N83: 428331.06 | O83: 473339.58 | P83: 518765.62 | Q83: 579993.28 | R83: 610893.76 | S83: 657607.85 | T83: 704763.47 | U83: 752366.91 | V83: 800424.58 | W83: 848943.01 | X83: 897928.85
A84: =HLOOKUP($H$6+1%,D82:X84,3,TRUE)*$O$6 -> 269047.96 | B84: DSRA | C84: =-PMT($J$6/$M$6,$K$6*$M$6,$I$6) -> 269039.46 | D84: 0 | E84: 19080.238 | F84: 38329.645 | G84: 57750.48 | H84: 77345.04 | I84: 97115.667 | J84: 117064.74 | K84: 137194.69 | L84: 157507.99 | M84: 178007.14 | N84: 198694.71 | O84: 219573.31 | P84: 240645.6 | Q84: 269047.96 | R84: 283382.11 | S84: 305051.9 | T84: 326926.5 | U84: 349008.84 | V84: 371301.89 | W84: 393808.67 | X84: 416532.28
B85: Current and Long-Term Liabilities
C86: 0 | D86: 1 | E86: 2 | F86: 3 | G86: 4 | H86: 5 | I86: 6 | J86: 7 | K86: 8 | L86: 9 | M86: 10 | N86: 11 | O86: 12 | P86: 13 | Q86: 14 | R86: 15 | S86: 16 | T86: 17 | U86: 18 | V86: 19 | W86: 20
B87: Current Liabilities | C87: =D73 -> 0 | D87: =E73 -> 0 | E87: =F73 -> 507459.06 | F87: =G73 -> 538598.55 | G87: =H73 -> 571648.87 | H87: =I73 -> 606727.27 | I87: =J73 -> 643958.21 | J87: =K73 -> 683473.78 | ... W87: =X73 -> 0
B88: Long-Term Liabilities | C88: =$I$6-C87 -> 9666249.4 | D88: =C88-D87 -> 9666249.4 | E88: =D88-E87 -> 9158790.3 | F88: =E88-F87 -> 8620191.8 | G88: =F88-G87 -> 8048542.9 | H88: =G88-H87 -> 7441815.6 | I88: =H88-I87 -> 6797857.4 | J88: =I88-J87 -> 6114383.6 | K88: =J88-K87 -> 5388969.5 | ... W88: =V88-W87 -> 4619041.3
B91: Year 2 Investment
B92: Interest & Principal by Payment
B93: Interest Pmt. | C93: 1 | D93: 2 | E93: 3 | F93: 4 | G93: 5 | H93: 6 | I93: 7 | J93: 8 | K93: 9 | L93: 10 | M93: 11 | N93: 12 | O93: 13 | P93: 14 | Q93: 15 | R93: 16 | S93: 17 | T93: 18 | U93: 19 | V93: 20 | W93: 21 | X93: 22 | Y93: 23 | Z93: 24 | AA93: 25 | AB93: 26 | AC93: 27 | AD93: 28 | AE93: 29 | AF93: 30 | AG93: 31 | AH93: 32 | AI93: 33 | AJ93: 34 | AK93: 35 | AL93: 36 | AM93: 37 | AN93: 38 | AO93: 39 | AP93: 40
B94: Principal Pmt. | C94: =MAX(C93-($L$7-1)*$M$7,0) -> 0 | D94: =MAX(D93-($L$7-1)*$M$7,0) -> 0 | E94: =MAX(E93-($L$7-1)*$M$7,0) -> 0 | F94: =MAX(F93-($L$7-1)*$M$7,0) -> 0 | G94: =MAX(G93-($L$7-1)*$M$7,0) -> 0 | H94: =MAX(H93-($L$7-1)*$M$7,0) -> 0 | I94: =MAX(I93-($L$7-1)*$M$7,0) -> 0 | J94: =MAX(J93-($L$7-1)*$M$7,0) -> 0 | ... AP94: =MAX(AP93-($L$7-1)*$M$7,0) -> 32
B95: Year | C95: =ROUNDUP(C93/$M$7,0) -> 1 | D95: =ROUNDUP(D93/$M$7,0) -> 1 | E95: =ROUNDUP(E93/$M$7,0) -> 1 | F95: =ROUNDUP(F93/$M$7,0) -> 1 | G95: =ROUNDUP(G93/$M$7,0) -> 2 | H95: =ROUNDUP(H93/$M$7,0) -> 2 | I95: =ROUNDUP(I93/$M$7,0) -> 2 | J95: =ROUNDUP(J93/$M$7,0) -> 2 | ... AP95: =ROUNDUP(AP93/$M$7,0) -> 10
B96: Interest | C96: =-IFERROR(IPMT($J$7/$M$7,MAX(C94,1),$K$7*$M$7,$I$7),0) -> 8.1550169e-140 | D96: =-IFERROR(IPMT($J$7/$M$7,MAX(D94,1),$K$7*$M$7,$I$7),0) -> 8.1550169e-140 | E96: =-IFERROR(IPMT($J$7/$M$7,MAX(E94,1),$K$7*$M$7,$I$7),0) -> 8.1550169e-140 | F96: =-IFERROR(IPMT($J$7/$M$7,MAX(F94,1),$K$7*$M$7,$I$7),0) -> 8.1550169e-140 | G96: =-IFERROR(IPMT($J$7/$M$7,MAX(G94,1),$K$7*$M$7,$I$7),0) -> 8.1550169e-140 | H96: =-IFERROR(IPMT($J$7/$M$7,MAX(H94,1),$K$7*$M$7,$I$7),0) -> 8.1550169e-140 | I96: =-IFERROR(IPMT($J$7/$M$7,MAX(I94,1),$K$7*$M$7,$I$7),0) -> 8.1550169e-140 | J96: =-IFERROR(IPMT($J$7/$M$7,MAX(J94,1),$K$7*$M$7,$I$7),0) -> 8.1550169e-140 | ... AP96: =-IFERROR(IPMT($J$7/$M$7,MAX(AP94,1),$K$7*$M$7,$I$7),0) -> 4.0629287e-140
B97: Principal | C97: =-IFERROR(PPMT($J$7/$M$7,C94,$K$7*$M$7,$I$7),0) -> 0 | D97: =-IFERROR(PPMT($J$7/$M$7,D94,$K$7*$M$7,$I$7),0) -> 0 | E97: =-IFERROR(PPMT($J$7/$M$7,E94,$K$7*$M$7,$I$7),0) -> 0 | F97: =-IFERROR(PPMT($J$7/$M$7,F94,$K$7*$M$7,$I$7),0) -> 0 | G97: =-IFERROR(PPMT($J$7/$M$7,G94,$K$7*$M$7,$I$7),0) -> 0 | H97: =-IFERROR(PPMT($J$7/$M$7,H94,$K$7*$M$7,$I$7),0) -> 0 | I97: =-IFERROR(PPMT($J$7/$M$7,I94,$K$7*$M$7,$I$7),0) -> 0 | J97: =-IFERROR(PPMT($J$7/$M$7,J94,$K$7*$M$7,$I$7),0) -> 0 | ... AP97: =-IFERROR(PPMT($J$7/$M$7,AP94,$K$7*$M$7,$I$7),0) -> 1.1068906e-139
B98: Total | C98: =SUM(C96:C97) -> 8.1550169e-140 | D98: =SUM(D96:D97) -> 8.1550169e-140 | E98: =SUM(E96:E97) -> 8.1550169e-140 | F98: =SUM(F96:F97) -> 8.1550169e-140 | G98: =SUM(G96:G97) -> 8.1550169e-140 | H98: =SUM(H96:H97) -> 8.1550169e-140 | I98: =SUM(I96:I97) -> 8.1550169e-140 | J98: =SUM(J96:J97) -> 8.1550169e-140 | ... AP98: =SUM(AP96:AP97) -> 1.5131835e-139
B99: Interest & Principal by Year
C100: 0 | D100: 1 | E100: 2 | F100: 3 | G100: 4 | H100: 5 | I100: 6 | J100: 7 | K100: 8 | L100: 9 | M100: 10 | N100: 11 | O100: 12 | P100: 13 | Q100: 14 | R100: 15 | S100: 16 | T100: 17 | U100: 18 | V100: 19 | W100: 20
B101: Interest | C101: =O109 -> 3.2620068e-139 | D101: =SUMIF($C95:$AP95,D$71,$C96:$AP96) -> 3.2620068e-139 | E101: =SUMIF($C95:$AP95,E$71,$C96:$AP96) -> 3.2620068e-139 | F101: =SUMIF($C95:$AP95,F$71,$C96:$AP96) -> 3.1985851e-139 | G101: =SUMIF($C95:$AP95,G$71,$C96:$AP96) -> 3.0234444e-139 | H101: =SUMIF($C95:$AP95,H$71,$C96:$AP96) -> 2.8375564e-139 | I101: =SUMIF($C95:$AP95,I$71,$C96:$AP96) -> 2.6402617e-139 | J101: =SUMIF($C95:$AP95,J$71,$C96:$AP96) -> 2.4308603e-139 | K101: =SUMIF($C95:$AP95,K$71,$C96:$AP96) -> 2.2086093e-139 | ... W101: =SUMIF($C95:$AP95,W$71,$C96:$AP96) -> 0
B102: Principal | D102: =SUMIF($C95:$AP95,D$42,$C97:$AP97) -> 0 | E102: =SUMIF($C95:$AP95,E$42,$C97:$AP97) -> 0 | F102: =SUMIF($C95:$AP95,F$42,$C97:$AP97) -> 2.8541489e-139 | G102: =SUMIF($C95:$AP95,G$42,$C97:$AP97) -> 3.0292896e-139 | H102: =SUMIF($C95:$AP95,H$42,$C97:$AP97) -> 3.2151775e-139 | I102: =SUMIF($C95:$AP95,I$42,$C97:$AP97) -> 3.4124722e-139 | J102: =SUMIF($C95:$AP95,J$42,$C97:$AP97) -> 3.6218737e-139 | K102: =SUMIF($C95:$AP95,K$42,$C97:$AP97) -> 3.8441247e-139 | ... W102: =SUMIF($C95:$AP95,W$42,$C97:$AP97) -> 0
B103: Total | C103: =SUM(C101:C102) -> 3.2620068e-139 | D103: =SUM(D101:D102) -> 3.2620068e-139 | E103: =SUM(E101:E102) -> 3.2620068e-139 | F103: =SUM(F101:F102) -> 6.052734e-139 | G103: =SUM(G101:G102) -> 6.052734e-139 | H103: =SUM(H101:H102) -> 6.052734e-139 | I103: =SUM(I101:I102) -> 6.052734e-139 | J103: =SUM(J101:J102) -> 6.052734e-139 | ... W103: =SUM(W101:W102) -> 0
B104: Interest During Construction (IDC)
C105: 1 | D105: 2 | E105: 3 | F105: 4 | G105: 5 | H105: 6 | I105: 7 | J105: 8 | K105: 9 | L105: 10 | M105: 11 | N105: 12 | O105: Total
B106: Withdrawal | C106: 1 | D106: 0 | E106: 0 | F106: 0 | G106: 0 | H106: 0 | I106: 0 | J106: 0 | K106: 0 | L106: 0 | M106: 0 | N106: 0
B107: Principal | C107: =$I$7*C106 -> 5.4366779e-138 | D107: =$I$7*D106 -> 0 | E107: =$I$7*E106 -> 0 | F107: =$I$7*F106 -> 0 | G107: =$I$7*G106 -> 0 | H107: =$I$7*H106 -> 0 | I107: =$I$7*I106 -> 0 | J107: =$I$7*J106 -> 0 | ... N107: =$I$7*N106 -> 0
B108: Accumulated Principal | C108: =C107 -> 5.4366779e-138 | D108: =D107+C108 -> 5.4366779e-138 | E108: =E107+D108 -> 5.4366779e-138 | F108: =F107+E108 -> 5.4366779e-138 | G108: =G107+F108 -> 5.4366779e-138 | H108: =H107+G108 -> 5.4366779e-138 | I108: =I107+H108 -> 5.4366779e-138 | J108: =J107+I108 -> 5.4366779e-138 | K108: =K107+J108 -> 5.4366779e-138 | ... N108: =N107+M108 -> 5.4366779e-138
B109: Interest | C109: =C108*$J$7/12 -> 2.718339e-140 | D109: =D108*$J$7/12 -> 2.718339e-140 | E109: =E108*$J$7/12 -> 2.718339e-140 | F109: =F108*$J$7/12 -> 2.718339e-140 | G109: =G108*$J$7/12 -> 2.718339e-140 | H109: =H108*$J$7/12 -> 2.718339e-140 | I109: =I108*$J$7/12 -> 2.718339e-140 | J109: =J108*$J$7/12 -> 2.718339e-140 | ... N109: =N108*$J$7/12 -> 2.718339e-140 | O109: =SUM(C109:N109) -> 3.2620068e-139
B110: DSRA & IDC Calculation (to avoid circular references)
B111: % Loan | D111: =$A$53 -> 0 | E111: =D111+5% -> 0.05 | F111: =E111+5% -> 0.1 | G111: =F111+5% -> 0.15 | H111: =G111+5% -> 0.2 | I111: =H111+5% -> 0.25 | J111: =I111+5% -> 0.3 | K111: =J111+5% -> 0.35 | L111: =K111+5% -> 0.4 | ... P111: =O111+5% -> 0.6 | Q111: 0.66666667 | R111: 0.7 | S111: =R111+5% -> 0.75 | T111: =S111+5% -> 0.8 | U111: =T111+5% -> 0.85 | V111: =U111+5% -> 0.9 | W111: =V111+5% -> 0.95 | X111: =W111+5% -> 1
...

Sheet WC Financing
B1: Company/Project: | C1: =Cover!$C$10 -> Mr. Amir Artine | D1: =Cover!$C$3 -> Cattle Integration, Baghara, Chad | G1: Last Update: | H1: =Cover!$C$13 -> 45763
B3: Financing Assumptions
B4: Year | C4: Working Capital | D4: Loan % | E4: Loan | F4: Interest Rate | G4: Term | H4: Grace*
B5: =1 -> 1 | C5: =Fin.Statements!D99*'Data Input'!$D$28 -> 5194550.7 | D5: =1-'Data Input'!$D$32 -> 1 | E5: =C5*D5 -> 5194550.7 | F5: ='Data Input'!D$29 -> 0.1 | G5: ='Data Input'!D$30 -> 1 | H5: ='Data Input'!D$31 -> 0
B6: =2 -> 2 | C6: =Fin.Statements!E99*'Data Input'!$D$28 -> 3908927.2 | D6: =1-'Data Input'!$D$32 -> 1 | E6: =C6*D6 -> 3908927.2 | F6: ='Data Input'!D$29 -> 0.1 | G6: ='Data Input'!D$30 -> 1 | H6: ='Data Input'!D$31 -> 0
B7: =3 -> 3 | C7: =Fin.Statements!F99*'Data Input'!$D$28 -> 2872029.9 | D7: =1-'Data Input'!$D$32 -> 1 | E7: =C7*D7 -> 2872029.9 | F7: ='Data Input'!D$29 -> 0.1 | G7: ='Data Input'!D$30 -> 1 | H7: ='Data Input'!D$31 -> 0
B8: =4 -> 4 | C8: =Fin.Statements!G99*'Data Input'!$D$28 -> 0 | D8: =1-'Data Input'!$D$32 -> 1 | E8: =C8*D8 -> 0 | F8: ='Data Input'!D$29 -> 0.1 | G8: ='Data Input'!D$30 -> 1 | H8: ='Data Input'!D$31 -> 0
B9: =5 -> 5 | C9: =Fin.Statements!H99*'Data Input'!$D$28 -> 0 | D9: =1-'Data Input'!$D$32 -> 1 | E9: =C9*D9 -> 0 | F9: ='Data Input'!D$29 -> 0.1 | G9: ='Data Input'!D$30 -> 1 | H9: ='Data Input'!D$31 -> 0
B10: 6 | C10: =Fin.Statements!I99*'Data Input'!$D$28 -> 0 | D10: =1-'Data Input'!$D$32 -> 1 | E10: =C10*D10 -> 0 | F10: ='Data Input'!D$29 -> 0.1 | G10: ='Data Input'!D$30 -> 1 | H10: ='Data Input'!D$31 -> 0
B11: 7 | C11: =Fin.Statements!J99*'Data Input'!$D$28 -> 0 | D11: =1-'Data Input'!$D$32 -> 1 | E11: =C11*D11 -> 0 | F11: ='Data Input'!D$29 -> 0.1 | G11: ='Data Input'!D$30 -> 1 | H11: ='Data Input'!D$31 -> 0
B12: 8 | C12: =Fin.Statements!K99*'Data Input'!$D$28 -> 0 | D12: =1-'Data Input'!$D$32 -> 1 | E12: =C12*D12 -> 0 | F12: ='Data Input'!D$29 -> 0.1 | G12: ='Data Input'!D$30 -> 1 | H12: ='Data Input'!D$31 -> 0
B13: 9 | C13: =Fin.Statements!L99*'Data Input'!$D$28 -> 0 | D13: =1-'Data Input'!$D$32 -> 1 | E13: =C13*D13 -> 0 | F13: ='Data Input'!D$29 -> 0.1 | G13: ='Data Input'!D$30 -> 1 | H13: ='Data Input'!D$31 -> 0
B14: 10 | C14: =Fin.Statements!M99*'Data Input'!$D$28 -> 0 | D14: =1-'Data Input'!$D$32 -> 1 | E14: =C14*D14 -> 0 | F14: ='Data Input'!D$29 -> 0.1 | G14: ='Data Input'!D$30 -> 1 | H14: ='Data Input'!D$31 -> 0
B15: Total | C15: =SUM(C5:C9) -> 11975508 | D15: =IFERROR(E15/C15,0) -> 1 | E15: =SUM(E5:E9) -> 11975508
H16: * Including Year 0
B18: Working Capital Financing
C19: 0 | D19: 1 | E19: 2 | F19: 3 | G19: 4 | H19: 5 | I19: 6 | J19: 7 | K19: 8 | L19: 9 | M19: 10 | N19: 11 | O19: 12 | P19: 13 | Q19: 14 | R19: 15 | S19: 16 | T19: 17 | U19: 18 | V19: 19 | W19: 20
B20: Working Capital
D21: =C5 -> 5194550.7 | E21: =C6 -> 3908927.2 | F21: =C7 -> 2872029.9 | G21: =C8 -> 0 | H21: =C9 -> 0 | I21: =C10 -> 0 | J21: =C11 -> 0 | K21: =C12 -> 0 | L21: =C13 -> 0 | M21: =C14 -> 0
B22: Financing
B23: Equity | D23: =C5-E5 -> 0 | E23: =C6-E6 -> 0 | F23: =C7-E7 -> 0 | G23: =C8-E8 -> 0 | H23: =C9-E9 -> 0 | I23: =C10-E10 -> 0 | J23: =C11-E11 -> 0 | K23: =C12-E12 -> 0 | L23: =C13-E13 -> 0 | M23: =C14-E14 -> 0
B24: Bank Loan | D24: =E5 -> 5194550.7 | E24: =E6 -> 3908927.2 | F24: =E7 -> 2872029.9 | G24: =E8 -> 0 | H24: =E9 -> 0 | I24: =E10 -> 0 | J24: =E11 -> 0 | K24: =E12 -> 0 | L24: =E13 -> 0 | M24: =C14 -> 0
B27: Interest & Principal by Payment
B28: Interest Payment | D28: =SUM(C47) -> 519455.07 | E28: =SUM(D47,C64) -> 910347.79 | F28: =SUM(E47,D64,C81) -> 678095.7 | G28: =SUM(F47,E64,D81,C98) -> 287202.99 | H28: =SUM(G47,F64,E81,D98,C115) -> 0 | I28: =SUM(H47,G64,F81,E98,D115,C132) -> 0 | J28: =SUM(I47,H64,G81,F98,E115,D132,C149) -> 0 | K28: =SUM(J47,I64,H81,G98,F115,E132,D149,C166) -> 0 | L28: =SUM(K47,J64,I81,H98,G115,F132,E149,D166,C183) -> 0 | M28: =SUM(L47,K64,J81,I98,H115,G132,F149,E166,D183,C200) -> 0 | N28: =SUM(M47,L64,K81,J98,I115,H132,G149,F166,E183,D200) -> 0 | O28: =SUM(N47,M64,L81,K98,J115,I132,H149,G166,F183,E200) -> 0 | P28: =SUM(O47,N64,M81,L98,K115,J132,I149,H166,G183,F200) -> 0 | Q28: =SUM(P47,O64,N81,M98,L115,K132,J149,I166,H183,G200) -> 0 | R28: =SUM(Q47,P64,O81,N98,M115,L132,K149,J166,I183,H200) -> 0 | S28: =SUM(R47,Q64,P81,O98,N115,M132,L149,K166,J183,I200) -> 0 | T28: =SUM(S47,R64,Q81,P98,O115,N132,M149,L166,K183,J200) -> 0 | ... W28: =SUM(V47,U64,T81,S98,R115,Q132,P149,O166,N183,M200) -> 0
B29: Principal Payment | D29: =SUM(C48) -> 0 | E29: =SUM(D48,C65) -> 5194550.7 | F29: =SUM(E48,D65,C82) -> 3908927.2 | G29: =SUM(F48,E65,D82,C99) -> 2872029.9 | H29: =SUM(G48,F65,E82,D99,C116) -> 0 | I29: =SUM(H48,G65,F82,E99,D116,C133) -> 0 | J29: =SUM(I48,H65,G82,F99,E116,D133,C150) -> 0 | K29: =SUM(J48,I65,H82,G99,F116,E133,D150,C167) -> 0 | L29: =SUM(K48,J65,I82,H99,G116,F133,E150,D167,C184) -> 0 | M29: =SUM(L48,K65,J82,I99,H116,G133,F150,E167,D184,C201) -> 0 | N29: =SUM(M48,L65,K82,J99,I116,H133,G150,F167,E184,D201) -> 0 | O29: =SUM(N48,M65,L82,K99,J116,I133,H150,G167,F184,E201) -> 0 | P29: =SUM(O48,N65,M82,L99,K116,J133,I150,H167,G184,F201) -> 0 | Q29: =SUM(P48,O65,N82,M99,L116,K133,J150,I167,H184,G201) -> 0 | R29: =SUM(Q48,P65,O82,N99,M116,L133,K150,J167,I184,H201) -> 0 | S29: =SUM(R48,Q65,P82,O99,N116,M133,L150,K167,J184,I201) -> 0 | T29: =SUM(S48,R65,Q82,P99,O116,N133,M150,L167,K184,J201) -> 0 | ... W29: =SUM(V48,U65,T82,S99,R116,Q133,P150,O167,N184,M201) -> 0
B30: Current and Long-Term Liabilities
B31: Current Liabilities | D31: =SUM(C51) -> 5194550.7 | E31: =SUM(D51,C68) -> 3908927.2 | F31: =SUM(E51,D68,C85) -> 2872029.9 | G31: =SUM(F51,E68,D85,C102) -> 0 | H31: =SUM(G51,F68,E85,D102,C119) -> 0 | I31: =SUM(H51,G68,F85,E102,D119,C136) -> 0 | J31: =SUM(I51,H68,G85,F102,E119,D136,C153) -> 0 | K31: =SUM(J51,I68,H85,G102,F119,E136,D153,C170) -> 0 | L31: =SUM(K51,J68,I85,H102,G119,F136,E153,D170,C187) -> 0 | M31: =SUM(L51,K68,J85,I102,H119,G136,F153,E170,D187,C204) -> 0 | N31: =SUM(M51,L68,K85,J102,I119,H136,G153,F170,E187,D204) -> 0 | O31: =SUM(N51,M68,L85,K102,J119,I136,H153,G170,F187,E204) -> 0 | P31: =SUM(O51,N68,M85,L102,K119,J136,I153,H170,G187,F204) -> 0 | Q31: =SUM(P51,O68,N85,M102,L119,K136,J153,I170,H187,G204) -> 0 | R31: =SUM(Q51,P68,O85,N102,M119,L136,K153,J170,I187,H204) -> 0 | S31: =SUM(R51,Q68,P85,O102,N119,M136,L153,K170,J187,I204) -> 0 | T31: =SUM(S51,R68,Q85,P102,O119,N136,M153,L170,K187,J204) -> 0 | ... W31: =SUM(V51,U68,T85,S102,R119,Q136,P153,O170,N187,M204) -> 0
B32: Long-Term Liabilities | D32: =SUM(C52) -> 0 | E32: =SUM(D52,C69) -> 0 | F32: =SUM(E52,D69,C86) -> 0 | G32: =SUM(F52,E69,D86,C103) -> 0 | H32: =SUM(G52,F69,E86,D103,C120) -> 0 | I32: =SUM(H52,G69,F86,E103,D120,C137) -> 0 | J32: =SUM(I52,H69,G86,F103,E120,D137,C154) -> 0 | K32: =SUM(J52,I69,H86,G103,F120,E137,D154,C171) -> 0 | L32: =SUM(K52,J69,I86,H103,G120,F137,E154,D171,C188) -> 0 | M32: =SUM(L52,K69,J86,I103,H120,G137,F154,E171,D188,C205) -> 0 | N32: =SUM(M52,L69,K86,J103,I120,H137,G154,F171,E188,D205) -> 0 | O32: =SUM(N52,M69,L86,K103,J120,I137,H154,G171,F188,E205) -> 0 | P32: =SUM(O52,N69,M86,L103,K120,J137,I154,H171,G188,F205) -> 0 | Q32: =SUM(P52,O69,N86,M103,L120,K137,J154,I171,H188,G205) -> 0 | R32: =SUM(Q52,P69,O86,N103,M120,L137,K154,J171,I188,H205) -> 0 | S32: =SUM(R52,Q69,P86,O103,N120,M137,L154,K171,J188,I205) -> 0 | T32: =SUM(S52,R69,Q86,P103,O120,N137,M154,L171,K188,J205) -> 0 | ... W32: =SUM(V52,U69,T86,S103,R120,Q137,P154,O171,N188,M205) -> 0
A38: 1 | B38: ="Year "&A38&" Working Capital Financing" -> Year 1 Working Capital Financing
C39: 0 | D39: 1 | E39: 2 | F39: 3 | G39: 4 | H39: 5 | I39: 6 | J39: 7 | K39: 8 | L39: 9 | M39: 10 | N39: 11 | O39: 12 | P39: 13 | Q39: 14 | R39: 15 | S39: 16 | T39: 17 | U39: 18 | V39: 19 | W39: 20
B40: Interest & Principal by Payment
B41: Interest Pmt. | D41: 1 | E41: 2 | F41: 3 | G41: 4 | H41: 5 | I41: 6 | J41: 7 | K41: 8 | L41: 9 | M41: 10 | N41: 11 | O41: 12 | P41: 13 | Q41: 14 | R41: 15 | S41: 16 | T41: 17 | U41: 18 | V41: 19 | W41: 20
B42: Principal Pmt. | D42: =MAX(D41-($H$5),0) -> 1 | E42: =MAX(E41-($H$5),0) -> 2 | F42: =MAX(F41-($H$5),0) -> 3 | G42: =MAX(G41-($H$5),0) -> 4 | H42: =MAX(H41-($H$5),0) -> 5 | I42: =MAX(I41-($H$5),0) -> 6 | J42: =MAX(J41-($H$5),0) -> 7 | K42: =MAX(K41-($H$5),0) -> 8 | ... W42: =MAX(W41-($H$5),0) -> 20
B43: Interest | D43: =-IFERROR(IPMT($F$5,MAX(D42,1),$G$5,$E$5),0) -> 519455.07 | E43: =-IFERROR(IPMT($F$5,MAX(E42,1),$G$5,$E$5),0) -> 0 | F43: =-IFERROR(IPMT($F$5,MAX(F42,1),$G$5,$E$5),0) -> 0 | G43: =-IFERROR(IPMT($F$5,MAX(G42,1),$G$5,$E$5),0) -> 0 | H43: =-IFERROR(IPMT($F$5,MAX(H42,1),$G$5,$E$5),0) -> 0 | I43: =-IFERROR(IPMT($F$5,MAX(I42,1),$G$5,$E$5),0) -> 0 | J43: =-IFERROR(IPMT($F$5,MAX(J42,1),$G$5,$E$5),0) -> 0 | K43: =-IFERROR(IPMT($F$5,MAX(K42,1),$G$5,$E$5),0) -> 0 | ... W43: =-IFERROR(IPMT($F$5,MAX(W42,1),$G$5,$E$5),0) -> 0
B44: Principal | D44: =-IFERROR(PPMT($F$5,D42,$G$5,$E$5),0) -> 5194550.7 | E44: =-IFERROR(PPMT($F$5,E42,$G$5,$E$5),0) -> 0 | F44: =-IFERROR(PPMT($F$5,F42,$G$5,$E$5),0) -> 0 | G44: =-IFERROR(PPMT($F$5,G42,$G$5,$E$5),0) -> 0 | H44: =-IFERROR(PPMT($F$5,H42,$G$5,$E$5),0) -> 0 | I44: =-IFERROR(PPMT($F$5,I42,$G$5,$E$5),0) -> 0 | J44: =-IFERROR(PPMT($F$5,J42,$G$5,$E$5),0) -> 0 | K44: =-IFERROR(PPMT($F$5,K42,$G$5,$E$5),0) -> 0 | ... W44: =-IFERROR(PPMT($F$5,W42,$G$5,$E$5),0) -> 0
B45: Total | D45: =SUM(D43:D44) -> 5714005.8 | E45: =SUM(E43:E44) -> 0 | F45: =SUM(F43:F44) -> 0 | G45: =SUM(G43:G44) -> 0 | H45: =SUM(H43:H44) -> 0 | I45: =SUM(I43:I44) -> 0 | J45: =SUM(J43:J44) -> 0 | K45: =SUM(K43:K44) -> 0 | ... W45: =SUM(W43:W44) -> 0
B46: Interest & Principal by Year
B47: Interest | C47: =-IFERROR(IPMT($F$5,MAX(D42,1),$G$5,$E$5),0) -> 519455.07 | D47: =SUMIF($D$39:$AQ$39,D$39,$D43:$AQ43) -> 519455.07 | E47: =SUMIF($D$39:$AQ$39,E$39,$D43:$AQ43) -> 0 | F47: =SUMIF($D$39:$AQ$39,F$39,$D43:$AQ43) -> 0 | G47: =SUMIF($D$39:$AQ$39,G$39,$D43:$AQ43) -> 0 | H47: =SUMIF($D$39:$AQ$39,H$39,$D43:$AQ43) -> 0 | I47: =SUMIF($D$39:$AQ$39,I$39,$D43:$AQ43) -> 0 | J47: =SUMIF($D$39:$AQ$39,J$39,$D43:$AQ43) -> 0 | K47: =SUMIF($D$39:$AQ$39,K$39,$D43:$AQ43) -> 0 | ... W47: =SUMIF($D$39:$AQ$39,W$39,$D43:$AQ43) -> 0
B48: Principal | D48: =D44 -> 5194550.7 | E48: =E44 -> 0 | F48: =F44 -> 0 | G48: =G44 -> 0 | H48: =H44 -> 0 | I48: =I44 -> 0 | J48: =J44 -> 0 | K48: =K44 -> 0 | ... W48: =W44 -> 0
B49: Total | C49: =SUM(C47:C48) -> 519455.07 | D49: =SUM(D47:D48) -> 5714005.8 | E49: =SUM(E47:E48) -> 0 | F49: =SUM(F47:F48) -> 0 | G49: =SUM(G47:G48) -> 0 | H49: =SUM(H47:H48) -> 0 | I49: =SUM(I47:I48) -> 0 | J49: =SUM(J47:J48) -> 0 | ... W49: =SUM(W47:W48) -> 0
B50: Current and Long-Term Liabilities
B51: Current Liabilities | C51: =D44 -> 5194550.7 | D51: =E44 -> 0 | E51: =F44 -> 0 | F51: =G44 -> 0 | G51: =H44 -> 0 | H51: =I44 -> 0 | I51: =J44 -> 0 | J51: =K44 -> 0 | ... W51: =X44 -> 0
B52: Long-Term Liabilities | C52: =$E$5-C51 -> 0 | D52: =C52-D51 -> 0 | E52: =D52-E51 -> 0 | F52: =E52-F51 -> 0 | G52: =F52-G51 -> 0 | H52: =G52-H51 -> 0 | I52: =H52-I51 -> 0 | J52: =I52-J51 -> 0 | K52: =J52-K51 -> 0 | ... W52: =V52-W51 -> 0
A55: =A38+1 -> 2 | B55: ="Year "&A55&" Working Capital Financing" -> Year 2 Working Capital Financing
C56: 0 | D56: 1 | E56: 2 | F56: 3 | G56: 4 | H56: 5 | I56: 6 | J56: 7 | K56: 8 | L56: 9 | M56: 10 | N56: 11 | O56: 12 | P56: 13 | Q56: 14 | R56: 15 | S56: 16 | T56: 17 | U56: 18 | V56: 19 | W56: 20
B57: Interest & Principal by Payment
B58: Interest Pmt. | D58: 1 | E58: 2 | F58: 3 | G58: 4 | H58: 5 | I58: 6 | J58: 7 | K58: 8 | L58: 9 | M58: 10 | N58: 11 | O58: 12 | P58: 13 | Q58: 14 | R58: 15 | S58: 16 | T58: 17 | U58: 18 | V58: 19 | W58: 20
B59: Principal Pmt. | D59: =MAX(D58-($H$6),0) -> 1 | E59: =MAX(E58-($H$6),0) -> 2 | F59: =MAX(F58-($H$6),0) -> 3 | G59: =MAX(G58-($H$6),0) -> 4 | H59: =MAX(H58-($H$6),0) -> 5 | I59: =MAX(I58-($H$6),0) -> 6 | J59: =MAX(J58-($H$6),0) -> 7 | K59: =MAX(K58-($H$6),0) -> 8 | ... W59: =MAX(W58-($H$6),0) -> 20
B60: Interest | D60: =-IFERROR(IPMT($F$6,MAX(D59,1),$G$6,$E$6),0) -> 390892.72 | E60: =-IFERROR(IPMT($F$6,MAX(E59,1),$G$6,$E$6),0) -> 0 | F60: =-IFERROR(IPMT($F$6,MAX(F59,1),$G$6,$E$6),0) -> 0 | G60: =-IFERROR(IPMT($F$6,MAX(G59,1),$G$6,$E$6),0) -> 0 | H60: =-IFERROR(IPMT($F$6,MAX(H59,1),$G$6,$E$6),0) -> 0 | I60: =-IFERROR(IPMT($F$6,MAX(I59,1),$G$6,$E$6),0) -> 0 | J60: =-IFERROR(IPMT($F$6,MAX(J59,1),$G$6,$E$6),0) -> 0 | K60: =-IFERROR(IPMT($F$6,MAX(K59,1),$G$6,$E$6),0) -> 0 | ... W60: =-IFERROR(IPMT($F$6,MAX(W59,1),$G$6,$E$6),0) -> 0
B61: Principal | D61: =-IFERROR(PPMT($F$6,D59,$G$6,$E$6),0) -> 3908927.2 | E61: =-IFERROR(PPMT($F$6,E59,$G$6,$E$6),0) -> 0 | F61: =-IFERROR(PPMT($F$6,F59,$G$6,$E$6),0) -> 0 | G61: =-IFERROR(PPMT($F$6,G59,$G$6,$E$6),0) -> 0 | H61: =-IFERROR(PPMT($F$6,H59,$G$6,$E$6),0) -> 0 | I61: =-IFERROR(PPMT($F$6,I59,$G$6,$E$6),0) -> 0 | J61: =-IFERROR(PPMT($F$6,J59,$G$6,$E$6),0) -> 0 | K61: =-IFERROR(PPMT($F$6,K59,$G$6,$E$6),0) -> 0 | ... W61: =-IFERROR(PPMT($F$6,W59,$G$6,$E$6),0) -> 0
B62: Total | D62: =SUM(D60:D61) -> 4299819.9 | E62: =SUM(E60:E61) -> 0 | F62: =SUM(F60:F61) -> 0 | G62: =SUM(G60:G61) -> 0 | H62: =SUM(H60:H61) -> 0 | I62: =SUM(I60:I61) -> 0 | J62: =SUM(J60:J61) -> 0 | K62: =SUM(K60:K61) -> 0 | ... W62: =SUM(W60:W61) -> 0
B63: Interest & Principal by Year
B64: Interest | C64: =-IFERROR(IPMT($F$6,MAX(D59,1),$G$6,$E$6),0) -> 390892.72 | D64: =SUMIF($D56:$AQ56,D$56,$D60:$AQ60) -> 390892.72 | E64: =SUMIF($D56:$AQ56,E$56,$D60:$AQ60) -> 0 | F64: =SUMIF($D56:$AQ56,F$56,$D60:$AQ60) -> 0 | G64: =SUMIF($D56:$AQ56,G$56,$D60:$AQ60) -> 0 | H64: =SUMIF($D56:$AQ56,H$56,$D60:$AQ60) -> 0 | I64: =SUMIF($D56:$AQ56,I$56,$D60:$AQ60) -> 0 | J64: =SUMIF($D56:$AQ56,J$56,$D60:$AQ60) -> 0 | K64: =SUMIF($D56:$AQ56,K$56,$D60:$AQ60) -> 0 | ... W64: =SUMIF($D56:$AQ56,W$56,$D60:$AQ60) -> 0
B65: Principal | D65: =D61 -> 3908927.2 | E65: =E61 -> 0 | F65: =F61 -> 0 | G65: =G61 -> 0 | H65: =H61 -> 0 | I65: =I61 -> 0 | J65: =J61 -> 0 | K65: =K61 -> 0 | ... W65: =W61 -> 0
B66: Total | C66: =SUM(C64:C65) -> 390892.72 | D66: =SUM(D64:D65) -> 4299819.9 | E66: =SUM(E64:E65) -> 0 | F66: =SUM(F64:F65) -> 0 | G66: =SUM(G64:G65) -> 0 | H66: =SUM(H64:H65) -> 0 | I66: =SUM(I64:I65) -> 0 | J66: =SUM(J64:J65) -> 0 | ... W66: =SUM(W64:W65) -> 0
B67: Current and Long-Term Liabilities
B68: Current Liabilities | C68: =D65 -> 3908927.2 | D68: =E65 -> 0 | E68: =F65 -> 0 | F68: =G65 -> 0 | G68: =H65 -> 0 | H68: =I65 -> 0 | I68: =J65 -> 0 | J68: =K65 -> 0 | ... W68: =X65 -> 0
B69: Long-Term Liabilities | C69: =$E$6-C68 -> 0 | D69: =C69-D68 -> 0 | E69: =D69-E68 -> 0 | F69: =E69-F68 -> 0 | G69: =F69-G68 -> 0 | H69: =G69-H68 -> 0 | I69: =H69-I68 -> 0 | J69: =I69-J68 -> 0 | K69: =J69-K68 -> 0 | ... W69: =V69-W68 -> 0
A72: =A55+1 -> 3 | B72: ="Year "&A72&" Working Capital Financing" -> Year 3 Working Capital Financing
C73: 0 | D73: 1 | E73: 2 | F73: 3 | G73: 4 | H73: 5 | I73: 6 | J73: 7 | K73: 8 | L73: 9 | M73: 10 | N73: 11 | O73: 12 | P73: 13 | Q73: 14 | R73: 15 | S73: 16 | T73: 17 | U73: 18 | V73: 19 | W73: 20
B74: Interest & Principal by Payment
B75: Interest Pmt. | D75: 1 | E75: 2 | F75: 3 | G75: 4 | H75: 5 | I75: 6 | J75: 7 | K75: 8 | L75: 9 | M75: 10 | N75: 11 | O75: 12 | P75: 13 | Q75: 14 | R75: 15 | S75: 16 | T75: 17 | U75: 18 | V75: 19 | W75: 20
B76: Principal Pmt. | D76: =MAX(D75-($H$7),0) -> 1 | E76: =MAX(E75-($H$7),0) -> 2 | F76: =MAX(F75-($H$7),0) -> 3 | G76: =MAX(G75-($H$7),0) -> 4 | H76: =MAX(H75-($H$7),0) -> 5 | I76: =MAX(I75-($H$7),0) -> 6 | J76: =MAX(J75-($H$7),0) -> 7 | K76: =MAX(K75-($H$7),0) -> 8 | ... W76: =MAX(W75-($H$7),0) -> 20
B77: Interest | D77: =-IFERROR(IPMT($F$7,MAX(D76,1),$G$7,$E$7),0) -> 287202.99 | E77: =-IFERROR(IPMT($F$7,MAX(E76,1),$G$7,$E$7),0) -> 0 | F77: =-IFERROR(IPMT($F$7,MAX(F76,1),$G$7,$E$7),0) -> 0 | G77: =-IFERROR(IPMT($F$7,MAX(G76,1),$G$7,$E$7),0) -> 0 | H77: =-IFERROR(IPMT($F$7,MAX(H76,1),$G$7,$E$7),0) -> 0 | I77: =-IFERROR(IPMT($F$7,MAX(I76,1),$G$7,$E$7),0) -> 0 | J77: =-IFERROR(IPMT($F$7,MAX(J76,1),$G$7,$E$7),0) -> 0 | K77: =-IFERROR(IPMT($F$7,MAX(K76,1),$G$7,$E$7),0) -> 0 | ... W77: =-IFERROR(IPMT($F$7,MAX(W76,1),$G$7,$E$7),0) -> 0
B78: Principal | D78: =-IFERROR(PPMT($F$7,D76,$G$7,$E$7),0) -> 2872029.9 | E78: =-IFERROR(PPMT($F$7,E76,$G$7,$E$7),0) -> 0 | F78: =-IFERROR(PPMT($F$7,F76,$G$7,$E$7),0) -> 0 | G78: =-IFERROR(PPMT($F$7,G76,$G$7,$E$7),0) -> 0 | H78: =-IFERROR(PPMT($F$7,H76,$G$7,$E$7),0) -> 0 | I78: =-IFERROR(PPMT($F$7,I76,$G$7,$E$7),0) -> 0 | J78: =-IFERROR(PPMT($F$7,J76,$G$7,$E$7),0) -> 0 | K78: =-IFERROR(PPMT($F$7,K76,$G$7,$E$7),0) -> 0 | ... W78: =-IFERROR(PPMT($F$7,W76,$G$7,$E$7),0) -> 0
B79: Total | D79: =SUM(D77:D78) -> 3159232.8 | E79: =SUM(E77:E78) -> 0 | F79: =SUM(F77:F78) -> 0 | G79: =SUM(G77:G78) -> 0 | H79: =SUM(H77:H78) -> 0 | I79: =SUM(I77:I78) -> 0 | J79: =SUM(J77:J78) -> 0 | K79: =SUM(K77:K78) -> 0 | ... W79: =SUM(W77:W78) -> 0
B80: Interest & Principal by Year
B81: Interest | C81: =-IFERROR(IPMT($F$7,MAX(D76,1),$G$7,$E$7),0) -> 287202.99 | D81: =SUMIF($D73:$AQ73,D$73,$D77:$AQ77) -> 287202.99 | E81: =SUMIF($D73:$AQ73,E$73,$D77:$AQ77) -> 0 | F81: =SUMIF($D73:$AQ73,F$73,$D77:$AQ77) -> 0 | G81: =SUMIF($D73:$AQ73,G$73,$D77:$AQ77) -> 0 | H81: =SUMIF($D73:$AQ73,H$73,$D77:$AQ77) -> 0 | I81: =SUMIF($D73:$AQ73,I$73,$D77:$AQ77) -> 0 | J81: =SUMIF($D73:$AQ73,J$73,$D77:$AQ77) -> 0 | K81: =SUMIF($D73:$AQ73,K$73,$D77:$AQ77) -> 0 | ... W81: =SUMIF($D73:$AQ73,W$73,$D77:$AQ77) -> 0
B82: Principal | D82: =D78 -> 2872029.9 | E82: =E78 -> 0 | F82: =F78 -> 0 | G82: =G78 -> 0 | H82: =H78 -> 0 | I82: =I78 -> 0 | J82: =J78 -> 0 | K82: =K78 -> 0 | ... W82: =W78 -> 0
B83: Total | C83: =SUM(C81:C82) -> 287202.99 | D83: =SUM(D81:D82) -> 3159232.8 | E83: =SUM(E81:E82) -> 0 | F83: =SUM(F81:F82) -> 0 | G83: =SUM(G81:G82) -> 0 | H83: =SUM(H81:H82) -> 0 | I83: =SUM(I81:I82) -> 0 | J83: =SUM(J81:J82) -> 0 | ... W83: =SUM(W81:W82) -> 0
B84: Current and Long-Term Liabilities
B85: Current Liabilities | C85: =D82 -> 2872029.9 | D85: =E82 -> 0 | E85: =F82 -> 0 | F85: =G82 -> 0 | G85: =H82 -> 0 | H85: =I82 -> 0 | I85: =J82 -> 0 | J85: =K82 -> 0 | ... W85: =X82 -> 0
B86: Long-Term Liabilities | C86: =$E$7-C85 -> 0 | D86: =C86-D85 -> 0 | E86: =D86-E85 -> 0 | F86: =E86-F85 -> 0 | G86: =F86-G85 -> 0 | H86: =G86-H85 -> 0 | I86: =H86-I85 -> 0 | J86: =I86-J85 -> 0 | K86: =J86-K85 -> 0 | ... W86: =V86-W85 -> 0
A89: =A72+1 -> 4 | B89: ="Year "&A89&" Working Capital Financing" -> Year 4 Working Capital Financing
C90: 0 | D90: 1 | E90: 2 | F90: 3 | G90: 4 | H90: 5 | I90: 6 | J90: 7 | K90: 8 | L90: 9 | M90: 10 | N90: 11 | O90: 12 | P90: 13 | Q90: 14 | R90: 15 | S90: 16 | T90: 17 | U90: 18 | V90: 19 | W90: 20
B91: Interest & Principal by Payment
B92: Interest Pmt. | D92: 1 | E92: 2 | F92: 3 | G92: 4 | H92: 5 | I92: 6 | J92: 7 | K92: 8 | L92: 9 | M92: 10 | N92: 11 | O92: 12 | P92: 13 | Q92: 14 | R92: 15 | S92: 16 | T92: 17 | U92: 18 | V92: 19 | W92: 20
B93: Principal Pmt. | D93: =MAX(D92-($H$8),0) -> 1 | E93: =MAX(E92-($H$8),0) -> 2 | F93: =MAX(F92-($H$8),0) -> 3 | G93: =MAX(G92-($H$8),0) -> 4 | H93: =MAX(H92-($H$8),0) -> 5 | I93: =MAX(I92-($H$8),0) -> 6 | J93: =MAX(J92-($H$8),0) -> 7 | K93: =MAX(K92-($H$8),0) -> 8 | ... W93: =MAX(W92-($H$8),0) -> 20
B94: Interest | D94: =-IFERROR(IPMT($F$8,MAX(D93,1),$G$8,$E$8),0) -> 0 | E94: =-IFERROR(IPMT($F$8,MAX(E93,1),$G$8,$E$8),0) -> 0 | F94: =-IFERROR(IPMT($F$8,MAX(F93,1),$G$8,$E$8),0) -> 0 | G94: =-IFERROR(IPMT($F$8,MAX(G93,1),$G$8,$E$8),0) -> 0 | H94: =-IFERROR(IPMT($F$8,MAX(H93,1),$G$8,$E$8),0) -> 0 | I94: =-IFERROR(IPMT($F$8,MAX(I93,1),$G$8,$E$8),0) -> 0 | J94: =-IFERROR(IPMT($F$8,MAX(J93,1),$G$8,$E$8),0) -> 0 | K94: =-IFERROR(IPMT($F$8,MAX(K93,1),$G$8,$E$8),0) -> 0 | ... W94: =-IFERROR(IPMT($F$8,MAX(W93,1),$G$8,$E$8),0) -> 0
B95: Principal | D95: =-IFERROR(PPMT($F$8,D93,$G$8,$E$8),0) -> 0 | E95: =-IFERROR(PPMT($F$8,E93,$G$8,$E$8),0) -> 0 | F95: =-IFERROR(PPMT($F$8,F93,$G$8,$E$8),0) -> 0 | G95: =-IFERROR(PPMT($F$8,G93,$G$8,$E$8),0) -> 0 | H95: =-IFERROR(PPMT($F$8,H93,$G$8,$E$8),0) -> 0 | I95: =-IFERROR(PPMT($F$8,I93,$G$8,$E$8),0) -> 0 | J95: =-IFERROR(PPMT($F$8,J93,$G$8,$E$8),0) -> 0 | K95: =-IFERROR(PPMT($F$8,K93,$G$8,$E$8),0) -> 0 | ... W95: =-IFERROR(PPMT($F$8,W93,$G$8,$E$8),0) -> 0
B96: Total | D96: =SUM(D94:D95) -> 0 | E96: =SUM(E94:E95) -> 0 | F96: =SUM(F94:F95) -> 0 | G96: =SUM(G94:G95) -> 0 | H96: =SUM(H94:H95) -> 0 | I96: =SUM(I94:I95) -> 0 | J96: =SUM(J94:J95) -> 0 | K96: =SUM(K94:K95) -> 0 | ... W96: =SUM(W94:W95) -> 0
B97: Interest & Principal by Year
B98: Interest | C98: =-IFERROR(IPMT($F$8,MAX(D93,1),$G$8,$E$8),0) -> 0 | D98: =SUMIF($D90:$AQ90,D$90,$D94:$AQ94) -> 0 | E98: =SUMIF($D90:$AQ90,E$90,$D94:$AQ94) -> 0 | F98: =SUMIF($D90:$AQ90,F$90,$D94:$AQ94) -> 0 | G98: =SUMIF($D90:$AQ90,G$90,$D94:$AQ94) -> 0 | H98: =SUMIF($D90:$AQ90,H$90,$D94:$AQ94) -> 0 | I98: =SUMIF($D90:$AQ90,I$90,$D94:$AQ94) -> 0 | J98: =SUMIF($D90:$AQ90,J$90,$D94:$AQ94) -> 0 | K98: =SUMIF($D90:$AQ90,K$90,$D94:$AQ94) -> 0 | ... W98: =SUMIF($D90:$AQ90,W$90,$D94:$AQ94) -> 0
B99: Principal | D99: =D95 -> 0 | E99: =E95 -> 0 | F99: =F95 -> 0 | G99: =G95 -> 0 | H99: =H95 -> 0 | I99: =I95 -> 0 | J99: =J95 -> 0 | K99: =K95 -> 0 | ... W99: =W95 -> 0
B100: Total | C100: =SUM(C98:C99) -> 0 | D100: =SUM(D98:D99) -> 0 | E100: =SUM(E98:E99) -> 0 | F100: =SUM(F98:F99) -> 0 | G100: =SUM(G98:G99) -> 0 | H100: =SUM(H98:H99) -> 0 | I100: =SUM(I98:I99) -> 0 | J100: =SUM(J98:J99) -> 0 | ... W100: =SUM(W98:W99) -> 0
B101: Current and Long-Term Liabilities
B102: Current Liabilities | C102: =D99 -> 0 | D102: =E99 -> 0 | E102: =F99 -> 0 | F102: =G99 -> 0 | G102: =H99 -> 0 | H102: =I99 -> 0 | I102: =J99 -> 0 | J102: =K99 -> 0 | ... W102: =X99 -> 0
B103: Long-Term Liabilities | C103: =$E$8-C102 -> 0 | D103: =C103-D102 -> 0 | E103: =D103-E102 -> 0 | F103: =E103-F102 -> 0 | G103: =F103-G102 -> 0 | H103: =G103-H102 -> 0 | I103: =H103-I102 -> 0 | J103: =I103-J102 -> 0 | K103: =J103-K102 -> 0 | ... W103: =V103-W102 -> 0
A106: =A89+1 -> 5 | B106: ="Year "&A106&" Working Capital Financing" -> Year 5 Working Capital Financing
C107: 0 | D107: 1 | E107: 2 | F107: 3 | G107: 4 | H107: 5 | I107: 6 | J107: 7 | K107: 8 | L107: 9 | M107: 10 | N107: 11 | O107: 12 | P107: 13 | Q107: 14 | R107: 15 | S107: 16 | T107: 17 | U107: 18 | V107: 19 | W107: 20
B108: Interest & Principal by Payment
B109: Interest Pmt. | D109: 1 | E109: 2 | F109: 3 | G109: 4 | H109: 5 | I109: 6 | J109: 7 | K109: 8 | L109: 9 | M109: 10 | N109: 11 | O109: 12 | P109: 13 | Q109: 14 | R109: 15 | S109: 16 | T109: 17 | U109: 18 | V109: 19 | W109: 20
B110: Principal Pmt. | D110: =MAX(D109-($H$9),0) -> 1 | E110: =MAX(E109-($H$9),0) -> 2 | F110: =MAX(F109-($H$9),0) -> 3 | G110: =MAX(G109-($H$9),0) -> 4 | H110: =MAX(H109-($H$9),0) -> 5 | I110: =MAX(I109-($H$9),0) -> 6 | J110: =MAX(J109-($H$9),0) -> 7 | K110: =MAX(K109-($H$9),0) -> 8 | ... W110: =MAX(W109-($H$9),0) -> 20
B111: Interest | D111: =-IFERROR(IPMT($F$9,MAX(D110,1),$G$9,$E$9),0) -> 0 | E111: =-IFERROR(IPMT($F$9,MAX(E110,1),$G$9,$E$9),0) -> 0 | F111: =-IFERROR(IPMT($F$9,MAX(F110,1),$G$9,$E$9),0) -> 0 | G111: =-IFERROR(IPMT($F$9,MAX(G110,1),$G$9,$E$9),0) -> 0 | H111: =-IFERROR(IPMT($F$9,MAX(H110,1),$G$9,$E$9),0) -> 0 | I111: =-IFERROR(IPMT($F$9,MAX(I110,1),$G$9,$E$9),0) -> 0 | J111: =-IFERROR(IPMT($F$9,MAX(J110,1),$G$9,$E$9),0) -> 0 | K111: =-IFERROR(IPMT($F$9,MAX(K110,1),$G$9,$E$9),0) -> 0 | ... W111: =-IFERROR(IPMT($F$9,MAX(W110,1),$G$9,$E$9),0) -> 0
B112: Principal | D112: =-IFERROR(PPMT($F$9,D110,$G$9,$E$9),0) -> 0 | E112: =-IFERROR(PPMT($F$9,E110,$G$9,$E$9),0) -> 0 | F112: =-IFERROR(PPMT($F$9,F110,$G$9,$E$9),0) -> 0 | G112: =-IFERROR(PPMT($F$9,G110,$G$9,$E$9),0) -> 0 | H112: =-IFERROR(PPMT($F$9,H110,$G$9,$E$9),0) -> 0 | I112: =-IFERROR(PPMT($F$9,I110,$G$9,$E$9),0) -> 0 | J112: =-IFERROR(PPMT($F$9,J110,$G$9,$E$9),0) -> 0 | K112: =-IFERROR(PPMT($F$9,K110,$G$9,$E$9),0) -> 0 | ... W112: =-IFERROR(PPMT($F$9,W110,$G$9,$E$9),0) -> 0
B113: Total | D113: =SUM(D111:D112) -> 0 | E113: =SUM(E111:E112) -> 0 | F113: =SUM(F111:F112) -> 0 | G113: =SUM(G111:G112) -> 0 | H113: =SUM(H111:H112) -> 0 | I113: =SUM(I111:I112) -> 0 | J113: =SUM(J111:J112) -> 0 | K113: =SUM(K111:K112) -> 0 | ... W113: =SUM(W111:W112) -> 0
B114: Interest & Principal by Year
B115: Interest | C115: =-IFERROR(IPMT($F$9,MAX(D110,1),$G$9,$E$9),0) -> 0 | D115: =SUMIF($D107:$AQ107,D$107,$D111:$AQ111) -> 0 | E115: =SUMIF($D107:$AQ107,E$107,$D111:$AQ111) -> 0 | F115: =SUMIF($D107:$AQ107,F$107,$D111:$AQ111) -> 0 | G115: =SUMIF($D107:$AQ107,G$107,$D111:$AQ111) -> 0 | H115: =SUMIF($D107:$AQ107,H$107,$D111:$AQ111) -> 0 | I115: =SUMIF($D107:$AQ107,I$107,$D111:$AQ111) -> 0 | J115: =SUMIF($D107:$AQ107,J$107,$D111:$AQ111) -> 0 | K115: =SUMIF($D107:$AQ107,K$107,$D111:$AQ111) -> 0 | ... W115: =SUMIF($D107:$AQ107,W$107,$D111:$AQ111) -> 0
B116: Principal | D116: =D112 -> 0 | E116: =E112 -> 0 | F116: =F112 -> 0 | G116: =G112 -> 0 | H116: =H112 -> 0 | I116: =I112 -> 0 | J116: =J112 -> 0 | K116: =K112 -> 0 | ... W116: =W112 -> 0
B117: Total | C117: =SUM(C115:C116) -> 0 | D117: =SUM(D115:D116) -> 0 | E117: =SUM(E115:E116) -> 0 | F117: =SUM(F115:F116) -> 0 | G117: =SUM(G115:G116) -> 0 | H117: =SUM(H115:H116) -> 0 | I117: =SUM(I115:I116) -> 0 | J117: =SUM(J115:J116) -> 0 | ... W117: =SUM(W115:W116) -> 0
...

Sheet Depreciation
B1: Company/Project: | C1: =Cover!$C$10 -> Mr. Amir Artine | D1: =Cover!$C$3 -> Cattle Integration, Baghara, Chad | G1: Last Update: | H1: =Cover!$C$13 -> 45763
B3: Depreciation Calculation
D4: Year 0 | E4: Year 1 | F4: Year 2 | G4: Year 3 | H4: Year 4 | I4: Reinvestment*
B5: CAPEX
B6: ='Data Input'!B12 -> Establishment cost | D6: ='Data Input'!D12*Dashboard!$C$102 -> 37124290 | E6: ='Data Input'!E12*Dashboard!$C$102 -> 13382679 | F6: ='Data Input'!F12*Dashboard!$C$102 -> 0 | G6: ='Data Input'!G12*Dashboard!$C$102 -> 0 | H6: ='Data Input'!H12*Dashboard!$C$102 -> 0 | I6: ='Data Input'!I12 -> 0
B7: Total | D7: =SUM(D6:D6) -> 37124290 | E7: =SUM(E6:E6) -> 13382679 | F7: =SUM(F6:F6) -> 0 | G7: =SUM(G6:G6) -> 0 | H7: =SUM(H6:H6) -> 0
B8: Annual Depreciation | C8: Depreciation Years
B9: =B6 -> Establishment cost | C9: ='Data Input'!C12+1E-100 -> 20 | D9: =IFERROR(D6/$C9,) -> 1856214.5 | E9: =IFERROR(E6/$C9,) -> 669133.96 | F9: =IFERROR(F6/$C9,) -> 0 | G9: =IFERROR(G6/$C9,) -> 0 | H9: =IFERROR(H6/$C9,) -> 0
I10: * 1-Yes; 2-No
B12: Depreciation by Year
D13: 1 | E13: 2 | F13: 3 | G13: 4 | H13: 5 | I13: 6 | J13: 7 | K13: 8 | L13: 9 | M13: 10 | N13: 11 | O13: 12 | P13: 13 | Q13: 14 | R13: 15 | S13: 16 | T13: 17 | U13: 18 | V13: 19 | W13: 20
B14: Depreciation on Year 0 Investment
B15: =$B$6 -> Establishment cost | D15: =IF($I6=1,$D9,IF($C9>=D$13,$D9,0)) -> 1856214.5 | E15: =IF($I6=1,$D9,IF($C9>=E$13,$D9,0)) -> 1856214.5 | F15: =IF($I6=1,$D9,IF($C9>=F$13,$D9,0)) -> 1856214.5 | G15: =IF($I6=1,$D9,IF($C9>=G$13,$D9,0)) -> 1856214.5 | H15: =IF($I6=1,$D9,IF($C9>=H$13,$D9,0)) -> 1856214.5 | I15: =IF($I6=1,$D9,IF($C9>=I$13,$D9,0)) -> 1856214.5 | J15: =IF($I6=1,$D9,IF($C9>=J$13,$D9,0)) -> 1856214.5 | K15: =IF($I6=1,$D9,IF($C9>=K$13,$D9,0)) -> 1856214.5 | ... W15: =IF($I6=1,$D9,IF($C9>=W$13,$D9,0)) -> 1856214.5
B16: Total | D16: =SUM(D15:D15) -> 1856214.5 | E16: =SUM(E15:E15) -> 1856214.5 | F16: =SUM(F15:F15) -> 1856214.5 | G16: =SUM(G15:G15) -> 1856214.5 | H16: =SUM(H15:H15) -> 1856214.5 | I16: =SUM(I15:I15) -> 1856214.5 | J16: =SUM(J15:J15) -> 1856214.5 | K16: =SUM(K15:K15) -> 1856214.5 | ... W16: =SUM(W15:W15) -> 1856214.5
B17: Depreciation on Year 1 Investment
B18: =$B$6 -> Establishment cost | E18: =IF($I6=1,$E9,IF($C9>=D$13,$E9,0)) -> 669133.96 | F18: =IF($I6=1,$E9,IF($C9>=E$13,$E9,0)) -> 669133.96 | G18: =IF($I6=1,$E9,IF($C9>=F$13,$E9,0)) -> 669133.96 | H18: =IF($I6=1,$E9,IF($C9>=G$13,$E9,0)) -> 669133.96 | I18: =IF($I6=1,$E9,IF($C9>=H$13,$E9,0)) -> 669133.96 | J18: =IF($I6=1,$E9,IF($C9>=I$13,$E9,0)) -> 669133.96 | K18: =IF($I6=1,$E9,IF($C9>=J$13,$E9,0)) -> 669133.96 | L18: =IF($I6=1,$E9,IF($C9>=K$13,$E9,0)) -> 669133.96 | ... W18: =IF($I6=1,$E9,IF($C9>=V$13,$E9,0)) -> 669133.96
B19: =B7 -> Total | D19: =SUM(D18:D18) -> 0 | E19: =SUM(E18:E18) -> 669133.96 | F19: =SUM(F18:F18) -> 669133.96 | G19: =SUM(G18:G18) -> 669133.96 | H19: =SUM(H18:H18) -> 669133.96 | I19: =SUM(I18:I18) -> 669133.96 | J19: =SUM(J18:J18) -> 669133.96 | K19: =SUM(K18:K18) -> 669133.96 | ... W19: =SUM(W18:W18) -> 669133.96
B20: Depreciation on Year 2 Investment
B21: =$B$6 -> Establishment cost | F21: =IF($I6=1,$F9,IF($C9>=D$13,$F9,0)) -> 0 | G21: =IF($I6=1,$F9,IF($C9>=E$13,$F9,0)) -> 0 | H21: =IF($I6=1,$F9,IF($C9>=F$13,$F9,0)) -> 0 | I21: =IF($I6=1,$F9,IF($C9>=G$13,$F9,0)) -> 0 | J21: =IF($I6=1,$F9,IF($C9>=H$13,$F9,0)) -> 0 | K21: =IF($I6=1,$F9,IF($C9>=I$13,$F9,0)) -> 0 | L21: =IF($I6=1,$F9,IF($C9>=J$13,$F9,0)) -> 0 | M21: =IF($I6=1,$F9,IF($C9>=K$13,$F9,0)) -> 0 | ... W21: =IF($I6=1,$F9,IF($C9>=U$13,$F9,0)) -> 0
B22: =B7 -> Total | D22: =SUM(D21:D21) -> 0 | E22: =SUM(E21:E21) -> 0 | F22: =SUM(F21:F21) -> 0 | G22: =SUM(G21:G21) -> 0 | H22: =SUM(H21:H21) -> 0 | I22: =SUM(I21:I21) -> 0 | J22: =SUM(J21:J21) -> 0 | K22: =SUM(K21:K21) -> 0 | ... W22: =SUM(W21:W21) -> 0
B23: Depreciation on Year 3 Investment
B24: =$B$6 -> Establishment cost | G24: =IF($I6=1,$G9,IF($C9>=D$13,$G9,0)) -> 0 | H24: =IF($I6=1,$G9,IF($C9>=E$13,$G9,0)) -> 0 | I24: =IF($I6=1,$G9,IF($C9>=F$13,$G9,0)) -> 0 | J24: =IF($I6=1,$G9,IF($C9>=G$13,$G9,0)) -> 0 | K24: =IF($I6=1,$G9,IF($C9>=H$13,$G9,0)) -> 0 | L24: =IF($I6=1,$G9,IF($C9>=I$13,$G9,0)) -> 0 | M24: =IF($I6=1,$G9,IF($C9>=J$13,$G9,0)) -> 0 | N24: =IF($I6=1,$G9,IF($C9>=K$13,$G9,0)) -> 0 | ... W24: =IF($I6=1,$G9,IF($C9>=T$13,$G9,0)) -> 0
B25: =B7 -> Total | D25: =SUM(D24:D24) -> 0 | E25: =SUM(E24:E24) -> 0 | F25: =SUM(F24:F24) -> 0 | G25: =SUM(G24:G24) -> 0 | H25: =SUM(H24:H24) -> 0 | I25: =SUM(I24:I24) -> 0 | J25: =SUM(J24:J24) -> 0 | K25: =SUM(K24:K24) -> 0 | ... W25: =SUM(W24:W24) -> 0
B26: Depreciation on Year 4 Investment
B27: =$B$6 -> Establishment cost | H27: =IF($I6=1,$H9,IF($C9>=D$13,$H9,0)) -> 0 | I27: =IF($I6=1,$H9,IF($C9>=E$13,$H9,0)) -> 0 | J27: =IF($I6=1,$H9,IF($C9>=F$13,$H9,0)) -> 0 | K27: =IF($I6=1,$H9,IF($C9>=G$13,$H9,0)) -> 0 | L27: =IF($I6=1,$H9,IF($C9>=H$13,$H9,0)) -> 0 | M27: =IF($I6=1,$H9,IF($C9>=I$13,$H9,0)) -> 0 | N27: =IF($I6=1,$H9,IF($C9>=J$13,$H9,0)) -> 0 | O27: =IF($I6=1,$H9,IF($C9>=K$13,$H9,0)) -> 0 | ... W27: =IF($I6=1,$H9,IF($C9>=S$13,$H9,0)) -> 0
B28: =B7 -> Total | D28: =SUM(D27:D27) -> 0 | E28: =SUM(E27:E27) -> 0 | F28: =SUM(F27:F27) -> 0 | G28: =SUM(G27:G27) -> 0 | H28: =SUM(H27:H27) -> 0 | I28: =SUM(I27:I27) -> 0 | J28: =SUM(J27:J27) -> 0 | K28: =SUM(K27:K27) -> 0 | ... W28: =SUM(W27:W27) -> 0
B29: Grand Total | D29: =SUM(D16,D19,D22,D25,D28) -> 1856214.5 | E29: =SUM(E16,E19,E22,E25,E28) -> 2525348.5 | F29: =SUM(F16,F19,F22,F25,F28) -> 2525348.5 | G29: =SUM(G16,G19,G22,G25,G28) -> 2525348.5 | H29: =SUM(H16,H19,H22,H25,H28) -> 2525348.5 | I29: =SUM(I16,I19,I22,I25,I28) -> 2525348.5 | J29: =SUM(J16,J19,J22,J25,J28) -> 2525348.5 | K29: =SUM(K16,K19,K22,K25,K28) -> 2525348.5 | ... W29: =SUM(W16,W19,W22,W25,W28) -> 2525348.5
B32: Reinvestment by Year
D33: 1 | E33: 2 | F33: 3 | G33: 4 | H33: 5 | I33: 6 | J33: 7 | K33: 8 | L33: 9 | M33: 10 | N33: 11 | O33: 12 | P33: 13 | Q33: 14 | R33: 15 | S33: 16 | T33: 17 | U33: 18 | V33: 19 | W33: 20
B34: Reinvestment on Year 0 Investment
B35: =$B$6 -> Establishment cost | E35: =IF(INT(D$33/($C9))=D$33/($C9),$D6,0)*$I6 -> 0 | F35: =IF(INT(E$33/($C9))=E$33/($C9),$D6,0)*$I6 -> 0 | G35: =IF(INT(F$33/($C9))=F$33/($C9),$D6,0)*$I6 -> 0 | H35: =IF(INT(G$33/($C9))=G$33/($C9),$D6,0)*$I6 -> 0 | I35: =IF(INT(H$33/($C9))=H$33/($C9),$D6,0)*$I6 -> 0 | J35: =IF(INT(I$33/($C9))=I$33/($C9),$D6,0)*$I6 -> 0 | K35: =IF(INT(J$33/($C9))=J$33/($C9),$D6,0)*$I6 -> 0 | L35: =IF(INT(K$33/($C9))=K$33/($C9),$D6,0)*$I6 -> 0 | ... W35: =IF(INT(V$33/($C9))=V$33/($C9),$D6,0)*$I6 -> 0
B36: Total | E36: =SUM(E35:E35) -> 0 | F36: =SUM(F35:F35) -> 0 | G36: =SUM(G35:G35) -> 0 | H36: =SUM(H35:H35) -> 0 | I36: =SUM(I35:I35) -> 0 | J36: =SUM(J35:J35) -> 0 | K36: =SUM(K35:K35) -> 0 | L36: =SUM(L35:L35) -> 0 | ... W36: =SUM(W35:W35) -> 0
B37: Reinvestment on Year 1 Investment
B38: =$B$6 -> Establishment cost | F38: =IF(INT(D$33/($C9))=D$33/($C9),$E6,0)*$I6 -> 0 | G38: =IF(INT(E$33/($C9))=E$33/($C9),$E6,0)*$I6 -> 0 | H38: =IF(INT(F$33/($C9))=F$33/($C9),$E6,0)*$I6 -> 0 | I38: =IF(INT(G$33/($C9))=G$33/($C9),$E6,0)*$I6 -> 0 | J38: =IF(INT(H$33/($C9))=H$33/($C9),$E6,0)*$I6 -> 0 | K38: =IF(INT(I$33/($C9))=I$33/($C9),$E6,0)*$I6 -> 0 | L38: =IF(INT(J$33/($C9))=J$33/($C9),$E6,0)*$I6 -> 0 | M38: =IF(INT(K$33/($C9))=K$33/($C9),$E6,0)*$I6 -> 0 | ... W38: =IF(INT(U$33/($C9))=U$33/($C9),$E6,0)*$I6 -> 0
B39: =B36 -> Total | F39: =SUM(F38:F38) -> 0 | G39: =SUM(G38:G38) -> 0 | H39: =SUM(H38:H38) -> 0 | I39: =SUM(I38:I38) -> 0 | J39: =SUM(J38:J38) -> 0 | K39: =SUM(K38:K38) -> 0 | L39: =SUM(L38:L38) -> 0 | M39: =SUM(M38:M38) -> 0 | ... W39: =SUM(W38:W38) -> 0
B40: Reinvestment on Year 2 Investment
B41: =$B$6 -> Establishment cost | G41: =IF(INT(D$33/($C9))=D$33/($C9),$F6,0)*$I6 -> 0 | H41: =IF(INT(E$33/($C9))=E$33/($C9),$F6,0)*$I6 -> 0 | I41: =IF(INT(F$33/($C9))=F$33/($C9),$F6,0)*$I6 -> 0 | J41: =IF(INT(G$33/($C9))=G$33/($C9),$F6,0)*$I6 -> 0 | K41: =IF(INT(H$33/($C9))=H$33/($C9),$F6,0)*$I6 -> 0 | L41: =IF(INT(I$33/($C9))=I$33/($C9),$F6,0)*$I6 -> 0 | M41: =IF(INT(J$33/($C9))=J$33/($C9),$F6,0)*$I6 -> 0 | N41: =IF(INT(K$33/($C9))=K$33/($C9),$F6,0)*$I6 -> 0 | ... W41: =IF(INT(T$33/($C9))=T$33/($C9),$F6,0)*$I6 -> 0
B42: =B36 -> Total | G42: =SUM(G41:G41) -> 0 | H42: =SUM(H41:H41) -> 0 | I42: =SUM(I41:I41) -> 0 | J42: =SUM(J41:J41) -> 0 | K42: =SUM(K41:K41) -> 0 | L42: =SUM(L41:L41) -> 0 | M42: =SUM(M41:M41) -> 0 | N42: =SUM(N41:N41) -> 0 | ... W42: =SUM(W41:W41) -> 0
B43: Reinvestment on Year 3 Investment
B44: =$B$6 -> Establishment cost | H44: =IF(INT(D$33/($C9))=D$33/($C9),$G6,0)*$I6 -> 0 | I44: =IF(INT(E$33/($C9))=E$33/($C9),$G6,0)*$I6 -> 0 | J44: =IF(INT(F$33/($C9))=F$33/($C9),$G6,0)*$I6 -> 0 | K44: =IF(INT(G$33/($C9))=G$33/($C9),$G6,0)*$I6 -> 0 | L44: =IF(INT(H$33/($C9))=H$33/($C9),$G6,0)*$I6 -> 0 | M44: =IF(INT(I$33/($C9))=I$33/($C9),$G6,0)*$I6 -> 0 | N44: =IF(INT(J$33/($C9))=J$33/($C9),$G6,0)*$I6 -> 0 | O44: =IF(INT(K$33/($C9))=K$33/($C9),$G6,0)*$I6 -> 0 | ... W44: =IF(INT(S$33/($C9))=S$33/($C9),$G6,0)*$I6 -> 0
B45: =B36 -> Total | H45: =SUM(H44:H44) -> 0 | I45: =SUM(I44:I44) -> 0 | J45: =SUM(J44:J44) -> 0 | K45: =SUM(K44:K44) -> 0 | L45: =SUM(L44:L44) -> 0 | M45: =SUM(M44:M44) -> 0 | N45: =SUM(N44:N44) -> 0 | O45: =SUM(O44:O44) -> 0 | ... W45: =SUM(W44:W44) -> 0
B46: Reinvestment on Year 4 Investment
B47: =$B$6 -> Establishment cost | I47: =IF(INT(D$33/($C9))=D$33/($C9),$H6,0)*$I6 -> 0 | J47: =IF(INT(E$33/($C9))=E$33/($C9),$H6,0)*$I6 -> 0 | K47: =IF(INT(F$33/($C9))=F$33/($C9),$H6,0)*$I6 -> 0 | L47: =IF(INT(G$33/($C9))=G$33/($C9),$H6,0)*$I6 -> 0 | M47: =IF(INT(H$33/($C9))=H$33/($C9),$H6,0)*$I6 -> 0 | N47: =IF(INT(I$33/($C9))=I$33/($C9),$H6,0)*$I6 -> 0 | O47: =IF(INT(J$33/($C9))=J$33/($C9),$H6,0)*$I6 -> 0 | P47: =IF(INT(K$33/($C9))=K$33/($C9),$H6,0)*$I6 -> 0 | ... W47: =IF(INT(R$33/($C9))=R$33/($C9),$H6,0)*$I6 -> 0
B48: =B36 -> Total | I48: =SUM(I47:I47) -> 0 | J48: =SUM(J47:J47) -> 0 | K48: =SUM(K47:K47) -> 0 | L48: =SUM(L47:L47) -> 0 | M48: =SUM(M47:M47) -> 0 | N48: =SUM(N47:N47) -> 0 | O48: =SUM(O47:O47) -> 0 | P48: =SUM(P47:P47) -> 0 | ... W48: =SUM(W47:W47) -> 0
B49: Grand Total | E49: =SUM(E36,E39,E42,E45,E48) -> 0 | F49: =SUM(F36,F39,F42,F45,F48) -> 0 | G49: =SUM(G36,G39,G42,G45,G48) -> 0 | H49: =SUM(H36,H39,H42,H45,H48) -> 0 | I49: =SUM(I36,I39,I42,I45,I48) -> 0 | J49: =SUM(J36,J39,J42,J45,J48) -> 0 | K49: =SUM(K36,K39,K42,K45,K48) -> 0 | L49: =SUM(L36,L39,L42,L45,L48) -> 0 | ... W49: =SUM(W36,W39,W42,W45,W48) -> 0

Sheet Revenues
B1: Company/Project: | C1: =Cover!$C$10 -> Mr. Amir Artine | D1: =Cover!$C$3 -> Cattle Integration, Baghara, Chad | G1: Last Update: | H1: =Cover!$C$13 -> 45763
C5: Year 1 | D5: Year 2 | E5: Year 3 | F5: Year 4 | G5: Year 5 | H5: Year 6 | I5: Year 7 | J5: Year 8 | K5: Year 9 | L5: Year 10 | M5: Year 11 | N5: Year 12
B6: Field Crop Operation
B7: Field crop excess production | C7: 212035.74 | D7: 522605.18 | E7: 512428.91 | F7: 377742.12 | G7: 297450.31 | H7: 304267.62 | I7: 254379.08 | J7: 265197.29 | K7: 272000.25 | L7: 278835.21 | M7: 285702.36 | N7: 292601.85
B8: Dairy Operation
B9: Pasteurized Milk | C9: ='Dairy Product Composition'!H15 -> 96000 | D9: ='Dairy Product Composition'!I15 -> 140400 | E9: ='Dairy Product Composition'!J15 -> 247087.38 | F9: ='Dairy Product Composition'!K15 -> 359914.57 | G9: ='Dairy Product Composition'!L15 -> 517807.09 | H9: ='Dairy Product Composition'!M15 -> 685754.4 | I9: ='Dairy Product Composition'!N15 -> 783229.49 | J9: ='Dairy Product Composition'!O15 -> 831661.22 | ... N9: ='Dairy Product Composition'!S15 -> 878383.07
B10: UHT Milk | C10: ='Dairy Product Composition'!H16 -> 166829.27 | D10: ='Dairy Product Composition'!I16 -> 243987.8 | E10: ='Dairy Product Composition'!J16 -> 429389.65 | F10: ='Dairy Product Composition'!K16 -> 625461.3 | G10: ='Dairy Product Composition'!L16 -> 899847.69 | H10: ='Dairy Product Composition'!M16 -> 1191707.3 | I10: ='Dairy Product Composition'!N16 -> 1361100 | J10: ='Dairy Product Composition'!O16 -> 1445264.9 | ... N10: ='Dairy Product Composition'!S16 -> 1526458.4
B11: Flavoured UHT Milk | C11: ='Dairy Product Composition'!H17 -> 0 | D11: ='Dairy Product Composition'!I17 -> 0 | E11: ='Dairy Product Composition'!J17 -> 0 | F11: ='Dairy Product Composition'!K17 -> 0 | G11: ='Dairy Product Composition'!L17 -> 0 | H11: ='Dairy Product Composition'!M17 -> 0 | I11: ='Dairy Product Composition'!N17 -> 0 | J11: ='Dairy Product Composition'!O17 -> 0 | ... N11: ='Dairy Product Composition'!S17 -> 0
B12: Plain yoghurt | C12: ='Dairy Product Composition'!H18 -> 1050000 | D12: ='Dairy Product Composition'!I18 -> 1535625 | E12: ='Dairy Product Composition'!J18 -> 2702518.2 | F12: ='Dairy Product Composition'!K18 -> 3936565.6 | G12: ='Dairy Product Composition'!L18 -> 5663515.1 | H12: ='Dairy Product Composition'!M18 -> 7500438.7 | I12: ='Dairy Product Composition'!N18 -> 8566572.5 | J12: ='Dairy Product Composition'!O18 -> 9096294.6 | ... N12: ='Dairy Product Composition'!S18 -> 9607314.8
B13: Flavoured yoghurt | C13: ='Dairy Product Composition'!H19 -> 1152439 | D13: ='Dairy Product Composition'!I19 -> 1685442.1 | E13: ='Dairy Product Composition'!J19 -> 2966178.5 | F13: ='Dairy Product Composition'!K19 -> 4320620.8 | G13: ='Dairy Product Composition'!L19 -> 6216053.1 | H13: ='Dairy Product Composition'!M19 -> 8232188.8 | I13: ='Dairy Product Composition'!N19 -> 9402335.7 | J13: ='Dairy Product Composition'!O19 -> 9983737.9 | ... N13: ='Dairy Product Composition'!S19 -> 10544614
B14: Ice Cream | C14: ='Dairy Product Composition'!H20 -> 128963.41 | D14: ='Dairy Product Composition'!I20 -> 188608.99 | E14: ='Dairy Product Composition'!J20 -> 331929.5 | F14: ='Dairy Product Composition'!K20 -> 483498.04 | G14: ='Dairy Product Composition'!L20 -> 695605.95 | H14: ='Dairy Product Composition'!M20 -> 921221.13 | I14: ='Dairy Product Composition'!N20 -> 1052166.1 | J14: ='Dairy Product Composition'!O20 -> 1117227.8 | ... N14: ='Dairy Product Composition'!S20 -> 1179992.5
A15: 1500 | B15: Pregnant heifers | C15: 0 | D15: 0 | E15: 0 | F15: 0 | G15: 70878.263 | H15: 315551.24 | I15: 393114.45 | J15: 392868.75 | K15: 392623.21 | L15: 392377.82 | M15: 392132.59 | N15: 391887.5
B16: Total Dairy Operation | C16: =SUM(C9:C15) -> 2594231.7 | D16: =SUM(D9:D15) -> 3794063.9 | E16: =SUM(E9:E15) -> 6677103.2 | F16: =SUM(F9:F15) -> 9726060.4 | G16: =SUM(G9:G15) -> 14063707 | H16: =SUM(H9:H15) -> 18846862 | I16: =SUM(I9:I15) -> 21558518 | J16: =SUM(J9:J15) -> 22867055 | ... N16: =SUM(N9:N15) -> 24128650
B17: Beef Operation
A18: 2.5 | B18: Carcass | C18: =$A18*'Beef Product Composition'!D9 -> 3107812.5 | D18: =$A18*'Beef Product Composition'!E9 -> 6247946.2 | E18: =$A18*'Beef Product Composition'!F9 -> 6275350.7 | F18: =$A18*'Beef Product Composition'!G9 -> 6290194.8 | G18: =$A18*'Beef Product Composition'!H9 -> 6305027.6 | H18: =$A18*'Beef Product Composition'!I9 -> 6317110.5 | I18: =$A18*'Beef Product Composition'!J9 -> 6317047.1 | J18: =$A18*'Beef Product Composition'!K9 -> 6316983.7 | ... N18: =$A18*'Beef Product Composition'!O9 -> 6316730.6
A19: 8 | B19: Meat | C19: =$A19*'Beef Product Composition'!D10 -> 2945250 | D19: =$A19*'Beef Product Composition'!E10 -> 5921130.6 | E19: =$A19*'Beef Product Composition'!F10 -> 5947101.5 | F19: =$A19*'Beef Product Composition'!G10 -> 5961169.2 | G19: =$A19*'Beef Product Composition'!H10 -> 5975226.2 | H19: =$A19*'Beef Product Composition'!I10 -> 5986677.1 | I19: =$A19*'Beef Product Composition'!J10 -> 5986616.9 | J19: =$A19*'Beef Product Composition'!K10 -> 5986556.9 | ... N19: =$A19*'Beef Product Composition'!O10 -> 5986317
A20: 1 | B20: Offal | C20: =$A20*'Beef Product Composition'!D11 -> 112500 | D20: =$A20*'Beef Product Composition'!E11 -> 226170 | E20: =$A20*'Beef Product Composition'!F11 -> 227162.01 | F20: =$A20*'Beef Product Composition'!G11 -> 227699.36 | G20: =$A20*'Beef Product Composition'!H11 -> 228236.29 | H20: =$A20*'Beef Product Composition'!I11 -> 228673.68 | I20: =$A20*'Beef Product Composition'!J11 -> 228671.39 | J20: =$A20*'Beef Product Composition'!K11 -> 228669.09 | ... N20: =$A20*'Beef Product Composition'!O11 -> 228659.93
A21: 8.3841463 | B21: Skin | C21: =$A21*'Beef Product Composition'!D12 -> 75457.317 | D21: =$A21*'Beef Product Composition'!E12 -> 151307.01 | E21: =$A21*'Beef Product Composition'!F12 -> 151639.7 | F21: =$A21*'Beef Product Composition'!G12 -> 151819.91 | G21: =$A21*'Beef Product Composition'!H12 -> 151999.98 | H21: =$A21*'Beef Product Composition'!I12 -> 152146.66 | I21: =$A21*'Beef Product Composition'!J12 -> 152145.89 | J21: =$A21*'Beef Product Composition'!K12 -> 152145.12 | ... N21: =$A21*'Beef Product Composition'!O12 -> 152142.05
B22: Total Beef Operation | C22: =SUM(C18:C21) -> 6241019.8 | D22: =SUM(D18:D21) -> 12546554 | E22: =SUM(E18:E21) -> 12601254 | F22: =SUM(F18:F21) -> 12630883 | G22: =SUM(G18:G21) -> 12660490 | H22: =SUM(H18:H21) -> 12684608 | I22: =SUM(I18:I21) -> 12684481 | J22: =SUM(J18:J21) -> 12684355 | ... N22: =SUM(N18:N21) -> 12683849
B23: Total | C23: =C7+C16+C22 -> 9047287.3 | D23: =D7+D16+D22 -> 16863223 | E23: =E7+E16+E22 -> 19790786 | F23: =F7+F16+F22 -> 22734686 | G23: =G7+G16+G22 -> 27021648 | H23: =H7+H16+H22 -> 31835737 | I23: =I7+I16+I22 -> 34497379 | J23: =J7+J16+J22 -> 35816607 | ... N23: =N7+N16+N22 -> 37105101
B24: Cumulative | C24: =C23+C25 -> 9047287.3 | D24: =D23+C24 -> 25910510 | E24: =E23+D24 -> 45701296 | F24: =F23+E24 -> 68435982 | G24: =G23+F24 -> 95457630 | H24: =H23+G24 -> 1.2729337e+08 | I24: =I23+H24 -> 1.6179075e+08 | J24: =J23+I24 -> 1.9760735e+08 | K24: =K23+J24 -> 2.3473753e+08 | ... N24: =N23+M24 -> 3.4607783e+08
C29: Year 1 | D29: Year 2 | E29: Year 3 | F29: Year 4 | G29: Year 5 | H29: Year 6 | I29: Year 7 | J29: Year 8 | K29: Year 9 | L29: Year 10
B30: Field Crop Operation
B31: Field crop excess production | C31: =C7/1000 -> 212.03574 | D31: =D7/1000 -> 522.60518 | E31: =E7/1000 -> 512.42891 | F31: =F7/1000 -> 377.74212 | G31: =G7/1000 -> 297.45031 | H31: =H7/1000 -> 304.26762 | I31: =I7/1000 -> 254.37908 | J31: =J7/1000 -> 265.19729 | ... L31: =L7/1000 -> 278.83521
B32: Dairy Operation
B33: Pasteurized Milk | C33: =C9/1000 -> 96 | D33: =D9/1000 -> 140.4 | E33: =E9/1000 -> 247.08738 | F33: =F9/1000 -> 359.91457 | G33: =G9/1000 -> 517.80709 | H33: =H9/1000 -> 685.7544 | I33: =I9/1000 -> 783.22949 | J33: =J9/1000 -> 831.66122 | ... L33: =L9/1000 -> 879.48208
B34: UHT Milk | C34: =C10/1000 -> 166.82927 | D34: =D10/1000 -> 243.9878 | E34: =E10/1000 -> 429.38965 | F34: =F10/1000 -> 625.4613 | G34: =G10/1000 -> 899.84769 | H34: =H10/1000 -> 1191.7073 | I34: =I10/1000 -> 1361.1 | J34: =J10/1000 -> 1445.2649 | ... L34: =L10/1000 -> 1528.3682
B35: Flavoured UHT Milk | C35: =C11/1000 -> 0 | D35: =D11/1000 -> 0 | E35: =E11/1000 -> 0 | F35: =F11/1000 -> 0 | G35: =G11/1000 -> 0 | H35: =H11/1000 -> 0 | I35: =I11/1000 -> 0 | J35: =J11/1000 -> 0 | ... L35: =L11/1000 -> 0
B36: Plain yoghurt | C36: =C12/1000 -> 1050 | D36: =D12/1000 -> 1535.625 | E36: =E12/1000 -> 2702.5182 | F36: =F12/1000 -> 3936.5656 | G36: =G12/1000 -> 5663.5151 | H36: =H12/1000 -> 7500.4387 | I36: =I12/1000 -> 8566.5725 | J36: =J12/1000 -> 9096.2946 | ... L36: =L12/1000 -> 9619.3353
B37: Flavoured yoghurt | C37: =C13/1000 -> 1152.439 | D37: =D13/1000 -> 1685.4421 | E37: =E13/1000 -> 2966.1785 | F37: =F13/1000 -> 4320.6208 | G37: =G13/1000 -> 6216.0531 | H37: =H13/1000 -> 8232.1888 | I37: =I13/1000 -> 9402.3357 | J37: =J13/1000 -> 9983.7379 | ... L37: =L13/1000 -> 10557.807
B38: Ice Cream | C38: =C14/1000 -> 128.96341 | D38: =D14/1000 -> 188.60899 | E38: =E14/1000 -> 331.9295 | F38: =F14/1000 -> 483.49804 | G38: =G14/1000 -> 695.60595 | H38: =H14/1000 -> 921.22113 | I38: =I14/1000 -> 1052.1661 | J38: =J14/1000 -> 1117.2278 | ... L38: =L14/1000 -> 1181.4689
B39: Pregnant heifers | C39: =C15/1000 -> 0 | D39: =D15/1000 -> 0 | E39: =E15/1000 -> 0 | F39: =F15/1000 -> 0 | G39: =G15/1000 -> 70.878263 | H39: =H15/1000 -> 315.55124 | I39: =I15/1000 -> 393.11445 | J39: =J15/1000 -> 392.86875 | ... L39: =L15/1000 -> 392.37782
B40: Total Dairy Operation | C40: =C16/1000 -> 2594.2317 | D40: =D16/1000 -> 3794.0639 | E40: =E16/1000 -> 6677.1032 | F40: =F16/1000 -> 9726.0604 | G40: =G16/1000 -> 14063.707 | H40: =H16/1000 -> 18846.862 | I40: =I16/1000 -> 21558.518 | J40: =J16/1000 -> 22867.055 | ... L40: =L16/1000 -> 24158.839
B41: Beef Operation
B42: Carcass | C42: =C18/1000 -> 3107.8125 | D42: =D18/1000 -> 6247.9462 | E42: =E18/1000 -> 6275.3507 | F42: =F18/1000 -> 6290.1948 | G42: =G18/1000 -> 6305.0276 | H42: =H18/1000 -> 6317.1105 | I42: =I18/1000 -> 6317.0471 | J42: =J18/1000 -> 6316.9837 | ... L42: =L18/1000 -> 6316.8571
B43: Meat | C43: =C19/1000 -> 2945.25 | D43: =D19/1000 -> 5921.1306 | E43: =E19/1000 -> 5947.1015 | F43: =F19/1000 -> 5961.1692 | G43: =G19/1000 -> 5975.2262 | H43: =H19/1000 -> 5986.6771 | I43: =I19/1000 -> 5986.6169 | J43: =J19/1000 -> 5986.5569 | ... L43: =L19/1000 -> 5986.4368
B44: Offal | C44: =C20/1000 -> 112.5 | D44: =D20/1000 -> 226.17 | E44: =E20/1000 -> 227.16201 | F44: =F20/1000 -> 227.69936 | G44: =G20/1000 -> 228.23629 | H44: =H20/1000 -> 228.67368 | I44: =I20/1000 -> 228.67139 | J44: =J20/1000 -> 228.66909 | ... L44: =L20/1000 -> 228.66451
B45: Skin | C45: =C21/1000 -> 75.457317 | D45: =D21/1000 -> 151.30701 | E45: =E21/1000 -> 151.6397 | F45: =F21/1000 -> 151.81991 | G45: =G21/1000 -> 151.99998 | H45: =H21/1000 -> 152.14666 | I45: =I21/1000 -> 152.14589 | J45: =J21/1000 -> 152.14512 | ... L45: =L21/1000 -> 152.14359
B46: Total Beef Operation | C46: =C22/1000 -> 6241.0198 | D46: =D22/1000 -> 12546.554 | E46: =E22/1000 -> 12601.254 | F46: =F22/1000 -> 12630.883 | G46: =G22/1000 -> 12660.49 | H46: =H22/1000 -> 12684.608 | I46: =I22/1000 -> 12684.481 | J46: =J22/1000 -> 12684.355 | ... L46: =L22/1000 -> 12684.102
B47: Total | C47: =C23/1000 -> 9047.2873 | D47: =D23/1000 -> 16863.223 | E47: =E23/1000 -> 19790.786 | F47: =F23/1000 -> 22734.686 | G47: =G23/1000 -> 27021.648 | H47: =H23/1000 -> 31835.737 | I47: =I23/1000 -> 34497.379 | J47: =J23/1000 -> 35816.607 | ... L47: =L23/1000 -> 37121.776
B48: Cumulative | C48: =C24/1000 -> 9047.2873 | D48: =D24/1000 -> 25910.51 | E48: =E24/1000 -> 45701.296 | F48: =F24/1000 -> 68435.982 | G48: =G24/1000 -> 95457.63 | H48: =H24/1000 -> 127293.37 | I48: =I24/1000 -> 161790.75 | J48: =J24/1000 -> 197607.35 | ... L48: =L24/1000 -> 271859.31

Sheet OPEX
B1: Company/Project: | H1: =Cover!$C$10 -> Mr. Amir Artine | I1: =Cover!$C$3 -> Cattle Integration, Baghara, Chad | L1: Last Update: | M1: =Cover!$C$13 -> 45763
C5: Unit | D5: Amount (Year 7) | E5: €/unit | F5: Total € (Year 7) | H5: Year 1 | I5: Year 2 | J5: Year 3 | K5: Year 4 | L5: Year 5 | M5: Year 6 | N5: Year 7 | O5: Year 8 | P5: Year 9 | Q5: Year 10 | R5: Year 11 | S5: Year 12
B6: Field Crops
B7: Fertilizers | C7: Complete | D7: 1 | E7: 745573.19 | F7: =D7*E7 -> 745573.19 | H7: 272745.83 | I7: 586849.01 | J7: 617032.77 | K7: 673669.79 | L7: 741072.98 | M7: 741000.66 | N7: 745573.19 | O7: 745229.38 | P7: 745208.02 | Q7: 745186.65 | R7: 745165.27 | S7: 745143.88
B8: Chemicals | C8: Complete | D8: 1 | E8: 210109.98 | F8: =D8*E8 -> 210109.98 | H8: 103194.54 | I8: 207898.05 | J8: 208106.69 | K8: 209297.94 | L8: 209797.94 | M8: 209792.92 | N8: 210109.98 | O8: 210086.14 | P8: 210084.66 | Q8: 210083.18 | R8: 210081.69 | S8: 210080.21
B9: Seeds | C9: Complete | D9: 1 | E9: 228964.86 | F9: =D9*E9 -> 228964.86 | H9: 112932.06 | I9: 227121.58 | J9: 227295.45 | K9: 228288.16 | L9: 228704.82 | M9: 228700.65 | N9: 228964.86 | O9: 228944.99 | P9: 228943.76 | Q9: 228942.52 | R9: 228941.29 | S9: 228940.05
B10: Machinery | C10: Complete | D10: 1 | E10: 246260.85 | F10: =D10*E10 -> 246260.85 | H10: 113896.84 | I10: 235282.82 | J10: 236318.31 | K10: 242230.62 | L10: 244712.17 | M10: 244687.28 | N10: 246260.85 | O10: 246142.54 | P10: 246135.19 | Q10: 246127.83 | R10: 246120.47 | S10: 246113.11
B11: Water | C11: Complete | D11: 1 | E11: 587290.82 | F11: =D11*E11 -> 587290.82 | H11: 304265.95 | I11: 599115.46 | J11: 597813.5 | K11: 590379.7 | L11: 587259.53 | M11: 587290.82 | N11: 585312.31 | O11: 585461.07 | P11: 585470.31 | Q11: 585479.56 | R11: 585488.81 | S11: 585498.07
B12: Variable manpower | C12: Complete | D12: 1 | E12: 85060.976 | F12: =D12*E12 -> 85060.976 | H12: 47103.659 | I12: 85060.976 | J12: 85060.976 | K12: 85060.976 | L12: 85060.976 | M12: 85060.976 | N12: 85060.976 | O12: 85060.976 | P12: 85060.976 | Q12: 85060.976 | R12: 85060.976 | S12: 85060.976
B13: Permanent manpower | C13: Complete | D13: 1 | E13: 41158.537 | F13: =D13*E13 -> 41158.537 | H13: 167158.54 | I13: 167158.54 | J13: 167158.54 | K13: 167158.54 | L13: 167158.54 | M13: 41158.537 | N13: 41158.537 | O13: 41158.537 | P13: 41158.537 | Q13: 41158.537 | R13: 41158.537 | S13: 41158.537
B14: Miscellaneous | C14: % | D14: 0.1 | E14: =SUM(F7:F13) -> 2144419.2 | F14: =D14*E14 -> 214441.92 | H14: =SUM(H7:H13)*$D$14 -> 112129.74 | I14: =SUM(I7:I13)*$D$14 -> 210848.64 | J14: =SUM(J7:J13)*$D$14 -> 213878.62 | K14: =SUM(K7:K13)*$D$14 -> 219608.57 | L14: =SUM(L7:L13)*$D$14 -> 226376.7 | M14: =SUM(M7:M13)*$D$14 -> 213769.19 | N14: =SUM(N7:N13)*$D$14 -> 214244.07 | O14: =SUM(O7:O13)*$D$14 -> 214208.36 | ... S14: =SUM(S7:S13)*$D$14 -> 214199.48
B15: ="Subtotal "&B6 -> Subtotal Field Crops | F15: =SUM(F7:F14) -> 2358861.1 | H15: =SUM(H7:H14) -> 1233427.2 | I15: =SUM(I7:I14) -> 2319335.1 | J15: =SUM(J7:J14) -> 2352664.9 | K15: =SUM(K7:K14) -> 2415694.3 | L15: =SUM(L7:L14) -> 2490143.7 | M15: =SUM(M7:M14) -> 2351461 | N15: =SUM(N7:N14) -> 2356684.8 | O15: =SUM(O7:O14) -> 2356292 | ... S15: =SUM(S7:S14) -> 2356194.3
B16: Total COGS | F16: =F15-F13 -> 2317702.6 | H16: =H15-H13 -> 1066268.6 | I16: =I15-I13 -> 2152176.5 | J16: =J15-J13 -> 2185506.3 | K16: =K15-K13 -> 2248535.7 | L16: =L15-L13 -> 2322985.1 | M16: =M15-M13 -> 2310302.5 | N16: =N15-N13 -> 2315526.2 | O16: =O15-O13 -> 2315133.5 | ... S16: =S15-S13 -> 2315035.8
B17: Total SG&A | F17: =F13 -> 41158.537 | H17: =H13 -> 167158.54 | I17: =I13 -> 167158.54 | J17: =J13 -> 167158.54 | K17: =K13 -> 167158.54 | L17: =L13 -> 167158.54 | M17: =M13 -> 41158.537 | N17: =N13 -> 41158.537 | O17: =O13 -> 41158.537 | ... S17: =S13 -> 41158.537
B18: Feed Center
B19: Purchased Feed | C19: Complete | D19: 1 | E19: 1370407.2 | F19: =D19*E19 -> 1370407.2 | H19: 612314.8 | I19: 986527.98 | J19: 1075811.5 | K19: 1175165.5 | L19: 1283014.2 | M19: 1352660.9 | N19: 1370407.2 | O19: 1368612.2 | P19: 1368152.4 | Q19: 1367692.9 | R19: 1367233.7 | S19: 1366774.8
B20: Corn grain purchase | C20: Mt | D20: 7851.9766 | E20: 365.85366 | F20: =D20*E20 -> 2872674.4 | H20: 1915934.5 | I20: 2865447 | J20: 2965248.4 | K20: 2852880.4 | L20: 2876537.1 | M20: 2935172 | N20: 2872674.4 | O20: 2865603.5 | P20: 2854830 | Q20: 2844007.7 | R20: 2833136.3 | S20: 2822215.8
B21: Water | C21: Lt. | D21: =10*365 -> 3650 | E21: 0.049518864 | F21: =D21*E21 -> 180.74385 | H21: =$F21 -> 180.74385 | I21: =$F21 -> 180.74385 | J21: =$F21 -> 180.74385 | K21: =$F21 -> 180.74385 | L21: =$F21 -> 180.74385 | M21: =$F21 -> 180.74385 | N21: =$F21 -> 180.74385 | O21: =$F21 -> 180.74385 | ... S21: =$F21 -> 180.74385
B22: Electric power | C22: Kw | D22: 29695.505 | E22: 0.28296494 | F22: =D22*E22 -> 8402.7867 | H22: 4198.4644 | I22: 7661.2199 | J22: 7878.4767 | K22: 8026.6498 | L22: 8234.4225 | M22: 8403.6751 | N22: 8402.7867 | O22: 8401.8987 | P22: 8401.0114 | Q22: 8400.1245 | R22: 8399.2383 | S22: 8398.3526
B23: Fuel | C23: Lt. | D23: =150*365 -> 54750 | E23: 0.83841463 | F23: =D23*E23 -> 45903.201 | H23: =$F23 -> 45903.201 | I23: =$F23 -> 45903.201 | J23: =$F23 -> 45903.201 | K23: =$F23 -> 45903.201 | L23: =$F23 -> 45903.201 | M23: =$F23 -> 45903.201 | N23: =$F23 -> 45903.201 | O23: =$F23 -> 45903.201 | ... S23: =$F23 -> 45903.201
B24: Vehicles and machinery maitenance | C24: Lt. | D24: =D23 -> 54750 | E24: 0.41920732 | F24: =D24*E24 -> 22951.601 | H24: =$F24 -> 22951.601 | I24: =$F24 -> 22951.601 | J24: =$F24 -> 22951.601 | K24: =$F24 -> 22951.601 | L24: =$F24 -> 22951.601 | M24: =$F24 -> 22951.601 | N24: =$F24 -> 22951.601 | O24: =$F24 -> 22951.601 | ... S24: =$F24 -> 22951.601
B25: Manpower, permanent | C25: Complete | D25: 1 | E25: 27439.024 | F25: =D25*E25 -> 27439.024 | H25: =F25 -> 27439.024 | I25: =H25 -> 27439.024 | J25: =I25 -> 27439.024 | K25: =J25 -> 27439.024 | L25: =K25 -> 27439.024 | M25: =L25 -> 27439.024 | N25: =M25 -> 27439.024 | O25: =N25 -> 27439.024 | P25: =O25 -> 27439.024 | ... S25: =R25 -> 27439.024
B26: Manpower, variable | C26: Complete | D26: 1 | E26: 18292.683 | F26: =D26*E26 -> 18292.683 | H26: =F26 -> 18292.683 | I26: =H26 -> 18292.683 | J26: =I26 -> 18292.683 | K26: =J26 -> 18292.683 | L26: =K26 -> 18292.683 | M26: =L26 -> 18292.683 | N26: =M26 -> 18292.683 | O26: =N26 -> 18292.683 | P26: =O26 -> 18292.683 | ... S26: =R26 -> 18292.683
B27: Miscellaneous | C27: % | D27: 0.1 | E27: =SUM(F21:F26) -> 123170.04 | F27: =D27*E27 -> 12317.004 | H27: =SUM(H21:H26)*$D$27 -> 11896.572 | I27: =SUM(I21:I26)*$D$27 -> 12242.847 | J27: =SUM(J21:J26)*$D$27 -> 12264.573 | K27: =SUM(K21:K26)*$D$27 -> 12279.39 | L27: =SUM(L21:L26)*$D$27 -> 12300.168 | M27: =SUM(M21:M26)*$D$27 -> 12317.093 | N27: =SUM(N21:N26)*$D$27 -> 12317.004 | O27: =SUM(O21:O26)*$D$27 -> 12316.915 | ... S27: =SUM(S21:S26)*$D$27 -> 12316.561
B28: ="Subtotal "&B18 -> Subtotal Feed Center | F28: =SUM(F19:F27) -> 4378568.6 | H28: =SUM(H19:H27) -> 2659111.6 | I28: =SUM(I19:I27) -> 3986646.3 | J28: =SUM(J19:J27) -> 4175970.2 | K28: =SUM(K19:K27) -> 4163119.1 | L28: =SUM(L19:L27) -> 4294853.1 | M28: =SUM(M19:M27) -> 4423320.9 | N28: =SUM(N19:N27) -> 4378568.6 | O28: =SUM(O19:O27) -> 4369701.8 | ... S28: =SUM(S19:S27) -> 4324472.8
B29: Total COGS | F29: =F28-F30 -> 4351129.6 | H29: =H28-H30 -> 2631672.5 | I29: =I28-I30 -> 3959207.3 | J29: =J28-J30 -> 4148531.2 | K29: =K28-K30 -> 4135680.1 | L29: =L28-L30 -> 4267414.1 | M29: =M28-M30 -> 4395881.9 | N29: =N28-N30 -> 4351129.6 | O29: =O28-O30 -> 4342262.8 | ... S29: =S28-S30 -> 4297033.7
B30: Total SG&A | F30: =SUM(F25:F25) -> 27439.024 | H30: =SUM(H25:H25) -> 27439.024 | I30: =SUM(I25:I25) -> 27439.024 | J30: =SUM(J25:J25) -> 27439.024 | K30: =SUM(K25:K25) -> 27439.024 | L30: =SUM(L25:L25) -> 27439.024 | M30: =SUM(M25:M25) -> 27439.024 | N30: =SUM(N25:N25) -> 27439.024 | O30: =SUM(O25:O25) -> 27439.024 | ... S30: =SUM(S25:S25) -> 27439.024
B31: Dairy Farm
B32: Water | C32: Lt. | D32: 107998.49 | E32: 0.049518864 | F32: =D32*E32 -> 5347.9623 | H32: 2139.2843 | I32: 2568.6268 | J32: 3217.9833 | K32: 3825.2622 | L32: 4564.5369 | M32: 5229.2278 | N32: 5347.9623 | O32: 5344.6199 | P32: 5341.2795 | Q32: 5337.9412 | R32: 5334.605 | S32: 5331.2708
B33: Veterinary care - Medication+Vaccination | C33: Heads | D33: 2367.0901 | E33: 12 | F33: =D33*E33 -> 28405.081 | H33: 11362.56 | I33: 13642.963 | J33: 17091.944 | K33: 20317.436 | L33: 24244.008 | M33: 27774.437 | N33: 28405.081 | O33: 28387.328 | P33: 28369.586 | Q33: 28351.855 | R33: 28334.135 | S33: 28316.426
B34: Artificial insemination | C34: Heads/Year | D34: 2510.3509 | E34: 4.2682927 | F34: =D34*E34 -> 10714.912 | H34: 5335.3659 | I34: 5121.9512 | J34: 6760.5208 | K34: 7878.055 | L34: 9445.095 | M34: 10721.613 | N34: 10714.912 | O34: 10708.216 | P34: 10701.523 | Q34: 10694.835 | R34: 10688.15 | S34: 10681.47
B35: Electric power | C35: Kw | D35: 4415456.2 | E35: 0.28296494 | F35: =D35*E35 -> 1249419.3 | H35: 622522.87 | I35: 597621.95 | J35: 788807.91 | K35: 919200.21 | L35: 1102040.2 | M35: 1250982.5 | N35: 1250200.7 | O35: 1249419.3 | P35: 1248638.4 | Q35: 1247858 | R35: 1247078.1 | S35: 1246298.7
B36: Fuel | C36: Lt. | D36: =150*365 -> 54750 | E36: 0.83841463 | F36: =D36*E36 -> 45903.201 | H36: =$F36 -> 45903.201 | I36: =$F36 -> 45903.201 | J36: =$F36 -> 45903.201 | K36: =$F36 -> 45903.201 | L36: =$F36 -> 45903.201 | M36: =$F36 -> 45903.201 | N36: =$F36 -> 45903.201 | O36: =$F36 -> 45903.201 | ... S36: =$F36 -> 45903.201
B37: Vehicles and machinery maitenance | C37: Lt. | D37: =D36 -> 54750 | E37: 0.41920732 | F37: =D37*E37 -> 22951.601 | H37: =$F37 -> 22951.601 | I37: =$F37 -> 22951.601 | J37: =$F37 -> 22951.601 | K37: =$F37 -> 22951.601 | L37: =$F37 -> 22951.601 | M37: =$F37 -> 22951.601 | N37: =$F37 -> 22951.601 | O37: =$F37 -> 22951.601 | ... S37: =$F37 -> 22951.601
B38: Operational Materials | C38: Complete | D38: 1 | E38: 30000 | F38: =D38*E38 -> 30000 | H38: =$F38 -> 30000 | I38: =$F38 -> 30000 | J38: =$F38 -> 30000 | K38: =$F38 -> 30000 | L38: =$F38 -> 30000 | M38: =$F38 -> 30000 | N38: =$F38 -> 30000 | O38: =$F38 -> 30000 | ... S38: =$F38 -> 30000
B39: Spare Parts | C39: Complete | D39: 1 | E39: 50000 | F39: =D39*E39 -> 50000 | H39: =$F39 -> 50000 | I39: =$F39 -> 50000 | J39: =$F39 -> 50000 | K39: =$F39 -> 50000 | L39: =$F39 -> 50000 | M39: =$F39 -> 50000 | N39: =$F39 -> 50000 | O39: =$F39 -> 50000 | ... S39: =$F39 -> 50000
B40: Manpower, permanent | C40: Complete | D40: 1 | E40: 54878.049 | F40: =D40*E40 -> 54878.049 | H40: 117878.05 | I40: 117878.05 | J40: 117878.05 | K40: 117878.05 | L40: 117878.05 | M40: 54878.049 | N40: 54878.049 | O40: 54878.049 | P40: 54878.049 | Q40: 54878.049 | R40: 54878.049 | S40: 54878.049
B41: Manpower, variable | C41: Complete | D41: 1 | E41: 172865.85 | F41: =D41*E41 -> 172865.85 | H41: 172865.85 | I41: 172865.85 | J41: 172865.85 | K41: 172865.85 | L41: 172865.85 | M41: 172865.85 | N41: 172865.85 | O41: 172865.85 | P41: 172865.85 | Q41: 172865.85 | R41: 172865.85 | S41: 172865.85
B42: Miscellaneous | C42: % | D42: 0.1 | E42: =SUM(F32:F41) -> 1670486 | F42: =D42*E42 -> 167048.6 | H42: =SUM(H32:H41)*$D42 -> 108095.88 | I42: =SUM(I32:I41)*$D42 -> 105855.42 | J42: =SUM(J32:J41)*$D42 -> 125547.71 | K42: =SUM(K32:K41)*$D42 -> 139081.97 | L42: =SUM(L32:L41)*$D42 -> 157989.25 | M42: =SUM(M32:M41)*$D42 -> 167130.65 | N42: =SUM(N32:N41)*$D42 -> 167126.73 | O42: =SUM(O32:O41)*$D42 -> 167045.82 | ... S42: =SUM(S32:S41)*$D42 -> 166722.66
B43: ="Subtotal "&B31 -> Subtotal Dairy Farm | F43: =SUM(F32:F42) -> 1837534.6 | H43: =SUM(H32:H42) -> 1189054.7 | I43: =SUM(I32:I42) -> 1164409.6 | J43: =SUM(J32:J42) -> 1381024.8 | K43: =SUM(K32:K42) -> 1529901.6 | L43: =SUM(L32:L42) -> 1737881.8 | M43: =SUM(M32:M42) -> 1838437.2 | N43: =SUM(N32:N42) -> 1838394.1 | O43: =SUM(O32:O42) -> 1837504 | ... S43: =SUM(S32:S42) -> 1833949.2
B44: Total COGS | F44: =F43-F45 -> 1732656.5 | H44: =H43-H45 -> 1021176.6 | I44: =I43-I45 -> 996531.57 | J44: =J43-J45 -> 1213146.7 | K44: =K43-K45 -> 1362023.6 | L44: =L43-L45 -> 1570003.7 | M44: =M43-M45 -> 1733559.1 | N44: =N43-N45 -> 1733516 | O44: =O43-O45 -> 1732625.9 | ... S44: =S43-S45 -> 1729071.2
B45: Total SG&A | F45: =SUM(F39:F40) -> 104878.05 | H45: =SUM(H39:H40) -> 167878.05 | I45: =SUM(I39:I40) -> 167878.05 | J45: =SUM(J39:J40) -> 167878.05 | K45: =SUM(K39:K40) -> 167878.05 | L45: =SUM(L39:L40) -> 167878.05 | M45: =SUM(M39:M40) -> 104878.05 | N45: =SUM(N39:N40) -> 104878.05 | O45: =SUM(O39:O40) -> 104878.05 | ... S45: =SUM(S39:S40) -> 104878.05
B46: Dairy Processing | H46: ='Dairy Product Composition'!H12 -> 0.12256944 | I46: ='Dairy Product Composition'!I12 -> 0.17925781 | J46: ='Dairy Product Composition'!J12 -> 0.31547252 | K46: ='Dairy Product Composition'!K12 -> 0.45952633 | L46: ='Dairy Product Composition'!L12 -> 0.66111798 | M46: ='Dairy Product Composition'!M12 -> 0.87554722 | N46: ='Dairy Product Composition'!N12 -> 1 | O46: ='Dairy Product Composition'!O12 -> 1.0618359 | ... S46: ='Dairy Product Composition'!S12 -> 1.1214888
B47: COGS
B48: Additives | C48: Liter | D48: ='Dairy Product Composition'!$C$11 -> 7832294.9 | E48: 0.05 | F48: =D48*E48 -> 391614.74 | H48: =$F48*H$46 -> 48000 | I48: =$F48*I$46 -> 70200 | J48: =$F48*J$46 -> 123543.69 | K48: =$F48*K$46 -> 179957.29 | L48: =$F48*L$46 -> 258903.55 | M48: =$F48*M$46 -> 342877.2 | N48: =$F48*N$46 -> 391614.74 | O48: =$F48*O$46 -> 415830.61 | ... S48: =$F48*S$46 -> 439191.54
B49: Packing Materials | C49: Liter | D49: ='Dairy Product Composition'!$C$11 -> 7832294.9 | E49: 0.15 | F49: =D49*E49 -> 1174844.2 | H49: =$F49*H$46 -> 144000 | I49: =$F49*I$46 -> 210600 | J49: =$F49*J$46 -> 370631.06 | K49: =$F49*K$46 -> 539871.86 | L49: =$F49*L$46 -> 776710.64 | M49: =$F49*M$46 -> 1028631.6 | N49: =$F49*N$46 -> 1174844.2 | O49: =$F49*O$46 -> 1247491.8 | ... S49: =$F49*S$46 -> 1317574.6
B50: Water | C50: m³ | D50: 6000 | E50: 0.049518864 | F50: =D50*E50 -> 297.11319 | H50: =$F50*H$46 -> 36.416997 | I50: =$F50*I$46 -> 53.259858 | J50: =$F50*J$46 -> 93.731044 | K50: =$F50*K$46 -> 136.53133 | L50: =$F50*L$46 -> 196.42687 | M50: =$F50*M$46 -> 260.13662 | N50: =$F50*N$46 -> 297.11319 | O50: =$F50*O$46 -> 315.48546 | ... S50: =$F50*S$46 -> 333.2091
B51: Electric power | C51: kWh | D51: 956250 | E51: 0.28296494 | F51: =D51*E51 -> 270585.22 | H51: =$F51*H$46 -> 33165.479 | I51: =$F51*I$46 -> 48504.514 | J51: =$F51*J$46 -> 85362.201 | K51: =$F51*K$46 -> 124341.03 | L51: =$F51*L$46 -> 178888.75 | M51: =$F51*M$46 -> 236910.14 | N51: =$F51*N$46 -> 270585.22 | O51: =$F51*O$46 -> 287317.11 | ... S51: =$F51*S$46 -> 303458.29
B52: Manpower, variable | C52: Complete | D52: 1 | E52: 82317.073 | F52: =D52*E52 -> 82317.073 | H52: =$F52*H$46 -> 10089.558 | I52: =$F52*I$46 -> 14755.978 | J52: =$F52*J$46 -> 25968.774 | K52: =$F52*K$46 -> 37826.863 | L52: =$F52*L$46 -> 54421.297 | M52: =$F52*M$46 -> 72072.484 | N52: =$F52*N$46 -> 82317.073 | O52: =$F52*O$46 -> 87407.227 | ... S52: =$F52*S$46 -> 92317.673
B53: Maintanance | C53: % | D53: 0.075 | E53: =SUM(F48:F52) -> 1919658.4 | F53: =D53*E53 -> 143974.38 | H53: =$F53*H$46 -> 17646.859 | I53: =$F53*I$46 -> 25808.531 | J53: =$F53*J$46 -> 45419.959 | K53: =$F53*K$46 -> 66160.018 | L53: =$F53*L$46 -> 95184.05 | M53: =$F53*M$46 -> 126056.37 | N53: =$F53*N$46 -> 143974.38 | O53: =$F53*O$46 -> 152877.17 | ... S53: =$F53*S$46 -> 161465.65
B54: Miscellaneous | C54: % | D54: 0.1 | E54: =E53 -> 1919658.4 | F54: =D54*E54 -> 191965.84 | H54: =$F54*H$46 -> 23529.145 | I54: =$F54*I$46 -> 34411.375 | J54: =$F54*J$46 -> 60559.946 | K54: =$F54*K$46 -> 88213.357 | L54: =$F54*L$46 -> 126912.07 | M54: =$F54*M$46 -> 168075.16 | N54: =$F54*N$46 -> 191965.84 | O54: =$F54*O$46 -> 203836.23 | ... S54: =$F54*S$46 -> 215287.53
B55: SG&A
B56: Manpower, permanent | C56: Complete | D56: 1 | E56: 54878.049 | F56: =D56*E56 -> 54878.049 | H56: 54878.049 | I56: 54878.049 | J56: 54878.049 | K56: 54878.049 | L56: 54878.049 | M56: 54878.049 | N56: 54878.049 | O56: 54878.049 | P56: 54878.049 | Q56: 54878.049 | R56: 54878.049 | S56: 54878.049
B57: Office materials | C57: Complete | D57: 1 | E57: 5000 | F57: =D57*E57 -> 5000 | H57: =$F57 -> 5000 | I57: =$F57 -> 5000 | J57: =$F57 -> 5000 | K57: =$F57 -> 5000 | L57: =$F57 -> 5000 | M57: =$F57 -> 5000 | N57: =$F57 -> 5000 | O57: =$F57 -> 5000 | ... S57: =$F57 -> 5000
B58: Fuel | C58: Liter | E58: =E36 -> 0.83841463 | F58: =D58*E58 -> 0 | H58: =$F58 -> 0 | I58: =$F58 -> 0 | J58: =$F58 -> 0 | K58: =$F58 -> 0 | L58: =$F58 -> 0 | M58: =$F58 -> 0 | N58: =$F58 -> 0 | O58: =$F58 -> 0 | ... S58: =$F58 -> 0
B59: Office Expenses | C59: Complete | D59: 1 | E59: 20000 | F59: =D59*E59 -> 20000 | H59: =$F59 -> 20000 | I59: =$F59 -> 20000 | J59: =$F59 -> 20000 | K59: =$F59 -> 20000 | L59: =$F59 -> 20000 | M59: =$F59 -> 20000 | N59: =$F59 -> 20000 | O59: =$F59 -> 20000 | ... S59: =$F59 -> 20000
B60: Miscellaneous | C60: % | D60: 0.1 | E60: =SUM(F56:F59) -> 79878.049 | F60: =D60*E60 -> 7987.8049 | H60: =$F60 -> 7987.8049 | I60: =$F60 -> 7987.8049 | J60: =$F60 -> 7987.8049 | K60: =$F60 -> 7987.8049 | L60: =$F60 -> 7987.8049 | M60: =$F60 -> 7987.8049 | N60: =$F60 -> 7987.8049 | O60: =$F60 -> 7987.8049 | ... S60: =$F60 -> 7987.8049
B61: Subtotal Dairy Processing | F61: =SUM(F48:F60) -> 2343464.5 | H61: =SUM(H48:H60) -> 364333.31 | I61: =SUM(I48:I60) -> 492199.51 | J61: =SUM(J48:J60) -> 799445.22 | K61: =SUM(K48:K60) -> 1124372.8 | L61: =SUM(L48:L60) -> 1579082.6 | M61: =SUM(M48:M60) -> 2062748.9 | N61: =SUM(N48:N60) -> 2343464.5 | O61: =SUM(O48:O60) -> 2482941.5 | ... S61: =SUM(S48:S60) -> 2617494.3
B62: Total COGS | F62: =SUM(F48:F54) -> 2255598.6 | H62: =SUM(H48:H54) -> 276467.46 | I62: =SUM(I48:I54) -> 404333.66 | J62: =SUM(J48:J54) -> 711579.36 | K62: =SUM(K48:K54) -> 1036506.9 | L62: =SUM(L48:L54) -> 1491216.8 | M62: =SUM(M48:M54) -> 1974883.1 | N62: =SUM(N48:N54) -> 2255598.6 | O62: =SUM(O48:O54) -> 2395075.7 | ... S62: =SUM(S48:S54) -> 2529628.5
B63: Total SG&A | F63: =SUM(F56:F60) -> 87865.854 | H63: =SUM(H56:H60) -> 87865.854 | I63: =SUM(I56:I60) -> 87865.854 | J63: =SUM(J56:J60) -> 87865.854 | K63: =SUM(K56:K60) -> 87865.854 | L63: =SUM(L56:L60) -> 87865.854 | M63: =SUM(M56:M60) -> 87865.854 | N63: =SUM(N56:N60) -> 87865.854 | O63: =SUM(O56:O60) -> 87865.854 | ... S63: =SUM(S56:S60) -> 87865.854
B64: Beef Farm | H64: 0.5 | I64: 1 | J64: 1 | K64: 1 | L64: 1 | M64: 1 | N64: 1 | O64: 1 | P64: 1 | Q64: 1 | R64: 1 | S64: 1
B65: Calves Purchasing | C65: Heads | D65: 18360 | E65: 164.63415 | F65: =D65*E65 -> 3022682.9 | H65: =$F65*H$64 -> 1511341.5 | I65: =$F65*I$64 -> 3022682.9 | J65: =$F65*J$64 -> 3022682.9 | K65: =$F65*K$64 -> 3022682.9 | L65: =$F65*L$64 -> 3022682.9 | M65: =$F65*M$64 -> 3022682.9 | N65: =$F65*N$64 -> 3022682.9 | O65: =$F65*O$64 -> 3022682.9 | ... S65: =$F65*S$64 -> 3022682.9
B66: Water | C66: Lt. | D66: 90063.03 | E66: 0.049518864 | F66: =D66*E66 -> 4459.819 | H66: =$F66*H$64 -> 2229.9095 | I66: =$F66*I$64 -> 4459.819 | J66: =$F66*J$64 -> 4459.819 | K66: =$F66*K$64 -> 4459.819 | L66: =$F66*L$64 -> 4459.819 | M66: =$F66*M$64 -> 4459.819 | N66: =$F66*N$64 -> 4459.819 | O66: =$F66*O$64 -> 4459.819 | ... S66: =$F66*S$64 -> 4459.819
B67: Veterinary care - Medication+Vaccination | C67: Heads | D67: 18360 | E67: 6 | F67: =D67*E67 -> 110160 | H67: =$F67*H$64 -> 55080 | I67: =$F67*I$64 -> 110160 | J67: =$F67*J$64 -> 110160 | K67: =$F67*K$64 -> 110160 | L67: =$F67*L$64 -> 110160 | M67: =$F67*M$64 -> 110160 | N67: =$F67*N$64 -> 110160 | O67: =$F67*O$64 -> 110160 | ... S67: =$F67*S$64 -> 110160
B68: Operational Materials | C68: Heads | D68: 18360 | E68: 3 | F68: =D68*E68 -> 55080 | H68: =$F68*H$64 -> 27540 | I68: =$F68*I$64 -> 55080 | J68: =$F68*J$64 -> 55080 | K68: =$F68*K$64 -> 55080 | L68: =$F68*L$64 -> 55080 | M68: =$F68*M$64 -> 55080 | N68: =$F68*N$64 -> 55080 | O68: =$F68*O$64 -> 55080 | ... S68: =$F68*S$64 -> 55080
B69: Electric power | C69: Kw | D69: 330642.36 | E69: 0.28296494 | F69: =D69*E69 -> 93560.194 | H69: =$F69*H$64 -> 46780.097 | I69: =$F69*I$64 -> 93560.194 | J69: =$F69*J$64 -> 93560.194 | K69: =$F69*K$64 -> 93560.194 | L69: =$F69*L$64 -> 93560.194 | M69: =$F69*M$64 -> 93560.194 | N69: =$F69*N$64 -> 93560.194 | O69: =$F69*O$64 -> 93560.194 | ... S69: =$F69*S$64 -> 93560.194
B70: Fuel | C70: Lt. | D70: 54750 | E70: 0.83841463 | F70: =D70*E70 -> 45903.201 | H70: =$F70*H$64 -> 22951.601 | I70: =$F70*I$64 -> 45903.201 | J70: =$F70*J$64 -> 45903.201 | K70: =$F70*K$64 -> 45903.201 | L70: =$F70*L$64 -> 45903.201 | M70: =$F70*M$64 -> 45903.201 | N70: =$F70*N$64 -> 45903.201 | O70: =$F70*O$64 -> 45903.201 | ... S70: =$F70*S$64 -> 45903.201
B71: Vehicles and machinery maitenance | C71: Lt. | D71: 54750 | E71: 0.41920732 | F71: =D71*E71 -> 22951.601 | H71: =$F71*H$64 -> 11475.8 | I71: =$F71*I$64 -> 22951.601 | J71: =$F71*J$64 -> 22951.601 | K71: =$F71*K$64 -> 22951.601 | L71: =$F71*L$64 -> 22951.601 | M71: =$F71*M$64 -> 22951.601 | N71: =$F71*N$64 -> 22951.601 | O71: =$F71*O$64 -> 22951.601 | ... S71: =$F71*S$64 -> 22951.601
B72: Operational Materials | C72: Complete | D72: 1 | E72: 30000 | F72: =D72*E72 -> 30000 | H72: =$F72*H$64 -> 15000 | I72: =$F72*I$64 -> 30000 | J72: =$F72*J$64 -> 30000 | K72: =$F72*K$64 -> 30000 | L72: =$F72*L$64 -> 30000 | M72: =$F72*M$64 -> 30000 | N72: =$F72*N$64 -> 30000 | O72: =$F72*O$64 -> 30000 | ... S72: =$F72*S$64 -> 30000
B73: Spare Parts | C73: Complete | D73: 1 | E73: 25000 | F73: =D73*E73 -> 25000 | H73: =$F73*H$64 -> 12500 | I73: =$F73*I$64 -> 25000 | J73: =$F73*J$64 -> 25000 | K73: =$F73*K$64 -> 25000 | L73: =$F73*L$64 -> 25000 | M73: =$F73*M$64 -> 25000 | N73: =$F73*N$64 -> 25000 | O73: =$F73*O$64 -> 25000 | ... S73: =$F73*S$64 -> 25000
B74: Manpower, permanent | C74: Complete | D74: 1 | E74: 54878.049 | F74: =D74*E74 -> 54878.049 | H74: 117878.05 | I74: 117878.05 | J74: 117878.05 | K74: 117878.05 | L74: 117878.05 | M74: 54878.049 | N74: 54878.049 | O74: 54878.049 | P74: 54878.049 | Q74: 54878.049 | R74: 54878.049 | S74: 54878.049
B75: Manpower, variable | C75: Complete | D75: 1 | E75: 31097.561 | F75: =D75*E75 -> 31097.561 | H75: 31097.561 | I75: 31097.561 | J75: 31097.561 | K75: 31097.561 | L75: 31097.561 | M75: 31097.561 | N75: 31097.561 | O75: 31097.561 | P75: 31097.561 | Q75: 31097.561 | R75: 31097.561 | S75: 31097.561
B76: Miscellaneous | C76: % | D76: 0.1 | E76: =SUM(F66:F75) -> 473090.43 | F76: =D76*E76 -> 47309.043 | H76: =SUM(H66:H75)*$D76 -> 34253.302 | I76: =SUM(I66:I75)*$D76 -> 53609.043 | J76: =SUM(J66:J75)*$D76 -> 53609.043 | K76: =SUM(K66:K75)*$D76 -> 53609.043 | L76: =SUM(L66:L75)*$D76 -> 53609.043 | M76: =SUM(M66:M75)*$D76 -> 47309.043 | N76: =SUM(N66:N75)*$D76 -> 47309.043 | O76: =SUM(O66:O75)*$D76 -> 47309.043 | ... S76: =SUM(S66:S75)*$D76 -> 47309.043
B77: ="Subtotal "&B64 -> Subtotal Beef Farm | F77: =SUM(F65:F76) -> 3543082.4 | H77: =SUM(H65:H76) -> 1888127.8 | I77: =SUM(I65:I76) -> 3612382.4 | J77: =SUM(J65:J76) -> 3612382.4 | K77: =SUM(K65:K76) -> 3612382.4 | L77: =SUM(L65:L76) -> 3612382.4 | M77: =SUM(M65:M76) -> 3543082.4 | N77: =SUM(N65:N76) -> 3543082.4 | O77: =SUM(O65:O76) -> 3543082.4 | ... S77: =SUM(S65:S76) -> 3543082.4
B78: Total COGS | F78: =F77-F79 -> 3463204.3 | H78: =H77-H79 -> 1757749.7 | I78: =I77-I79 -> 3469504.3 | J78: =J77-J79 -> 3469504.3 | K78: =K77-K79 -> 3469504.3 | L78: =L77-L79 -> 3469504.3 | M78: =M77-M79 -> 3463204.3 | N78: =N77-N79 -> 3463204.3 | O78: =O77-O79 -> 3463204.3 | ... S78: =S77-S79 -> 3463204.3
B79: Total SG&A | F79: =SUM(F73:F74) -> 79878.049 | H79: =SUM(H73:H74) -> 130378.05 | I79: =SUM(I73:I74) -> 142878.05 | J79: =SUM(J73:J74) -> 142878.05 | K79: =SUM(K73:K74) -> 142878.05 | L79: =SUM(L73:L74) -> 142878.05 | M79: =SUM(M73:M74) -> 79878.049 | N79: =SUM(N73:N74) -> 79878.049 | O79: =SUM(O73:O74) -> 79878.049 | ... S79: =SUM(S73:S74) -> 79878.049
B80: Beef Processing
B81: Water | C81: m³ | D81: 18000 | E81: 0.049518864 | F81: =D81*E81 -> 891.33956 | H81: =H$64*$F81 -> 445.66978 | I81: =I$64*$F81 -> 891.33956 | J81: =J$64*$F81 -> 891.33956 | K81: =K$64*$F81 -> 891.33956 | L81: =L$64*$F81 -> 891.33956 | M81: =M$64*$F81 -> 891.33956 | N81: =N$64*$F81 -> 891.33956 | O81: =O$64*$F81 -> 891.33956 | ... S81: =S$64*$F81 -> 891.33956
B82: Operational materials | C82: head | D82: 18000 | E82: 10 | F82: =D82*E82 -> 180000 | H82: =H$64*$F82 -> 90000 | I82: =I$64*$F82 -> 180000 | J82: =J$64*$F82 -> 180000 | K82: =K$64*$F82 -> 180000 | L82: =L$64*$F82 -> 180000 | M82: =M$64*$F82 -> 180000 | N82: =N$64*$F82 -> 180000 | O82: =O$64*$F82 -> 180000 | ... S82: =S$64*$F82 -> 180000
B83: Packing materials | C83: head | D83: 18000 | E83: 2 | F83: =D83*E83 -> 36000 | H83: =H$64*$F83 -> 18000 | I83: =I$64*$F83 -> 36000 | J83: =J$64*$F83 -> 36000 | K83: =K$64*$F83 -> 36000 | L83: =L$64*$F83 -> 36000 | M83: =M$64*$F83 -> 36000 | N83: =N$64*$F83 -> 36000 | O83: =O$64*$F83 -> 36000 | ... S83: =S$64*$F83 -> 36000
B84: Manpower, variable | C84: Complete | D84: 1 | E84: 100609.76 | F84: =D84*E84 -> 100609.76 | H84: =F84 -> 100609.76 | I84: =H84 -> 100609.76 | J84: =I84 -> 100609.76 | K84: =J84 -> 100609.76 | L84: =K84 -> 100609.76 | M84: =L84 -> 100609.76 | N84: =M84 -> 100609.76 | O84: =N84 -> 100609.76 | P84: =O84 -> 100609.76 | ... S84: =R84 -> 100609.76
B85: Electric power | C85: kWh | D85: 180000 | E85: 0.28296494 | F85: =D85*E85 -> 50933.689 | H85: =H$64*$F85 -> 25466.845 | I85: =I$64*$F85 -> 50933.689 | J85: =J$64*$F85 -> 50933.689 | K85: =K$64*$F85 -> 50933.689 | L85: =L$64*$F85 -> 50933.689 | M85: =M$64*$F85 -> 50933.689 | N85: =N$64*$F85 -> 50933.689 | O85: =O$64*$F85 -> 50933.689 | ... S85: =S$64*$F85 -> 50933.689
B86: Fuel | C86: Lt. | E86: 0.83841463 | F86: =D86*E86 -> 0 | H86: =H$64*$F86 -> 0 | I86: =I$64*$F86 -> 0 | J86: =J$64*$F86 -> 0 | K86: =K$64*$F86 -> 0 | L86: =L$64*$F86 -> 0 | M86: =M$64*$F86 -> 0 | N86: =N$64*$F86 -> 0 | O86: =O$64*$F86 -> 0 | ... S86: =S$64*$F86 -> 0
B87: Vehicles and machinery maitenance | C87: Lt. | E87: 0.41920732 | F87: =D87*E87 -> 0 | H87: =H$64*$F87 -> 0 | I87: =I$64*$F87 -> 0 | J87: =J$64*$F87 -> 0 | K87: =K$64*$F87 -> 0 | L87: =L$64*$F87 -> 0 | M87: =M$64*$F87 -> 0 | N87: =N$64*$F87 -> 0 | O87: =O$64*$F87 -> 0 | ... S87: =S$64*$F87 -> 0
B88: Office materials | C88: Complete | E88: 20000 | F88: =D88*E88 -> 0 | H88: =H$64*$F88 -> 0 | I88: =I$64*$F88 -> 0 | J88: =J$64*$F88 -> 0 | K88: =K$64*$F88 -> 0 | L88: =L$64*$F88 -> 0 | M88: =M$64*$F88 -> 0 | N88: =N$64*$F88 -> 0 | O88: =O$64*$F88 -> 0 | ... S88: =S$64*$F88 -> 0
B89: Maintanance | C89: % | D89: 0.075 | E89: 368434.78 | F89: =D89*E89 -> 27632.609 | H89: =$F89*H$46 -> 3386.9134 | I89: =$F89*I$46 -> 4953.3609 | J89: =$F89*J$46 -> 8717.3286 | K89: =$F89*K$46 -> 12697.911 | L89: =$F89*L$46 -> 18268.414 | M89: =$F89*M$46 -> 24193.654 | N89: =$F89*N$46 -> 27632.609 | O89: =$F89*O$46 -> 29341.297 | ... S89: =$F89*S$46 -> 30989.66
B90: Marketing | C90: % of incomes | D90: 0.025 | E90: 6317047.1 | F90: =D90*E90 -> 157926.18 | H90: =H$64*$F90 -> 78963.089 | I90: =I$64*$F90 -> 157926.18 | J90: =J$64*$F90 -> 157926.18 | K90: =K$64*$F90 -> 157926.18 | L90: =L$64*$F90 -> 157926.18 | M90: =M$64*$F90 -> 157926.18 | N90: =N$64*$F90 -> 157926.18 | O90: =O$64*$F90 -> 157926.18 | ... S90: =S$64*$F90 -> 157926.18
B91: Manpower, permanent | C91: Complete | D91: 1 | E91: 68597.561 | F91: =D91*E91 -> 68597.561 | H91: =F91 -> 68597.561 | I91: =H91 -> 68597.561 | J91: =I91 -> 68597.561 | K91: =J91 -> 68597.561 | L91: =K91 -> 68597.561 | M91: =L91 -> 68597.561 | N91: =M91 -> 68597.561 | O91: =N91 -> 68597.561 | P91: =O91 -> 68597.561 | ... S91: =R91 -> 68597.561
B92: Miscellaneous | C92: % | D92: 0.1 | E92: =SUM(F81:F91) -> 622591.13 | F92: =D92*E92 -> 62259.113 | H92: =SUM(H81:H91)*$D92 -> 38546.983 | I92: =SUM(I81:I91)*$D92 -> 59991.188 | J92: =SUM(J81:J91)*$D92 -> 60367.585 | K92: =SUM(K81:K91)*$D92 -> 60765.643 | L92: =SUM(L81:L91)*$D92 -> 61322.694 | M92: =SUM(M81:M91)*$D92 -> 61915.218 | N92: =SUM(N81:N91)*$D92 -> 62259.113 | O92: =SUM(O81:O91)*$D92 -> 62429.982 | ... S92: =SUM(S81:S91)*$D92 -> 62594.818
B93: Subtotal Beef Processing | F93: =SUM(F81:F92) -> 684850.25 | H93: =SUM(H81:H92) -> 424016.82 | I93: =SUM(I81:I92) -> 659903.07 | J93: =SUM(J81:J92) -> 664043.44 | K93: =SUM(K81:K92) -> 668422.08 | L93: =SUM(L81:L92) -> 674549.63 | M93: =SUM(M81:M92) -> 681067.39 | N93: =SUM(N81:N92) -> 684850.25 | O93: =SUM(O81:O92) -> 686729.8 | ... S93: =SUM(S81:S92) -> 688543
B94: Total COGS | F94: =SUM(F81:F87) -> 368434.78 | H94: =SUM(H81:H87) -> 234522.27 | I94: =SUM(I81:I87) -> 368434.78 | J94: =SUM(J81:J87) -> 368434.78 | K94: =SUM(K81:K87) -> 368434.78 | L94: =SUM(L81:L87) -> 368434.78 | M94: =SUM(M81:M87) -> 368434.78 | N94: =SUM(N81:N87) -> 368434.78 | O94: =SUM(O81:O87) -> 368434.78 | ... S94: =SUM(S81:S87) -> 368434.78
B95: Total SG&A | F95: =SUM(F88:F92) -> 316415.46 | H95: =SUM(H88:H92) -> 189494.55 | I95: =SUM(I88:I92) -> 291468.29 | J95: =SUM(J88:J92) -> 295608.65 | K95: =SUM(K88:K92) -> 299987.29 | L95: =SUM(L88:L92) -> 306114.85 | M95: =SUM(M88:M92) -> 312632.61 | N95: =SUM(N88:N92) -> 316415.46 | O95: =SUM(O88:O92) -> 318295.02 | ... S95: =SUM(S88:S92) -> 320108.22
B96: Headquarters | H96: =B96&" Annual Development" -> Headquarters Annual Development
B97: Fuel and vehicles maintenance | C97: Lt. | D97: 78750 | E97: 0.83841463 | F97: =D97*E97 -> 66025.152 | H97: =$F97 -> 66025.152 | I97: =$F97 -> 66025.152 | J97: =$F97 -> 66025.152 | K97: =$F97 -> 66025.152 | L97: =$F97 -> 66025.152 | M97: =$F97 -> 66025.152 | N97: =$F97 -> 66025.152 | O97: =$F97 -> 66025.152 | ... S97: =$F97 -> 66025.152
B98: Vehicles and machinery maitenance | C98: Lt. | E98: 0.41920732 | F98: =D98*E98 -> 0 | H98: =$F98 -> 0 | I98: =$F98 -> 0 | J98: =$F98 -> 0 | K98: =$F98 -> 0 | L98: =$F98 -> 0 | M98: =$F98 -> 0 | N98: =$F98 -> 0 | O98: =$F98 -> 0 | ... S98: =$F98 -> 0
B99: Electric power | C99: Kw | D99: 3296290.3 | E99: 0.28296494 | F99: =D99*E99 -> 932734.57 | H99: =$F99 -> 932734.57 | I99: =$F99 -> 932734.57 | J99: =$F99 -> 932734.57 | K99: =$F99 -> 932734.57 | L99: =$F99 -> 932734.57 | M99: =$F99 -> 932734.57 | N99: =$F99 -> 932734.57 | O99: =$F99 -> 932734.57 | ... S99: =$F99 -> 932734.57
B100: Water, tap | C100: m³ | D100: 10000 | E100: 0.049518864 | F100: =D100*E100 -> 495.18864 | H100: =$F100 -> 495.18864 | I100: =$F100 -> 495.18864 | J100: =$F100 -> 495.18864 | K100: =$F100 -> 495.18864 | L100: =$F100 -> 495.18864 | M100: =$F100 -> 495.18864 | N100: =$F100 -> 495.18864 | O100: =$F100 -> 495.18864 | ... S100: =$F100 -> 495.18864
B101: Manpower, Permanent | C101: Complete | D101: 1 | E101: 237347.56 | F101: =D101*E101 -> 237347.56 | H101: 363347.56 | I101: 363347.56 | J101: 363347.56 | K101: 363347.56 | L101: 363347.56 | M101: 237347.56 | N101: 237347.56 | O101: 237347.56 | P101: 237347.56 | Q101: 237347.56 | R101: 237347.56 | S101: 237347.56
B102: Manpower, Vaiable | C102: Complete | D102: 1 | E102: 0 | F102: =D102*E102 -> 0 | H102: 0 | I102: 0 | J102: 0 | K102: 0 | L102: 0 | M102: 0 | N102: 0 | O102: 0 | P102: 0 | Q102: 0 | R102: 0 | S102: 0
B103: Office Expenses | C103: Complete | D103: 1 | E103: 35000 | F103: =D103*E103 -> 35000 | H103: =$F103 -> 35000 | I103: =$F103 -> 35000 | J103: =$F103 -> 35000 | K103: =$F103 -> 35000 | L103: =$F103 -> 35000 | M103: =$F103 -> 35000 | N103: =$F103 -> 35000 | O103: =$F103 -> 35000 | ... S103: =$F103 -> 35000
...

Sheet CAPEX
A1: Company/Project: | B1: =Cover!$C$10 -> Mr. Amir Artine | C1: =Cover!$C$3 -> Cattle Integration, Baghara, Chad | F1: Last Update: | G1: =Cover!$C$13 -> 45763
B2: HARAZ Agriculture & Industrual Investment Plan
C4: Total for Project (€) | E4: Year 0 | F4: Year 1 | G4: Year 2 | H4: Year 3 | I4: Year 4
B5: General Infrastructure and HQ
B6: Infrastructure
B7: Land purchase | C7: 0 | E7: 0 | F7: 0 | G7: 0 | H7: 0 | I7: 0
B8: Access Road, non paved (3000 m) | C8: 185000 | E8: =SUM(C8) -> 185000 | F8: 0 | G8: 0 | H8: 0 | I8: 0
B9: Electricity Line (2000 m) | C9: 110000 | E9: =SUM(C9) -> 110000 | F9: 0 | G9: 0 | H9: 0 | I9: 0
B10: Water Supply System | C10: 875000 | E10: =SUM(C10) -> 875000 | F10: 0 | G10: 0 | H10: 0 | I10: 0
B11: Trenching & fences (14000 m) | C11: 495000 | E11: =SUM(C11) -> 495000 | F11: 0 | G11: 0 | H11: 0 | I11: 0
B12: Camp
B13: Land reclamation, civil works, landscaping, roads, parking, drainage | C13: 19726.464 | E13: =SUM(C13) -> 19726.464 | F13: 0 | G13: 0 | H13: 0 | I13: 0
B14: Fuel station | C14: 9726.4639 | E14: =SUM(C14) -> 9726.4639 | F14: 0 | G14: 0 | H14: 0 | I14: 0
B15: Within camp electric grid and work | C15: 113938.58 | E15: =SUM(C15) -> 113938.58 | F15: 0 | G15: 0 | H15: 0 | I15: 0
B16: Communications | C16: 28484.644 | E16: =SUM(C16) -> 28484.644 | F16: 0 | G16: 0 | H16: 0 | I16: 0
B17: Camp water purifying and supply system | C17: 34181.573 | E17: =SUM(C17) -> 34181.573 | F17: 0 | G17: 0 | H17: 0 | I17: 0
B18: Fence, guard building, gates | C18: 7781.1711 | E18: =SUM(C18) -> 7781.1711 | F18: 0 | G18: 0 | H18: 0 | I18: 0
B19: Generators 120 KVA | C19: 0 | E19: =SUM(C19) -> 0 | F19: 0 | G19: 0 | H19: 0 | I19: 0
B20: Generators 800 KVA | C20: 0 | E20: =SUM(C20) -> 0 | F20: 0 | G20: 0 | H20: 0 | I20: 0
B21: Generator shed | C21: 0 | E21: =SUM(C21) -> 0 | F21: 0 | G21: 0 | H21: 0 | I21: 0
B22: Central building: administration & services, fully equipped
B23: Office HQ | C23: 650000 | E23: =SUM(C23) -> 650000 | F23: 0 | G23: 0 | H23: 0 | I23: 0
B24: Office equipment | C24: 9726.4639 | E24: =SUM(C24) -> 9726.4639 | F24: 0 | G24: 0 | H24: 0 | I24: 0
B25: Clinic | C25: 10421.211 | E25: =SUM(C25) -> 10421.211 | F25: 0 | G25: 0 | H25: 0 | I25: 0
B26: Clinic equipment | C26: 9726.4639 | E26: =SUM(C26) -> 9726.4639 | F26: 0 | G26: 0 | H26: 0 | I26: 0
B27: Amenity, public are, service facilities | C27: 52106.057 | E27: =SUM(C27) -> 52106.057 | F27: 0 | G27: 0 | H27: 0 | I27: 0
B28: Amenity, public are, service facilities | C28: 19452.928 | E28: =SUM(C28) -> 19452.928 | F28: 0 | G28: 0 | H28: 0 | I28: 0
B29: Accommodation, fully equipped
B30: Staff housing, 2 rooms | C30: 104212.11 | E30: =SUM(C30) -> 104212.11 | F30: 0 | G30: 0 | H30: 0 | I30: 0
B31: Staff housing, 2 rooms equipment | C31: 19452.928 | E31: =SUM(C31) -> 19452.928 | F31: 0 | G31: 0 | H31: 0 | I31: 0
B32: Workers housing, dormitory | C32: 130265.14 | E32: =SUM(C32) -> 130265.14 | F32: 0 | G32: 0 | H32: 0 | I32: 0
B33: Workers housing, dormitory equipment | C33: 9726.4639 | E33: =SUM(C33) -> 9726.4639 | F33: 0 | G33: 0 | H33: 0 | I33: 0
B34: Farm buildings, fully equipped | E34: =SUM(C34) -> 0
B35: Garage | C35: 58358.783 | E35: =SUM(C35) -> 58358.783 | F35: 0 | G35: 0 | H35: 0 | I35: 0
B36: Garage equipment | C36: 194529.28 | E36: =SUM(C36) -> 194529.28 | F36: 0 | G36: 0 | H36: 0 | I36: 0
B37: Workshop and spare parts warehouse | C37: 38905.856 | E37: =SUM(C37) -> 38905.856 | F37: 0 | G37: 0 | H37: 0 | I37: 0
B38: Workshop and spare parts warehouse equipment | C38: 72948.479 | E38: =SUM(C38) -> 72948.479 | F38: 0 | G38: 0 | H38: 0 | I38: 0
B39: Machinery shed | C39: 36474.24 | E39: =SUM(C39) -> 36474.24 | F39: 0 | G39: 0 | H39: 0 | I39: 0
B40: General equipment | C40: 19452.928 | E40: =SUM(C40) -> 19452.928 | F40: 0 | G40: 0 | H40: 0 | I40: 0
B41: Mechanized equipment and vehicles | E41: =SUM(C41) -> 0
B42: Pickup | C42: 116718 | E42: =SUM(C42) -> 116718 | F42: 0 | G42: 0 | H42: 0 | I42: 0
B43: Milk tanker | C43: 0 | E43: =SUM(C43) -> 0 | F43: 0 | G43: 0 | H43: 0 | I43: 0
B44: Refrigirated truck | C44: 0 | E44: =SUM(C44) -> 0 | F44: 0 | G44: 0 | H44: 0 | I44: 0
B45: Transportation | E45: =SUM(C45) -> 0
B46: Transportation | C46: 54711.359 | E46: =SUM(C46) -> 54711.359 | F46: 0 | G46: 0 | H46: 0 | I46: 0
B47: Planning, construction, miscellaneous | E47: =SUM(C47) -> 0
B48: Engineering, Design and Planning | C48: =SUM(D52)*1.5/100 -> 52290.414 | E48: =SUM(C48) -> 52290.414 | F48: 0 | G48: 0 | H48: 0 | I48: 0
B49: Construction supervision | C49: =SUM(D52)*2.5/100 -> 87150.69 | E49: =SUM(C49) -> 87150.69 | F49: 0 | G49: 0 | H49: 0 | I49: 0
B50: Construction (local contractor) | C50: =SUM(D52)*6/100 -> 209161.66 | E50: =SUM(C50) -> 209161.66 | F50: 0 | G50: 0 | H50: 0 | I50: 0
B51: Miscellaneous | C51: =SUM(D52)*5/100 -> 174301.38 | E51: =SUM(C51) -> 174301.38 | F51: 0 | G51: 0 | H51: 0 | I51: 0
B52: ="Subtotal "&B5 -> Subtotal General Infrastructure and HQ | C52: =SUM(C8:C51) -> 4008931.7 | D52: =SUM(C8:C47) -> 3486027.6 | E52: =SUM(E8:E51) -> 4008931.7 | F52: 0 | G52: 0 | H52: 0 | I52: 0
B54: Field Crop Farm & 3 X 3Moissons Model
B55: Farm
B56: Land reclamation: civil works, field roads, land clearing, leveling, drainage | C56: 392609.25 | E56: =SUM(C56/3)*2 -> 261739.5 | F56: =SUM(C56/3) -> 130869.75 | G56: 0 | H56: 0 | I56: 0
B57: Power grid and work | C57: 184529.28 | E57: =SUM(C57/3)*2 -> 123019.52 | F57: =SUM(C57/3) -> 61509.759 | G57: 0 | H57: 0 | I57: 0
B58: Bulk water supply system | C58: 117000 | E58: =SUM(C58/3)*2 -> 78000 | F58: =SUM(C58/3) -> 39000 | G58: 0 | H58: 0 | I58: 0
B59: Reservoir construction | C59: 230000 | E59: =SUM(C59/3)*2 -> 153333.33 | F59: =SUM(C59/3) -> 76666.667 | G59: 0 | H59: 0 | I59: 0
B60: Irrigation system & center pivots | C60: 1374132.4 | E60: =SUM(C60/3)*2 -> 916088.25 | F60: =SUM(C60/3) -> 458044.12 | G60: 0 | H60: 0 | I60: 0
B61: Farm logistic center
B62: Camp | C62: 0 | E62: =SUM(C62/3)*2 -> 0 | F62: =SUM(C62/3) -> 0 | G62: 0 | H62: 0 | I62: 0
B63: Central building: administration & services | C63: 0 | E63: =SUM(C63/3)*2 -> 0 | F63: =SUM(C63/3) -> 0 | G63: 0 | H63: 0 | I63: 0
B64: Barns and hay lofts | C64: 175000 | E64: =SUM(C64/3)*2 -> 116666.67 | F64: =SUM(C64/3) -> 58333.333 | G64: 0 | H64: 0 | I64: 0
B65: Farm buildings | C65: 158000 | E65: =SUM(C65/3)*2 -> 105333.33 | F65: =SUM(C65/3) -> 52666.667 | G65: 0 | H65: 0 | I65: 0
B66: Storage | C66: 97286.634 | E66: =SUM(C66/3)*2 -> 64857.756 | F66: =SUM(C66/3) -> 32428.878 | G66: 0 | H66: 0 | I66: 0
B67: Vehicles | C67: 38900 | E67: =SUM(C67/3)*2 -> 25933.333 | F67: =SUM(C67/3) -> 12966.667 | G67: 0 | H67: 0 | I67: 0
B68: Vehicles and machinery
B69: Vehicles transport | C69: 111854.33 | E69: =SUM(C69/3)*2 -> 74569.557 | F69: =SUM(C69/3) -> 37284.778 | G69: 0 | H69: 0 | I69: 0
B70: Tractors and self propelled tools | C70: 550517.86 | E70: =SUM(C70/3)*2 -> 367011.9 | F70: =SUM(C70/3) -> 183505.95 | G70: 0 | H70: 0 | I70: 0
B71: Cultivation and accessory tools | C71: 376414.15 | E71: =SUM(C71/3)*2 -> 250942.77 | F71: =SUM(C71/3) -> 125471.38 | G71: 0 | H71: 0 | I71: 0
B72: Transportation
B73: Transportation | C73: 109422.72 | E73: =SUM(C73/3)*2 -> 72948.479 | F73: =SUM(C73/3) -> 36474.24 | G73: 0 | H73: 0 | I73: 0
B74: Planning, construction, miscellaneous
B75: Engineering, Design and Planning | C75: =SUM(D79)*1.5/100 -> 58734.999 | E75: =SUM(C75/3)*2 -> 39156.666 | F75: =SUM(C75/3) -> 19578.333 | G75: 0 | H75: 0 | I75: 0
B76: Construction supervision | C76: =SUM(D79)*2.5/100 -> 97891.665 | E76: =SUM(C76/3)*2 -> 65261.11 | F76: =SUM(C76/3) -> 32630.555 | G76: 0 | H76: 0 | I76: 0
B77: Construction (local contractor) | C77: =SUM(D79)*6/100 -> 234940 | E77: =SUM(C77/3)*2 -> 156626.66 | F77: =SUM(C77/3) -> 78313.332 | G77: 0 | H77: 0 | I77: 0
B78: Miscellaneous | C78: =SUM(D79)*5/100 -> 195783.33 | E78: =SUM(C78/3)*2 -> 130522.22 | F78: =SUM(C78/3) -> 65261.11 | G78: 0 | H78: 0 | I78: 0
